Workbook
Name CMNOTES: #REF!
Name GLNo: '[1]GL#'!$A$2:$A$1329
Name RESULTS: #REF!
Name Status: #REF!

Sheet NEW OSAR
B1: CREFC Investor Reporting Package
C2: MULTIFAMILY OPERATING STATEMENT ANALYSIS REPORT (includes Mobile Home Parks, Single Family Rentals, and Co-ops)
C3: as of 03/31/2026
C4: PROPERTY OVERVIEW | H4: Allocated Loan Amount/Percentage
C5: Property ID | E5: 1001-001 | F5: Paid Thru Date | G5: Debt Outside Trust (1) | H5: $ | I5: %
C6: Note A-Scheduled Loan Balance | E6: 92071459 | G6: 0 | H6: 0 | I6: 0
C7: Note B-Scheduled Loan Balance | E7: 0 | G7: 0 | H7: 0 | I7: 0
C8: Note C-Scheduled Loan Balance | E8: 0 | G8: 0 | H8: 0 | I8: 0
C9: Property Name | E9: Strada
C10: Property Type | E10: MF
C11: Property Address, City, State | E11: 701 W Grove Pkwy, Tempe, AZ 85283
C12: Current Net Rentable SF/Units/Beds/Rooms | E12: 495 | G12: Use second box to specify sqft.,units…
C13: Year Built/Year Renovated | E13: 1995 | F13: 2020
C14: Cap Ex Reserve (annually)/per Unit.etc. (2) | E14: 250 | F14: 0 | G14: specify annual/per unit…
C15: Statement Ending Date | E15: Underwriting | F15: 45930 | G15: 46022 | H15: 46112 | I15: =H15 -> 46112
C16: Occupancy Rate (physical) | E16: =1-5.9% -> 0.941 | F16: 0.93333333 | G16: 0.91717172 | H16: 0.91919192 | I16: ='Rent Roll'!L543 -> 0.9195171 | M16: =I16-H16 -> 0.00032518342
C17: Occupancy Date | F17: 45930 | G17: 46022 | H17: 46112 | I17: =I15 -> 46112
E18: (1) "X" if debt is outside of the trust, otherwise leave blank
E19: (2) Total $ amount of Capital Reserves required annually by loan documents
C20: INCOME:
C21: Number of Mos. Covered | F21: 12 | G21: 12 | H21: 12 | I21: 12 | J21: (prcdng yr to base) | K21: (prcdng yr to 2nd prcdng)
C22: Period Ended | E22: At Contribution | F22: DY TEST | G22: DY TEST | H22: TTM | I22: DY TEST | J22: YYYY-U/W | K22: YYYY-YYYY
C23: Statement Ending Date | E23: Information | F23: as of 09/30/2025 | G23: as of 12/31/2025 | H23: =I23 -> as of 03/31/2026 | I23: ="as of "&TEXT(I15,"MM/DD/YYYY") -> as of 03/31/2026 | J23: Variance | K23: Variance | L23: Notes
C24: Gross Potential Rent (3) | E24: 8474519 | F24: 7840380 | G24: 7679808 | H24: =INDEX('Operating Statement'!W:W,MATCH('NEW OSAR'!$C24,'Operating Statement'!V:V,0)) -> 7969528.7 | I24: =('Rent Roll'!M542*12)+'Operating Statement'!R54 -> 7693836 | J24: =IF(E24=0, " ",(H24-E24)/E24) -> -0.05958926 | K24: =IF(G24=0, " ",(H24-G24)/G24) -> 0.037724987 | L24: Annualized Rent Roll as of 3/31/2026 less delinquent rents 60+ days | N24: =I24-G24 -> 14028 | O24: =(I24-G24)/G24 -> 0.0018266082
C25: Less: Vacancy Loss | E25: -499996.62 | F25: 0 | G25: 0 | H25: =INDEX('Operating Statement'!W:W,MATCH('NEW OSAR'!$C25,'Operating Statement'!V:V,0)) -> -576358.57 | I25: =IF(I16>0.95,(I24/I16)*M25,0) -> 0 | J25: =IF(E25=0, " ",(H25-E25)/E25) -> 0.15272493 | K25: =IF(G25=0, " ",(H25-G25)/G25) | L25: ="Greater of actual vacancy ("&TEXT(1-I16,"0.00%")&") and 5.00%" -> Greater of actual vacancy (8.05%) and 5.00% | M25: =5%-(1-I16) -> -0.030482897
C26: OR
C27: Base Rent (3) | H27: =INDEX('Operating Statement'!W:W,MATCH('NEW OSAR'!$C27,'Operating Statement'!V:V,0)) -> 0 | I27: =SUMIF('Operating Statement'!A:A,'NEW OSAR'!$C27,'Operating Statement'!S:S) -> 0 | J27: =IF(E27=0, " ",(H27-E27)/E27) | K27: =IF(G27=0, " ",(H27-G27)/G27) | L27: =IF(G27=0, " ",(J27-G27)/G27)
C28: Laundry/Vending Income | E28: 0 | F28: 0 | G28: 0 | H28: =INDEX('Operating Statement'!W:W,MATCH('NEW OSAR'!$C28,'Operating Statement'!V:V,0)) -> 0 | I28: =SUMIF('Operating Statement'!A:A,'NEW OSAR'!$C28,'Operating Statement'!S:S) -> 0 | J28: =IF(E28=0, " ",(H28-E28)/E28) | K28: =IF(G28=0, " ",(H28-G28)/G28) | L28: =IF(G28=0, " ",(J28-G28)/G28)
C29: Parking Income | E29: 0 | F29: 45753.12 | G29: 43723.24 | H29: =INDEX('Operating Statement'!W:W,MATCH('NEW OSAR'!$C29,'Operating Statement'!V:V,0)) -> 44205.67 | I29: =SUMIF('Operating Statement'!A:A,'NEW OSAR'!$C29,'Operating Statement'!S:S) -> 43379.96 | J29: =IF(E29=0, " ",(H29-E29)/E29) | K29: =IF(G29=0, " ",(H29-G29)/G29) -> 0.01103372 | L29: T3A | N29: =I29-G29 -> -343.28 | O29: =(I29-G29)/G29 -> -0.0078512022
C30: Other Income | E30: =1242919.25-117056-10606-114839.31 -> 1000417.9 | F30: 793695.26 | G30: 812340.8 | H30: =INDEX('Operating Statement'!W:W,MATCH('NEW OSAR'!$C30,'Operating Statement'!V:V,0)) -> 1009345 | I30: ='Operating Statement'!R55 -> 820163.88 | J30: =IF(E30=0, " ",(H30-E30)/E30) -> 0.0089233406 | K30: =IF(G30=0, " ",(H30-G30)/G30) -> 0.24251424 | L30: T3A total less T6A concessions + T6 special allowance | N30: =I30-G30 -> 7823.08 | O30: =(I30-G30)/G30 -> 0.0096302931
C32: *Effective Gross Income | E32: =SUM(E24:E30) -> 8974940.3 | F32: 8679828.4 | G32: 8535872 | H32: =INDEX('Operating Statement'!W:W,MATCH('NEW OSAR'!$C32,'Operating Statement'!V:V,0)) -> 8446720.8 | I32: =SUM(I24:I30) -> 8557379.8 | J32: =IF(E32=0, " ",(H32-E32)/E32) -> -0.058854935 | K32: =IF(G32=0, " ",(H32-G32)/G32) -> -0.010444307 | L32: =IF(G32=0, " ",(I32-G32)/G32) -> 0.0025196957 | N32: =I32-G32 -> 21507.8 | O32: =(I32-G32)/G32 -> 0.0025196957
E33: (3) Use either Gross Potential (with Vacancy Loss) or Base Rents; use negative $amt for Vacancy Loss
C35: OPERATING EXPENSES: | J35: =IF(E35=0, " ",(H35-E35)/E35) | L35: =IF(G35=0, " ",(J35-G35)/G35)
C36: Real Estate Taxes | E36: 387583 | F36: 384021.67 | G36: 385107.81 | H36: =INDEX('Operating Statement'!W:W,MATCH('NEW OSAR'!$C36,'Operating Statement'!V:V,0)) -> 389066.52 | I36: =MAX(H36,Tax!B3) -> 389066.52 | J36: =IF(E36=0, " ",(H36-E36)/E36) -> 0.0038276189 | K36: =IF(G36=0, " ",(H36-G36)/G36) -> 0.010279485 | L36: Greater of actual 2025 tax bill dated 5/18/2026 ($382.2K) and T12 ending 3/31/2026 | N36: =I36-G36 -> 3958.71 | O36: =(I36-G36)/G36 -> 0.010279485
C37: Property Insurance | E37: 139580.38 | F37: 130448.95 | G37: 131369.85 | H37: =INDEX('Operating Statement'!W:W,MATCH('NEW OSAR'!$C37,'Operating Statement'!V:V,0)) -> 130999.1 | I37: =INDEX('Operating Statement'!W:W,MATCH('NEW OSAR'!$C37,'Operating Statement'!V:V,0)) -> 130999.1 | J37: =IF(E37=0, " ",(H37-E37)/E37) -> -0.061479104 | K37: =IF(G37=0, " ",(H37-G37)/G37) -> -0.0028221848 | L37: Greater of actual insurance premium from 6/28/2025-6/28/2026 ($130.4K) | N37: =I37-G37 -> -370.75 | O37: =(I37-G37)/G37 -> -0.0028221848
C38: Utilities | E38: =287016.97+42872 -> 329888.97 | F38: 368598.31 | G38: 374867.92 | H38: =INDEX('Operating Statement'!W:W,MATCH('NEW OSAR'!$C38,'Operating Statement'!V:V,0)) -> 411158.29 | I38: =H38 -> 411158.29 | J38: =IF(E38=0, " ",(H38-E38)/E38) -> 0.24635355 | K38: =IF(G38=0, " ",(H38-G38)/G38) -> 0.096808417 | L38: T12 ended 3/31/2026 | N38: =I38-G38 -> 36290.37 | O38: =(I38-G38)/G38 -> 0.096808417
C39: Repairs and Maintenance | E39: 232268.57 | F39: 381931.97 | G39: 367637.38 | H39: =INDEX('Operating Statement'!W:W,MATCH('NEW OSAR'!$C39,'Operating Statement'!V:V,0)) -> 354217.02 | I39: =H39 -> 354217.02 | J39: =IF(E39=0, " ",(H39-E39)/E39) -> 0.52503208 | K39: =IF(G39=0, " ",(H39-G39)/G39) -> -0.03650434 | L39: T12 ended 3/31/2026 | N39: =I39-G39 -> -13420.36 | O39: =(I39-G39)/G39 -> -0.03650434
C40: Management Fees | E40: 314494.13 | F40: 260394.85 | G40: 256076.16 | H40: =INDEX('Operating Statement'!W:W,MATCH('NEW OSAR'!$C40,'Operating Statement'!V:V,0)) -> 210758.11 | I40: =MAX(H40,(I32*M40)) -> 256721.4 | J40: =IF(E40=0, " ",(H40-E40)/E40) -> -0.32985042 | K40: =IF(G40=0, " ",(H40-G40)/G40) -> -0.17697099 | L40: Greater of actual fees and 3% of EGI | M40: 0.03 | N40: =I40-G40 -> 645.234 | O40: =(I40-G40)/G40 -> 0.0025196957
C41: Payroll & Benefits | E41: 574480.84 | F41: 571910.18 | G41: 583888.92 | H41: =INDEX('Operating Statement'!W:W,MATCH('NEW OSAR'!$C41,'Operating Statement'!V:V,0)) -> 589879.68 | I41: =H41 -> 589879.68 | J41: =IF(E41=0, " ",(H41-E41)/E41) -> 0.026804793 | K41: =IF(G41=0, " ",(H41-G41)/G41) -> 0.010260102 | L41: T12 ended 3/31/2026 | N41: =I41-G41 -> 5990.76 | O41: =(I41-G41)/G41 -> 0.010260102
C42: Advertising & Marketing | E42: 91494.43 | F42: 123097.15 | G42: 129586.72 | H42: =INDEX('Operating Statement'!W:W,MATCH('NEW OSAR'!$C42,'Operating Statement'!V:V,0)) -> 107708.43 | I42: =H42 -> 107708.43 | J42: =IF(E42=0, " ",(H42-E42)/E42) -> 0.17721297 | K42: =IF(G42=0, " ",(H42-G42)/G42) -> -0.16883127 | L42: T12 ended 3/31/2026 | N42: =I42-G42 -> -21878.29 | O42: =(I42-G42)/G42 -> -0.16883127
C43: Professional Fees | E43: =113265.91+20740 -> 134005.91 | F43: 2280 | G43: 3314 | H43: =INDEX('Operating Statement'!W:W,MATCH('NEW OSAR'!$C43,'Operating Statement'!V:V,0)) -> 2732 | I43: =H43 -> 2732 | J43: =IF(E43=0, " ",(H43-E43)/E43) -> -0.97961284 | K43: =IF(G43=0, " ",(H43-G43)/G43) -> -0.17561859 | L43: T12 ended 3/31/2026 | N43: =I43-G43 -> -582 | O43: =(I43-G43)/G43 -> -0.17561859
C44: General and Administrative | E44: 207771.55 | F44: 217651.72 | G44: 224269.13 | H44: =INDEX('Operating Statement'!W:W,MATCH('NEW OSAR'!$C44,'Operating Statement'!V:V,0)) -> 238036.4 | I44: =H44 -> 238036.4 | J44: =IF(E44=0, " ",(H44-E44)/E44) -> 0.14566407 | K44: =IF(G44=0, " ",(H44-G44)/G44) -> 0.061387272 | L44: T12 ended 3/31/2026 | N44: =I44-G44 -> 13767.27 | O44: =(I44-G44)/G44 -> 0.061387272
C45: Other Expenses | E45: 0 | F45: 0 | G45: 0 | H45: =INDEX('Operating Statement'!W:W,MATCH('NEW OSAR'!$C45,'Operating Statement'!V:V,0)) -> 0 | I45: =H45 -> 0 | J45: =IF(E45=0, " ",(H45-E45)/E45) | K45: =IF(G45=0, " ",(H45-G45)/G45) | L45: T12 ended 3/31/2026
C46: Ground Rent | E46: 0 | F46: 0 | G46: 0 | H46: =INDEX('Operating Statement'!W:W,MATCH('NEW OSAR'!$C46,'Operating Statement'!V:V,0)) -> 0 | I46: =H46 -> 0 | J46: =IF(E46=0, " ",(H46-E46)/E46) | K46: =IF(G46=0, " ",(H46-G46)/G46)
C47: *Total Operating Expenses | E47: =SUM(E36:E46) -> 2411567.8 | F47: 2440334.8 | G47: 2456117.9 | H47: =INDEX('Operating Statement'!W:W,MATCH('NEW OSAR'!$C47,'Operating Statement'!V:V,0)) -> 2434555.6 | I47: =SUM(I36:I46) -> 2480518.8 | J47: =IF(E47=0, " ",(H47-E47)/E47) -> 0.009532293 | K47: =IF(G47=0, " ",(H47-G47)/G47) -> -0.0087790335 | N47: =I47-G47 -> 24400.944 | O47: =(I47-G47)/G47 -> 0.0099347609
C49: Operating Expense Ratio | E49: =E47/E32 -> 0.26870015 | F49: 0.28115012 | G49: 0.28774071 | H49: =H47/H32 -> 0.28822494 | I49: =I47/I32 -> 0.28986896 | J49: =IF(E49=0, " ",(H49-E49)/E49) -> 0.072663854 | K49: =IF(G49=0, " ",(H49-G49)/G49) -> 0.0016828499 | N49: =I49-G49 -> 0.0021282536 | O49: =(I49-G49)/G49 -> 0.0073964285
C51: *Net Operating Income | E51: =E32-E47 -> 6563372.5 | F51: 6239493.6 | G51: 6079754.1 | H51: =INDEX('Operating Statement'!W:W,MATCH('NEW OSAR'!$C51,'Operating Statement'!V:V,0)) -> 6012165.2 | I51: =I32-I47 -> 6076861 | J51: =IF(E51=0, " ",(H51-E51)/E51) -> -0.083982327 | K51: =IF(G51=0, " ",(H51-G51)/G51) -> -0.01111705 | L51: =IF(G51=0, " ",(I51-G51)/G51) -> -0.00047586529 | M51: NOI | N51: =I51-G51 -> -2893.144 | O51: =(I51-G51)/G51 -> -0.00047586529
C53: Capital Expenditures | E53: 123750 | F53: 123750 | G53: 123750 | H53: =I53 -> 123750 | I53: =E12*E14 -> 123750 | J53: =IF(E53=0, " ",(H53-E53)/E53) -> 0 | K53: =IF(G53=0, " ",(H53-G53)/G53) -> 0 | L53: $250 per unit per LA
C54: Extraordinary Capital Expenditures
C55: Total Capital Items | E55: 123750 | F55: 123750 | G55: 123750 | H55: =SUM(H53:H54) -> 123750 | I55: =SUM(I53:I54) -> 123750 | J55: =IF(E55=0, " ",(H55-E55)/E55) -> 0 | K55: =IF(G55=0, " ",(H55-G55)/G55) -> 0 | L55: =IF(G55=0, " ",(I55-G55)/G55) -> 0
C57: *Net Cash Flow | E57: =E51-E55 -> 6439622.5 | F57: 6115743.6 | G57: 5956004.1 | H57: =H51-H55 -> 5888415.2 | I57: =I51-I55 -> 5953111 | J57: =IF(E57=0, " ",(H57-E57)/E57) -> -0.085596212 | K57: =IF(G57=0, " ",(H57-G57)/G57) -> -0.011348033 | L57: =IF(G57=0, " ",(I57-G57)/G57) -> -0.00048575252
C59: Debt Service - A Note | F59: 6189783.2 | G59: 5728520.8 | H59: ='Debt Service'!C11 -> 5629018.8 | I59: ='Debt Service'!C11 -> 5629018.8
C60: Debt Service - B Note
C61: Debt Service - C Note
C63: *Net Cash Flow after Debt Service | F63: -74039.663 | G63: 227483.31 | H63: =H57-H59 -> 259396.39 | I63: =I57-I59 -> 324092.17 | J63: =IF(E63=0, " ",(H63-E63)/E63) | K63: =IF(G63=0, " ",(H63-G63)/G63) -> 0.14028757 | L63: =IF(G63=0, " ",(I63-G63)/G63) -> 0.42468552
C65: *DSCR: (NOI/Debt Service) - A Note | F65: 0.98803841 | G65: 1.0613131 | H65: =H51/H59 -> 1.0680663 | I65: =I51/I59 -> 1.0795595 | K65: =IF(G65=0, " ",(H65-G65)/G65) -> 0.0063630554 | L65: Capped benchmark rate of 4.50%
C66: *DSCR: (NOI/Debt Service) - A & B Note
C67: *DSCR: (NOI/Debt Service) - A, B & C Note
C69: *DSCR: (NCF/Debt Service) - A Note | F69: 0.98803841 | G69: 1.0397107 | H69: =H57/H59 -> 1.046082 | I69: =I57/I59 -> 1.0575753 | K69: =IF(G69=0, " ",(H69-G69)/G69) -> 0.0061279896 | L69: Capped benchmark rate of 4.50%
C70: *DSCR: (NCF/Debt Service) - A & B Note
C71: *DSCR: (NCF/Debt Service) - A, B & C Note
C73: * Debt Yield: (NCF/Debt Balance) | F73: 0.066692951 | G73: 0.06468893 | H73: =H57/E6 -> 0.063954838 | I73: =I57/$E$6 -> 0.064657507 | L73: 7.00% DY beginning 6/9/2027
C75: Source of Financial Data:
E76: (ie. operating statements, financial statements, tax return, other)
C77: Notes and Assumptions: Years above will roll, always showing a 3yr sequential history. Comments from the most recent NOI Adjustment Worksheet should be carried forward to Operating Statement
C78: Analysis Report. Year-over-year variances (either higher or lower) must be explained and noted for the following: >20% DSCR change, >20% EGI/Total Operating Expenses or Total Capital
C79: Items. Quarterly variance comments may be necessary if the loan is on the Watch List.
C80: Income: Comments
C83: Expense: Comments
C86: Capital Items: Comments
C89: DSCR: Comments
C92: * Used in the CREFC Comparative Financial Status Report/CREFC Property File/CREFC Loan Periodic Update File. Note that information for multiple property loans must be consolidated (if available)
C93: for reporting to the CREFC Loan Periodic Update file.

Sheet Paydown Scenario
B2: DY
B3: Target DY | D3: 0.0625
B5: Current Principal | D5: =#REF! -> #REF!
B6: Paydown | D6: =+IF(D9/D5<D3,D5-(D9/D3),0) -> #REF!
B7: Total Principal | D7: =+D5-D6 -> #REF!
B9: Current Net Cash Flow | D9: =#REF! -> #REF!
B11: Needed Net Cash Flow | D11: =+D5*D3 -> #REF!
B12: DY | D12: =D11/D5 -> #REF!
B13: NCF Change | D13: =D11-D9 -> #REF!

Sheet Comm OSAR
C1: CREFC Investor Reporting Package
C2: COMMERCIAL OPERATING STATEMENT ANALYSIS REPORT (includes Retail/Office/Industrial/Mixed Use/Self Storage)
C3: as of MM/DD/YY
C4: PROPERTY OVERVIEW | H4: Allocated Loan Amount/Percentage
C5: Property ID | E5: 1001-001 | F5: Paid Thru Date | G5: Debt Outside Trust (1) | H5: $ | I5: %
C6: Note A-Scheduled Loan Balance | E6: 0 | F6: MM/DD/YY | G6: X or Blank | H6: 0 | I6: 0
C7: Note B-Scheduled Loan Balance | E7: 0 | F7: MM/DD/YY | G7: X or Blank | H7: 0 | I7: 0
C8: Note C-Scheduled Loan Balance | E8: 0 | F8: MM/DD/YY | G8: X or Blank | H8: 0 | I8: 0
C9: Property Name
C10: Property Type
C11: Property Address, City, State
C12: Current Net Rentable SF/Units/Beds/Rooms | G12: Use second box to specify sqft.,units…
C13: Year Built/Year Renovated | E13: YYYY | F13: YYYY
C14: Cap Ex Reserve (annually)/per Unit.etc. (2) | E14: 0 | F14: 0 | G14: specify annual/per unit…
C15: Statement Ending Date | E15: Underwriting | F15: MM/DD/YY | G15: MM/DD/YY | H15: MM/DD/YY | I15: MM/DD/YY
C16: Occupancy Rate (physical) | E16: 0 | F16: 0 | G16: 0 | H16: 0 | I16: 0
C17: Occupancy Date | E17: MM/DD/YY | F17: MM/DD/YY | G17: MM/DD/YY | H17: MM/DD/YY | I17: MM/DD/YY
E18: (1) "X" if debt is outside of the trust, otherwise leave blank
E19: (2) Total $ amount of Capital Reserves required annually by loan documents
C21: INCOME:
C22: Number of Mos. Covered
C23: Period Ended | E23: At Contribution | F23: 3rd Preceding | G23: 2nd Preceding | H23: Preceding Yr. | I23: TTM/YTD | J23: DY Test | K23: Notes
C24: Statement Ending Date | E24: Information | H24: (fm NOI Adj Sheet) | I24: as of / / | J24: as of / /
C25: Gross Potential Rent (3)
C26: Less: Vacancy Loss
C27: OR
C28: Base Rent (3)
C29: Expense Reimbursement
C30: Percentage Rent
C31: Parking Income
C32: Other Income
C34: *Effective Gross Income
E35: (3) Use either Gross Potential (with Vacancy Loss) or Base Rents; use negative $amt for Vacancy Loss
C37: OPERATING EXPENSES:
C38: Real Estate Taxes
C39: Property Insurance
C40: Utilities
C41: Repairs and Maintenance
C42: Janitorial
C43: Management Fees
C44: Payroll & Benefits
C45: Advertising & Marketing
C46: Professional Fees
C47: General and Administrative
C48: Other Expenses
... C76: *DSCR: (NCF/Debt Service) - A, B & C Note
C78: *Debt Yield (NOI/Debt Balance) | I78: =I54/$E$6 -> #DIV/0! | J78: =J56/E11 -> #DIV/0! | K78: 0.06
C80: Source of Financial Data:
E81: (ie. operating statements, financial statements, tax return, other)
C82: Notes and Assumptions: Years above will roll, always showing a 3yr sequential history. Comments from the most recent NOI Adjustment Worksheet should be carried forward to Operating Statement
C83: * Used in the CREFC Comparative Financial Status Report/CREFC Property File/CREFC Loan Periodic Update File. Note that information for multiple property loans must be consolidated (if available)
C84: for reporting to the CREFC Loan Periodic Update file.

Sheet Operating Statement
B3: Location: Strada
B4: Strada
AC5: MULTIFAMILY CASH FLOW
B6: Knightvest Management LLC | AC6: Strada
B7: 12 Month Income Statement | AC7: Investment Year | AD7: IRE In-Place NOI Definition | AE7: 1 | AF7: 2 | AG7: 3 | AH7: 4 | AI7: 5 | AJ7: 6 | AK7: 7 | AL7: 8 | AM7: 9 | AN7: 10
B8: Reporting Book: | C8: ACCRUAL | AC8: Year Ending | AE8: 46173 | AF8: 46538 | AG8: 46904 | AH8: 47269 | AI8: 47634 | AJ8: 47999 | AK8: 48365 | AL8: 48730 | AM8: 49095 | AN8: 49460
B9: As of Date: | C9: 03/31/2026
AC10: INCOME | AD10: $ Gross
C11: Month Ending | D11: Month Ending | E11: Month Ending | F11: Month Ending | G11: Month Ending | H11: Month Ending | I11: Month Ending | J11: Month Ending | K11: Month Ending | L11: Month Ending | M11: Month Ending | N11: Month Ending | O11: Total | AC11: Potential Rental Revenue | AD11: 8474519 | AE11: 8357667.1 | AF11: 8579313.5 | AG11: 8960894.7 | AH11: 9318313.2 | AI11: 9674923.9 | AJ11: 9995970.5 | AK11: 10295850 | AL11: 10604725 | AM11: 10922867 | AN11: 11250553
C12: 04/30/2025 | D12: 05/31/2025 | E12: 06/30/2025 | F12: 07/31/2025 | G12: 08/31/2025 | H12: 09/30/2025 | I12: 10/31/2025 | J12: 11/30/2025 | K12: 12/31/2025 | L12: 01/31/2026 | M12: 02/28/2026 | N12: 03/31/2026 | O12: 03/31/2026 | AC12: Loss To Lease | AD12: 0 | AE12: 33125.696 | AF12: -103648.36 | AG12: -153090.98 | AH12: -156337.08 | AI12: -147550.63 | AJ12: -121551.92 | AK12: -111673.93 | AL12: -110350.84 | AM12: -108988.06 | AN12: -107584.39
C13: Actual | D13: Actual | E13: Actual | F13: Actual | G13: Actual | H13: Actual | I13: Actual | J13: Actual | K13: Actual | L13: Actual | M13: Actual | N13: Actual | O13: Actual | AC13: Scheduled Base Rental Revenue | AD13: 8474519 | AE13: 8390792.8 | AF13: 8475665.2 | AG13: 8807803.7 | AH13: 9161976.1 | AI13: 9527373.3 | AJ13: 9874418.6 | AK13: 10184176 | AL13: 10494374 | AM13: 10813879 | AN13: 11142968
B14: INCOME | AC14: Other Income | AD14: 1242919.2 | AE14: 1220508 | AF14: 1503810.3 | AG14: 1640643.9 | AH14: 1679333.5 | AI14: 1718943.7 | AJ14: 1759496.8 | AK14: 1801015.2 | AL14: 1843522.3 | AM14: 1887041.6 | AN14: 1931597.6
AC15: Potential Gross Income | AD15: 9717438.2 | AE15: 9611300.8 | AF15: 9979475.5 | AG15: 10448448 | AH15: 10841310 | AI15: 11246317 | AJ15: 11633915 | AK15: 11985191 | AL15: 12337897 | AM15: 12700920 | AN15: 13074566
B16: RENTAL REVENUE | Q16: Annualized T12 | R16: Annualized T6 | S16: Annualized T3 | V16: 46022 | W16: T12 ROLLUP | X16: Lender Calc | AC16: Minus: Vacancy | AD16: -499996.62 | AE16: -461493.6 | AF16: -466161.58 | AG16: -484429.2 | AH16: -503908.69 | AI16: -524005.53 | AJ16: -543093.02 | AK16: -560129.66 | AL16: -577190.58 | AM16: -594763.33 | AN16: -612863.26
A17: Gross Potential Rent (3) | B17: 4001.000 - Gross Potential Rent | C17: 710972.5 | D17: 709919.04 | E17: 709165.83 | F17: 707103.39 | G17: 706700.48 | H17: 706373.63 | I17: 707219.04 | J17: 658440 | K17: 657027.42 | L17: 677622.1 | M17: 692639.3 | N17: 692640 | O17: 8335822.7 | Q17: =IF(SUM(C17:N17)=0,0,SUM(C17:N17)) -> 8335822.7 | R17: =IF(Q17=0,0,SUM(I17:N17)*2) -> 8171175.7 | S17: =IF(Q17=0,0,SUM(L17:N17)*4) -> 8251605.6 | V17: Gross Potential Rent (3) | W17: =SUMIF(A:A,$V17,O:O) -> 7969528.7 | AC17: Minus: Credit Loss | AD17: -114839.31 | AE17: -125861.89 | AF17: -105945.81 | AG17: -88078.037 | AH17: -91619.761 | AI17: -95273.733 | AJ17: -98744.186 | AK17: -101841.76 | AL17: -104943.74 | AM17: -108138.79 | AN17: -111429.68
A18: Less: Vacancy Loss | B18: 4002.000 - Loss/Gain to Lease | C18: -2799.58 | D18: -2650.15 | E18: -2687.68 | F18: -4409.17 | G18: -3076.69 | H18: -5544.37 | I18: -5613.39 | J18: 37972.64 | K18: 37968.9 | L18: 18710.7 | M18: 3754.9 | N18: 3279.74 | O18: 74905.85 | Q18: =IF(SUM(C18:N18)=0,0,SUM(C18:N18)) -> 74905.85 | R18: =IF(Q18=0,0,SUM(I18:N18)*2) -> 192146.98 | S18: =IF(Q18=0,0,SUM(L18:N18)*4) -> 102981.36 | V18: Less: Vacancy Loss | W18: =SUMIF(A:A,$V18,O:O) -> -576358.57 | AC18: Minus: Model Unit | AD18: 0 | AE18: 0 | AF18: 0 | AG18: 0 | AH18: 0 | AI18: 0 | AJ18: 0 | AK18: 0 | AL18: 0 | AM18: 0 | AN18: 0
A19: Less: Vacancy Loss | B19: 4011.000 - Vacancy Loss | C19: -43114.26 | D19: -53948.19 | E19: -57543.33 | F19: -56344.1 | G19: -51258.7 | H19: -47472.31 | I19: -52857.62 | J19: -67000.77 | K19: -61906.17 | L19: -51872.73 | M19: -54647.44 | N19: -53298.8 | O19: -651264.42 | Q19: =IF(SUM(C19:N19)=0,0,SUM(C19:N19)) -> -651264.42 | R19: =IF(Q19=0,0,SUM(I19:N19)*2) -> -683167.06 | S19: =IF(Q19=0,0,SUM(L19:N19)*4) -> -639275.88 | AC19: Minus: Concessions Initial Lease Up | AD19: -117055.64 | AE19: -47462.588 | AF19: -36695.348 | AG19: -2996.4319 | AH19: 0 | AI19: 0 | AJ19: 0 | AK19: 0 | AL19: 0 | AM19: 0 | AN19: 0
A20: Gross Potential Rent (3) | B20: 4011.100 - Month to Month Rent | C20: 1867.85 | D20: 2266.4 | E20: 2106.89 | F20: 2499.91 | G20: 3028.37 | H20: 2796.34 | I20: 3222.05 | J20: 2775.95 | K20: 2887.84 | L20: 2276.35 | M20: 3193.24 | N20: 1918.15 | O20: 30839.34 | Q20: =IF(SUM(C20:N20)=0,0,SUM(C20:N20)) -> 30839.34 | R20: =IF(Q20=0,0,SUM(I20:N20)*2) -> 32547.16 | S20: =IF(Q20=0,0,SUM(L20:N20)*4) -> 29550.96 | V20: Base Rent (3) | W20: =SUMIF(A:A,$V20,O:O) -> 0 | AC20: Minus: Concessions Ongoing | AE20: -349333.62 | AF20: -177978.04 | AG20: -94639.172 | AH20: 0 | AI20: 0 | AJ20: 0 | AK20: 0 | AL20: 0 | AM20: 0 | AN20: 0
A21: Gross Potential Rent (3) | B21: 4012.000 - Discounts/Concessions | C21: 0 | D21: 0 | E21: 0 | F21: -200.52 | G21: -1554 | H21: -1554 | I21: -1554 | J21: -1554 | K21: -1554 | L21: -1604.13 | M21: -1665 | N21: -1554 | O21: -12793.65 | Q21: =IF(SUM(C21:N21)=0,0,SUM(C21:N21)) -> -12793.65 | R21: =IF(Q21=0,0,SUM(I21:N21)*2) -> -18970.26 | S21: =IF(Q21=0,0,SUM(L21:N21)*4) -> -19292.52 | V21: Laundry/Vending Income | W21: =SUMIF(A:A,$V21,O:O) -> 0 | AC21: Effective Gross Income | AD21: 8985546.7 | AE21: 8627149.1 | AF21: 9192694.7 | AG21: 9778304.8 | AH21: 10245781 | AI21: 10627038 | AJ21: 10992078 | AK21: 11323219 | AL21: 11655762 | AM21: 11998018 | AN21: 12350273
A22: Gross Potential Rent (3) | B22: 4014.000 - Bad Debt | C22: -8091.09 | D22: -2715.94 | E22: -27759.2 | F22: -3529.88 | G22: -3581.47 | H22: -12831.95 | I22: -18168.46 | J22: -12021.55 | K22: -12156.51 | L22: -35285.15 | M22: -248.68 | N22: -22978.88 | O22: -159368.76 | Q22: =IF(SUM(C22:N22)=0,0,SUM(C22:N22)) -> -159368.76 | R22: =IF(Q22=0,0,SUM(I22:N22)*2) -> -201718.46 | S22: =IF(Q22=0,0,SUM(L22:N22)*4) -> -234050.84 | V22: Parking Income | W22: =SUMIF(A:A,$V22,O:O) -> 44205.67
A23: Gross Potential Rent (3) | B23: 4040.000 - One-Time Special or Allowance | C23: -14875 | D23: -5032.26 | E23: 451 | F23: -8422.98 | G23: -34920.51 | H23: -47726.38 | I23: -22988.63 | J23: -9278.94 | K23: -1774.92 | L23: -30293.36 | M23: -35474.34 | N23: -14634.68 | O23: -224971 | Q23: =IF(SUM(C23:N23)=0,0,SUM(C23:N23)) -> -224971 | R23: =IF(Q23=0,0,SUM(I23:N23)*2) -> -228889.74 | S23: =IF(Q23=0,0,SUM(L23:N23)*4) -> -321609.52 | V23: Other Income | W23: =SUMIF(A:A,$V23,O:O) -> 1009345 | AC23: OPERATING EXPENSES | AD23: $ Gross
B24: NET RENTAL REVENUE | C24: 643960.42 | D24: 647838.9 | E24: 623733.51 | F24: 636696.65 | G24: 615337.48 | H24: 594040.96 | I24: 609258.99 | J24: 609333.33 | K24: 620492.56 | L24: 579553.78 | M24: 607551.98 | N24: 605371.53 | O24: 7393170.1 | Q24: =SUM(Q17:Q23) -> 7393170.1 | R24: =SUM(R17:R23) -> 7263124.3 | S24: =SUM(S17:S23) -> 7169909.2 | AC24: Payroll | AD24: 574480.84 | AE24: 569345.6 | AF24: 586425.97 | AG24: 604018.75 | AH24: 622139.31 | AI24: 640803.49 | AJ24: 660027.59 | AK24: 679828.42 | AL24: 700223.27 | AM24: 721229.97 | AN24: 742866.87
U25: =IF(W25=O49,"YES","NO") -> YES | V25: *Effective Gross Income | W25: =SUM(W17:W23) -> 8446720.8 | AC25: Employee Units | AD25: 10605.92 | AE25: 10924.098 | AF25: 11251.821 | AG25: 11589.375 | AH25: 11937.056 | AI25: 12295.168 | AJ25: 12664.023 | AK25: 13043.944 | AL25: 13435.262 | AM25: 13838.32 | AN25: 14253.47
B26: OTHER TENANT INCOME | AC26: Marketing | AD26: 91494.43 | AE26: 91575 | AF26: 94322.25 | AG26: 97151.917 | AH26: 100066.48 | AI26: 103068.47 | AJ26: 106160.52 | AK26: 109345.34 | AL26: 112625.7 | AM26: 116004.47 | AN26: 119484.6
A27: Other Income | B27: 4100.000 - Late Charges | C27: 5493 | D27: 9660 | E27: 2484.37 | F27: 7065 | G27: 8715 | H27: 9660 | I27: 5790 | J27: 10425 | K27: 12561.6 | L27: 2808 | M27: 9660 | N27: 3780.23 | O27: 88102.2 | Q27: =IF(SUM(C27:N27)=0,0,SUM(C27:N27)) -> 88102.2 | R27: =IF(Q27=0,0,SUM(I27:N27)*2) -> 90049.66 | S27: =IF(Q27=0,0,SUM(L27:N27)*4) -> 64992.92 | V27: OPERATING EXPENSES: | W27: =SUMIF(A:A,$V27,O:O) -> 0 | AC27: General & Admin. | AD27: 207771.55 | AE27: 210375 | AF27: 216686.25 | AG27: 223186.84 | AH27: 229882.44 | AI27: 236778.92 | AJ27: 243882.28 | AK27: 251198.75 | AL27: 258734.71 | AM27: 266496.76 | AN27: 274491.66
A28: Other Income | B28: 4120.000 - Application Fee Income | C28: 1500 | D28: 800 | E28: 1800 | F28: 2300 | G28: 2295.58 | H28: 1050 | I28: 200 | J28: 600 | K28: -50 | L28: 0 | M28: 0 | N28: 0 | O28: 10495.58 | Q28: =IF(SUM(C28:N28)=0,0,SUM(C28:N28)) -> 10495.58 | R28: =IF(Q28=0,0,SUM(I28:N28)*2) -> 1500 | S28: =IF(Q28=0,0,SUM(L28:N28)*4) -> 0 | V28: Real Estate Taxes | W28: =SUMIF(A:A,$V28,O:O) -> 389066.52 | AC28: Managed WiFi | AD28: 0 | AE28: 44550 | AF28: 183546 | AG28: 189052.38 | AH28: 194723.95 | AI28: 200565.67 | AJ28: 206582.64 | AK28: 212780.12 | AL28: 219163.52 | AM28: 225738.43 | AN28: 232510.58
A29: Other Income | B29: 4120.100 - Pet Fees | C29: 3801 | D29: 2872.34 | E29: 2839.68 | F29: 2641.94 | G29: 2611.45 | H29: 2473.33 | I29: 3661.46 | J29: 2903.5 | K29: 2888.07 | L29: 3905.02 | M29: 2993.75 | N29: 3424.35 | O29: 37015.89 | Q29: =IF(SUM(C29:N29)=0,0,SUM(C29:N29)) -> 37015.89 | R29: =IF(Q29=0,0,SUM(I29:N29)*2) -> 39552.3 | S29: =IF(Q29=0,0,SUM(L29:N29)*4) -> 41292.48 | V29: Property Insurance | W29: =SUMIF(A:A,$V29,O:O) -> 130999.1 | AC29: Landscaping/Grounds | AD29: 113265.91 | AE29: 111375 | AF29: 114716.25 | AG29: 118157.74 | AH29: 121702.47 | AI29: 125353.54 | AJ29: 129114.15 | AK29: 132987.57 | AL29: 136977.2 | AM29: 141086.52 | AN29: 145319.11
A30: Other Income | B30: 4120.200 - Administrative Fees | C30: 5400 | D30: 3100.69 | E30: 6875 | F30: 10179.03 | G30: 11150 | H30: 5450 | I30: 1683.07 | J30: 1850 | K30: 7800 | L30: 10000 | M30: 6000 | N30: 7750 | O30: 77237.79 | Q30: =IF(SUM(C30:N30)=0,0,SUM(C30:N30)) -> 77237.79 | R30: =IF(Q30=0,0,SUM(I30:N30)*2) -> 70166.14 | S30: =IF(Q30=0,0,SUM(L30:N30)*4) -> 95000 | V30: Utilities | W30: =SUMIF(A:A,$V30,O:O) -> 411158.29 | AC30: Make-ready | AD30: 0 | AE30: 0 | AF30: 0 | AG30: 0 | AH30: 0 | AI30: 0 | AJ30: 0 | AK30: 0 | AL30: 0 | AM30: 0 | AN30: 0
A31: Other Income | B31: 4124.000 - Lease Termination Fees | C31: 3915.58 | D31: 7301.51 | E31: 6030.86 | F31: 4375.64 | G31: 3907.48 | H31: 3745.08 | I31: 3513.02 | J31: 2993.54 | K31: 2924.22 | L31: 10335.01 | M31: 6742.67 | N31: 2852.95 | O31: 58637.56 | Q31: =IF(SUM(C31:N31)=0,0,SUM(C31:N31)) -> 58637.56 | R31: =IF(Q31=0,0,SUM(I31:N31)*2) -> 58722.82 | S31: =IF(Q31=0,0,SUM(L31:N31)*4) -> 79722.52 | V31: Repairs and Maintenance | W31: =SUMIF(A:A,$V31,O:O) -> 354217.02 | AC31: Repairs & Maint. | AD31: 232268.57 | AE31: 232268.57 | AF31: 239236.63 | AG31: 246413.73 | AH31: 253806.14 | AI31: 261420.32 | AJ31: 269262.93 | AK31: 277340.82 | AL31: 285661.04 | AM31: 294230.88 | AN31: 303057.8
A32: Parking Income | B32: 4140.000 - Reserved/ Covered Parking Fees | C32: 3611 | D32: 3717.59 | E32: 3663 | F32: 3819.67 | G32: 3861.26 | H32: 3757.35 | I32: 3692.92 | J32: 3651 | K32: 3586.89 | L32: 3644.49 | M32: 3561.79 | N32: 3638.71 | O32: 44205.67 | Q32: =IF(SUM(C32:N32)=0,0,SUM(C32:N32)) -> 44205.67 | R32: =IF(Q32=0,0,SUM(I32:N32)*2) -> 43551.6 | S32: =IF(Q32=0,0,SUM(L32:N32)*4) -> 43379.96 | V32: Management Fees | W32: =SUMIF(A:A,$V32,O:O) -> 210758.11 | AC32: Trash Expense | AD32: 42871.94 | AE32: 45045 | AF32: 46396.35 | AG32: 47788.24 | AH32: 49221.888 | AI32: 50698.544 | AJ32: 52219.501 | AK32: 53786.086 | AL32: 55399.668 | AM32: 57061.658 | AN32: 58773.508
A33: Other Income | B33: 4150.000 - Miscellaneous Income | C33: -826.67 | D33: 4721.78 | E33: 3229.02 | F33: 1661.33 | G33: 1759.53 | H33: 3333.07 | I33: 546.03 | J33: 5269.3 | K33: 2390.74 | L33: 5622.64 | M33: 1658.02 | N33: 1033.83 | O33: 30398.62 | Q33: =IF(SUM(C33:N33)=0,0,SUM(C33:N33)) -> 30398.62 | R33: =IF(Q33=0,0,SUM(I33:N33)*2) -> 33041.12 | S33: =IF(Q33=0,0,SUM(L33:N33)*4) -> 33257.96 | V33: Payroll & Benefits | W33: =SUMIF(A:A,$V33,O:O) -> 589879.68 | AC33: Security/Life Safety | AD33: 20740.1 | AE33: 25245 | AF33: 26002.35 | AG33: 26782.42 | AH33: 27585.893 | AI33: 28413.47 | AJ33: 29265.874 | AK33: 30143.85 | AL33: 31048.166 | AM33: 31979.611 | AN33: 32938.999
A34: Other Income | B34: 4150.100 - Cable/Internet Charges | C34: 7 | D34: 151.3 | E34: 619.68 | F34: 1494.84 | G34: 3201.9 | H34: 4362.44 | I34: 4644.46 | J34: 6360.67 | K34: 7056.44 | L34: 8744.64 | M34: 10446.94 | N34: 11940.66 | O34: 59030.97 | Q34: =IF(SUM(C34:N34)=0,0,SUM(C34:N34)) -> 59030.97 | R34: =IF(Q34=0,0,SUM(I34:N34)*2) -> 98387.62 | S34: =IF(Q34=0,0,SUM(L34:N34)*4) -> 124528.96 | V34: Advertising & Marketing | W34: =SUMIF(A:A,$V34,O:O) -> 107708.43 | AC34: Utilities | AD34: 287016.97 | AE34: 294525 | AF34: 303360.75 | AG34: 312461.57 | AH34: 321835.42 | AI34: 331490.48 | AJ34: 341435.2 | AK34: 351678.25 | AL34: 362228.6 | AM34: 373095.46 | AN34: 384288.32
A35: Other Income | B35: 4150.200 - Renters Insurance Charges | C35: 7283.15 | D35: 7288.32 | E35: 6946.32 | F35: 6895.83 | G35: 7339.34 | H35: 7252.47 | I35: 7072.01 | J35: 7007.73 | K35: 7064.69 | L35: 7094.77 | M35: 7248.44 | N35: 7140.91 | O35: 85633.98 | Q35: =IF(SUM(C35:N35)=0,0,SUM(C35:N35)) -> 85633.98 | R35: =IF(Q35=0,0,SUM(I35:N35)*2) -> 85257.1 | S35: =IF(Q35=0,0,SUM(L35:N35)*4) -> 85936.48 | V35: Professional Fees | W35: =SUMIF(A:A,$V35,O:O) -> 2732 | AC35: Insurance | AD35: 139580.38 | AE35: 139580.38 | AF35: 132601.36 | AG35: 135253.38 | AH35: 139310.99 | AI35: 143490.32 | AJ35: 147795.03 | AK35: 152228.88 | AL35: 156795.74 | AM35: 161499.61 | AN35: 166344.6
A36: Other Income | B36: 4150.300 - Transfer Fee | C36: 350 | D36: 0 | E36: 0 | F36: 0 | G36: 0 | H36: 750 | I36: 200 | J36: 1250 | K36: 0 | L36: 2450 | M36: -750 | N36: 1750 | O36: 6000 | Q36: =IF(SUM(C36:N36)=0,0,SUM(C36:N36)) -> 6000 | R36: =IF(Q36=0,0,SUM(I36:N36)*2) -> 9800 | S36: =IF(Q36=0,0,SUM(L36:N36)*4) -> 13800 | V36: General and Administrative | W36: =SUMIF(A:A,$V36,O:O) -> 238036.4 | AC36: Replacement Reserves | AD36: 123750 | AE36: 123750 | AF36: 123750 | AG36: 123750 | AH36: 123750 | AI36: 123750 | AJ36: 123750 | AK36: 123750 | AL36: 123750 | AM36: 123750 | AN36: 123750
A37: Other Income | B37: 4150.400 - Keys, Cards and Remotes | C37: 0 | D37: 0 | E37: 0 | F37: 0 | G37: 0 | H37: 0 | I37: 0 | J37: 5 | K37: 0 | L37: 0 | M37: 0 | N37: 0 | O37: 5 | Q37: =IF(SUM(C37:N37)=0,0,SUM(C37:N37)) -> 5 | R37: =IF(Q37=0,0,SUM(I37:N37)*2) -> 10 | S37: =IF(Q37=0,0,SUM(L37:N37)*4) -> 0 | V37: Other Expenses | W37: =SUMIF(A:A,$V37,O:O) -> 0 | AC37: Misc #2 | AD37: 0 | AE37: 0 | AF37: 0 | AG37: 0 | AH37: 0 | AI37: 0 | AJ37: 0 | AK37: 0 | AL37: 0 | AM37: 0 | AN37: 0
A38: Other Income | B38: 4150.600 - Technology Fee | C38: 13725 | D38: 13639.08 | E38: 13073.14 | F38: 13542.56 | G38: 13643.96 | H38: 13598.29 | I38: 13289.51 | J38: 13015.55 | K38: 13147.75 | L38: 13022.73 | M38: 13594.01 | N38: 13314.53 | O38: 160606.11 | Q38: =IF(SUM(C38:N38)=0,0,SUM(C38:N38)) -> 160606.11 | R38: =IF(Q38=0,0,SUM(I38:N38)*2) -> 158768.16 | S38: =IF(Q38=0,0,SUM(L38:N38)*4) -> 159725.08 | V38: Ground Rent | W38: =SUMIF(A:A,$V38,O:O) -> 0 | AC38: RE Taxes | AD38: 387583 | AE38: 387583 | AF38: 406962.15 | AG38: 427310.26 | AH38: 448675.77 | AI38: 471109.56 | AJ38: 494665.04 | AK38: 519398.29 | AL38: 545368.2 | AM38: 572636.61 | AN38: 601268.44
A39: Other Income | B39: 4160.000 - Utility Reimb/Water | C39: 19604.18 | D39: 19942.16 | E39: 20778.64 | F39: 21955.42 | G39: 21638.14 | H39: 21098.62 | I39: 28712.46 | J39: 28448.09 | K39: 24277.72 | L39: 18897.34 | M39: 19324.65 | N39: 20444.21 | O39: 265121.63 | Q39: =IF(SUM(C39:N39)=0,0,SUM(C39:N39)) -> 265121.63 | R39: =IF(Q39=0,0,SUM(I39:N39)*2) -> 280208.94 | S39: =IF(Q39=0,0,SUM(L39:N39)*4) -> 234664.8 | U39: =IF(W39=O138,"YES","NO") -> YES | V39: *Total Operating Expenses | W39: =SUM(W27:W38) -> 2434555.6 | AC39: Management Fee | AD39: 314494.13 | AE39: 301950.22 | AF39: 321744.31 | AG39: 342240.67 | AH39: 358602.34 | AI39: 371946.32 | AJ39: 384722.73 | AK39: 396312.68 | AL39: 407951.68 | AM39: 419930.64 | AN39: 432259.56
A40: Other Income | B40: 4161.000 - Utility Reimb/Electric | C40: 1727.91 | D40: 1599.61 | E40: 2261.64 | F40: 1607.7 | G40: 1578.72 | H40: 2256.44 | I40: 2475.36 | J40: 3856.12 | K40: 3533.05 | L40: 2044.64 | M40: 2000.75 | N40: 2241.36 | O40: 27183.3 | Q40: =IF(SUM(C40:N40)=0,0,SUM(C40:N40)) -> 27183.3 | R40: =IF(Q40=0,0,SUM(I40:N40)*2) -> 32302.56 | S40: =IF(Q40=0,0,SUM(L40:N40)*4) -> 25147 | AC40: Total Operating Expenses | AD40: 2545923.7 | AE40: 2588091.9 | AF40: 2807002.4 | AG40: 2905157.3 | AH40: 3003240.1 | AI40: 3101184.3 | AJ40: 3201547.5 | AK40: 3303823 | AL40: 3409362.8 | AM40: 3518578.9 | AN40: 3631607.5
A41: Other Income | B41: 4162.000 - Utility Reimb/Trash | C41: 4598.67 | D41: 4570.12 | E41: 4375.31 | F41: 4520.93 | G41: 4560.31 | H41: 4536.34 | I41: 4438.32 | J41: 4357.33 | K41: 4392.61 | L41: 4340.92 | M41: 4558.41 | N41: 4440.98 | O41: 53690.25 | Q41: =IF(SUM(C41:N41)=0,0,SUM(C41:N41)) -> 53690.25 | R41: =IF(Q41=0,0,SUM(I41:N41)*2) -> 53057.14 | S41: =IF(Q41=0,0,SUM(L41:N41)*4) -> 53361.24 | V41: Operating Expense Ratio | W41: =W39/W25 -> 0.28822494 | AC41: Operating Expenses % EGR | AE41: 0.29999387 | AF41: 0.30535143 | AG41: 0.29710234 | AH41: 0.29311969 | AI41: 0.2918202 | AJ41: 0.29125953 | AK41: 0.29177417 | AL41: 0.29250449 | AM41: 0.29326334 | AN41: 0.29405079
A42: Other Income | B42: 4163.000 - Utility Reimb/Pest Control | C42: 2300.66 | D42: 2283.74 | E42: 2187.69 | F42: 2260.5 | G42: 2280.17 | H42: 2268.14 | I42: 2219.13 | J42: 2178.67 | K42: 2196.29 | L42: 2175.47 | M42: 2279.28 | N42: 2220.49 | O42: 26850.23 | Q42: =IF(SUM(C42:N42)=0,0,SUM(C42:N42)) -> 26850.23 | R42: =IF(Q42=0,0,SUM(I42:N42)*2) -> 26538.66 | S42: =IF(Q42=0,0,SUM(L42:N42)*4) -> 26700.96 | AC42: Real Estate Taxes %/EGR | AE42: 0.044925965 | AF42: 0.044270169 | AG42: 0.04369983 | AH42: 0.04379127 | AI42: 0.044331221 | AJ42: 0.045001958 | AK42: 0.045870195 | AL42: 0.046789579 | AM42: 0.0477276 | AN42: 0.048684627
A43: Other Income | B43: 4170.000 - Security Deposit Forfeiture | C43: 64.21 | D43: 0 | E43: 0 | F43: 0 | G43: 0 | H43: 0 | I43: 1793.74 | J43: -201.45 | K43: 0 | L43: 0 | M43: 0 | N43: 0 | O43: 1656.5 | Q43: =IF(SUM(C43:N43)=0,0,SUM(C43:N43)) -> 1656.5 | R43: =IF(Q43=0,0,SUM(I43:N43)*2) -> 3184.58 | S43: =IF(Q43=0,0,SUM(L43:N43)*4) -> 0 | U43: =IF(W43=O140,"YES","NO") -> YES | V43: *Net Operating Income | W43: =W25-W39 -> 6012165.2
B44: TOTAL OTHER TENANT INCOME | C44: 72554.69 | D44: 81648.24 | E44: 77164.35 | F44: 84320.39 | G44: 88542.84 | H44: 85591.57 | I44: 83931.49 | J44: 93970.05 | K44: 93770.07 | L44: 95085.67 | M44: 89318.71 | N44: 85973.21 | O44: 1031871.3 | Q44: =SUM(Q27:Q43) -> 1031871.3 | R44: =SUM(R27:R43) -> 1084098.4 | S44: =SUM(S27:S43) -> 1081510.4 | AC44: Net Operating Income | AD44: 6439622.9 | AE44: 6039057.2 | AF44: 6385692.3 | AG44: 6873147.5 | AH44: 7242541 | AI44: 7525853.5 | AJ44: 7790530.6 | AK44: 8019396.5 | AL44: 8246399.4 | AM44: 8479439.4 | AN44: 8718665.6
V45: Capital Expenditures | W45: =SUMIF(A:A,$V45,O:O) -> 0
B46: OTHER INCOME | V46: Extraordinary Capital Expenditures | W46: =SUMIF(A:A,$V46,O:O) -> 0
A47: Other Income | B47: 4200.000 - Interest on Bank Accounts | C47: 11099.61 | D47: 10261.56 | E47: 34.16 | F47: 35.41 | G47: 35.54 | H47: 33.58 | I47: 33.42 | J47: 30.45 | K47: 30.04 | L47: 29.42 | M47: 26.64 | N47: 29.57 | O47: 21679.4 | Q47: =IF(SUM(C47:N47)=0,0,SUM(C47:N47)) -> 21679.4 | R47: =IF(Q47=0,0,SUM(I47:N47)*2) -> 359.08 | S47: =IF(Q47=0,0,SUM(L47:N47)*4) -> 342.52 | V47: Total Capital Items | W47: =SUM(W45:W46) -> 0
B48: TOTAL OTHER INCOME | C48: 11099.61 | D48: 10261.56 | E48: 34.16 | F48: 35.41 | G48: 35.54 | H48: 33.58 | I48: 33.42 | J48: 30.45 | K48: 30.04 | L48: 29.42 | M48: 26.64 | N48: 29.57 | O48: 21679.4 | Q48: =SUM(Q47) -> 21679.4 | R48: =SUM(R47) -> 359.08 | S48: =SUM(S47) -> 342.52
B49: TOTAL INCOME | C49: 727614.72 | D49: 739748.7 | E49: 700932.02 | F49: 721052.45 | G49: 703915.86 | H49: 679666.11 | I49: 693223.9 | J49: 703333.83 | K49: 714292.67 | L49: 674668.87 | M49: 696897.33 | N49: 691374.31 | O49: 8446720.8 | Q49: =Q48+Q44+Q24 -> 8446720.8 | R49: =R48+R44+R24 -> 8347581.8 | S49: =S48+S44+S24 -> 8251762 | V49: *Net Cash Flow | W49: =W43-W47 -> 6012165.2
V51: Debt Service - A Note | W51: =SUMIF(A:A,$V51,O:O) -> 0
B52: EXPENSES | Q52: Other Income | R52: =S48+S44+S20-S32 -> 1068023.9 | V52: Debt Service - B Note | W52: =SUMIF(A:A,$V52,O:O) -> 0
Q53: Concessions | R53: =R21+R23 -> -247860 | V53: Debt Service - C Note | W53: =SUMIF(A:A,$V53,O:O) -> 0
B54: UTILITIES | Q54: Delinquent Rents | R54: =AR!AB1 -> 0
B55: 6010.000 - Utilities - Electric / Vacant | C55: 1384.92 | D55: 892.09 | E55: 650.35 | F55: 686.72 | G55: 12655.23 | H55: 4831.83 | I55: 5020.92 | J55: 2882.6 | K55: 3122.58 | L55: 1935.15 | M55: 2415.04 | N55: 4381.7 | O55: 40859.13 | Q55: Total | R55: =SUM(R52:R53) -> 820163.88 | V55: *Net Cash Flow after Debt Service | W55: =W49-W51 -> 6012165.2
B56: 6015.000 - Utilities - Electric / House | C56: 1758.42 | D56: 1368.95 | E56: 2457.74 | F56: 3297.11 | G56: 3214.03 | H56: 2949.06 | I56: 2216.13 | J56: 1559.61 | K56: 1423.46 | L56: 940.57 | M56: 957.88 | N56: 1460.18 | O56: 23603.14
B57: 6025.000 - Utilities - Gas/ Heating Oil | C57: 136.69 | D57: 150 | E57: 151.42 | F57: 170.25 | G57: 150 | H57: 170.7 | I57: 177.95 | J57: 150 | K57: 154.6 | L57: 150 | M57: 179.77 | N57: 182.06 | O57: 1923.44 | V57: *DSCR: (NOI/Debt Service) - A Note
B58: 6050.000 - Utilities - Water/Sewer | C58: 14100.55 | D58: 23713.77 | E58: 23091.06 | F58: 23348.27 | G58: 24552.62 | H58: 30694.62 | I58: 23251.55 | J58: 3292.31 | K58: 14872.98 | L58: 22567.97 | M58: 36103.19 | N58: 6154.38 | O58: 245743.27 | V58: *DSCR: (NOI/Debt Service) - A & B Note
B59: 6055.100 - Utilities-Property Internet | C59: 0 | D59: 0 | E59: 0 | F59: 0 | G59: 0 | H59: 0 | I59: 0 | J59: 0 | K59: 0 | L59: 5520 | M59: 5550 | N59: 5556.95 | O59: 16626.95 | V59: *DSCR: (NOI/Debt Service) - A, B & C Note
B60: 6090.000 - Telephone | C60: 700 | D60: 893.1 | E60: 589.95 | F60: 2589.33 | G60: 3461.45 | H60: 3414.9 | I60: 4491.27 | J60: 4240.6 | K60: 8251.26 | L60: 0 | M60: 0 | N60: 0 | O60: 28631.86
B61: 6090.100 - Telephone Internet | C61: 0 | D61: 0 | E61: 0 | F61: 0 | G61: 0 | H61: 0 | I61: 0 | J61: 0 | K61: 0 | L61: 673.51 | M61: 678.4 | N61: 1101.4 | O61: 2453.31 | V61: *DSCR: (NCF/Debt Service) - A Note
B62: 6100.000 - Waste Disposal | C62: 3768.94 | D62: 4081.7 | E62: 4081.7 | F62: 4081.7 | G62: 4081.7 | H62: 4399.32 | I62: 4081.7 | J62: 4064.08 | K62: 5677.71 | L62: 3581.7 | M62: 4208.47 | N62: 5208.47 | O62: 51317.19 | V62: *DSCR: (NCF/Debt Service) - A & B Note
A63: Utilities | B63: TOTAL UTILITIES | C63: 21849.52 | D63: 31099.61 | E63: 31022.22 | F63: 34173.38 | G63: 48115.03 | H63: 46460.43 | I63: 39239.52 | J63: 16189.2 | K63: 33502.59 | L63: 35368.9 | M63: 50092.75 | N63: 24045.14 | O63: 411158.29 | V63: *DSCR: (NCF/Debt Service) - A, B & C Note
B65: CONTRACT SERVICES
B66: 6110.000 - Contract - Landscape Contract | C66: 7000 | D66: 7000 | E66: 7000 | F66: 7000 | G66: 7000 | H66: 7000 | I66: 7000 | J66: 7000 | K66: 7000 | L66: 7200 | M66: 7200 | N66: 7200 | O66: 84600
B67: 6111.000 - Contract - Other Landscape/Irr | C67: 0 | D67: 2730 | E67: 0 | F67: 0 | G67: 0 | H67: 0 | I67: 989.99 | J67: 0 | K67: 0 | L67: 1175 | M67: 0 | N67: 0 | O67: 4894.99
B68: 6120.000 - Contract - Security Patrol | C68: 1707.5 | D68: 1707 | E68: 1707 | F68: 1782 | G68: 1707 | H68: 1782 | I68: 1707 | J68: 1782 | K68: 1782 | L68: 1794.07 | M68: 1719.07 | N68: 1719.07 | O68: 20895.71
B69: 6121.000 - Contract - Alarm Monitor | C69: 42.95 | D69: 42.95 | E69: 42.95 | F69: 42.95 | G69: 85.9 | H69: 0 | I69: 0 | J69: 0 | K69: 0 | L69: 171.8 | M69: 56.95 | N69: 56.95 | O69: 543.4
B70: 6123.000 - Contract - Key Maintenance | C70: 323.35 | D70: 1049.76 | E70: 646.7 | F70: 323.35 | G70: 323.35 | H70: 323.35 | I70: 323.35 | J70: 345.2 | K70: 316.7 | L70: 533.93 | M70: 475 | N70: 475 | O70: 5459.04
B71: 6140.000 - Contract - Pest Control | C71: 2431.29 | D71: 2051.29 | E71: 3186.29 | F71: 2971.29 | G71: 2301.29 | H71: 2361.29 | I71: 1931.29 | J71: 2681.29 | K71: 2689.78 | L71: 2181.31 | M71: 2246.31 | N71: 2652.62 | O71: 29685.34
B72: 6210.000 - Contract - Repair Services | C72: 177.22 | D72: 88.61 | E72: 88.61 | F72: 88.61 | G72: 177.12 | H72: 88.56 | I72: 88.56 | J72: 88.56 | K72: 88.56 | L72: 90.72 | M72: 90.72 | N72: 181.44 | O72: 1337.29
A73: Repairs and Maintenance | B73: TOTAL CONTRACT SERVICES | C73: 11682.31 | D73: 14669.61 | E73: 12671.55 | F73: 12208.2 | G73: 11594.66 | H73: 11555.2 | I73: 12040.19 | J73: 11897.05 | K73: 11877.04 | L73: 13146.83 | M73: 11788.05 | N73: 12285.08 | O73: 147415.77
B75: REPAIRS & MAINTENANCE
B76: 6220.000 - Equipment Repairs | C76: 368.12 | D76: 0 | E76: 0 | F76: 0 | G76: 0 | H76: 0 | I76: 0 | J76: 0 | K76: 275.83 | L76: 0 | M76: 179.55 | N76: 0 | O76: 823.5
B77: 6230.000 - HVAC Repairs & Supplies | C77: 974.09 | D77: 1153.49 | E77: 894.24 | F77: 2897.73 | G77: 2361.26 | H77: 3608.49 | I77: 3457.88 | J77: 2173.26 | K77: 1092.69 | L77: 732.15 | M77: 1112.11 | N77: 0 | O77: 20457.39
B78: 6240.000 - Pool Supplies | C78: 714.48 | D78: 459.43 | E78: 195.43 | F78: 581.57 | G78: 0 | H78: 400.04 | I78: 316.46 | J78: 2311.21 | K78: 238.26 | L78: 0 | M78: 740.56 | N78: 0 | O78: 5957.44
B79: 6250.000 - Paint Service & Supplies | C79: 875.31 | D79: 4047.52 | E79: 1480.53 | F79: 132.55 | G79: 1137.39 | H79: 2015.04 | I79: 157.23 | J79: 1102.98 | K79: 552.55 | L79: 6345.81 | M79: 4708.25 | N79: 4660.37 | O79: 27215.53
B80: 6251.000 - Resurface | C80: 0 | D80: 1170 | E80: 0 | F80: 0 | G80: 0 | H80: 1400 | I80: 510 | J80: -250 | K80: 100 | L80: 2045 | M80: 1080 | N80: 1380 | O80: 7435
B81: 6252.000 - Gate Repairs | C81: 0 | D81: 0 | E81: 0 | F81: 200 | G81: 0 | H81: 0 | I81: 0 | J81: 0 | K81: 0 | L81: 0 | M81: 0 | N81: 0 | O81: 200
B82: 6260.000 - Plumbing Repairs/Supplies | C82: 3727.57 | D82: 1360.45 | E82: 2950.86 | F82: 2976.28 | G82: 3394.22 | H82: 1499.13 | I82: 2255.61 | J82: 648.34 | K82: 4696.24 | L82: 1878.73 | M82: 3675.81 | N82: 2810.22 | O82: 31873.46
B83: 6270.000 - Electrical Repairs/Supplies | C83: 846.47 | D83: 1741.26 | E83: 1741.46 | F83: 329.83 | G83: 527.29 | H83: 474.18 | I83: 119.17 | J83: 1507.1 | K83: 1446.93 | L83: 784.21 | M83: 281.63 | N83: 93.41 | O83: 9892.94
B84: 6272.000 - Small Tools | C84: 30.48 | D84: 0 | E84: 165.94 | F84: 291.18 | G84: 0 | H84: 0 | I84: 0 | J84: 5.34 | K84: 317.23 | L84: 0 | M84: 63.97 | N84: 0 | O84: 874.14
B85: 6273.000 - Keys & Locks | C85: 0 | D85: 0 | E85: 0 | F85: 0 | G85: 0 | H85: 0 | I85: 0 | J85: 0 | K85: 86.92 | L85: 665.21 | M85: 570.4 | N85: 0 | O85: 1322.53
B86: 6280.000 - Parking Lot Repair/Maintenance | C86: 580.37 | D86: 580.37 | E86: 580.37 | F86: 580.37 | G86: 580.37 | H86: 580.37 | I86: 580.37 | J86: 580.37 | K86: 580.37 | L86: 580.37 | M86: 580.37 | N86: 580.37 | O86: 6964.44
B87: 6310.000 - Building Exterior Repairs | C87: 605 | D87: 0 | E87: 0 | F87: 0 | G87: 0 | H87: 390 | I87: 0 | J87: 0 | K87: 0 | L87: 0 | M87: 0 | N87: 100 | O87: 1095
... B92: 6355.000 - General Interior Repairs | C92: 1841.24 | D92: 1473.97 | E92: 1496.59 | F92: 747.68 | G92: 1586.67 | H92: 1990.13 | I92: 1442.89 | J92: 31.55 | K92: 1818.67 | L92: 623.14 | M92: 407.07 | N92: 302.32 | O92: 13761.92
A93: Repairs and Maintenance | B93: TOTAL REPAIRS & MAINTENANCE | C93: 19607.38 | D93: 15501.75 | E93: 17349.02 | F93: 17276.19 | G93: 17317.65 | H93: 17346.22 | I93: 17307.24 | J93: 14058.82 | K93: 19829.29 | L93: 18389.91 | M93: 19813.36 | N93: 13004.42 | O93: 206801.25
B95: PAYROLL
B96: 6410.000 - Payroll - Administrative | C96: 46462.6 | D96: 47993.69 | E96: 45268.93 | F96: 37058.73 | G96: 46653.15 | H96: 49229.96 | I96: 43971.49 | J96: 45963.82 | K96: 56682.51 | L96: 50647.44 | M96: 44600.46 | N96: 47909.98 | O96: 562442.76
B97: 6410.700 - Payroll Rent Credit | C97: 2493.09 | D97: 2313.8 | E97: 1500 | F97: 636.38 | G97: 645.08 | H97: 640.52 | I97: 640.52 | J97: 966.67 | K97: 1140.52 | L97: 1281.04 | M97: 1176.23 | N97: 2067.55 | O97: 15501.4
B98: 6460.000 - Group Health Insurance | C98: 1395.88 | D98: 1395.88 | E98: 796.05 | F98: 124.09 | G98: 124.09 | H98: 124.09 | I98: 124.09 | J98: 124.09 | K98: 0 | L98: 864.3 | M98: 884.1 | N98: 885.83 | O98: 6842.49
B99: 6470.000 - Worker’s Compensation | C99: 426.29 | D99: 317.64 | E99: 256.54 | F99: 188.53 | G99: 257.59 | H99: 346.55 | I99: 221.69 | J99: 252.09 | K99: 313.92 | L99: 260.45 | M99: 257.2 | N99: 396.68 | O99: 3495.17
B100: 6480.000 - Drug Screening | C100: 0 | D100: 109.02 | E100: 327.06 | F100: 436.08 | G100: 218.04 | H100: 0 | I100: 170.79 | J100: 218.04 | K100: 0 | L100: 0 | M100: 0 | N100: 118.83 | O100: 1597.86
A101: Payroll & Benefits | B101: TOTAL PAYROLL | C101: 50777.86 | D101: 52130.03 | E101: 48148.58 | F101: 38443.81 | G101: 47897.95 | H101: 50341.12 | I101: 45128.58 | J101: 47524.71 | K101: 58136.95 | L101: 53053.23 | M101: 46917.99 | N101: 51378.87 | O101: 589879.68
B103: TAXES AND INSURANCE
A104: Property Insurance | B104: 6510.000 - Insurance | C104: 10949.78 | D104: 10949.78 | E104: 10949.78 | F104: 10905.92 | G104: 10905.48 | H104: 10905.48 | I104: 10905.48 | J104: 10905.48 | K104: 10905.48 | L104: 10905.48 | M104: 10905.48 | N104: 10905.48 | O104: 130999.1
A105: Real Estate Taxes | B105: 6520.000 - Ad Valorem (Property) Taxes | C105: 32298.61 | D105: 32298.61 | E105: 32298.61 | F105: 32298.61 | G105: 32298.61 | H105: 32298.61 | I105: 31173.44 | J105: 31173.44 | K105: 31173.44 | L105: 33618.18 | M105: 33618.18 | N105: 33618.18 | O105: 388166.52
A106: Real Estate Taxes | B106: 6530.000 - Other Taxes | C106: 0 | D106: 900 | E106: 0 | F106: 0 | G106: 0 | H106: 0 | I106: 0 | J106: 0 | K106: 0 | L106: 0 | M106: 0 | N106: 0 | O106: 900
B107: TOTAL TAXES AND INSURANCE | C107: 43248.39 | D107: 44148.39 | E107: 43248.39 | F107: 43204.53 | G107: 43204.09 | H107: 43204.09 | I107: 42078.92 | J107: 42078.92 | K107: 42078.92 | L107: 44523.66 | M107: 44523.66 | N107: 44523.66 | O107: 520065.62
B109: MANAGEMENT FEES
A110: Management Fees | B110: 6540.000 - Management Fees | C110: 18445.33 | D110: 18027.39 | E110: 17761.28 | F110: 17828.4 | G110: 17582.65 | H110: 16544.73 | I110: 17698.29 | J110: 17469.59 | K110: 17468.09 | L110: 17158.33 | M110: 17218.82 | N110: 17555.21 | O110: 210758.11
B111: TOTAL MANAGEMENT FEES | C111: 18445.33 | D111: 18027.39 | E111: 17761.28 | F111: 17828.4 | G111: 17582.65 | H111: 16544.73 | I111: 17698.29 | J111: 17469.59 | K111: 17468.09 | L111: 17158.33 | M111: 17218.82 | N111: 17555.21 | O111: 210758.11
B113: ADMINISTRATIVE EXPENSE
...

Sheet Rent Roll
A1: Knightvest Management LLC - Strada
A2: RENT ROLL DETAIL
A3: 05/15/2026 03:30 PM
A4: As of Date: 03/31/2026
A5: Parameters: Properties: - all subproperties-; Show All Unit Designations or Filter by: ALL; Subjournals: ALL; Sort by: Unit; Report Type: Details + Summary; Exclude Formers?: Yes; Show Unit Rent as: Market Rent; Hide all PII Data?: No
A6: Resh ID | B6: Lease ID | C6: Unit | D6: Floorplan | F6: Unit Designation | G6: SQFT | H6: Unit/Lease Status | I6: Name | J6: Move-In | K6: Move-Out | L6: Lease Start | M6: Lease End | N6: Market Rent | O6: Sub Journal | P6: Required Deposit | Q6: Dep On Hand | R6: Balance | S6: Lease Rent | T6: RENT | U6: SMARTHOME | V6: TRASHREIMB | W6: UTILITY | X6: PESTREIMNB | Y6: RENTERSINS | Z6: CARPORT | AA6: Internet | AB6: PETRENT | AC6: SHRTTERM | AD6: MTOM | AE6: CONC/SPECL | AF6: EMPLCRED | AG6: CARES | AH6: Total Billing
A7: 32095 | B7: 43131 | C7: 1-101 | D7: B2Q | E7: =RIGHT(D7,1) -> Q | F7: N/A | G7: 1076 | H7: Occupied | I7: Jou-Zanfack, Carine | J7: 01/14/2026 | L7: 01/14/2026 | M7: 01/13/2027 | N7: 1659 | O7: RESIDENT | P7: 0 | Q7: 0 | R7: 0 | S7: 1589 | T7: 1589 | U7: 30 | V7: 10 | W7: 5.5 | X7: 5 | Y7: 18 | Z7: 0 | AA7: 0 | AB7: 0 | AC7: 0 | AD7: 0 | AE7: 0 | AF7: 0 | AG7: 0 | AH7: 1657.5 | AJ7: Investment Year | AK7: 0 | AL7: 1 | AO7: MULTIFAMILY CASH FLOW
A8: 31530 | B8: 42707 | C8: 1-102 | D8: B2Q | E8: =RIGHT(D8,1) -> Q | F8: N/A | G8: 1076 | H8: Occupied | I8: Arellano, samantha | J8: 06/13/2025 | L8: 06/13/2025 | M8: 06/11/2026 | N8: 1659 | O8: RESIDENT | P8: 0 | Q8: 0 | R8: 62.69 | S8: 1689 | T8: 1689 | U8: 30 | V8: 10 | W8: 5.5 | X8: 5 | Y8: 18 | Z8: 0 | AA8: 0 | AB8: 0 | AC8: 0 | AD8: 0 | AE8: 0 | AF8: 0 | AG8: 0 | AH8: 1757.5 | AJ8: Year Ending | AK8: In Place | AL8: 46172 | AO8: Strada
A9: 31601 | B9: 42858 | C9: 1-103 | D9: B2G | E9: =RIGHT(D9,1) -> G | F9: N/A | G9: 1076 | H9: Occupied | I9: Walker, Darion | J9: 08/01/2025 | L9: 08/01/2025 | M9: 08/03/2026 | N9: 1609 | O9: RESIDENT | P9: 0 | Q9: 0 | R9: 0 | S9: 1639 | T9: 1639 | U9: 30 | V9: 10 | W9: 5.5 | X9: 5 | Y9: 18 | Z9: 30 | AA9: 0 | AB9: 0 | AC9: 0 | AD9: 0 | AE9: 0 | AF9: 0 | AG9: 0 | AH9: 1737.5 | AJ9: Annual Base Rent | AK9: =+AP15 -> 8474519 | AL9: =+AQ15 -> 8390792.8 | AO9: Investment Year | AP9: IRE In-Place NOI Definition | AQ9: 1 | AR9: 2 | AS9: 3 | AT9: 4 | AU9: 5 | AV9: 6 | AW9: 7 | AX9: 8 | AY9: 9 | AZ9: 10
A10: 768 | B10: 42766 | C10: 1-104 | D10: B2G | E10: =RIGHT(D10,1) -> G | F10: N/A | G10: 1076 | H10: Occupied | I10: Cesar, Maria | J10: 06/01/2022 | L10: 07/29/2025 | M10: 07/27/2026 | N10: 1609 | O10: RESIDENT | P10: 0 | Q10: 0 | R10: 0 | S10: 1730 | T10: 1730 | U10: 30 | V10: 10 | W10: 5.5 | X10: 5 | Y10: 18 | Z10: 15 | AA10: 0 | AB10: 0 | AC10: 0 | AD10: 0 | AE10: 0 | AF10: 0 | AG10: 0 | AH10: 1813.5 | AJ10: Monthly Base Rent | AK10: =AK9/12 -> 706209.91 | AL10: =AL9/12 -> 699232.73 | AO10: Year Ending | AQ10: 46173 | AR10: 46538 | AS10: 46904 | AT10: 47269 | AU10: 47634 | AV10: 47999 | AW10: 48365 | AX10: 48730 | AY10: 49095 | AZ10: 49460
A11: 31930 | B11: 42826 | C11: 1-105 | D11: B2G | E11: =RIGHT(D11,1) -> G | F11: N/A | G11: 1076 | H11: Occupied | I11: Wendy, FNU | J11: 07/11/2025 | L11: 07/11/2025 | M11: 07/10/2026 | N11: 1609 | O11: RESIDENT | P11: 0 | Q11: 0 | R11: -46.69 | S11: 1589 | T11: 1589 | U11: 30 | V11: 10 | W11: 5.5 | X11: 5 | Y11: 18 | Z11: 30 | AA11: 0 | AB11: 0 | AC11: 0 | AD11: 0 | AE11: 0 | AF11: 0 | AG11: 0 | AH11: 1687.5 | AJ11: % Occ. | AK11: 1 | AL11: 1
A12: 31990 | B12: 42926 | C12: 1-106 | D12: B2Q | E12: =RIGHT(D12,1) -> Q | F12: N/A | G12: 1076 | H12: Occupied | I12: Belyeu, Akelya | J12: 09/18/2025 | L12: 09/18/2025 | M12: 09/17/2026 | N12: 1659 | O12: RESIDENT | P12: 0 | Q12: 0 | R12: 0 | S12: 1689 | T12: 1689 | U12: 30 | V12: 10 | W12: 5.5 | X12: 5 | Y12: 0 | Z12: 30 | AA12: 0 | AB12: 0 | AC12: 0 | AD12: 0 | AE12: 0 | AF12: 0 | AG12: 0 | AH12: 1769.5 | AJ12: Rent/Occ Unit | AK12: =+AK10/(495*AK11) -> 1426.6867 | AL12: =+AL10/(495*AL11) -> 1412.5914 | AO12: INCOME | AP12: $ Gross
A13: 31995 | B13: 42933 | C13: 1-107 | D13: B2Q | E13: =RIGHT(D13,1) -> Q | F13: N/A | G13: 1076 | H13: Occupied | I13: Rodriguez, David | J13: 09/19/2025 | L13: 09/19/2025 | M13: 09/18/2026 | N13: 1659 | O13: RESIDENT | P13: 0 | Q13: 0 | R13: 0 | S13: 1689 | T13: 1689 | U13: 30 | V13: 10 | W13: 5.5 | X13: 5 | Y13: 18 | Z13: 0 | AA13: 0 | AB13: 0 | AC13: 0 | AD13: 0 | AE13: 0 | AF13: 0 | AG13: 0 | AH13: 1757.5 | AJ13: Multiplier | AK13: 0.41666667 | AL13: =1-AK13 -> 0.58333333 | AO13: Potential Rental Revenue | AP13: 8474519 | AQ13: 8357667.1 | AR13: 8579313.5 | AS13: 8960894.7 | AT13: 9318313.2 | AU13: 9674923.9 | AV13: 9995970.5 | AW13: 10295850 | AX13: 10604725 | AY13: 10922867 | AZ13: 11250553
A14: 31552 | B14: 42815 | C14: 1-108 | D14: B2Q | E14: =RIGHT(D14,1) -> Q | F14: N/A | G14: 1076 | H14: Occupied | I14: Snider, Lillian | J14: 08/24/2024 | L14: 08/23/2025 | M14: 08/24/2026 | N14: 1629 | O14: RESIDENT | P14: 0 | Q14: 0 | R14: 0 | S14: 1764 | T14: 1764 | U14: 30 | V14: 10 | W14: 5.5 | X14: 5 | Y14: 18 | Z14: 15 | AA14: 0 | AB14: 0 | AC14: 0 | AD14: 0 | AE14: 0 | AF14: 0 | AG14: 0 | AH14: 1847.5 | AJ14: Average UW Rent | AL14: =SUMPRODUCT(AK13:AL13,AK12:AL12) -> 1418.4644 | AO14: Loss To Lease | AP14: 0 | AQ14: 33125.696 | AR14: -103648.36 | AS14: -153090.98 | AT14: -156337.08 | AU14: -147550.63 | AV14: -121551.92 | AW14: -111673.93 | AX14: -110350.84 | AY14: -108988.06 | AZ14: -107584.39
A15: 31948 | B15: 42909 | C15: 1-109 | D15: A3Q | E15: =RIGHT(D15,1) -> Q | F15: N/A | G15: 825 | H15: Occupied | I15: Contreras, Brooklynn | J15: 08/14/2025 | L15: 08/14/2025 | M15: 08/13/2026 | N15: 1419 | O15: RESIDENT | P15: 0 | Q15: 0 | R15: 0 | S15: 1369 | T15: 1369 | U15: 30 | V15: 10 | W15: 5.5 | X15: 5 | Y15: 18 | Z15: 15 | AA15: 0 | AB15: 0 | AC15: 0 | AD15: 0 | AE15: 0 | AF15: 0 | AG15: 0 | AH15: 1452.5 | AJ15: In-Place Rent | AL15: =AVERAGEIFS(T7:T501,T7:T501,">0") -> 1403.4336 | AO15: Scheduled Base Rental Revenue | AP15: 8474519 | AQ15: 8390792.8 | AR15: 8475665.2 | AS15: 8807803.7 | AT15: 9161976.1 | AU15: 9527373.3 | AV15: 9874418.6 | AW15: 10184176 | AX15: 10494374 | AY15: 10813879 | AZ15: 11142968
A16: 11048 | B16: 42717 | C16: 1-110 | D16: A3G | E16: =RIGHT(D16,1) -> G | F16: N/A | G16: 825 | H16: Occupied | I16: Tapia, Angela | J16: 04/12/2023 | L16: 05/13/2025 | M16: 05/12/2026 | N16: 1379 | O16: RESIDENT | P16: 0 | Q16: 0 | R16: -551.92 | S16: 1430 | T16: 1430 | U16: 30 | V16: 10 | W16: 5.5 | X16: 5 | Y16: 18 | Z16: 0 | AA16: 0 | AB16: 0 | AC16: 0 | AD16: 0 | AE16: 0 | AF16: 0 | AG16: 0 | AH16: 1498.5 | AJ16: Market Rent | AL16: =+AVERAGE(N7:N501) -> 1358.6343 | AO16: Other Income | AP16: 1242919.2 | AQ16: 1220508 | AR16: 1503810.3 | AS16: 1640643.9 | AT16: 1679333.5 | AU16: 1718943.7 | AV16: 1759496.8 | AW16: 1801015.2 | AX16: 1843522.3 | AY16: 1887041.6 | AZ16: 1931597.6
A17: 32066 | B17: 43094 | C17: 1-111 | D17: A3G | E17: =RIGHT(D17,1) -> G | F17: N/A | G17: 825 | H17: Occupied | I17: Preis, Taryn | J17: 12/10/2025 | L17: 12/10/2025 | M17: 03/09/2027 | N17: 1379 | O17: RESIDENT | P17: 0 | Q17: 0 | R17: 0 | S17: 1309 | T17: 1309 | U17: 30 | V17: 10 | W17: 5 | X17: 5 | Y17: 0 | Z17: 15 | AA17: 0 | AB17: 35 | AC17: 0 | AD17: 0 | AE17: 0 | AF17: 0 | AG17: 0 | AH17: 1409 | AL17: =(AL15/AL14)-1 -> -0.010596585 | AO17: Potential Gross Income | AP17: 9717438.2 | AQ17: 9611300.8 | AR17: 9979475.5 | AS17: 10448448 | AT17: 10841310 | AU17: 11246317 | AV17: 11633915 | AW17: 11985191 | AX17: 12337897 | AY17: 12700920 | AZ17: 13074566
A18: 31607 | B18: 42856 | C18: 1-112 | D18: A3Q | E18: =RIGHT(D18,1) -> Q | F18: N/A | G18: 825 | H18: Occupied | I18: Davis, Bailey | J18: 08/09/2024 | L18: 08/09/2025 | M18: 08/10/2026 | N18: 1419 | O18: RESIDENT | P18: 0 | Q18: 0 | R18: 0 | S18: 1479 | T18: 1479 | U18: 30 | V18: 10 | W18: 5.5 | X18: 5 | Y18: 18 | Z18: 0 | AA18: 0 | AB18: 0 | AC18: 0 | AD18: 0 | AE18: 0 | AF18: 0 | AG18: 0 | AH18: 1547.5 | AL18: =(AL15/AL16)-1 -> 0.032973705 | AO18: Minus: Vacancy | AP18: -499996.62 | AQ18: -461493.6 | AR18: -466161.58 | AS18: -484429.2 | AT18: -503908.69 | AU18: -524005.53 | AV18: -543093.02 | AW18: -560129.66 | AX18: -577190.58 | AY18: -594763.33 | AZ18: -612863.26
A19: 11370 | B19: 43152 | C19: 1-113 | D19: A3Q | E19: =RIGHT(D19,1) -> Q | F19: N/A | G19: 825 | H19: Occupied | I19: Rossell, Shanna | J19: 01/26/2024 | L19: 01/24/2026 | M19: 01/25/2027 | N19: 1419 | O19: RESIDENT | P19: 0 | Q19: 0 | R19: 0 | S19: 1379 | T19: 1379 | U19: 30 | V19: 10 | W19: 5.5 | X19: 5 | Y19: 0 | Z19: 15 | AA19: 0 | AB19: 0 | AC19: 0 | AD19: 0 | AE19: 0 | AF19: 0 | AG19: 0 | AH19: 1444.5 | AO19: Minus: Credit Loss | AP19: -114839.31 | AQ19: -125861.89 | AR19: -105945.81 | AS19: -88078.037 | AT19: -91619.761 | AU19: -95273.733 | AV19: -98744.186 | AW19: -101841.76 | AX19: -104943.74 | AY19: -108138.79 | AZ19: -111429.68
A20: 32055 | B20: 43069 | C20: 1-114 | D20: A3F | E20: =RIGHT(D20,1) -> F | F20: N/A | G20: 825 | H20: Occupied | I20: Engelman, Jessica | J20: 12/02/2025 | L20: 12/02/2025 | M20: 12/01/2026 | N20: 1309 | O20: RESIDENT | P20: 0 | Q20: 0 | R20: 0 | S20: 1089 | T20: 1089 | U20: 30 | V20: 10 | W20: 5.5 | X20: 5 | Y20: 18 | Z20: 0 | AA20: 0 | AB20: 0 | AC20: 0 | AD20: 0 | AE20: 0 | AF20: 0 | AG20: 0 | AH20: 1157.5 | AO20: Minus: Model Unit | AP20: 0 | AQ20: 0 | AR20: 0 | AS20: 0 | AT20: 0 | AU20: 0 | AV20: 0 | AW20: 0 | AX20: 0 | AY20: 0 | AZ20: 0
A21: 58 | B21: 42648 | C21: 1-115 | D21: A3F | E21: =RIGHT(D21,1) -> F | F21: N/A | G21: 825 | H21: Occupied-NTV | I21: Kupka, William | J21: 09/18/2015 | K21: 04/27/2026 | L21: 03/18/2025 | M21: 03/17/2026 | N21: 1309 | O21: RESIDENT | P21: 0 | Q21: 250 | R21: -391 | S21: 1379 | T21: 1379 | U21: 30 | V21: 10 | W21: 5.5 | X21: 5 | Y21: 18 | Z21: 0 | AA21: 0 | AB21: 70 | AC21: 0 | AD21: 0 | AE21: 0 | AF21: 0 | AG21: 0 | AH21: 1517.5 | AO21: Minus: Concessions Initial Lease Up | AP21: -117055.64 | AQ21: -47462.588 | AR21: -36695.348 | AS21: -2996.4319 | AT21: 0 | AU21: 0 | AV21: 0 | AW21: 0 | AX21: 0 | AY21: 0 | AZ21: 0
A22: 31967 | B22: 42895 | C22: 1-116 | D22: A3Q | E22: =RIGHT(D22,1) -> Q | F22: N/A | G22: 825 | H22: Occupied | I22: Ramirez, Guillermo | J22: 08/28/2025 | L22: 08/28/2025 | M22: 08/27/2026 | N22: 1419 | O22: RESIDENT | P22: 0 | Q22: 0 | R22: 0 | S22: 1319 | T22: 1319 | U22: 30 | V22: 10 | W22: 5.5 | X22: 5 | Y22: 18 | Z22: 0 | AA22: 0 | AB22: 0 | AC22: 0 | AD22: 0 | AE22: 0 | AF22: 0 | AG22: 0 | AH22: 1387.5 | AJ22: 3Q 2025 Concessions | AO22: Minus: Concessions Ongoing | AQ22: -349333.62 | AR22: -177978.04 | AS22: -94639.172 | AT22: 0 | AU22: 0 | AV22: 0 | AW22: 0 | AX22: 0 | AY22: 0 | AZ22: 0
A23: 31935 | B23: 42834 | C23: 1-117 | D23: A1G | E23: =RIGHT(D23,1) -> G | F23: N/A | G23: 600 | H23: Occupied | I23: Tuttle, Gianah | J23: 07/14/2025 | L23: 07/14/2025 | M23: 07/13/2026 | N23: 1269 | O23: RESIDENT | P23: 0 | Q23: 0 | R23: 0 | S23: 1219 | T23: 1219 | U23: 30 | V23: 10 | W23: 5.5 | X23: 5 | Y23: 18 | Z23: 15 | AA23: 0 | AB23: 0 | AC23: 0 | AD23: 0 | AE23: 0 | AF23: 0 | AG23: 0 | AH23: 1302.5 | AJ23: Oct | AK23: 0 | AO23: Effective Gross Income | AP23: 8985546.7 | AQ23: 8627149.1 | AR23: 9192694.7 | AS23: 9778304.8 | AT23: 10245781 | AU23: 10627038 | AV23: 10992078 | AW23: 11323219 | AX23: 11655762 | AY23: 11998018 | AZ23: 12350273
A24: 31749 | B24: 43029 | C24: 1-118 | D24: A1F | E24: =RIGHT(D24,1) -> F | F24: N/A | G24: 600 | H24: Occupied | I24: Igwee, Lydia | J24: 12/28/2024 | L24: 12/27/2025 | M24: 12/28/2026 | N24: 1199 | O24: RESIDENT | P24: 0 | Q24: 0 | R24: -1448.59 | S24: 1228 | T24: 1228 | U24: 30 | V24: 10 | W24: 5.5 | X24: 5 | Y24: 18 | Z24: 15 | AA24: 0 | AB24: 0 | AC24: 0 | AD24: 0 | AE24: 0 | AF24: 0 | AG24: 0 | AH24: 1311.5 | AJ24: Nov | AK24: 0
A25: 31896 | B25: 42749 | C25: 1-119 | D25: A1F | E25: =RIGHT(D25,1) -> F | F25: N/A | G25: 600 | H25: Occupied | I25: Cochran, Matthew | J25: 07/01/2025 | L25: 07/01/2025 | M25: 07/01/2026 | N25: 1169 | O25: RESIDENT | P25: 0 | Q25: 0 | R25: 0 | S25: 1229 | T25: 1229 | U25: 30 | V25: 10 | W25: 5.5 | X25: 5 | Y25: 18 | Z25: 0 | AA25: 0 | AB25: 0 | AC25: 0 | AD25: 0 | AE25: 0 | AF25: 0 | AG25: 0 | AH25: 1297.5 | AJ25: Dec | AK25: 0 | AO25: OPERATING EXPENSES | AP25: $ Gross
A26: 31834 | B26: 43211 | C26: 1-120 | D26: A1Q | E26: =RIGHT(D26,1) -> Q | F26: N/A | G26: 600 | H26: Occupied | I26: Biggers, Jessica | J26: 02/21/2025 | L26: 02/21/2026 | M26: 03/01/2027 | N26: 1309 | O26: RESIDENT | P26: 0 | Q26: 0 | R26: 0 | S26: 1299 | T26: 1299 | U26: 30 | V26: 10 | W26: 5.5 | X26: 5 | Y26: 18 | Z26: 0 | AA26: 0 | AB26: 35 | AC26: 0 | AD26: 0 | AE26: 0 | AF26: 0 | AG26: 0 | AH26: 1402.5 | AJ26: Quarterly | AK26: =+SUM(AK23:AK25) -> 0 | AO26: Payroll | AP26: 574480.84 | AQ26: 569345.6 | AR26: 586425.97 | AS26: 604018.75 | AT26: 622139.31 | AU26: 640803.49 | AV26: 660027.59 | AW26: 679828.42 | AX26: 700223.27 | AY26: 721229.97 | AZ26: 742866.87
A27: 83 | B27: 42828 | C27: 1-121 | D27: A1 | E27: =RIGHT(D27,1) -> 1 | F27: N/A | G27: 600 | H27: Occupied | I27: Kane, Alan | J27: 07/06/2017 | L27: 09/03/2025 | M27: 09/02/2026 | N27: 1299 | O27: RESIDENT | P27: 0 | Q27: 0 | R27: -1431.44 | S27: 1326 | T27: 1326 | U27: 30 | V27: 10 | W27: 5.5 | X27: 5 | Y27: 18 | Z27: 0 | AA27: 0 | AB27: 0 | AC27: 0 | AD27: 0 | AE27: 0 | AF27: 0 | AG27: 0 | AH27: 1394.5 | AJ27: Yearly | AK27: =+AK26*4 -> 0 | AO27: Employee Units | AP27: 10605.92 | AQ27: 10924.098 | AR27: 11251.821 | AS27: 11589.375 | AT27: 11937.056 | AU27: 12295.168 | AV27: 12664.023 | AW27: 13043.944 | AX27: 13435.262 | AY27: 13838.32 | AZ27: 14253.47
A28: 31660 | B28: 42989 | C28: 1-122 | D28: A1F | E28: =RIGHT(D28,1) -> F | F28: N/A | G28: 600 | H28: Occupied | I28: Dossani, Omer | J28: 10/04/2024 | L28: 10/04/2025 | M28: 10/05/2026 | N28: 1169 | O28: RESIDENT | P28: 0 | Q28: 0 | R28: 0 | S28: 1199 | T28: 1199 | U28: 30 | V28: 10 | W28: 5.5 | X28: 5 | Y28: 18 | Z28: 0 | AA28: 0 | AB28: 0 | AC28: 0 | AD28: 0 | AE28: 0 | AF28: 0 | AG28: 0 | AH28: 1267.5 | AO28: Marketing | AP28: 91494.43 | AQ28: 91575 | AR28: 94322.25 | AS28: 97151.917 | AT28: 100066.48 | AU28: 103068.47 | AV28: 106160.52 | AW28: 109345.34 | AX28: 112625.7 | AY28: 116004.47 | AZ28: 119484.6
A29: 0 | B29: 0 | C29: 1-123 | D29: A1Q | E29: =RIGHT(D29,1) -> Q | F29: N/A | G29: 600 | H29: Vacant | I29: VACANT | N29: 1309 | P29: 0 | Q29: 0 | R29: 0 | S29: 0 | T29: 0 | U29: 0 | V29: 0 | W29: 0 | X29: 0 | Y29: 0 | Z29: 0 | AA29: 0 | AB29: 0 | AC29: 0 | AD29: 0 | AE29: 0 | AF29: 0 | AG29: 0 | AH29: 0 | AJ29: 3Q 2025 Concessions | AO29: General & Admin. | AP29: 207771.55 | AQ29: 210375 | AR29: 216686.25 | AS29: 223186.84 | AT29: 229882.44 | AU29: 236778.92 | AV29: 243882.28 | AW29: 251198.75 | AX29: 258734.71 | AY29: 266496.76 | AZ29: 274491.66
A30: 0 | B30: 0 | C30: 1-124 | D30: A1G | E30: =RIGHT(D30,1) -> G | F30: N/A | G30: 600 | H30: Vacant-Leased | I30: VACANT | N30: 1099 | P30: 0 | Q30: 0 | R30: 0 | S30: 0 | T30: 0 | U30: 0 | V30: 0 | W30: 0 | X30: 0 | Y30: 0 | Z30: 0 | AA30: 0 | AB30: 0 | AC30: 0 | AD30: 0 | AE30: 0 | AF30: 0 | AG30: 0 | AH30: 0 | AJ30: July | AK30: 0 | AO30: Managed WiFi | AP30: 0 | AQ30: 44550 | AR30: 183546 | AS30: 189052.38 | AT30: 194723.95 | AU30: 200565.67 | AV30: 206582.64 | AW30: 212780.12 | AX30: 219163.52 | AY30: 225738.43 | AZ30: 232510.58
A31: 32161 | B31: 43264 | C31: 1-124 | D31: A1G | E31: =RIGHT(D31,1) -> G | F31: N/A | G31: 600 | H31: Applicant | I31: Gargiulo, Timothy | J31: 04/02/2026 | L31: 04/02/2026 | M31: 04/01/2027 | N31: 0 | O31: RESIDENT | P31: 0 | Q31: 0 | R31: 250 | S31: 1099 | T31: 1099 | U31: 30 | V31: 10 | W31: 5.5 | X31: 5 | Y31: 18 | Z31: 15 | AA31: 70 | AB31: 0 | AC31: 0 | AD31: 0 | AE31: 0 | AF31: 0 | AG31: 0 | AH31: 1252.5 | AJ31: August | AK31: 0 | AO31: Landscaping/Grounds | AP31: 113265.91 | AQ31: 111375 | AR31: 114716.25 | AS31: 118157.74 | AT31: 121702.47 | AU31: 125353.54 | AV31: 129114.15 | AW31: 132987.57 | AX31: 136977.2 | AY31: 141086.52 | AZ31: 145319.11
A32: 761 | B32: 42750 | C32: 1-125 | D32: B2G | E32: =RIGHT(D32,1) -> G | F32: N/A | G32: 1076 | H32: Occupied | I32: Moran, Keegan | J32: 05/27/2022 | L32: 07/08/2025 | M32: 07/06/2026 | N32: 1609 | O32: RESIDENT | P32: 0 | Q32: 0 | R32: 0 | S32: 1730 | T32: 1730 | U32: 30 | V32: 10 | W32: 5.5 | X32: 5 | Y32: 18 | Z32: 0 | AA32: 0 | AB32: 35 | AC32: 0 | AD32: 0 | AE32: 0 | AF32: 0 | AG32: 0 | AH32: 1833.5 | AJ32: September | AK32: 0 | AO32: Make-ready | AP32: 0 | AQ32: 0 | AR32: 0 | AS32: 0 | AT32: 0 | AU32: 0 | AV32: 0 | AW32: 0 | AX32: 0 | AY32: 0 | AZ32: 0
A33: 31927 | B33: 42817 | C33: 1-126 | D33: B2F | E33: =RIGHT(D33,1) -> F | F33: N/A | G33: 1076 | H33: Occupied | I33: Javier, Ejay | J33: 07/07/2025 | L33: 07/07/2025 | M33: 07/06/2026 | N33: 1539 | O33: RESIDENT | P33: 0 | Q33: 0 | R33: -863 | S33: 1569 | T33: 1569 | U33: 30 | V33: 10 | W33: 5.5 | X33: 5 | Y33: 18 | Z33: 30 | AA33: 0 | AB33: 0 | AC33: 0 | AD33: 0 | AE33: 0 | AF33: 0 | AG33: 0 | AH33: 1667.5 | AJ33: Quarterly | AK33: =+SUM(AK30:AK32) -> 0 | AO33: Repairs & Maint. | AP33: 232268.57 | AQ33: 232268.57 | AR33: 239236.63 | AS33: 246413.73 | AT33: 253806.14 | AU33: 261420.32 | AV33: 269262.93 | AW33: 277340.82 | AX33: 285661.04 | AY33: 294230.88 | AZ33: 303057.8
A34: 31892 | B34: 42741 | C34: 1-127 | D34: B2F | E34: =RIGHT(D34,1) -> F | F34: N/A | G34: 1076 | H34: Occupied-NTV | I34: Ramirez, Alejandra | J34: 05/12/2025 | K34: 05/11/2026 | L34: 05/12/2025 | M34: 05/11/2026 | N34: 1539 | O34: RESIDENT | P34: 0 | Q34: 0 | R34: 0 | S34: 1569 | T34: 1569 | U34: 30 | V34: 10 | W34: 5.5 | X34: 5 | Y34: 18 | Z34: 30 | AA34: 0 | AB34: 0 | AC34: 0 | AD34: 0 | AE34: 0 | AF34: 0 | AG34: 0 | AH34: 1667.5 | AJ34: Yearly | AK34: =+AK33*4 -> 0 | AO34: Trash Expense | AP34: 42871.94 | AQ34: 45045 | AR34: 46396.35 | AS34: 47788.24 | AT34: 49221.888 | AU34: 50698.544 | AV34: 52219.501 | AW34: 53786.086 | AX34: 55399.668 | AY34: 57061.658 | AZ34: 58773.508
A35: 154 | B35: 42869 | C35: 1-128 | D35: B2 | E35: =RIGHT(D35,1) -> 2 | F35: N/A | G35: 1076 | H35: Occupied | I35: Coleman, Quinsey | J35: 08/06/2019 | L35: 10/02/2025 | M35: 10/05/2026 | N35: 1609 | O35: RESIDENT | P35: 0 | Q35: 0 | R35: 25 | S35: 1744 | T35: 1744 | U35: 30 | V35: 10 | W35: 5.5 | X35: 5 | Y35: 18 | Z35: 45 | AA35: 0 | AB35: 0 | AC35: 0 | AD35: 0 | AE35: 0 | AF35: 0 | AG35: 0 | AH35: 1857.5 | AO35: Security/Life Safety | AP35: 20740.1 | AQ35: 25245 | AR35: 26002.35 | AS35: 26782.42 | AT35: 27585.893 | AU35: 28413.47 | AV35: 29265.874 | AW35: 30143.85 | AX35: 31048.166 | AY35: 31979.611 | AZ35: 32938.999
A36: 10977 | B36: 42680 | C36: 1-129 | D36: B2G | E36: =RIGHT(D36,1) -> G | F36: N/A | G36: 1076 | H36: Occupied | I36: Harrell Jr, Calvin | J36: 02/21/2023 | L36: 04/03/2025 | M36: 04/02/2026 | N36: 1579 | O36: RESIDENT | P36: 0 | Q36: 0 | R36: 25 | S36: 1652 | T36: 1652 | U36: 30 | V36: 10 | W36: 5.5 | X36: 5 | Y36: 18 | Z36: 30 | AA36: 0 | AB36: 0 | AC36: 0 | AD36: 0 | AE36: 0 | AF36: 0 | AG36: 0 | AH36: 1750.5 | AO36: Utilities | AP36: 287016.97 | AQ36: 294525 | AR36: 303360.75 | AS36: 312461.57 | AT36: 321835.42 | AU36: 331490.48 | AV36: 341435.2 | AW36: 351678.25 | AX36: 362228.6 | AY36: 373095.46 | AZ36: 384288.32
A37: 0 | B37: 0 | C37: 1-130 | D37: B2Q | E37: =RIGHT(D37,1) -> Q | F37: N/A | G37: 1076 | H37: Vacant | I37: VACANT | N37: 1659 | P37: 0 | Q37: 0 | R37: 0 | S37: 0 | T37: 0 | U37: 0 | V37: 0 | W37: 0 | X37: 0 | Y37: 0 | Z37: 0 | AA37: 0 | AB37: 0 | AC37: 0 | AD37: 0 | AE37: 0 | AF37: 0 | AG37: 0 | AH37: 0 | AO37: Insurance | AP37: 139580.38 | AQ37: 139580.38 | AR37: 132601.36 | AS37: 135253.38 | AT37: 139310.99 | AU37: 143490.32 | AV37: 147795.03 | AW37: 152228.88 | AX37: 156795.74 | AY37: 161499.61 | AZ37: 166344.6
A38: 31973 | B38: 42904 | C38: 1-131 | D38: B2F | E38: =RIGHT(D38,1) -> F | F38: N/A | G38: 1076 | H38: Occupied | I38: Chavez Mora, Jeremy | J38: 09/06/2025 | L38: 09/06/2025 | M38: 09/04/2026 | N38: 1539 | O38: RESIDENT | P38: 0 | Q38: 0 | R38: 0 | S38: 1569 | T38: 1569 | U38: 30 | V38: 10 | W38: 5.5 | X38: 5 | Y38: 18 | Z38: 0 | AA38: 0 | AB38: 0 | AC38: 0 | AD38: 0 | AE38: 0 | AF38: 0 | AG38: 0 | AH38: 1637.5 | AO38: Replacement Reserves | AP38: 123750 | AQ38: 123750 | AR38: 123750 | AS38: 123750 | AT38: 123750 | AU38: 123750 | AV38: 123750 | AW38: 123750 | AX38: 123750 | AY38: 123750 | AZ38: 123750
A39: 0 | B39: 0 | C39: 1-132 | D39: B2G | E39: =RIGHT(D39,1) -> G | F39: N/A | G39: 1076 | H39: Vacant | I39: VACANT | N39: 1609 | P39: 0 | Q39: 0 | R39: 0 | S39: 0 | T39: 0 | U39: 0 | V39: 0 | W39: 0 | X39: 0 | Y39: 0 | Z39: 0 | AA39: 0 | AB39: 0 | AC39: 0 | AD39: 0 | AE39: 0 | AF39: 0 | AG39: 0 | AH39: 0 | AO39: Misc #2 | AP39: 0 | AQ39: 0 | AR39: 0 | AS39: 0 | AT39: 0 | AU39: 0 | AV39: 0 | AW39: 0 | AX39: 0 | AY39: 0 | AZ39: 0
A40: 11324 | B40: 43016 | C40: 1-133 | D40: A2Q | E40: =RIGHT(D40,1) -> Q | F40: N/A | G40: 700 | H40: Occupied | I40: Teller, Damian | J40: 12/26/2023 | L40: 12/27/2025 | M40: 12/28/2026 | N40: 1359 | O40: RESIDENT | P40: 0 | Q40: 0 | R40: 0 | S40: 1439 | T40: 1439 | U40: 30 | V40: 10 | W40: 5.5 | X40: 5 | Y40: 18 | Z40: 15 | AA40: 0 | AB40: 0 | AC40: 0 | AD40: 0 | AE40: 0 | AF40: 0 | AG40: 0 | AH40: 1522.5 | AO40: RE Taxes | AP40: 387583 | AQ40: 387583 | AR40: 406962.15 | AS40: 427310.26 | AT40: 448675.77 | AU40: 471109.56 | AV40: 494665.04 | AW40: 519398.29 | AX40: 545368.2 | AY40: 572636.61 | AZ40: 601268.44
A41: 32107 | B41: 43147 | C41: 1-134 | D41: A2Q | E41: =RIGHT(D41,1) -> Q | F41: N/A | G41: 700 | H41: Occupied | I41: Murphey, Hunter | J41: 01/23/2026 | L41: 01/23/2026 | M41: 01/22/2027 | N41: 1359 | O41: RESIDENT | P41: 0 | Q41: 0 | R41: 0 | S41: 1289 | T41: 1289 | U41: 30 | V41: 10 | W41: 5.5 | X41: 5 | Y41: 18 | Z41: 15 | AA41: 0 | AB41: 35 | AC41: 0 | AD41: 0 | AE41: 0 | AF41: 0 | AG41: 0 | AH41: 1407.5 | AO41: Management Fee | AP41: 314494.13 | AQ41: 301950.22 | AR41: 321744.31 | AS41: 342240.67 | AT41: 358602.34 | AU41: 371946.32 | AV41: 384722.73 | AW41: 396312.68 | AX41: 407951.68 | AY41: 419930.64 | AZ41: 432259.56
A42: 32083 | B42: 43115 | C42: 1-135 | D42: A2Q | E42: =RIGHT(D42,1) -> Q | F42: N/A | G42: 700 | H42: Occupied | I42: Esquerra, Tyson | J42: 12/26/2025 | L42: 12/26/2025 | M42: 01/26/2027 | N42: 1329 | O42: RESIDENT | P42: 0 | Q42: 0 | R42: 2.42 | S42: 1289 | T42: 1289 | U42: 30 | V42: 10 | W42: 5.5 | X42: 5 | Y42: 18 | Z42: 15 | AA42: 0 | AB42: 0 | AC42: 0 | AD42: 0 | AE42: 0 | AF42: 0 | AG42: 0 | AH42: 1372.5 | AO42: Total Operating Expenses | AP42: 2545923.7 | AQ42: 2588091.9 | AR42: 2807002.4 | AS42: 2905157.3 | AT42: 3003240.1 | AU42: 3101184.3 | AV42: 3201547.5 | AW42: 3303823 | AX42: 3409362.8 | AY42: 3518578.9 | AZ42: 3631607.5
A43: 319 | B43: 43066 | C43: 1-137 | D43: A2 | E43: =RIGHT(D43,1) -> 2 | F43: N/A | G43: 700 | H43: Occupied | I43: Corrigan, Kevin | J43: 12/12/2020 | L43: 01/14/2026 | M43: 01/18/2027 | N43: 1319 | O43: RESIDENT | P43: 0 | Q43: 0 | R43: 0 | S43: 1329 | T43: 1329 | U43: 30 | V43: 10 | W43: 5.5 | X43: 5 | Y43: 0 | Z43: 15 | AA43: 0 | AB43: 0 | AC43: 0 | AD43: 0 | AE43: 0 | AF43: 0 | AG43: 0 | AH43: 1394.5 | AO43: Operating Expenses % EGR | AQ43: 0.29999387 | AR43: 0.30535143 | AS43: 0.29710234 | AT43: 0.29311969 | AU43: 0.2918202 | AV43: 0.29125953 | AW43: 0.29177417 | AX43: 0.29250449 | AY43: 0.29326334 | AZ43: 0.29405079
A44: 31526 | B44: 42824 | C44: 1-138 | D44: A2F | E44: =RIGHT(D44,1) -> F | F44: N/A | G44: 700 | H44: Occupied | I44: Riley, Kody | J44: 07/27/2024 | L44: 08/27/2025 | M44: 08/24/2026 | N44: 1249 | O44: RESIDENT | P44: 0 | Q44: 0 | R44: -6.46 | S44: 1309 | T44: 1309 | U44: 30 | V44: 10 | W44: 5.5 | X44: 5 | Y44: 18 | Z44: 0 | AA44: 0 | AB44: 0 | AC44: 0 | AD44: 0 | AE44: 0 | AF44: 0 | AG44: 0 | AH44: 1377.5 | AO44: Real Estate Taxes %/EGR | AQ44: 0.044925965 | AR44: 0.044270169 | AS44: 0.04369983 | AT44: 0.04379127 | AU44: 0.044331221 | AV44: 0.045001958 | AW44: 0.045870195 | AX44: 0.046789579 | AY44: 0.0477276 | AZ44: 0.048684627
A45: 0 | B45: 0 | C45: 1-139 | D45: A2Q | E45: =RIGHT(D45,1) -> Q | F45: N/A | G45: 700 | H45: Vacant | I45: VACANT | N45: 1359 | P45: 0 | Q45: 0 | R45: 0 | S45: 0 | T45: 0 | U45: 0 | V45: 0 | W45: 0 | X45: 0 | Y45: 0 | Z45: 0 | AA45: 0 | AB45: 0 | AC45: 0 | AD45: 0 | AE45: 0 | AF45: 0 | AG45: 0 | AH45: 0
A46: 31830 | B46: 43138 | C46: 1-140 | D46: A2Q | E46: =RIGHT(D46,1) -> Q | F46: N/A | G46: 700 | H46: Occupied | I46: Nelson, Norris | J46: 02/28/2025 | L46: 02/28/2026 | M46: 03/01/2027 | N46: 1329 | O46: RESIDENT | P46: 0 | Q46: 0 | R46: 0 | S46: 1349 | T46: 1349 | U46: 30 | V46: 10 | W46: 5.5 | X46: 5 | Y46: 18 | Z46: 0 | AA46: 0 | AB46: 35 | AC46: 0 | AD46: 0 | AE46: 0 | AF46: 0 | AG46: 0 | AH46: 1452.5 | AO46: Net Operating Income | AP46: 6439622.9 | AQ46: 6039057.2 | AR46: 6385692.3 | AS46: 6873147.5 | AT46: 7242541 | AU46: 7525853.5 | AV46: 7790530.6 | AW46: 8019396.5 | AX46: 8246399.4 | AY46: 8479439.4 | AZ46: 8718665.6
A47: 32088 | B47: 43121 | C47: 1-141 | D47: A2F | E47: =RIGHT(D47,1) -> F | F47: N/A | G47: 700 | H47: Occupied | I47: Soto, Alejandro | J47: 01/30/2026 | L47: 01/30/2026 | M47: 01/29/2027 | N47: 1249 | O47: RESIDENT | P47: 0 | Q47: 0 | R47: 0 | S47: 1179 | T47: 1179 | U47: 30 | V47: 10 | W47: 5.5 | X47: 5 | Y47: 0 | Z47: 0 | AA47: 0 | AB47: 0 | AC47: 0 | AD47: 0 | AE47: 0 | AF47: 0 | AG47: 0 | AH47: 1229.5
A48: 31591 | B48: 42875 | C48: 1-142 | D48: A2G | E48: =RIGHT(D48,1) -> G | F48: N/A | G48: 700 | H48: Occupied | I48: Campbell, Alexandra | J48: 09/07/2024 | L48: 10/07/2025 | M48: 10/12/2026 | N48: 1319 | O48: RESIDENT | P48: 0 | Q48: 0 | R48: -1515.37 | S48: 1379 | T48: 1379 | U48: 30 | V48: 10 | W48: 5.5 | X48: 5 | Y48: 0 | Z48: 0 | AA48: 0 | AB48: 35 | AC48: 0 | AD48: 0 | AE48: 0 | AF48: 0 | AG48: 0 | AH48: 1464.5
A49: 31748 | B49: 43023 | C49: 1-143 | D49: A2Q | E49: =RIGHT(D49,1) -> Q | F49: N/A | G49: 700 | H49: Occupied | I49: Mc Cutcheon, Lynda | J49: 12/30/2025 | L49: 12/30/2025 | M49: 12/28/2026 | N49: 1359 | O49: RESIDENT | P49: 0 | Q49: 0 | R49: 0 | S49: 1389 | T49: 1389 | U49: 30 | V49: 10 | W49: 5.5 | X49: 5 | Y49: 18 | Z49: 15 | AA49: 0 | AB49: 70 | AC49: 0 | AD49: 0 | AE49: 0 | AF49: 0 | AG49: 0 | AH49: 1542.5
A50: 10886 | B50: 43089 | C50: 1-144 | D50: A2F | E50: =RIGHT(D50,1) -> F | F50: N/A | G50: 700 | H50: Occupied | I50: Montez, Marissa | J50: 12/16/2022 | L50: 01/14/2026 | M50: 01/18/2027 | N50: 1249 | O50: RESIDENT | P50: 0 | Q50: 0 | R50: 0 | S50: 1290 | T50: 1290 | U50: 30 | V50: 10 | W50: 5.5 | X50: 5 | Y50: 18 | Z50: 15 | AA50: 0 | AB50: 35 | AC50: 0 | AD50: 0 | AE50: 0 | AF50: 0 | AG50: 0 | AH50: 1408.5
A51: 32021 | B51: 42990 | C51: 1-145 | D51: A2Q | E51: =RIGHT(D51,1) -> Q | F51: N/A | G51: 700 | H51: Occupied | I51: Yaptangco, Jayden | J51: 10/06/2025 | L51: 10/06/2025 | M51: 10/05/2026 | N51: 1359 | O51: RESIDENT | P51: 0 | Q51: 0 | R51: 0 | S51: 1389 | T51: 1389 | U51: 30 | V51: 10 | W51: 5.5 | X51: 5 | Y51: 18 | Z51: 0 | AA51: 0 | AB51: 35 | AC51: 0 | AD51: 0 | AE51: 0 | AF51: 0 | AG51: 0 | AH51: 1492.5
A52: 31910 | B52: 42779 | C52: 1-146 | D52: A2F | E52: =RIGHT(D52,1) -> F | F52: N/A | G52: 700 | H52: Occupied | I52: Munoz, Savannah | J52: 07/16/2025 | L52: 07/16/2025 | M52: 07/15/2026 | N52: 1249 | O52: RESIDENT | P52: 0 | Q52: 0 | R52: -713 | S52: 1279 | T52: 1279 | U52: 30 | V52: 10 | W52: 5.5 | X52: 5 | Y52: 18 | Z52: 15 | AA52: 0 | AB52: 0 | AC52: 0 | AD52: 0 | AE52: 0 | AF52: 0 | AG52: 0 | AH52: 1362.5
A53: 11166 | B53: 42887 | C53: 1-147 | D53: A2G | E53: =RIGHT(D53,1) -> G | F53: N/A | G53: 700 | H53: Occupied | I53: Sosa, Christina | J53: 09/18/2023 | L53: 09/18/2025 | M53: 09/21/2026 | N53: 1319 | O53: RESIDENT | P53: 0 | Q53: 0 | R53: -1511.49 | S53: 1389 | T53: 1389 | U53: 30 | V53: 10 | W53: 5.5 | X53: 5 | Y53: 18 | Z53: 15 | AA53: 0 | AB53: 0 | AC53: 0 | AD53: 0 | AE53: 0 | AF53: 0 | AG53: 0 | AH53: 1472.5
A54: 32065 | B54: 43090 | C54: 1-148 | D54: A2G | E54: =RIGHT(D54,1) -> G | F54: N/A | G54: 700 | H54: Occupied | I54: Gutierrez Cordova, Jessica | J54: 12/23/2025 | L54: 12/23/2025 | M54: 01/22/2027 | N54: 1319 | O54: RESIDENT | P54: 0 | Q54: 0 | R54: 0 | S54: 1249 | T54: 1249 | U54: 30 | V54: 10 | W54: 5.5 | X54: 5 | Y54: 18 | Z54: 15 | AA54: 0 | AB54: 0 | AC54: 0 | AD54: 0 | AE54: 0 | AF54: 0 | AG54: 0 | AH54: 1332.5
A55: 31945 | B55: 42851 | C55: 1-149 | D55: A2Q | E55: =RIGHT(D55,1) -> Q | F55: N/A | G55: 700 | H55: Occupied | I55: Gsell, Rory | J55: 07/28/2025 | L55: 07/28/2025 | M55: 07/27/2026 | N55: 1359 | O55: RESIDENT | P55: 0 | Q55: 0 | R55: -1420.37 | S55: 1319 | T55: 1319 | U55: 30 | V55: 10 | W55: 5.5 | X55: 5 | Y55: 0 | Z55: 0 | AA55: 0 | AB55: 0 | AC55: 0 | AD55: 0 | AE55: 0 | AF55: 0 | AG55: 0 | AH55: 1369.5
A56: 11042 | B56: 42690 | C56: 1-150 | D56: A2G | E56: =RIGHT(D56,1) -> G | F56: N/A | G56: 700 | H56: Occupied-NTV | I56: Othman, Mohamed | J56: 05/02/2023 | K56: 05/05/2026 | L56: 05/06/2025 | M56: 05/05/2026 | N56: 1319 | O56: RESIDENT | P56: 0 | Q56: 0 | R56: 0 | S56: 1370 | T56: 1370 | U56: 30 | V56: 10 | W56: 5.5 | X56: 5 | Y56: 18 | Z56: 15 | AA56: 0 | AB56: 0 | AC56: 0 | AD56: 0 | AE56: 0 | AF56: 0 | AG56: 0 | AH56: 1453.5
A57: 31907 | B57: 42770 | C57: 1-151 | D57: A2G | E57: =RIGHT(D57,1) -> G | F57: N/A | G57: 700 | H57: Occupied | I57: Reyes, Dimitrius | J57: 08/06/2025 | L57: 08/06/2025 | M57: 08/05/2026 | N57: 1319 | O57: RESIDENT | P57: 0 | Q57: 0 | R57: 0 | S57: 1349 | T57: 1349 | U57: 30 | V57: 10 | W57: 5.5 | X57: 5 | Y57: 18 | Z57: 0 | AA57: 0 | AB57: 0 | AC57: 0 | AD57: 0 | AE57: 0 | AF57: 0 | AG57: 0 | AH57: 1417.5
A58: 11140 | B58: 42866 | C58: 1-152 | D58: A2Q | E58: =RIGHT(D58,1) -> Q | F58: N/A | G58: 700 | H58: Occupied | I58: Maples, Ivan | J58: 08/04/2023 | L58: 08/02/2025 | M58: 08/03/2026 | N58: 1359 | O58: RESIDENT | P58: 0 | Q58: 0 | R58: 0 | S58: 1439 | T58: 1439 | U58: 30 | V58: 10 | W58: 5.5 | X58: 5 | Y58: 0 | Z58: 15 | AA58: 0 | AB58: 0 | AC58: 0 | AD58: 0 | AE58: 0 | AF58: 0 | AG58: 0 | AH58: 1504.5
A59: 32124 | B59: 43186 | C59: 1-153 | D59: A2Q | E59: =RIGHT(D59,1) -> Q | F59: N/A | G59: 700 | H59: Occupied | I59: Whitmore, Roger | J59: 03/02/2026 | L59: 03/02/2026 | M59: 06/01/2027 | N59: 1359 | O59: RESIDENT | P59: 0 | Q59: 0 | R59: 0 | S59: 1129 | T59: 1129 | U59: 30 | V59: 10 | W59: 5.5 | X59: 5 | Y59: 18 | Z59: 0 | AA59: 70 | AB59: 0 | AC59: 200 | AD59: 0 | AE59: 0 | AF59: 0 | AG59: 0 | AH59: 1467.5
A60: 32054 | B60: 43068 | C60: 1-154 | D60: A2F | E60: =RIGHT(D60,1) -> F | F60: N/A | G60: 700 | H60: Occupied | I60: Mehta, Sammy | J60: 12/01/2025 | L60: 12/01/2025 | M60: 12/01/2026 | N60: 1249 | O60: RESIDENT | P60: 0 | Q60: 0 | R60: 0 | S60: 1059 | T60: 1059 | U60: 30 | V60: 10 | W60: 5.5 | X60: 5 | Y60: 18 | Z60: 0 | AA60: 0 | AB60: 0 | AC60: 0 | AD60: 0 | AE60: 0 | AF60: 0 | AG60: 0 | AH60: 1127.5
A61: 21393 | B61: 43180 | C61: 1-155 | D61: A2F | E61: =RIGHT(D61,1) -> F | F61: N/A | G61: 700 | H61: Occupied | I61: Dryden, Dylan | J61: 02/20/2024 | L61: 03/20/2026 | M61: 03/22/2027 | N61: 1249 | O61: RESIDENT | P61: 0 | Q61: 0 | R61: 0 | S61: 1248 | T61: 1248 | U61: 30 | V61: 10 | W61: 5.5 | X61: 5 | Y61: 18 | Z61: 0 | AA61: 0 | AB61: 0 | AC61: 0 | AD61: 0 | AE61: 0 | AF61: 0 | AG61: 0 | AH61: 1316.5
A62: 31903 | B62: 42761 | C62: 1-156 | D62: A2F | E62: =RIGHT(D62,1) -> F | F62: N/A | G62: 700 | H62: Occupied | I62: Jones, Sade | J62: 07/12/2025 | L62: 07/12/2025 | M62: 07/10/2026 | N62: 1249 | O62: RESIDENT | P62: 0 | Q62: 0 | R62: -1386.49 | S62: 1279 | T62: 1279 | U62: 30 | V62: 10 | W62: 5.5 | X62: 5 | Y62: 18 | Z62: 0 | AA62: 0 | AB62: 0 | AC62: 0 | AD62: 0 | AE62: 0 | AF62: 0 | AG62: 0 | AH62: 1347.5
A63: 622 | B63: 10688 | C63: 1-157 | D63: A3Q | E63: =RIGHT(D63,1) -> Q | F63: N/A | G63: 825 | H63: Occupied | I63: Wiscombe, John | J63: 12/29/2021 | L63: 12/29/2021 | M63: 12/28/2022 | N63: 1419 | O63: RESIDENT | P63: 0 | Q63: 0 | R63: 0 | S63: 1690 | T63: 1690 | U63: 30 | V63: 10 | W63: 5.5 | X63: 5 | Y63: 18 | Z63: 0 | AA63: 0 | AB63: 0 | AC63: 0 | AD63: 250 | AE63: 0 | AF63: 0 | AG63: 0 | AH63: 2008.5
A64: 31939 | B64: 42841 | C64: 1-158 | D64: A3G | E64: =RIGHT(D64,1) -> G | F64: N/A | G64: 825 | H64: Occupied | I64: Stevenson, DeAvion | J64: 07/15/2025 | L64: 07/15/2025 | M64: 07/13/2026 | N64: 1379 | O64: RESIDENT | P64: 0 | Q64: 0 | R64: 3867.33 | S64: 1329 | T64: 1329 | U64: 30 | V64: 10 | W64: 5.5 | X64: 5 | Y64: 18 | Z64: 0 | AA64: 0 | AB64: 0 | AC64: 0 | AD64: 0 | AE64: 0 | AF64: 0 | AG64: 0 | AH64: 1397.5
A65: 31586 | B65: 42847 | C65: 1-159 | D65: A3G | E65: =RIGHT(D65,1) -> G | F65: N/A | G65: 825 | H65: Occupied | I65: Quah, Eliza | J65: 07/29/2024 | L65: 07/29/2025 | M65: 07/28/2026 | N65: 1379 | O65: RESIDENT | P65: 0 | Q65: 0 | R65: 0 | S65: 1439 | T65: 1439 | U65: 30 | V65: 10 | W65: 5.5 | X65: 5 | Y65: 18 | Z65: 15 | AA65: 0 | AB65: 0 | AC65: 0 | AD65: 0 | AE65: 0 | AF65: 0 | AG65: 0 | AH65: 1522.5
A66: 31964 | B66: 42889 | C66: 1-160 | D66: A3Q | E66: =RIGHT(D66,1) -> Q | F66: N/A | G66: 825 | H66: Occupied | I66: Wicks, Catherine | J66: 09/19/2025 | L66: 09/19/2025 | M66: 10/16/2026 | N66: 1419 | O66: RESIDENT | P66: 0 | Q66: 0 | R66: 1986.41 | S66: 1369 | T66: 1369 | U66: 30 | V66: 10 | W66: 5.5 | X66: 5 | Y66: 18 | Z66: 0 | AA66: 0 | AB66: 0 | AC66: 0 | AD66: 0 | AE66: 0 | AF66: 0 | AG66: 0 | AH66: 1437.5
A67: 32028 | B67: 42999 | C67: 1-161 | D67: A3F | E67: =RIGHT(D67,1) -> F | F67: N/A | G67: 825 | H67: Occupied | I67: Mackay, Riley | J67: 11/13/2025 | L67: 11/13/2025 | M67: 11/12/2026 | N67: 1309 | O67: RESIDENT | P67: 0 | Q67: 0 | R67: -1449.04 | S67: 1339 | T67: 1339 | U67: 30 | V67: 10 | W67: 5.5 | X67: 5 | Y67: 18 | Z67: 0 | AA67: 0 | AB67: 0 | AC67: 0 | AD67: 0 | AE67: 0 | AF67: 0 | AG67: 0 | AH67: 1407.5
A68: 31784 | B68: 43063 | C68: 1-162 | D68: A3G | E68: =RIGHT(D68,1) -> G | F68: N/A | G68: 825 | H68: Occupied | I68: Herreman, Emily | J68: 01/22/2025 | L68: 01/22/2026 | M68: 01/21/2027 | N68: 1379 | O68: RESIDENT | P68: 0 | Q68: 0 | R68: 0 | S68: 1409 | T68: 1409 | U68: 30 | V68: 10 | W68: 5.5 | X68: 5 | Y68: 18 | Z68: 15 | AA68: 0 | AB68: 0 | AC68: 0 | AD68: 0 | AE68: 0 | AF68: 0 | AG68: 0 | AH68: 1492.5
... A74: 31894 | B74: 42747 | C74: 1-168 | D74: B2Q | E74: =RIGHT(D74,1) -> Q | F74: N/A | G74: 1076 | H74: Occupied | I74: Feliciano, Deanna | J74: 05/19/2025 | L74: 05/19/2025 | M74: 05/18/2026 | N74: 1659 | O74: RESIDENT | P74: 0 | Q74: 0 | R74: 0 | S74: 1639 | T74: 1639 | U74: 30 | V74: 10 | W74: 5.5 | X74: 5 | Y74: 18 | Z74: 0 | AA74: 0 | AB74: 0 | AC74: 0 | AD74: 0 | AE74: 0 | AF74: 0 | AG74: 0 | AH74: 1707.5
A75: 827 | B75: 42950 | C75: 1-169 | D75: B2G | E75: =RIGHT(D75,1) -> G | F75: N/A | G75: 1076 | H75: Occupied-NTV | I75: Killingsworth, micheal | J75: 10/25/2022 | K75: 04/27/2026 | L75: 10/25/2025 | M75: 04/27/2026 | N75: 1609 | O75: RESIDENT | P75: 0 | Q75: 0 | R75: -1801.58 | S75: 1780 | T75: 1780 | U75: 30 | V75: 10 | W75: 5.5 | X75: 5 | Y75: 18 | Z75: 0 | AA75: 0 | AB75: 0 | AC75: 75 | AD75: 0 | AE75: 0 | AF75: 0 | AG75: 0 | AH75: 1923.5
A76: 803 | B76: 42310 | C76: 1-170 | D76: B2Q | E76: =RIGHT(D76,1) -> Q | F76: N/A | G76: 1076 | H76: Occupied | I76: Touchine, Mercedes | J76: 07/15/2022 | L76: 08/18/2024 | M76: 08/14/2025 | N76: 1659 | O76: RESIDENT | P76: 0 | Q76: 0 | R76: 0 | S76: 1870 | T76: 1870 | U76: 30 | V76: 10 | W76: 5.5 | X76: 5 | Y76: 18 | Z76: 0 | AA76: 0 | AB76: 35 | AC76: 0 | AD76: 250 | AE76: 0 | AF76: 0 | AG76: 0 | AH76: 2223.5
A77: 0 | B77: 0 | C77: 1-171 | D77: B2F | E77: =RIGHT(D77,1) -> F | F77: N/A | G77: 1076 | H77: Vacant | I77: VACANT | N77: 1509 | P77: 0 | Q77: 0 | R77: 0 | S77: 0 | T77: 0 | U77: 0 | V77: 0 | W77: 0 | X77: 0 | Y77: 0 | Z77: 0 | AA77: 0 | AB77: 0 | AC77: 0 | AD77: 0 | AE77: 0 | AF77: 0 | AG77: 0 | AH77: 0
A78: 31651 | B78: 42946 | C78: 1-172 | D78: B2Q | E78: =RIGHT(D78,1) -> Q | F78: N/A | G78: 1076 | H78: Occupied-NTV | I78: Nuadjim Guiakam, Pierre Cyrille | J78: 10/25/2024 | K78: 04/23/2026 | L78: 10/25/2025 | M78: 04/24/2026 | N78: 1659 | O78: RESIDENT | P78: 0 | Q78: 0 | R78: 799.67 | S78: 1699 | T78: 1699 | U78: 30 | V78: 10 | W78: 5.5 | X78: 5 | Y78: 18 | Z78: 0 | AA78: 0 | AB78: 0 | AC78: 75 | AD78: 0 | AE78: 0 | AF78: 0 | AG78: 0 | AH78: 1842.5
A79: 632 | B79: 42636 | C79: 1-173 | D79: B1F | E79: =RIGHT(D79,1) -> F | F79: N/A | G79: 1010 | H79: Occupied | I79: Barendrick, Sydney | J79: 02/26/2022 | L79: 02/25/2025 | M79: 02/24/2026 | N79: 1459 | O79: RESIDENT | P79: 0 | Q79: 0 | R79: 0 | S79: 1606 | T79: 1606 | U79: 30 | V79: 10 | W79: 5.5 | X79: 5 | Y79: 18 | Z79: 30 | AA79: 0 | AB79: 35 | AC79: 0 | AD79: 0 | AE79: 0 | AF79: 0 | AG79: 0 | AH79: 1739.5
A80: 632 | B80: 43297 | C80: 1-173 | D80: B1F | E80: =RIGHT(D80,1) -> F | F80: N/A | G80: 1010 | H80: Pending renewal | I80: Barendrick, Sydney | J80: 02/26/2022 | L80: 02/25/2026 | M80: 03/01/2027 | N80: 0 | O80: RESIDENT | P80: 0 | Q80: 0 | R80: 0 | S80: 1606 | T80: 1606 | U80: 30 | V80: 10 | W80: 5.5 | X80: 5 | Y80: 18 | Z80: 0 | AA80: 0 | AB80: 35 | AC80: 0 | AD80: 0 | AE80: 0 | AF80: 0 | AG80: 0 | AH80: 1709.5
A81: 129 | B81: 42988 | C81: 1-174 | D81: B1 | E81: =RIGHT(D81,1) -> 1 | F81: N/A | G81: 1010 | H81: Occupied-NTV | I81: Fye, Russell | J81: 02/18/2019 | K81: 05/04/2026 | L81: 10/02/2025 | M81: 04/06/2026 | N81: 1559 | O81: RESIDENT | P81: 500 | Q81: 0 | R81: 0 | S81: 1590 | T81: 1590 | U81: 30 | V81: 10 | W81: 5.5 | X81: 5 | Y81: 18 | Z81: 0 | AA81: 0 | AB81: 35 | AC81: 75 | AD81: 0 | AE81: 0 | AF81: 0 | AG81: 0 | AH81: 1768.5
A82: 151 | B82: 42665 | C82: 1-175 | D82: B2 | E82: =RIGHT(D82,1) -> 2 | F82: N/A | G82: 1076 | H82: Occupied | I82: Abril, Claudia | J82: 07/26/2019 | L82: 04/29/2025 | M82: 04/28/2026 | N82: 1639 | O82: RESIDENT | P82: 0 | Q82: 0 | R82: 0 | S82: 1730 | T82: 1730 | U82: 30 | V82: 10 | W82: 5.5 | X82: 5 | Y82: 18 | Z82: 0 | AA82: 0 | AB82: 35 | AC82: 0 | AD82: 0 | AE82: 0 | AF82: 0 | AG82: 0 | AH82: 1833.5
A83: 32006 | B83: 42957 | C83: 1-176 | D83: B2Q | E83: =RIGHT(D83,1) -> Q | F83: N/A | G83: 1076 | H83: Occupied | I83: williams, rashine | J83: 09/12/2025 | L83: 09/12/2025 | M83: 10/12/2026 | N83: 1659 | O83: RESIDENT | P83: 0 | Q83: 0 | R83: 0 | S83: 1639 | T83: 1639 | U83: 30 | V83: 10 | W83: 5.5 | X83: 5 | Y83: 18 | Z83: 15 | AA83: 0 | AB83: 0 | AC83: 0 | AD83: 0 | AE83: 0 | AF83: 0 | AG83: 0 | AH83: 1722.5
A84: 31829 | B84: 43190 | C84: 1-177 | D84: B1Q | E84: =RIGHT(D84,1) -> Q | F84: N/A | G84: 1010 | H84: Occupied | I84: Quiruz, Izaiah | J84: 03/21/2025 | L84: 03/31/2026 | M84: 04/05/2027 | N84: 1579 | O84: RESIDENT | P84: 0 | Q84: 0 | R84: 0 | S84: 1609 | T84: 1609 | U84: 30 | V84: 10 | W84: 5.5 | X84: 5 | Y84: 18 | Z84: 30 | AA84: 0 | AB84: 0 | AC84: 0 | AD84: 0 | AE84: 0 | AF84: 0 | AG84: 0 | AH84: 1707.5
A85: 136 | B85: 42733 | C85: 1-178 | D85: B1 | E85: =RIGHT(D85,1) -> 1 | F85: N/A | G85: 1010 | H85: Occupied | I85: Vukas, Sheryl | J85: 04/19/2019 | L85: 07/02/2025 | M85: 07/01/2026 | N85: 1559 | O85: RESIDENT | P85: 0 | Q85: 0 | R85: -57.21 | S85: 1599 | T85: 1599 | U85: 30 | V85: 10 | W85: 5.5 | X85: 5 | Y85: 0 | Z85: 0 | AA85: 0 | AB85: 0 | AC85: 0 | AD85: 0 | AE85: 0 | AF85: 0 | AG85: 0 | AH85: 1649.5
A86: 187 | B86: 43101 | C86: 1-179 | D86: A2 | E86: =RIGHT(D86,1) -> 2 | F86: N/A | G86: 700 | H86: Occupied | I86: Simpson, Rebecca | J86: 01/11/2020 | L86: 01/21/2026 | M86: 01/25/2027 | N86: 1319 | O86: RESIDENT | P86: 500 | Q86: 500 | R86: 0 | S86: 1349 | T86: 1349 | U86: 30 | V86: 10 | W86: 5.5 | X86: 5 | Y86: 0 | Z86: 0 | AA86: 0 | AB86: 0 | AC86: 0 | AD86: 0 | AE86: 0 | AF86: 0 | AG86: 0 | AH86: 1399.5
A87: 10895 | B87: 43087 | C87: 1-180 | D87: A2G | E87: =RIGHT(D87,1) -> G | F87: N/A | G87: 700 | H87: Occupied | I87: Ortis, Colin | J87: 12/16/2022 | L87: 01/14/2026 | M87: 01/18/2027 | N87: 1319 | O87: RESIDENT | P87: 0 | Q87: 0 | R87: 0 | S87: 1390 | T87: 1390 | U87: 30 | V87: 10 | W87: 5.5 | X87: 5 | Y87: 18 | Z87: 0 | AA87: 0 | AB87: 0 | AC87: 0 | AD87: 0 | AE87: 0 | AF87: 0 | AG87: 0 | AH87: 1458.5
A88: 32070 | B88: 43098 | C88: 1-181 | D88: A2F | E88: =RIGHT(D88,1) -> F | F88: N/A | G88: 700 | H88: Occupied | I88: Yeh, Chin | J88: 12/23/2025 | L88: 12/23/2025 | M88: 03/22/2027 | N88: 1249 | O88: RESIDENT | P88: 0 | Q88: 0 | R88: 0 | S88: 1179 | T88: 1179 | U88: 30 | V88: 10 | W88: 5 | X88: 5 | Y88: 0 | Z88: 0 | AA88: 0 | AB88: 0 | AC88: 0 | AD88: 0 | AE88: 0 | AF88: 0 | AG88: 0 | AH88: 1229
A89: 32067 | B89: 43095 | C89: 1-182 | D89: A2F | E89: =RIGHT(D89,1) -> F | F89: N/A | G89: 700 | H89: Occupied | I89: Reyes, Daniel | J89: 12/16/2025 | L89: 12/16/2025 | M89: 12/15/2026 | N89: 1249 | O89: RESIDENT | P89: 0 | Q89: 0 | R89: 0 | S89: 1029 | T89: 1029 | U89: 30 | V89: 10 | W89: 5 | X89: 5 | Y89: 18 | Z89: 0 | AA89: 0 | AB89: 0 | AC89: 0 | AD89: 0 | AE89: 0 | AF89: 0 | AG89: 0 | AH89: 1097
A90: 17 | B90: 43067 | C90: 1-183 | D90: A2 | E90: =RIGHT(D90,1) -> 2 | F90: N/A | G90: 700 | H90: Occupied | I90: Thompson, Carole | J90: 11/06/2001 | L90: 01/14/2026 | M90: 01/18/2027 | N90: 1319 | O90: RESIDENT | P90: 160 | Q90: 160 | R90: 0 | S90: 1299 | T90: 1299 | U90: 30 | V90: 10 | W90: 5.5 | X90: 5 | Y90: 18 | Z90: 0 | AA90: 0 | AB90: 0 | AC90: 0 | AD90: 0 | AE90: 0 | AF90: 0 | AG90: 0 | AH90: 1367.5
A91: 31710 | B91: 43171 | C91: 1-184 | D91: A2F | E91: =RIGHT(D91,1) -> F | F91: N/A | G91: 700 | H91: Occupied | I91: Gayosso, Eric | J91: 01/30/2025 | L91: 03/03/2026 | M91: 03/08/2027 | N91: 1249 | O91: RESIDENT | P91: 0 | Q91: 0 | R91: 250 | S91: 1248 | T91: 1248 | U91: 30 | V91: 10 | W91: 5.5 | X91: 5 | Y91: 18 | Z91: 0 | AA91: 0 | AB91: 0 | AC91: 0 | AD91: 0 | AE91: 0 | AF91: 0 | AG91: 0 | AH91: 1316.5
A92: 31457 | B92: 42601 | C92: 1-185 | D92: A2Q | E92: =RIGHT(D92,1) -> Q | F92: N/A | G92: 700 | H92: Occupied | I92: Montes, Whitley | J92: 04/04/2024 | L92: 04/04/2025 | M92: 04/03/2026 | N92: 1329 | O92: RESIDENT | P92: 0 | Q92: 0 | R92: 0 | S92: 1359 | T92: 1359 | U92: 30 | V92: 10 | W92: 5.5 | X92: 5 | Y92: 18 | Z92: 15 | AA92: 0 | AB92: 0 | AC92: 0 | AD92: 0 | AE92: 0 | AF92: 0 | AG92: 0 | AH92: 1442.5
A93: 32139 | B93: 43209 | C93: 1-186 | D93: A2Q | E93: =RIGHT(D93,1) -> Q | F93: N/A | G93: 700 | H93: Occupied | I93: Skalitzky, Rick | J93: 03/02/2026 | L93: 03/02/2026 | M93: 06/01/2026 | N93: 1329 | O93: RESIDENT | P93: 0 | Q93: 0 | R93: 6.45 | S93: 1329 | T93: 1329 | U93: 30 | V93: 10 | W93: 5.5 | X93: 5 | Y93: 18 | Z93: 0 | AA93: 0 | AB93: 0 | AC93: 200 | AD93: 0 | AE93: 0 | AF93: 0 | AG93: 0 | AH93: 1597.5
... A96: 32098 | B96: 43134 | C96: 1-189 | D96: B1Q | E96: =RIGHT(D96,1) -> Q | F96: N/A | G96: 1010 | H96: Occupied | I96: Ruiz, Claudia | J96: 01/08/2026 | L96: 01/08/2026 | M96: 01/06/2027 | N96: 1579 | O96: RESIDENT | P96: 0 | Q96: 0 | R96: 0 | S96: 1449 | T96: 1449 | U96: 30 | V96: 10 | W96: 5.5 | X96: 5 | Y96: 18 | Z96: 0 | AA96: 0 | AB96: 0 | AC96: 0 | AD96: 0 | AE96: 0 | AF96: 0 | AG96: 0 | AH96: 1517.5
A97: 0 | B97: 0 | C97: 1-190 | D97: B1Q | E97: =RIGHT(D97,1) -> Q | F97: N/A | G97: 1010 | H97: Vacant | I97: VACANT | N97: 1579 | P97: 0 | Q97: 0 | R97: 0 | S97: 0 | T97: 0 | U97: 0 | V97: 0 | W97: 0 | X97: 0 | Y97: 0 | Z97: 0 | AA97: 0 | AB97: 0 | AC97: 0 | AD97: 0 | AE97: 0 | AF97: 0 | AG97: 0 | AH97: 0
A98: 11155 | B98: 42767 | C98: 1-191 | D98: B1G | E98: =RIGHT(D98,1) -> G | F98: N/A | G98: 1010 | H98: Occupied | I98: Palthe, Daniel | J98: 07/26/2023 | L98: 07/29/2025 | M98: 07/27/2026 | N98: 1529 | O98: RESIDENT | P98: 0 | Q98: 0 | R98: 0 | S98: 1639 | T98: 1639 | U98: 30 | V98: 10 | W98: 5.5 | X98: 5 | Y98: 18 | Z98: 15 | AA98: 0 | AB98: 0 | AC98: 0 | AD98: 0 | AE98: 0 | AF98: 0 | AG98: 0 | AH98: 1722.5
A99: 101 | B99: 43212 | C99: 1-192 | D99: B1 | E99: =RIGHT(D99,1) -> 1 | F99: N/A | G99: 1010 | H99: Occupied | I99: Mayback, Susan | J99: 02/03/2018 | L99: 03/18/2026 | M99: 03/22/2027 | N99: 1559 | O99: RESIDENT | P99: 250 | Q99: 250 | R99: 0 | S99: 1499 | T99: 1499 | U99: 30 | V99: 10 | W99: 5.5 | X99: 5 | Y99: 18 | Z99: 0 | AA99: 0 | AB99: 0 | AC99: 0 | AD99: 0 | AE99: 0 | AF99: 0 | AG99: 0 | AH99: 1567.5
A100: 32101 | B100: 43139 | C100: 1-193 | D100: B1G | E100: =RIGHT(D100,1) -> G | F100: N/A | G100: 1010 | H100: Occupied | I100: Banford, Karen | J100: 01/16/2026 | L100: 01/16/2026 | M100: 01/15/2027 | N100: 1529 | O100: RESIDENT | P100: 0 | Q100: 0 | R100: -1499.18 | S100: 1359 | T100: 1359 | U100: 30 | V100: 10 | W100: 5.5 | X100: 5 | Y100: 18 | Z100: 15 | AA100: 0 | AB100: 0 | AC100: 0 | AD100: 0 | AE100: -522.72 | AF100: 0 | AG100: 0 | AH100: 919.78
A101: 425 | B101: 42778 | C101: 1-194 | D101: B1 | E101: =RIGHT(D101,1) -> 1 | F101: N/A | G101: 1010 | H101: Occupied | I101: Frey, Heidi | J101: 04/30/2021 | L101: 06/25/2025 | M101: 06/24/2026 | N101: 1559 | O101: RESIDENT | P101: 0 | Q101: 0 | R101: 0 | S101: 1602 | T101: 1602 | U101: 30 | V101: 10 | W101: 5.5 | X101: 5 | Y101: 18 | Z101: 0 | AA101: 0 | AB101: 35 | AC101: 0 | AD101: 0 | AE101: 0 | AF101: 0 | AG101: 0 | AH101: 1705.5
A102: 11379 | B102: 43228 | C102: 1-201 | D102: B2Q | E102: =RIGHT(D102,1) -> Q | F102: N/A | G102: 1076 | H102: Occupied | I102: Schlinglof, Lilly | J102: 03/27/2024 | L102: 03/27/2026 | M102: 03/29/2027 | N102: 1644 | O102: RESIDENT | P102: 0 | Q102: 0 | R102: -40.48 | S102: 1643 | T102: 1643 | U102: 30 | V102: 10 | W102: 5.5 | X102: 5 | Y102: 18 | Z102: 0 | AA102: 70 | AB102: 0 | AC102: 0 | AD102: 0 | AE102: 0 | AF102: 0 | AG102: 0 | AH102: 1781.5
A103: 76 | B103: 43221 | C103: 1-202 | D103: B2 | E103: =RIGHT(D103,1) -> 2 | F103: N/A | G103: 1076 | H103: Occupied | I103: Fruzynski, Andrew | J103: 03/21/2017 | L103: 03/05/2026 | M103: 03/08/2027 | N103: 1594 | O103: RESIDENT | P103: 666 | Q103: 666 | R103: 0 | S103: 1604 | T103: 1604 | U103: 30 | V103: 10 | W103: 5.5 | X103: 5 | Y103: 18 | Z103: 30 | AA103: 0 | AB103: 35 | AC103: 0 | AD103: 0 | AE103: 0 | AF103: 0 | AG103: 0 | AH103: 1737.5
A104: 31915 | B104: 42795 | C104: 1-203 | D104: B2G | E104: =RIGHT(D104,1) -> G | F104: N/A | G104: 1076 | H104: Occupied | I104: Scott, Kristopher | J104: 06/19/2025 | L104: 06/19/2025 | M104: 06/18/2026 | N104: 1594 | O104: RESIDENT | P104: 0 | Q104: 0 | R104: -1694.81 | S104: 1544 | T104: 1544 | U104: 30 | V104: 10 | W104: 5.5 | X104: 5 | Y104: 18 | Z104: 0 | AA104: 0 | AB104: 0 | AC104: 0 | AD104: 0 | AE104: 0 | AF104: 0 | AG104: 0 | AH104: 1612.5
A105: 0 | B105: 0 | C105: 1-204 | D105: B2Q | E105: =RIGHT(D105,1) -> Q | F105: N/A | G105: 1076 | H105: Vacant-Leased | I105: VACANT | N105: 1629 | P105: 0 | Q105: 0 | R105: 0 | S105: 0 | T105: 0 | U105: 0 | V105: 0 | W105: 0 | X105: 0 | Y105: 0 | Z105: 0 | AA105: 0 | AB105: 0 | AC105: 0 | AD105: 0 | AE105: 0 | AF105: 0 | AG105: 0 | AH105: 0
A106: 32159 | B106: 43259 | C106: 1-204 | D106: B2Q | E106: =RIGHT(D106,1) -> Q | F106: N/A | G106: 1076 | H106: Applicant | I106: Riley, Evan | J106: 04/01/2026 | L106: 04/01/2026 | M106: 10/01/2026 | N106: 0 | O106: RESIDENT | P106: 0 | Q106: 0 | R106: 0 | S106: 1554 | T106: 1554 | U106: 30 | V106: 10 | W106: 5.5 | X106: 5 | Y106: 18 | Z106: 0 | AA106: 70 | AB106: 0 | AC106: 75 | AD106: 0 | AE106: 0 | AF106: 0 | AG106: 0 | AH106: 1767.5
A107: 31988 | B107: 42924 | C107: 1-205 | D107: B2F | E107: =RIGHT(D107,1) -> F | F107: N/A | G107: 1076 | H107: Occupied | I107: Galaviz cano, Mario | J107: 08/29/2025 | L107: 08/29/2025 | M107: 09/28/2026 | N107: 1524 | O107: RESIDENT | P107: 0 | Q107: 0 | R107: 0 | S107: 1554 | T107: 1554 | U107: 30 | V107: 10 | W107: 5.5 | X107: 5 | Y107: 18 | Z107: 30 | AA107: 0 | AB107: 0 | AC107: 0 | AD107: 0 | AE107: 0 | AF107: 0 | AG107: 0 | AH107: 1652.5
...

Sheet AR
A1: Knightvest Management LLC - Strada DELINQUENT AND PREPAID FISCAL PERIOD 032026 AS OF 05/15/2026 05/15/2026 03:33 PM Parameters: Report Type: Details Subproperties: - all subproperties- Subjournals: ALL Statuses to include: Current resident; Include delinquencies that equal NTV Credit? Yes; Exclude transactions payable in arrears: No; Delinquency range 0 through 99999999; Aging Columns: Fiscal; Filter type: ALL; Show Prepaid As Allocated: Yes; Include outstanding deposits: No; Hide all PII data: No; Delinquent Comments: Current only | AB1: =+SUM($AB$3:$AB$10) -> 0
A2: Resh ID | B2: Lease ID | C2: Bldg/Unit | D2: Name | E2: Phone Number | F2: Email | G2: Status | H2: Move-In/Out | I2: Code Description | J2: Total Prepaid | K2: Total Delinquent | L2: D | M2: O | N2: Net Balance | O2: Current | P2: 30 Days | Q2: 60 Days | R2: 90+ Days | S2: Prorate Credit | T2: Deposits Held | U2: Outstanding Deposit | V2: #Late | W2: #NSF | X2: Comment Date | Y2: Leasing Agent | AA2: RENT
A3: 31939 | B3: 42841 | C3: 1-158 | D3: Stevenson, DeAvion Alicia | E3: (602)456-9286 | F3: deavionstvn98@gmail.com | G3: Current resident | H3: 07/15/2025 | I3: RENT | J3: 0 | K3: 1328.37 | L3: † | N3: 1328.37 | O3: 0 | P3: 1328.37 | Q3: 0 | R3: 0 | S3: 0 | T3: 0 | U3: 0 | V3: 8 | W3: 2 | X3: 03/23/2026 | AA3: =+_xlfn.XLOOKUP(C3,'Rent Roll'!$C$7:$C$501,'Rent Roll'!$T$7:$T$501) -> 1329 | AB3: =+IF(SUM(Q3:R3)>AA3,AA3,0) -> 0
A4: 31939 | B4: 42841 | C4: 1-158 | D4: Stevenson, DeAvion Alicia | E4: (602)456-9286 | F4: deavionstvn98@gmail.com | G4: Current resident | H4: 07/15/2025 | I4: RENT | J4: 0 | K4: 1329 | N4: 1329 | O4: 1329 | P4: 0 | Q4: 0 | R4: 0 | S4: 0 | T4: 0 | U4: 0 | V4: 8 | W4: 2 | X4: 03/23/2026 | AA4: =+_xlfn.XLOOKUP(C4,'Rent Roll'!$C$7:$C$501,'Rent Roll'!$T$7:$T$501) -> 1329 | AB4: =+IF(SUM(Q4:R4)>AA4,AA4,0) -> 0
A5: 31964 | B5: 42889 | C5: 1-160 | D5: Catherine Wicks | E5: (480)772-9296 | F5: catherinem.wicks@gmail.com | G5: Current resident | H5: 09/19/2025 | I5: RENT | J5: 0 | K5: 1369 | N5: 1369 | O5: 1369 | P5: 0 | Q5: 0 | R5: 0 | S5: 0 | T5: 0 | U5: 0 | V5: 7 | W5: 1 | X5: 03/23/2026 | AA5: =+_xlfn.XLOOKUP(C5,'Rent Roll'!$C$7:$C$501,'Rent Roll'!$T$7:$T$501) -> 1369 | AB5: =+IF(SUM(Q5:R5)>AA5,AA5,0) -> 0
A6: 31926 | B6: 42816 | C6: 1-263 | D6: Pinder, John Timothy | E6: (602)247-0742 | F6: john.t.pinder@outlook.com | G6: Current resident | H6: 06/28/2025 | I6: RENT | J6: 0 | K6: 1324 | N6: 1324 | O6: 1324 | P6: 0 | Q6: 0 | R6: 0 | S6: 0 | T6: 0 | U6: 0 | V6: 6 | W6: 0 | X6: 03/23/2026 | AA6: =+_xlfn.XLOOKUP(C6,'Rent Roll'!$C$7:$C$501,'Rent Roll'!$T$7:$T$501) -> 1324 | AB6: =+IF(SUM(Q6:R6)>AA6,AA6,0) -> 0
A7: 31893 | B7: 42745 | C7: 1-374 | D7: Uribe, Bryan Alejandro | E7: N/A | F7: bryan.2911@hotmail.com | G7: Current resident | H7: 05/31/2025 | I7: RENT | J7: 0 | K7: 1579 | N7: 1579 | O7: 1579 | P7: 0 | Q7: 0 | R7: 0 | S7: 0 | T7: 0 | U7: 0 | V7: 5 | W7: 1 | X7: 03/23/2026 | AA7: =+_xlfn.XLOOKUP(C7,'Rent Roll'!$C$7:$C$501,'Rent Roll'!$T$7:$T$501) -> 1579 | AB7: =+IF(SUM(Q7:R7)>AA7,AA7,0) -> 0
A8: 32132 | B8: 43199 | C8: 2-163 | D8: Spade, Eric | E8: (606) 401-8122 | F8: eespade2@gmail.com | G8: Current resident | H8: 03/30/2026 | I8: RENT | J8: 0 | K8: 101.87 | N8: 101.87 | O8: 101.87 | P8: 0 | Q8: 0 | R8: 0 | S8: 0 | T8: 0 | U8: 0 | V8: 1 | W8: 0 | AA8: =+_xlfn.XLOOKUP(C8,'Rent Roll'!$C$7:$C$501,'Rent Roll'!$T$7:$T$501) -> 1579 | AB8: =+IF(SUM(Q8:R8)>AA8,AA8,0) -> 0
A9: 32086 | B9: 43118 | C9: 2-180 | D9: Dawson, Dion | E9: (480) 720-1590 | F9: dion.dawson16@gmail.com | G9: Current resident | H9: 12/26/2025 | I9: RENT | J9: 0 | K9: 2358 | N9: 2358 | O9: 1179 | P9: 1179 | Q9: 0 | R9: 0 | S9: 0 | T9: 0 | U9: 0 | V9: 2 | W9: 0 | X9: 03/23/2026 | AA9: =+_xlfn.XLOOKUP(C9,'Rent Roll'!$C$7:$C$501,'Rent Roll'!$T$7:$T$501) -> 1179 | AB9: =+IF(SUM(Q9:R9)>AA9,AA9,0) -> 0
A10: 31695 | B10: 43053 | C10: 2-241 | D10: Traill, Cameron Rosser | E10: (209) 596-1519 | F10: ctraill74@gmail.com | G10: Current resident | H10: 11/16/2024 | I10: RENT | J10: 0 | K10: 1249 | N10: 1249 | O10: 1249 | P10: 0 | Q10: 0 | R10: 0 | S10: 0 | T10: 0 | U10: 0 | V10: 5 | W10: 0 | X10: 03/23/2026 | AA10: =+_xlfn.XLOOKUP(C10,'Rent Roll'!$C$7:$C$501,'Rent Roll'!$T$7:$T$501) -> 1249 | AB10: =+IF(SUM(Q10:R10)>AA10,AA10,0) -> 0
I12: TOTALS | J12: 0 | K12: 10638.24 | N12: 10638.24 | O12: 8130.87 | P12: 2507.37 | Q12: 0 | R12: 0 | S12: 0 | T12: 0
A13: * -- Resident is under eviction † -- Balance due includes NSF transaction(s). Please refer to the appropriate ledger for more information ‡ -- Includes amounts that are 120+ days past due § -- Cash basis charge codes: Income account will match the AR account

Sheet Tax
F1: Address | G1: Parcel # | H1: Tax | I1: Updated
B2: Tax Details | E2: Parcel 1 | F2: 701 W Grove Pkwy Tempe, AZ 85283 | G2: 301-90-007A | H2: 196372.3 | I2: 46160
B3: =+SUM(H2:H3) -> 384207.82 | E3: Parcel 2 | F3: 7250 S Kyrene Rd Tempe, AZ 85283 | G3: 301-90-007B | H3: 187835.52 | I3: 46160

Sheet Debt Service
B2: Interest Rate Cap | C2: 0.045 | D2: =IF(C2=C3,"At-the-Money",IF(C2<C3,"In-the-Money",IF(C2>C3,"Out-of-the-Money"))) -> Out-of-the-Money
B3: SOFR | C3: 0.0368 | D3: 46022
B4: Spread | C4: 0.0235
B5: Effective Interest Rate | C5: =SUM(MIN(C3,C2),C4) -> 0.0603
B7: Current Principal Balance | C7: ='NEW OSAR'!E6 -> 92071459
B9: NOI | C9: ='NEW OSAR'!I57 -> 5953111
B10: Debt Service (w/o Cap) | C10: =C7*(C3+C4)*(365/360) -> 5629018.8
B11: Debt Service (w/Cap) | C11: =C7*C5*(365/360) -> 5629018.8
B13: DSCR (w/o Cap) | C13: =C9/C10 -> 1.0575753
B14: DSCR (w/Cap) | C14: =C9/C11 -> 1.0575753

Sheet Variance Analysis
A1: 1
C2: 3Q 2025 | G2: 4Q 2025 | K2: QoQ ∆ | O2: Cash Management
B3: Property | C3: Occupancy | D3: NOI | E3: DY | F3: DSCR | G3: Occupancy | H3: NOI | I3: DY | J3: DSCR | K3: Occupancy | L3: NOI | M3: DY | N3: DSCR | O3: In CM? | P3: Threshold
B4: Strada Apartments | C4: 0.93333333 | D4: 6115743.6 | E4: 0.066692951 | F4: 0.98803841 | G4: =#REF! -> #REF! | H4: =+#REF! -> #REF! | I4: =#REF! -> #REF! | J4: =#REF! -> #REF! | K4: =IF(G4="","-",G4-C4) -> #REF! | L4: =IF(H4="","-",H4-D4) -> #REF! | M4: =IF(I4="","-",I4-E4) -> #REF! | N4: =IF(J4="","-",J4-F4) -> #REF! | O4: No | P4: 0.07
B6: Notes:
B7: NOI adjusted per the loan agreement.
B8: DSCR inclusive of benefit from in-the-money rate cap.

Sheet Insurance
A1: 130448.95

Sheet Renovation Schedule
B2: At Close Renovations | C2: 431
B3: 06/30 Renovations | C3: 436
B4: IRE Assumed Renovations | C4: 64
B5: Total Renovations | C5: =+C4+C2 -> 495
B6: Total Units | C6: =+#REF! -> #REF! | D6: =+C6/C5 -> #REF!
B7: Renovation Start | C7: 45809
B9: Renovation Schedule | D9: =+C7+365 -> 46174 | E9: =+D9+365 -> 46539 | F9: =+E9+365 -> 46904 | G9: =+F9+365 -> 47269 | H9: =+G9+365 -> 47634 | I9: =+H9+365 -> 47999 | J9: =+I9+365 -> 48364 | K9: =+J9+365 -> 48729 | L9: =+K9+365 -> 49094 | ... O9: =+N9+365 -> 50189
D10: 1 | E10: =+D10+1 -> 2 | F10: =+E10+1 -> 3 | G10: =+F10+1 -> 4 | H10: =+G10+1 -> 5 | I10: =+H10+1 -> 6 | J10: =+I10+1 -> 7 | K10: =+J10+1 -> 8 | L10: =+K10+1 -> 9 | ... O10: =+N10+1 -> 12
B11: Non-Renovated Units
B12: Units Renovated | D12: 12 | E12: 12 | F12: 0 | G12: 0 | H12: 0 | I12: 0 | J12: 0 | K12: 0 | L12: 0 | M12: 0 | N12: 0 | O12: 0
B13: Non-Renovated Units Remaining | C13: 64 | D13: =+C13-D12 -> 52 | E13: =+D13-E12 -> 40 | F13: =+E13-F12 -> 40 | G13: =+F13-G12 -> 40 | H13: =+G13-H12 -> 40 | I13: =+H13-I12 -> 40 | J13: =+I13-J12 -> 40 | K13: =+J13-K12 -> 40 | ... O13: =+N13-O12 -> 40
B14: Completed per month | D14: =+D12/12 -> 1 | E14: =+E12/12 -> 1 | F14: =+F12/12 -> 0 | G14: =+G12/12 -> 0 | H14: =+H12/12 -> 0 | I14: =+I12/12 -> 0 | J14: =+J12/12 -> 0 | K14: =+K12/12 -> 0 | ... O14: =+O12/12 -> 0
B16: Mid-Renovated Units
B17: Units Renovated | D17: 24 | E17: 12 | F17: 0 | G17: 0 | H17: 0 | I17: 0 | J17: 0 | K17: 0 | L17: 0 | M17: 0 | N17: 0 | O17: 0
B18: Non-Renovated Units Remaining | C18: 95 | D18: =+C18-D17 -> 71 | E18: =+D18-E17 -> 59 | F18: =+E18-F17 -> 59 | G18: =+F18-G17 -> 59 | H18: =+G18-H17 -> 59 | I18: =+H18-I17 -> 59 | J18: =+I18-J17 -> 59 | K18: =+J18-K17 -> 59 | ... O18: =+N18-O17 -> 59
B19: Completed per month | D19: =+D17/12 -> 2 | E19: =+E17/12 -> 1 | F19: =+F17/12 -> 0 | G19: =+G17/12 -> 0 | H19: =+H17/12 -> 0 | I19: =+I17/12 -> 0 | J19: =+J17/12 -> 0 | K19: =+K17/12 -> 0 | ... O19: =+O17/12 -> 0

Sheet Unit Mix
A2: Knightvest Management LLC - Solano at Chapel Hill
A3: RENT ROLL DETAIL
A4: 07/26/2022 09:07 AM
A5: As of Date: 06/30/2022
A6: Parameters: Properties: - all subproperties-; Show All Unit Designations or Filter by: ALL; Subjournals: ALL; Sort by: Unit; Report Type: Details + Summary; Exclude Formers?: Yes; Show Unit Rent as: Market Rent
A7: Amt / SQFT: Market = 266,365 SQFT; Leased = 235,641 SQFT;
A8: Floorplan | B8: # Units | C8: Average SQFT | D8: Average Market Rent | E8: Market Rent Amt/SQFT | F8: Average Leased | G8: Leased Amt/SQFT | H8: Units Occupied | I8: Occupancy % | J8: Units Available
A9: A1 | B9: 9 | C9: 713 | D9: 1,300.00 | E9: 1.82 | F9: 1,296.33 | G9: 1.82 | H9: 9 | I9: 100.00 | J9: 0
A10: A1F | B10: 9 | C10: 713 | D10: 1,300.00 | E10: 1.82 | F10: 1,263.71 | G10: 1.77 | H10: 7 | I10: 77.78 | J10: 1
A11: A1Q | B11: 6 | C11: 713 | D11: 1,425.00 | E11: 2.00 | F11: 1,334.50 | G11: 1.87 | H11: 2 | I11: 33.33 | J11: 1
A12: A2 | B12: 11 | C12: 763 | D12: 1,425.00 | E12: 1.87 | F12: 1,350.73 | G12: 1.77 | H12: 11 | I12: 100.00 | J12: 0
A13: A2F | B13: 7 | C13: 763 | D13: 1,425.00 | E13: 1.87 | F13: 1,414.80 | G13: 1.85 | H13: 5 | I13: 71.43 | J13: 1
A14: A2Q | B14: 7 | C14: 763 | D14: 1,525.00 | E14: 2.00 | F14: 1,468.50 | G14: 1.92 | H14: 4 | I14: 57.14 | J14: 3
A15: A3 | B15: 6 | C15: 817 | D15: 1,450.00 | E15: 1.77 | F15: 1,343.00 | G15: 1.64 | H15: 6 | I15: 100.00 | J15: 0
A16: A3F | B16: 3 | C16: 817 | D16: 1,450.00 | E16: 1.77 | F16: 1,450.00 | G16: 1.77 | H16: 2 | I16: 66.67 | J16: 0
A17: A3Q | B17: 2 | C17: 817 | D17: 1,550.00 | E17: 1.90 | F17: 1,550.00 | G17: 1.90 | H17: 1 | I17: 50.00 | J17: 0
A18: A4 | B18: 14 | C18: 932 | D18: 1,475.00 | E18: 1.58 | F18: 1,353.71 | G18: 1.45 | H18: 14 | I18: 100.00 | J18: 0
A19: A4F | B19: 4 | C19: 932 | D19: 1,475.00 | E19: 1.58 | F19: 1,437.25 | G19: 1.54 | H19: 4 | I19: 100.00 | J19: 1
A20: A4Q | B20: 6 | C20: 932 | D20: 1,575.00 | E20: 1.69 | F20: 1,496.17 | G20: 1.61 | H20: 6 | I20: 100.00 | J20: 3
... A38: Totals / Averages: | B38: 240 | C38: 1,110 | D38: 1,661.15 | E38: 1.50 | F38: 1,602.98 | G38: 1.43 | H38: 210 | I38: 87.50 | J38: 17

Sheet Argus Comm Rollover Schedule
