Workbook
Name \0: #REF!
Name \A: #REF!
Name \A: #REF!
Name \B: #REF!
Name \B: #REF!
Name \C: #REF!
Name \D: #REF!
Name \E: #REF!
Name \g: '[1]Mixed Use'!#REF!
Name \g: '[1]Mixed Use'!#REF!
Name \H: #REF!
Name \H: #REF!
Name \I: #REF!
Name \j: #REF!
Name \L: #REF!
Name \N: #REF!
Name \o: '[1]Mixed Use'!#REF!
Name \p: #N/A
Name \s: '[1]Mixed Use'!#REF!
Name \t: #REF!
Name \x: '[1]Mixed Use'!#REF!
Name \Y: #REF!
Name \z: '[1]Mixed Use'!#REF!
Name ____________________cap104: #REF!
Name ___________________cap104: #REF!
Name ___________________LSC1: 1439078
Name ___________________LSC2: 611287
Name ___________________LSC3: 302107
Name ___________________LSE1: 201298
Name ___________________LSE2: 24644
Name ___________________LSE3: 399493
Name ___________________LSE4: 802332
Name ___________________LSE9: 604106
Name ___________________LSF1: 255134
Name ___________________LSF2: 90236
Name ___________________LSG1: 15916
Name ___________________LSK1: 10216765
Name ___________________LSK2: 97598247
Name ___________________LSK4: -75746217
Name ___________________LSM1: -289783200
Name ___________________LSM2: -23132787
Name ___________________LSP1: -426407
Name ___________________LSP2: -619666
Name ___________________LSP3: -115995
Name ___________________LSP4: -513016
Name ___________________LST1: 277494370
Name ___________________MAC2: #REF!
Name ___________________MAC3: #REF!
Name ___________________MAC4: #REF!
Name __________________cap104: #REF!
Name __________________LSC1: 1439078
Name __________________LSC2: 611287
Name __________________LSC3: 302107
Name __________________LSE1: 201298
Name __________________LSE2: 24644
Name __________________LSE3: 399493
Name __________________LSE4: 802332
Name __________________LSE9: 604106
Name __________________LSF1: 255134
Name __________________LSF2: 90236

Sheet Comm OSAR
C1: CREFC Investor Reporting Package
C2: COMMERCIAL OPERATING STATEMENT ANALYSIS REPORT (includes Retail/Office/Industrial/Mixed Use/Self Storage)
C3: ="as of " &TEXT(F6," mm/dd/yyyy") -> as of 03/31/2026
C4: PROPERTY OVERVIEW | H4: Allocated Loan Amount/Percentage
C5: Property ID | E5: 1001-001 | F5: Paid Thru Date | G5: Debt Outside Trust (1) | H5: $ | I5: %
C6: Note A-Scheduled Loan Balance | E6: 63000000 | F6: 46112 | H6: 0 | I6: 1
C7: Note B-Scheduled Loan Balance | E7: 0 | H7: 0 | I7: 0
C8: Note C-Scheduled Loan Balance | E8: 0 | H8: 0 | I8: 0
C9: Property Name | E9: The Campus at Villa La Jolla
C10: Property Type | E10: Medical Office
C11: Property Address, City, State | E11: 8950 Villa La Jolla Dr, La Jolla, CA 92037
C12: Current Net Rentable SF/Units/Beds/Rooms | E12: 191454 | F12: SF | G12: Use second box to specify sqft.,units…
C13: Year Built/Year Renovated | E13: 2018 | F13: 2025
C14: Cap Ex Reserve (annually)/per Unit.etc. (2) | E14: 0.25 | F14: PSF | G14: specify annual/per unit…
C15: Statement Ending Date | E15: Underwriting | G15: 46022 | H15: =+F6 -> 46112 | I15: =+F6 -> 46112
C16: Occupancy Rate (physical) | E16: 0.714 | G16: 0.67098943 | H16: ='Rent Roll'!B95 -> 0.68435973 | I16: =+H16 -> 0.68435973
C17: Occupancy Date | E17: 46265 | G17: 46022 | H17: =+H15 -> 46112 | I17: =+I15 -> 46112
E18: (1) "X" if debt is outside of the trust, otherwise leave blank
E19: (2) Total $ amount of Capital Reserves required annually by loan documents | N19: Vacancy factor | O19: 0.05
N20: Actual | O20: =1-I16 -> 0.31564027
C21: INCOME:
C22: Number of Mos. Covered | J22: (prcdng yr to base) | K22: (prcdng yr to 2nd prcdng)
C23: Period Ended | E23: At Contribution | F23: 3rd Preceding | G23: DY Test | H23: TTM | I23: DY Test | J23: =TEXT(H15," mm/dd/yyyy")& "-U/W" -> 03/31/2026-U/W | K23: =TEXT(G15," mm/dd/yyyy -") & TEXT(H15,"mm/dd/yyyy") -> 12/31/2025 -03/31/2026
C24: Statement Ending Date | E24: Information | G24: as of 12/31/2025 | H24: =+H17 -> 46112 | I24: ="as of" &TEXT(I15," mm/dd/yyyy") -> as of 03/31/2026 | J24: Variance | K24: Variance | L24: Notes | M24: Var $ | N24: Var %
C25: Gross Potential Rent (3) | E25: 9567046 | G25: 6673141.8 | H25: =_xlfn.XLOOKUP($C25,TTM!$T:$T,TTM!$U:$U,0) -> 0 | I25: =+'Rent Roll'!$Y$87 -> 6695002.4 | J25: =IFERROR(IF(E25=0, " ",(H25-E25)/E25),"") -> -1 | K25: =IF(G25=0, " ",(H25-G25)/G25) -> -1 | L25: ="Annualized RR as of" & TEXT($I$15," mm/dd/yyyy") & ", adjusted for free rent and KVs" -> Annualized RR as of 03/31/2026, adjusted for free rent and KVs | M25: =+IFERROR(I25-G25,"N/A") -> 21860.58 | N25: =+IFERROR(M25/G25,"N/A") -> 0.0032759052
C26: Less: Vacancy Loss | E26: -2897565 | H26: =_xlfn.XLOOKUP($C26,TTM!$T:$T,TTM!$U:$U,0) -> 0 | I26: =+IF(O20>O19,"",(O19-O20)*-I25) | J26: =IFERROR(IF(E26=0, " ",(H26-E26)/E26),"") -> -1 | K26: =IF(G26=0, " ",(H26-G26)/G26) -> #VALUE! | L26: ="Greater of Actual "&TEXT(1-I16,"(0.00%)")&" or 5.00% of GPR" -> Greater of Actual (31.56%) or 5.00% of GPR | M26: =+IFERROR(I26-G26,"N/A") -> N/A | N26: =+IFERROR(M26/G26,"N/A") -> N/A
C27: OR | H27: =_xlfn.XLOOKUP($C27,TTM!$T:$T,TTM!$U:$U,0) -> 0 | J27: =IFERROR(IF(E27=0, " ",(H27-E27)/E27),"") | K27: =IF(G27=0, " ",(H27-G27)/G27) | M27: =+IFERROR(I27-G27,"N/A") -> 0 | N27: =+IFERROR(M27/G27,"N/A") -> N/A
C28: Base Rent (3) | H28: =_xlfn.XLOOKUP($C28,TTM!$T:$T,TTM!$U:$U,0) -> 5796406.8 | J28: =IFERROR(IF(E28=0, " ",(H28-E28)/E28),"") | K28: =IF(G28=0, " ",(H28-G28)/G28) | M28: =+IFERROR(I28-G28,"N/A") -> 0 | N28: =+IFERROR(M28/G28,"N/A") -> N/A
C29: Expense Reimbursement | E29: 700149 | G29: 381795.51 | H29: =_xlfn.XLOOKUP($C29,TTM!$T:$T,TTM!$U:$U,0) -> 504137.47 | I29: ='Rent Roll'!$Z$87 -> 435812.98 | J29: =IFERROR(IF(E29=0, " ",(H29-E29)/E29),"") -> -0.27995688 | K29: =IF(G29=0, " ",(H29-G29)/G29) -> 0.32043845 | L29: ="Annualized RR as of" & TEXT($I$15," mm/dd/yyyy") -> Annualized RR as of 03/31/2026 | M29: =+IFERROR(I29-G29,"N/A") -> 54017.47 | N29: =+IFERROR(M29/G29,"N/A") -> 0.14148273
C30: Percentage Rent | G30: 0 | H30: =_xlfn.XLOOKUP($C30,TTM!$T:$T,TTM!$U:$U,0) -> 0 | I30: =_xlfn.XLOOKUP($C30,TTM!$T:$T,TTM!$U:$U,0) -> 0 | J30: =IFERROR(IF(E30=0, " ",(H30-E30)/E30),"") | K30: =IF(G30=0, " ",(H30-G30)/G30) | L30: ="TTM ended" &TEXT($I$15, " mm/dd/yyyy") -> TTM ended 03/31/2026 | M30: =+IFERROR(I30-G30,"N/A") -> 0 | N30: =+IFERROR(M30/G30,"N/A") -> N/A
C31: Parking Income | E31: 333230 | G31: 414384.19 | H31: =_xlfn.XLOOKUP($C31,TTM!$T:$T,TTM!$U:$U,0) -> 448011.03 | I31: =_xlfn.XLOOKUP($C31,TTM!$T:$T,TTM!$U:$U,0) -> 448011.03 | J31: =IFERROR(IF(E31=0, " ",(H31-E31)/E31),"") -> 0.34444987 | K31: =IF(G31=0, " ",(H31-G31)/G31) -> 0.081148945 | L31: ="TTM ended" &TEXT($I$15, " mm/dd/yyyy") -> TTM ended 03/31/2026 | M31: =+IFERROR(I31-G31,"N/A") -> 33626.84 | N31: =+IFERROR(M31/G31,"N/A") -> 0.081148945
C32: Other Income | E32: -48753 | G32: 44055.18 | H32: =_xlfn.XLOOKUP($C32,TTM!$T:$T,TTM!$U:$U,0) -> 58413.56 | I32: =_xlfn.XLOOKUP($C32,TTM!$T:$T,TTM!$U:$U,0) -> 58413.56 | J32: =IFERROR(IF(E32=0, " ",(H32-E32)/E32),"") -> -2.1981531 | K32: =IF(G32=0, " ",(H32-G32)/G32) -> 0.32591809 | L32: ="TTM ended" &TEXT($I$15, " mm/dd/yyyy") -> TTM ended 03/31/2026 | M32: =+IFERROR(I32-G32,"N/A") -> 14358.38 | N32: =+IFERROR(M32/G32,"N/A") -> 0.32591809
L33: =IF(G33=0, " ",(J33-G33)/G33)
C34: *Effective Gross Income | E34: =+SUM(E25:E32) -> 7654107 | G34: 7513376.7 | H34: =+SUM(H25:H32) -> 6806968.9 | I34: =+SUM(I25:I32) -> 7637240 | J34: =IFERROR(IF(E34=0, " ",(H34-E34)/E34),"") -> -0.11067759 | K34: =IF(G34=0, " ",(H34-G34)/G34) -> -0.094020015 | M34: =+IFERROR(I34-G34,"N/A") -> 123863.27 | N34: =+IFERROR(M34/G34,"N/A") -> 0.016485699
E35: (3) Use either Gross Potential (with Vacancy Loss) or Base Rents; use negative $amt for Vacancy Loss
L36: =IF(G36=0, " ",(J36-G36)/G36)
C37: OPERATING EXPENSES: | L37: =IF(G37=0, " ",(J37-G37)/G37)
C38: Real Estate Taxes | E38: 915368 | G38: 1038275.6 | H38: =_xlfn.XLOOKUP($C38,TTM!$T:$T,TTM!$U:$U,0) -> 1032690.2 | I38: =+MAX(H38,Tax!$D$6) -> 1038275.6 | J38: =IFERROR(IF(E38=0, " ",(H38-E38)/E38),"") -> 0.12816946 | K38: =IF(G38=0, " ",(H38-G38)/G38) -> -0.0053795156 | L38: ="Greater of actual tax bill from " & TEXT(Tax!$B$8,"mm/d/yyyy") & "-" & TEXT(Tax!$B$9,"mm/d/yyyy") & " (" & TEXT(Tax!$D$6/1000000,"$0.0""MM""") & ") and TTM ended " & TEXT($I$15,"mm/d/yyyy") -> Greater of actual tax bill from 07/1/2025-06/30/2026 ($1.0MM) and TTM ended 03/31/2026 | M38: =+IFERROR(I38-G38,"N/A") -> 0 | N38: =+IFERROR(M38/G38,"N/A") -> 0
C39: Property Insurance | E39: 185337 | G39: 189226.62 | H39: =_xlfn.XLOOKUP($C39,TTM!$T:$T,TTM!$U:$U,0) -> 191090.61 | I39: =+MAX(H39,Insurance!R9) -> 191090.61 | J39: =IFERROR(IF(E39=0, " ",(H39-E39)/E39),"") -> 0.031044044 | K39: =IF(G39=0, " ",(H39-G39)/G39) -> 0.0098505697 | L39: ="Greater of Actual insurance premium from 5/17/2025 - 5/17/2026 "&TEXT(Insurance!R9/1000,"($0.0K)")&" and TTM ended "&TEXT($I$15,"mm/dd/yyyy") -> Greater of Actual insurance premium from 5/17/2025 - 5/17/2026 ($187.0K) and TTM ended 03/31/2026 | M39: =+IFERROR(I39-G39,"N/A") -> 1863.99 | N39: =+IFERROR(M39/G39,"N/A") -> 0.0098505697
C40: Utilities | E40: 529032 | G40: 616358.64 | H40: =_xlfn.XLOOKUP($C40,TTM!$T:$T,TTM!$U:$U,0) -> 663763.62 | I40: =+H40 -> 663763.62 | J40: =IFERROR(IF(E40=0, " ",(H40-E40)/E40),"") -> 0.25467575 | K40: =IF(G40=0, " ",(H40-G40)/G40) -> 0.076911358 | L40: ="TTM ended" &TEXT($I$15, " mm/dd/yyyy") -> TTM ended 03/31/2026 | M40: =+IFERROR(I40-G40,"N/A") -> 47404.98 | N40: =+IFERROR(M40/G40,"N/A") -> 0.076911358
C41: Repairs and Maintenance | E41: 366300 | G41: 507856.18 | H41: =_xlfn.XLOOKUP($C41,TTM!$T:$T,TTM!$U:$U,0) -> 477146.7 | I41: =+H41 -> 477146.7 | J41: =IFERROR(IF(E41=0, " ",(H41-E41)/E41),"") -> 0.30261179 | K41: =IF(G41=0, " ",(H41-G41)/G41) -> -0.060468852 | L41: ="TTM ended" &TEXT($I$15, " mm/dd/yyyy") -> TTM ended 03/31/2026 | M41: =+IFERROR(I41-G41,"N/A") -> -30709.48 | N41: =+IFERROR(M41/G41,"N/A") -> -0.060468852
C42: Janitorial | E42: 305250 | G42: 275372.32 | H42: =_xlfn.XLOOKUP($C42,TTM!$T:$T,TTM!$U:$U,0) -> 275362.38 | I42: =+H42 -> 275362.38 | J42: =IFERROR(IF(E42=0, " ",(H42-E42)/E42),"") -> -0.097911941 | K42: =IF(G42=0, " ",(H42-G42)/G42) -> -3.6096584e-05 | L42: ="TTM ended" &TEXT($I$15, " mm/dd/yyyy") -> TTM ended 03/31/2026 | M42: =+IFERROR(I42-G42,"N/A") -> -9.94 | N42: =+IFERROR(M42/G42,"N/A") -> -3.6096584e-05
C43: Management Fees | E43: 229623 | G43: 225401.3 | H43: =_xlfn.XLOOKUP($C43,TTM!$T:$T,TTM!$U:$U,0) -> 111110.94 | I43: =+MAX(H43,0.03*I34) -> 229117.2 | J43: =IFERROR(IF(E43=0, " ",(H43-E43)/E43),"") -> -0.51611581 | K43: =IF(G43=0, " ",(H43-G43)/G43) -> -0.5070528 | L43: ="Greater of Actual "&TEXT(TTM!U24/1000,"($###.#K)")&" or 3.00% of EGI" -> Greater of Actual ($111.1K) or 3.00% of EGI | M43: =+IFERROR(I43-G43,"N/A") -> 3715.8981 | N43: =+IFERROR(M43/G43,"N/A") -> 0.016485699
C44: Payroll & Benefits | E44: 358499 | G44: 416599.89 | H44: =_xlfn.XLOOKUP($C44,TTM!$T:$T,TTM!$U:$U,0) -> 434643.21 | I44: =+H44 -> 434643.21 | J44: =IFERROR(IF(E44=0, " ",(H44-E44)/E44),"") -> 0.21239727 | K44: =IF(G44=0, " ",(H44-G44)/G44) -> 0.043310909 | L44: ="TTM ended" &TEXT($I$15, " mm/dd/yyyy") -> TTM ended 03/31/2026 | M44: =+IFERROR(I44-G44,"N/A") -> 18043.32 | N44: =+IFERROR(M44/G44,"N/A") -> 0.043310909
C45: Advertising & Marketing | E45: 0 | G45: 6290.29 | H45: =_xlfn.XLOOKUP($C45,TTM!$T:$T,TTM!$U:$U,0) -> 7395.28 | I45: =+H45 -> 7395.28 | J45: =IFERROR(IF(E45=0, " ",(H45-E45)/E45),"") | K45: =IF(G45=0, " ",(H45-G45)/G45) -> 0.17566599 | L45: ="TTM ended" &TEXT($I$15, " mm/dd/yyyy") -> TTM ended 03/31/2026 | M45: =+IFERROR(I45-G45,"N/A") -> 1104.99 | N45: =+IFERROR(M45/G45,"N/A") -> 0.17566599
C46: Professional Fees | E46: 235046 | G46: 215728.76 | H46: =_xlfn.XLOOKUP($C46,TTM!$T:$T,TTM!$U:$U,0) -> 201585.86 | I46: =+H46 -> 201585.86 | J46: =IFERROR(IF(E46=0, " ",(H46-E46)/E46),"") -> -0.14235571 | K46: =IF(G46=0, " ",(H46-G46)/G46) -> -0.065558714 | L46: ="TTM ended" &TEXT($I$15, " mm/dd/yyyy") -> TTM ended 03/31/2026 | M46: =+IFERROR(I46-G46,"N/A") -> -14142.9 | N46: =+IFERROR(M46/G46,"N/A") -> -0.065558714
C47: General and Administrative | E47: 61820 | G47: 57292.11 | H47: =_xlfn.XLOOKUP($C47,TTM!$T:$T,TTM!$U:$U,0) -> 59576.01 | I47: =+H47 -> 59576.01 | J47: =IFERROR(IF(E47=0, " ",(H47-E47)/E47),"") -> -0.036298771 | K47: =IF(G47=0, " ",(H47-G47)/G47) -> 0.039864128 | L47: ="TTM ended" &TEXT($I$15, " mm/dd/yyyy") -> TTM ended 03/31/2026 | M47: =+IFERROR(I47-G47,"N/A") -> 2283.9 | N47: =+IFERROR(M47/G47,"N/A") -> 0.039864128
C48: Other Expenses | E48: 186206 | G48: 182600.79 | H48: =_xlfn.XLOOKUP($C48,TTM!$T:$T,TTM!$U:$U,0) -> 186986.3 | I48: =+H48 -> 186986.3 | J48: =IFERROR(IF(E48=0, " ",(H48-E48)/E48),"") -> 0.0041905202 | K48: =IF(G48=0, " ",(H48-G48)/G48) -> 0.024016928 | L48: ="TTM ended" &TEXT($I$15, " mm/dd/yyyy") -> TTM ended 03/31/2026 | M48: =+IFERROR(I48-G48,"N/A") -> 4385.51 | N48: =+IFERROR(M48/G48,"N/A") -> 0.024016928
C49: Ground Rent | E49: 0 | G49: 0 | H49: =_xlfn.XLOOKUP($C49,TTM!$T:$T,TTM!$U:$U,0) -> 0 | I49: =_xlfn.XLOOKUP($C49,TTM!$T:$T,TTM!$U:$U,0) -> 0 | J49: =IFERROR(IF(E49=0, " ",(H49-E49)/E49),"") | K49: =IF(G49=0, " ",(H49-G49)/G49) | L49: ="TTM ended" &TEXT($I$15, " mm/dd/yyyy") -> TTM ended 03/31/2026 | M49: =+IFERROR(I49-G49,"N/A") -> 0 | N49: =+IFERROR(M49/G49,"N/A") -> N/A
C50: *Total Operating Expenses | E50: =+SUM(E38:E49) -> 3372481 | G50: 3731002.5 | H50: =+SUM(H38:H49) -> 3641351.1 | I50: =+SUM(I38:I49) -> 3764942.8 | M50: =+IFERROR(I50-G50,"N/A") -> 33940.268 | N50: =+IFERROR(M50/G50,"N/A") -> 0.0090968226
C52: Operating Expense Ratio | E52: =+E50/E34 -> 0.44061064 | G52: 0.49658132 | H52: =+H50/H34 -> 0.53494458 | I52: =+I50/I34 -> 0.49297165
C54: *Net Operating Income | E54: =+E34-E50 -> 4281626 | G54: 3782374.1 | H54: =+H34-H50 -> 3165617.8 | I54: =+I34-I50 -> 3872297.1 | M54: =+IFERROR(I54-G54,"N/A") -> 89923.002 | N54: =+IFERROR(M54/G54,"N/A") -> 0.023774222
C56: Leasing Commissions | E56: 688800 | H56: =_xlfn.XLOOKUP($C56,TTM!$T:$T,TTM!$U:$U,0) -> 0
C57: Tenant Improvements | E57: 2437568 | H57: =_xlfn.XLOOKUP($C57,TTM!$T:$T,TTM!$U:$U,0) -> 0
C58: Capital Expenditures | E58: 47004 | G58: 47863.5 | H58: =_xlfn.XLOOKUP($C58,TTM!$T:$T,TTM!$U:$U,0) -> 0 | I58: =+L58*E12 -> 47863.5 | L58: 0.25
C59: Extraordinary Capital Expenditures
C60: Total Capital Items | E60: =+SUM(E56:E59) -> 3173372 | G60: 47863.5 | H60: =+SUM(H56:H58) -> 0 | I60: =+SUM(I56:I59) -> 47863.5
C62: *Net Cash Flow | E62: =+E54-E60 -> 1108254 | G62: 3734510.6 | H62: =+H54-H60 -> 3165617.8 | I62: =+I54-I60 -> 3824433.6
C64: Debt Service - A Note | G64: 4322159.4 | H64: =+TTM!U37 -> 4904625.8 | I64: =+DS!M16 -> 4254075 | L64: =IF(H64=0, " ",(I64-H64)/H64) -> -0.13264025
C65: Debt Service - B Note
C66: Debt Service - C Note | L66: =IF(H66=0, " ",(I66-H66)/H66)
C68: *Net Cash Flow after Debt Service | G68: -587648.72 | H68: =+H62-H64 -> -1739008 | I68: =+I62-I64 -> -429641.36
C70: *DSCR: (NOI/Debt Service) - A Note | G70: 0.87511214 | H70: =H54/H64 -> 0.64543512 | I70: =I54/I64 -> 0.91025596 | L70: =IF(H70=0, " ",(I70-H70)/H70) -> 0.41029816
C71: *DSCR: (NOI/Debt Service) - A & B Note
C72: *DSCR: (NOI/Debt Service) - A, B & C Note
C74: *DSCR: (NCF/Debt Service) - A Note | G74: 0.86403816 | H74: =H62/H64 -> 0.64543512 | I74: =I62/I64 -> 0.89900475
C75: *DSCR: (NCF/Debt Service) - A & B Note
C76: *DSCR: (NCF/Debt Service) - A, B & C Note
C78: Debt Yield (NCF/UPB) | G78: 0.059277947 | I78: =+I62/E6 -> 0.060705296
C80: Source of Financial Data:
E81: (ie. operating statements, financial statements, tax return, other)
C82: Notes and Assumptions: Years above will roll, always showing a 3yr sequential history. Comments from the most recent NOI Adjustment Worksheet should be carried forward to Operating Statement
C83: Analysis Report. Year-over-year variances (either higher or lower) must be explained and noted for the following: >20% DSCR change, >20% EGI/Total Operating Expenses or Total Capital
C84: Items. Quarterly variance comments may be necessary if the loan is on the Watch List.
C85: Income: Comments
C88: Expense: Comments
C91: Capital Items: Comments
C94: DSCR: Comments
C97: * Used in the CREFC Comparative Financial Status Report/CREFC Property File/CREFC Loan Periodic Update File. Note that information for multiple property loans must be consolidated (if available)
C98: for reporting to the CREFC Loan Periodic Update file.

Sheet DS
L1: Previous | M1: Current
L2: 46022 | M2: =+'Comm OSAR'!I15 -> 46112
C3: UPB | L3: 63000000 | M3: =+'Comm OSAR'!E6 -> 63000000
C4: Occupancy | L4: 0.67098943 | M4: =+'Comm OSAR'!I16 -> 0.68435973
C6: Rate Cap | L6: 0.05 | M6: 0.05
C7: SOFR | L7: 0.0378659 | M7: 0.0368
C8: Spread | L8: 0.0298 | M8: 0.0298
C10: Effective Interest Rate | L10: 0.0676659 | M10: =+SUM(M7:M8) -> 0.0666
C11: Effective Capped Interest Rate | L11: 0.0676659 | M11: =+MIN(M6,M7)+M8 -> 0.0666
C13: Net Cash Flow | L13: 3734510.6 | M13: =+'Comm OSAR'!I62 -> 3824433.6
C15: Debt Service (Excluding Rate Cap) | L15: 4322159.4 | M15: =+M10*$M$3*(365/360) -> 4254075
C16: Debt Service (Including Rate Cap) | L16: 4322159.4 | M16: =+M11*$M$3*(365/360) -> 4254075
C18: DSCR (Excluding Rate Cap) | L18: 0.86403816 | M18: =+$M$13/M15 -> 0.89900475
C19: DSCR (Including Rate Cap) | L19: 0.86403816 | M19: =+$M$13/M16 -> 0.89900475
C21: DY | L21: 0.059277947 | M21: =M13/M3 -> 0.060705296

Sheet OSAR
A1: 1
B2: CREFC Investor Reporting Package
B3: COMMERCIAL OPERATING STATEMENT ANALYSIS REPORT
B4: 46022
B5: PROPERTY OVERVIEW | F5: Allocated Loan Amount/Percentage
B6: THE RESERVE | D6: Paid Thru Date | E6: Debt Outside Trust (1) | F6: $ | G6: %
B7: Note A-Scheduled Loan Balance | C7: 63000000 | D7: =+B4 -> 46022 | G7: 1
B8: Property Name | C8: The Campus at Villa La Jolla
B9: Property Type | C9: Medical Office
B10: Property Address, City, State
B11: Current Net Rentable SF/Units/Beds/Rooms | C11: 191454
B12: Year Built/Year Renovated | C12: 2018/2018
B13: CapEx Reserve (annually)/per Unit.etc. | C13: 0.25
B14: Statement Ending Date | C14: Underwriting | G14: =B4 -> 46022 | H14: =G14 -> 46022
B15: Occupancy Rate (physical) | C15: =1-0.286 -> 0.714 | G15: ='Rent Roll'!B95 -> 0.68435973 | H15: =G15 -> 0.68435973
B16: Occupancy Date | C16: 46265 | G16: =G14 -> 46022 | H16: =G16 -> 46022
K18: Vacancy Factor | L18: 0.05
G20: T12 | H20: DY Test | K20: DY Test | L20: DY Test
B21: INCOME | C21: At Contribution | G21: =$G$14 -> 46022 | H21: =$G$14 -> 46022 | I21: Notes | K21: QoQ | L21: QoQ (%)
B22: Gross Potential Rent | C22: 9567046 | G22: =+TTM!U10 -> 5796406.8 | H22: ='Rent Roll'!Y87 -> 6695002.4 | I22: ="Annualized RR as of" & TEXT($D$7," mm/dd/yyyy") & ", adjusted for free rent and KVs" -> Annualized RR as of 12/31/2025, adjusted for free rent and KVs
B23: Less: Vacancy Loss | C23: -2897565 | H23: =IF(H15<(1-L18),0,-(H15-(1-L18))*H22) -> 0 | I23: ="Greater of Actual "&TEXT(1-$H$15,"(0.00%)")&" or 5.00% of GPR" -> Greater of Actual (31.56%) or 5.00% of GPR
B24: OR
B25: Base Rent | K25: =H25-F25 -> 0 | L25: =+IFERROR(K25/F25," - ") -> -
B26: Expense Reimbursement | C26: 700149 | G26: =_xlfn.XLOOKUP($B26,TTM!$T:$T,TTM!$U:$U,0) -> 0 | H26: ='Rent Roll'!Z87 -> 435812.98 | I26: ="Annualized RR as of" & TEXT($D$7," mm/dd/yyyy") -> Annualized RR as of 12/31/2025 | K26: =H26-F26 -> 435812.98 | L26: =+IFERROR(K26/F26," - ") -> -
B27: Percentage Rent | G27: =_xlfn.XLOOKUP($B27,TTM!$T:$T,TTM!$U:$U,0) -> 0 | H27: 0 | I27: ="T12 ended" &TEXT($D$7, " mm/dd/yyyy") -> T12 ended 12/31/2025 | K27: =H27-F27 -> 0 | L27: =+IFERROR(K27/F27," - ") -> -
B28: Parking Income | C28: 333230 | G28: =_xlfn.XLOOKUP($B28,TTM!$T:$T,TTM!$U:$U,0) -> 0 | H28: =G28 -> 0 | I28: ="T12 ended" &TEXT($D$7, " mm/dd/yyyy") -> T12 ended 12/31/2025 | K28: =H28-F28 -> 0 | L28: =+IFERROR(K28/F28," - ") -> -
B29: Other Income | C29: -48753 | G29: =_xlfn.XLOOKUP($B29,TTM!$T:$T,TTM!$U:$U,0) -> 0 | H29: =+G29 -> 0 | I29: ="T12 ended" &TEXT($D$7, " mm/dd/yyyy") -> T12 ended 12/31/2025 | K29: =H29-F29 -> 0 | L29: =+IFERROR(K29/F29," - ") -> -
B31: Effective Gross Income | C31: 7654107 | G31: =SUM(G22:G30) -> 5796406.8 | H31: =SUM(H22:H29) -> 7130815.4 | K31: =H31-F31 -> 7130815.4 | L31: =+IFERROR(K31/F31," - ") -> -
B33: OPERATING EXPENSES
B34: Real Estate Taxes | C34: 915368 | G34: =_xlfn.XLOOKUP($B34,TTM!$T:$T,TTM!$U:$U,0) -> 0 | H34: =+MAX(G34,Tax!$D$6) -> 1038275.6 | I34: ="Greater of Actual "&TEXT(Tax!$D$6/1000,"($0.0K)")&" T12 ended "&TEXT($D$7,"mm/dd/yyyy") -> Greater of Actual ($1038.3K) T12 ended 12/31/2025 | K34: =H34-F34 -> 1038275.6 | L34: =+IFERROR(K34/F34," - ") -> -
B35: Property Insurance | C35: 185337 | G35: =_xlfn.XLOOKUP($B35,TTM!$T:$T,TTM!$U:$U,0) -> 0 | H35: =MAX(G35,Insurance!R9) -> 186983.74 | I35: ="Greater of Actual "&TEXT(Insurance!R9/1000,"($0.0K)")&" T12 ended "&TEXT($D$7,"mm/dd/yyyy") -> Greater of Actual ($187.0K) T12 ended 12/31/2025 | K35: =H35-F35 -> 186983.74 | L35: =+IFERROR(K35/F35," - ") -> -
B36: Utilities | C36: 529032 | G36: =_xlfn.XLOOKUP($B36,TTM!$T:$T,TTM!$U:$U,0) -> 0 | H36: =G36 -> 0 | I36: ="T12 ended" &TEXT($D$7, " mm/dd/yyyy") -> T12 ended 12/31/2025 | K36: =H36-F36 -> 0 | L36: =+IFERROR(K36/F36," - ") -> -
B37: Repairs & Maintenance | C37: 366300 | G37: =_xlfn.XLOOKUP($B37,TTM!$T:$T,TTM!$U:$U,0) -> 0 | H37: =G37 -> 0 | I37: ="T12 ended" &TEXT($D$7, " mm/dd/yyyy") -> T12 ended 12/31/2025 | K37: =H37-F37 -> 0 | L37: =+IFERROR(K37/F37," - ") -> -
B38: Janitorial | C38: 305250 | G38: =_xlfn.XLOOKUP($B38,TTM!$T:$T,TTM!$U:$U,0) -> 0 | H38: =G38 -> 0 | I38: ="T12 ended" &TEXT($D$7, " mm/dd/yyyy") -> T12 ended 12/31/2025 | K38: =H38-F38 -> 0 | L38: =+IFERROR(K38/F38," - ") -> -
B39: Management Fees | C39: 229623 | G39: =_xlfn.XLOOKUP($B39,TTM!$T:$T,TTM!$U:$U,0) -> 0 | H39: =MAX(G39,H31*0.03) -> 213924.46 | I39: ="Greater of Actual "&TEXT(G39/1000,"($###.#K)")&" or 3.00% of EGI" -> Greater of Actual ($.K) or 3.00% of EGI | K39: =H39-F39 -> 213924.46 | L39: =+IFERROR(K39/F39," - ") -> -
B40: Payroll & Benefits | C40: 358499 | G40: =_xlfn.XLOOKUP($B40,TTM!$T:$T,TTM!$U:$U,0) -> 0 | H40: =G40 -> 0 | I40: ="T12 ended" &TEXT($D$7, " mm/dd/yyyy") -> T12 ended 12/31/2025 | K40: =H40-F40 -> 0 | L40: =+IFERROR(K40/F40," - ") -> -
B41: Advertising & Marketing | C41: 0 | G41: =_xlfn.XLOOKUP($B41,TTM!$T:$T,TTM!$U:$U,0) -> 0 | H41: =G41 -> 0 | I41: ="T12 ended" &TEXT($D$7, " mm/dd/yyyy") -> T12 ended 12/31/2025 | K41: =H41-F41 -> 0 | L41: =+IFERROR(K41/F41," - ") -> -
B42: Professional Fees | C42: 235046 | G42: =_xlfn.XLOOKUP($B42,TTM!$T:$T,TTM!$U:$U,0) -> 0 | H42: =G42 -> 0 | I42: ="T12 ended" &TEXT($D$7, " mm/dd/yyyy") -> T12 ended 12/31/2025 | K42: =H42-F42 -> 0 | L42: =+IFERROR(K42/F42," - ") -> -
B43: General and Administrative | C43: 61820 | G43: =_xlfn.XLOOKUP($B43,TTM!$T:$T,TTM!$U:$U,0) -> 0 | H43: =G43 -> 0 | I43: ="T12 ended" &TEXT($D$7, " mm/dd/yyyy") -> T12 ended 12/31/2025 | K43: =H43-F43 -> 0 | L43: =+IFERROR(K43/F43," - ") -> -
B44: Other Expenses | C44: 186206 | G44: =_xlfn.XLOOKUP($B44,TTM!$T:$T,TTM!$U:$U,0) -> 0 | H44: =G44 -> 0 | I44: ="T12 ended" &TEXT($D$7, " mm/dd/yyyy") -> T12 ended 12/31/2025 | K44: =H44-F44 -> 0 | L44: =+IFERROR(K44/F44," - ") -> -
B45: Ground Rent | C45: 0 | G45: =_xlfn.XLOOKUP($B45,TTM!$T:$T,TTM!$U:$U,0) -> 0 | H45: 0 | I45: ="T12 ended" &TEXT($D$7, " mm/dd/yyyy") -> T12 ended 12/31/2025 | K45: =H45-F45 -> 0 | L45: =+IFERROR(K45/F45," - ") -> -
B46: Total Operating Expenses | C46: 3372481 | G46: =SUM(G34:G45) -> 0 | H46: =SUM(H34:H44) -> 1439183.8 | K46: =H46-F46 -> 1439183.8 | L46: =+IFERROR(K46/F46," - ") -> -
B48: Operating Expense Ratio | C48: 0.44061064 | G48: =G46/G31 -> 0 | H48: =H46/H31 -> 0.20182599 | K48: =H48-F48 -> 0.20182599
B50: Net Operating Income | C50: 4281626 | G50: =G31-G46 -> 5796406.8 | H50: =H31-H46 -> 5691631.5 | K50: =H50-F50 -> 5691631.5 | L50: =+IFERROR(K50/F50," - ") -> -
B52: Leasing Commissions | C52: 688800 | G52: 0 | H52: 0 | K52: =H52-F52 -> 0 | L52: =+IFERROR(K52/F52," - ") -> -
B53: Tenant Improvements | C53: 2437568 | G53: 0 | H53: 0 | K53: =H53-F53 -> 0 | L53: =+IFERROR(K53/F53," - ") -> -
B54: Capital Expenditures | C54: 47004 | G54: 0 | H54: =$C$13*C11 -> 47863.5 | I54: 0.25 | K54: =H54-F54 -> 47863.5 | L54: =+IFERROR(K54/F54," - ") -> -
B55: Extraordinary Capital Expenditures | K55: =H55-F55 -> 0 | L55: =+IFERROR(K55/F55," - ") -> -
B56: Total Capital Items | C56: 3173372 | G56: 0 | H56: =SUM(H52:H55) -> 47863.5 | K56: =H56-F56 -> 47863.5 | L56: =+IFERROR(K56/F56," - ") -> -
B58: Net Cash Flow | C58: 1108254 | G58: =G50-G56 -> 5796406.8 | H58: =H50-H56 -> 5643768 | K58: =H58-F58 -> 5643768 | L58: =+IFERROR(K58/F58," - ") -> -
B60: Debt Service | G60: =_xlfn.XLOOKUP($B60,TTM!$T:$T,TTM!$U:$U,0) -> 4904625.8 | H60: =MIN(H79:H80) -> 4322159.4 | I60: (Min. of Rate Cap and SOFR + Spread) * UPB * 365/360 | K60: =H60-F60 -> 4322159.4 | L60: =+IFERROR(K60/F60," - ") -> -
B62: Net Cash Flow after Debt Service | G62: =G58-G60 -> 891781.02 | H62: =H58-H60 -> 1321608.7 | K62: =H62-F62 -> 1321608.7 | L62: =+IFERROR(K62/F62," - ") -> -
B64: DSCR: (NCF/Debt Service) | G64: =G58/G60 -> 1.1818245 | H64: =+H58/H60 -> 1.3057751 | I64: Includes the benefit of the rate cap | K64: =H64-F64 -> 1.3057751
B66: Debt Yield: (NCF/Outstanding Principal) | G66: =G58/$C$7 -> 0.092006458 | H66: =H58/$C$7 -> 0.089583619 | I66: 0.05 | K66: =H66-F66 -> 0.089583619
B68: Notes and Assumptions:
B71: UPB | H71: =+C7 -> 63000000 | K71: =H71-F71 -> 63000000 | L71: =+IFERROR(K71/F71," - ") -> -
B73: SOFR | H73: 0.0378659 | I73: ="SOFR as of" &TEXT(D7," mm/dd/yyyy") -> SOFR as of 12/31/2025 | K73: =H73-F73 -> 0.0378659
B74: Spread | H74: 0.0298 | K74: =H74-F74 -> 0.0298
B75: Uncapped Interest Rate | H75: =+SUM(H73:H74) -> 0.0676659 | I75: SOFR + Spread | K75: =H75-F75 -> 0.0676659
B76: Rate Cap Strike Price | H76: 0.05 | K76: =H76-F76 -> 0.05
B77: Capped Interest Rate | H77: =+IF(H73>H76,MIN(H73,H76)+H74,H75) -> 0.0676659 | I77: Min. of Rate Cap and SOFR + Spread | K77: =H77-F77 -> 0.0676659
B79: Uncapped Debt Service | H79: =+H71*H75*365/360 -> 4322159.4 | I79: Based on Act/360 | K79: =H79-F79 -> 4322159.4 | L79: =+IFERROR(K79/F79," - ") -> -
B80: Capped Debt Service | H80: =+H71*H77*365/360 -> 4322159.4 | I80: Based on Act/360 | K80: =H80-F80 -> 4322159.4 | L80: =+IFERROR(K80/F80," - ") -> -
B82: DSCR (w/o Rate Cap) | H82: =+H$58/H79 -> 1.3057751 | K82: =H82-F82 -> 1.3057751
B83: DSCR (with Rate Cap) | H83: =+H$58/H80 -> 1.3057751 | K83: =H83-F83 -> 1.3057751
G87: Post-mod UPB | H87: =60000000+3835000+17012524 -> 80847524
G88: Post-mod DY | H88: =H58/H87 -> 0.069807556

Sheet QoQ
A1: 1
D2: 4Q 2025 | H2: 1Q 2026 | L2: QoQ ∆ | P2: Cash Management
C3: Property | D3: Occupancy | E3: NOI | F3: DY | G3: DSCR | H3: Occupancy | I3: NOI | J3: DY | K3: DSCR | L3: Occupancy | M3: NOI | N3: DY | O3: DSCR | P3: In CM? | Q3: Threshold
C4: The Campus on Villa La Jolla | D4: 0.67098943 | E4: 3734510.6 | F4: 0.059277947 | G4: 0.86403816 | H4: ='Comm OSAR'!I16 -> 0.68435973 | I4: =+'Comm OSAR'!I62 -> 3824433.6 | J4: =+DS!M21 -> 0.060705296 | K4: =+DS!M19 -> 0.89900475 | L4: =IF(H4="","-",H4-D4) -> 0.013370296 | M4: =IF(I4="","-",I4-E4) -> 89923.002 | N4: =IF(J4="","-",J4-F4) -> 0.0014273492 | O4: =IF(K4="","-",K4-G4) -> 0.034966588 | P4: No | Q4: 0.055
C6: Notes:
C7: NOI adjusted per the Loan Agreement.
C8: DSCR includes the benefit of the rate cap.
C9: Performance remained flat QoQ.

Sheet TTM
A1: Ocotillo SD VillaLaJolla, LLC (a01030)
A2: Statement (12 months)
A3: Period = Apr 2025-Mar 2026
A4: Book = Accrual
C5: Apr 2025 | D5: May 2025 | E5: Jun 2025 | F5: Jul 2025 | G5: Aug 2025 | H5: Sep 2025 | I5: Oct 2025 | J5: Nov 2025 | K5: Dec 2025 | L5: Jan 2026 | M5: Feb 2026 | N5: Mar 2026 | O5: Total | Q5: Expense Category
A6: 4000-0000 | B6: INCOME | U6: =+'Comm OSAR'!F6 -> 46112 | V6: 46022
A7: 4002-0000 | B7: OPERATING REVENUE | U7: Current | V7: Prior
A8: 4003-0000 | B8: TENANT RENTS & SERVICES | T8: Line Item | U8: T12 Total | V8: T12 Total
A9: 4100-0000 | B9: OFFICE
A10: 4110-0000 | B10: Rent-Office | C10: 521739.2 | D10: 529051.3 | E10: 531023.73 | F10: 526271.3 | G10: 530117.07 | H10: 526728.34 | I10: 534666.46 | J10: 539426.81 | K10: 552216.53 | L10: 569474.28 | M10: 578337.56 | N10: 581867.15 | O10: 6520919.7 | Q10: =_xlfn.XLOOKUP($B10,coding!$A:$A,coding!$C:$C,"") -> Base Rent (3) | T10: Base Rent (3) | U10: =SUMIF($Q:$Q,T10,$O:$O) -> 5796406.8 | V10: 5799465
A11: 4125-0000 | B11: Rent-Office Parking | C11: 21375.47 | D11: 23025.31 | E11: 27995.14 | F11: 28798.34 | G11: 27361.77 | H11: 21583.11 | I11: 19678.4 | J11: 143443.58 | K11: 31252.83 | L11: 32028.81 | M11: 24555.74 | N11: 46912.53 | O11: 448011.03 | Q11: =_xlfn.XLOOKUP($B11,coding!$A:$A,coding!$C:$C,"") -> Parking Income | T11: Expense Reimbursement | U11: =SUMIF($Q:$Q,T11,$O:$O) -> 504137.47 | V11: 569922.03
A12: 4130-0000 | B12: Rent Abatement-Office | C12: -21738.04 | D12: -21910.6 | E12: -28167.4 | F12: -36532.48 | G12: -51621.2 | H12: -20268.7 | I12: -95323.43 | J12: -91901.35 | K12: -88203.85 | L12: -104449.45 | M12: -115819.95 | N12: -48576.45 | O12: -724512.9 | Q12: =_xlfn.XLOOKUP($B12,coding!$A:$A,coding!$C:$C,"") -> Base Rent (3) | T12: Percentage Rent | U12: =SUMIF($Q:$Q,T12,$O:$O) -> 0 | V12: 0
A13: 4190-0000 | B13: TOTAL OFFICE | C13: 521376.63 | D13: 530166.01 | E13: 530851.47 | F13: 518537.16 | G13: 505857.64 | H13: 528042.75 | I13: 459021.43 | J13: 590969.04 | K13: 495265.51 | L13: 497053.64 | M13: 487073.35 | N13: 580203.23 | O13: 6244417.9 | Q13: =_xlfn.XLOOKUP($B13,coding!$A:$A,coding!$C:$C,"") -> 0 | T13: Parking Income | U13: =SUMIF($Q:$Q,T13,$O:$O) -> 448011.03 | V13: 414384.19
A14: 4400-0000 | B14: RESIDENTIAL | Q14: =_xlfn.XLOOKUP($B14,coding!$A:$A,coding!$C:$C,"") -> 0 | T14: Other Income | U14: =SUMIF($Q:$Q,T14,$O:$O) -> 58413.56 | V14: 44055.18
A15: 4700-0000 | B15: REIMBURSABLE EXPENSES | Q15: =_xlfn.XLOOKUP($B15,coding!$A:$A,coding!$C:$C,"") -> 0
A16: 4705-0000 | B16: CAM Recovery-Estimate | C16: 51383.77 | D16: 52748.84 | E16: 52748.84 | F16: 51402.76 | G16: 51254.99 | H16: 32311.27 | I16: 32311.27 | J16: 32311.27 | K16: 32311.27 | L16: 37866.81 | M16: 37568.54 | N16: 37568.54 | O16: 501788.17 | Q16: =_xlfn.XLOOKUP($B16,coding!$A:$A,coding!$C:$C,"") -> Expense Reimbursement | T16: Effective Gross Income | U16: =SUM(U10:U15) -> 6806968.9 | V16: 6827826.4
A17: 4710-0000 | B17: CAM Recovery-Y/End | C17: 0 | D17: 0 | E17: -181768.85 | F17: 118289.6 | G17: 0 | H17: 0 | I17: -10567.33 | J17: 0 | K17: 0 | L17: 0 | M17: 0 | N17: 0 | O17: -74046.58 | Q17: =_xlfn.XLOOKUP($B17,coding!$A:$A,coding!$C:$C,"") -> Expense Reimbursement
A18: 4745-0000 | B18: Utilities Recovery-Estimate | C18: 4381.83 | D18: 4033.14 | E18: 4601.54 | F18: 3209.21 | G18: 5661.65 | H18: 3344.98 | I18: 4811.78 | J18: 5982.63 | K18: 183.88 | L18: -671.13 | M18: 507.63 | N18: 340 | O18: 36387.14 | Q18: =_xlfn.XLOOKUP($B18,coding!$A:$A,coding!$C:$C,"") -> Expense Reimbursement | T18: OPERATING EXPENSES
A19: 4760-0000 | B19: Misc Income | C19: 18642.49 | D19: 2347.59 | E19: 0 | F19: 0 | G19: 5276.43 | H19: 38742.41 | I19: 349.75 | J19: 5724.29 | K19: -37747.5 | L19: 318.97 | M19: 3774.54 | N19: 2579.77 | O19: 40008.74 | Q19: =_xlfn.XLOOKUP($B19,coding!$A:$A,coding!$C:$C,"") -> Expense Reimbursement | T19: Real Estate Taxes | U19: =SUMIF($Q:$Q,T19,$O:$O) -> 1032690.2 | V19: 997085.11
A20: 4799-0000 | B20: TOTAL REIMBURSABLE EXPENSES | C20: 74408.09 | D20: 59129.57 | E20: -124418.47 | F20: 172901.57 | G20: 62193.07 | H20: 74398.66 | I20: 26905.47 | J20: 44018.19 | K20: -5252.35 | L20: 37514.65 | M20: 41850.71 | N20: 40488.31 | O20: 504137.47 | Q20: =_xlfn.XLOOKUP($B20,coding!$A:$A,coding!$C:$C,"") -> 0 | T20: Property Insurance | U20: =SUMIF($Q:$Q,T20,$O:$O) -> 191090.61 | V20: 189226.62
A21: 4800-0000 | B21: OTHER OPERATING INCOME | Q21: =_xlfn.XLOOKUP($B21,coding!$A:$A,coding!$C:$C,"") -> 0 | T21: Utilities | U21: =SUMIF($Q:$Q,T21,$O:$O) -> 663763.62 | V21: 616358.64
A22: 4851-0000 | B22: Tenant Service Revenue | C22: 0 | D22: 8262.24 | E22: 8674.83 | F22: 8382.44 | G22: 1034.26 | H22: 8644.64 | I22: 2319.13 | J22: 6737.64 | K22: 0 | L22: 7769.71 | M22: 1526.84 | N22: 6619.82 | O22: 59971.55 | Q22: =_xlfn.XLOOKUP($B22,coding!$A:$A,coding!$C:$C,"") -> Other Income | T22: Repairs and Maintenance | U22: =SUMIF($Q:$Q,T22,$O:$O) -> 477146.7 | V22: 507856.18
A23: 4852-0000 | B23: Cost of Tenant Services | C23: 0 | D23: 0 | E23: 0 | F23: -111.64 | G23: 111.64 | H23: 0 | I23: 0 | J23: 0 | K23: 0 | L23: 0 | M23: 0 | N23: 0 | O23: 0 | Q23: =_xlfn.XLOOKUP($B23,coding!$A:$A,coding!$C:$C,"") -> Other Income | T23: Janitorial | U23: =SUMIF($Q:$Q,T23,$O:$O) -> 275362.38 | V23: 275372.32
A24: 4855-0000 | B24: Late Fees | C24: 0 | D24: 0 | E24: 0 | F24: 0 | G24: 0 | H24: 0 | I24: 0 | J24: 0 | K24: 0 | L24: -5 | M24: 0 | N24: 5 | O24: 0 | Q24: =_xlfn.XLOOKUP($B24,coding!$A:$A,coding!$C:$C,"") -> Other Income | T24: Management Fees | U24: =SUMIF($Q:$Q,T24,$O:$O) -> 111110.94 | V24: 97431.15
A25: 4865-0000 | B25: Miscellaneous | C25: 409.05 | D25: 422.95 | E25: 344.32 | F25: 359.68 | G25: -3093.99 | H25: 0 | I25: 0 | J25: 0 | K25: 0 | L25: 0 | M25: 0 | N25: 0 | O25: -1557.99 | Q25: =_xlfn.XLOOKUP($B25,coding!$A:$A,coding!$C:$C,"") -> Other Income | T25: Payroll & Benefits | U25: =SUMIF($Q:$Q,T25,$O:$O) -> 434643.21 | V25: 416599.89
A26: 4890-0000 | B26: TOTAL OTHER OPERATING INCOME | C26: 409.05 | D26: 8685.19 | E26: 9019.15 | F26: 8630.48 | G26: -1948.09 | H26: 8644.64 | I26: 2319.13 | J26: 6737.64 | K26: 0 | L26: 7764.71 | M26: 1526.84 | N26: 6624.82 | O26: 58413.56 | Q26: =_xlfn.XLOOKUP($B26,coding!$A:$A,coding!$C:$C,"") -> 0 | T26: Advertising & Marketing | U26: =SUMIF($Q:$Q,T26,$O:$O) -> 7395.28 | V26: 6290.29
A27: 4999-0000 | B27: TOTAL OPERATING REVENUE | C27: 596193.77 | D27: 597980.77 | E27: 415452.15 | F27: 700069.21 | G27: 566102.62 | H27: 611086.05 | I27: 488246.03 | J27: 641724.87 | K27: 490013.16 | L27: 542333 | M27: 530450.9 | N27: 627316.36 | O27: 6806968.9 | Q27: =_xlfn.XLOOKUP($B27,coding!$A:$A,coding!$C:$C,"") -> 0 | T27: Professional Fees | U27: =SUMIF($Q:$Q,T27,$O:$O) -> 201585.86 | V27: 215728.76
A28: 5001-0000 | B28: OPERATING EXPENSES | Q28: =_xlfn.XLOOKUP($B28,coding!$A:$A,coding!$C:$C,"") -> 0 | T28: General and Administrative | U28: =SUMIF($Q:$Q,T28,$O:$O) -> 59576.01 | V28: 57292.11
A29: 5002-0000 | B29: OPERATING EXPENSES - RECOVERABLE | Q29: =_xlfn.XLOOKUP($B29,coding!$A:$A,coding!$C:$C,"") -> 0 | T29: Other Expenses | U29: =SUMIF($Q:$Q,T29,$O:$O) -> 186986.3 | V29: 182600.79
A30: 5100-0000 | B30: CLEANING - RECOVERABLE | Q30: =_xlfn.XLOOKUP($B30,coding!$A:$A,coding!$C:$C,"") -> 0 | T30: Ground Rent | U30: =SUMIF($Q:$Q,T30,$O:$O) -> 0 | V30: 0
A31: 5110-0000 | B31: Cleaning-Day Porter | C31: 5147 | D31: 5147 | E31: 5147 | F31: 5147 | G31: 5147 | H31: 5147 | I31: 5147 | J31: 5147 | K31: 5147 | L31: 5472.95 | M31: 5266 | N31: 5266 | O31: 62327.95 | Q31: =_xlfn.XLOOKUP($B31,coding!$A:$A,coding!$C:$C,"") -> Janitorial | T31: Total Operating Expenses | U31: =SUM(U19:U30) -> 3641351.1 | V31: 3561841.9
A32: 5112-0000 | B32: Cleaning-Contract Srvcs | C32: 13924.79 | D32: 13815.52 | E32: 15471.04 | F32: 14112 | G32: 14209.23 | H32: 14892.55 | I32: 14221.5 | J32: 14221.5 | K32: 14221.5 | L32: 14549.3 | M32: 14221.5 | N32: 14133.24 | O32: 171993.67 | Q32: =_xlfn.XLOOKUP($B32,coding!$A:$A,coding!$C:$C,"") -> Janitorial
A33: 5116-0000 | B33: Cleaning-Window Cleaning | C33: 0 | D33: 0 | E33: 204 | F33: 0 | G33: 0 | H33: 0 | I33: 0 | J33: 0 | K33: 0 | L33: 0 | M33: 0 | N33: 0 | O33: 204 | Q33: =_xlfn.XLOOKUP($B33,coding!$A:$A,coding!$C:$C,"") -> Janitorial | T33: NOI | U33: =U16-U31 -> 3165617.8 | V33: 3265984.5
A34: 5118-0000 | B34: Cleaning-Supplies | C34: 3899.07 | D34: 4996.7 | E34: 1864.33 | F34: 3948.68 | G34: 2774.57 | H34: 2897.06 | I34: 7185.92 | J34: 4289.41 | K34: 1036.34 | L34: 3360.15 | M34: 2012.53 | N34: 2300 | O34: 40564.76 | Q34: =_xlfn.XLOOKUP($B34,coding!$A:$A,coding!$C:$C,"") -> Janitorial
A35: 5199-0000 | B35: TOTAL CLEANING - RECOVERABLE | C35: 22970.86 | D35: 23959.22 | E35: 22686.37 | F35: 23207.68 | G35: 22130.8 | H35: 22936.61 | I35: 26554.42 | J35: 23657.91 | K35: 20404.84 | L35: 23382.4 | M35: 21500.03 | N35: 21699.24 | O35: 275090.38 | Q35: =_xlfn.XLOOKUP($B35,coding!$A:$A,coding!$C:$C,"") -> 0 | T35: Non-Operating Expenses | U35: =SUMIF($Q:$Q,T35,$O:$O) -> 0 | V35: 0
A36: 5200-0000 | B36: REPAIR & MAINTENANCE - RECOVERABLE | Q36: =_xlfn.XLOOKUP($B36,coding!$A:$A,coding!$C:$C,"") -> 0 | T36: Interest Expense | U36: =SUMIF($Q:$Q,T36,$O:$O) -> 1583007.7 | V36: 1576987.6
A37: 5201-0000 | B37: RM-Pay/Wages | C37: 19739.02 | D37: 18501.38 | E37: 18681.6 | F37: 19108.17 | G37: 20901.38 | H37: 26205.96 | I37: 7992.68 | J37: 20020.52 | K37: 14507.23 | L37: 19773.14 | M37: 27863.56 | N37: 18672.24 | O37: 231966.88 | Q37: =_xlfn.XLOOKUP($B37,coding!$A:$A,coding!$C:$C,"") -> Repairs and Maintenance | T37: Debt Service | U37: =SUMIF($Q:$Q,T37,$O:$O) -> 4904625.8 | V37: 5207007.6
A38: 5207-0000 | B38: RM-Supplies | C38: 46.77 | D38: 0 | E38: 0 | F38: 1455.2 | G38: 154.7 | H38: 2185.23 | I38: 387.89 | J38: 26.92 | K38: 102.78 | L38: 0 | M38: 0 | N38: 496.19 | O38: 4855.68 | Q38: =_xlfn.XLOOKUP($B38,coding!$A:$A,coding!$C:$C,"") -> Repairs and Maintenance
A39: 5208-0000 | B39: RM-Uniforms | C39: 131 | D39: 131 | E39: 131 | F39: 416.58 | G39: 131 | H39: 131 | I39: 131 | J39: 65.5 | K39: 1260.03 | L39: -800.82 | M39: 131.4 | N39: 131.2 | O39: 1989.89 | Q39: =_xlfn.XLOOKUP($B39,coding!$A:$A,coding!$C:$C,"") -> Repairs and Maintenance | T39: Non-Recurring Expenses
A40: 5209-0000 | B40: RM-Equipment | C40: 87.79 | D40: 0 | E40: 0 | F40: 37.02 | G40: 0 | H40: 0 | I40: 0 | J40: 0 | K40: 0 | L40: 0 | M40: 0 | N40: 290.85 | O40: 415.66 | Q40: =_xlfn.XLOOKUP($B40,coding!$A:$A,coding!$C:$C,"") -> Repairs and Maintenance | T40: HVAC R&M
A41: 5212-0000 | B41: RM-Roof | C41: 0 | D41: 0 | E41: 0 | F41: 4250 | G41: 0 | H41: 0 | I41: 0 | J41: 0 | K41: 0 | L41: 0 | M41: 0 | N41: 0 | O41: 4250 | Q41: =_xlfn.XLOOKUP($B41,coding!$A:$A,coding!$C:$C,"") -> Repairs and Maintenance | T41: Plumbing R&M
A42: 5213-0000 | B42: RM-Keys/Access Cards/Locks | C42: 0 | D42: 0 | E42: 383.56 | F42: 833.88 | G42: 455.76 | H42: 390 | I42: 0 | J42: 195 | K42: 0 | L42: 1785.06 | M42: 333.53 | N42: 225 | O42: 4601.79 | Q42: =_xlfn.XLOOKUP($B42,coding!$A:$A,coding!$C:$C,"") -> Repairs and Maintenance | T42: FLS R&M
A43: 5219-0000 | B43: RM-Signage | C43: 725 | D43: 0 | E43: 0 | F43: 0 | G43: 0 | H43: 1111.01 | I43: 0 | J43: 0 | K43: 0 | L43: 0 | M43: 3472.79 | N43: 465.48 | O43: 5774.28 | Q43: =_xlfn.XLOOKUP($B43,coding!$A:$A,coding!$C:$C,"") -> Repairs and Maintenance | T43: Bldg Interior - Painting
A44: 5220-0000 | B44: RM-Pest Control | C44: 482.66 | D44: 567.83 | E44: 524.83 | F44: 525.66 | G44: 674.83 | H44: 524 | I44: 524.83 | J44: 524.33 | K44: 432.33 | L44: 779.83 | M44: 489 | N44: 486.66 | O44: 6536.79 | Q44: =_xlfn.XLOOKUP($B44,coding!$A:$A,coding!$C:$C,"") -> Repairs and Maintenance | T44: Tree Trimming
A45: 5224-0000 | B45: RM-Windows/Doors | C45: 0 | D45: 0 | E45: 0 | F45: 3808 | G45: 0 | H45: 0 | I45: 0 | J45: 1950 | K45: 450 | L45: 0 | M45: 0 | N45: 450 | O45: 6658 | Q45: =_xlfn.XLOOKUP($B45,coding!$A:$A,coding!$C:$C,"") -> Repairs and Maintenance | T45: Bldg Exterior R&M
A46: 5234-0000 | B46: RM-Office Exp/Supplies | C46: 61.56 | D46: 0 | E46: 0 | F46: 0 | G46: 0 | H46: 0 | I46: 0 | J46: 0 | K46: 0 | L46: 0 | M46: 0 | N46: 0 | O46: 61.56 | Q46: =_xlfn.XLOOKUP($B46,coding!$A:$A,coding!$C:$C,"") -> Repairs and Maintenance | T46: T12 Total | U46: =+SUM(U40:U45) -> 0 | V46: 0
A47: 5237-0000 | B47: RM-Communications/Radio/Pagers | C47: 408.14 | D47: 478.83 | E47: 549.72 | F47: 817.95 | G47: 366.8 | H47: 857.06 | I47: 518.15 | J47: 562.64 | K47: 434.74 | L47: 1500.57 | M47: 1084.74 | N47: 592 | O47: 8171.34 | Q47: =_xlfn.XLOOKUP($B47,coding!$A:$A,coding!$C:$C,"") -> Repairs and Maintenance
A48: 5244-0000 | B48: RM-Miscellaneous | C48: 18.95 | D48: 0 | E48: 8.95 | F48: 3825 | G48: 3000 | H48: 0 | I48: 0 | J48: 0 | K48: 551.61 | L48: 0 | M48: 0 | N48: 0 | O48: 7404.51 | Q48: =_xlfn.XLOOKUP($B48,coding!$A:$A,coding!$C:$C,"") -> Repairs and Maintenance
A49: 5245-0000 | B49: RM-Elect/Lighting Contract Srv | C49: 2352.52 | D49: 0 | E49: 0 | F49: 0 | G49: 0 | H49: 0 | I49: 0 | J49: 0 | K49: 0 | L49: 0 | M49: 0 | N49: 0 | O49: 2352.52 | Q49: =_xlfn.XLOOKUP($B49,coding!$A:$A,coding!$C:$C,"") -> Repairs and Maintenance
A50: 5246-0000 | B50: RM-Elect/Lighting R&M | C50: 309.37 | D50: 0 | E50: 0 | F50: 0 | G50: 0 | H50: 921 | I50: 0 | J50: 0 | K50: 0 | L50: 0 | M50: 600 | N50: 600 | O50: 2430.37 | Q50: =_xlfn.XLOOKUP($B50,coding!$A:$A,coding!$C:$C,"") -> Repairs and Maintenance
A51: 5248-0000 | B51: RM-Elect/Lighting Supplies | C51: 0 | D51: 4504.32 | E51: 0 | F51: 0 | G51: 0 | H51: 0 | I51: 0 | J51: 1387.82 | K51: 525.26 | L51: 0 | M51: 0 | N51: 0 | O51: 6417.4 | Q51: =_xlfn.XLOOKUP($B51,coding!$A:$A,coding!$C:$C,"") -> Repairs and Maintenance
A52: 5250-0000 | B52: RM-Elev/Esc Contract Srvcs | C52: 2729.62 | D52: 440.26 | E52: 440.26 | F52: 442 | G52: 442 | H52: 442 | I52: 435.04 | J52: 453.68 | K52: 514.82 | L52: 446.49 | M52: 680.52 | N52: 453.68 | O52: 7920.37 | Q52: =_xlfn.XLOOKUP($B52,coding!$A:$A,coding!$C:$C,"") -> Repairs and Maintenance
A53: 5251-0000 | B53: RM-Elev/Esc R&M | C53: 0 | D53: 0 | E53: 0 | F53: 0 | G53: 0 | H53: 0 | I53: 857 | J53: 0 | K53: 0 | L53: 0 | M53: 0 | N53: 548 | O53: 1405 | Q53: =_xlfn.XLOOKUP($B53,coding!$A:$A,coding!$C:$C,"") -> Repairs and Maintenance
A54: 5257-0000 | B54: RM-HVAC Contract Srvcs | C54: 3986 | D54: 2198 | E54: 2301 | F54: 2232.83 | G54: 2232.34 | H54: 2232.83 | I54: 2232.5 | J54: 2232.17 | K54: 2232.83 | L54: 2232.33 | M54: 2232.34 | N54: 2232.33 | O54: 28577.5 | Q54: =_xlfn.XLOOKUP($B54,coding!$A:$A,coding!$C:$C,"") -> Repairs and Maintenance
A55: 5258-0000 | B55: RM-HVAC R&M | C55: 6001.63 | D55: 1128.9 | E55: 1166 | F55: 660 | G55: 865 | H55: 2606 | I55: 3804.35 | J55: 1736.31 | K55: 572.5 | L55: 3162.48 | M55: 2762.03 | N55: 4325.18 | O55: 28790.38 | Q55: =_xlfn.XLOOKUP($B55,coding!$A:$A,coding!$C:$C,"") -> Repairs and Maintenance
A56: 5259-0000 | B56: RM-HVAC Supplies | C56: 0 | D56: 1260.03 | E56: 0 | F56: 0 | G56: 0 | H56: 0 | I56: 0 | J56: 746.64 | K56: 0 | L56: 1393.67 | M56: 0 | N56: 126.8 | O56: 3527.14 | Q56: =_xlfn.XLOOKUP($B56,coding!$A:$A,coding!$C:$C,"") -> Repairs and Maintenance
A57: 5265-0000 | B57: RM-Plumbing R&M | C57: 0 | D57: 0 | E57: 0 | F57: 330 | G57: 1732.8 | H57: 68.95 | I57: 0 | J57: 1364.76 | K57: 1890.5 | L57: 0 | M57: 432.21 | N57: 2660 | O57: 8479.22 | Q57: =_xlfn.XLOOKUP($B57,coding!$A:$A,coding!$C:$C,"") -> Repairs and Maintenance
A58: 5266-0000 | B58: RM-Plumbing Supplies | C58: 0 | D58: 770.57 | E58: 0 | F58: 0 | G58: 0 | H58: 0 | I58: 0 | J58: 0 | K58: 0 | L58: 0 | M58: 0 | N58: 0 | O58: 770.57 | Q58: =_xlfn.XLOOKUP($B58,coding!$A:$A,coding!$C:$C,"") -> Repairs and Maintenance
A59: 5290-0000 | B59: TOTAL REPAIR & MAINTENANCE - RECOVERABLE | C59: 37080.03 | D59: 29981.12 | E59: 24186.92 | F59: 38742.29 | G59: 30956.61 | H59: 37675.04 | I59: 16883.44 | J59: 31266.29 | K59: 23474.63 | L59: 30272.75 | M59: 40082.12 | N59: 32755.61 | O59: 373356.85 | Q59: =_xlfn.XLOOKUP($B59,coding!$A:$A,coding!$C:$C,"") -> 0
A60: 5300-0000 | B60: SECURITY FIRE / LIFE SAFETY - RECOVERABLE | Q60: =_xlfn.XLOOKUP($B60,coding!$A:$A,coding!$C:$C,"") -> 0
A61: 5302-0000 | B61: Security-Contract Srvcs | C61: 13278.88 | D61: 12125.61 | E61: 13832.18 | F61: 10462.58 | G61: 11793.34 | H61: 14461.55 | I61: 12492.57 | J61: 13113.37 | K61: 12479.91 | L61: 13400.1 | M61: 13309.07 | N61: 14299.61 | O61: 155048.77 | Q61: =_xlfn.XLOOKUP($B61,coding!$A:$A,coding!$C:$C,"") -> Other Expenses
A62: 5306-0000 | B62: Security-Supplies | C62: 0 | D62: 0 | E62: 0 | F62: 0 | G62: 79.96 | H62: 0 | I62: 0 | J62: 0 | K62: 0 | L62: 0 | M62: 0 | N62: 0 | O62: 79.96 | Q62: =_xlfn.XLOOKUP($B62,coding!$A:$A,coding!$C:$C,"") -> Other Expenses
A63: 5316-0000 | B63: Security-Miscellaneous | C63: 54.09 | D63: 52.44 | E63: 153.99 | F63: 138.52 | G63: -55.59 | H63: 178.1 | I63: 223.24 | J63: 132.2 | K63: 152.21 | L63: 44.4 | M63: 143.39 | N63: 484.45 | O63: 1701.44 | Q63: =_xlfn.XLOOKUP($B63,coding!$A:$A,coding!$C:$C,"") -> Other Expenses
A64: 5320-0000 | B64: Fire/Life-Alarm System | C64: 0 | D64: 0 | E64: 0 | F64: 0 | G64: 0 | H64: 1357.57 | I64: 0 | J64: 0 | K64: 77.79 | L64: 0 | M64: 65 | N64: 30 | O64: 1530.36 | Q64: =_xlfn.XLOOKUP($B64,coding!$A:$A,coding!$C:$C,"") -> Other Expenses
A65: 5328-0000 | B65: Fire/Life-Sprinklers | C65: 0 | D65: 0 | E65: 870 | F65: 0 | G65: 11360 | H65: 0 | I65: 0 | J65: 0 | K65: 0 | L65: 320 | M65: 0 | N65: 0 | O65: 12550 | Q65: =_xlfn.XLOOKUP($B65,coding!$A:$A,coding!$C:$C,"") -> Other Expenses
A66: 5330-0000 | B66: Fire/Life-Safety | C66: 1686.49 | D66: -10 | E66: 70 | F66: 1527.86 | G66: -30 | H66: 365 | I66: 70 | J66: 335.95 | K66: 168 | L66: 1064 | M66: 320 | N66: 160 | O66: 5727.3 | Q66: =_xlfn.XLOOKUP($B66,coding!$A:$A,coding!$C:$C,"") -> Other Expenses
A67: 5332-0000 | B67: Fire/Life-Miscellaneous | C67: 0 | D67: 0 | E67: 0 | F67: 2134.33 | G67: 0 | H67: 0 | I67: 0 | J67: 156.88 | K67: 1457.86 | L67: 1457.86 | M67: 0 | N67: 0 | O67: 5206.93 | Q67: =_xlfn.XLOOKUP($B67,coding!$A:$A,coding!$C:$C,"") -> Other Expenses
A68: 5399-0000 | B68: TOTAL SECURITY FIRE / LIFE SAFETY - RECOVERABLE | C68: 15019.46 | D68: 12168.05 | E68: 14926.17 | F68: 14263.29 | G68: 23147.71 | H68: 16362.22 | I68: 12785.81 | J68: 13738.4 | K68: 14335.77 | L68: 16286.36 | M68: 13837.46 | N68: 14974.06 | O68: 181844.76 | Q68: =_xlfn.XLOOKUP($B68,coding!$A:$A,coding!$C:$C,"") -> 0
A69: 5400-0000 | B69: UTILITIES - RECOVERABLE | Q69: =_xlfn.XLOOKUP($B69,coding!$A:$A,coding!$C:$C,"") -> 0
A70: 5460-0000 | B70: Electric | C70: 39853.77 | D70: 38825.82 | E70: 41152.97 | F70: 55149.66 | G70: 51894.66 | H70: 65351.36 | I70: 49832.8 | J70: 49852.64 | K70: 30449.47 | L70: 35579.33 | M70: 39785.16 | N70: 58533.67 | O70: 556261.31 | Q70: =_xlfn.XLOOKUP($B70,coding!$A:$A,coding!$C:$C,"") -> Utilities
A71: 5465-0000 | B71: Gas | C71: 205.06 | D71: 1986.09 | E71: 263.43 | F71: -619.49 | G71: -186.68 | H71: 63.12 | I71: 332.56 | J71: 256.26 | K71: 1611.86 | L71: 5411.15 | M71: 2027.57 | N71: 796.24 | O71: 12147.17 | Q71: =_xlfn.XLOOKUP($B71,coding!$A:$A,coding!$C:$C,"") -> Utilities
A72: 5470-0000 | B72: Water & Sewage | C72: 5935.24 | D72: 3473.05 | E72: 3361.02 | F72: 6452.2 | G72: 5939.35 | H72: 4672.37 | I72: 9902.76 | J72: 6722.81 | K72: 2241.75 | L72: 4278.91 | M72: 32036.38 | N72: -16075.24 | O72: 68940.6 | Q72: =_xlfn.XLOOKUP($B72,coding!$A:$A,coding!$C:$C,"") -> Utilities
A73: 5475-0000 | B73: Trash Removal | C73: 1554.59 | D73: 1554.59 | E73: 1554.59 | F73: 2176.43 | G73: 1710.05 | H73: 1710.05 | I73: 1710.05 | J73: 1710.05 | K73: 1710.05 | L73: 4621.53 | M73: 3389.28 | N73: 3013.28 | O73: 26414.54 | Q73: =_xlfn.XLOOKUP($B73,coding!$A:$A,coding!$C:$C,"") -> Utilities
A74: 5490-0000 | B74: TOTAL UTILITIES - RECOVERABLE | C74: 47548.66 | D74: 45839.55 | E74: 46332.01 | F74: 63158.8 | G74: 59357.38 | H74: 71796.9 | I74: 61778.17 | J74: 58541.76 | K74: 36013.13 | L74: 49890.92 | M74: 77238.39 | N74: 46267.95 | O74: 663763.62 | Q74: =_xlfn.XLOOKUP($B74,coding!$A:$A,coding!$C:$C,"") -> 0
A75: 5500-0000 | B75: LANDSCAPING - RECOVERABLE | Q75: =_xlfn.XLOOKUP($B75,coding!$A:$A,coding!$C:$C,"") -> 0
A76: 5505-0000 | B76: Landscaping-Contract Srvcs | C76: 3734.64 | D76: 3734.64 | E76: 3734.64 | F76: 3734.64 | G76: 3734.64 | H76: 3734.64 | I76: 3734.64 | J76: 3734.64 | K76: 12734.64 | L76: 3847 | M76: 3847 | N76: 3847 | O76: 54152.76 | Q76: =_xlfn.XLOOKUP($B76,coding!$A:$A,coding!$C:$C,"") -> Professional Fees
A77: 5510-0000 | B77: Landscaping-R&M | C77: 0 | D77: 0 | E77: 0 | F77: 0 | G77: 0 | H77: 0 | I77: 460 | J77: 0 | K77: 0 | L77: 1940 | M77: 1023 | N77: 0 | O77: 3423 | Q77: =_xlfn.XLOOKUP($B77,coding!$A:$A,coding!$C:$C,"") -> Repairs and Maintenance
A78: 5525-0000 | B78: Landscaping-Miscellaneous | C78: 0 | D78: 0 | E78: 0 | F78: 0 | G78: 0 | H78: 0 | I78: 38.68 | J78: 0 | K78: 0 | L78: 0 | M78: 750 | N78: 0 | O78: 788.68 | Q78: =_xlfn.XLOOKUP($B78,coding!$A:$A,coding!$C:$C,"") -> Repairs and Maintenance
A79: 5599-0000 | B79: TOTAL LANDSCAPING - RECOVERABLE | C79: 3734.64 | D79: 3734.64 | E79: 3734.64 | F79: 3734.64 | G79: 3734.64 | H79: 3734.64 | I79: 4233.32 | J79: 3734.64 | K79: 12734.64 | L79: 5787 | M79: 5620 | N79: 3847 | O79: 58364.44 | Q79: =_xlfn.XLOOKUP($B79,coding!$A:$A,coding!$C:$C,"") -> 0
A80: 5600-0000 | B80: PARKING - RECOVERABLE | Q80: =_xlfn.XLOOKUP($B80,coding!$A:$A,coding!$C:$C,"") -> 0
A81: 5602-0000 | B81: Parking Lot-Contract Srvcs | C81: 11000 | D81: 11000 | E81: 13370 | F81: 11000 | G81: 11000 | H81: 11000 | I81: 11000 | J81: 9975.17 | K81: 10255.02 | L81: 10989.33 | M81: 11000 | N81: 12139.03 | O81: 133728.55 | Q81: =_xlfn.XLOOKUP($B81,coding!$A:$A,coding!$C:$C,"") -> Professional Fees
A82: 5604-0000 | B82: Parking Lot-R&M | C82: 0 | D82: 0 | E82: 0 | F82: 0 | G82: 0 | H82: 1600 | I82: 0 | J82: 0 | K82: 0 | L82: 0 | M82: 0 | N82: 0 | O82: 1600 | Q82: =_xlfn.XLOOKUP($B82,coding!$A:$A,coding!$C:$C,"") -> Repairs and Maintenance
A83: 5608-0000 | B83: Parking Lot-Sweeping | C83: 1030 | D83: 1030 | E83: 1030 | F83: 1030 | G83: 1030 | H83: 1030 | I83: 1030 | J83: 1030 | K83: 1030 | L83: 1051 | M83: 1051 | N83: 1051 | O83: 12423 | Q83: =_xlfn.XLOOKUP($B83,coding!$A:$A,coding!$C:$C,"") -> Repairs and Maintenance
A84: 5649-0000 | B84: TOTAL PARKING - RECOVERABLE | C84: 12030 | D84: 12030 | E84: 14400 | F84: 12030 | G84: 12030 | H84: 13630 | I84: 12030 | J84: 11005.17 | K84: 11285.02 | L84: 12040.33 | M84: 12051 | N84: 13190.03 | O84: 147751.55 | Q84: =_xlfn.XLOOKUP($B84,coding!$A:$A,coding!$C:$C,"") -> 0
A85: 5700-0000 | B85: GENERAL AND ADMINISTRATIVE - RECOVERABLE | Q85: =_xlfn.XLOOKUP($B85,coding!$A:$A,coding!$C:$C,"") -> 0
A86: 5701-0000 | B86: Admin-Pay/Wages | C86: 69834.73 | D86: 25901.52 | E86: 28341.46 | F86: 29899.5 | G86: 40328.48 | H86: 27380.81 | I86: 29900.5 | J86: 24997.78 | K86: 37899.87 | L86: 26480.55 | M86: 23992.45 | N86: 69409.76 | O86: 434367.41 | Q86: =_xlfn.XLOOKUP($B86,coding!$A:$A,coding!$C:$C,"") -> Payroll & Benefits
A87: 5703-0000 | B87: Admin-Pay/Overtime | C87: 0 | D87: 0 | E87: 0 | F87: 0 | G87: 0 | H87: 0 | I87: 0 | J87: 0 | K87: 0 | L87: 0 | M87: 275.8 | N87: 0 | O87: 275.8 | Q87: Payroll & Benefits
A88: 5706-0000 | B88: Admin-Property Management Fee | C88: 10006.96 | D88: 10057.67 | E88: 10504.5 | F88: 9444.99 | G88: 9324.38 | H88: 9224.62 | I88: 8611.36 | J88: 7655.97 | K88: 8530.75 | L88: 8880.38 | M88: 8587.19 | N88: 10282.17 | O88: 111110.94 | Q88: =_xlfn.XLOOKUP($B88,coding!$A:$A,coding!$C:$C,"") -> Management Fees
A89: 5707-0000 | B89: Admin-Contract Srvcs | C89: 614.94 | D89: 366.18 | E89: 899.21 | F89: 739.79 | G89: 632.01 | H89: 1902.13 | I89: 843.19 | J89: 748.1 | K89: 862.19 | L89: 883.12 | M89: 790.39 | N89: 1176.98 | O89: 10458.23 | Q89: =_xlfn.XLOOKUP($B89,coding!$A:$A,coding!$C:$C,"") -> Professional Fees
A90: 5721-0000 | B90: Admin-Office Exp/Supplies | C90: 633.52 | D90: 701.59 | E90: 609.42 | F90: 2208.35 | G90: 242.04 | H90: 1430.11 | I90: 570.5 | J90: 525.9 | K90: 486.95 | L90: 407.85 | M90: 375 | N90: 458.3 | O90: 8649.53 | Q90: =_xlfn.XLOOKUP($B90,coding!$A:$A,coding!$C:$C,"") -> General and Administrative
A91: 5723-0000 | B91: Admin-Postage | C91: 253.94 | D91: 27.12 | E91: 0 | F91: 84.45 | G91: 188.12 | H91: 173.92 | I91: 295.4 | J91: 435.39 | K91: 221.89 | L91: 360.53 | M91: 116.14 | N91: 273.54 | O91: 2430.44 | Q91: =_xlfn.XLOOKUP($B91,coding!$A:$A,coding!$C:$C,"") -> General and Administrative
A92: 5725-0000 | B92: Admin-Travel | C92: 0 | D92: 0 | E92: 0 | F92: 0 | G92: 0 | H92: 0 | I92: 0 | J92: 0 | K92: 0 | L92: 0 | M92: 0 | N92: 609.77 | O92: 609.77 | Q92: =_xlfn.XLOOKUP($B92,coding!$A:$A,coding!$C:$C,"") -> General and Administrative
A93: 5729-0000 | B93: Admin-Telephone | C93: 1811.08 | D93: 1882.98 | E93: 1860.36 | F93: 3167.36 | G93: 1491.76 | H93: 1719.09 | I93: 2109.44 | J93: 1725.13 | K93: 3084.34 | L93: 512.29 | M93: 3635.13 | N93: 3232.57 | O93: 26231.53 | Q93: =_xlfn.XLOOKUP($B93,coding!$A:$A,coding!$C:$C,"") -> General and Administrative
A94: 5731-0000 | B94: Admin-Dues License Subscpt | C94: 99.16 | D94: 99.16 | E94: 523.66 | F94: 50 | G94: 109 | H94: 109 | I94: 109 | J94: 109 | K94: 109 | L94: 0 | M94: 0 | N94: 0 | O94: 1316.98 | Q94: =_xlfn.XLOOKUP($B94,coding!$A:$A,coding!$C:$C,"") -> General and Administrative
A95: 5733-0000 | B95: Admin-Training Development | C95: 0 | D95: 0 | E95: 0 | F95: 456.35 | G95: 0 | H95: 0 | I95: 0 | J95: 0 | K95: 0 | L95: 0 | M95: 0 | N95: 0 | O95: 456.35 | Q95: =_xlfn.XLOOKUP($B95,coding!$A:$A,coding!$C:$C,"") -> General and Administrative
A96: 5737-0000 | B96: Admin-Bank Fees | C96: 1620.22 | D96: 1592.56 | E96: 1477.15 | F96: 1463.42 | G96: 1464.33 | H96: 1259.63 | I96: 1143.45 | J96: 1925.19 | K96: 1463.79 | L96: 1373.15 | M96: 1342.55 | N96: 1370.52 | O96: 17495.96 | Q96: =_xlfn.XLOOKUP($B96,coding!$A:$A,coding!$C:$C,"") -> General and Administrative
A97: 5739-0000 | B97: Admin-Computer/Software | C97: 0 | D97: 0 | E97: 0 | F97: 0 | G97: 0 | H97: 0 | I97: 339.65 | J97: 339.65 | K97: 339.65 | L97: 339.65 | M97: 339.65 | N97: 339.65 | O97: 2037.9 | Q97: =_xlfn.XLOOKUP($B97,coding!$A:$A,coding!$C:$C,"") -> General and Administrative
A98: 5747-0000 | B98: Admin-Tax/License/Permits | C98: 0 | D98: 0 | E98: 0 | F98: 102.5 | G98: 0 | H98: 0 | I98: 0 | J98: 0 | K98: 0 | L98: 0 | M98: 0 | N98: 0 | O98: 102.5 | Q98: =_xlfn.XLOOKUP($B98,coding!$A:$A,coding!$C:$C,"") -> General and Administrative
A99: 5751-0000 | B99: Admin-Miscellaneous | C99: 9.99 | D99: 0 | E99: 0 | F99: 0 | G99: 0 | H99: 44.99 | I99: 0 | J99: 0 | K99: 0 | L99: 0 | M99: 0 | N99: 0 | O99: 54.98 | Q99: =_xlfn.XLOOKUP($B99,coding!$A:$A,coding!$C:$C,"") -> General and Administrative
... A101: 5799-0000 | B101: TOTAL GENERAL AND ADMINISTRATIVE - RECOVERABLE | C101: 84884.54 | D101: 40628.78 | E101: 44215.76 | F101: 47616.71 | G101: 53780.12 | H101: 43244.3 | I101: 43922.49 | J101: 38462.11 | K101: 53178.5 | L101: 39237.52 | M101: 39454.3 | N101: 87153.26 | O101: 615778.39 | Q101: =_xlfn.XLOOKUP($B101,coding!$A:$A,coding!$C:$C,"") -> 0
...

Sheet Rent Roll
A1: Tenancy Schedule I
A2: All Selected Properties As of Date: 03/31/2026 By Property Notes : 1. * Future Active lease / Future Active Amendment 2. ** Pending Amendments 3. *** Past / Superseded Amendments
A3: Property | B3: Unit(s) | C3: Lease | D3: Lease Type | E3: Area | F3: Lease From | G3: Lease To | H3: Term | I3: Tenancy | J3: Monthly | K3: Monthly | L3: Annual | M3: Annual | N3: Annual | O3: Annual | P3: Security | Q3: LOC Amount/ | T3: Include in DY Test? | U3: Term (YR) | V3: Free Rent Period | W3: Month Excluded | X3: Months Included | Y3: Adj Annnal Rent | Z3: Adj. Annual Recoveries | AA3: Adjusted Occupied SF | AC3: Last Update
I4: Years | J4: Rent | K4: Rent/Area | L4: Rent | M4: Rent/Area | N4: Rec./Area | O4: Misc/Area | P4: Deposit | Q4: Bank Guarantee | T4: 46112 | AC4: 46112
A5: x | B5: x | C5: x | D5: x | E5: x | F5: x | G5: x | H5: x | I5: x | J5: x | K5: x | L5: x | M5: x | N5: x | O5: x | P5: Received | Q5: x | S5: Notes | AC5: Credit Rating Rating above (BBB-) ?
A6: Campus at LaJolla (a0103013) | B6: 8910 | C6: The Regents of the University of California (8910) (t0000137) | D6: Office Net | E6: 14750 | F6: 42594 | G6: 49887 | H6: 240 | I6: 9.67 | J6: 73012.5 | K6: 4.95 | L6: 876150 | M6: 59.4 | N6: 6.07 | O6: 0 | P6: 0 | Q6: 0 | T6: =+IF(OR(C6="Vacant",G6=""),FALSE,IF($AC6="Yes",F6<=($T$4+180),F6<=($T$4+90))) -> TRUE | U6: =+IF(G6="",0,DATEDIF(F6,G6,"M")/12) -> 19.916667 | W6: =+MAX(V6-U6,0) -> 0 | X6: =12-W6 -> 12 | Y6: =+(J6*X6+E6*O6)*T6 -> 876150 | Z6: =(X6*N6*E6/12)*T6 -> 89532.5 | AA6: =+T6*E6 -> 14750 | AC6: Yes
A7: Campus at LaJolla (a0103013) | B7: A105 | C7: Coleman Meadows DDS, Inc. (A105) (t0000071) | D7: Office Net | E7: 2548 | F7: 43678 | G7: 47330 | H7: 120 | I7: 6.67 | J7: 11873.68 | K7: 4.66 | L7: 142484.16 | M7: 55.92 | N7: 6.65 | O7: 0 | P7: 9200 | Q7: 0 | T7: =+IF(OR(C7="Vacant",G7=""),FALSE,IF($AC7="Yes",F7<=($T$4+180),F7<=($T$4+90))) -> TRUE | U7: =+IF(G7="",0,DATEDIF(F7,G7,"M")/12) -> 9.9166667 | W7: =+MAX(V7-U7,0) -> 0 | X7: =12-W7 -> 12 | Y7: =+(J7*X7+E7*O7)*T7 -> 142484.16 | Z7: =(X7*N7*E7/12)*T7 -> 16944.2 | AA7: =+T7*E7 -> 2548
A8: Campus at LaJolla (a0103013) | B8: A107 | C8: Bronner Handwerger (A107) (t0000072) | D8: Office Net | E8: 1438 | F8: 45170 | G8: 47118 | H8: 64 | I8: 2.58 | J8: 6859.26 | K8: 4.77 | L8: 82311.12 | M8: 57.24 | N8: 2.47 | O8: 0 | P8: 4807.33 | Q8: 0 | T8: =+IF(OR(C8="Vacant",G8=""),FALSE,IF($AC8="Yes",F8<=($T$4+180),F8<=($T$4+90))) -> TRUE | U8: =+IF(G8="",0,DATEDIF(F8,G8,"M")/12) -> 5.25 | W8: =+MAX(V8-U8,0) -> 0 | X8: =12-W8 -> 12 | Y8: =+(J8*X8+E8*O8)*T8 -> 82311.12 | Z8: =(X8*N8*E8/12)*T8 -> 3551.86 | AA8: =+T8*E8 -> 1438
A9: Campus at LaJolla (a0103013) | B9: A108 | C9: Nancy Markel (A108) (t0000073) | D9: Office Net | E9: 620 | F9: 44896 | G9: 46174 | I9: 3.33 | J9: 2728 | K9: 4.4 | L9: 32736 | M9: 52.8 | N9: 8.34 | O9: 0 | P9: 1652.52 | Q9: 0 | T9: =+IF(OR(C9="Vacant",G9=""),FALSE,IF($AC9="Yes",F9<=($T$4+180),F9<=($T$4+90))) -> TRUE | U9: =+IF(G9="",0,DATEDIF(F9,G9,"M")/12) -> 3.5 | W9: =+MAX(V9-U9,0) -> 0 | X9: =12-W9 -> 12 | Y9: =+(J9*X9+E9*O9)*T9 -> 32736 | Z9: =(X9*N9*E9/12)*T9 -> 5170.8 | AA9: =+T9*E9 -> 620
A10: Campus at LaJolla (a0103013) | B10: A109 | C10: Advantech GS Enterprises, Inc. (B208) (t0000074) | D10: Office Net | E10: 1284 | F10: 44350 | G10: 48060 | H10: 122 | I10: 4.83 | J10: 5970.6 | K10: 4.65 | L10: 71647.2 | M10: 55.8 | N10: 6.34 | O10: 0 | P10: 14381.5 | Q10: 0 | T10: =+IF(OR(C10="Vacant",G10=""),FALSE,IF($AC10="Yes",F10<=($T$4+180),F10<=($T$4+90))) -> TRUE | U10: =+IF(G10="",0,DATEDIF(F10,G10,"M")/12) -> 10.083333 | W10: =+MAX(V10-U10,0) -> 0 | X10: =12-W10 -> 12 | Y10: =+(J10*X10+E10*O10)*T10 -> 71647.2 | Z10: =(X10*N10*E10/12)*T10 -> 8140.56 | AA10: =+T10*E10 -> 1284
A11: Campus at LaJolla (a0103013) | B11: A110 | C11: Maria Hiraldo (A110) (t0000075) | D11: Office Net | E11: 326 | F11: 44044 | G11: 47695 | H11: 120 | I11: 5.67 | J11: 1483.3 | K11: 4.55 | L11: 17799.6 | M11: 54.6 | N11: 6.33 | O11: 0 | P11: 1499.6 | Q11: 0 | T11: =+IF(OR(C11="Vacant",G11=""),FALSE,IF($AC11="Yes",F11<=($T$4+180),F11<=($T$4+90))) -> TRUE | U11: =+IF(G11="",0,DATEDIF(F11,G11,"M")/12) -> 9.9166667 | W11: =+MAX(V11-U11,0) -> 0 | X11: =12-W11 -> 12 | Y11: =+(J11*X11+E11*O11)*T11 -> 17799.6 | Z11: =(X11*N11*E11/12)*T11 -> 2063.58 | AA11: =+T11*E11 -> 326
A12: Campus at LaJolla (a0103013) | B12: A118 | C12: SureFire CPR (A118) (t0000149) | D12: Office Net | E12: 309 | F12: 45498 | G12: 46599 | H12: 37 | I12: 1.75 | J12: 1384.32 | K12: 4.48 | L12: 16611.84 | M12: 53.76 | N12: 2.05 | O12: 0 | P12: 2848.98 | Q12: 0 | T12: =+IF(OR(C12="Vacant",G12=""),FALSE,IF($AC12="Yes",F12<=($T$4+180),F12<=($T$4+90))) -> TRUE | U12: =+IF(G12="",0,DATEDIF(F12,G12,"M")/12) -> 3 | W12: =+MAX(V12-U12,0) -> 0 | X12: =12-W12 -> 12 | Y12: =+(J12*X12+E12*O12)*T12 -> 16611.84 | Z12: =(X12*N12*E12/12)*T12 -> 633.45 | AA12: =+T12*E12 -> 309
A13: Campus at LaJolla (a0103013) | B13: A125 | C13: La Jolla Sol Ventures, Inc. (A125) (t0000076) | D13: Office Net | E13: 1846 | F13: 44986 | G13: 46904 | H13: 63 | I13: 3.08 | J13: 9008.48 | K13: 4.88 | L13: 108101.76 | M13: 58.56 | N13: 2.32 | O13: 0 | P13: 4190.45 | Q13: 0 | T13: =+IF(OR(C13="Vacant",G13=""),FALSE,IF($AC13="Yes",F13<=($T$4+180),F13<=($T$4+90))) -> TRUE | U13: =+IF(G13="",0,DATEDIF(F13,G13,"M")/12) -> 5.1666667 | W13: =+MAX(V13-U13,0) -> 0 | X13: =12-W13 -> 12 | Y13: =+(J13*X13+E13*O13)*T13 -> 108101.76 | Z13: =(X13*N13*E13/12)*T13 -> 4282.72 | AA13: =+T13*E13 -> 1846
A14: Campus at LaJolla (a0103013) | B14: A127 | C14: Chemometec, Inc. (A127) (t0000077) | D14: Office Net | E14: 1469 | F14: 44562 | G14: 46507 | H14: 64 | I14: 4.25 | J14: 6654.57 | K14: 4.53 | L14: 79854.84 | M14: 54.36 | N14: 3.25 | O14: 0 | P14: 0 | Q14: 0 | T14: =+IF(OR(C14="Vacant",G14=""),FALSE,IF($AC14="Yes",F14<=($T$4+180),F14<=($T$4+90))) -> TRUE | U14: =+IF(G14="",0,DATEDIF(F14,G14,"M")/12) -> 5.25 | W14: =+MAX(V14-U14,0) -> 0 | X14: =12-W14 -> 12 | Y14: =+(J14*X14+E14*O14)*T14 -> 79854.84 | Z14: =(X14*N14*E14/12)*T14 -> 4774.25 | AA14: =+T14*E14 -> 1469
A15: Campus at LaJolla (a0103013) | B15: A128 | C15: J Zeidan, DMD, Inc. (A128) (t0000078) | D15: Office Net | E15: 2354 | F15: 44953 | G15: 46934 | H15: 66 | I15: 3.25 | J15: 11534.6 | K15: 4.9 | L15: 138415.2 | M15: 58.8 | N15: 2.81 | O15: 0 | P15: 12553 | Q15: 0 | T15: =+IF(OR(C15="Vacant",G15=""),FALSE,IF($AC15="Yes",F15<=($T$4+180),F15<=($T$4+90))) -> TRUE | U15: =+IF(G15="",0,DATEDIF(F15,G15,"M")/12) -> 5.4166667 | W15: =+MAX(V15-U15,0) -> 0 | X15: =12-W15 -> 12 | Y15: =+(J15*X15+E15*O15)*T15 -> 138415.2 | Z15: =(X15*N15*E15/12)*T15 -> 6614.74 | AA15: =+T15*E15 -> 2354
A16: Campus at LaJolla (a0103013) | B16: A207 | C16: Katherine A. Thomson, DDS, MS Inc. (A207) (t0000066) | D16: Office Net | E16: 1665 | F16: 43770 | G16: 47542 | H16: 124 | I16: 6.42 | J16: 7958.7 | K16: 4.78 | L16: 95504.4 | M16: 57.36 | N16: 4.23 | O16: 0 | P16: 6000 | Q16: 0 | T16: =+IF(OR(C16="Vacant",G16=""),FALSE,IF($AC16="Yes",F16<=($T$4+180),F16<=($T$4+90))) -> TRUE | U16: =+IF(G16="",0,DATEDIF(F16,G16,"M")/12) -> 10.25 | W16: =+MAX(V16-U16,0) -> 0 | X16: =12-W16 -> 12 | Y16: =+(J16*X16+E16*O16)*T16 -> 95504.4 | Z16: =(X16*N16*E16/12)*T16 -> 7042.95 | AA16: =+T16*E16 -> 1665
A17: Campus at LaJolla (a0103013) | B17: A215 | C17: Arash Khatami (A215) (t0000079) | D17: Office Net | E17: 907 | F17: 44531 | G17: 46478 | H17: 64 | I17: 4.33 | J17: 4181.27 | K17: 4.61 | L17: 50175.24 | M17: 55.32 | N17: 3.21 | O17: 0 | P17: 3700 | Q17: 0 | T17: =+IF(OR(C17="Vacant",G17=""),FALSE,IF($AC17="Yes",F17<=($T$4+180),F17<=($T$4+90))) -> TRUE | U17: =+IF(G17="",0,DATEDIF(F17,G17,"M")/12) -> 5.3333333 | W17: =+MAX(V17-U17,0) -> 0 | X17: =12-W17 -> 12 | Y17: =+(J17*X17+E17*O17)*T17 -> 50175.24 | Z17: =(X17*N17*E17/12)*T17 -> 2911.47 | AA17: =+T17*E17 -> 907
A18: Campus at LaJolla (a0103013) | B18: A218 | C18: Marin Wellness Pharmacy LLC (A218) (t0000606) | D18: Office Net | E18: 1422 | F18: 45778 | G18: 46904 | H18: 37 | I18: 0.92 | J18: 6256.8 | K18: 4.4 | L18: 75081.6 | M18: 52.8 | N18: 1.91 | O18: 0 | P18: 6839.82 | Q18: 0 | T18: =+IF(OR(C18="Vacant",G18=""),FALSE,IF($AC18="Yes",F18<=($T$4+180),F18<=($T$4+90))) -> TRUE | U18: =+IF(G18="",0,DATEDIF(F18,G18,"M")/12) -> 3 | W18: =+MAX(V18-U18,0) -> 0 | X18: =12-W18 -> 12 | Y18: =+(J18*X18+E18*O18)*T18 -> 75081.6 | Z18: =(X18*N18*E18/12)*T18 -> 2716.02 | AA18: =+T18*E18 -> 1422
A19: Campus at LaJolla (a0103013) | B19: A219 | C19: Rui Liu (A219) (t0000080) | D19: Office Net | E19: 905 | F19: 44501 | G19: 46387 | H19: 62 | I19: 4.42 | J19: 4126.8 | K19: 4.56 | L19: 49521.6 | M19: 54.72 | N19: 6.34 | O19: 0 | P19: 4253.5 | Q19: 0 | T19: =+IF(OR(C19="Vacant",G19=""),FALSE,IF($AC19="Yes",F19<=($T$4+180),F19<=($T$4+90))) -> TRUE | U19: =+IF(G19="",0,DATEDIF(F19,G19,"M")/12) -> 5.0833333 | W19: =+MAX(V19-U19,0) -> 0 | X19: =12-W19 -> 12 | Y19: =+(J19*X19+E19*O19)*T19 -> 49521.6 | Z19: =(X19*N19*E19/12)*T19 -> 5737.7 | AA19: =+T19*E19 -> 905
A20: Campus at LaJolla (a0103013) | B20: A220 | C20: Practical Recovery Psychology Group, Inc. & Mario Salguero Inc. (A220) (t0000081) | D20: Office Net | E20: 1386 | F20: 43558 | G20: 47573 | H20: 132 | I20: 7 | J20: 6278.58 | K20: 4.53 | L20: 75342.96 | M20: 54.36 | N20: 4.42 | O20: 0 | P20: 6347.88 | Q20: 0 | T20: =+IF(OR(C20="Vacant",G20=""),FALSE,IF($AC20="Yes",F20<=($T$4+180),F20<=($T$4+90))) -> TRUE | U20: =+IF(G20="",0,DATEDIF(F20,G20,"M")/12) -> 10.916667 | W20: =+MAX(V20-U20,0) -> 0 | X20: =12-W20 -> 12 | Y20: =+(J20*X20+E20*O20)*T20 -> 75342.96 | Z20: =(X20*N20*E20/12)*T20 -> 6126.12 | AA20: =+T20*E20 -> 1386
A21: Campus at LaJolla (a0103013) | B21: B101 | C21: Farnaz Farid, D.M.D., Inc. (B101) (t0000068) | D21: Office Net | E21: 1325 | F21: 43678 | G21: 47330 | H21: 120 | I21: 6.67 | J21: 6015.5 | K21: 4.54 | L21: 72186 | M21: 54.48 | N21: 6.23 | O21: 0 | P21: 6572 | Q21: 0 | T21: =+IF(OR(C21="Vacant",G21=""),FALSE,IF($AC21="Yes",F21<=($T$4+180),F21<=($T$4+90))) -> TRUE | U21: =+IF(G21="",0,DATEDIF(F21,G21,"M")/12) -> 9.9166667 | W21: =+MAX(V21-U21,0) -> 0 | X21: =12-W21 -> 12 | Y21: =+(J21*X21+E21*O21)*T21 -> 72186 | Z21: =(X21*N21*E21/12)*T21 -> 8254.75 | AA21: =+T21*E21 -> 1325
A22: Campus at LaJolla (a0103013) | B22: B107 | C22: Conference Room (B107) (t0000162) | D22: Office Net | E22: 1434 | F22: 44515 | I22: 4.42 | J22: 0 | K22: 0 | L22: 0 | M22: 0 | N22: 0 | O22: 0 | P22: 0 | Q22: 0 | T22: =+IF(OR(C22="Vacant",G22=""),FALSE,IF($AC22="Yes",F22<=($T$4+180),F22<=($T$4+90))) -> FALSE | U22: =+IF(G22="",0,DATEDIF(F22,G22,"M")/12) -> 0 | W22: =+MAX(V22-U22,0) -> 0 | X22: =12-W22 -> 12 | Y22: =+(J22*X22+E22*O22)*T22 -> 0 | Z22: =(X22*N22*E22/12)*T22 -> 0 | AA22: =+T22*E22 -> 0
A23: Campus at LaJolla (a0103013) | B23: B108 | C23: Jesse Sanchez (t0000601) | D23: Office Net | E23: 870 | F23: 45784 | G23: 49552 | H23: 124 | I23: 0.92 | J23: 3697.5 | K23: 4.25 | L23: 44370 | M23: 51 | N23: 0 | O23: 0 | P23: 10440 | Q23: 0 | T23: =+IF(OR(C23="Vacant",G23=""),FALSE,IF($AC23="Yes",F23<=($T$4+180),F23<=($T$4+90))) -> TRUE | U23: =+IF(G23="",0,DATEDIF(F23,G23,"M")/12) -> 10.25 | W23: =+MAX(V23-U23,0) -> 0 | X23: =12-W23 -> 12 | Y23: =+(J23*X23+E23*O23)*T23 -> 44370 | Z23: =(X23*N23*E23/12)*T23 -> 0 | AA23: =+T23*E23 -> 870
A24: Campus at LaJolla (a0103013) | B24: B109 | C24: Ayman Naser DDS, Inc (B109) (t0000604) | D24: Office Net | E24: 2271 | F24: 45924 | G24: 51409 | H24: 181 | I24: 0.58 | J24: 9651.75 | K24: 4.25 | L24: 115821 | M24: 51 | N24: 2.13 | O24: 0 | P24: 14602.53 | Q24: 0 | T24: =+IF(OR(C24="Vacant",G24=""),FALSE,IF($AC24="Yes",F24<=($T$4+180),F24<=($T$4+90))) -> TRUE | U24: =+IF(G24="",0,DATEDIF(F24,G24,"M")/12) -> 15 | V24: 6 | W24: =+MAX(V24-U24,0) -> 0 | X24: =12-W24 -> 12 | Y24: =+(J24*X24+E24*O24)*T24 -> 115821 | Z24: =(X24*N24*E24/12)*T24 -> 4837.23 | AA24: =+T24*E24 -> 2271
A25: Campus at LaJolla (a0103013) | B25: B112 | C25: Skin & Vein Center West, P.C. (B112) (t0000082) | D25: Office Net | E25: 1271 | F25: 44958 | G25: 47238 | H25: 75 | I25: 3.17 | J25: 6011.83 | K25: 4.73 | L25: 72141.96 | M25: 56.76 | N25: 6.24 | O25: 0 | P25: 6609.2 | Q25: 0 | T25: =+IF(OR(C25="Vacant",G25=""),FALSE,IF($AC25="Yes",F25<=($T$4+180),F25<=($T$4+90))) -> TRUE | U25: =+IF(G25="",0,DATEDIF(F25,G25,"M")/12) -> 6.1666667 | W25: =+MAX(V25-U25,0) -> 0 | X25: =12-W25 -> 12 | Y25: =+(J25*X25+E25*O25)*T25 -> 72141.96 | Z25: =(X25*N25*E25/12)*T25 -> 7931.04 | AA25: =+T25*E25 -> 1271
A26: Campus at LaJolla (a0103013) | B26: B114 | C26: Chris Proud (B114) (t0000034) | D26: Office Net | E26: 1027 | F26: 43617 | G26: 47330 | H26: 122 | I26: 6.83 | J26: 4765.28 | K26: 4.64 | L26: 57183.36 | M26: 55.68 | N26: 2.07 | O26: 0 | P26: 3385 | Q26: 0 | T26: =+IF(OR(C26="Vacant",G26=""),FALSE,IF($AC26="Yes",F26<=($T$4+180),F26<=($T$4+90))) -> TRUE | U26: =+IF(G26="",0,DATEDIF(F26,G26,"M")/12) -> 10.083333 | W26: =+MAX(V26-U26,0) -> 0 | X26: =12-W26 -> 12 | Y26: =+(J26*X26+E26*O26)*T26 -> 57183.36 | Z26: =(X26*N26*E26/12)*T26 -> 2125.89 | AA26: =+T26*E26 -> 1027
A27: Campus at LaJolla (a0103013) | B27: B115 | C27: Silva Laine, LLC (B115) (t0000874) | D27: Office Net | E27: 1282 | F27: 46054 | G27: 47968 | H27: 63 | I27: 0.17 | J27: =K27*E27 -> 5769 | K27: 4.5 | L27: =+J27*12 -> 69228 | M27: =+K27*12 -> 54 | N27: 0 | O27: 0 | P27: 0 | Q27: 0 | T27: =+IF(OR(C27="Vacant",G27=""),FALSE,IF($AC27="Yes",F27<=($T$4+180),F27<=($T$4+90))) -> TRUE | U27: =+IF(G27="",0,DATEDIF(F27,G27,"M")/12) -> 5.1666667 | V27: 11 | W27: =+MAX(V27-U27,0) -> 5.8333333 | X27: =12-W27 -> 6.1666667 | Y27: =+(J27*X27+E27*O27)*T27 -> 35575.5 | Z27: =(X27*N27*E27/12)*T27 -> 0 | AA27: =+T27*E27 -> 1282
A28: Campus at LaJolla (a0103013) | B28: B120 | C28: Mehrack Kajian-Faraji (B120) (t0000083) | D28: Office Net | E28: 2530 | F28: 43739 | G28: 48273 | H28: 149 | I28: 6.5 | J28: 11207.9 | K28: 4.43 | L28: 134494.8 | M28: 53.16 | N28: 0.78 | O28: 0 | P28: 14081.28 | Q28: 0 | T28: =+IF(OR(C28="Vacant",G28=""),FALSE,IF($AC28="Yes",F28<=($T$4+180),F28<=($T$4+90))) -> TRUE | U28: =+IF(G28="",0,DATEDIF(F28,G28,"M")/12) -> 12.333333 | W28: =+MAX(V28-U28,0) -> 0 | X28: =12-W28 -> 12 | Y28: =+(J28*X28+E28*O28)*T28 -> 134494.8 | Z28: =(X28*N28*E28/12)*T28 -> 1973.4 | AA28: =+T28*E28 -> 2530
A29: Campus at LaJolla (a0103013) | B29: B123 | C29: Shelley Cassar (B123) (t0000160) | D29: Retail Gross | E29: 1320 | F29: 44545 | G29: 46356 | H29: 60 | I29: 4.33 | J29: 0 | K29: 0 | L29: 0 | M29: 0 | N29: 0 | O29: 3.09 | P29: 1000 | Q29: 0 | T29: =+IF(OR(C29="Vacant",G29=""),FALSE,IF($AC29="Yes",F29<=($T$4+180),F29<=($T$4+90))) -> TRUE | U29: =+IF(G29="",0,DATEDIF(F29,G29,"M")/12) -> 4.9166667 | W29: =+MAX(V29-U29,0) -> 0 | X29: =12-W29 -> 12 | Y29: =+(J29*X29+E29*O29)*T29 -> 4078.8 | Z29: =(X29*N29*E29/12)*T29 -> 0 | AA29: =+T29*E29 -> 1320
A30: Campus at LaJolla (a0103013) | B30: B124 | C30: Robert C. Kim (B124) (t0000085) | D30: Office Net | E30: 2234 | F30: 43252 | G30: 46904 | H30: 120 | I30: 7.83 | J30: 10432.78 | K30: 4.67 | L30: 125193.36 | M30: 56.04 | N30: 6.09 | O30: 0 | P30: 11080.64 | Q30: 0 | T30: =+IF(OR(C30="Vacant",G30=""),FALSE,IF($AC30="Yes",F30<=($T$4+180),F30<=($T$4+90))) -> TRUE | U30: =+IF(G30="",0,DATEDIF(F30,G30,"M")/12) -> 9.9166667 | W30: =+MAX(V30-U30,0) -> 0 | X30: =12-W30 -> 12 | Y30: =+(J30*X30+E30*O30)*T30 -> 125193.36 | Z30: =(X30*N30*E30/12)*T30 -> 13605.06 | AA30: =+T30*E30 -> 2234
A31: Campus at LaJolla (a0103013) | B31: B128 | C31: Claude A. Valenti (B128) (t0000086) | D31: Office Net | E31: 3691 | F31: 44197 | G31: 46203 | H31: 66 | I31: 5.25 | J31: 16055.85 | K31: 4.35 | L31: 192670.2 | M31: 52.2 | N31: 5.58 | O31: 0 | P31: 10807.72 | Q31: 0 | T31: =+IF(OR(C31="Vacant",G31=""),FALSE,IF($AC31="Yes",F31<=($T$4+180),F31<=($T$4+90))) -> TRUE | U31: =+IF(G31="",0,DATEDIF(F31,G31,"M")/12) -> 5.4166667 | W31: =+MAX(V31-U31,0) -> 0 | X31: =12-W31 -> 12 | Y31: =+(J31*X31+E31*O31)*T31 -> 192670.2 | Z31: =(X31*N31*E31/12)*T31 -> 20595.78 | AA31: =+T31*E31 -> 3691
A32: Campus at LaJolla (a0103013) | B32: B129 | C32: Julia Simonton (B129) (t0000087) | D32: Office Net | E32: 1281 | F32: 44896 | G32: 46843 | H32: 64 | I32: 3.33 | J32: 4355.4 | K32: 3.4 | L32: 52264.8 | M32: 40.8 | N32: 0 | O32: 0 | P32: 5879.79 | Q32: 0 | T32: =+IF(OR(C32="Vacant",G32=""),FALSE,IF($AC32="Yes",F32<=($T$4+180),F32<=($T$4+90))) -> TRUE | U32: =+IF(G32="",0,DATEDIF(F32,G32,"M")/12) -> 5.25 | W32: =+MAX(V32-U32,0) -> 0 | X32: =12-W32 -> 12 | Y32: =+(J32*X32+E32*O32)*T32 -> 52264.8 | Z32: =(X32*N32*E32/12)*T32 -> 0 | AA32: =+T32*E32 -> 1281
A33: Campus at LaJolla (a0103013) | B33: B203 | C33: Randolph Foote Alexander and Andrew Alexander (B203) (t0000088) | D33: Office Net | E33: 1292 | F33: 44348 | G33: 47452 | H33: 102 | I33: 4.83 | J33: 5852.76 | K33: 4.53 | L33: 70233.12 | M33: 54.36 | N33: 0.97 | O33: 0 | P33: 4588.33 | Q33: 0 | T33: =+IF(OR(C33="Vacant",G33=""),FALSE,IF($AC33="Yes",F33<=($T$4+180),F33<=($T$4+90))) -> TRUE | U33: =+IF(G33="",0,DATEDIF(F33,G33,"M")/12) -> 8.4166667 | W33: =+MAX(V33-U33,0) -> 0 | X33: =12-W33 -> 12 | Y33: =+(J33*X33+E33*O33)*T33 -> 70233.12 | Z33: =(X33*N33*E33/12)*T33 -> 1253.24 | AA33: =+T33*E33 -> 1292
A34: Campus at LaJolla (a0103013) | B34: B204 | C34: HPA Support Services, LLC (B204) (t0000089) | D34: Office Net | E34: 1310 | F34: 44788 | G34: 46752 | H34: 65 | I34: 3.67 | J34: 5868.8 | K34: 4.48 | L34: 70425.6 | M34: 53.76 | N34: 3.24 | O34: 0 | P34: 6576.2 | Q34: 0 | T34: =+IF(OR(C34="Vacant",G34=""),FALSE,IF($AC34="Yes",F34<=($T$4+180),F34<=($T$4+90))) -> TRUE | U34: =+IF(G34="",0,DATEDIF(F34,G34,"M")/12) -> 5.3333333 | W34: =+MAX(V34-U34,0) -> 0 | X34: =12-W34 -> 12 | Y34: =+(J34*X34+E34*O34)*T34 -> 70425.6 | Z34: =(X34*N34*E34/12)*T34 -> 4244.4 | AA34: =+T34*E34 -> 1310
A35: Campus at LaJolla (a0103013) | B35: B206 | C35: Srinivas Iyengar (B206) (t0000090) | D35: Office Net | E35: 770 | F35: 43892 | G35: 48029 | H35: 136 | I35: 6.08 | J35: 3526.6 | K35: 4.58 | L35: 42319.2 | M35: 54.96 | N35: 5.97 | O35: 0 | P35: 3642.1 | Q35: 0 | T35: =+IF(OR(C35="Vacant",G35=""),FALSE,IF($AC35="Yes",F35<=($T$4+180),F35<=($T$4+90))) -> TRUE | U35: =+IF(G35="",0,DATEDIF(F35,G35,"M")/12) -> 11.25 | W35: =+MAX(V35-U35,0) -> 0 | X35: =12-W35 -> 12 | Y35: =+(J35*X35+E35*O35)*T35 -> 42319.2 | Z35: =(X35*N35*E35/12)*T35 -> 4596.9 | AA35: =+T35*E35 -> 770
A36: Campus at LaJolla (a0103013) | B36: B207 | C36: Fereshteh Maghsoudy, D.M.D., Inc. (B207) (t0000091) | D36: Office Net | E36: 690 | F36: 45017 | G36: 47999 | H36: 98 | I36: 3 | J36: 3513.1 | K36: 5.09 | L36: 42157.2 | M36: 61.1 | N36: 2.29 | O36: 0 | P36: 2507.81 | Q36: 0 | T36: =+IF(OR(C36="Vacant",G36=""),FALSE,IF($AC36="Yes",F36<=($T$4+180),F36<=($T$4+90))) -> TRUE | U36: =+IF(G36="",0,DATEDIF(F36,G36,"M")/12) -> 8.0833333 | W36: =+MAX(V36-U36,0) -> 0 | X36: =12-W36 -> 12 | Y36: =+(J36*X36+E36*O36)*T36 -> 42157.2 | Z36: =(X36*N36*E36/12)*T36 -> 1580.1 | AA36: =+T36*E36 -> 690
A37: Campus at LaJolla (a0103013) | B37: B212 | C37: Brandon W. Goldstein (B212) (t0000070) | D37: Office Net | E37: 1797 | F37: 43191 | G37: 46112 | H37: 96 | I37: 8 | J37: 8398.31 | K37: 4.67 | L37: 100779.72 | M37: 56.08 | N37: 5.78 | O37: 0 | P37: 0 | Q37: 0 | T37: FALSE | U37: =+IF(G37="",0,DATEDIF(F37,G37,"M")/12) -> 7.9166667 | W37: =+MAX(V37-U37,0) -> 0 | X37: =12-W37 -> 12 | Y37: =+(J37*X37+E37*O37)*T37 -> 0 | Z37: =(X37*N37*E37/12)*T37 -> 0 | AA37: =+T37*E37 -> 0
A38: Campus at LaJolla (a0103013) | B38: B214 | C38: Seattle Sperm Bank, LLC. (B214) (t0000093) | D38: Office Net | E38: 2553 | F38: 43619 | G38: 47269 | H38: 120 | I38: 6.83 | J38: 12075.69 | K38: 4.73 | L38: 144908.28 | M38: 56.76 | N38: 6.33 | O38: 0 | P38: 12075.69 | Q38: 0 | T38: =+IF(OR(C38="Vacant",G38=""),FALSE,IF($AC38="Yes",F38<=($T$4+180),F38<=($T$4+90))) -> TRUE | U38: =+IF(G38="",0,DATEDIF(F38,G38,"M")/12) -> 9.9166667 | W38: =+MAX(V38-U38,0) -> 0 | X38: =12-W38 -> 12 | Y38: =+(J38*X38+E38*O38)*T38 -> 144908.28 | Z38: =(X38*N38*E38/12)*T38 -> 16160.49 | AA38: =+T38*E38 -> 2553
A39: Campus at LaJolla (a0103013) | B39: B216 | C39: NKMD MGMT, LLC (B216) (t0000094) | D39: Office Net | E39: 2058 | F39: 45170 | G39: 47149 | H39: 65 | I39: 2.58 | J39: 9816.66 | K39: 4.77 | L39: 117799.92 | M39: 57.24 | N39: 2.79 | O39: 0 | P39: 20826.96 | Q39: 0 | T39: =+IF(OR(C39="Vacant",G39=""),FALSE,IF($AC39="Yes",F39<=($T$4+180),F39<=($T$4+90))) -> TRUE | U39: =+IF(G39="",0,DATEDIF(F39,G39,"M")/12) -> 5.3333333 | W39: =+MAX(V39-U39,0) -> 0 | X39: =12-W39 -> 12 | Y39: =+(J39*X39+E39*O39)*T39 -> 117799.92 | Z39: =(X39*N39*E39/12)*T39 -> 5741.82 | AA39: =+T39*E39 -> 2058
A40: Campus at LaJolla (a0103013) | B40: B223 | C40: Jessica Sperber (Individual) and Clinical and Consulting Psychology Group, LLC (B223) (t0000095) | D40: Office Net | E40: 1397 | F40: 43358 | G40: 47026 | H40: 121 | I40: 7.58 | J40: 6817.36 | K40: 4.88 | L40: 81808.32 | M40: 58.56 | N40: 8.19 | O40: 0 | P40: 7264.4 | Q40: 0 | T40: =+IF(OR(C40="Vacant",G40=""),FALSE,IF($AC40="Yes",F40<=($T$4+180),F40<=($T$4+90))) -> TRUE | U40: =+IF(G40="",0,DATEDIF(F40,G40,"M")/12) -> 10 | W40: =+MAX(V40-U40,0) -> 0 | X40: =12-W40 -> 12 | Y40: =+(J40*X40+E40*O40)*T40 -> 81808.32 | Z40: =(X40*N40*E40/12)*T40 -> 11441.43 | AA40: =+T40*E40 -> 1397
A41: Campus at LaJolla (a0103013) | B41: B225 | C41: Foyouzi Reproductive Genetics Medical Corporation (t0000151) | D41: Office Net | E41: 2532 | F41: 45733 | G41: 49582 | H41: 127 | I41: 1.08 | J41: 11031.6 | K41: 4.36 | L41: 132379.2 | M41: 52.28 | N41: 2.07 | O41: 0 | P41: 0 | Q41: 0 | T41: =+IF(OR(C41="Vacant",G41=""),FALSE,IF($AC41="Yes",F41<=($T$4+180),F41<=($T$4+90))) -> TRUE | U41: =+IF(G41="",0,DATEDIF(F41,G41,"M")/12) -> 10.5 | W41: =+MAX(V41-U41,0) -> 0 | X41: =12-W41 -> 12 | Y41: =+(J41*X41+E41*O41)*T41 -> 132379.2 | Z41: =(X41*N41*E41/12)*T41 -> 5241.24 | AA41: =+T41*E41 -> 2532
A42: Campus at LaJolla (a0103013) | B42: B227 | C42: The Regents of the University of California (B227) (t0000128) | D42: Office Net | E42: 2466 | F42: 42887 | G42: 47483 | H42: 151 | I42: 8.83 | J42: 10924.38 | K42: 4.43 | L42: 131092.56 | M42: 53.16 | N42: 0 | O42: 0 | P42: 0 | Q42: 0 | T42: =+IF(OR(C42="Vacant",G42=""),FALSE,IF($AC42="Yes",F42<=($T$4+180),F42<=($T$4+90))) -> TRUE | U42: =+IF(G42="",0,DATEDIF(F42,G42,"M")/12) -> 12.5 | W42: =+MAX(V42-U42,0) -> 0 | X42: =12-W42 -> 12 | Y42: =+(J42*X42+E42*O42)*T42 -> 131092.56 | Z42: =(X42*N42*E42/12)*T42 -> 0 | AA42: =+T42*E42 -> 2466 | AC42: Yes
A43: Campus at LaJolla (a0103013) | B43: C101 | C43: The Regents of the University of California (C101) (t0000129) | D43: Office Net | E43: 7541 | F43: 43132 | G43: 46783 | H43: 120 | I43: 8.17 | J43: 33912.13 | K43: 4.5 | L43: 406945.56 | M43: 53.96 | N43: 0 | O43: 0 | P43: 0 | Q43: 0 | T43: =+IF(OR(C43="Vacant",G43=""),FALSE,IF($AC43="Yes",F43<=($T$4+180),F43<=($T$4+90))) -> TRUE | U43: =+IF(G43="",0,DATEDIF(F43,G43,"M")/12) -> 9.9166667 | W43: =+MAX(V43-U43,0) -> 0 | X43: =12-W43 -> 12 | Y43: =+(J43*X43+E43*O43)*T43 -> 406945.56 | Z43: =(X43*N43*E43/12)*T43 -> 0 | AA43: =+T43*E43 -> 7541 | AC43: Yes
A44: Campus at LaJolla (a0103013) | B44: C106 | C44: The Regents of the University of California (C106) (t0000130) | D44: Office Net | E44: 2717 | F44: 43770 | G44: 46783 | H44: 99 | I44: 6.42 | J44: 11683.1 | K44: 4.3 | L44: 140197.2 | M44: 51.6 | N44: 0 | O44: 0 | P44: 0 | Q44: 0 | T44: =+IF(OR(C44="Vacant",G44=""),FALSE,IF($AC44="Yes",F44<=($T$4+180),F44<=($T$4+90))) -> TRUE | U44: =+IF(G44="",0,DATEDIF(F44,G44,"M")/12) -> 8.1666667 | W44: =+MAX(V44-U44,0) -> 0 | X44: =12-W44 -> 12 | Y44: =+(J44*X44+E44*O44)*T44 -> 140197.2 | Z44: =(X44*N44*E44/12)*T44 -> 0 | AA44: =+T44*E44 -> 2717
A45: Campus at LaJolla (a0103013) | B45: C108 | C45: Masha Mirkin (C108) (t0000096) | D45: Office Net | E45: 1002 | F45: 44228 | G45: 47879 | H45: 120 | I45: 5.17 | J45: 4529.04 | K45: 4.52 | L45: 54348.48 | M45: 54.24 | N45: 5.24 | O45: 0 | P45: 5100.18 | Q45: 0 | T45: =+IF(OR(C45="Vacant",G45=""),FALSE,IF($AC45="Yes",F45<=($T$4+180),F45<=($T$4+90))) -> TRUE | U45: =+IF(G45="",0,DATEDIF(F45,G45,"M")/12) -> 9.9166667 | W45: =+MAX(V45-U45,0) -> 0 | X45: =12-W45 -> 12 | Y45: =+(J45*X45+E45*O45)*T45 -> 54348.48 | Z45: =(X45*N45*E45/12)*T45 -> 5250.48 | AA45: =+T45*E45 -> 1002
A46: Campus at LaJolla (a0103013) | B46: C110 | C46: Management Office (C110) (t0000157) | D46: Office Net | E46: 1388 | F46: 44201 | I46: 5.25 | J46: 0 | K46: 0 | L46: 0 | M46: 0 | N46: 0 | O46: 0 | P46: 0 | Q46: 0 | T46: =+IF(OR(C46="Vacant",G46=""),FALSE,IF($AC46="Yes",F46<=($T$4+180),F46<=($T$4+90))) -> FALSE | U46: =+IF(G46="",0,DATEDIF(F46,G46,"M")/12) -> 0 | W46: =+MAX(V46-U46,0) -> 0 | X46: =12-W46 -> 12 | Y46: =+(J46*X46+E46*O46)*T46 -> 0 | Z46: =(X46*N46*E46/12)*T46 -> 0 | AA46: =+T46*E46 -> 0
A47: Campus at LaJolla (a0103013) | B47: C112 | C47: Charles Moreau and Kendra Dobalian (C112) (t0000154) | D47: Office Net | E47: 922 | F47: 45383 | G47: 46934 | H47: 51 | I47: 2 | J47: 4084.46 | K47: 4.43 | L47: 49013.52 | M47: 53.16 | N47: 2.06 | O47: 0 | P47: 4462.48 | Q47: 0 | T47: =+IF(OR(C47="Vacant",G47=""),FALSE,IF($AC47="Yes",F47<=($T$4+180),F47<=($T$4+90))) -> TRUE | U47: =+IF(G47="",0,DATEDIF(F47,G47,"M")/12) -> 4.1666667 | W47: =+MAX(V47-U47,0) -> 0 | X47: =12-W47 -> 12 | Y47: =+(J47*X47+E47*O47)*T47 -> 49013.52 | Z47: =(X47*N47*E47/12)*T47 -> 1899.32 | AA47: =+T47*E47 -> 922
A48: Campus at LaJolla (a0103013) | B48: C113 | C48: Garrett M. Guess, DDS, Inc. (C113) (t0000168) | D48: Office Net | E48: 1259 | F48: 45836 | G48: 49674 | H48: 127 | I48: 0.83 | J48: 5539.6 | K48: 4.4 | L48: 66475.2 | M48: 52.8 | N48: 0 | O48: 0 | P48: 14881.38 | Q48: 0 | T48: =+IF(OR(C48="Vacant",G48=""),FALSE,IF($AC48="Yes",F48<=($T$4+180),F48<=($T$4+90))) -> TRUE | U48: =+IF(G48="",0,DATEDIF(F48,G48,"M")/12) -> 10.5 | W48: =+MAX(V48-U48,0) -> 0 | X48: =12-W48 -> 12 | Y48: =+(J48*X48+E48*O48)*T48 -> 66475.2 | Z48: =(X48*N48*E48/12)*T48 -> 0 | AA48: =+T48*E48 -> 1259
A49: Campus at LaJolla (a0103013) | B49: C114, C135 | C49: The Med Spa Boutique Inc. (C114 & C135) (t0000464) | D49: Office Net | E49: 2321 | F49: 45722 | G49: 48029 | H49: 76 | I49: 1.08 | J49: 10264.5 | K49: 4.42 | L49: 123174 | M49: 53.07 | N49: 0.93 | O49: 0 | P49: 0 | Q49: 0 | T49: =+IF(OR(C49="Vacant",G49=""),FALSE,IF($AC49="Yes",F49<=($T$4+180),F49<=($T$4+90))) -> TRUE | U49: =+IF(G49="",0,DATEDIF(F49,G49,"M")/12) -> 6.25 | W49: =+MAX(V49-U49,0) -> 0 | X49: =12-W49 -> 12 | Y49: =+(J49*X49+E49*O49)*T49 -> 123174 | Z49: =(X49*N49*E49/12)*T49 -> 2158.53 | AA49: =+T49*E49 -> 2321
A50: Campus at LaJolla (a0103013) | B50: C115 | C50: John Andrus (C115) (t0000098) | D50: Office Net | E50: 994 | F50: 45139 | G50: 46265 | H50: 37 | I50: 2.67 | J50: 5009.76 | K50: 5.04 | L50: 60117.12 | M50: 60.48 | N50: 9.24 | O50: 0 | P50: 2748.34 | Q50: 0 | T50: =+IF(OR(C50="Vacant",G50=""),FALSE,IF($AC50="Yes",F50<=($T$4+180),F50<=($T$4+90))) -> TRUE | U50: =+IF(G50="",0,DATEDIF(F50,G50,"M")/12) -> 3 | W50: =+MAX(V50-U50,0) -> 0 | X50: =12-W50 -> 12 | Y50: =+(J50*X50+E50*O50)*T50 -> 60117.12 | Z50: =(X50*N50*E50/12)*T50 -> 9184.56 | AA50: =+T50*E50 -> 994
A51: Campus at LaJolla (a0103013) | B51: C117 | C51: Iman Shirali (C117) (t0000099) | D51: Office Net | E51: 1426 | F51: 44562 | G51: 46112 | H51: 51 | I51: 4.25 | J51: 6630.9 | K51: 4.65 | L51: 79570.8 | M51: 55.8 | N51: 3.23 | O51: 0 | P51: 0 | Q51: 0 | S51: Delinquent | T51: FALSE | U51: =+IF(G51="",0,DATEDIF(F51,G51,"M")/12) -> 4.1666667 | W51: =+MAX(V51-U51,0) -> 0 | X51: =12-W51 -> 12 | Y51: =+(J51*X51+E51*O51)*T51 -> 0 | Z51: =(X51*N51*E51/12)*T51 -> 0 | AA51: =+T51*E51 -> 0
A52: Campus at LaJolla (a0103013) | B52: C121 | C52: Acacia Psychological Corporation (C121) (t0000101) | D52: Office Net | E52: 3489 | F52: 43466 | G52: 47269 | H52: 125 | I52: 7.25 | J52: 16747.2 | K52: 4.8 | L52: 200966.4 | M52: 57.6 | N52: 6.65 | O52: 0 | P52: 18282.36 | Q52: 0 | T52: =+IF(OR(C52="Vacant",G52=""),FALSE,IF($AC52="Yes",F52<=($T$4+180),F52<=($T$4+90))) -> TRUE | U52: =+IF(G52="",0,DATEDIF(F52,G52,"M")/12) -> 10.333333 | W52: =+MAX(V52-U52,0) -> 0 | X52: =12-W52 -> 12 | Y52: =+(J52*X52+E52*O52)*T52 -> 200966.4 | Z52: =(X52*N52*E52/12)*T52 -> 23201.85 | AA52: =+T52*E52 -> 3489
A53: Campus at LaJolla (a0103013) | B53: C129 | C53: Daniel Michaels, M.D., Inc. and Gregory M. Berkoff, D.C., Inc. (C129) (t0000103) | D53: Office Net | E53: 3227 | F53: 44333 | G53: 48395 | H53: 134 | I53: 4.92 | J53: 13972.91 | K53: 4.33 | L53: 167674.92 | M53: 51.96 | N53: 6.36 | O53: 0 | P53: 17199.91 | Q53: 0 | T53: =+IF(OR(C53="Vacant",G53=""),FALSE,IF($AC53="Yes",F53<=($T$4+180),F53<=($T$4+90))) -> TRUE | U53: =+IF(G53="",0,DATEDIF(F53,G53,"M")/12) -> 11.083333 | W53: =+MAX(V53-U53,0) -> 0 | X53: =12-W53 -> 12 | Y53: =+(J53*X53+E53*O53)*T53 -> 167674.92 | Z53: =(X53*N53*E53/12)*T53 -> 20523.72 | AA53: =+T53*E53 -> 3227
A54: Campus at LaJolla (a0103013) | B54: C130 | C54: Torrey Pines Eye Care (C130) (t0000104) | D54: Office Net | E54: 2038 | F54: 44628 | G54: 47573 | H54: 97 | I54: 4.08 | J54: 8804.16 | K54: 4.32 | L54: 105649.92 | M54: 51.84 | N54: 6.36 | O54: 0 | P54: 9904.68 | Q54: 0 | T54: =+IF(OR(C54="Vacant",G54=""),FALSE,IF($AC54="Yes",F54<=($T$4+180),F54<=($T$4+90))) -> TRUE | U54: =+IF(G54="",0,DATEDIF(F54,G54,"M")/12) -> 8 | W54: =+MAX(V54-U54,0) -> 0 | X54: =12-W54 -> 12 | Y54: =+(J54*X54+E54*O54)*T54 -> 105649.92 | Z54: =(X54*N54*E54/12)*T54 -> 12961.68 | AA54: =+T54*E54 -> 2038
A55: Campus at LaJolla (a0103013) | B55: C131 | C55: Positive Development Services, LLC (C131) (t0000105) | D55: Office Net | E55: 3162 | F55: 45105 | G55: 47817 | H55: 90 | I55: 2.83 | J55: 14978.64 | K55: 4.74 | L55: 179743.68 | M55: 56.84 | N55: 3.24 | O55: 0 | P55: 15746.76 | Q55: 0 | T55: =+IF(OR(C55="Vacant",G55=""),FALSE,IF($AC55="Yes",F55<=($T$4+180),F55<=($T$4+90))) -> TRUE | U55: =+IF(G55="",0,DATEDIF(F55,G55,"M")/12) -> 7.4166667 | W55: =+MAX(V55-U55,0) -> 0 | X55: =12-W55 -> 12 | Y55: =+(J55*X55+E55*O55)*T55 -> 179743.68 | Z55: =(X55*N55*E55/12)*T55 -> 10244.88 | AA55: =+T55*E55 -> 3162
A56: Campus at LaJolla (a0103013) | B56: C134 | C56: College Area Pregnancy Services (C134) (t0000155) | D56: Office Net | E56: 1026 | F56: 45383 | G56: 49613 | H56: 139 | I56: 2 | J56: 4760.64 | K56: 4.64 | L56: 57127.68 | M56: 55.68 | N56: 1.58 | O56: 0 | P56: 6391.98 | Q56: 0 | T56: =+IF(OR(C56="Vacant",G56=""),FALSE,IF($AC56="Yes",F56<=($T$4+180),F56<=($T$4+90))) -> TRUE | U56: =+IF(G56="",0,DATEDIF(F56,G56,"M")/12) -> 11.5 | W56: =+MAX(V56-U56,0) -> 0 | X56: =12-W56 -> 12 | Y56: =+(J56*X56+E56*O56)*T56 -> 57127.68 | Z56: =(X56*N56*E56/12)*T56 -> 1621.08 | AA56: =+T56*E56 -> 1026
A57: Campus at LaJolla (a0103013) | B57: C207 | C57: The Regents of the University of California (C207) (t0000131) | D57: Office Net | E57: 6031 | F57: 43313 | G57: 46783 | H57: 114 | I57: 7.67 | J57: 25933.3 | K57: 4.3 | L57: 311199.6 | M57: 51.6 | N57: 0 | O57: 0 | P57: 0 | Q57: 0 | T57: =+IF(OR(C57="Vacant",G57=""),FALSE,IF($AC57="Yes",F57<=($T$4+180),F57<=($T$4+90))) -> TRUE | U57: =+IF(G57="",0,DATEDIF(F57,G57,"M")/12) -> 9.4166667 | W57: =+MAX(V57-U57,0) -> 0 | X57: =12-W57 -> 12 | Y57: =+(J57*X57+E57*O57)*T57 -> 311199.6 | Z57: =(X57*N57*E57/12)*T57 -> 0 | AA57: =+T57*E57 -> 6031 | AC57: Yes
A58: Campus at LaJolla (a0103013) | B58: C210 | C58: James Strother (C210) (t0000100) | D58: Office Net | E58: 1064 | F58: 45231 | G58: 47057 | H58: 60 | I58: 2.42 | J58: 5149.76 | K58: 4.84 | L58: 61797.12 | M58: 58.08 | N58: 8.63 | O58: 0 | P58: 3047.36 | Q58: 0 | T58: =+IF(OR(C58="Vacant",G58=""),FALSE,IF($AC58="Yes",F58<=($T$4+180),F58<=($T$4+90))) -> TRUE | U58: =+IF(G58="",0,DATEDIF(F58,G58,"M")/12) -> 4.9166667 | W58: =+MAX(V58-U58,0) -> 0 | X58: =12-W58 -> 12 | Y58: =+(J58*X58+E58*O58)*T58 -> 61797.12 | Z58: =(X58*N58*E58/12)*T58 -> 9182.32 | AA58: =+T58*E58 -> 1064
A59: Campus at LaJolla (a0103013) | B59: C212 | C59: Essenza Wellness Center (C212) (t0000823) | D59: Office Gross | E59: 2323 | F59: 46023 | G59: 47938 | H59: 63 | I59: 0.25 | J59: 10453.5 | K59: 4.5 | L59: =+J59*12 -> 125442 | M59: =+K59*12 -> 54 | N59: 0 | O59: 0 | P59: 12706.81 | Q59: 0 | T59: =+IF(OR(C59="Vacant",G59=""),FALSE,IF($AC59="Yes",F59<=($T$4+180),F59<=($T$4+90))) -> TRUE | U59: =+IF(G59="",0,DATEDIF(F59,G59,"M")/12) -> 5.1666667 | V59: 5 | W59: =+MAX(V59-U59,0) -> 0 | X59: =12-W59 -> 12 | Y59: =+(J59*X59+E59*O59)*T59 -> 125442 | Z59: =(X59*N59*E59/12)*T59 -> 0 | AA59: =+T59*E59 -> 2323
A60: Campus at LaJolla (a0103013) | B60: C216 | C60: The Regents of the University of California (C216) (t0000134) | D60: Office Net | E60: 2831 | F60: 43313 | G60: 46783 | H60: 114 | I60: 7.67 | J60: 12173.3 | K60: 4.3 | L60: 146079.6 | M60: 51.6 | N60: 0 | O60: 0 | P60: 0 | Q60: 0 | T60: =+IF(OR(C60="Vacant",G60=""),FALSE,IF($AC60="Yes",F60<=($T$4+180),F60<=($T$4+90))) -> TRUE | U60: =+IF(G60="",0,DATEDIF(F60,G60,"M")/12) -> 9.4166667 | W60: =+MAX(V60-U60,0) -> 0 | X60: =12-W60 -> 12 | Y60: =+(J60*X60+E60*O60)*T60 -> 146079.6 | Z60: =(X60*N60*E60/12)*T60 -> 0 | AA60: =+T60*E60 -> 2831 | AC60: Yes
A61: Campus at LaJolla (a0103013) | B61: C217 | C61: Community Psychiatry Management, LLC (C217) (t0000106) | D61: Office Net | E61: 3288 | F61: 43800 | G61: 46371 | H61: 84 | I61: 6.33 | J61: 16407.12 | K61: 4.99 | L61: 196885.44 | M61: 59.88 | N61: 5.95 | O61: 0 | P61: 16407.12 | Q61: 0 | T61: =+IF(OR(C61="Vacant",G61=""),FALSE,IF($AC61="Yes",F61<=($T$4+180),F61<=($T$4+90))) -> TRUE | U61: =+IF(G61="",0,DATEDIF(F61,G61,"M")/12) -> 7 | W61: =+MAX(V61-U61,0) -> 0 | X61: =12-W61 -> 12 | Y61: =+(J61*X61+E61*O61)*T61 -> 196885.44 | Z61: =(X61*N61*E61/12)*T61 -> 19563.6 | AA61: =+T61*E61 -> 3288
A62: Campus at LaJolla (a0103013) | B62: C225 | C62: Strive Pharmacy San Diego, LLC (C225) (t0000107) | D62: Office Net | E62: 2558 | F62: 44287 | G62: 47087 | H62: 92 | I62: 5 | J62: 11485.42 | K62: 4.49 | L62: 137825.04 | M62: 53.88 | N62: 6.37 | O62: 0 | P62: 12636.52 | Q62: 0 | T62: =+IF(OR(C62="Vacant",G62=""),FALSE,IF($AC62="Yes",F62<=($T$4+180),F62<=($T$4+90))) -> TRUE | U62: =+IF(G62="",0,DATEDIF(F62,G62,"M")/12) -> 7.5833333 | W62: =+MAX(V62-U62,0) -> 0 | X62: =12-W62 -> 12 | Y62: =+(J62*X62+E62*O62)*T62 -> 137825.04 | Z62: =(X62*N62*E62/12)*T62 -> 16294.46 | AA62: =+T62*E62 -> 2558
A63: Campus at LaJolla (a0103013) | B63: C226 | C63: Paradyne LLC (C226) (t0000824) | D63: Office Gross | E63: 1263 | F63: 46023 | G63: 47634 | H63: 53 | I63: 0.25 | J63: 0 | K63: 0 | L63: 0 | M63: 0 | N63: 0 | O63: 0 | P63: 0 | Q63: 0 | S63: Delinquent | T63: FALSE | U63: =+IF(G63="",0,DATEDIF(F63,G63,"M")/12) -> 4.3333333 | W63: =+MAX(V63-U63,0) -> 0 | X63: =12-W63 -> 12 | Y63: =+(J63*X63+E63*O63)*T63 -> 0 | Z63: =(X63*N63*E63/12)*T63 -> 0 | AA63: =+T63*E63 -> 0
A64: Campus at LaJolla (a0103013) | B64: C227 | C64: Knownwell, Inc. (C227) (t0000738) | D64: Office Net | E64: 3868 | F64: 45984 | G64: 49887 | H64: 129 | I64: 0.42 | J64: =+K64*E64 -> 16245.6 | K64: 4.2 | L64: =+J64*12 -> 194947.2 | M64: =+L64/E64 -> 50.4 | N64: 0 | O64: 0 | P64: 21815.52 | Q64: 0 | T64: =+IF(OR(C64="Vacant",G64=""),FALSE,IF($AC64="Yes",F64<=($T$4+180),F64<=($T$4+90))) -> TRUE | U64: =+IF(G64="",0,DATEDIF(F64,G64,"M")/12) -> 10.666667 | V64: 9 | W64: =+MAX(V64-U64,0) -> 0 | X64: =12-W64 -> 12 | Y64: =+(J64*X64+E64*O64)*T64 -> 194947.2 | Z64: =(X64*N64*E64/12)*T64 -> 0 | AA64: =+T64*E64 -> 3868
A65: Campus at LaJolla (a0103013) | B65: C230 | C65: Pacific Coast Psychiatric Associates, Inc. (C230) (t0000108) | D65: Office Net | E65: 4627 | F65: 43901 | G65: 46660 | H65: 91 | I65: 6.08 | J65: 21191.66 | K65: 4.58 | L65: 254299.92 | M65: 54.96 | N65: 6.03 | O65: 0 | P65: 22579.76 | Q65: 0 | T65: =+IF(OR(C65="Vacant",G65=""),FALSE,IF($AC65="Yes",F65<=($T$4+180),F65<=($T$4+90))) -> TRUE | U65: =+IF(G65="",0,DATEDIF(F65,G65,"M")/12) -> 7.5 | W65: =+MAX(V65-U65,0) -> 0 | X65: =12-W65 -> 12 | Y65: =+(J65*X65+E65*O65)*T65 -> 254299.92 | Z65: =(X65*N65*E65/12)*T65 -> 27900.81 | AA65: =+T65*E65 -> 4627
A66: Campus at LaJolla (a0103013) | B66: NODE | C66: The Regents of the University of California (Node) (t0000135) | D66: Office Net | E66: 90 | F66: 44927 | G66: 46783 | H66: 61 | I66: 3.25 | J66: 354.34 | K66: 3.94 | L66: 4252.08 | M66: 47.25 | N66: 0 | O66: 0 | P66: 0 | T66: =+IF(OR(C66="Vacant",G66=""),FALSE,IF($AC66="Yes",F66<=($T$4+180),F66<=($T$4+90))) -> TRUE | U66: =+IF(G66="",0,DATEDIF(F66,G66,"M")/12) -> 5 | W66: =+MAX(V66-U66,0) -> 0 | X66: =12-W66 -> 12 | Y66: =+(J66*X66+E66*O66)*T66 -> 4252.08 | Z66: =(X66*N66*E66/12)*T66 -> 0 | AA66: =+T66*E66 -> 90
A67: Campus at LaJolla (a0103013) | B67: A124 | C67: VACANT | E67: 11249 | T67: =+IF(OR(C67="Vacant",G67=""),FALSE,IF($AC67="Yes",F67<=($T$4+180),F67<=($T$4+90))) -> FALSE | U67: =+IF(G67="",0,DATEDIF(F67,G67,"M")/12) -> 0 | W67: =+MAX(V67-U67,0) -> 0 | X67: =12-W67 -> 12 | Y67: =+(J67*X67+E67*O67)*T67 -> 0 | Z67: =(X67*N67*E67/12)*T67 -> 0 | AA67: =+T67*E67 -> 0
A68: Campus at LaJolla (a0103013) | B68: A126 | C68: VACANT | E68: 2280 | T68: =+IF(OR(C68="Vacant",G68=""),FALSE,IF($AC68="Yes",F68<=($T$4+180),F68<=($T$4+90))) -> FALSE | U68: =+IF(G68="",0,DATEDIF(F68,G68,"M")/12) -> 0 | W68: =+MAX(V68-U68,0) -> 0 | X68: =12-W68 -> 12 | Y68: =+(J68*X68+E68*O68)*T68 -> 0 | Z68: =(X68*N68*E68/12)*T68 -> 0 | AA68: =+T68*E68 -> 0
A69: Campus at LaJolla (a0103013) | B69: A203 | C69: VACANT | E69: 5176 | T69: =+IF(OR(C69="Vacant",G69=""),FALSE,IF($AC69="Yes",F69<=($T$4+180),F69<=($T$4+90))) -> FALSE | U69: =+IF(G69="",0,DATEDIF(F69,G69,"M")/12) -> 0 | W69: =+MAX(V69-U69,0) -> 0 | X69: =12-W69 -> 12 | Y69: =+(J69*X69+E69*O69)*T69 -> 0 | Z69: =(X69*N69*E69/12)*T69 -> 0 | AA69: =+T69*E69 -> 0
A70: Campus at LaJolla (a0103013) | B70: A204 | C70: VACANT | E70: 2537 | T70: =+IF(OR(C70="Vacant",G70=""),FALSE,IF($AC70="Yes",F70<=($T$4+180),F70<=($T$4+90))) -> FALSE | U70: =+IF(G70="",0,DATEDIF(F70,G70,"M")/12) -> 0 | W70: =+MAX(V70-U70,0) -> 0 | X70: =12-W70 -> 12 | Y70: =+(J70*X70+E70*O70)*T70 -> 0 | Z70: =(X70*N70*E70/12)*T70 -> 0 | AA70: =+T70*E70 -> 0
A71: Campus at LaJolla (a0103013) | B71: A206 | C71: VACANT | E71: 3631 | T71: =+IF(OR(C71="Vacant",G71=""),FALSE,IF($AC71="Yes",F71<=($T$4+180),F71<=($T$4+90))) -> FALSE | U71: =+IF(G71="",0,DATEDIF(F71,G71,"M")/12) -> 0 | W71: =+MAX(V71-U71,0) -> 0 | X71: =12-W71 -> 12 | Y71: =+(J71*X71+E71*O71)*T71 -> 0 | Z71: =(X71*N71*E71/12)*T71 -> 0 | AA71: =+T71*E71 -> 0
A72: Campus at LaJolla (a0103013) | B72: A208 | C72: VACANT | E72: 3122 | T72: =+IF(OR(C72="Vacant",G72=""),FALSE,IF($AC72="Yes",F72<=($T$4+180),F72<=($T$4+90))) -> FALSE | U72: =+IF(G72="",0,DATEDIF(F72,G72,"M")/12) -> 0 | W72: =+MAX(V72-U72,0) -> 0 | X72: =12-W72 -> 12 | Y72: =+(J72*X72+E72*O72)*T72 -> 0 | Z72: =(X72*N72*E72/12)*T72 -> 0 | AA72: =+T72*E72 -> 0
A73: Campus at LaJolla (a0103013) | B73: A212 | C73: VACANT | E73: 4953 | T73: =+IF(OR(C73="Vacant",G73=""),FALSE,IF($AC73="Yes",F73<=($T$4+180),F73<=($T$4+90))) -> FALSE | U73: =+IF(G73="",0,DATEDIF(F73,G73,"M")/12) -> 0 | W73: =+MAX(V73-U73,0) -> 0 | X73: =12-W73 -> 12 | Y73: =+(J73*X73+E73*O73)*T73 -> 0 | Z73: =(X73*N73*E73/12)*T73 -> 0 | AA73: =+T73*E73 -> 0
A74: Campus at LaJolla (a0103013) | B74: A217 | C74: VACANT | E74: 2509 | T74: =+IF(OR(C74="Vacant",G74=""),FALSE,IF($AC74="Yes",F74<=($T$4+180),F74<=($T$4+90))) -> FALSE | U74: =+IF(G74="",0,DATEDIF(F74,G74,"M")/12) -> 0 | W74: =+MAX(V74-U74,0) -> 0 | X74: =12-W74 -> 12 | Y74: =+(J74*X74+E74*O74)*T74 -> 0 | Z74: =(X74*N74*E74/12)*T74 -> 0 | AA74: =+T74*E74 -> 0
A75: Campus at LaJolla (a0103013) | B75: B122 | C75: VACANT | E75: 6415 | T75: =+IF(OR(C75="Vacant",G75=""),FALSE,IF($AC75="Yes",F75<=($T$4+180),F75<=($T$4+90))) -> FALSE | U75: =+IF(G75="",0,DATEDIF(F75,G75,"M")/12) -> 0 | W75: =+MAX(V75-U75,0) -> 0 | X75: =12-W75 -> 12 | Y75: =+(J75*X75+E75*O75)*T75 -> 0 | Z75: =(X75*N75*E75/12)*T75 -> 0 | AA75: =+T75*E75 -> 0
A76: Campus at LaJolla (a0103013) | B76: B208 | C76: VACANT | E76: 823 | T76: =+IF(OR(C76="Vacant",G76=""),FALSE,IF($AC76="Yes",F76<=($T$4+180),F76<=($T$4+90))) -> FALSE | U76: =+IF(G76="",0,DATEDIF(F76,G76,"M")/12) -> 0 | W76: =+MAX(V76-U76,0) -> 0 | X76: =12-W76 -> 12 | Y76: =+(J76*X76+E76*O76)*T76 -> 0 | Z76: =(X76*N76*E76/12)*T76 -> 0 | AA76: =+T76*E76 -> 0
A77: Campus at LaJolla (a0103013) | B77: B218 | C77: VACANT | E77: 2268 | T77: =+IF(OR(C77="Vacant",G77=""),FALSE,IF($AC77="Yes",F77<=($T$4+180),F77<=($T$4+90))) -> FALSE | U77: =+IF(G77="",0,DATEDIF(F77,G77,"M")/12) -> 0 | W77: =+MAX(V77-U77,0) -> 0 | X77: =12-W77 -> 12 | Y77: =+(J77*X77+E77*O77)*T77 -> 0 | Z77: =(X77*N77*E77/12)*T77 -> 0 | AA77: =+T77*E77 -> 0
A78: Campus at LaJolla (a0103013) | B78: B220 | C78: VACANT | E78: 2057 | T78: =+IF(OR(C78="Vacant",G78=""),FALSE,IF($AC78="Yes",F78<=($T$4+180),F78<=($T$4+90))) -> FALSE | U78: =+IF(G78="",0,DATEDIF(F78,G78,"M")/12) -> 0 | W78: =+MAX(V78-U78,0) -> 0 | X78: =12-W78 -> 12 | Y78: =+(J78*X78+E78*O78)*T78 -> 0 | Z78: =(X78*N78*E78/12)*T78 -> 0 | AA78: =+T78*E78 -> 0
... A83: Campus at LaJolla (a0103013) | B83: ROOF | C83: VACANT | E83: 0 | T83: =+IF(OR(C83="Vacant",G83=""),FALSE,IF($AC83="Yes",F83<=($T$4+180),F83<=($T$4+90))) -> FALSE | U83: =+IF(G83="",0,DATEDIF(F83,G83,"M")/12) -> 0 | W83: =+MAX(V83-U83,0) -> 0 | X83: =12-W83 -> 12 | Y83: =+(J83*X83+E83*O83)*T83 -> 0 | Z83: =(X83*N83*E83/12)*T83 -> 0 | AA83: =+T83*E83 -> 0
T84: =+IF(OR(C84="Vacant",G84=""),FALSE,IF($AC84="Yes",F84<=($T$4+180),F84<=($T$4+90))) -> FALSE | U84: =+IF(G84="",0,DATEDIF(F84,G84,"M")/12) -> 0 | W84: =+MAX(V84-U84,0) -> 0 | X84: =12-W84 -> 12 | Y84: =+(J84*X84+E84*O84)*T84 -> 0 | Z84: =(X84*N84*E84/12)*T84 -> 0 | AA84: =+T84*E84 -> 0
A85: Campus at LaJolla (a0103013) | B85: ROOF | C85: VACANT | E85: 0 | T85: =+IF(OR(C85="Vacant",G85=""),FALSE,IF($AC85="Yes",F85<=($T$4+180),F85<=($T$4+90))) -> FALSE | U85: =+IF(G85="",0,DATEDIF(F85,G85,"M")/12) -> 0 | W85: =+MAX(V85-U85,0) -> 0 | X85: =12-W85 -> 12 | Y85: =+(J85*X85+E85*O85)*T85 -> 0 | Z85: =(X85*N85*E85/12)*T85 -> 0 | AA85: =+T85*E85 -> 0
X87: Total Rent | Y87: =SUM(Y6:Y85) -> 6695002.4 | Z87: =SUM(Z6:Z85) -> 435812.98 | AA87: =SUM(AA6:AA85) -> 123777
A90: Occupancy Summary | J90: Monthly Rent | K90: Annual Rent
A91: Occupied | B91: =SUMIF($C:$C,"<>Vacant",$E:$E) -> 131085 | J91: =SUM(J6:J86) -> 575410.55 | K91: =J91*12 -> 6904926.6
A92: Vacant | B92: =SUMIF($C:$C,"Vacant",$E:$E) -> 60459
A93: Total/Wtd. Average | B93: =SUM(B91:B92) -> 191544
A95: =+A91 -> Occupied | B95: =B91/$B$93 -> 0.68435973 | J95: Annual in-place | K95: =K91/B91 -> 52.675185
A96: =+A92 -> Vacant | B96: =B92/$B$93 -> 0.31564027 | J96: Per Mo. | K96: =K95/12 -> 4.3895987
I103: 1282
I104: =+E49-1042 -> 1279

Sheet WALT
A1: 1
C2: Tenant | D2: SF | E2: % of NRA | F2: LXD | G2: Exp. Year | H2: WALT | J2: Date
C3: The Regents of the University of California (8910) (t0000137) | D3: 14750 | E3: =$D3/$D$65 -> 0.077042005 | F3: 49887 | G3: =YEAR(F3) -> 2036 | H3: =(F3-$J$3)/365 -> 10.342466 | J3: 46112
C4: Coleman Meadows DDS, Inc. (A105) (t0000071) | D4: 2548 | E4: =$D4/$D$65 -> 0.01330868 | F4: 47330 | G4: =YEAR(F4) -> 2029 | H4: =(F4-$J$3)/365 -> 3.3369863
C5: Bronner Handwerger (A107) (t0000072) | D5: 1438 | E5: =$D5/$D$65 -> 0.0075109426 | F5: 47118 | G5: =YEAR(F5) -> 2028 | H5: =(F5-$J$3)/365 -> 2.7561644
C6: Nancy Markel (A108) (t0000073) | D6: 620 | E6: =$D6/$D$65 -> 0.0032383758 | F6: 46173 | G6: =YEAR(F6) -> 2026 | H6: =(F6-$J$3)/365 -> 0.16712329
C7: Advantech GS Enterprises, Inc. (B208) (t0000074) | D7: 1284 | E7: =$D7/$D$65 -> 0.0067065718 | F7: 48060 | G7: =YEAR(F7) -> 2031 | H7: =(F7-$J$3)/365 -> 5.3369863
C8: Maria Hiraldo (A110) (t0000075) | D8: 326 | E8: =$D8/$D$65 -> 0.0017027589 | F8: 47695 | G8: =YEAR(F8) -> 2030 | H8: =(F8-$J$3)/365 -> 4.3369863
C9: SureFire CPR (A118) (t0000149) | D9: 309 | E9: =$D9/$D$65 -> 0.0016139647 | F9: 46599 | G9: =YEAR(F9) -> 2027 | H9: =(F9-$J$3)/365 -> 1.3342466
C10: La Jolla Sol Ventures, Inc. (A125) (t0000076) | D10: 1846 | E10: =$D10/$D$65 -> 0.0096420028 | F10: 46904 | G10: =YEAR(F10) -> 2028 | H10: =(F10-$J$3)/365 -> 2.169863
C11: Chemometec, Inc. (A127) (t0000077) | D11: 1469 | E11: =$D11/$D$65 -> 0.0076728614 | F11: 46507 | G11: =YEAR(F11) -> 2027 | H11: =(F11-$J$3)/365 -> 1.0821918
C12: J Zeidan, DMD, Inc. (A128) (t0000078) | D12: 2354 | E12: =$D12/$D$65 -> 0.012295382 | F12: 46934 | G12: =YEAR(F12) -> 2028 | H12: =(F12-$J$3)/365 -> 2.2520548
C13: Katherine A. Thomson, DDS, MS Inc. (A207) (t0000066) | D13: 1665 | E13: =$D13/$D$65 -> 0.008696606 | F13: 47542 | G13: =YEAR(F13) -> 2030 | H13: =(F13-$J$3)/365 -> 3.9178082
C14: Arash Khatami (A215) (t0000079) | D14: 907 | E14: =$D14/$D$65 -> 0.0047374304 | F14: 46478 | G14: =YEAR(F14) -> 2027 | H14: =(F14-$J$3)/365 -> 1.0027397
C15: Marin Wellness Pharmacy LLC (A218) (t0000606) | D15: 1422 | E15: =$D15/$D$65 -> 0.0074273716 | F15: 46904 | G15: =YEAR(F15) -> 2028 | H15: =(F15-$J$3)/365 -> 2.169863
... C61: The Regents of the University of California (Node) (t0000135) | D61: 90 | E61: =$D61/$D$65 -> 0.00047008681 | F61: 46783 | G61: =YEAR(F61) -> 2028 | H61: =(F61-$J$3)/365 -> 1.8383562
H62: =SUMPRODUCT(H3:H61,D3:D61)/D63 -> 4.2523262
C63: Occupied SF | D63: =SUM(D3:D61)+I65 -> 131085 | E63: =D63/$D$65 -> 0.68468144
C64: Vacant SF | D64: =D65-D63 -> 60369 | E64: =D64/$D$65 -> 0.31531856
C65: Total SF | D65: =OSAR!C11 -> 191454 | E65: =D65/$D$65 -> 1 | H65: Unit Offset | I65: 2822
C67: *Excludes known vacates, MTM tenants, and amenity spaces.

Sheet Aging Report
A1: Aging Detail
A2: DB Caption: Live 09/11/2023 All Selected Properties Status: Current, Past, Future Age As Of: 03/31/2026 Post To: 03/2026
A3: Property | B3: Customer | C3: Lease | D3: Status | E3: Tran# | F3: Charge | G3: Date | H3: Month | I3: Current | J3: 0-30 | K3: 31-60 | L3: 61-90 | M3: Over | N3: Pre- | O3: Total
F4: Code | I4: Owed | J4: Owed | K4: Owed | L4: Owed | M4: 90 Owed | N4: payments | O4: Owed
A5: Campus at LaJolla (a0103013)
A6: Acacia Psychological Corporation (C121) (t0000101)
A7: a0103013 | C7: Acacia Psychological Corporation (C121) | D7: Current | E7: R-20487 | F7: Prepay | G7: 46112 | H7: 03/2026 | I7: 0 | J7: 0 | K7: 0 | L7: 0 | M7: 0 | N7: -18681 | O7: -18681
C8: Acacia Psychological Corporation (C121) | I8: 0 | J8: 0 | K8: 0 | L8: 0 | M8: 0 | N8: -18681 | O8: -18681
A10: Ayman Naser DDS, Inc (B109) (t0000604)
A11: a0103013 | C11: Ayman Naser DDS, Inc (B109) | D11: Current | E11: C-54392 | F11: cam | G11: 46082 | H11: 03/2026 | I11: 0.2 | J11: 0.2 | K11: 0 | L11: 0 | M11: 0 | N11: 0 | O11: 0.2
C12: Ayman Naser DDS, Inc (B109) | I12: 0.2 | J12: 0.2 | K12: 0 | L12: 0 | M12: 0 | N12: 0 | O12: 0.2
A14: Chemometec, Inc. (A127) (t0000077)
A15: a0103013 | C15: Chemometec, Inc. (A127) | D15: Current | E15: R-20025 | F15: Prepay | G15: 46106 | H15: 03/2026 | I15: 0 | J15: 0 | K15: 0 | L15: 0 | M15: 0 | N15: -7052.45 | O15: -7052.45
C16: Chemometec, Inc. (A127) | I16: 0 | J16: 0 | K16: 0 | L16: 0 | M16: 0 | N16: -7052.45 | O16: -7052.45
A18: Community Psychiatry Management, LLC (C217) (t0000106)
A19: a0103013 | C19: Community Psychiatry Management, LLC (C217) | D19: Current | E19: R-18215 | F19: Prepay | G19: 46052 | H19: 01/2026 | I19: 0 | J19: 0 | K19: 0 | L19: 0 | M19: 0 | N19: -956.68 | O19: -956.68
A20: a0103013 | C20: Community Psychiatry Management, LLC (C217) | D20: Current | E20: R-18215 | F20: Prepay | G20: 46052 | H20: 01/2026 | I20: 0 | J20: 0 | K20: 0 | L20: 0 | M20: 0 | N20: -118.53 | O20: -118.53
A21: a0103013 | C21: Community Psychiatry Management, LLC (C217) | D21: Current | E21: R-20486 | F21: Prepay | G21: 46112 | H21: 03/2026 | I21: 0 | J21: 0 | K21: 0 | L21: 0 | M21: 0 | N21: -18037.8 | O21: -18037.8
C22: Community Psychiatry Management, LLC (C217) | I22: 0 | J22: 0 | K22: 0 | L22: 0 | M22: 0 | N22: -19113.01 | O22: -19113.01
A24: Foyouzi Reproductive Genetics Medical Corporation (t0000151)
A25: a0103013 | C25: Foyouzi Reproductive Genetics Medical Corporation | D25: Current | E25: R-14093 | F25: Prepay | G25: 45938 | H25: 10/2025 | I25: 0 | J25: 0 | K25: 0 | L25: 0 | M25: 0 | N25: -767.06 | O25: -767.06
A26: a0103013 | C26: Foyouzi Reproductive Genetics Medical Corporation | D26: Current | E26: R-14093 | F26: Prepay | G26: 45938 | H26: 10/2025 | I26: 0 | J26: 0 | K26: 0 | L26: 0 | M26: 0 | N26: -437.38 | O26: -437.38
A27: a0103013 | C27: Foyouzi Reproductive Genetics Medical Corporation | D27: Current | E27: R-14093 | F27: Prepay | G27: 45938 | H27: 10/2025 | I27: 0 | J27: 0 | K27: 0 | L27: 0 | M27: 0 | N27: -7026.58 | O27: -7026.58
A28: a0103013 | C28: Foyouzi Reproductive Genetics Medical Corporation | D28: Current | E28: R-15619 | F28: Prepay | G28: 45978 | H28: 11/2025 | I28: 0 | J28: 0 | K28: 0 | L28: 0 | M28: 0 | N28: -11031.6 | O28: -11031.6
C29: Foyouzi Reproductive Genetics Medical Corporation | I29: 0 | J29: 0 | K29: 0 | L29: 0 | M29: 0 | N29: -19262.62 | O29: -19262.62
A31: Garrett M. Guess, DDS, Inc. (C113) (t0000168)
A32: a0103013 | C32: Garrett M. Guess, DDS, Inc. (C113) | D32: Current | E32: R-20294 | F32: Prepay | G32: 46111 | H32: 03/2026 | I32: 0 | J32: 0 | K32: 0 | L32: 0 | M32: 0 | N32: -5539.6 | O32: -5539.6
C33: Garrett M. Guess, DDS, Inc. (C113) | I33: 0 | J33: 0 | K33: 0 | L33: 0 | M33: 0 | N33: -5539.6 | O33: -5539.6
A35: Iman Shirali (C117) (t0000099)
A36: a0103013 | C36: Iman Shirali (C117) | D36: Past | E36: C-30782 | F36: cam | G36: 45870 | H36: 08/2025 | I36: 144.63 | J36: 0 | K36: 0 | L36: 0 | M36: 144.63 | N36: 0 | O36: 144.63
A37: a0103013 | C37: Iman Shirali (C117) | D37: Past | E37: C-30783 | F37: rnoff | G37: 45870 | H37: 08/2025 | I37: 6402.74 | J37: 0 | K37: 0 | L37: 0 | M37: 6402.74 | N37: 0 | O37: 6402.74
A38: a0103013 | C38: Iman Shirali (C117) | D38: Past | E38: C-33916 | F38: cam | G38: 45901 | H38: 09/2025 | I38: 276.78 | J38: 0 | K38: 0 | L38: 0 | M38: 276.78 | N38: 0 | O38: 276.78
A39: a0103013 | C39: Iman Shirali (C117) | D39: Past | E39: C-33917 | F39: rnoff | G39: 45901 | H39: 09/2025 | I39: 6402.74 | J39: 0 | K39: 0 | L39: 0 | M39: 6402.74 | N39: 0 | O39: 6402.74
A40: a0103013 | C40: Iman Shirali (C117) | D40: Past | E40: C-37018 | F40: cam | G40: 45931 | H40: 10/2025 | I40: 276.78 | J40: 0 | K40: 0 | L40: 0 | M40: 276.78 | N40: 0 | O40: 276.78
A41: a0103013 | C41: Iman Shirali (C117) | D41: Past | E41: C-37019 | F41: rnoff | G41: 45931 | H41: 10/2025 | I41: 3201.37 | J41: 0 | K41: 0 | L41: 0 | M41: 3201.37 | N41: 0 | O41: 3201.37
A42: a0103013 | C42: Iman Shirali (C117) | D42: Past | E42: C-40216 | F42: cam | G42: 45962 | H42: 11/2025 | I42: 276.78 | J42: 0 | K42: 0 | L42: 0 | M42: 276.78 | N42: 0 | O42: 276.78
A43: a0103013 | C43: Iman Shirali (C117) | D43: Past | E43: C-40217 | F43: rnoff | G43: 45962 | H43: 11/2025 | I43: 3201.37 | J43: 0 | K43: 0 | L43: 0 | M43: 3201.37 | N43: 0 | O43: 3201.37
A44: a0103013 | C44: Iman Shirali (C117) | D44: Past | E44: C-43547 | F44: cam | G44: 45992 | H44: 12/2025 | I44: 276.78 | J44: 0 | K44: 0 | L44: 0 | M44: 276.78 | N44: 0 | O44: 276.78
A45: a0103013 | C45: Iman Shirali (C117) | D45: Past | E45: C-43548 | F45: rnoff | G45: 45992 | H45: 12/2025 | I45: 3201.37 | J45: 0 | K45: 0 | L45: 0 | M45: 3201.37 | N45: 0 | O45: 3201.37
A46: a0103013 | C46: Iman Shirali (C117) | D46: Past | E46: C-50303 | F46: cam | G46: 46054 | H46: 02/2026 | I46: 383.32 | J46: 0 | K46: 383.32 | L46: 0 | M46: 0 | N46: 0 | O46: 383.32
A47: a0103013 | C47: Iman Shirali (C117) | D47: Past | E47: C-54352 | F47: cam | G47: 46082 | H47: 03/2026 | I47: 383.32 | J47: 383.32 | K47: 0 | L47: 0 | M47: 0 | N47: 0 | O47: 383.32
A48: a0103013 | C48: Iman Shirali (C117) | D48: Past | E48: C-54353 | F48: rnoff | G48: 46082 | H48: 03/2026 | I48: 6630.9 | J48: 6630.9 | K48: 0 | L48: 0 | M48: 0 | N48: 0 | O48: 6630.9
C49: Iman Shirali (C117) | I49: 31058.88 | J49: 7014.22 | K49: 383.32 | L49: 0 | M49: 23661.34 | N49: 0 | O49: 31058.88 | Q49: Delinquent
A51: J Zeidan, DMD, Inc. (A128) (t0000078)
A52: a0103013 | C52: J Zeidan, DMD, Inc. (A128) | D52: Current | E52: R-20216 | F52: Prepay | G52: 46108 | H52: 03/2026 | I52: 0 | J52: 0 | K52: 0 | L52: 0 | M52: 0 | N52: -11534.6 | O52: -11534.6
C53: J Zeidan, DMD, Inc. (A128) | I53: 0 | J53: 0 | K53: 0 | L53: 0 | M53: 0 | N53: -11534.6 | O53: -11534.6
A55: Jessica Sperber (Individual) and Clinical and Consulting Psychology Group, LLC (B223) (t0000095)
A56: a0103013 | C56: Jessica Sperber (Individual) and Clinical and Consulting Psychology Group, LLC (B223) | D56: Current | E56: R-20293 | F56: Prepay | G56: 46111 | H56: 03/2026 | I56: 0 | J56: 0 | K56: 0 | L56: 0 | M56: 0 | N56: -7771.15 | O56: -7771.15
C57: Jessica Sperber (Individual) and Clinical and Consulting Psychology Group, LLC (B223) | I57: 0 | J57: 0 | K57: 0 | L57: 0 | M57: 0 | N57: -7771.15 | O57: -7771.15
A59: Julia Simonton (B129) (t0000087)
A60: a0103013 | C60: Julia Simonton (B129) | D60: Current | E60: C-54332 | F60: rnoff | G60: 46082 | H60: 03/2026 | I60: 1790.1 | J60: 1790.1 | K60: 0 | L60: 0 | M60: 0 | N60: 0 | O60: 1790.1
C61: Julia Simonton (B129) | I61: 1790.1 | J61: 1790.1 | K61: 0 | L61: 0 | M61: 0 | N61: 0 | O61: 1790.1
A63: Katherine A. Thomson, DDS, MS Inc. (A207) (t0000066)
A64: a0103013 | C64: Katherine A. Thomson, DDS, MS Inc. (A207) | D64: Current | E64: R-20001 | F64: Prepay | G64: 46104 | H64: 03/2026 | I64: 0 | J64: 0 | K64: 0 | L64: 0 | M64: 0 | N64: -8545.07 | O64: -8545.07
C65: Katherine A. Thomson, DDS, MS Inc. (A207) | I65: 0 | J65: 0 | K65: 0 | L65: 0 | M65: 0 | N65: -8545.07 | O65: -8545.07
A67: La Jolla Sol Ventures, Inc. (A125) (t0000076)
A68: a0103013 | C68: La Jolla Sol Ventures, Inc. (A125) | D68: Current | E68: R-19849 | F68: Prepay | G68: 46091 | H68: 03/2026 | I68: 0 | J68: 0 | K68: 0 | L68: 0 | M68: 0 | N68: -43.45 | O68: -43.45
C69: La Jolla Sol Ventures, Inc. (A125) | I69: 0 | J69: 0 | K69: 0 | L69: 0 | M69: 0 | N69: -43.45 | O69: -43.45
A71: Marin Wellness Pharmacy LLC (A218) (t0000606)
A72: a0103013 | C72: Marin Wellness Pharmacy LLC (A218) | D72: Current | E72: R-19665 | F72: Prepay | G72: 46085 | H72: 03/2026 | I72: 0 | J72: 0 | K72: 0 | L72: 0 | M72: 0 | N72: -6256.8 | O72: -6256.8
C73: Marin Wellness Pharmacy LLC (A218) | I73: 0 | J73: 0 | K73: 0 | L73: 0 | M73: 0 | N73: -6256.8 | O73: -6256.8
A75: Nancy Markel (A108) (t0000073)
A76: a0103013 | C76: Nancy Markel (A108) | D76: Current | E76: C-50260 | F76: rnoff | G76: 46054 | H76: 02/2026 | I76: 738.41 | J76: 0 | K76: 738.41 | L76: 0 | M76: 0 | N76: 0 | O76: 738.41
C77: Nancy Markel (A108) | I77: 738.41 | J77: 0 | K77: 738.41 | L77: 0 | M77: 0 | N77: 0 | O77: 738.41
A79: Pacific Coast Psychiatric Associates, Inc. (C230) (t0000108)
A80: a0103013 | C80: Pacific Coast Psychiatric Associates, Inc. (C230) | D80: Current | E80: R-20485 | F80: Prepay | G80: 46112 | H80: 03/2026 | I80: 0 | J80: 0 | K80: 0 | L80: 0 | M80: 0 | N80: -24210.99 | O80: -24210.99
C81: Pacific Coast Psychiatric Associates, Inc. (C230) | I81: 0 | J81: 0 | K81: 0 | L81: 0 | M81: 0 | N81: -24210.99 | O81: -24210.99
A83: Paradyne LLC (C226) (t0000824)
A84: a0103013 | C84: Paradyne LLC (C226) | D84: Current | E84: C-47007 | F84: sdep | G84: 46009 | H84: 12/2025 | I84: 12326.88 | J84: 0 | K84: 0 | L84: 0 | M84: 12326.88 | N84: 0 | O84: 12326.88
A85: a0103013 | C85: Paradyne LLC (C226) | D85: Current | E85: C-47412 | F85: rnoff | G85: 46023 | H85: 01/2026 | I85: 5367.75 | J85: 0 | K85: 0 | L85: 5367.75 | M85: 0 | N85: 0 | O85: 5367.75
C86: Paradyne LLC (C226) | I86: 17694.63 | J86: 0 | K86: 0 | L86: 5367.75 | M86: 12326.88 | N86: 0 | O86: 17694.63 | Q86: Delinquent
A88: Positive Development Services, LLC (C131) (t0000105)
A89: a0103013 | C89: Positive Development Services, LLC (C131) | D89: Current | E89: R-20484 | F89: Prepay | G89: 46112 | H89: 03/2026 | I89: 0 | J89: 0 | K89: 0 | L89: 0 | M89: 0 | N89: -16752.71 | O89: -16752.71
A90: a0103013 | C90: Positive Development Services, LLC (C131) | D90: Current | E90: R-20484 | F90: Prepay | G90: 46112 | H90: 03/2026 | I90: 0 | J90: 0 | K90: 0 | L90: 0 | M90: 0 | N90: -920.09 | O90: -920.09
C91: Positive Development Services, LLC (C131) | I91: 0 | J91: 0 | K91: 0 | L91: 0 | M91: 0 | N91: -17672.8 | O91: -17672.8
A93: Shelley Cassar (B123) (t0000160)
A94: a0103013 | C94: Shelley Cassar (B123) | D94: Current | E94: C-55046 | F94: misc | G94: 46082 | H94: 03/2026 | I94: 513.02 | J94: 513.02 | K94: 0 | L94: 0 | M94: 0 | N94: 0 | O94: 513.02
C95: Shelley Cassar (B123) | I95: 513.02 | J95: 513.02 | K95: 0 | L95: 0 | M95: 0 | N95: 0 | O95: 513.02
A97: Skin & Vein Center West, P.C. (B112) (t0000082)
A98: a0103013 | C98: Skin & Vein Center West, P.C. (B112) | D98: Current | E98: R-20031 | F98: Prepay | G98: 46107 | H98: 03/2026 | I98: 0 | J98: 0 | K98: 0 | L98: 0 | M98: 0 | N98: -6672.82 | O98: -6672.82
C99: Skin & Vein Center West, P.C. (B112) | I99: 0 | J99: 0 | K99: 0 | L99: 0 | M99: 0 | N99: -6672.82 | O99: -6672.82
A101: SureFire CPR (A118) (t0000149)
A102: a0103013 | C102: SureFire CPR (A118) | D102: Current | E102: R-19626 | F102: Prepay | G102: 46084 | H102: 03/2026 | I102: 0 | J102: 0 | K102: 0 | L102: 0 | M102: 0 | N102: -11.76 | O102: -11.76
C103: SureFire CPR (A118) | I103: 0 | J103: 0 | K103: 0 | L103: 0 | M103: 0 | N103: -11.76 | O103: -11.76
A105: The Med Spa Boutique Inc. (C114 & C135) (t0000464)
A106: a0103013 | C106: The Med Spa Boutique Inc. (C114 & C135) | D106: Current | E106: C-54390 | F106: rnoff | G106: 46082 | H106: 03/2026 | I106: 809.42 | J106: 809.42 | K106: 0 | L106: 0 | M106: 0 | N106: 0 | O106: 809.42
C107: The Med Spa Boutique Inc. (C114 & C135) | I107: 809.42 | J107: 809.42 | K107: 0 | L107: 0 | M107: 0 | N107: 0 | O107: 809.42
A109: The Regents of the University of California (8910) (t0000137)
A110: a0103013 | C110: The Regents of the University of California (8910) | D110: Current | E110: R-15447 | F110: Prepay | G110: 45964 | H110: 11/2025 | I110: 0 | J110: 0 | K110: 0 | L110: 0 | M110: 0 | N110: -9300.45 | O110: -9300.45
A111: a0103013 | C111: The Regents of the University of California (8910) | D111: Current | E111: R-15532 | F111: Prepay | G111: 45971 | H111: 11/2025 | I111: 0 | J111: 0 | K111: 0 | L111: 0 | M111: 0 | N111: -1727.84 | O111: -1727.84
A112: a0103013 | C112: The Regents of the University of California (8910) | D112: Current | E112: R-15633 | F112: Prepay | G112: 45980 | H112: 11/2025 | I112: 0 | J112: 0 | K112: 0 | L112: 0 | M112: 0 | N112: -5905.64 | O112: -5905.64
A113: a0103013 | C113: The Regents of the University of California (8910) | D113: Current | E113: R-15990 | F113: Prepay | G113: 45989 | H113: 11/2025 | I113: 0 | J113: 0 | K113: 0 | L113: 0 | M113: 0 | N113: -9300.45 | O113: -9300.45
A114: a0103013 | C114: The Regents of the University of California (8910) | D114: Current | E114: C-43573 | F114: rtabao | G114: 45992 | H114: 12/2025 | I114: -42866.91 | J114: 0 | K114: 0 | L114: 0 | M114: -42866.91 | N114: 0 | O114: -42866.91
A115: a0103013 | C115: The Regents of the University of California (8910) | D115: Current | E115: R-16869 | F115: Prepay | G115: 46017 | H115: 12/2025 | I115: 0 | J115: 0 | K115: 0 | L115: 0 | M115: 0 | N115: -1840.44 | O115: -1840.44
A116: a0103013 | C116: The Regents of the University of California (8910) | D116: Current | E116: C-46969 | F116: servfee | G116: 46023 | H116: 01/2026 | I116: 240.26 | J116: 0 | K116: 0 | L116: 240.26 | M116: 0 | N116: 0 | O116: 240.26
A117: a0103013 | C117: The Regents of the University of California (8910) | D117: Current | E117: C-46970 | F117: servfee | G117: 46023 | H117: 01/2026 | I117: 240.26 | J117: 0 | K117: 0 | L117: 240.26 | M117: 0 | N117: 0 | O117: 240.26
A118: a0103013 | C118: The Regents of the University of California (8910) | D118: Current | E118: C-46971 | F118: servfee | G118: 46023 | H118: 01/2026 | I118: 240.26 | J118: 0 | K118: 0 | L118: 240.26 | M118: 0 | N118: 0 | O118: 240.26
A119: a0103013 | C119: The Regents of the University of California (8910) | D119: Current | E119: C-46972 | F119: servfee | G119: 46023 | H119: 01/2026 | I119: 55 | J119: 0 | K119: 0 | L119: 55 | M119: 0 | N119: 0 | O119: 55
A120: a0103013 | C120: The Regents of the University of California (8910) | D120: Current | E120: C-46973 | F120: servfee | G120: 46023 | H120: 01/2026 | I120: 285 | J120: 0 | K120: 0 | L120: 285 | M120: 0 | N120: 0 | O120: 285
A121: a0103013 | C121: The Regents of the University of California (8910) | D121: Current | E121: C-46974 | F121: servfee | G121: 46023 | H121: 01/2026 | I121: 503.53 | J121: 0 | K121: 0 | L121: 503.53 | M121: 0 | N121: 0 | O121: 503.53
...

Sheet coding
A1: Line Item | B1: Code | G1: Base Rent | I1: Gross Potential Rent (3)
A2: INCOME | G2: Expense Reimbursement | I2: Less: Vacancy Loss
A3: OPERATING REVENUE | G3: Percentage Rent | I3: OR
A4: TENANT RENTS & SERVICES | G4: Parking Income | I4: Base Rent (3)
A5: OFFICE | G5: Other Income | I5: Expense Reimbursement
A6: Rent-Office | B6: Base Rent | C6: Base Rent (3) | I6: Percentage Rent
A7: Rent-Office Parking | B7: Parking Income | C7: Parking Income | G7: Effective Gross Income | I7: Parking Income
A8: Rent Abatement-Office | B8: Base Rent | C8: Base Rent (3) | I8: Other Income
A9: TOTAL OFFICE | G9: OPERATING EXPENSES
A10: RESIDENTIAL | G10: Real Estate Taxes | I10: *Effective Gross Income
A11: REIMBURSABLE EXPENSES | G11: Property Insurance
A12: CAM Recovery-Estimate | B12: Expense Reimbursement | C12: Expense Reimbursement | G12: Utilities
A13: CAM Recovery-Y/End | B13: Expense Reimbursement | C13: Expense Reimbursement | G13: Repairs & Maintenance | I13: OPERATING EXPENSES:
A14: Utilities Recovery-Estimate | B14: Expense Reimbursement | C14: Expense Reimbursement | G14: Janitorial | I14: Real Estate Taxes
A15: Misc Income | B15: Expense Reimbursement | C15: Expense Reimbursement | G15: Management Fees | I15: Property Insurance
A16: TOTAL REIMBURSABLE EXPENSES | G16: Payroll & Benefits | I16: Utilities
A17: OTHER OPERATING INCOME | G17: Advertising & Marketing | I17: Repairs and Maintenance
A18: Tenant Service Revenue | B18: Other Income | C18: Other Income | G18: Professional Fees | I18: Janitorial
A19: Cost of Tenant Services | B19: Other Income | C19: Other Income | G19: General and Administrative | I19: Management Fees
A20: Miscellaneous | B20: Other Income | C20: Other Income | G20: Other Expenses | I20: Payroll & Benefits
A21: TOTAL OTHER OPERATING INCOME | G21: Ground Rent | I21: Advertising & Marketing
A22: TOTAL OPERATING REVENUE | G22: Total Operating Expenses | I22: Professional Fees
A23: OPERATING EXPENSES | G23: =TTM!T35 -> Non-Operating Expenses | I23: General and Administrative
A24: OPERATING EXPENSES - RECOVERABLE | G24: =TTM!T36 -> Interest Expense | I24: Other Expenses
A25: CLEANING - RECOVERABLE | G25: =TTM!T37 -> Debt Service | I25: Ground Rent
A26: Cleaning-Day Porter | B26: Janitorial | C26: Janitorial
A27: Cleaning-Contract Srvcs | B27: Janitorial | C27: Janitorial
A28: Cleaning-Window Cleaning | B28: Janitorial | C28: Janitorial
A29: Cleaning-Supplies | B29: Janitorial | C29: Janitorial
A30: TOTAL CLEANING - RECOVERABLE
A31: REPAIR & MAINTENANCE - RECOVERABLE
A32: RM-Pay/Wages | B32: Repairs & Maintenance | C32: Repairs and Maintenance
A33: RM-Supplies | B33: Repairs & Maintenance | C33: Repairs and Maintenance
A34: RM-Uniforms | B34: Repairs & Maintenance | C34: Repairs and Maintenance
A35: RM-Equipment | B35: Repairs & Maintenance | C35: Repairs and Maintenance
A36: RM-Roof | B36: Repairs & Maintenance | C36: Repairs and Maintenance
A37: RM-Keys/Access Cards/Locks | B37: Repairs & Maintenance | C37: Repairs and Maintenance
A38: RM-Signage | B38: Repairs & Maintenance | C38: Repairs and Maintenance
A39: RM-Pest Control | B39: Repairs & Maintenance | C39: Repairs and Maintenance
A40: RM-Windows/Doors | B40: Repairs & Maintenance | C40: Repairs and Maintenance
A41: RM-Office Exp/Supplies | B41: Repairs & Maintenance | C41: Repairs and Maintenance
A42: RM-Communications/Radio/Pagers | B42: Repairs & Maintenance | C42: Repairs and Maintenance
A43: RM-Miscellaneous | B43: Repairs & Maintenance | C43: Repairs and Maintenance
... A53: RM-Plumbing Supplies | B53: Repairs & Maintenance | C53: Repairs and Maintenance
A54: TOTAL REPAIR & MAINTENANCE - RECOVERABLE
A55: SECURITY FIRE / LIFE SAFETY - RECOVERABLE
A56: Security-Contract Srvcs | B56: Other Expenses | C56: Other Expenses
A57: Security-Supplies | B57: Other Expenses | C57: Other Expenses
A58: Security-Miscellaneous | B58: Other Expenses | C58: Other Expenses
A59: Fire/Life-Alarm System | B59: Other Expenses | C59: Other Expenses
A60: Fire/Life-Sprinklers | B60: Other Expenses | C60: Other Expenses
A61: Fire/Life-Safety | B61: Other Expenses | C61: Other Expenses
A62: Fire/Life-Miscellaneous | B62: Other Expenses | C62: Other Expenses
A63: TOTAL SECURITY FIRE / LIFE SAFETY - RECOVERABLE
A64: UTILITIES - RECOVERABLE
A65: Electric | B65: Utilities | C65: Utilities
A66: Gas | B66: Utilities | C66: Utilities
A67: Water & Sewage | B67: Utilities | C67: Utilities
A68: Water & Sewage - Common Areas/Bldg Equipment | B68: Utilities | C68: Utilities
A69: Trash Removal | B69: Utilities | C69: Utilities
A70: TOTAL UTILITIES - RECOVERABLE
A71: LANDSCAPING - RECOVERABLE
A72: Landscaping-Contract Srvcs | B72: Professional Fees | C72: Professional Fees
A73: Landscaping-R&M | B73: Repairs & Maintenance | C73: Repairs and Maintenance
A74: Landscaping-Miscellaneous | B74: Repairs & Maintenance | C74: Repairs and Maintenance
A75: TOTAL LANDSCAPING - RECOVERABLE
A76: PARKING - RECOVERABLE
A77: Parking Lot-Contract Srvcs | B77: Professional Fees | C77: Professional Fees
A78: Parking Lot-R&M | B78: Repairs & Maintenance | C78: Repairs and Maintenance
A79: Parking Lot-Sweeping | B79: Repairs & Maintenance | C79: Repairs and Maintenance
A80: TOTAL PARKING - RECOVERABLE
A81: GENERAL AND ADMINISTRATIVE - RECOVERABLE
A82: Admin-Pay/Wages | B82: Payroll & Benefits | C82: Payroll & Benefits
A83: Admin-Property Management Fee | B83: Management Fees | C83: Management Fees
A84: Admin-Contract Srvcs | B84: Professional Fees | C84: Professional Fees
A85: Admin-Office Exp/Supplies | B85: General and Administrative | C85: General and Administrative
A86: Admin-Postage | B86: General and Administrative | C86: General and Administrative
A87: Admin-Telephone | B87: General and Administrative | C87: General and Administrative
A88: Admin-Dues License Subscpt | B88: General and Administrative | C88: General and Administrative
A89: Admin-Training Development | B89: General and Administrative | C89: General and Administrative
A90: Admin-Bank Fees | B90: General and Administrative | C90: General and Administrative
A91: Admin-Computer/Software | B91: General and Administrative | C91: General and Administrative
A92: Admin-Tax/License/Permits | B92: General and Administrative | C92: General and Administrative
A93: Admin-Miscellaneous | B93: General and Administrative | C93: General and Administrative
A94: Admin-Cellular Phones/Pager/Radios | B94: General and Administrative | C94: General and Administrative
A95: TOTAL GENERAL AND ADMINISTRATIVE - RECOVERABLE
A96: INSURANCE - RECOVERABLE
A97: Insurance-Property | B97: Property Insurance | C97: Property Insurance
A98: Insurance-Gen Liability | B98: Property Insurance | C98: Property Insurance
A99: Insurance-Earthquake | B99: Property Insurance | C99: Property Insurance
A100: TOTAL INSURANCE - RECOVERABLE
A101: REAL ESTATE TAXES - RECOVERABLE
A102: Real Estate Taxes | B102: Real Estate Taxes | C102: Real Estate Taxes
A103: Taxes-Personal Property | B103: Real Estate Taxes | C103: Real Estate Taxes
A104: Property Tax Consultant Fees | B104: Real Estate Taxes | C104: Real Estate Taxes
A105: Taxes-Other | B105: Real Estate Taxes | C105: Real Estate Taxes
A106: TOTAL REAL ESTATE TAXES - RECOVERABLE
A107: TOTAL OPERATING EXPENSES - RECOVERABLE
A108: OPERATING EXPENSES - NON RECOVERABLE
A109: CLEANING - NON RECOVERABLE
...

Sheet Tax
A1: https://www.sdttc.com/content/ttc/en/tax-collection/prior-year-tax-records.html
A2: https://wps.sdttc.com/webpayments/CoSDTreasurer2/search
A4: Parcel Number | B4: 1st Installment | C4: 2nd Installment | D4: Annual Total
A5: 344-250-10-00 | B5: =+C5 -> 519137.82 | C5: 519137.82 | D5: =SUM(B5:C5) -> 1038275.6
A6: Total | D6: =SUM(D5:D5) -> 1038275.6
A8: From | B8: 45839
A9: To | B9: 46203

Sheet Insurance
Q2: Insurance Catgeory | R2: Premium
Q3: Property | R3: 64143.72
Q4: General Liability | R4: 20057.28
Q5: Excess Liability | R5: 6768.56
Q6: Pollution Liability | R6: 5295.22
Q7: DIC/EQ | R7: 87583.63
Q8: Earthquake | R8: 3135.33
Q9: Total | R9: =SUM(R3:R8) -> 186983.74
Q12: From | R12: 45794
Q13: To | R13: =+R12+365 -> 46159

Sheet Future Funding
C2: Spec Buildout | D2: CapEx | E2: TILC | F2: Interest | G2: Total
B3: FF Commitment | C3: 15175000 | D3: 20098000 | E3: 4109000 | F3: 5565000 | G3: =SUM(C3:F3) -> 44947000
B4: Advanced to Date | C4: 12807229 | D4: 14920038 | E4: 1041863 | F4: 4851643 | G4: =SUM(C4:F4) -> 33620773
B5: % Billed | C5: =C4/C3 -> 0.84396896 | D5: =D4/D3 -> 0.74236431 | E5: =E4/E3 -> 0.25355634 | F5: =F4/F3 -> 0.87181366 | G5: =G4/G3 -> 0.74800928
B7: Remaining | C7: =C3-C4 -> 2367771 | D7: =D3-D4 -> 5177962 | E7: =E3-E4 -> 3067137 | F7: =+F3-F4 -> 713357 | G7: =SUM(C7:F7) -> 11326227
B9: *As of Draw #22
