Workbook
Name BiMonthly: #REF!
Name CMNOTES: #REF!
Name EffGrowth: #REF!
Name Expense_Growth: #REF!
Name Market: #REF!
Name MktGrowth: #REF!
Name N_Units: #REF!
Name OpexMonths: #REF!
Name Property_Name: #REF!
Name Quarterly_Growth: #REF!
Name Rent: #REF!
Name RESULTS: #REF!

Sheet (New) Comm OSAR
C1: CREFC Investor Reporting Package
C2: COMMERCIAL OPERATING STATEMENT ANALYSIS REPORT (includes Retail/Office/Industrial/Mixed Use/Self Storage)
C3: ="as of " &TEXT($I$15,"mm/dd/yyyy") -> as of 03/31/2026
C4: PROPERTY OVERVIEW | H4: Allocated Loan Amount/Percentage
C5: Property ID | E5: 1001-001 | F5: Paid Thru Date | G5: Debt Outside Trust (1) | H5: $ | I5: %
C6: Note A-Scheduled Loan Balance | E6: 42768425 | F6: 46112 | G6: X or Blank | I6: =IFERROR(E6/SUM($E$6:$E$8),0) -> 1
C7: Note B-Scheduled Loan Balance | F7: ='[1](Old) Comm OSAR'!G7 -> MM/DD/YY | G7: X or Blank | I7: =IFERROR(E7/SUM($E$6:$E$8),0) -> 0
C8: Note C-Scheduled Loan Balance | F8: ='[1](Old) Comm OSAR'!G8 -> MM/DD/YY | G8: X or Blank | I8: =IFERROR(E8/SUM($E$6:$E$8),0) -> 0
C9: Property Name | E9: Hialeah Infill Industrial Park
C10: Property Type | E10: Industrial
C11: Property Address, City, State | E11: 3455 NW 54th St & 5400 NW 32nd Ct & 5530 NW 32nd Ct Miami FL
C12: Current Net Rentable SF/Units/Beds/Rooms | E12: ='1Q26 RR'!F57 -> 298769 | F12: ='[1](Old) Comm OSAR'!G12 -> SF | G12: Use second box to specify sqft.,units…
C13: Year Built/Year Renovated | E13: 1959-1968 | F13: ='[1](Old) Comm OSAR'!G13 -> YYYY
C14: Cap Ex Reserve (annually)/per Unit.etc. (2) | E14: 0.25 | F14: ='[1](Old) Comm OSAR'!G14 -> (annual/per SF) | G14: specify annual/per unit…
C15: Statement Ending Date | E15: MM/DD/YY | F15: 45838 | G15: 45930 | H15: 46022 | I15: 46112
C16: Occupancy Rate (physical) | E16: 1 | F16: 0.53475853 | G16: 0.53475853 | H16: 0.5348 | I16: ='1Q26 RR'!F62 -> 0.44819576
C17: Occupancy Date | E17: =E15 -> MM/DD/YY | F17: 45838 | G17: 45930 | H17: 46022 | I17: 46112
E18: (1) "X" if debt is outside of the trust, otherwise leave blank
E19: (2) Total $ amount of Capital Reserves required annually by loan documents
C21: INCOME:
C22: Number of Mos. Covered | F22: DY Test | G22: DY Test | H22: T12 | I22: DY Test | J22: (prcdng yr to base) | K22: (prcdng yr to 2nd prcdng)
C23: Period Ended | E23: At Contribution | F23: 2nd Preceding | G23: Preceding | H23: Current | I23: Current | J23: YYYY-U/W | K23: =YEAR('[2](Old) Comm OSAR'!H24)&"-"&YEAR(F6) -> 2025-2026 | N23: QoQ Variance
C24: Statement Ending Date | E24: Information | F24: as of 9/30/25 | G24: as of 12/31/25 | H24: ="as of "&TEXT($F$6,"mm/dd/yy") -> as of 03/31/26 | I24: ="as of "&TEXT($F$6,"mm/dd/yy") -> as of 03/31/26 | J24: Variance | K24: Variance | L24: Notes | N24: Value | O24: %
C25: Gross Potential Rent (3) | E25: 2442036 | F25: 1605912.4 | G25: 1630918.4 | H25: ='1Q26 T12'!O13 -> 1604326.7 | I25: =SUM('1Q26 RR'!V:V) -> 1413927 | J25: =IF(E25=0," ",(I25-E25)/E25) -> -0.42100486 | K25: =IF(G25=0," ",(I25-G25)/G25) -> -0.13304862 | L25: Annualized in-place RR | N25: =IFERROR(I25-G25,0) -> -216991.45 | O25: =IFERROR(N25/G25,"") -> -0.13304862
C26: Less: Vacancy Loss | E26: 0 | F26: 0 | G26: 0 | H26: 0 | I26: =-IF(I16>0.95,(I16-0.95)*I25,0) -> 0 | J26: =IF(E26=0," ",(I26-E26)/E26) | K26: =IF(G26=0," ",(I26-G26)/G26) | L26: ="Greater of actual ("&TEXT(1-$I$16,"0%")&") or 5%" -> Greater of actual (55%) or 5% | N26: =IFERROR(I26-G26,0) -> 0 | O26: =IFERROR(N26/G26,"")
C27: OR | N27: =IFERROR(I27-G27,0) -> 0 | O27: =IFERROR(N27/G27,"")
C28: Base Rent (3) | N28: =IFERROR(I28-G28,0) -> 0 | O28: =IFERROR(N28/G28,"")
C29: Expense Reimbursement | E29: 949400 | F29: 466440 | G29: 466440 | H29: =SUM('1Q26 T12'!O14:O16) -> 298740 | I29: =SUM('1Q26 RR'!R:R)*12 -> 610140 | L29: Annualized in-place RR | N29: =IFERROR(I29-G29,0) -> 143700 | O29: =IFERROR(N29/G29,"") -> 0.30807821
C30: Percentage Rent | E30: 0 | F30: 0 | G30: 0 | H30: 0 | I30: 0 | J30: =IF(E30=0," ",(I30-E30)/E30) | K30: =IF(G30=0," ",(I30-G30)/G30) | N30: =IFERROR(I30-G30,0) -> 0 | O30: =IFERROR(N30/G30,"")
C31: Parking Income | E31: 0 | F31: 0 | G31: 0 | H31: 0 | I31: 0 | K31: =IF(G31=0," ",(I31-G31)/G31) | N31: =IFERROR(I31-G31,0) -> 0 | O31: =IFERROR(N31/G31,"")
C32: Other Income | E32: 0 | F32: 160.77 | G32: 60 | H32: ='1Q26 T12'!O21 -> 0 | I32: =H32 -> 0 | L32: ="T12 ended "&TEXT($I$15,"mm/dd/yyyy") -> T12 ended 03/31/2026 | N32: =IFERROR(I32-G32,0) -> -60 | O32: =IFERROR(N32/G32,"") -> -1
N33: =IFERROR(I33-G33,0) -> 0 | O33: =IFERROR(N33/G33,"")
C34: *Effective Gross Income | E34: 3391436 | F34: 2072513.1 | G34: 2097418.4 | H34: =SUM(H25:H32) -> 1903066.7 | I34: =SUM(I25:I32) -> 2024067 | N34: =IFERROR(I34-G34,0) -> -73351.446 | O34: =IFERROR(N34/G34,"") -> -0.034972252
E35: (3) Use either Gross Potential (with Vacancy Loss) or Base Rents; use negative $ amt for Vacancy Loss | N35: =IFERROR(I35-G35,0) -> 0 | O35: =IFERROR(N35/G35,"")
N36: =IFERROR(I36-G36,0) -> 0 | O36: =IFERROR(N36/G36,"")
C37: OPERATING EXPENSES: | N37: =IFERROR(I37-G37,0) -> 0 | O37: =IFERROR(N37/G37,"")
C38: Real Estate Taxes | E38: 561986 | F38: 494233.61 | G38: 474465 | H38: ='1Q26 T12'!O31 -> 383350.47 | I38: =MAX(H38,Tax!B7) -> 452696.25 | L38: ="Greater of actual tax bill from 01/01/2025-01/01/2026 ($"&TEXT(Tax!B7/1000,"0.0")&"K) and T12 ended "&TEXT('(New) Comm OSAR'!I15,"mm/dd/yyyy") -> Greater of actual tax bill from 01/01/2025-01/01/2026 ($452.7K) and T12 ended 03/31/2026 | N38: =IFERROR(I38-G38,0) -> -21768.75 | O38: =IFERROR(N38/G38,"") -> -0.045880623
C39: Property Insurance | E39: 344808 | F39: 171976.41 | G39: 210758 | H39: ='1Q26 T12'!O32 -> 194042.95 | I39: =MAX(H39,Insurance!O4) -> 194042.95 | L39: ="Greater of actual insurance bill from 05/31/2025-05/31/2026 ($"&TEXT(Insurance!O4/1000,"0.0")&"K) and T12 ended "&TEXT('(New) Comm OSAR'!I15,"mm/dd/yyyy") -> Greater of actual insurance bill from 05/31/2025-05/31/2026 ($112.8K) and T12 ended 03/31/2026 | N39: =IFERROR(I39-G39,0) -> -16715.05 | O39: =IFERROR(N39/G39,"") -> -0.079309208
C40: Utilities | E40: 0 | F40: 68375.81 | G40: 60040 | H40: ='1Q26 T12'!O59 -> 63835.99 | I40: =H40 -> 63835.99 | L40: ="T12 ended "&TEXT($I$15,"mm/dd/yyyy") -> T12 ended 03/31/2026 | N40: =IFERROR(I40-G40,0) -> 3795.99 | O40: =IFERROR(N40/G40,"") -> 0.06322435
C41: Repairs and Maintenance | E41: 71832 | F41: 66518.56 | G41: 52989 | H41: ='1Q26 T12'!O74 -> 67844.72 | I41: =H41 -> 67844.72 | L41: ="T12 ended "&TEXT($I$15,"mm/dd/yyyy") -> T12 ended 03/31/2026 | N41: =IFERROR(I41-G41,0) -> 14855.72 | O41: =IFERROR(N41/G41,"") -> 0.28035479
C42: Janitorial | E42: 0 | F42: 0 | G42: 0 | H42: 0 | I42: =H42 -> 0 | L42: ="T12 ended "&TEXT($I$15,"mm/dd/yyyy") -> T12 ended 03/31/2026 | N42: =IFERROR(I42-G42,0) -> 0 | O42: =IFERROR(N42/G42,"")
C43: Management Fees | E43: 101744 | F43: 62175.394 | G43: 62922.552 | H43: ='1Q26 T12'!O82 -> 54928.48 | I43: =MAX(+I34*0.03,H43) -> 60722.009 | L43: Greater of actual or 3% of GPR | N43: =IFERROR(I43-G43,0) -> -2200.5434 | O43: =IFERROR(N43/G43,"") -> -0.034972252
C44: Payroll & Benefits | E44: 0 | F44: 0 | G44: 0 | H44: 0 | I44: =H44 -> 0 | L44: ="T12 ended "&TEXT($I$15,"mm/dd/yyyy") -> T12 ended 03/31/2026 | N44: =IFERROR(I44-G44,0) -> 0 | O44: =IFERROR(N44/G44,"")
C45: Advertising & Marketing | E45: 0 | F45: 0 | G45: 0 | H45: 0 | I45: =H45 -> 0 | L45: ="T12 ended "&TEXT($I$15,"mm/dd/yyyy") -> T12 ended 03/31/2026 | N45: =IFERROR(I45-G45,0) -> 0 | O45: =IFERROR(N45/G45,"")
C46: Professional Fees | E46: 0 | F46: 64488.74 | G46: 63484 | H46: =SUM('1Q26 T12'!O50,'1Q26 T12'!O98:O99) -> 170477.52 | I46: =H46 -> 170477.52 | L46: ="T12 ended "&TEXT($I$15,"mm/dd/yyyy") -> T12 ended 03/31/2026 | N46: =IFERROR(I46-G46,0) -> 106993.52 | O46: =IFERROR(N46/G46,"") -> 1.685362
C47: General and Administrative | E47: 0 | F47: 24250.93 | G47: 18946 | H47: =SUM('1Q26 T12'!O43,'1Q26 T12'!O100) -> 16053.91 | I47: =H47 -> 16053.91 | L47: ="T12 ended "&TEXT($I$15,"mm/dd/yyyy") -> T12 ended 03/31/2026 | N47: =IFERROR(I47-G47,0) -> -2892.09 | O47: =IFERROR(N47/G47,"") -> -0.15264911
C48: Other Expenses | E48: 0 | F48: 0 | G48: 0 | H48: ='1Q26 T12'!O97 -> 3919.36 | I48: =H48 -> 3919.36 | L48: ="T12 ended "&TEXT($I$15,"mm/dd/yyyy") -> T12 ended 03/31/2026 | N48: =IFERROR(I48-G48,0) -> 3919.36 | O48: =IFERROR(N48/G48,"")
C49: Ground Rent | E49: 0 | F49: 0 | G49: 0 | H49: 0 | I49: =H49 -> 0 | L49: ="T12 ended "&TEXT($I$15,"mm/dd/yyyy") -> T12 ended 03/31/2026 | N49: =IFERROR(I49-G49,0) -> 0 | O49: =IFERROR(N49/G49,"")
C50: *Total Operating Expenses | E50: 1080370 | F50: 952019.45 | G50: 943604.55 | H50: =SUM(H38:H49) -> 954453.4 | I50: =SUM(I38:I49) -> 1029592.7 | N50: =IFERROR(I50-G50,0) -> 85988.157 | O50: =IFERROR(N50/G50,"") -> 0.091127323
N51: =IFERROR(I51-G51,0) -> 0 | O51: =IFERROR(N51/G51,"")
C52: Operating Expense Ratio | E52: 0.31855827 | F52: 0.45935509 | G52: 0.44988856 | H52: =H50/H34 -> 0.5015344 | I52: =I50/I34 -> 0.50867522 | N52: =IFERROR(I52-G52,0) -> 0.058786658 | O52: =IFERROR(N52/G52,"") -> 0.13066938
N53: =IFERROR(I53-G53,0) -> 0 | O53: =IFERROR(N53/G53,"")
C54: *Net Operating Income | E54: 2311066 | F54: 1120493.7 | G54: 1153813.9 | H54: =H34-H50 -> 948613.28 | I54: =I34-I50 -> 994474.26 | N54: =IFERROR(I54-G54,0) -> -159339.6 | O54: =IFERROR(N54/G54,"") -> -0.13809819
N55: =IFERROR(I55-G55,0) -> 0 | O55: =IFERROR(N55/G55,"")
C56: Leasing Commissions | H56: ='1Q26 T12'!O120 -> 743322.43 | N56: =IFERROR(I56-G56,0) -> 0 | O56: =IFERROR(N56/G56,"")
C57: Tenant Improvements | H57: ='1Q26 T12'!O119 -> 19675.3 | N57: =IFERROR(I57-G57,0) -> 0 | O57: =IFERROR(N57/G57,"")
C58: Capital Expenditures | E58: 71832 | F58: 72586.5 | G58: 74692.25 | H58: =SUM('1Q26 T12'!O118,'1Q26 T12'!O121) -> 1400955 | I58: =$E$12*$E$14 -> 74692.25 | L58: $0.25PSF | N58: =IFERROR(I58-G58,0) -> 0 | O58: =IFERROR(N58/G58,"") -> 0
C59: Extraordinary Capital Expenditures | N59: =IFERROR(I59-G59,0) -> 0 | O59: =IFERROR(N59/G59,"")
C60: Total Capital Items | E60: 71832 | F60: 72586.5 | G60: 74692.25 | H60: =SUM(H56:H59) -> 2163952.7 | I60: =SUM(I56:I59) -> 74692.25 | N60: =IFERROR(I60-G60,0) -> 0 | O60: =IFERROR(N60/G60,"") -> 0
N61: =IFERROR(I61-G61,0) -> 0 | O61: =IFERROR(N61/G61,"")
C62: *Net Cash Flow | E62: 2239234 | F62: 1047907.2 | G62: 1079121.6 | H62: =H54-H60 -> -1215339.4 | I62: =I54-I60 -> 919782.01 | N62: =IFERROR(I62-G62,0) -> -159339.6 | O62: =IFERROR(N62/G62,"") -> -0.14765676
N63: =IFERROR(I63-G63,0) -> 0 | O63: =IFERROR(N63/G63,"")
C64: Debt Service - A Note | E64: 3070163.6 | F64: 2855579 | G64: 2623520.3 | H64: ='1Q26 T12'!O109 -> 2747766.2 | I64: =+'Debt Service'!$C$11 -> 2723160.7 | N64: =IFERROR(I64-G64,0) -> 99640.385 | O64: =IFERROR(N64/G64,"") -> 0.037979651
C65: Debt Service - B Note | N65: =IFERROR(I65-G65,0) -> 0 | O65: =IFERROR(N65/G65,"")
C66: Debt Service - C Note
C68: *Net Cash Flow after Debt Service | F68: -1807671.8 | G68: -1544398.7 | H68: =H62-H64 -> -3963105.6 | I68: =I62-I64 -> -1803378.7
C70: *DSCR: (NOI/Debt Service) - A Note | F70: 0.36696838 | G70: 0.41132581 | H70: =H54/H64 -> 0.34523072 | I70: ='Debt Service'!$C$14 -> 0.36519118
C71: *DSCR: (NOI/Debt Service) - A & B Note
C72: *DSCR: (NOI/Debt Service) - A, B & C Note
C74: *DSCR: (NCF/Debt Service) - A Note | E74: 0.75275013 | F74: 0.36696838 | G74: 0.41132581 | H74: =H62/H64 -> -0.4423009 | I74: ='Debt Service'!$C$14 -> 0.36519118
C75: *DSCR: (NCF/Debt Service) - A & B Note
C76: *DSCR: (NCF/Debt Service) - A, B & C Note
C78: Debt Yield | E78: 0.062854635 | F78: 0.028500191 | G78: 0.029349138 | H78: =H62/$E$6 -> -0.028416745 | I78: =I62/$E$6 -> 0.0215061
C80: Source of Financial Data:
E81: (ie. operating statements, financial statements, tax return, other)
C82: Notes and Assumptions: Years above will roll, always showing a 3yr sequential history. Comments from the most recent NOI Adjustment Worksheet should be carried forward to Operating Statement
C83: Analysis Report. Year-over-year variances (either higher or lower) must be explained and noted for the following: >20% DSCR change, >20% EGI/Total Operating Expenses or Total Capital
C84: Items. Quarterly variance comments may be necessary if the loan is on the Watch List.
C85: Income: Comments
C88: Expense: Comments
C91: Capital Items: Comments
C94: DSCR: Comments
C97: * Used in the CREFC Comparative Financial Status Report/CREFC Property File/CREFC Loan Periodic Update File. Note that information for multiple property loans must be consolidated (if available)
C98: for reporting to the CREFC Loan Periodic Update file.

Sheet QoQ
C2: 4Q 2025 | G2: 1Q 2026 | K2: QoQ ∆ | O2: Cash Management
B3: Property | C3: Occupancy | D3: NOI | E3: DY | F3: DSCR | G3: Occupancy | H3: NOI | I3: DY | J3: DSCR | K3: Occupancy | L3: NOI | M3: DY | N3: DSCR | O3: In CM? | P3: Threshold/Cure
B4: =#REF! -> #REF! | C4: 0.5348 | D4: 1079121.6 | E4: 0.029349138 | F4: 0.41132581 | G4: ='(New) Comm OSAR'!I16 -> 0.44819576 | H4: ='(New) Comm OSAR'!I62 -> 919782.01 | I4: ='(New) Comm OSAR'!I78 -> 0.0215061 | J4: ='(New) Comm OSAR'!I74 -> 0.36519118 | K4: =IF(G4="","-",G4-C4) -> -0.086604237 | L4: =IF(H4="","-",H4-D4) -> -159339.6 | M4: =IF(I4="","-",I4-E4) -> -0.0078430386 | N4: =IF(J4="","-",J4-F4) -> -0.046134632 | O4: Yes | P4: 0.07
B6: Notes:
B7: NOI adjusted per the Loan Agreement.
B8: The Property remains in cash management as it failed to meet the DY cure of 7.00% for one quarter.
B9: DY decreased 73 bps QoQ due to both the UPB increasing from $36.8MM to $42.8MM QoQ and the tenant Beacon Sales Acquisition's lease ending inside the next 90 days. The decrease in In-Place Rents from Beacon vacating (-$650.3K) was only partially offset by the new lease with Zoox (+$450.5K).
B10: Occupancy increased 28% QoQ due to the new tenant Zoox leasing 143.5K SF and Beacon vacating only 55.4K SF.

Sheet Debt Service
B2: Interest Rate Cap | C2: 0.045 | D2: =IF(C2=C3,"At-the-Money",IF(C2<C3,"In-the-Money",IF(C2>C3,"Out-of-the-Money"))) -> Out-of-the-Money
B3: SOFR | C3: 0.0368 | D3: 46112
B4: Spread | C4: 0.026
B5: Effective Interest Rate | C5: =SUM(MIN(C3,C2),C4) -> 0.0628
B7: Current Principal Balance | C7: ='(New) Comm OSAR'!E6 -> 42768425
B9: NOI | C9: ='(New) Comm OSAR'!I54 -> 994474.26
B10: Debt Service (w/o Cap) | C10: =$C$7*($C$3+$C$4)*(365/360) -> 2723160.7
B11: Debt Service (w/Cap) | C11: =$C$7*$C$5*(365/360) -> 2723160.7
B13: DSCR (w/o Cap) | C13: =C9/C10 -> 0.36519118
B14: DSCR (w/Cap) | C14: =C9/C11 -> 0.36519118
B16: DY | C16: =C9/$C$7 -> 0.023252534

Sheet Tax
A1: Miami-Dade | B1: No 2026 Tax Data Available
B2: 2025
A3: 30-3116-016-0020 | B3: 84403.89
A4: 30-3116-016-0040 | B4: 161851.51
A5: 30-3116-016-0100 | B5: 206440.85
A7: Total | B7: =SUM(B3:B5) -> 452696.25

Sheet Insurance
O3: Total Insurance
O4: 112826.12

Sheet 1Q26 T12
A1: Database: | B1: MSDE_SE | C1: Rolling Twelve Month Income Statement | N1: Page: | O1: 1
A2: Report Id: | B2: LPC_R12MINCS | C2: Lincoln Property Company | N2: Date: | O2: 46162.707
C3: Seaboard 27279 | N3: Time: | O3: 46162.707
C4: Ending Period March 2026
A5: Accrual
C8: 04/25 | D8: 05/25 | E8: 06/25 | F8: 07/25 | G8: 08/25 | H8: 09/25 | I8: 10/25 | J8: 11/25 | K8: 12/25 | L8: 01/26 | M8: 02/26 | N8: 03/26 | O8: Total
A9: REVENUES
A11: RENTAL INCOME
A13: 4005-00 | B13: BASE/MINIMUM RENT | C13: 132240.35 | D13: 133826.03 | E13: 133826.03 | F13: 133826.03 | G13: 133826.03 | H13: 133826.03 | I13: 133826.03 | J13: 133826.03 | K13: 133826.03 | L13: 133826.03 | M13: 133826.03 | N13: 133826.03 | O13: 1604326.7
A14: 4105-02 | B14: INSURANCE REIMB | C14: 11494 | D14: -130205 | E14: 11494 | F14: 11494 | G14: 54224.58 | H14: 11494 | I14: 11494 | J14: 36494 | K14: 11494 | L14: 3414 | M14: 3414 | N14: 3414 | O14: 39719.58
A15: 4105-03 | B15: PROPERTY TAX REIMB | C15: 24390 | D15: 21093 | E15: 24390 | F15: 24390 | G15: 24390 | H15: 24390 | I15: 24390 | J15: 24390 | K15: 24390 | L15: 21006 | M15: 21006 | N15: 21006 | O15: 279231
A16: 4105-07 | B16: CAM REIMBURSEMENT | C16: 2986 | D16: -10326 | E16: -39744.58 | F16: 2986 | G16: 2986 | H16: 2986 | I16: 2986 | J16: 2986 | K16: 2986 | L16: 2986 | M16: 2986 | N16: 2986 | O16: -20210.58
A17: TOTAL RENTAL REVENUE | C17: 171110.35 | D17: 14388.03 | E17: 129965.45 | F17: 172696.03 | G17: 215426.61 | H17: 172696.03 | I17: 172696.03 | J17: 197696.03 | K17: 172696.03 | L17: 161232.03 | M17: 161232.03 | N17: 161232.03 | O17: 1903066.7
A19: OTHER INCOME
A21: TOTAL OTHER INCOME | C21: 0 | D21: 0 | E21: 0 | F21: 0 | G21: 0 | H21: 0 | I21: 0 | J21: 0 | K21: 0 | L21: 0 | M21: 0 | N21: 0 | O21: 0
A23: TOTAL INCOME | C23: 171110.35 | D23: 14388.03 | E23: 129965.45 | F23: 172696.03 | G23: 215426.61 | H23: 172696.03 | I23: 172696.03 | J23: 197696.03 | K23: 172696.03 | L23: 161232.03 | M23: 161232.03 | N23: 161232.03 | O23: 1903066.7
A25: EXPENSES
A27: OPERATING EXPENSES
A29: TAXES & INSURANCE
A31: 5005-01 | B31: REAL ESTATE TAXES | C31: 48858.75 | D31: 48858.75 | E31: 48858.75 | F31: 48858.75 | G31: 48858.75 | H31: 48858.75 | I31: 11578.75 | J31: 11578.75 | K31: 11578.75 | L31: 18487.24 | M31: 18487.24 | N31: 18487.24 | O31: 383350.47
A32: 5007-00 | B32: INSURANCE | C32: 751.41 | D32: 665.67 | E32: 9724.02 | F32: 19334.78 | G32: 19332.7 | H32: 9666.34 | I32: 85858.58 | J32: 9666.35 | K32: 9666.35 | L32: 9652.02 | M32: 9666.35 | N32: 10058.38 | O32: 194042.95
A33: TOTAL TAXES & INSURANCE | C33: 49610.16 | D33: 49524.42 | E33: 58582.77 | F33: 68193.53 | G33: 68191.45 | H33: 58525.09 | I33: 97437.33 | J33: 21245.1 | K33: 21245.1 | L33: 28139.26 | M33: 28153.59 | N33: 28545.62 | O33: 577393.42
A35: ADMINISTRATION
A37: 5010-04 | B37: BANK CHARGES | C37: 625 | D37: 625 | E37: 625 | F37: 625 | G37: 625 | H37: 625 | I37: 625 | J37: 625 | K37: 0 | L37: 0 | M37: 0 | N37: 0 | O37: 5000
A38: 5010-13 | B38: LICENSES & PERMITS | C38: 0 | D38: 0 | E38: 0 | F38: 0 | G38: 417.55 | H38: 0 | I38: 0 | J38: 0 | K38: 0 | L38: 0 | M38: 0 | N38: 0 | O38: 417.55
A39: 5010-15 | B39: OTHER ADMINISTRATIVE | C39: 440.65 | D39: 196.52 | E39: 0 | F39: 0 | G39: 786.1 | H39: 196.52 | I39: 3688.42 | J39: 196.53 | K39: 1494.5 | L39: 943.07 | M39: 0 | N39: 0 | O39: 7942.31
A40: 5010-16 | B40: POSTAGE & DELIVERY | C40: 0 | D40: 0 | E40: 0 | F40: 0 | G40: 45.68 | H40: 112.97 | I40: 0 | J40: 28.29 | K40: 0 | L40: 0 | M40: 0 | N40: 0 | O40: 186.94
A41: 5010-22 | B41: TRAVEL & TRANSPORTATION | C41: 0 | D41: 0 | E41: 0 | F41: 0 | G41: 0 | H41: 0 | I41: 0 | J41: 0 | K41: 1494.5 | L41: 0 | M41: 0 | N41: 0 | O41: 1494.5
A42: 5010-34 | B42: MILEAGE REIMBURSEMENT | C42: 0 | D42: 0 | E42: 9.73 | F42: 0 | G42: 2.88 | H42: 0 | I42: 0 | J42: 0 | K42: 0 | L42: 0 | M42: 0 | N42: 0 | O42: 12.61
A43: TOTAL ADMINISTRATION | C43: 1065.65 | D43: 821.52 | E43: 634.73 | F43: 625 | G43: 1877.21 | H43: 934.49 | I43: 4313.42 | J43: 849.82 | K43: 2989 | L43: 943.07 | M43: 0 | N43: 0 | O43: 15053.91
A45: PROFESSIONAL FEES
A47: 5015-00 | B47: PROFESSIONAL FEES | C47: 105 | D47: 0 | E47: 0 | F47: 0 | G47: 5500 | H47: 0 | I47: 0 | J47: 105 | K47: 1800 | L47: 3950 | M47: 5000 | N47: 0 | O47: 16460
A48: 5015-01 | B48: PROF FEES LEGAL | C48: 0 | D48: 0 | E48: 0 | F48: 0 | G48: 0 | H48: 2732.5 | I48: 0 | J48: 0 | K48: 174 | L48: 0 | M48: 0 | N48: 93420 | O48: 96326.5
A49: 5015-04 | B49: PROF FEES TAX APPEALS | C49: 0 | D49: 0 | E49: 7001.93 | F49: 0 | G49: 0 | H49: 0 | I49: 0 | J49: 0 | K49: 0 | L49: 0 | M49: 10384.54 | N49: 0 | O49: 17386.47
A50: TOTAL PROFESSIONAL FEES | C50: 105 | D50: 0 | E50: 7001.93 | F50: 0 | G50: 5500 | H50: 2732.5 | I50: 0 | J50: 105 | K50: 1974 | L50: 3950 | M50: 15384.54 | N50: 93420 | O50: 130172.97
A52: UTILITIES
A54: 5020-01 | B54: ELECTRICITY | C54: 0 | D54: 3053.81 | E54: 1589.06 | F54: 1492.63 | G54: 781.01 | H54: 604.7 | I54: 1392.11 | J54: 549.92 | K54: 1668.63 | L54: 1400 | M54: 1565.39 | N54: 1982.65 | O54: 16079.91
A55: 5020-05 | B55: WATER & SEWER | C55: 0 | D55: 8240.84 | E55: 0 | F55: -3268.32 | G55: 0 | H55: 8874.05 | I55: 0 | J55: 3486.56 | K55: 0 | L55: 0 | M55: 2599.38 | N55: -451.23 | O55: 19481.28
A56: 5020-09 | B56: ELECTRICITY VACANT | C56: 0 | D56: 0 | E56: 0 | F56: 0 | G56: 0 | H56: 0 | I56: 0 | J56: 0 | K56: 0 | L56: 0 | M56: 83 | N56: 0 | O56: 83
A57: 5020-13 | B57: WATER | C57: 0 | D57: 3459.36 | E57: 1729.68 | F57: 1729.68 | G57: 1729.68 | H57: 1729.68 | I57: 1729.68 | J57: 2162.11 | K57: 2162.11 | L57: 2599.38 | M57: 4324.22 | N57: 4324.22 | O57: 27679.8
A58: 5020-30 | B58: WATER - FIRE LINES | C58: 0 | D58: 256 | E58: 0 | F58: 0 | G58: 0 | H58: 256 | I58: 0 | J58: 0 | K58: 0 | L58: 0 | M58: 0 | N58: 0 | O58: 512
A59: TOTAL UTILITIES | C59: 0 | D59: 15010.01 | E59: 3318.74 | F59: -46.01 | G59: 2510.69 | H59: 11464.43 | I59: 3121.79 | J59: 6198.59 | K59: 3830.74 | L59: 3999.38 | M59: 8571.99 | N59: 5855.64 | O59: 63835.99
A61: REPAIRS & MAINTENANCE
A63: 5025-10 | B63: R&M EQUIP MONITORING SYS | C63: 0 | D63: 0 | E63: 0 | F63: 0 | G63: 0 | H63: 0 | I63: 311.38 | J63: 0 | K63: 0 | L63: 0 | M63: 0 | N63: 0 | O63: 311.38
A64: 5025-11 | B64: R&M FIRE SAFETY CONTRACT | C64: 179.76 | D64: 179.76 | E64: 179.76 | F64: 1925.46 | G64: 179.76 | H64: 179.76 | I64: 359.52 | J64: 179.76 | K64: 179.76 | L64: 179.76 | M64: 179.76 | N64: 179.76 | O64: 4082.58
A65: 5025-12 | B65: R&M FIRE SAFETY REPAIRS | C65: 0 | D65: 0 | E65: 0 | F65: 0 | G65: 2187.55 | H65: 3683.44 | I65: 5625 | J65: 0 | K65: 526.44 | L65: 0 | M65: 0 | N65: 3535.58 | O65: 15558.01
A66: 5025-15 | B66: R&M HVAC REPAIRS | C66: 0 | D66: 0 | E66: 0 | F66: 420.7 | G66: 0 | H66: 0 | I66: 0 | J66: 0 | K66: 0 | L66: 2028.13 | M66: 0 | N66: 0 | O66: 2448.83
A67: 5025-19 | B67: R&M LANDSCAPE EXT CONTRCT | C67: 1558.06 | D67: 1558.06 | E67: 1558.06 | F67: 1558.06 | G67: 1558.06 | H67: 1558.06 | I67: 1558.06 | J67: 1558.06 | K67: 1558.06 | L67: 1620.38 | M67: 1620.38 | N67: 1620.38 | O67: 18883.68
A68: 5025-26 | B68: R&M MINOR CLEANING | C68: 0 | D68: 680 | E68: 0 | F68: 0 | G68: 0 | H68: 0 | I68: 2130 | J68: 0 | K68: 0 | L68: 0 | M68: 0 | N68: 0 | O68: 2810
A69: 5025-29 | B69: R&M PARKING LOT CLEANING | C69: 0 | D69: 0 | E69: 0 | F69: 0 | G69: 0 | H69: 635 | I69: -1155 | J69: 0 | K69: 0 | L69: 100 | M69: 0 | N69: 0 | O69: -420
A70: 5025-33 | B70: R&M PLUMBING REPAIRS | C70: 1041 | D70: 0 | E70: 0 | F70: 0 | G70: 0 | H70: 0 | I70: 4235 | J70: 0 | K70: 0 | L70: 0 | M70: 0 | N70: 0 | O70: 5276
A71: 5025-37 | B71: R&M ROOFING REPAIRS | C71: 0 | D71: 0 | E71: 0 | F71: 0 | G71: 0 | H71: 2635 | I71: 0 | J71: 0 | K71: 0 | L71: 1245 | M71: 0 | N71: 0 | O71: 3880
A72: 5025-62 | B72: R&M EXTERIOR REPAIRS & LABOR | C72: 0 | D72: 0 | E72: 4999.24 | F72: 0 | G72: 0 | H72: 0 | I72: 0 | J72: 0 | K72: 0 | L72: 0 | M72: 0 | N72: 0 | O72: 4999.24
A73: 5025-82 | B73: R&M OTHER | C73: 0 | D73: 0 | E73: 0 | F73: 520 | G73: 0 | H73: 975 | I73: -975 | J73: 0 | K73: 0 | L73: 1000 | M73: 0 | N73: 8495 | O73: 10015
A74: TOTAL REPAIRS & MAINTENANCE | C74: 2778.82 | D74: 2417.82 | E74: 6737.06 | F74: 4424.22 | G74: 3925.37 | H74: 9666.26 | I74: 12088.96 | J74: 1737.82 | K74: 2264.26 | L74: 6173.27 | M74: 1800.14 | N74: 13830.72 | O74: 67844.72
A76: BLDG SERVICE OFFICERS
A78: TOTAL BLDG SERVICE OFFICERS | C78: 0 | D78: 0 | E78: 0 | F78: 0 | G78: 0 | H78: 0 | I78: 0 | J78: 0 | K78: 0 | L78: 0 | M78: 0 | N78: 0 | O78: 0
A80: MANAGEMENT FEE
A82: 5030-00 | B82: PROPERTY MANAGEMENT FEES | C82: 5177.55 | D82: 2085.39 | E82: 3527.67 | F82: 8279.7 | G82: 3098.83 | H82: 5180.88 | I82: 5180.88 | J82: 3786.37 | K82: 5180.88 | L82: 5079.78 | M82: 2082.05 | N82: 6268.5 | O82: 54928.48
A83: TOTAL MANAGEMENT FEE | C83: 5177.55 | D83: 2085.39 | E83: 3527.67 | F83: 8279.7 | G83: 3098.83 | H83: 5180.88 | I83: 5180.88 | J83: 3786.37 | K83: 5180.88 | L83: 5079.78 | M83: 2082.05 | N83: 6268.5 | O83: 54928.48
A85: PAYROLL
A87: TOTAL PAYROLL | C87: 0 | D87: 0 | E87: 0 | F87: 0 | G87: 0 | H87: 0 | I87: 0 | J87: 0 | K87: 0 | L87: 0 | M87: 0 | N87: 0 | O87: 0
A89: OTHER OPERATING EXPENSES
A91: TOTAL OTHER OPERATING EXPENSES | C91: 0 | D91: 0 | E91: 0 | F91: 0 | G91: 0 | H91: 0 | I91: 0 | J91: 0 | K91: 0 | L91: 0 | M91: 0 | N91: 0 | O91: 0
A93: TOTAL OPERATING EXPENSES | C93: 58737.18 | D93: 69859.16 | E93: 79802.9 | F93: 81476.44 | G93: 85103.55 | H93: 88503.65 | I93: 122142.38 | J93: 33922.7 | K93: 37483.98 | L93: 48284.76 | M93: 55992.31 | N93: 147920.48 | O93: 909229.49
A95: NON-RECOVERABLE EXPENSES
A97: 6012-04 | B97: BANK CHARGES - NON | C97: 0 | D97: 0 | E97: 0 | F97: 0 | G97: 0 | H97: 0 | I97: 0 | J97: 0 | K97: 0 | L97: 1544.21 | M97: 1250 | N97: 1125.15 | O97: 3919.36
A98: 6015-00 | B98: PROFESSIONAL FEES NON | C98: 0 | D98: 20472 | E98: 16320 | F98: 1000 | G98: 0 | H98: 0.4 | I98: 0 | J98: 0 | K98: 267.75 | L98: 0 | M98: 1644.4 | N98: 0 | O98: 39704.55
A99: 6015-01 | B99: PROF FEES LEGAL NON | C99: 0 | D99: 0 | E99: 0 | F99: 0 | G99: 600 | H99: 0 | I99: 0 | J99: 0 | K99: 0 | L99: 0 | M99: 0 | N99: 0 | O99: 600
A100: 6045-01 | B100: SOFTWARE LICENSING-NON RECOV | C100: 250 | D100: 0 | E100: 0 | F100: 250 | G100: 0 | H100: 0 | I100: 250 | J100: 0 | K100: 0 | L100: 250 | M100: 0 | N100: 0 | O100: 1000
A101: TOTAL NON-RECOVERABLE EXPENSES | C101: 250 | D101: 20472 | E101: 16320 | F101: 1250 | G101: 600 | H101: 0.4 | I101: 250 | J101: 0 | K101: 267.75 | L101: 1794.21 | M101: 2894.4 | N101: 1125.15 | O101: 45223.91
A102: TOTAL EXPENSES | C102: 58987.18 | D102: 90331.16 | E102: 96122.9 | F102: 82726.44 | G102: 85703.55 | H102: 88504.05 | I102: 122392.38 | J102: 33922.7 | K102: 37751.73 | L102: 50078.97 | M102: 58886.71 | N102: 149045.63 | O102: 954453.4
A104: NET OPERATING INCOME | C104: 112123.17 | D104: -75943.13 | E104: 33842.55 | F104: 89969.59 | G104: 129723.06 | H104: 84191.98 | I104: 50303.65 | J104: 163773.33 | K104: 134944.3 | L104: 111153.06 | M104: 102345.32 | N104: 12186.4 | O104: 948613.28
A106: NON-OPERATING EXPENSES
A108: 8010-00 | B108: ASSET MANAGEMENT FEES | C108: 1260.83 | D108: 0 | E108: 2613.69 | F108: 881.92 | G108: 0 | H108: 0 | I108: 3943.31 | J108: 1295.22 | K108: 946.59 | L108: 1269.95 | M108: 1295.22 | N108: 1551.5 | O108: 15058.23
A109: 8030-01 | B109: INTEREST EXPENSE | C109: 174537.11 | D109: 242708.28 | E109: 243625.78 | F109: 235490.64 | G109: 244885.65 | H109: 245351.53 | I109: 230109.06 | J109: 234899.17 | K109: 268141.67 | L109: 225114.69 | M109: 221610.53 | N109: 181292.06 | O109: 2747766.2
A110: 8050-00 | B110: BANK FEES | C110: 0 | D110: 0 | E110: 0 | F110: 0 | G110: 0 | H110: 0 | I110: 0 | J110: 0 | K110: 625 | L110: 0 | M110: 0 | N110: 0 | O110: 625
A111: 8620-00 | B111: GAIN/LOSS ON SWAP | C111: 0 | D111: 0 | E111: 0 | F111: 0 | G111: 0 | H111: 0 | I111: 36000 | J111: 0 | K111: 0 | L111: 0 | M111: 0 | N111: 0 | O111: 36000
A112: 8630-00 | B112: UNREALIZED FMV ADJ | C112: 0 | D112: 0 | E112: 0 | F112: 0 | G112: 0 | H112: 0 | I112: -14604.85 | J112: 0 | K112: 0 | L112: 0 | M112: 0 | N112: 0 | O112: -14604.85
A113: TOTALNON OPERATING EXPENSES | C113: 175797.94 | D113: 242708.28 | E113: 246239.47 | F113: 236372.56 | G113: 244885.65 | H113: 245351.53 | I113: 255447.52 | J113: 236194.39 | K113: 269713.26 | L113: 226384.64 | M113: 222905.75 | N113: 182843.56 | O113: 2784844.5
A114: NET OPERATING INCOME | C114: -63674.77 | D114: -318651.41 | E114: -212396.92 | F114: -146402.97 | G114: -115162.59 | H114: -161159.55 | I114: -205143.87 | J114: -72421.06 | K114: -134768.96 | L114: -115231.58 | M114: -120560.43 | N114: -170657.16 | O114: -1836231.3
A116: CAPITAL EXPENSES
A118: 1708-00 | B118: BUILDING IMPROVEMENTS | C118: 0 | D118: 0 | E118: 0 | F118: 0 | G118: 0 | H118: 0 | I118: 31126 | J118: 0 | K118: 23332.45 | L118: 0 | M118: 17290.63 | N118: 2052276.2 | O118: 2124025.3
A119: 1714-00 | B119: TENANT IMPROVEMENTS | C119: 0 | D119: 5625 | E119: 0 | F119: 0 | G119: 0 | H119: 0 | I119: -5625 | J119: 0 | K119: 0 | L119: 0 | M119: 19675.3 | N119: 0 | O119: 19675.3
A120: 1720-00 | B120: LEASING COMMISSIONS | C120: 0 | D120: 0 | E120: 0 | F120: 0 | G120: 0 | H120: 0 | I120: 0 | J120: 0 | K120: 0 | L120: 0 | M120: 0 | N120: 743322.43 | O120: 743322.43
A121: 1725-00 | B121: CONSTRUCTION IN PROGRESS | C121: 0 | D121: 104147.81 | E121: 0 | F121: 0 | G121: 0 | H121: 0 | I121: 0 | J121: 0 | K121: 14019 | L121: 172770.9 | M121: 554048.23 | N121: -1568056.2 | O121: -723070.31
A122: 1730-06 | B122: LEGAL | C122: 0 | D122: 0 | E122: 0 | F122: 0 | G122: 0 | H122: 0 | I122: 0 | J122: 0 | K122: 0 | L122: 60360 | M122: 0 | N122: -60360 | O122: 0
A123: 1899-00 | B123: EARNEST MONEY DEPOSIT | C123: 0 | D123: 0 | E123: 0 | F123: 0 | G123: 0 | H123: 0 | I123: 0 | J123: 0 | K123: 0 | L123: 0 | M123: 225000 | N123: -225000 | O123: 0
A124: TOTAL CAPITAL EXPENSES | C124: 0 | D124: 109772.81 | E124: 0 | F124: 0 | G124: 0 | H124: 0 | I124: 25501 | J124: 0 | K124: 37351.45 | L124: 233130.9 | M124: 816014.16 | N124: 942182.4 | O124: 2163952.7
A126: NET OPERATING INCOME LESS CAPITAL | C126: -63674.77 | D126: -428424.22 | E126: -212396.92 | F126: -146402.97 | G126: -115162.59 | H126: -161159.55 | I126: -230644.87 | J126: -72421.06 | K126: -172120.41 | L126: -348362.48 | M126: -936574.59 | N126: -1112839.6 | O126: -4000184

Sheet 1Q RR
A2: Database: | B2: MSDE_SE | E2: Rent Roll | K2: Page: 1
A3: Bldg Status: | B3: Active only | E3: Seaboard Indust-3455 NW 54 St | K3: Date: 1/15/2025
E4: 45747 | K4: Time: 12/30/1899
A7: Bldg Id-Suit Id | F7: GLA | G7: Monthly | H7: Annual | I7: Monthly | J7: Expense | K7: Monthly ---------------- Future Rent Increases ----------------
A8: -Lease Id | B8: Occupant Name | D8: Lease Start | E8: Expiration | F8: Sqft | G8: Base Rent | H8: Rate PSF | I8: Cost Recovery | J8: Stop | K8: Other Income Cat Date Monthly Amount PSF
A10: Vacant Suites
A12: 2727901 | B12: -100 | C12: Vacant | F12: 101880
A14: 2727901 | B14: -100A | C14: Vacant | F14: 33201
A17: Totals: | B17: Occupied Sqft: | D17: 0 | E17: 0 Units | F17: 0 | G17: 0 | I17: 0 | K17: 0
B18: Leased/Unoccupied Sqft: | E18: 0 Units | F18: 0
B19: Vacant Sqft: | D19: 1 | E19: 2 Units | F19: 135,081
B20: Total Sqft: | E20: 2 Units | F20: 135,081
A23: Total Seaboard Indust-3455 NW 54 St:
B24: Occupied Sqft: | D24: 0 | E24: 0 Units | F24: 0 | G24: 0 | I24: 0 | K24: 0
B25: Leased/Unoccupied Sqft: | E25: 0 Units | F25: 0
B26: Vacant Sqft: | D26: 1 | E26: 2 Units | F26: 135,081
B27: Total Sqft: | E27: 2 Units | F27: 135,081
A57: Database: | B57: MSDE_SE | E57: Rent Roll | K57: Page: 2
A58: Bldg Status: | B58: Active only | E58: Seaboard Indust-5400 NW 32 Ct | K58: Date: 1/15/2025
E59: 45657 | K59: Time: 12/30/1899
A62: Bldg Id-Suit Id | F62: GLA | G62: Monthly | H62: Annual | I62: Monthly | J62: Expense | K62: Monthly ---------------- Future Rent Increases ----------------
A63: -Lease Id | B63: Occupant Name | D63: Lease Start | E63: Expiration | F63: Sqft | G63: Base Rent | H63: Rate PSF | I63: Cost Recovery | J63: Stop | K63: Other Income Cat Date Monthly Amount PSF
A65: Occupied Suites
A67: 2727902 | B67: -100 | C67: Sun Commodities Inc. | D67: 44805 | E67: 46721 | F67: 99907 | G67: 76699.73 | H67: 9.21 | I67: 23910 | K67: BRT 4/1/2025 79,384.22 9.53 | M67: Escalation within 90 Days | N67: Date | O67: DY Test Rent
B68: -6854 | K68: BRT 4/1/2026 82,162.67 9.87 | M68: 79384.22 | N68: 45748 | O68: =IF(N68-M71<1,M68,(ROUND((N68-M71)/30,0)/12)*G67+(((12-ROUND((N68-M71)/30,0))/12)*M68)) -> #REF!
K69: BRT 4/1/2027 85,038.36 10.21
M70: Forward start period
A71: Totals: | B71: Occupied Sqft: | D71: 1 | E71: 1 Units | F71: 99907 | G71: 76699.73 | I71: 23910 | K71: 0 | M71: =EOMONTH(#REF!,0)+1 -> #REF!
B72: Leased/Unoccupied Sqft: | E72: 0 Units | F72: 0
B73: Vacant Sqft: | E73: 0 Units | F73: 0
B74: Total Sqft: | E74: 1 Units | F74: 99,907 | G74: 76699.73
A77: Total Seaboard Indust-5400 NW 32 Ct:
B78: Occupied Sqft: | D78: 1 | E78: 1 Units | F78: 99907 | G78: 76699.73 | I78: 23910 | K78: 0
B79: Leased/Unoccupied Sqft: | E79: 0 Units | F79: 0
B80: Vacant Sqft: | E80: 0 Units | F80: 0
B81: Total Sqft: | E81: 1 Units | F81: 99,907 | G81: 76699.73
A112: Database: | B112: MSDE_SE | E112: Rent Roll | K112: Page: 3
A113: Bldg Status: | B113: Active only | E113: Seaboard Indust-5530 NW 32 Ct | K113: Date: 1/15/2025
E114: 45657 | K114: Time: 12/30/1899
A117: Bldg Id-Suit Id | F117: GLA | G117: Monthly | H117: Annual | I117: Monthly | J117: Expense | K117: Monthly ---------------- Future Rent Increases ----------------
A118: -Lease Id | B118: Occupant Name | D118: Lease Start | E118: Expiration | F118: Sqft | G118: Base Rent | H118: Rate PSF | I118: Cost Recovery | J118: Stop | K118: Other Income Cat Date Monthly Amount PSF
A120: Occupied Suites
A122: 2727903 | B122: -100 | C122: Beacon Sales Acquisition Inc | D122: 40585 | E122: 46142 | F122: 55358 | G122: 52856.13 | H122: 11.46 | I122: 14960 | K122: BRT 5/1/2025 54,441.81 11.80
B123: -6853 | M123: Escalation within 90 Days | N123: Date | O123: DY Test Rent
M124: 54441.81 | N124: 45778 | O124: =IF(N124-M127<1,M124,(ROUND((N124-M127)/30,0)/12)*G122+(((12-ROUND((N124-M127)/30,0))/12)*M124)) -> #REF!
A125: Totals: | B125: Occupied Sqft: | D125: 1 | E125: 1 Units | F125: 55358 | G125: 52856.13 | I125: 14960 | K125: 0
B126: Leased/Unoccupied Sqft: | E126: 0 Units | F126: 0 | M126: Forward start period
B127: Vacant Sqft: | E127: 0 Units | F127: 0 | M127: =EOMONTH(#REF!,0)+1 -> #REF!
B128: Total Sqft: | E128: 1 Units | F128: 55,358 | G128: 52856.13
A131: Total Seaboard Indust-5530 NW 32 Ct:
B132: Occupied Sqft: | D132: 1 | E132: 1 Units | F132: 55358 | G132: 52856.13 | I132: 14960 | K132: 0
B133: Leased/Unoccupied Sqft: | E133: 0 Units | F133: 0
B134: Vacant Sqft: | E134: 0 Units | F134: 0
B135: Total Sqft: | E135: 1 Units | F135: 55,358 | G135: 52856.13
A137: Grand Total:
B138: Occupied Sqft: | C138: 0.5348 | D138: 2 Units | E138: 155265 | F138: 129555.86 | H138: 42515.5 | J138: 0
B139: Leased/Unoccupied Sqft: | D139: 0 Units | E139: 0
B140: Vacant Sqft: | C140: 0.4652 | E140: 2 Units 135,081
B141: Total Sqft: | D141: 4 Units | E141: 290346 | F141: 129555.86 | G141: =E138/E141 -> 0.53475853

Sheet 1Q26 RR
A1: Seaboard Indust-3455 NW 54 St (Building Id: 2727901)
J2: Bldg Status: Active only
A3: Rent Roll | J3: Report Date: 3/31/2026 | M3: 46112
A4: . | B4: . | C4: . | D4: . | E4: . | F4: GLA | G4: Monthly | H4: Annual | I4: Monthly Cost | J4: Expense | K4: Monthly | L4: ---------------- Future Rent Increases ---------------- | Q4: Excluding tenants with NTV inside 90 days
A5: Bldg Id | B5: Suite Id | C5: Occupant Name | D5: Rent Start | E5: Expiration | F5: Sqft | G5: Base Rent | H5: Rate PSF | I5: Recovery | J5: Stop | K5: Other Income | L5: Cat | M5: Date | N5: Monthly Amt | O5: PSF | Q5: DY Test Rent Monthly | R5: DY Cost Recovery | S5: WALT | T5: =SUMPRODUCT($T$7:$T$41,$S$7:$S$41)/SUM($T$7:$T$41) -> 4.098565 | V5: Annualized Amounts including step ups inside 90 days
A6: Occupied Suites
A7: 2727901 | B7: 100 | C7: Zoox, Inc | D7: 46082 | E7: 48791 | F7: 143504 | G7: 0 | I7: 30305 | L7: BRT | M7: 46235 | N7: 37541.66 | O7: 3.14 | Q7: =N7 -> 37541.66 | R7: =I15 -> 30305 | S7: =(E7-$M$3)/365 -> 7.339726 | T7: =F7 -> 143504 | V7: =(Q7*12)*0.95 -> 427974.92
L8: BRT | M8: 46419 | N8: 98270.83 | O8: 8.22
L9: BRT | M9: 46600 | N9: 158452.33 | O9: 13.25
L10: BRT | M10: 46966 | N10: 163998.17 | O10: 13.71
L11: BRT | M11: 47331 | N11: 169738.1 | O11: 14.19
L12: BRT | M12: 47696 | N12: 175678.93 | O12: 14.69
L13: BRT | M13: 48061 | N13: 181827.2 | O13: 15.2
L14: BRT | M14: 48427 | N14: 188191.67 | O14: 15.74
A15: Totals: | C15: Occupied Sqft: | D15: 1 | E15: 1 Units | F15: 143504 | G15: 0 | I15: 30305 | K15: 0
C16: Vacant Sqft: | E16: 0 Units | F16: 0
C17: Total Sqft: | E17: 1 Units | F17: 143504
C18: Total Sqft: | E18: 1 Units | F18: 143504
A20: Total Seaboard Owner-3455 NW 54 St:
C21: Occupied Sqft: | D21: 1 | E21: 1 Units | F21: 143504 | G21: 0 | I21: 30305 | K21: 0
C22: Vacant Sqft: | E22: 0 Units | F22: 0
C23: Total Sqft: | E23: 1 Units | F23: 143504
C24: Total Sqft: | E24: 1 Units | F24: 143504
A26: Occupied Suites
A27: 2727902 | B27: 100 | C27: Sun Commodities Inc. | D27: 44805 | E27: 46721 | F27: 99907 | G27: 79384.22 | H27: 9.53 | I27: 20540 | L27: BRT | M27: 46113 | N27: 82162.67 | O27: 9.87 | Q27: =N27 -> 82162.67 | R27: =I35 -> 20540 | S27: =(E27-$M$3)/365 -> 1.6684932 | T27: =F35 -> 99907 | V27: =Q27*12 -> 985952.04
L28: BRT | M28: 46478 | N28: 85038.36 | O28: 10.21
A29: Totals: | C29: Occupied Sqft: | D29: 1 | E29: 1 Units | F29: 99907 | G29: 79384.22 | I29: 20540 | K29: 0
C30: Vacant Sqft: | E30: 0 Units | F30: 0
C31: Total Sqft: | E31: 1 Units | F31: 99907 | G31: 79384.22
C32: Total Sqft: | E32: 1 Units | F32: 99907 | G32: 79384.22
A34: Total Seaboard Owner-5400 NW 32nd Ct:
C35: Occupied Sqft: | D35: 1 | E35: 1 Units | F35: 99907 | G35: 79384.22 | I35: 20540 | K35: 0
C36: Vacant Sqft: | E36: 0 Units | F36: 0
C37: Total Sqft: | E37: 1 Units | F37: 99907 | G37: 79384.22
C38: Total Sqft: | E38: 1 Units | F38: 99907 | G38: 79384.22
A40: Occupied Suites
A41: 2727903 | B41: 100 | C41: Beacon Sales Acquisition Inc | D41: 40585 | E41: 46142 | F41: 55358 | G41: 54441.81 | H41: 11.8 | I41: 6866 | S41: =(E41-$M$3)/365 -> 0.082191781 | T41: =F42 -> 55358
A42: Totals: | C42: Occupied Sqft: | D42: 1 | E42: 1 Units | F42: 55358 | G42: 54441.81 | I42: 6866 | K42: 0
C43: Vacant Sqft: | E43: 0 Units | F43: 0 | N43: =G41*12 -> 653301.72
C44: Total Sqft: | E44: 1 Units | F44: 55358 | G44: 54441.81
C45: Total Sqft: | E45: 1 Units | F45: 55358 | G45: 54441.81
A47: Total Seaboard Owner-5530 NW 32 Ct:
C48: Occupied Sqft: | D48: 1 | E48: 1 Units | F48: 55358 | G48: 54441.81 | I48: 6866 | K48: 0
C49: Vacant Sqft: | E49: 0 Units | F49: 0
C50: Total Sqft: | E50: 1 Units | F50: 55358 | G50: 54441.81
C51: Total Sqft: | E51: 1 Units | F51: 55358 | G51: 54441.81
A53: Grand Total:
C54: Occupied Sqft: | D54: 1 | E54: 3 Units | F54: 298769 | G54: 133826.03 | I54: 57711 | K54: 0
C55: Vacant Sqft: | E55: 0 Units | F55: 0
C56: Total Sqft: | E56: 3 Units | F56: 298769 | G56: 133826.03
C57: Total Sqft: | E57: 3 Units | F57: 298769 | G57: 133826.03
A60: Report Id MRIX_CMROLL | C60: Database MSDE_SE | G60: Reported by Desiree Gonzalez | K60: 5/22/2026 11:57 AM | N60: Page | O60: 3
C62: Occupancy Current | F62: =(F54-F41-F7+34000)/F54 -> 0.44819576

Sheet 3Q T12
A1: Database: MSDE_SE | H1: Forecast - Budget Report
A2: PROJ: 27279 | H2: Lincoln Property Company
H3: WSLP Seaboard Owner IX LP
A5: Accrual
H6: Actual amounts from 01/25 to 09/25, Budget amounts from 10/25 to 12/25
C9: 45566 | D9: 45597 | E9: 45627 | F9: 45688 | G9: 45716 | H9: 45747 | I9: 45777 | J9: 45808 | K9: 45838 | L9: 45869 | M9: 45900 | N9: 45930 | O9: Total
A10: REVENUES
A12: 4005-00 | B12: BASE/MINIMUM RENT | C12: =SUMIFS('2Q T12'!F:F,'2Q T12'!$A:$A,'3Q T12'!$B12) -> 129555.86 | D12: =SUMIFS('2Q T12'!G:G,'2Q T12'!$A:$A,'3Q T12'!$B12) -> 129555.86 | E12: =SUMIFS('2Q T12'!H:H,'2Q T12'!$A:$A,'3Q T12'!$B12) -> 129555.86 | F12: 129556 | G12: 129556 | H12: 129556 | I12: 132240 | J12: 133826 | K12: 133826 | L12: 133826 | M12: 133826 | N12: 133826 | O12: =SUM(C12:N12) -> 1578705.6
A13: 4007-00 | B13: RENT CONCESSIONS | C13: =SUMIFS('2Q T12'!F:F,'2Q T12'!$A:$A,'3Q T12'!$B13) -> 0 | D13: =SUMIFS('2Q T12'!G:G,'2Q T12'!$A:$A,'3Q T12'!$B13) -> 0 | E13: =SUMIFS('2Q T12'!H:H,'2Q T12'!$A:$A,'3Q T12'!$B13) -> 0 | F13: 0 | G13: 0 | H13: 0 | I13: 0 | J13: 0 | K13: 0 | L13: 0 | M13: 0 | N13: 0 | O13: =SUM(C13:N13) -> 0
A14: 4025-00 | B14: UTILITY INCOME | C14: =SUMIFS('2Q T12'!F:F,'2Q T12'!$A:$A,'3Q T12'!$B14) -> 0 | D14: =SUMIFS('2Q T12'!G:G,'2Q T12'!$A:$A,'3Q T12'!$B14) -> 0 | E14: =SUMIFS('2Q T12'!H:H,'2Q T12'!$A:$A,'3Q T12'!$B14) -> 0 | F14: 0 | G14: -325 | H14: 0 | I14: 0 | J14: 0 | K14: 0 | L14: 0 | M14: 0 | N14: 0 | O14: =SUM(C14:N14) -> -325
A15: 4025-53 | B15: UTILITY INCOME-ELECTRIC | C15: =SUMIFS('2Q T12'!F:F,'2Q T12'!$A:$A,'3Q T12'!$B15) -> 0 | D15: =SUMIFS('2Q T12'!G:G,'2Q T12'!$A:$A,'3Q T12'!$B15) -> 0 | E15: =SUMIFS('2Q T12'!H:H,'2Q T12'!$A:$A,'3Q T12'!$B15) -> 0 | F15: 26 | G15: 0 | H15: 0 | I15: 0 | J15: 0 | K15: 0 | L15: 0 | M15: 0 | N15: 0 | O15: =SUM(C15:N15) -> 26
A16: 4105-02 | B16: INSURANCE REIMB | C16: =SUMIFS('2Q T12'!F:F,'2Q T12'!$A:$A,'3Q T12'!$B16) -> 8569.83 | D16: =SUMIFS('2Q T12'!G:G,'2Q T12'!$A:$A,'3Q T12'!$B16) -> 8569.83 | E16: =SUMIFS('2Q T12'!H:H,'2Q T12'!$A:$A,'3Q T12'!$B16) -> 8569.83 | F16: 11494 | G16: 11494 | H16: 11494 | I16: 11494 | J16: -130205 | K16: 11494 | L16: 11494 | M16: 54225 | N16: 11494 | O16: =SUM(C16:N16) -> 30187.49
A17: 4105-03 | B17: PROPERTY TAX REIMB | C17: =SUMIFS('2Q T12'!F:F,'2Q T12'!$A:$A,'3Q T12'!$B17) -> 28825.92 | D17: =SUMIFS('2Q T12'!G:G,'2Q T12'!$A:$A,'3Q T12'!$B17) -> 28825.92 | E17: =SUMIFS('2Q T12'!H:H,'2Q T12'!$A:$A,'3Q T12'!$B17) -> 28825.92 | F17: 24390 | G17: 24390 | H17: 24390 | I17: 24390 | J17: 21093 | K17: 24390 | L17: 24390 | M17: 24390 | N17: 24390 | O17: =SUM(C17:N17) -> 302690.76
A18: 4105-07 | B18: CAM REIMBURSEMENT | C18: =SUMIFS('2Q T12'!F:F,'2Q T12'!$A:$A,'3Q T12'!$B18) -> 5119.75 | D18: =SUMIFS('2Q T12'!G:G,'2Q T12'!$A:$A,'3Q T12'!$B18) -> 5119.75 | E18: =SUMIFS('2Q T12'!H:H,'2Q T12'!$A:$A,'3Q T12'!$B18) -> 5119.75 | F18: 2986 | G18: 2986 | H18: 2986 | I18: 2986 | J18: -10326 | K18: -39745 | L18: 2986 | M18: 2986 | N18: 2986 | O18: =SUM(C18:N18) -> -13809.75
A19: 4105-10 | B19: RECOVERY YEAR END EST | C19: =SUMIFS('2Q T12'!F:F,'2Q T12'!$A:$A,'3Q T12'!$B19) -> 0 | D19: =SUMIFS('2Q T12'!G:G,'2Q T12'!$A:$A,'3Q T12'!$B19) -> 0 | E19: =SUMIFS('2Q T12'!H:H,'2Q T12'!$A:$A,'3Q T12'!$B19) -> 0 | F19: 0 | G19: 0 | H19: 0 | I19: 0 | J19: 0 | K19: 0 | L19: 0 | M19: 0 | N19: 0 | O19: =SUM(C19:N19) -> 0
A20: 4115-00 | B20: MISCELLANEOUS INCOME | C20: =SUMIFS('2Q T12'!F:F,'2Q T12'!$A:$A,'3Q T12'!$B20) -> 40.77 | D20: =SUMIFS('2Q T12'!G:G,'2Q T12'!$A:$A,'3Q T12'!$B20) -> 30 | E20: =SUMIFS('2Q T12'!H:H,'2Q T12'!$A:$A,'3Q T12'!$B20) -> 30 | F20: 30 | G20: 30 | H20: 0 | I20: 0 | J20: 0 | K20: 0 | L20: 0 | M20: 0 | N20: 0 | O20: =SUM(C20:N20) -> 160.77
A21: EFFECTIVE RENTAL REVENUE | C21: =SUM(C12:C20) -> 172112.13 | D21: =SUM(D12:D20) -> 172101.36 | E21: =SUM(E12:E20) -> 172101.36 | F21: 168481 | G21: 168131 | H21: 168426 | I21: 171110 | J21: 14388 | K21: 129965 | L21: 172696 | M21: 215427 | N21: 172696 | O21: =SUM(C21:N21) -> 1897634.9
O22: =SUM(C22:N22) -> 0
A23: EFFECTIVE GROSS REVENUE | C23: =SUMIFS('2Q T12'!F:F,'2Q T12'!$A:$A,'3Q T12'!$B23) -> 0 | D23: =SUMIFS('2Q T12'!G:G,'2Q T12'!$A:$A,'3Q T12'!$B23) -> 0 | E23: =SUMIFS('2Q T12'!H:H,'2Q T12'!$A:$A,'3Q T12'!$B23) -> 0 | F23: 0 | G23: 0 | H23: 0 | I23: 0 | J23: 0 | K23: 0 | L23: 0 | M23: 0 | N23: 0 | O23: =SUM(C23:N23) -> 0
O24: =SUM(C24:N24) -> 0
A25: EXPENSES | O25: =SUM(C25:N25) -> 0
O26: =SUM(C26:N26) -> 0
A27: OPERATING EXPENSES | O27: =SUM(C27:N27) -> 0
A28: 5005-01 | B28: REAL ESTATE TAXES | C28: =SUMIFS('2Q T12'!F:F,'2Q T12'!$A:$A,'3Q T12'!$B28) -> -109312.86 | D28: =SUMIFS('2Q T12'!G:G,'2Q T12'!$A:$A,'3Q T12'!$B28) -> 41186.13 | E28: =SUMIFS('2Q T12'!H:H,'2Q T12'!$A:$A,'3Q T12'!$B28) -> 57003.51 | F28: 48859 | G28: 48859 | H28: 48859 | I28: 48859 | J28: 48859 | K28: 48859 | L28: 48859 | M28: 48859 | N28: 48859 | O28: =SUM(C28:N28) -> 428607.78
A29: 5007-00 | B29: INSURANCE | C29: =SUMIFS('2Q T12'!F:F,'2Q T12'!$A:$A,'3Q T12'!$B29) -> 23757.58 | D29: =SUMIFS('2Q T12'!G:G,'2Q T12'!$A:$A,'3Q T12'!$B29) -> 23757.58 | E29: =SUMIFS('2Q T12'!H:H,'2Q T12'!$A:$A,'3Q T12'!$B29) -> 18894.25 | F29: 23046 | G29: 23046 | H29: 0 | I29: 751 | J29: 666 | K29: 9724 | L29: 19335 | M29: 19333 | N29: 9666 | O29: =SUM(C29:N29) -> 171976.41
A30: 5010-04 | B30: BANK CHARGES | C30: =SUMIFS('2Q T12'!F:F,'2Q T12'!$A:$A,'3Q T12'!$B30) -> 1525 | D30: =SUMIFS('2Q T12'!G:G,'2Q T12'!$A:$A,'3Q T12'!$B30) -> 1525 | E30: =SUMIFS('2Q T12'!H:H,'2Q T12'!$A:$A,'3Q T12'!$B30) -> 2025 | F30: 1535 | G30: 1535 | H30: 625 | I30: 625 | J30: 625 | K30: 625 | L30: 625 | M30: 625 | N30: 625 | O30: =SUM(C30:N30) -> 12520
A31: 5010-13 | B31: LICENSES & PERMITS | C31: =SUMIFS('2Q T12'!F:F,'2Q T12'!$A:$A,'3Q T12'!$B31) -> 0 | D31: =SUMIFS('2Q T12'!G:G,'2Q T12'!$A:$A,'3Q T12'!$B31) -> 0 | E31: =SUMIFS('2Q T12'!H:H,'2Q T12'!$A:$A,'3Q T12'!$B31) -> 0 | F31: 0 | G31: 0 | H31: 0 | I31: 0 | J31: 0 | K31: 0 | L31: 0 | M31: 418 | N31: 0 | O31: =SUM(C31:N31) -> 418
A32: 5010-15 | B32: OTHER ADMINISTRATIVE | C32: =SUMIFS('2Q T12'!F:F,'2Q T12'!$A:$A,'3Q T12'!$B32) -> 1054.84 | D32: =SUMIFS('2Q T12'!G:G,'2Q T12'!$A:$A,'3Q T12'!$B32) -> 0 | E32: =SUMIFS('2Q T12'!H:H,'2Q T12'!$A:$A,'3Q T12'!$B32) -> 32.08 | F32: 214 | G32: 0 | H32: 0 | I32: 441 | J32: 197 | K32: 0 | L32: 0 | M32: 786 | N32: 197 | O32: =SUM(C32:N32) -> 2921.92
A33: 5010-16 | B33: POSTAGE & DELIVERY | C33: =SUMIFS('2Q T12'!F:F,'2Q T12'!$A:$A,'3Q T12'!$B33) -> 0 | D33: =SUMIFS('2Q T12'!G:G,'2Q T12'!$A:$A,'3Q T12'!$B33) -> 0 | E33: =SUMIFS('2Q T12'!H:H,'2Q T12'!$A:$A,'3Q T12'!$B33) -> 0 | F33: 0 | G33: 0 | H33: 0 | I33: 0 | J33: 0 | K33: 0 | L33: 0 | M33: 46 | N33: 113 | O33: =SUM(C33:N33) -> 159
A34: 5010-22 | B34: TRAVEL & TRANSPORTATION | C34: =SUMIFS('2Q T12'!F:F,'2Q T12'!$A:$A,'3Q T12'!$B34) -> 0 | D34: =SUMIFS('2Q T12'!G:G,'2Q T12'!$A:$A,'3Q T12'!$B34) -> 0 | E34: =SUMIFS('2Q T12'!H:H,'2Q T12'!$A:$A,'3Q T12'!$B34) -> 0 | F34: 0 | G34: 0 | H34: 0 | I34: 0 | J34: 0 | K34: 0 | L34: 0 | M34: 0 | N34: 0 | O34: =SUM(C34:N34) -> 0
A35: 5010-34 | B35: MILEAGE REIMBURSEMENT | C35: =SUMIFS('2Q T12'!F:F,'2Q T12'!$A:$A,'3Q T12'!$B35) -> 0 | D35: =SUMIFS('2Q T12'!G:G,'2Q T12'!$A:$A,'3Q T12'!$B35) -> 0 | E35: =SUMIFS('2Q T12'!H:H,'2Q T12'!$A:$A,'3Q T12'!$B35) -> 0 | F35: 0 | G35: 0 | H35: 9 | I35: 0 | J35: 0 | K35: 10 | L35: 0 | M35: 3 | N35: 0 | O35: =SUM(C35:N35) -> 22
A36: 5015-00 | B36: PROFESSIONAL FEES | C36: =SUMIFS('2Q T12'!F:F,'2Q T12'!$A:$A,'3Q T12'!$B36) -> 0 | D36: =SUMIFS('2Q T12'!G:G,'2Q T12'!$A:$A,'3Q T12'!$B36) -> 0 | E36: =SUMIFS('2Q T12'!H:H,'2Q T12'!$A:$A,'3Q T12'!$B36) -> 0 | F36: 0 | G36: 0 | H36: 0 | I36: 105 | J36: 0 | K36: 0 | L36: 0 | M36: 5500 | N36: 0 | O36: =SUM(C36:N36) -> 5605
A37: 5015-01 | B37: PROF FEES LEGAL | C37: =SUMIFS('2Q T12'!F:F,'2Q T12'!$A:$A,'3Q T12'!$B37) -> -100 | D37: =SUMIFS('2Q T12'!G:G,'2Q T12'!$A:$A,'3Q T12'!$B37) -> 0 | E37: =SUMIFS('2Q T12'!H:H,'2Q T12'!$A:$A,'3Q T12'!$B37) -> 0 | F37: 0 | G37: 0 | H37: 1150 | I37: 0 | J37: 0 | K37: 0 | L37: 0 | M37: 0 | N37: 2733 | O37: =SUM(C37:N37) -> 3783
A38: 5015-04 | B38: PROF FEES TAX APPEALS | C38: =SUMIFS('2Q T12'!F:F,'2Q T12'!$A:$A,'3Q T12'!$B38) -> 0 | D38: =SUMIFS('2Q T12'!G:G,'2Q T12'!$A:$A,'3Q T12'!$B38) -> 0 | E38: =SUMIFS('2Q T12'!H:H,'2Q T12'!$A:$A,'3Q T12'!$B38) -> -3954.33 | F38: 0 | G38: 0 | H38: 0 | I38: 0 | J38: 0 | K38: 7002 | L38: 0 | M38: 0 | N38: 0 | O38: =SUM(C38:N38) -> 3047.67
A39: 5020-01 | B39: ELECTRICITY | C39: =SUMIFS('2Q T12'!F:F,'2Q T12'!$A:$A,'3Q T12'!$B39) -> 1527.52 | D39: =SUMIFS('2Q T12'!G:G,'2Q T12'!$A:$A,'3Q T12'!$B39) -> 1322.87 | E39: =SUMIFS('2Q T12'!H:H,'2Q T12'!$A:$A,'3Q T12'!$B39) -> 2572.5 | F39: 2275 | G39: 965 | H39: 4621 | I39: 0 | J39: 3054 | K39: 1589 | L39: 1493 | M39: 781 | N39: 605 | O39: =SUM(C39:N39) -> 20805.89
... A54: 5030-00 | B54: PROPERTY MANAGEMENT FEES | C54: =SUMIFS('2Q T12'!F:F,'2Q T12'!$A:$A,'3Q T12'!$B54) -> 8380.5 | D54: =SUMIFS('2Q T12'!G:G,'2Q T12'!$A:$A,'3Q T12'!$B54) -> 2000 | E54: =SUMIFS('2Q T12'!H:H,'2Q T12'!$A:$A,'3Q T12'!$B54) -> 5162.14 | F54: 5098 | G54: 5053 | H54: 5043 | I54: 5178 | J54: 2085 | K54: 3528 | L54: 8280 | M54: 3099 | N54: 5181 | O54: =SUM(C54:N54) -> 58087.64
A55: TOTAL OPERATING EXPENSES | C55: =SUM(C28:C54) -> -47307.01 | D55: =SUM(D28:D54) -> 75162.89 | E55: =SUM(E28:E54) -> 96183.91 | F55: 87688 | G55: 84465 | H55: 61003 | I55: 58737 | J55: 69859 | K55: 79803 | L55: 81476 | M55: 85104 | N55: 88504 | O55: =SUM(C55:N55) -> 820678.79
O56: =SUM(C56:N56) -> 0
A57: OPERATING EXPENSES - NON RECOVER | O57: =SUM(C57:N57) -> 0
A58: 6015-00 | B58: PROFESSIONAL FEES NON | C58: =SUMIFS('2Q T12'!F:F,'2Q T12'!$A:$A,'3Q T12'!$B58) -> 7406.07 | D58: =SUMIFS('2Q T12'!G:G,'2Q T12'!$A:$A,'3Q T12'!$B58) -> 0 | E58: =SUMIFS('2Q T12'!H:H,'2Q T12'!$A:$A,'3Q T12'!$B58) -> 0 | F58: 0 | G58: 0 | H58: 5775 | I58: 0 | J58: 20472 | K58: 16320 | L58: 1000 | M58: 0 | N58: 0 | O58: =SUM(C58:N58) -> 50973.07
A59: 6015-01 | B59: PROF FEES LEGAL NON | C59: =SUMIFS('2Q T12'!F:F,'2Q T12'!$A:$A,'3Q T12'!$B59) -> 0 | D59: =SUMIFS('2Q T12'!G:G,'2Q T12'!$A:$A,'3Q T12'!$B59) -> 0 | E59: =SUMIFS('2Q T12'!H:H,'2Q T12'!$A:$A,'3Q T12'!$B59) -> 0 | F59: 0 | G59: 0 | H59: 480 | I59: 0 | J59: 0 | K59: 0 | L59: 0 | M59: 600 | N59: 0 | O59: =SUM(C59:N59) -> 1080
A60: 6020-02 | B60: HVAC-NON RECOV | C60: =SUMIFS('2Q T12'!F:F,'2Q T12'!$A:$A,'3Q T12'!$B60) -> 0 | D60: =SUMIFS('2Q T12'!G:G,'2Q T12'!$A:$A,'3Q T12'!$B60) -> 0 | E60: =SUMIFS('2Q T12'!H:H,'2Q T12'!$A:$A,'3Q T12'!$B60) -> 0 | F60: 0 | G60: 948 | H60: 406 | I60: 0 | J60: 0 | K60: 0 | L60: 0 | M60: 0 | N60: 0 | O60: =SUM(C60:N60) -> 1354
A61: 6045-01 | B61: SOFTWARE LICENSING-NON RECOV | C61: =SUMIFS('2Q T12'!F:F,'2Q T12'!$A:$A,'3Q T12'!$B61) -> 83.35 | D61: =SUMIFS('2Q T12'!G:G,'2Q T12'!$A:$A,'3Q T12'!$B61) -> 83.33 | E61: =SUMIFS('2Q T12'!H:H,'2Q T12'!$A:$A,'3Q T12'!$B61) -> 83.33 | F61: 83 | G61: 83 | H61: 0 | I61: 250 | J61: 0 | K61: 0 | L61: 250 | M61: 0 | N61: 0 | O61: =SUM(C61:N61) -> 916.01
A62: 8010-00 | B62: ASSET MANAGEMENT FEES | C62: =SUMIFS('2Q T12'!F:F,'2Q T12'!$A:$A,'3Q T12'!$B62) -> 0 | D62: =SUMIFS('2Q T12'!G:G,'2Q T12'!$A:$A,'3Q T12'!$B62) -> 0 | E62: =SUMIFS('2Q T12'!H:H,'2Q T12'!$A:$A,'3Q T12'!$B62) -> 0 | F62: 1274 | G62: 1263 | H62: 0 | I62: 1261 | J62: 0 | K62: 2614 | L62: 882 | M62: 0 | N62: 0 | O62: =SUM(C62:N62) -> 7294
A63: 8030-01 | B63: INTEREST EXPENSE | C63: 261948.03 | D63: 241477.04 | E63: 242472.14 | F63: 242835 | G63: 216515 | H63: 290887 | I63: 174537 | J63: 242708 | K63: 243626 | L63: 235491 | M63: 244886 | N63: 245352 | O63: =SUM(C63:N63) -> 2882734.2
A64: TOTAL OPER EXP N/R | C64: =SUMIFS('2Q T12'!F:F,'2Q T12'!$A:$A,'3Q T12'!$B64) -> 0 | D64: =SUMIFS('2Q T12'!G:G,'2Q T12'!$A:$A,'3Q T12'!$B64) -> 0 | E64: =SUMIFS('2Q T12'!H:H,'2Q T12'!$A:$A,'3Q T12'!$B64) -> 0 | F64: 244192 | G64: 218809 | H64: 297548 | I64: 176048 | J64: 263180 | K64: 262559 | L64: 237623 | M64: 245486 | N64: 245352 | O64: =SUM(C64:N64) -> 2190797
O65: =SUM(C65:N65) -> 0
A66: NET OPERATING INCOME | C66: =SUMIFS('2Q T12'!F:F,'2Q T12'!$A:$A,'3Q T12'!$B66) -> 0 | D66: =SUMIFS('2Q T12'!G:G,'2Q T12'!$A:$A,'3Q T12'!$B66) -> 0 | E66: =SUMIFS('2Q T12'!H:H,'2Q T12'!$A:$A,'3Q T12'!$B66) -> 0 | F66: -163399 | G66: -135143 | H66: -190125 | I66: -63675 | J66: -318651 | K66: -212397 | L66: -146403 | M66: -115163 | N66: -161160 | O66: =SUM(C66:N66) -> -1506116
C67: =C21-C55-SUM(C58:C62) -> 211929.72 | D67: =D21-D55-SUM(D58:D62) -> 96855.14 | E67: =E21-E55-SUM(E58:E62) -> 75834.12 | F67: =F21-F55-SUM(F58:F62) -> 79436 | G67: =G21-G55-SUM(G58:G62) -> 81372 | H67: =H21-H55-SUM(H58:H62) -> 100762 | I67: =I21-I55-SUM(I58:I62) -> 110862 | J67: =J21-J55-SUM(J58:J62) -> -75943 | ... N67: =N21-N55-SUM(N58:N62) -> 84192 | O67: =SUM(C67:N67) -> 1015339
C68: =SUMIFS('2Q T12'!F:F,'2Q T12'!$A:$A,'3Q T12'!$B68) -> 0 | D68: =SUMIFS('2Q T12'!G:G,'2Q T12'!$A:$A,'3Q T12'!$B68) -> 0 | E68: =SUMIFS('2Q T12'!H:H,'2Q T12'!$A:$A,'3Q T12'!$B68) -> 0
A69: NET INCOME | C69: =SUMIFS('2Q T12'!F:F,'2Q T12'!$A:$A,'3Q T12'!$B69) -> 0 | D69: =SUMIFS('2Q T12'!G:G,'2Q T12'!$A:$A,'3Q T12'!$B69) -> 0 | E69: =SUMIFS('2Q T12'!H:H,'2Q T12'!$A:$A,'3Q T12'!$B69) -> 0 | F69: -163399 | G69: -135143 | H69: -190125 | I69: -63675 | J69: -318651 | K69: -212397 | L69: -146403 | M69: 210935 | N69: 213175
B71: CAPITAL EXPENSES
B72: BUILDING IMPROVEMENTS | C72: 0 | D72: 0 | E72: -1101532.6 | F72: 0 | G72: 270514 | H72: 0 | I72: 0 | J72: 0 | K72: 0 | L72: 0 | M72: 0 | N72: 0 | O72: =SUM(C72:N72) -> -831018.55
B73: TENANT IMPROVEMENTS | C73: 0 | D73: 0 | E73: -1500 | F73: 0 | G73: 0 | H73: 0 | I73: 0 | J73: 5625 | K73: 0 | L73: 0 | M73: 0 | N73: 0 | O73: =SUM(C73:N73) -> 4125
B74: LEASING COMMISSIONS | F74: 0 | G74: 0 | H74: 0 | I74: 0 | J74: 0 | K74: 0 | L74: 0 | M74: 0 | N74: 0
B75: CONSTRUCTION IN PROGRESS | C75: 208802.92 | D75: 471034.7 | E75: 1158386.4 | F75: 33892 | G75: -251276 | H75: -119128 | I75: 0 | J75: 104148 | K75: 0 | L75: 0 | M75: 0 | N75: 0 | O75: =SUM(C75:N75) -> 1605860
B76: TOTAL CAPITAL EXPENSES | C76: =SUM(C72:C75) -> 208802.92 | D76: =SUM(D72:D75) -> 471034.7 | E76: =SUM(E72:E75) -> 55353.85 | F76: 33892 | G76: 19239 | H76: -119128 | I76: 0 | J76: 109773 | K76: 0 | L76: 0 | M76: 0 | N76: 0 | O76: =SUM(O72:O75) -> 778966.47
A78: NET INCOME LESS CAPITAL EXPENSES | F78: -197292 | G78: -154382 | H78: -70997 | I78: -63675 | J78: -428424 | K78: -212397 | L78: -146403 | M78: 210935 | N78: 213175

Sheet 2Q T12
B1: Database: MSDE_SE | C1: Rolling Twelve Month Income Statement
B2: Report Id: MRI_R12MINCS | C2: Lincoln Property Company
B3: PROJ: 27279 | C3: WSLP Seaboard Owner IX LP
B4: SEABOARD
B6: Accrual | C6: Ending Period June 2025
A9: CODE for 3Q T12 | C9: 07/24 | D9: 08/24 | E9: 09/24 | F9: 10/24 | G9: 11/24 | H9: 12/24 | I9: 01/25 | J9: 02/25 | K9: 03/25 | L9: 04/25 | M9: 05/25 | N9: 06/25 | O9: Total
B10: REVENUES:
B12: RENTAL INCOME
A13: BASE/MINIMUM RENT | B13: BASE/MINIMUM RENT | C13: 129555.86 | D13: 129555.86 | E13: 129555.86 | F13: 129555.86 | G13: 129555.86 | H13: 129555.86 | I13: 129555.86 | J13: 129555.86 | K13: 129555.86 | L13: 132240.35 | M13: 133826.03 | N13: 133826.03 | O13: 1565895.1
A14: BASE/MINIMUM RENT | B14: HOLDOVER RENT | C14: 96708.93 | D14: 52952.55 | E14: 0 | F14: 0 | G14: 0 | H14: 0 | I14: 0 | J14: 0 | K14: 0 | L14: 0 | M14: 0 | N14: 0 | O14: 149661.48
B15: TOTAL RENTAL REVENUE | C15: 226264.79 | D15: 182508.41 | E15: 129555.86 | F15: 129555.86 | G15: 129555.86 | H15: 129555.86 | I15: 129555.86 | J15: 129555.86 | K15: 129555.86 | L15: 132240.35 | M15: 133826.03 | N15: 133826.03 | O15: 1715556.6
B17: OTHER INCOME
A18: UTILITY INCOME | B18: UTILITY INCOME | C18: 0 | D18: 0 | E18: 0 | F18: 0 | G18: 0 | H18: 0 | I18: 0 | J18: -325.25 | K18: 0 | L18: 0 | M18: 0 | N18: 0 | O18: -325.25
A19: UTILITY INCOME-ELECTRIC | B19: UTILITY INCOME-ELECTRIC | C19: 0 | D19: 0 | E19: 0 | F19: 0 | G19: 0 | H19: 0 | I19: 25.62 | J19: 0 | K19: 0 | L19: 0 | M19: 0 | N19: 0 | O19: 25.62
A20: INSURANCE REIMB | B20: INSURANCE REIMB | C20: 37986.67 | D20: 29330.68 | E20: 19972.39 | F20: 8569.83 | G20: 8569.83 | H20: 8569.83 | I20: 11494 | J20: 11494 | K20: 11494 | L20: 11494 | M20: -130205 | N20: 11494 | O20: 40264.23
A21: PROPERTY TAX REIMB | B21: PROPERTY TAX REIMB | C21: 36311.46 | D21: 27437.21 | E21: 17840.74 | F21: 28825.92 | G21: 28825.92 | H21: 28825.92 | I21: 24390 | J21: 24390 | K21: 24390 | L21: 24390 | M21: 21093 | N21: 24390 | O21: 311110.17
A22: CAM REIMBURSEMENT | B22: CAM REIMBURSEMENT | C22: 4992.7 | D22: 4992.7 | E22: 4992.7 | F22: 5119.75 | G22: 5119.75 | H22: 5119.75 | I22: 2986 | J22: 2986 | K22: 2986 | L22: 2986 | M22: -10326 | N22: -39744.58 | O22: -7789.23
A23: MISCELLANEOUS INCOME | B23: INTEREST ESCROW | C23: 6.49 | D23: 0 | E23: 0 | F23: 10.77 | G23: 0 | H23: 0 | I23: 0 | J23: 0 | K23: 0 | L23: 0 | M23: 0 | N23: 0 | O23: 17.26
A24: MISCELLANEOUS INCOME | B24: MISCELLANEOUS INCOME | C24: 30 | D24: 30 | E24: 30 | F24: 30 | G24: 30 | H24: 30 | I24: 30 | J24: 30 | K24: 0 | L24: 0 | M24: 0 | N24: 0 | O24: 240
A25: MISCELLANEOUS INCOME | B25: TENANT WORK ORDER REIMB | C25: 0 | D25: 7550 | E25: 0 | F25: 0 | G25: 0 | H25: 0 | I25: 0 | J25: 0 | K25: 0 | L25: 0 | M25: 0 | N25: 0 | O25: 7550
B26: TOTAL OTHER INCOME | C26: 79327.32 | D26: 69340.59 | E26: 42835.83 | F26: 42556.27 | G26: 42545.5 | H26: 42545.5 | I26: 38925.62 | J26: 38574.75 | K26: 38870 | L26: 38870 | M26: -119438 | N26: -3860.58 | O26: 351092.8
B28: TOTAL REVENUE | C28: 305592.11 | D28: 251849 | E28: 172391.69 | F28: 172112.13 | G28: 172101.36 | H28: 172101.36 | I28: 168481.48 | J28: 168130.61 | K28: 168425.86 | L28: 171110.35 | M28: 14388.03 | N28: 129965.45 | O28: 2066649.4
B30: EXPENSES:
B31: OPERATING EXPENSES
B33: TAXES & INSURANCE
A34: REAL ESTATE TAXES | B34: REAL ESTATE TAXES | C34: 57908.24 | D34: 57908.24 | E34: 57908.24 | F34: -109312.86 | G34: 41186.13 | H34: 41186.18 | I34: 48858.75 | J34: 48858.77 | K34: 48858.75 | L34: 48858.75 | M34: 48858.75 | N34: 48858.75 | O34: 439936.69
A35: REAL ESTATE TAXES | B35: RE TAXES - PRIOR YR | C35: 0 | D35: 0 | E35: 0 | F35: 0 | G35: 0 | H35: 15817.33 | I35: 0 | J35: 0 | K35: 0 | L35: 0 | M35: 0 | N35: 0 | O35: 15817.33
A36: INSURANCE | B36: INSURANCE | C36: 23157.56 | D36: 23757.58 | E36: 23757.58 | F36: 23757.58 | G36: 23757.58 | H36: 18894.25 | I36: 23045.86 | J36: 23045.86 | K36: 0 | L36: 751.41 | M36: 665.67 | N36: 9724.02 | O36: 194314.95
B37: TOTAL TAXES & INSURANCE | C37: 81065.8 | D37: 81665.82 | E37: 81665.82 | F37: -85555.28 | G37: 64943.71 | H37: 75897.76 | I37: 71904.61 | J37: 71904.63 | K37: 48858.75 | L37: 49610.16 | M37: 49524.42 | N37: 58582.77 | O37: 650068.97
B39: ADMINISTRATION
A40: BANK CHARGES | B40: BANK CHARGES | C40: 1518.2 | D40: 1523.08 | E40: 1525 | F40: 1525 | G40: 1525 | H40: 2025 | I40: 1534.68 | J40: 1534.68 | K40: 625 | L40: 625 | M40: 625 | N40: 625 | O40: 15210.64
A41: OTHER ADMINISTRATIVE | B41: OTHER ADMINISTRATIVE | C41: 0 | D41: 0 | E41: 0 | F41: 0 | G41: 0 | H41: 32.08 | I41: 214.39 | J41: 0 | K41: 0 | L41: 440.65 | M41: 196.52 | N41: 0 | O41: 883.64
A42: MILEAGE REIMBURSEMENT | B42: MILEAGE REIMBURSEMENT | C42: 0 | D42: 0 | E42: 0 | F42: 0 | G42: 0 | H42: 0 | I42: 0 | J42: 0 | K42: 9.1 | L42: 0 | M42: 0 | N42: 9.73 | O42: 18.83
B43: TOTAL ADMINISTRATION | C43: 1518.2 | D43: 1523.08 | E43: 1525 | F43: 1525 | G43: 1525 | H43: 2057.08 | I43: 1749.07 | J43: 1534.68 | K43: 634.1 | L43: 1065.65 | M43: 821.52 | N43: 634.73 | O43: 16113.11
B45: PROFESSIONAL FEES
A46: PROFESSIONAL FEES | B46: PROFESSIONAL FEES | C46: 0 | D46: 5500 | E46: 0 | F46: 0 | G46: 0 | H46: 0 | I46: 0 | J46: 0 | K46: 0 | L46: 105 | M46: 0 | N46: 0 | O46: 5605
A47: PROF FEES LEGAL | B47: PROF FEES LEGAL | C47: 3025 | D47: 6300 | E47: 0 | F47: -100 | G47: 0 | H47: 0 | I47: 0 | J47: 0 | K47: 1150 | L47: 0 | M47: 0 | N47: 0 | O47: 10375
A48: PROF FEES TAX APPEALS | B48: PROF FEES TAX APPEALS | C48: 0 | D48: 8018.51 | E48: 0 | F48: 0 | G48: 0 | H48: -3954.33 | I48: 0 | J48: 0 | K48: 0 | L48: 0 | M48: 0 | N48: 7001.93 | O48: 11066.11
B49: TOTAL PROFESSIONAL FEES | C49: 3025 | D49: 19818.51 | E49: 0 | F49: -100 | G49: 0 | H49: -3954.33 | I49: 0 | J49: 0 | K49: 1150 | L49: 105 | M49: 0 | N49: 7001.93 | O49: 27046.11
B51: UTILITIES
A52: ELECTRICITY | B52: ELECTRICITY | C52: 1032.16 | D52: 483.68 | E52: 1794.33 | F52: 1527.52 | G52: 1322.87 | H52: 2572.5 | I52: 2275.05 | J52: 965.25 | K52: 4620.82 | L52: 0 | M52: 3053.81 | N52: 1589.06 | O52: 21237.05
A53: WATER & SEWER | B53: WATER & SEWER | C53: 0 | D53: 23 | E53: 4.08 | F53: 8 | G53: 9.09 | H53: 10798.07 | I53: 3026.72 | J53: 2127 | K53: -1460.81 | L53: 0 | M53: 8240.84 | N53: 0 | O53: 22775.99
A54: WATER | B54: WATER | C54: 2935.37 | D54: 697.88 | E54: 1393.4 | F54: 1489.4 | G54: 1970.68 | H54: 1786.68 | I54: 1729.68 | J54: 928.43 | K54: 418.68 | L54: 0 | M54: 3459.36 | N54: 1729.68 | O54: 18539.24
A55: WATER - FIRE LINES | B55: WATER - FIRE LINES | C55: 0 | D55: 0 | E55: 0 | F55: 0 | G55: 0 | H55: 0 | I55: 0 | J55: 0 | K55: 0 | L55: 0 | M55: 256 | N55: 0 | O55: 256
B56: TOTAL UTILITIES | C56: 3967.53 | D56: 1204.56 | E56: 3191.81 | F56: 3024.92 | G56: 3302.64 | H56: 15157.25 | I56: 7031.45 | J56: 4020.68 | K56: 3578.69 | L56: 0 | M56: 15010.01 | N56: 3318.74 | O56: 62808.28
B58: REPAIRS & MAINTENANCE
A59: R&M EQUIP MONITORING SYS | B59: R&M EQUIP MONITORING SYS | C59: 179.76 | D59: 179.76 | E59: 179.76 | F59: 179.76 | G59: 179.76 | H59: 179.76 | I59: 179.76 | J59: -179.76 | K59: 0 | L59: 0 | M59: 0 | N59: 0 | O59: 1078.56
A60: R&M FIRE SAFETY CONTRACT | B60: R&M FIRE SAFETY CONTRACT | C60: 0 | D60: 1745.7 | E60: 0 | F60: 0 | G60: 0 | H60: 0 | I60: 0 | J60: 359.52 | K60: 179.76 | L60: 179.76 | M60: 179.76 | N60: 179.76 | O60: 2824.26
A61: R&M FIRE SAFETY REPAIRS | B61: R&M FIRE SAFETY REPAIRS | C61: 430.68 | D61: 6444.46 | E61: 624.36 | F61: 1600.19 | G61: 268.04 | H61: 0 | I61: 167.99 | J61: 0 | K61: 0 | L61: 0 | M61: 0 | N61: 0 | O61: 9535.72
A62: R&M HVAC REPAIRS | B62: R&M HVAC REPAIRS | C62: 0 | D62: 0 | E62: 0 | F62: 0 | G62: 1260.7 | H62: 0 | I62: 0 | J62: 0 | K62: 0 | L62: 0 | M62: 0 | N62: 0 | O62: 1260.7
A63: R&M LANDSCAPE EXT CONTRCT | B63: R&M LANDSCAPE EXT CONTRCT | C63: 1469.86 | D63: 4409.58 | E63: 1469.86 | F63: 1469.86 | G63: 1469.86 | H63: 1469.86 | I63: 1558.06 | J63: 1558.06 | K63: 1558.06 | L63: 1558.06 | M63: 1558.06 | N63: 1558.06 | O63: 21107.24
A64: R&M LANDSCAPE EXT CONTRCT | B64: R&M LANDSCAPE EXT REPAIRS | C64: 0 | D64: -2939.72 | E64: 0 | F64: 0 | G64: 0 | H64: 0 | I64: 0 | J64: 0 | K64: 0 | L64: 0 | M64: 0 | N64: 0 | O64: -2939.72
A65: R&M MINOR CLEANING | B65: R&M MINOR CLEANING | C65: 0 | D65: 0 | E65: 0 | F65: 0 | G65: 0 | H65: 0 | I65: 0 | J65: 0 | K65: 0 | L65: 0 | M65: 680 | N65: 0 | O65: 680
A66: R&M PLUMBING REPAIRS | B66: R&M PLUMBING REPAIRS | C66: 0 | D66: 0 | E66: 0 | F66: 0 | G66: 0 | H66: 0 | I66: 0 | J66: 0 | K66: 0 | L66: 1041 | M66: 0 | N66: 0 | O66: 1041
A67: R&M EXTERIOR REPAIRS & LABOR | B67: R&M EXTERIOR REPAIRS & LABOR | C67: 0 | D67: 0 | E67: 0 | F67: 20900 | G67: 0 | H67: 0 | I67: 0 | J67: 0 | K67: 0 | L67: 0 | M67: 0 | N67: 4999.24 | O67: 25899.24
A68: R&M OTHER | B68: R&M OTHER | C68: 213.2 | D68: 213.2 | E68: 213.2 | F68: 213.2 | G68: 213.18 | H68: 214.39 | I68: 0 | J68: 214.39 | K68: 0 | L68: 0 | M68: 0 | N68: 0 | O68: 1494.76
B69: TOTAL REPAIRS & MAINTENANCE | C69: 2293.5 | D69: 10052.98 | E69: 2487.18 | F69: 24363.01 | G69: 3391.54 | H69: 1864.01 | I69: 1905.81 | J69: 1952.21 | K69: 1737.82 | L69: 2778.82 | M69: 2417.82 | N69: 6737.06 | O69: 61981.76
B71: MANAGEMENT FEE
A72: PROPERTY MANAGEMENT FEES | B72: PROPERTY MANAGEMENT FEES | C72: 13427.21 | D72: 7580.23 | E72: 2000 | F72: 8380.5 | G72: 2000 | H72: 5162.14 | I72: 5097.55 | J72: 5052.77 | K72: 5043.3 | L72: 5177.55 | M72: 2085.39 | N72: 3527.67 | O72: 64534.31
B73: TOTAL MANAGEMENT FEE | C73: 13427.21 | D73: 7580.23 | E73: 2000 | F73: 8380.5 | G73: 2000 | H73: 5162.14 | I73: 5097.55 | J73: 5052.77 | K73: 5043.3 | L73: 5177.55 | M73: 2085.39 | N73: 3527.67 | O73: 64534.31
B75: TOTAL OPERATING EXPENSES | C75: 105297.24 | D75: 121845.18 | E75: 90869.81 | F75: -48361.85 | G75: 75162.89 | H75: 96183.91 | I75: 87688.49 | J75: 84464.97 | K75: 61002.66 | L75: 58737.18 | M75: 69859.16 | N75: 79802.9 | O75: 882552.54
B77: NON-RECOVERABLE EXPENSES
A78: OTHER ADMINISTRATIVE | B78: OTHER ADMINISTRATIVE - NON | C78: 3871.29 | D78: 0 | E78: 0 | F78: 1054.84 | G78: 0 | H78: 0 | I78: 0 | J78: 0 | K78: 0 | L78: 0 | M78: 0 | N78: 0 | O78: 4926.13
A79: PROFESSIONAL FEES NON | B79: PROFESSIONAL FEES NON | C79: 1133.87 | D79: 0 | E79: 0 | F79: 7406.07 | G79: 0 | H79: 0 | I79: 0 | J79: 0 | K79: 5775.35 | L79: 0 | M79: 20472 | N79: 16320 | O79: 51107.29
A80: PROF FEES LEGAL | B80: PROF FEES LEGAL NON | C80: 0 | D80: 0 | E80: 0 | F80: 0 | G80: 0 | H80: 0 | I80: 0 | J80: 0 | K80: 480 | L80: 0 | M80: 0 | N80: 0 | O80: 480
A81: HVAC-NON RECOV | B81: HVAC-NON RECOV | C81: 0 | D81: 0 | E81: 0 | F81: 0 | G81: 0 | H81: 0 | I81: 0 | J81: 947.68 | K81: 405.7 | L81: 0 | M81: 0 | N81: 0 | O81: 1353.38
A82: SOFTWARE LICENSING-NON RECOV | B82: SOFTWARE LICENSING-NON RECOV | C82: 83.33 | D82: 83.33 | E82: 83.33 | F82: 83.35 | G82: 83.33 | H82: 83.33 | I82: 83.34 | J82: 83.33 | K82: 0 | L82: 250 | M82: 0 | N82: 0 | O82: 916.67
B83: TOTAL NON-RECOVERABLE EXPENSES | C83: 5088.49 | D83: 83.33 | E83: 83.33 | F83: 8544.26 | G83: 83.33 | H83: 83.33 | I83: 83.34 | J83: 1031.01 | K83: 6661.05 | L83: 250 | M83: 20472 | N83: 16320 | O83: 58783.47
B84: TOTAL EXPENSES | C84: 110385.73 | D84: 121928.51 | E84: 90953.14 | F84: -39817.59 | G84: 75246.22 | H84: 96267.24 | I84: 87771.83 | J84: 85495.98 | K84: 67663.71 | L84: 58987.18 | M84: 90331.16 | N84: 96122.9 | O84: 941336.01
B86: NET OPERATING INCOME | C86: 195206.38 | D86: 129920.49 | E86: 81438.55 | F86: 211929.72 | G86: 96855.14 | H86: 75834.12 | I86: 80709.65 | J86: 82634.63 | K86: 100762.15 | L86: 112123.17 | M86: -75943.13 | N86: 33842.55 | O86: 1125313.4
B88: NON OPERATING EXPENSES
B90: ASSET MANAGEMENT FEES | C90: 4475.74 | D90: -15829.54 | E90: 4566.96 | F90: 2095.12 | G90: 495.85 | H90: 1290.53 | I90: 1274.39 | J90: 1263.19 | K90: 0 | L90: 1260.83 | M90: 0 | N90: 2613.69 | O90: 3506.76
B91: INTEREST EXPENSE | C91: 268279.64 | D91: 268641.24 | E91: 257389.52 | F91: 261948.03 | G91: 241477.04 | H91: 242472.14 | I91: 242834.75 | J91: 216514.74 | K91: 290887.32 | L91: 174537.11 | M91: 242708.28 | N91: 243625.78 | O91: 2951315.6
B92: INT RATE CAP EXPENSE | C92: -11694.76 | D92: -17572.11 | E92: -13648.41 | F92: 1468.75 | G92: 1856 | H92: 0 | I92: 0 | J92: 0 | K92: 0 | L92: 0 | M92: 0 | N92: 0 | O92: -39590.53
B93: GAIN/LOSS ON SWAP | C93: 0 | D93: 0 | E93: 268000 | F93: 0 | G93: 0 | H93: 0 | I93: 0 | J93: 0 | K93: 0 | L93: 0 | M93: 0 | N93: 0 | O93: 268000
B94: UNREALIZED FMV ADJ | C94: 0 | D94: 0 | E94: -205946 | F94: 0 | G94: 0 | H94: 5322 | I94: 0 | J94: 0 | K94: 0 | L94: 0 | M94: 0 | N94: 0 | O94: -200624
B95: TOTAL NON OPERATING EXPENSES | C95: 261060.62 | D95: 235239.59 | E95: 310362.07 | F95: 265511.9 | G95: 243828.89 | H95: 249084.67 | I95: 244109.14 | J95: 217777.93 | K95: 290887.32 | L95: 175797.94 | M95: 242708.28 | N95: 246239.47 | O95: 2982607.8
B96: NET INCOME | C96: -65854.24 | D96: -105319.1 | E96: -228923.52 | F96: -53582.18 | G96: -146973.75 | H96: -173250.55 | I96: -163399.49 | J96: -135143.3 | K96: -190125.17 | L96: -63674.77 | M96: -318651.41 | N96: -212396.92 | O96: -1857294.4
B98: CAPITAL EXPENSES
B99: BUILDING IMPROVEMENTS | C99: -6270.71 | D99: 0 | E99: 0 | F99: 0 | G99: 0 | H99: -1101532.6 | I99: 0 | J99: 270514.17 | K99: 0 | L99: 0 | M99: 0 | N99: 0 | O99: -837289.09
B100: TENANT IMPROVEMENTS | C100: 0 | D100: 0 | E100: 0 | F100: 0 | G100: 0 | H100: -1500 | I100: 0 | J100: 0 | K100: 0 | L100: 0 | M100: 5625 | N100: 0 | O100: 4125
B101: CONSTRUCTION IN PROGRESS | C101: 15296.43 | D101: 106610.35 | E101: 263484.92 | F101: 208802.92 | G101: 471034.7 | H101: 1158386.4 | I101: 33892.29 | J101: -251275.65 | K101: -119127.95 | L101: 0 | M101: 104147.81 | N101: 0 | O101: 1991252.2
B102: TOTAL CAPITAL EXPENSES | C102: 9025.72 | D102: 106610.35 | E102: 263484.92 | F102: 208802.92 | G102: 471034.7 | H102: 55353.85 | I102: 33892.29 | J102: 19238.52 | K102: -119127.95 | L102: 0 | M102: 109772.81 | N102: 0 | O102: 1158088.1
B104: NET INCOME LESS CAPITAL EXPENSES | C104: -74879.96 | D104: -211929.45 | E104: -492408.44 | F104: -262385.1 | G104: -618008.45 | H104: -228604.4 | I104: -197291.78 | J104: -154381.82 | K104: -70997.22 | L104: -63674.77 | M104: -428424.22 | N104: -212396.92 | O104: -3015382.5

Sheet Definitions
