Workbook
Name and: #REF!
Name andd: #REF!
Name anddd: #REF!
Name andddd: #REF!
Name att: #REF!
Name Attribute: #REF!
Name Benchmark: #REF!
Name Body: #REF!
Name bug: #REF!
Name Capped: #REF!
Name CMNOTES: #REF!
Name date: #REF!
Name det: #REF!
Name Detail: #REF!
Name doo: #REF!
Name jeunee: #REF!
Name jnue: #REF!
Name JR_PAGE_ANCHOR_0_1: #REF!
Name juenn: #REF!
Name jul: #REF!
Name july614amt: #REF!
Name jun: #REF!
Name june: #REF!
Name june14amt: #REF!
Name june7380: #REF!
Name june7381: #REF!
Name june814amt: #REF!
Name june8810: #REF!
Name june8825: #REF!
Name june8826: #REF!
Name junee: #REF!
Name juneeee: #REF!
Name Level3IL: #REF!
Name my: #REF!
Name MyAttribute: #REF!
Name mybug: #REF!
Name MyDate: #REF!
Name MyQuarter: #REF!
Name MyRange: #REF!
Name MyRateIncrease: #REF!
Name myunit: #REF!
Name MyUnitTransferDecrease: #REF!
Name MyUnitTransIncrease: #REF!
Name nana: #REF!
Name nanana: #REF!
Name newsummary: #REF!
Name operations: #REF!
Name opie: #REF!
Name pre: #REF!
Name prep: #REF!
Name Prepaid3: #REF!
Name prepaid4: #REF!
Name quart: #REF!
Name range: #REF!
Name rate: #REF!
Name RESULTS: #REF!
Name Sample1: #REF!
Name savings: #REF!
Name sec: #REF!
Name Sec3TotalRes: #REF!

Sheet Comm OSAR
B1: CREFC Investor Reporting Package
B2: COMMERCIAL OPERATING STATEMENT ANALYSIS REPORT (includes Retail/Office/Industrial/Mixed Use/Self Storage)
B3: =H24 -> as of 03/31/2026
B4: PROPERTY OVERVIEW | G4: Allocated Loan Amount/Percentage
B5: Property ID | D5: 1001-001 | E5: Paid Thru Date | F5: Debt Outside Trust (1) | G5: $ | H5: %
B6: Note A-Scheduled Loan Balance | D6: ='Debt Service'!C4 -> 10409000 | E6: =H24 -> as of 03/31/2026 | F6: X or Blank | G6: 0 | H6: 0
B7: Note B-Scheduled Loan Balance | D7: 0 | E7: MM/DD/YY | F7: X or Blank | G7: 0 | H7: 0
B8: Note C-Scheduled Loan Balance | D8: 0 | E8: MM/DD/YY | F8: X or Blank | G8: 0 | H8: 0
B9: Property Name | D9: Ares Fund XI Industrial - 55th Ave
B10: Property Type | D10: Industrial
B11: Property Address, City, State | D11: 601 S 55th Ave | F11: Phoenix | H11: AZ
B12: Current Net Rentable SF/Units/Beds/Rooms | D12: 100000 | E12: RSF | F12: Use second box to specify sqft.,units…
B13: Year Built/Year Renovated | D13: 1986 | E13: N/A
B14: Cap Ex Reserve (annually)/per Unit.etc. (2) | D14: 0.09996 | E14: /SF/Yr | F14: specify annual/per unit…
B15: Statement Ending Date | D15: Underwriting | E15: =EOMONTH(F15,-3) -> 45838 | F15: =EOMONTH(G15,-3) -> 45930 | G15: =EOMONTH(H15,-3) -> 46022 | H15: 46112
B16: Occupancy Rate (physical) | D16: 0 | G16: 1 | H16: =SUM(RR!I:I)/'Comm OSAR'!$D$12 -> 1
B17: Occupancy Date | D17: MM/DD/YY | E17: =E15 -> 45838 | F17: =F15 -> 45930 | G17: =G15 -> 46022 | H17: =H15 -> 46112
D18: (1) "X" if debt is outside of the trust, otherwise leave blank
D19: (2) Total $ amount of Capital Reserves required annually by loan documents
B21: INCOME:
B22: Number of Mos. Covered | G22: 4 | H22: 7
B23: Period Ended | D23: At Contribution | E23: 3rd Preceding | F23: 2nd Preceding | G23: Preceding Yr. | H23: T7 | I23: Lender Calc | K23: Lender Calc Adjustments
B24: Statement Ending Date | D24: Information | E24: ="as of "&TEXT(E15,"MM/DD/YYYY") -> as of 06/30/2025 | F24: ="as of "&TEXT(F15,"MM/DD/YYYY") -> as of 09/30/2025 | G24: ="as of "&TEXT(G15,"MM/DD/YYYY") -> as of 12/31/2025 | H24: ="as of "&TEXT(H15,"MM/DD/YYYY") -> as of 03/31/2026 | I24: =H24 -> as of 03/31/2026
B25: Gross Potential Rent (3) | G25: 796403.76 | H25: ='Actuals (T12)'!E5 -> 771432.31 | I25: ='Lender Calc'!E5 -> 796403.76 | K25: Rent Roll less tenants 60+ days past due, MTM, BK, non-credit tenants "gone dark", credit tenants with < 2 years of remaining lease term that have "gone dark", known vacates. Include tenants taking occupancy within 90 day (180 days for BBB- or higher tenants), include rental value of free rent period of up to 1 month free per lease year,
B26: Less: Vacancy Loss | G26: -39820.188 | H26: ='Actuals (T12)'!E9 -> 0 | I26: ='Lender Calc'!E9 -> -39820.188 | K26: =1-H16 -> 0
B27: OR
B28: Base Rent (3) | G28: 0 | H28: 0 | I28: 0
B29: Expense Reimbursement | G29: 0 | H29: 0 | I29: 0
B30: Percentage Rent | G30: 0 | H30: 0 | I30: 0
B31: Parking Income | G31: 0 | H31: 0 | I31: 0
B32: Other Income | G32: 202044.12 | H32: ='Actuals (T12)'!E12 -> 187397.71 | I32: ='Lender Calc'!E12 -> 187397.71 | K32: =TEXT($H$23,)&TEXT(B32,) -> T7 Other Income
B34: *Effective Gross Income | G34: 958627.69 | H34: =SUM(H25:H32) -> 958830.02 | I34: =SUM(I25:I32) -> 943981.28
D35: (3) Use either Gross Potential (with Vacancy Loss) or Base Rents; use negative $amt for Vacancy Loss
B37: OPERATING EXPENSES:
B38: Real Estate Taxes | G38: 124384.24 | H38: ='Actuals (T12)'!E21 -> 100287.14 | I38: ='Lender Calc'!E18 -> 103093.34 | K38: ="Greater of actual tax bill from "&TEXT('RE Taxes'!$C$2,"MM/DD/YYYY")&"-"&TEXT('RE Taxes'!$D$2,"MM/DD/YYYY")&" ($"&TEXT('RE Taxes'!C3,"0.#")&"MM) and "&$H$23&" ended "&TEXT($H$15,"MM/DD/YYYY") -> Greater of actual tax bill from 03/01/2025-03/01/2026 ($0.1MM) and T7 ended 03/31/2026
B39: Property Insurance | G39: 14802.6 | H39: ='Actuals (T12)'!E23 -> 13287.446 | I39: ='Lender Calc'!E20 -> 13287.446 | K39: ="Greater of actual insurance premium from "&TEXT(Insurance!C2,"MM/DD/YYYY")&"-"&TEXT(Insurance!D2,"MM/DD/YYYY")&" ($"&TEXT(Insurance!C3,"0.##")&"MM) and origination" -> Greater of actual insurance premium from 04/01/2026-04/01/2027 ($0.01MM) and origination
B40: Utilities | G40: 1299.92 | H40: ='Actuals (T12)'!E25 -> 1713.2057 | I40: ='Lender Calc'!E22 -> 1713.2057 | K40: =TEXT($H$23,)&TEXT(B40,) -> T7 Utilities
B41: Repairs and Maintenance | G41: 21693.04 | H41: ='Actuals (T12)'!E28 -> 27018.823 | I41: ='Lender Calc'!E25 -> 27018.823 | K41: =TEXT($H$23,)&TEXT(B41,) -> T7 Repairs and Maintenance
B42: Janitorial | G42: 0 | H42: 0 | I42: 0 | K42: =TEXT($H$23,)&TEXT(B42,) -> T7 Janitorial
B43: Management Fees | G43: 38427 | H43: ='Actuals (T12)'!E31 -> 29701.594 | I43: ='Lender Calc'!E28 -> 29701.594 | K43: Greater of actual fees and 3.0% of EGI
B44: Payroll & Benefits | G44: 0 | H44: ='Actuals (T12)'!E33 -> 0 | I44: ='Lender Calc'!E29 -> 0 | K44: =TEXT($H$23,)&TEXT(B44,) -> T7 Payroll & Benefits
B45: Advertising & Marketing | G45: 0 | H45: ='Actuals (T12)'!E34 -> 0 | I45: ='Lender Calc'!E30 -> 0 | K45: =TEXT($H$23,)&TEXT(B45,) -> T7 Advertising & Marketing
B46: Professional Fees | G46: 0 | H46: ='Actuals (T12)'!E35 -> 2192.2629 | I46: ='Lender Calc'!E31 -> 2192.2629 | K46: =TEXT($H$23,)&TEXT(B46,) -> T7 Professional Fees
B47: General and Administrative | G47: 22092.6 | H47: ='Lender Calc'!E33 -> 18579.326 | I47: ='Lender Calc'!E33 -> 18579.326 | K47: =TEXT($H$23,)&TEXT(B47,) -> T7 General and Administrative
B48: Other Expenses | G48: 1437.32 | H48: ='Actuals (T12)'!E39 -> 573.32571 | I48: ='Lender Calc'!E35 -> 573.32571 | K48: =TEXT($H$23,)&TEXT(B48,) -> T7 Other Expenses
B49: Ground Rent | G49: 0 | H49: 0 | I49: 0
B50: *Total Operating Expenses | G50: 224136.72 | H50: =SUM(H38:H49) -> 193353.12 | I50: =SUM(I38:I49) -> 196159.32
B52: Operating Expense Ratio | G52: 0.23380998 | H52: =H50/H34 -> 0.20165526 | I52: =I50/I34 -> 0.20780001
B54: *Net Operating Income | G54: 734490.97 | H54: =H34-H50 -> 765476.9 | I54: =I34-I50 -> 747821.96
B56: Leasing Commissions | G56: 0 | H56: 0 | I56: 0
B57: Tenant Improvements | G57: 0 | H57: 0 | I57: 0
B58: Capital Expenditures | G58: 9996 | H58: =I58 -> 9996 | I58: =D14*D12 -> 9996
B59: Extraordinary Capital Expenditures
B60: Total Capital Items | G60: 9996 | H60: =SUM(H56:H59) -> 9996 | I60: =SUM(I56:I58) -> 9996
B62: *Net Cash Flow | G62: 724494.97 | H62: =H54-H60 -> 755480.9 | I62: =I54-I60 -> 737825.96
B64: Debt Service - A Note | G64: 658279.95 | H64: =I64 -> 657487.38 | I64: ='Debt Service'!C12 -> 657487.38
B65: Debt Service - B Note
B66: Debt Service - C Note
B68: *Net Cash Flow after Debt Service | G68: 66215.023 | H68: =H62-H64 -> 97993.521 | I68: =I62-I64 -> 80338.581
B70: *DSCR: (NOI/Debt Service) - A Note | G70: 1.115773 | H70: =H54/H64 -> 1.1642458 | I70: =I54/I64 -> 1.1373936
B71: *DSCR: (NOI/Debt Service) - A & B Note
B72: *DSCR: (NOI/Debt Service) - A, B & C Note
B74: *DSCR: (NCF/Debt Service) - A Note | G74: 1.1005879 | H74: =H62/H64 -> 1.1490424 | I74: =I62/I64 -> 1.1221903
B75: *DSCR: (NCF/Debt Service) - A & B Note
B76: *DSCR: (NCF/Debt Service) - A, B & C Note
B78: *Debt Yield: (NCF/UPB) | G78: 0.069602745 | H78: =H62/$D$6 -> 0.072579585 | I78: =I62/$D$6 -> 0.070883462
B80: Source of Financial Data: | E80: ="Per "&IF(MONTH(E15)=12,"4Q",IF(MONTH(E15)=9,"3Q",IF(MONTH(E15)=6,"2Q","1Q")))&RIGHT(YEAR(E15),2)&" Reporting" -> Per 2Q25 Reporting | F80: ="Per "&IF(MONTH(F15)=12,"4Q",IF(MONTH(F15)=9,"3Q",IF(MONTH(F15)=6,"2Q","1Q")))&RIGHT(YEAR(F15),2)&" Reporting" -> Per 3Q25 Reporting | G80: ="Per "&IF(MONTH(G15)=12,"4Q",IF(MONTH(G15)=9,"3Q",IF(MONTH(G15)=6,"2Q","1Q")))&RIGHT(YEAR(G15),2)&" Reporting" -> Per 4Q25 Reporting | H80: ="Per "&IF(MONTH(H15)=12,"4Q",IF(MONTH(H15)=9,"3Q",IF(MONTH(H15)=6,"2Q","1Q")))&RIGHT(YEAR(H15),2)&" Reporting" -> Per 1Q26 Reporting
D81: (ie. operating statements, financial statements, tax return, other)
B82: Notes and Assumptions: Years above will roll, always showing a 3yr sequential history. Comments from the most recent NOI Adjustment Worksheet should be carried forward to Operating Statement
B83: Analysis Report. Year-over-year variances (either higher or lower) must be explained and noted for the following: >20% DSCR change, >20% EGI/Total Operating Expenses or Total Capital
B84: Items. Quarterly variance comments may be necessary if the loan is on the Watch List.
B85: Income: Comments
B88: Expense: Comments
B91: Capital Items: Comments
B94: DSCR: Comments
B97: * Used in the CREFC Comparative Financial Status Report/CREFC Property File/CREFC Loan Periodic Update File. Note that information for multiple property loans must be consolidated (if available)
B98: for reporting to the CREFC Loan Periodic Update file.

Sheet Variance Analysis
B2: Period | C2: 46022 | D2: 46112 | F2: Variance | I2: =IF(MONTH('Comm OSAR'!G15)=12,"4Q",IF(MONTH('Comm OSAR'!G15)=9,"3Q",IF(MONTH('Comm OSAR'!G15)=6,"2Q","1Q")))&" "&YEAR('Comm OSAR'!G15) -> 4Q 2025 | M2: =IF(MONTH('Comm OSAR'!H15)=12,"4Q",IF(MONTH('Comm OSAR'!H15)=9,"3Q",IF(MONTH('Comm OSAR'!H15)=6,"2Q","1Q")))&" "&YEAR('Comm OSAR'!H15) -> 1Q 2026 | Q2: QoQ ∆
B4: INCOME: | I4: Occupancy | J4: NCF | K4: DY | L4: DSCR | M4: Occupancy | N4: NCF | O4: DY | P4: DSCR | Q4: Occupancy | R4: NCF | S4: DY | T4: DSCR
B5: Gross Potential Rent | C5: =INDEX('Lender Calc'!$D$5:$F$45,MATCH('Variance Analysis'!$B5,'Lender Calc'!$C$5:$C$45,0),MATCH('Variance Analysis'!$C$2,'Lender Calc'!$D$2:$F$2,0)) -> 796403.76 | D5: =INDEX('Lender Calc'!$E$5:$E$42,MATCH('Variance Analysis'!$B5,'Lender Calc'!$C$5:$C$42,0),MATCH('Variance Analysis'!$D$2,'Lender Calc'!$E$2:$E$2,0)) -> 796403.76 | F5: =IFERROR(D5-C5,0) -> 0 | G5: =IFERROR(F5/C5,0) -> 0 | I5: ='Comm OSAR'!G16 -> 1 | J5: ='Comm OSAR'!G62 -> 724494.97 | K5: ='Comm OSAR'!G78 -> 0.069602745 | L5: ='Comm OSAR'!G74 -> 1.1005879 | M5: ='Comm OSAR'!H16 -> 1 | N5: ='Comm OSAR'!I62 -> 737825.96 | O5: ='Lender Calc'!E42/'Comm OSAR'!D6 -> 0.071843785 | P5: ='Comm OSAR'!I74 -> 1.1221903 | Q5: =M5-I5 -> 0 | R5: =N5-J5 -> 13330.986 | S5: =(O5-K5)*10000 -> 22.4104 | T5: =P5-L5 -> 0.021602365
B6: Base Rent | C6: =INDEX('Lender Calc'!$E$5:$E$42,MATCH('Variance Analysis'!$B6,'Lender Calc'!$C$5:$C$42,0),MATCH('Variance Analysis'!$C$2,'Lender Calc'!$E$2:$E$2,0)) -> #N/A | D6: =INDEX('Lender Calc'!$E$5:$E$42,MATCH('Variance Analysis'!$B6,'Lender Calc'!$C$5:$C$42,0),MATCH('Variance Analysis'!$D$2,'Lender Calc'!$E$2:$E$2,0)) -> 0 | F6: =IFERROR(D6-C6,0) -> 0 | G6: =IFERROR(F6/C6,0) -> 0
B7: Straight-line Rent | C7: =INDEX('Lender Calc'!$E$5:$E$42,MATCH('Variance Analysis'!$B7,'Lender Calc'!$C$5:$C$42,0),MATCH('Variance Analysis'!$C$2,'Lender Calc'!$E$2:$E$2,0)) -> #N/A | D7: =INDEX('Lender Calc'!$E$5:$E$42,MATCH('Variance Analysis'!$B7,'Lender Calc'!$C$5:$C$42,0),MATCH('Variance Analysis'!$D$2,'Lender Calc'!$E$2:$E$2,0)) -> 0 | F7: =IFERROR(D7-C7,0) -> 0 | G7: =IFERROR(F7/C7,0) -> 0
B8: Other Rent | C8: =INDEX('Lender Calc'!$E$5:$E$42,MATCH('Variance Analysis'!$B8,'Lender Calc'!$C$5:$C$42,0),MATCH('Variance Analysis'!$C$2,'Lender Calc'!$E$2:$E$2,0)) -> #N/A | D8: =INDEX('Lender Calc'!$E$5:$E$42,MATCH('Variance Analysis'!$B8,'Lender Calc'!$C$5:$C$42,0),MATCH('Variance Analysis'!$D$2,'Lender Calc'!$E$2:$E$2,0)) -> 0 | F8: =IFERROR(D8-C8,0) -> 0 | G8: =IFERROR(F8/C8,0) -> 0
B9: Less: Vacancy Loss | C9: =INDEX('Lender Calc'!$D$5:$F$45,MATCH('Variance Analysis'!$B9,'Lender Calc'!$C$5:$C$45,0),MATCH('Variance Analysis'!$C$2,'Lender Calc'!$D$2:$F$2,0)) -> -39820.188 | D9: =INDEX('Lender Calc'!$E$5:$E$42,MATCH('Variance Analysis'!$B9,'Lender Calc'!$C$5:$C$42,0),MATCH('Variance Analysis'!$D$2,'Lender Calc'!$E$2:$E$2,0)) -> -39820.188 | F9: =IFERROR(D9-C9,0) -> 0 | G9: =IFERROR(F9/C9,0) -> 0
B10: Delinquent Rent | C10: =INDEX('Lender Calc'!$D$5:$F$45,MATCH('Variance Analysis'!$B10,'Lender Calc'!$C$5:$C$45,0),MATCH('Variance Analysis'!$C$2,'Lender Calc'!$D$2:$F$2,0)) -> 0 | D10: =INDEX('Lender Calc'!$E$5:$E$42,MATCH('Variance Analysis'!$B10,'Lender Calc'!$C$5:$C$42,0),MATCH('Variance Analysis'!$D$2,'Lender Calc'!$E$2:$E$2,0)) -> 0 | F10: =IFERROR(D10-C10,0) -> 0 | G10: =IFERROR(F10/C10,0) -> 0
B11: Concessions/Bad Debt | C11: =INDEX('Lender Calc'!$D$5:$F$45,MATCH('Variance Analysis'!$B11,'Lender Calc'!$C$5:$C$45,0),MATCH('Variance Analysis'!$C$2,'Lender Calc'!$D$2:$F$2,0)) -> 0 | D11: =INDEX('Lender Calc'!$E$5:$E$42,MATCH('Variance Analysis'!$B11,'Lender Calc'!$C$5:$C$42,0),MATCH('Variance Analysis'!$D$2,'Lender Calc'!$E$2:$E$2,0)) -> 0 | F11: =IFERROR(D11-C11,0) -> 0 | G11: =IFERROR(F11/C11,0) -> 0
B12: Other Income | C12: =INDEX('Lender Calc'!$D$5:$F$45,MATCH('Variance Analysis'!$B12,'Lender Calc'!$C$5:$C$45,0),MATCH('Variance Analysis'!$C$2,'Lender Calc'!$D$2:$F$2,0)) -> 202044.12 | D12: =INDEX('Lender Calc'!$E$5:$E$42,MATCH('Variance Analysis'!$B12,'Lender Calc'!$C$5:$C$42,0),MATCH('Variance Analysis'!$D$2,'Lender Calc'!$E$2:$E$2,0)) -> 187397.71 | F12: =IFERROR(D12-C12,0) -> -14646.411 | G12: =IFERROR(F12/C12,0) -> -0.072491154
B13: Total Recovery Rental Revenue | C13: =INDEX('Lender Calc'!$E$5:$E$42,MATCH('Variance Analysis'!$B13,'Lender Calc'!$C$5:$C$42,0),MATCH('Variance Analysis'!$C$2,'Lender Calc'!$E$2:$E$2,0)) -> #N/A | D13: =INDEX('Lender Calc'!$E$5:$E$42,MATCH('Variance Analysis'!$B13,'Lender Calc'!$C$5:$C$42,0),MATCH('Variance Analysis'!$D$2,'Lender Calc'!$E$2:$E$2,0)) -> 187397.71 | F13: =IFERROR(D13-C13,0) -> 0 | G13: =IFERROR(F13/C13,0) -> 0
B15: *Effective Gross Income | C15: =SUM(C12,C11,C10,C9,C5) -> 958627.69 | D15: =SUM(D12,D11,D10,D9,D5) -> 943981.28 | F15: =IFERROR(D15-C15,0) -> -14646.411 | G15: =IFERROR(F15/C15,0) -> -0.015278519
B17: OPERATING EXPENSES:
B18: Real Estate Taxes | C18: =INDEX('Lender Calc'!$D$5:$F$45,MATCH('Variance Analysis'!$B18,'Lender Calc'!$C$5:$C$45,0),MATCH('Variance Analysis'!$C$2,'Lender Calc'!$D$2:$F$2,0)) -> 124384.24 | D18: =INDEX('Lender Calc'!$E$5:$E$42,MATCH('Variance Analysis'!$B18,'Lender Calc'!$C$5:$C$42,0),MATCH('Variance Analysis'!$D$2,'Lender Calc'!$E$2:$E$2,0)) -> 103093.34 | F18: =IFERROR(D18-C18,0) -> -21290.9 | G18: =IFERROR(F18/C18,0) -> -0.1711704
B19: Total Real Estate Taxes | C19: =INDEX('Lender Calc'!$D$5:$F$45,MATCH('Variance Analysis'!$B19,'Lender Calc'!$C$5:$C$45,0),MATCH('Variance Analysis'!$C$2,'Lender Calc'!$D$2:$F$2,0)) -> 124384.24 | D19: =INDEX('Lender Calc'!$E$5:$E$42,MATCH('Variance Analysis'!$B19,'Lender Calc'!$C$5:$C$42,0),MATCH('Variance Analysis'!$D$2,'Lender Calc'!$E$2:$E$2,0)) -> 103093.34 | F19: =IFERROR(D19-C19,0) -> -21290.9 | G19: =IFERROR(F19/C19,0) -> -0.1711704
B20: Property Insurance | C20: =INDEX('Lender Calc'!$D$5:$F$45,MATCH('Variance Analysis'!$B20,'Lender Calc'!$C$5:$C$45,0),MATCH('Variance Analysis'!$C$2,'Lender Calc'!$D$2:$F$2,0)) -> 14802.6 | D20: =INDEX('Lender Calc'!$E$5:$E$42,MATCH('Variance Analysis'!$B20,'Lender Calc'!$C$5:$C$42,0),MATCH('Variance Analysis'!$D$2,'Lender Calc'!$E$2:$E$2,0)) -> 13287.446 | F20: =IFERROR(D20-C20,0) -> -1515.1543 | G20: =IFERROR(F20/C20,0) -> -0.10235731
B21: Total Property Insurance | C21: =INDEX('Lender Calc'!$D$5:$F$45,MATCH('Variance Analysis'!$B21,'Lender Calc'!$C$5:$C$45,0),MATCH('Variance Analysis'!$C$2,'Lender Calc'!$D$2:$F$2,0)) -> 14802.6 | D21: =INDEX('Lender Calc'!$E$5:$E$42,MATCH('Variance Analysis'!$B21,'Lender Calc'!$C$5:$C$42,0),MATCH('Variance Analysis'!$D$2,'Lender Calc'!$E$2:$E$2,0)) -> 13287.446 | F21: =IFERROR(D21-C21,0) -> -1515.1543 | G21: =IFERROR(F21/C21,0) -> -0.10235731
B22: Utilities | C22: =INDEX('Lender Calc'!$D$5:$F$45,MATCH('Variance Analysis'!$B22,'Lender Calc'!$C$5:$C$45,0),MATCH('Variance Analysis'!$C$2,'Lender Calc'!$D$2:$F$2,0)) -> 1299.92 | D22: =INDEX('Lender Calc'!$E$5:$E$42,MATCH('Variance Analysis'!$B22,'Lender Calc'!$C$5:$C$42,0),MATCH('Variance Analysis'!$D$2,'Lender Calc'!$E$2:$E$2,0)) -> 1713.2057 | F22: =IFERROR(D22-C22,0) -> 413.28571 | G22: =IFERROR(F22/C22,0) -> 0.31793165
B23: Total Utilities | C23: =INDEX('Lender Calc'!$D$5:$F$45,MATCH('Variance Analysis'!$B23,'Lender Calc'!$C$5:$C$45,0),MATCH('Variance Analysis'!$C$2,'Lender Calc'!$D$2:$F$2,0)) -> 1299.92 | D23: =INDEX('Lender Calc'!$E$5:$E$42,MATCH('Variance Analysis'!$B23,'Lender Calc'!$C$5:$C$42,0),MATCH('Variance Analysis'!$D$2,'Lender Calc'!$E$2:$E$2,0)) -> 1713.2057 | F23: =IFERROR(D23-C23,0) -> 413.28571 | G23: =IFERROR(F23/C23,0) -> 0.31793165
B24: NR - Utilities | C24: =INDEX('Lender Calc'!$D$5:$F$45,MATCH('Variance Analysis'!$B24,'Lender Calc'!$C$5:$C$45,0),MATCH('Variance Analysis'!$C$2,'Lender Calc'!$D$2:$F$2,0)) -> 0 | D24: =INDEX('Lender Calc'!$E$5:$E$42,MATCH('Variance Analysis'!$B24,'Lender Calc'!$C$5:$C$42,0),MATCH('Variance Analysis'!$D$2,'Lender Calc'!$E$2:$E$2,0)) -> 0 | F24: =IFERROR(D24-C24,0) -> 0 | G24: =IFERROR(F24/C24,0) -> 0
B25: Repairs and Maintenance | C25: =INDEX('Lender Calc'!$D$5:$F$45,MATCH('Variance Analysis'!$B25,'Lender Calc'!$C$5:$C$45,0),MATCH('Variance Analysis'!$C$2,'Lender Calc'!$D$2:$F$2,0)) -> 21693.04 | D25: =INDEX('Lender Calc'!$E$5:$E$42,MATCH('Variance Analysis'!$B25,'Lender Calc'!$C$5:$C$42,0),MATCH('Variance Analysis'!$D$2,'Lender Calc'!$E$2:$E$2,0)) -> 27018.823 | F25: =IFERROR(D25-C25,0) -> 5325.7829 | G25: =IFERROR(F25/C25,0) -> 0.24550652
B26: Total R&M | C26: =INDEX('Lender Calc'!$D$5:$F$45,MATCH('Variance Analysis'!$B26,'Lender Calc'!$C$5:$C$45,0),MATCH('Variance Analysis'!$C$2,'Lender Calc'!$D$2:$F$2,0)) -> 21693.04 | D26: =INDEX('Lender Calc'!$E$5:$E$42,MATCH('Variance Analysis'!$B26,'Lender Calc'!$C$5:$C$42,0),MATCH('Variance Analysis'!$D$2,'Lender Calc'!$E$2:$E$2,0)) -> 27018.823 | F26: =IFERROR(D26-C26,0) -> 5325.7829 | G26: =IFERROR(F26/C26,0) -> 0.24550652
B27: NR - Other Repairs | C27: =INDEX('Lender Calc'!$D$5:$F$45,MATCH('Variance Analysis'!$B27,'Lender Calc'!$C$5:$C$45,0),MATCH('Variance Analysis'!$C$2,'Lender Calc'!$D$2:$F$2,0)) -> 0 | D27: =INDEX('Lender Calc'!$E$5:$E$42,MATCH('Variance Analysis'!$B27,'Lender Calc'!$C$5:$C$42,0),MATCH('Variance Analysis'!$D$2,'Lender Calc'!$E$2:$E$2,0)) -> 0 | F27: =IFERROR(D27-C27,0) -> 0 | G27: =IFERROR(F27/C27,0) -> 0
B28: 0.03 | C28: =INDEX('Lender Calc'!$D$5:$F$45,MATCH('Variance Analysis'!$B28,'Lender Calc'!$C$5:$C$45,0),MATCH('Variance Analysis'!$C$2,'Lender Calc'!$D$2:$F$2,0)) -> 38427 | D28: =INDEX('Lender Calc'!$E$5:$E$42,MATCH('Variance Analysis'!$B28,'Lender Calc'!$C$5:$C$42,0),MATCH('Variance Analysis'!$D$2,'Lender Calc'!$E$2:$E$2,0)) -> 29701.594 | F28: =IFERROR(D28-C28,0) -> -8725.4057 | G28: =IFERROR(F28/C28,0) -> -0.22706445
B29: Payroll & Benefits | C29: =INDEX('Lender Calc'!$D$5:$F$45,MATCH('Variance Analysis'!$B29,'Lender Calc'!$C$5:$C$45,0),MATCH('Variance Analysis'!$C$2,'Lender Calc'!$D$2:$F$2,0)) -> 0 | D29: =INDEX('Lender Calc'!$E$5:$E$42,MATCH('Variance Analysis'!$B29,'Lender Calc'!$C$5:$C$42,0),MATCH('Variance Analysis'!$D$2,'Lender Calc'!$E$2:$E$2,0)) -> 0 | F29: =IFERROR(D29-C29,0) -> 0 | G29: =IFERROR(F29/C29,0) -> 0
B30: Advertising & Marketing | C30: =INDEX('Lender Calc'!$D$5:$F$45,MATCH('Variance Analysis'!$B30,'Lender Calc'!$C$5:$C$45,0),MATCH('Variance Analysis'!$C$2,'Lender Calc'!$D$2:$F$2,0)) -> 0 | D30: =INDEX('Lender Calc'!$E$5:$E$42,MATCH('Variance Analysis'!$B30,'Lender Calc'!$C$5:$C$42,0),MATCH('Variance Analysis'!$D$2,'Lender Calc'!$E$2:$E$2,0)) -> 0 | F30: =IFERROR(D30-C30,0) -> 0 | G30: =IFERROR(F30/C30,0) -> 0
B31: Professional Fees | C31: =INDEX('Lender Calc'!$D$5:$F$45,MATCH('Variance Analysis'!$B31,'Lender Calc'!$C$5:$C$45,0),MATCH('Variance Analysis'!$C$2,'Lender Calc'!$D$2:$F$2,0)) -> 0 | D31: =INDEX('Lender Calc'!$E$5:$E$42,MATCH('Variance Analysis'!$B31,'Lender Calc'!$C$5:$C$42,0),MATCH('Variance Analysis'!$D$2,'Lender Calc'!$E$2:$E$2,0)) -> 2192.2629 | F31: =IFERROR(D31-C31,0) -> 2192.2629 | G31: =IFERROR(F31/C31,0) -> 0
B32: NR - Consulting Services | C32: =INDEX('Lender Calc'!$D$5:$F$45,MATCH('Variance Analysis'!$B32,'Lender Calc'!$C$5:$C$45,0),MATCH('Variance Analysis'!$C$2,'Lender Calc'!$D$2:$F$2,0)) -> 0 | D32: =INDEX('Lender Calc'!$E$5:$E$42,MATCH('Variance Analysis'!$B32,'Lender Calc'!$C$5:$C$42,0),MATCH('Variance Analysis'!$D$2,'Lender Calc'!$E$2:$E$2,0)) -> 2192.2629 | F32: =IFERROR(D32-C32,0) -> 2192.2629 | G32: =IFERROR(F32/C32,0) -> 0
B33: General and Administrative | C33: =INDEX('Lender Calc'!$D$5:$F$45,MATCH('Variance Analysis'!$B33,'Lender Calc'!$C$5:$C$45,0),MATCH('Variance Analysis'!$C$2,'Lender Calc'!$D$2:$F$2,0)) -> 22092.6 | D33: =INDEX('Lender Calc'!$E$5:$E$42,MATCH('Variance Analysis'!$B33,'Lender Calc'!$C$5:$C$42,0),MATCH('Variance Analysis'!$D$2,'Lender Calc'!$E$2:$E$2,0)) -> 18579.326 | F33: =IFERROR(D33-C33,0) -> -3513.2743 | G33: =IFERROR(F33/C33,0) -> -0.15902494
B34: NR - Bank Fees | C34: =INDEX('Lender Calc'!$D$5:$F$45,MATCH('Variance Analysis'!$B34,'Lender Calc'!$C$5:$C$45,0),MATCH('Variance Analysis'!$C$2,'Lender Calc'!$D$2:$F$2,0)) -> 22092.6 | D34: =INDEX('Lender Calc'!$E$5:$E$42,MATCH('Variance Analysis'!$B34,'Lender Calc'!$C$5:$C$42,0),MATCH('Variance Analysis'!$D$2,'Lender Calc'!$E$2:$E$2,0)) -> 18579.326 | F34: =IFERROR(D34-C34,0) -> -3513.2743 | G34: =IFERROR(F34/C34,0) -> -0.15902494
B35: Other Expenses | C35: =INDEX('Lender Calc'!$D$5:$F$45,MATCH('Variance Analysis'!$B35,'Lender Calc'!$C$5:$C$45,0),MATCH('Variance Analysis'!$C$2,'Lender Calc'!$D$2:$F$2,0)) -> 1437.32 | D35: =INDEX('Lender Calc'!$E$5:$E$42,MATCH('Variance Analysis'!$B35,'Lender Calc'!$C$5:$C$42,0),MATCH('Variance Analysis'!$D$2,'Lender Calc'!$E$2:$E$2,0)) -> 573.32571 | F35: =IFERROR(D35-C35,0) -> -863.99429 | G35: =IFERROR(F35/C35,0) -> -0.60111477
B36: Total Other Recovery Expenses | C36: =INDEX('Lender Calc'!$E$5:$E$42,MATCH('Variance Analysis'!$B36,'Lender Calc'!$C$5:$C$42,0),MATCH('Variance Analysis'!$C$2,'Lender Calc'!$E$2:$E$2,0)) -> #N/A | D36: =INDEX('Lender Calc'!$E$5:$E$42,MATCH('Variance Analysis'!$B36,'Lender Calc'!$C$5:$C$42,0),MATCH('Variance Analysis'!$D$2,'Lender Calc'!$E$2:$E$2,0)) -> 573.32571 | F36: =IFERROR(D36-C36,0) -> 0 | G36: =IFERROR(F36/C36,0) -> 0
B38: *Total Operating Expenses | C38: =SUM(C18,C20,C22,C25,C28,C29,C30,C31,C33,C35) -> 224136.72 | D38: =SUM(D18,D20,D22,D25,D28,D29,D30,D31,D33,D35) -> 196159.32 | F38: =IFERROR(D38-C38,0) -> -27977.397 | G38: =IFERROR(F38/C38,0) -> -0.12482291
B40: Operating Expense Ratio | C40: =C38/C15 -> 0.23380998 | D40: =D38/D15 -> 0.20780001
B42: *Net Operating Income | C42: =C15-C38 -> 734490.97 | D42: =D15-D38 -> 747821.96 | F42: =IFERROR(D42-C42,0) -> 13330.986 | G42: =IFERROR(F42/C42,0) -> 0.018149965

Sheet Historicals>>>

Sheet Actuals (T12)
B2: CODE | C2: Period | D2: 46022 | E2: ='Comm OSAR'!H15 -> 46112
C4: INCOME:
C5: Gross Potential Rent | D5: 985934.36 | E5: =SUM(E6:E8) -> 771432.31
B6: Base Rent | C6: Base Rent | D6: 964533.32 | E6: =IFERROR(INDEX('T12'!$N:$N,MATCH('Actuals (T12)'!$B6,'T12'!$A:$A,0)),0) -> 754687.32
B7: Straight-line Rent | C7: Straight-line Rent | D7: 21401.04 | E7: =IFERROR(INDEX('T12'!$N:$N,MATCH('Actuals (T12)'!$B7,'T12'!$A:$A,0)),0) -> 16744.989
B8: Other Rent | C8: Other Rent | D8: 0 | E8: =IFERROR(INDEX('T12'!$N:$N,MATCH('Actuals (T12)'!$B8,'T12'!$A:$A,0)),0) -> 0
C9: Less: Vacancy Loss | D9: 0 | E9: =IFERROR(INDEX('T12'!$N:$N,MATCH('Actuals (T12)'!$B9,'T12'!$A:$A,0)),0) -> 0
C10: Delinquent Rent | D10: 0 | E10: =IFERROR(INDEX('T12'!$N:$N,MATCH('Actuals (T12)'!$B10,'T12'!$A:$A,0)),0) -> 0
C11: Concessions/Bad Debt | D11: 0 | E11: =IFERROR(INDEX('T12'!$O:$O,MATCH('Actuals (T12)'!$B11,'T12'!$A:$A,0)),0) -> 0
C12: Other Income | D12: 202044.12 | E12: =SUM(E13) -> 187397.71
B13: TOTAL RECOVERY RENTAL REV | C13: Total Recovery Rental Revenue | D13: 202044.12 | E13: =IFERROR(INDEX('T12'!$N:$N,MATCH('Actuals (T12)'!$B13,'T12'!$A:$A,0)),0) -> 187397.71
C15: *Effective Gross Income | D15: 1187978.5 | E15: =SUM(E5,E9,E10,E11,E12) -> 958830.02
C17: Check | D17: 0 | E17: =E15-E18 -> 0
B18: TOTAL REVENUE AND INCOME | D18: 1187978.5 | E18: =IFERROR(INDEX('T12'!$N:$N,MATCH('Actuals (T12)'!$B18,'T12'!$A:$A,0)),0) -> 958830.02
C20: OPERATING EXPENSES:
C21: Real Estate Taxes | D21: 124384.24 | E21: =SUM(E22) -> 100287.14
B22: TOTAL REAL ESTATE TAXES | C22: Total Real Estate Taxes | D22: 124384.24 | E22: =IFERROR(INDEX('T12'!$N:$N,MATCH('Actuals (T12)'!$B22,'T12'!$A:$A,0)),0) -> 100287.14
C23: Property Insurance | D23: 14802.6 | E23: =SUM(E24) -> 13287.446
B24: TOTAL PROPERTY INSURANCE | C24: Total Property Insurance | D24: 14802.6 | E24: =IFERROR(INDEX('T12'!$N:$N,MATCH('Actuals (T12)'!$B24,'T12'!$A:$A,0)),0) -> 13287.446
C25: Utilities | D25: 1299.92 | E25: =SUM(E26:E27) -> 1713.2057
B26: TOTAL UTILITIES | C26: Total Utilities | D26: 1299.92 | E26: =IFERROR(INDEX('T12'!$N:$N,MATCH('Actuals (T12)'!$B26,'T12'!$A:$A,0)),0) -> 1713.2057
B27: NR - Utilities | C27: NR - Utilities | D27: 0 | E27: =IFERROR(INDEX('T12'!$N:$N,MATCH('Actuals (T12)'!$B27,'T12'!$A:$A,0)),0) -> 0
C28: Repairs and Maintenance | D28: 21693.04 | E28: =SUM(E29:E30) -> 27018.823
B29: TOTAL REPAIR & MAINTENANC | C29: Total R&M | D29: 21693.04 | E29: =IFERROR(INDEX('T12'!$N:$N,MATCH('Actuals (T12)'!$B29,'T12'!$A:$A,0)),0) -> 27018.823
B30: NR - Other Repairs | C30: NR - Other Repairs | D30: 0 | E30: =IFERROR(INDEX('T12'!$N:$N,MATCH('Actuals (T12)'!$B30,'T12'!$A:$A,0)),0) -> 0
C31: 0.03 | D31: 38427 | E31: =SUM(E32) -> 29701.594
B32: TOTAL PROPERTY MANAGEMENT FEES | C32: Total Property Management Fees | D32: 38427 | E32: =IFERROR(INDEX('T12'!$N:$N,MATCH('Actuals (T12)'!$B32,'T12'!$A:$A,0)),0) -> 29701.594
C33: Payroll & Benefits | D33: 0 | E33: =IFERROR(INDEX('T12'!$N:$N,MATCH('Actuals (T12)'!$B33,'T12'!$A:$A,0)),0) -> 0
C34: Advertising & Marketing | D34: 0 | E34: =IFERROR(INDEX('T12'!$N:$N,MATCH('Actuals (T12)'!$B34,'T12'!$A:$A,0)),0) -> 0
C35: Professional Fees | D35: 0 | E35: =SUM(E36) -> 2192.2629
B36: NR - Consulting Services | C36: NR - Consulting Services | D36: 0 | E36: =IFERROR(INDEX('T12'!$N:$N,MATCH('Actuals (T12)'!$B36,'T12'!$A:$A,0)),0) -> 2192.2629
C37: General and Administrative | D37: 22092.6 | E37: =SUM(E38) -> 18579.326
B38: NR - Bank Fees | C38: NR - Bank Fees | D38: 22092.6 | E38: =IFERROR(INDEX('T12'!$N:$N,MATCH('Actuals (T12)'!$B38,'T12'!$A:$A,0)),0) -> 18579.326
C39: Other Expenses | D39: 1437.32 | E39: =SUM(E40) -> 573.32571
B40: TOTAL OTHER RECOV | C40: Total Other Recovery Expenses | D40: 1437.32 | E40: =IFERROR(INDEX('T12'!$N:$N,MATCH('Actuals (T12)'!$B40,'T12'!$A:$A,0)),0) -> 573.32571
C42: *Total Operating Expenses | D42: 224136.72 | E42: =SUM(E21,E23,E25,E28,E31,E33,E34,E35,E37,E39) -> 193353.12
C44: Check | D44: 0 | E44: =E42-SUM(E45:E46) -> 0
B45: TOTAL RECOVERABLE EXPENSES | D45: 202044.12 | E45: =IFERROR(INDEX('T12'!$N:$N,MATCH('Actuals (T12)'!$B45,'T12'!$A:$A,0)),0) -> 172581.53
B46: TOTAL NON-RECOVERABLE OPER EXP | D46: 22092.6 | E46: =IFERROR(INDEX('T12'!$N:$N,MATCH('Actuals (T12)'!$B46,'T12'!$A:$A,0)),0) -> 20771.589
C48: Operating Expense Ratio | D48: 0.18867069 | E48: =E42/E15 -> 0.20165526
C50: *Net Operating Income | D50: 963841.76 | E50: =E15-E42 -> 765476.9

Sheet Lender Calc
B2: CODE | C2: Period | D2: 46022 | E2: ='Comm OSAR'!H15 -> 46112
C4: INCOME:
C5: Gross Potential Rent | D5: 796403.76 | E5: =SUM(RR!J8) -> 796403.76
B6: Base Rent | C6: Base Rent | D6: 0 | E6: 0
B7: Straight-line Rent | C7: Straight-line Rent | D7: 0 | E7: 0
B8: Other Rent | C8: Other Rent | D8: 0 | E8: =IFERROR(INDEX('T12'!$N:$N,MATCH('Lender Calc'!$B8,'T12'!$A:$A,0)),0) -> 0
C9: Less: Vacancy Loss | D9: -39820.188 | E9: =IF('Comm OSAR'!H16<95%,'Actuals (T12)'!E9,-'Lender Calc'!E5*5%) -> -39820.188
C10: Delinquent Rent | D10: 0 | E10: =IFERROR(INDEX('T12'!$N:$N,MATCH('Lender Calc'!$B10,'T12'!$A:$A,0)),0) -> 0
C11: Concessions/Bad Debt | D11: 0 | E11: =IFERROR(INDEX('T12'!$O:$O,MATCH('Lender Calc'!$B11,'T12'!$A:$A,0)),0) -> 0
C12: Other Income | D12: 202044.12 | E12: =SUM(E13) -> 187397.71
B13: TOTAL RECOVERY RENTAL REV | C13: Total Recovery Rental Revenue | D13: 202044.12 | E13: =IFERROR(INDEX('T12'!$N:$N,MATCH('Lender Calc'!$B13,'T12'!$A:$A,0)),0) -> 187397.71
C15: *Effective Gross Income | D15: 958627.69 | E15: =SUM(E5,E9,E10,E11,E12) -> 943981.28
C17: OPERATING EXPENSES:
C18: Real Estate Taxes | D18: 124384.24 | E18: =SUM(E19) -> 103093.34
B19: TOTAL REAL ESTATE TAXES | C19: Total Real Estate Taxes | D19: 124384.24 | E19: =MAX('Actuals (T12)'!E22,'RE Taxes'!T5) -> 103093.34
C20: Property Insurance | D20: 14802.6 | E20: =SUM(E21) -> 13287.446
B21: TOTAL PROPERTY INSURANCE | C21: Total Property Insurance | D21: 14802.6 | E21: =MAX('Actuals (T12)'!E24,Insurance!C3/Insurance!C4) -> 13287.446
C22: Utilities | D22: 1299.92 | E22: =SUM(E23:E24) -> 1713.2057
B23: TOTAL UTILITIES | C23: Total Utilities | D23: 1299.92 | E23: =IFERROR(INDEX('T12'!$N:$N,MATCH('Lender Calc'!$B23,'T12'!$A:$A,0)),0) -> 1713.2057
B24: NR - Utilities | C24: NR - Utilities | D24: 0 | E24: =IFERROR(INDEX('T12'!$N:$N,MATCH('Lender Calc'!$B24,'T12'!$A:$A,0)),0) -> 0
C25: Repairs and Maintenance | D25: 21693.04 | E25: =SUM(E26:E27) -> 27018.823
B26: TOTAL REPAIR & MAINTENANC | C26: Total R&M | D26: 21693.04 | E26: =IFERROR(INDEX('T12'!$N:$N,MATCH('Lender Calc'!$B26,'T12'!$A:$A,0)),0) -> 27018.823
B27: NR - Other Repairs | C27: NR - Other Repairs | D27: 0 | E27: =IFERROR(INDEX('T12'!$N:$N,MATCH('Lender Calc'!$B27,'T12'!$A:$A,0)),0) -> 0
C28: 0.03 | D28: 38427 | E28: =MAX($C$28*E15,'Actuals (T12)'!E31) -> 29701.594
C29: Payroll & Benefits | D29: 0 | E29: =IFERROR(INDEX('T12'!$N:$N,MATCH('Lender Calc'!$B29,'T12'!$A:$A,0)),0) -> 0
C30: Advertising & Marketing | D30: 0 | E30: =IFERROR(INDEX('T12'!$N:$N,MATCH('Lender Calc'!$B30,'T12'!$A:$A,0)),0) -> 0
C31: Professional Fees | D31: 0 | E31: =SUM(E32) -> 2192.2629
B32: NR - Consulting Services | C32: NR - Consulting Services | D32: 0 | E32: =IFERROR(INDEX('T12'!$N:$N,MATCH('Lender Calc'!$B32,'T12'!$A:$A,0)),0) -> 2192.2629
C33: General and Administrative | D33: 22092.6 | E33: =SUM(E34) -> 18579.326
B34: NR - Bank Fees | C34: NR - Bank Fees | D34: 22092.6 | E34: =IFERROR(INDEX('T12'!$N:$N,MATCH('Lender Calc'!$B34,'T12'!$A:$A,0)),0) -> 18579.326
C35: Other Expenses | D35: 1437.32 | E35: =SUM(E36) -> 573.32571
B36: TOTAL OTHER RECOV | C36: Total Other Recovery Expenses | D36: 1437.32 | E36: =IFERROR(INDEX('T12'!$N:$N,MATCH('Lender Calc'!$B36,'T12'!$A:$A,0)),0) -> 573.32571
C38: *Total Operating Expenses | D38: 224136.72 | E38: =SUM(E18,E20,E22,E25,E28,E29,E30,E31,E33,E35) -> 196159.32
C40: Operating Expense Ratio | D40: 0.23380998 | E40: =E38/E15 -> 0.20780001
C42: *Net Operating Income | D42: 734490.97 | E42: =E15-E38 -> 747821.96

Sheet Support>>>

Sheet T12
A1: 601 S. 55th Avenue (v1103001)
A2: Statement (12 months)
A3: Period = Jan 2025-Dec 2025 | M3: Months Available | N3: ='Comm OSAR'!H22 -> 7
A4: Book = Accrual,Depreciation,Straight-Line Rent,Elimination ; Tree = ysi_is
B5: Apr 2025 | C5: May 2025 | D5: Jun 2025 | E5: Jul 2025 | F5: Aug 2025 | G5: Sep 2025 | H5: Oct 2025 | I5: Nov 2025 | J5: Dec 2025 | K5: Jan 2026 | L5: Feb 2026 | M5: Mar 2026 | N5: T12 | O5: T6 | P5: T3
A7: REVENUE & INCOME
A9: RENTAL REVENUE
A10: Base Rent | B10: 0 | C10: 0 | D10: 0 | E10: 0 | F10: 0 | G10: 42032.39 | H10: 66366.98 | I10: 66366.98 | J10: 66366.98 | K10: 66366.98 | L10: 66366.98 | M10: 66366.98 | N10: =IF(SUM(B10:M10)=0,"",SUM(B10:M10))/$N$3*12 -> 754687.32 | O10: =IF(N10="","",SUM(H10:M10)*2) -> 796403.76 | P10: =IF(O10="","",SUM(K10:M10)*4) -> 796403.76
A11: Straight-line Rent | B11: 0 | C11: 0 | D11: 0 | E11: 0 | F11: 0 | G11: 932.61 | H11: 1472.55 | I11: 1472.55 | J11: 1472.55 | K11: 1472.55 | L11: 1472.55 | M11: 1472.55 | N11: =IF(SUM(B11:M11)=0,"",SUM(B11:M11))/$N$3*12 -> 16744.989 | O11: =IF(N11="","",SUM(H11:M11)*2) -> 17670.6 | P11: =IF(O11="","",SUM(K11:M11)*4) -> 17670.6
A12: TOTAL RENTAL REVENUE | B12: 0 | C12: 0 | D12: 0 | E12: 0 | F12: 0 | G12: 42965 | H12: 67839.53 | I12: 67839.53 | J12: 67839.53 | K12: 67839.53 | L12: 67839.53 | M12: 67839.53 | N12: =IF(SUM(B12:M12)=0,"",SUM(B12:M12))/$N$3*12 -> 771432.31 | O12: =IF(N12="","",SUM(H12:M12)*2) -> 814074.36 | P12: =IF(O12="","",SUM(K12:M12)*4) -> 814074.36
N13: =IF(SUM(B13:M13)=0,"",SUM(B13:M13))/$N$3*12 -> #VALUE! | O13: =IF(N13="","",SUM(H13:M13)*2) -> #VALUE! | P13: =IF(O13="","",SUM(K13:M13)*4) -> #VALUE!
A14: RECOVERY RENTAL REVENUE | N14: =IF(SUM(B14:M14)=0,"",SUM(B14:M14))/$N$3*12 -> #VALUE! | O14: =IF(N14="","",SUM(H14:M14)*2) -> #VALUE! | P14: =IF(O14="","",SUM(K14:M14)*4) -> #VALUE!
N15: =IF(SUM(B15:M15)=0,"",SUM(B15:M15))/$N$3*12 -> #VALUE! | O15: =IF(N15="","",SUM(H15:M15)*2) -> #VALUE! | P15: =IF(O15="","",SUM(K15:M15)*4) -> #VALUE!
A16: ESTIMATED RECOV RENT REV | N16: =IF(SUM(B16:M16)=0,"",SUM(B16:M16))/$N$3*12 -> #VALUE! | O16: =IF(N16="","",SUM(H16:M16)*2) -> #VALUE! | P16: =IF(O16="","",SUM(K16:M16)*4) -> #VALUE!
A17: Recov Estimate - Oper Exp | B17: 0 | C17: 0 | D17: 0 | E17: 0 | F17: 0 | G17: 4820.96 | H17: 7612.04 | I17: 7612.04 | J17: 7612.04 | K17: 9191.9 | L17: 9191.9 | M17: 9191.9 | N17: =IF(SUM(B17:M17)=0,"",SUM(B17:M17))/$N$3*12 -> 94684.766 | O17: =IF(N17="","",SUM(H17:M17)*2) -> 100823.64 | P17: =IF(O17="","",SUM(K17:M17)*4) -> 110302.8
A18: Recov Estimate - RE Tax | B18: 0 | C18: 0 | D18: 0 | E18: 0 | F18: 0 | G18: 5687.68 | H18: 8980.54 | I18: 8980.54 | J18: 8980.54 | K18: 9155.75 | L18: 9155.75 | M18: 9155.75 | N18: =IF(SUM(B18:M18)=0,"",SUM(B18:M18))/$N$3*12 -> 103022.66 | O18: =IF(N18="","",SUM(H18:M18)*2) -> 108817.74 | P18: =IF(O18="","",SUM(K18:M18)*4) -> 109869
A19: Recov Estimate - Insuranc | B19: 0 | C19: 0 | D19: 0 | E19: 0 | F19: 0 | G19: 962.81 | H19: 1520.23 | I19: 1520.23 | J19: 1520.23 | K19: 1054.03 | L19: 1054.03 | M19: 1054.03 | N19: =IF(SUM(B19:M19)=0,"",SUM(B19:M19))/$N$3*12 -> 14889.583 | O19: =IF(N19="","",SUM(H19:M19)*2) -> 15445.56 | P19: =IF(O19="","",SUM(K19:M19)*4) -> 12648.36
A20: CAP Recov - Amortized | B20: 0 | C20: 0 | D20: 0 | E20: 0 | F20: 0 | G20: 2315.2 | H20: 3655.58 | I20: 3655.58 | J20: 3655.58 | K20: 0 | L20: 0 | M20: 0 | N20: =IF(SUM(B20:M20)=0,"",SUM(B20:M20))/$N$3*12 -> 22769.04 | O20: =IF(N20="","",SUM(H20:M20)*2) -> 21933.48 | P20: =IF(O20="","",SUM(K20:M20)*4) -> 0
A21: TOTAL EST. RECOV RENT REV | B21: 0 | C21: 0 | D21: 0 | E21: 0 | F21: 0 | G21: 13786.65 | H21: 21768.39 | I21: 21768.39 | J21: 21768.39 | K21: 19401.68 | L21: 19401.68 | M21: 19401.68 | N21: =IF(SUM(B21:M21)=0,"",SUM(B21:M21))/$N$3*12 -> 235366.05 | O21: =IF(N21="","",SUM(H21:M21)*2) -> 247020.42 | P21: =IF(O21="","",SUM(K21:M21)*4) -> 232820.16
N22: =IF(SUM(B22:M22)=0,"",SUM(B22:M22))/$N$3*12 -> #VALUE! | O22: =IF(N22="","",SUM(H22:M22)*2) -> #VALUE! | P22: =IF(O22="","",SUM(K22:M22)*4) -> #VALUE!
A23: RECONCIL RECOV RENT REV | N23: =IF(SUM(B23:M23)=0,"",SUM(B23:M23))/$N$3*12 -> #VALUE! | O23: =IF(N23="","",SUM(H23:M23)*2) -> #VALUE! | P23: =IF(O23="","",SUM(K23:M23)*4) -> #VALUE!
A24: CY Recon - Oper Exp | B24: 0 | C24: 0 | D24: 0 | E24: 0 | F24: 0 | G24: -4543 | H24: -7612.04 | I24: -5788.23 | J24: 6000.51 | K24: -4037.29 | L24: -6760.09 | M24: 1854.47 | N24: =IF(SUM(B24:M24)=0,"",SUM(B24:M24))/$N$3*12 -> -35804.006 | O24: =IF(N24="","",SUM(H24:M24)*2) -> -32685.34 | P24: =IF(O24="","",SUM(K24:M24)*4) -> -35771.64
A25: CY Recon - RE Tax | B25: 0 | C25: 0 | D25: 0 | E25: 0 | F25: 0 | G25: -364.93 | H25: -389.44 | I25: -389.43 | J25: -389.44 | K25: -20.82 | L25: -20.83 | M25: -20.83 | N25: =IF(SUM(B25:M25)=0,"",SUM(B25:M25))/$N$3*12 -> -2735.52 | O25: =IF(N25="","",SUM(H25:M25)*2) -> -2461.58 | P25: =IF(O25="","",SUM(K25:M25)*4) -> -249.92
A26: CY Recon - Insurance | B26: 0 | C26: 0 | D26: 0 | E26: 0 | F26: 0 | G26: -402.2 | H26: -1520.23 | I26: 269.69 | J26: -170.11 | K26: 296.09 | L26: 296.09 | M26: 296.09 | N26: =IF(SUM(B26:M26)=0,"",SUM(B26:M26))/$N$3*12 -> -1602.1371 | O26: =IF(N26="","",SUM(H26:M26)*2) -> -1064.76 | P26: =IF(O26="","",SUM(K26:M26)*4) -> 3553.08
A27: CY Recon - Amortized Capital | B27: 0 | C27: 0 | D27: 0 | E27: 0 | F27: 0 | G27: -2315.2 | H27: -3655.58 | I27: -3655.58 | J27: -3655.58 | K27: 0 | L27: 5810.92 | M27: 2905.46 | N27: =IF(SUM(B27:M27)=0,"",SUM(B27:M27))/$N$3*12 -> -7826.6743 | O27: =IF(N27="","",SUM(H27:M27)*2) -> -4500.72 | P27: =IF(O27="","",SUM(K27:M27)*4) -> 34865.52
A28: TOT CY RECON RECOV REV | B28: 0 | C28: 0 | D28: 0 | E28: 0 | F28: 0 | G28: -7625.33 | H28: -13177.29 | I28: -9563.55 | J28: 1785.38 | K28: -3762.02 | L28: -673.91 | M28: 5035.19 | N28: =IF(SUM(B28:M28)=0,"",SUM(B28:M28))/$N$3*12 -> -47968.337 | O28: =IF(N28="","",SUM(H28:M28)*2) -> -40712.4 | P28: =IF(O28="","",SUM(K28:M28)*4) -> 2397.04
A29: TOTAL RECOVERY RENTAL REV | B29: 0 | C29: 0 | D29: 0 | E29: 0 | F29: 0 | G29: 6161.32 | H29: 8591.1 | I29: 12204.84 | J29: 23553.77 | K29: 15639.66 | L29: 18727.77 | M29: 24436.87 | N29: =IF(SUM(B29:M29)=0,"",SUM(B29:M29))/$N$3*12 -> 187397.71 | O29: =IF(N29="","",SUM(H29:M29)*2) -> 206308.02 | P29: =IF(O29="","",SUM(K29:M29)*4) -> 235217.2
A30: TOTAL REVENUE AND INCOME | B30: 0 | C30: 0 | D30: 0 | E30: 0 | F30: 0 | G30: 49126.32 | H30: 76430.63 | I30: 80044.37 | J30: 91393.3 | K30: 83479.19 | L30: 86567.3 | M30: 92276.4 | N30: =IF(SUM(B30:M30)=0,"",SUM(B30:M30))/$N$3*12 -> 958830.02 | O30: =IF(N30="","",SUM(H30:M30)*2) -> 1020382.4 | P30: =IF(O30="","",SUM(K30:M30)*4) -> 1049291.6
N31: =IF(SUM(B31:M31)=0,"",SUM(B31:M31))/$N$3*12 -> #VALUE! | O31: =IF(N31="","",SUM(H31:M31)*2) -> #VALUE! | P31: =IF(O31="","",SUM(K31:M31)*4) -> #VALUE!
A32: RECOVERABLE EXPENSES | N32: =IF(SUM(B32:M32)=0,"",SUM(B32:M32))/$N$3*12 -> #VALUE! | O32: =IF(N32="","",SUM(H32:M32)*2) -> #VALUE! | P32: =IF(O32="","",SUM(K32:M32)*4) -> #VALUE!
N33: =IF(SUM(B33:M33)=0,"",SUM(B33:M33))/$N$3*12 -> #VALUE! | O33: =IF(N33="","",SUM(H33:M33)*2) -> #VALUE! | P33: =IF(O33="","",SUM(K33:M33)*4) -> #VALUE!
A34: REAL ESTATE TAXES | N34: =IF(SUM(B34:M34)=0,"",SUM(B34:M34))/$N$3*12 -> #VALUE! | O34: =IF(N34="","",SUM(H34:M34)*2) -> #VALUE! | P34: =IF(O34="","",SUM(K34:M34)*4) -> #VALUE!
A35: Property Taxes - Building | B35: 0 | C35: 0 | D35: 0 | E35: 0 | F35: 0 | G35: 5322.75 | H35: 8591.1 | I35: 8591.11 | J35: 8591.1 | K35: 9134.93 | L35: 9134.92 | M35: 9134.92 | N35: =IF(SUM(B35:M35)=0,"",SUM(B35:M35))/$N$3*12 -> 100287.14 | O35: =IF(N35="","",SUM(H35:M35)*2) -> 106356.16 | P35: =IF(O35="","",SUM(K35:M35)*4) -> 109619.08
A36: TOTAL REAL ESTATE TAXES | B36: 0 | C36: 0 | D36: 0 | E36: 0 | F36: 0 | G36: 5322.75 | H36: 8591.1 | I36: 8591.11 | J36: 8591.1 | K36: 9134.93 | L36: 9134.92 | M36: 9134.92 | N36: =IF(SUM(B36:M36)=0,"",SUM(B36:M36))/$N$3*12 -> 100287.14 | O36: =IF(N36="","",SUM(H36:M36)*2) -> 106356.16 | P36: =IF(O36="","",SUM(K36:M36)*4) -> 109619.08
N37: =IF(SUM(B37:M37)=0,"",SUM(B37:M37))/$N$3*12 -> #VALUE! | O37: =IF(N37="","",SUM(H37:M37)*2) -> #VALUE! | P37: =IF(O37="","",SUM(K37:M37)*4) -> #VALUE!
A38: PROPERTY INSURANCE | N38: =IF(SUM(B38:M38)=0,"",SUM(B38:M38))/$N$3*12 -> #VALUE! | O38: =IF(N38="","",SUM(H38:M38)*2) -> #VALUE! | P38: =IF(O38="","",SUM(K38:M38)*4) -> #VALUE!
A39: Building Insurance | B39: 0 | C39: 0 | D39: 0 | E39: 0 | F39: 0 | G39: 504.08 | H39: 0 | I39: 1609.52 | J39: 1225.8 | K39: 1225.8 | L39: 1225.8 | M39: 1225.8 | N39: =IF(SUM(B39:M39)=0,"",SUM(B39:M39))/$N$3*12 -> 12028.8 | O39: =IF(N39="","",SUM(H39:M39)*2) -> 13025.44 | P39: =IF(O39="","",SUM(K39:M39)*4) -> 14709.6
A40: Liability Insurance | B40: 0 | C40: 0 | D40: 0 | E40: 0 | F40: 0 | G40: 45.52 | H40: 0 | I40: 145.34 | J40: 100.14 | K40: 100.14 | L40: 100.14 | M40: 100.14 | N40: =IF(SUM(B40:M40)=0,"",SUM(B40:M40))/$N$3*12 -> 1013.8629 | O40: =IF(N40="","",SUM(H40:M40)*2) -> 1091.8 | P40: =IF(O40="","",SUM(K40:M40)*4) -> 1201.68
A41: Insurance - Other | B41: 0 | C41: 0 | D41: 0 | E41: 0 | F41: 0 | G41: 11.01 | H41: 0 | I41: 35.06 | J41: 24.18 | K41: 24.18 | L41: 24.18 | M41: 24.18 | N41: =IF(SUM(B41:M41)=0,"",SUM(B41:M41))/$N$3*12 -> 244.78286 | O41: =IF(N41="","",SUM(H41:M41)*2) -> 263.56 | P41: =IF(O41="","",SUM(K41:M41)*4) -> 290.16
A42: TOTAL PROPERTY INSURANCE | B42: 0 | C42: 0 | D42: 0 | E42: 0 | F42: 0 | G42: 560.61 | H42: 0 | I42: 1789.92 | J42: 1350.12 | K42: 1350.12 | L42: 1350.12 | M42: 1350.12 | N42: =IF(SUM(B42:M42)=0,"",SUM(B42:M42))/$N$3*12 -> 13287.446 | O42: =IF(N42="","",SUM(H42:M42)*2) -> 14380.8 | P42: =IF(O42="","",SUM(K42:M42)*4) -> 16201.44
N43: =IF(SUM(B43:M43)=0,"",SUM(B43:M43))/$N$3*12 -> #VALUE! | O43: =IF(N43="","",SUM(H43:M43)*2) -> #VALUE! | P43: =IF(O43="","",SUM(K43:M43)*4) -> #VALUE!
A44: UTILITIES | N44: =IF(SUM(B44:M44)=0,"",SUM(B44:M44))/$N$3*12 -> #VALUE! | O44: =IF(N44="","",SUM(H44:M44)*2) -> #VALUE! | P44: =IF(O44="","",SUM(K44:M44)*4) -> #VALUE!
A45: Utilities - Water & Sewer | B45: 0 | C45: 0 | D45: 0 | E45: 0 | F45: 0 | G45: 0 | H45: 0 | I45: 180.81 | J45: 144.17 | K45: 271.07 | L45: 198.68 | M45: 204.64 | N45: =IF(SUM(B45:M45)=0,"",SUM(B45:M45))/$N$3*12 -> 1713.2057 | O45: =IF(N45="","",SUM(H45:M45)*2) -> 1998.74 | P45: =IF(O45="","",SUM(K45:M45)*4) -> 2697.56
A46: TOTAL UTILITIES | B46: 0 | C46: 0 | D46: 0 | E46: 0 | F46: 0 | G46: 0 | H46: 0 | I46: 180.81 | J46: 144.17 | K46: 271.07 | L46: 198.68 | M46: 204.64 | N46: =IF(SUM(B46:M46)=0,"",SUM(B46:M46))/$N$3*12 -> 1713.2057 | O46: =IF(N46="","",SUM(H46:M46)*2) -> 1998.74 | P46: =IF(O46="","",SUM(K46:M46)*4) -> 2697.56
N47: =IF(SUM(B47:M47)=0,"",SUM(B47:M47))/$N$3*12 -> #VALUE! | O47: =IF(N47="","",SUM(H47:M47)*2) -> #VALUE! | P47: =IF(O47="","",SUM(K47:M47)*4) -> #VALUE!
A48: REPAIR & MAINTENANCE | N48: =IF(SUM(B48:M48)=0,"",SUM(B48:M48))/$N$3*12 -> #VALUE! | O48: =IF(N48="","",SUM(H48:M48)*2) -> #VALUE! | P48: =IF(O48="","",SUM(K48:M48)*4) -> #VALUE!
A49: Lot Sweeping | B49: 0 | C49: 0 | D49: 0 | E49: 0 | F49: 0 | G49: 53.83 | H49: 0 | I49: 70 | J49: 170 | K49: 0 | L49: 180 | M49: 90 | N49: =IF(SUM(B49:M49)=0,"",SUM(B49:M49))/$N$3*12 -> 966.56571 | O49: =IF(N49="","",SUM(H49:M49)*2) -> 1020 | P49: =IF(O49="","",SUM(K49:M49)*4) -> 1080
A50: Landscaping - Contract | B50: 0 | C50: 0 | D50: 0 | E50: 0 | F50: 0 | G50: 0 | H50: 0 | I50: 1418 | J50: 709 | K50: 820 | L50: 982.33 | M50: 657.67 | N50: =IF(SUM(B50:M50)=0,"",SUM(B50:M50))/$N$3*12 -> 7863.4286 | O50: =IF(N50="","",SUM(H50:M50)*2) -> 9174 | P50: =IF(O50="","",SUM(K50:M50)*4) -> 9840
A51: Landscaping - Other | B51: 0 | C51: 0 | D51: 0 | E51: 0 | F51: 0 | G51: 0 | H51: 0 | I51: 0 | J51: 1650 | K51: -1650 | L51: 0 | M51: 2850 | N51: =IF(SUM(B51:M51)=0,"",SUM(B51:M51))/$N$3*12 -> 4885.7143 | O51: =IF(N51="","",SUM(H51:M51)*2) -> 5700 | P51: =IF(O51="","",SUM(K51:M51)*4) -> 4800
A52: Electrical & Lighting | B52: 0 | C52: 0 | D52: 0 | E52: 0 | F52: 0 | G52: 47.5 | H52: 0 | I52: 75 | J52: 150 | K52: 0 | L52: 75 | M52: 0 | N52: =IF(SUM(B52:M52)=0,"",SUM(B52:M52))/$N$3*12 -> 595.71429 | O52: =IF(N52="","",SUM(H52:M52)*2) -> 600 | P52: =IF(O52="","",SUM(K52:M52)*4) -> 300
A53: Maintenance-Parking Lots | B53: 0 | C53: 0 | D53: 0 | E53: 0 | F53: 0 | G53: 0 | H53: 0 | I53: 0 | J53: 0 | K53: 2400 | L53: -2400 | M53: 1200 | N53: =IF(SUM(B53:M53)=0,"",SUM(B53:M53))/$N$3*12 -> 2057.1429 | O53: =IF(N53="","",SUM(H53:M53)*2) -> 2400 | P53: =IF(O53="","",SUM(K53:M53)*4) -> 4800
A54: Maintenance-Pest Control | B54: 0 | C54: 0 | D54: 0 | E54: 0 | F54: 0 | G54: 0 | H54: 0 | I54: 80 | J54: 160 | K54: 0 | L54: 168 | M54: 0 | N54: =IF(SUM(B54:M54)=0,"",SUM(B54:M54))/$N$3*12 -> 699.42857 | O54: =IF(N54="","",SUM(H54:M54)*2) -> 816 | P54: =IF(O54="","",SUM(K54:M54)*4) -> 672
A55: Maintenance-Misc | B55: 0 | C55: 0 | D55: 0 | E55: 0 | F55: 0 | G55: 0 | H55: 0 | I55: 0 | J55: 168.3 | K55: 1001.72 | L55: 102 | M55: 0 | N55: =IF(SUM(B55:M55)=0,"",SUM(B55:M55))/$N$3*12 -> 2180.6057 | O55: =IF(N55="","",SUM(H55:M55)*2) -> 2544.04 | P55: =IF(O55="","",SUM(K55:M55)*4) -> 4414.88
A56: Maintenance-Roof | B56: 0 | C56: 0 | D56: 0 | E56: 0 | F56: 0 | G56: 0 | H56: 0 | I56: 0 | J56: 0 | K56: 0 | L56: 0 | M56: 1500 | N56: =IF(SUM(B56:M56)=0,"",SUM(B56:M56))/$N$3*12 -> 2571.4286 | O56: =IF(N56="","",SUM(H56:M56)*2) -> 3000 | P56: =IF(O56="","",SUM(K56:M56)*4) -> 6000
A57: Maintenance-Fire Protect | B57: 0 | C57: 0 | D57: 0 | E57: 0 | F57: 0 | G57: 176.63 | H57: 0 | I57: 0 | J57: 495 | K57: 0 | L57: 390 | M57: 1971 | N57: =IF(SUM(B57:M57)=0,"",SUM(B57:M57))/$N$3*12 -> 5198.7943 | O57: =IF(N57="","",SUM(H57:M57)*2) -> 5712 | P57: =IF(O57="","",SUM(K57:M57)*4) -> 9444
A58: TOTAL REPAIR & MAINTENANC | B58: 0 | C58: 0 | D58: 0 | E58: 0 | F58: 0 | G58: 277.96 | H58: 0 | I58: 1643 | J58: 3502.3 | K58: 2571.72 | L58: -502.67 | M58: 8268.67 | N58: =IF(SUM(B58:M58)=0,"",SUM(B58:M58))/$N$3*12 -> 27018.823 | O58: =IF(N58="","",SUM(H58:M58)*2) -> 30966.04 | P58: =IF(O58="","",SUM(K58:M58)*4) -> 41350.88
N59: =IF(SUM(B59:M59)=0,"",SUM(B59:M59))/$N$3*12 -> #VALUE! | O59: =IF(N59="","",SUM(H59:M59)*2) -> #VALUE! | P59: =IF(O59="","",SUM(K59:M59)*4) -> #VALUE!
A60: OTHER RECOVERABLE | N60: =IF(SUM(B60:M60)=0,"",SUM(B60:M60))/$N$3*12 -> #VALUE! | O60: =IF(N60="","",SUM(H60:M60)*2) -> #VALUE! | P60: =IF(O60="","",SUM(K60:M60)*4) -> #VALUE!
A61: Recov - Accounting Fees | B61: 0 | C61: 0 | D61: 0 | E61: 0 | F61: 0 | G61: 0 | H61: 0 | I61: 0 | J61: 359.33 | K61: -98.5 | L61: 0 | M61: 73.61 | N61: =IF(SUM(B61:M61)=0,"",SUM(B61:M61))/$N$3*12 -> 573.32571 | O61: =IF(N61="","",SUM(H61:M61)*2) -> 668.88 | P61: =IF(O61="","",SUM(K61:M61)*4) -> -99.56
A62: TOTAL OTHER RECOV | B62: 0 | C62: 0 | D62: 0 | E62: 0 | F62: 0 | G62: 0 | H62: 0 | I62: 0 | J62: 359.33 | K62: -98.5 | L62: 0 | M62: 73.61 | N62: =IF(SUM(B62:M62)=0,"",SUM(B62:M62))/$N$3*12 -> 573.32571 | O62: =IF(N62="","",SUM(H62:M62)*2) -> 668.88 | P62: =IF(O62="","",SUM(K62:M62)*4) -> -99.56
N63: =IF(SUM(B63:M63)=0,"",SUM(B63:M63))/$N$3*12 -> #VALUE! | O63: =IF(N63="","",SUM(H63:M63)*2) -> #VALUE! | P63: =IF(O63="","",SUM(K63:M63)*4) -> #VALUE!
A64: PROPERTY MANAGEMENT FEES | N64: =IF(SUM(B64:M64)=0,"",SUM(B64:M64))/$N$3*12 -> #VALUE! | O64: =IF(N64="","",SUM(H64:M64)*2) -> #VALUE! | P64: =IF(O64="","",SUM(K64:M64)*4) -> #VALUE!
A65: Property Management Fees | B65: 0 | C65: 0 | D65: 0 | E65: 0 | F65: 0 | G65: 0 | H65: 1674.57 | I65: 5288.12 | J65: 2644.06 | K65: 2573.06 | L65: 2573.06 | M65: 2573.06 | N65: =IF(SUM(B65:M65)=0,"",SUM(B65:M65))/$N$3*12 -> 29701.594 | O65: =IF(N65="","",SUM(H65:M65)*2) -> 34651.86 | P65: =IF(O65="","",SUM(K65:M65)*4) -> 30876.72
A66: TOTAL PROPERTY MANAGEMENT FEES | B66: 0 | C66: 0 | D66: 0 | E66: 0 | F66: 0 | G66: 0 | H66: 1674.57 | I66: 5288.12 | J66: 2644.06 | K66: 2573.06 | L66: 2573.06 | M66: 2573.06 | N66: =IF(SUM(B66:M66)=0,"",SUM(B66:M66))/$N$3*12 -> 29701.594 | O66: =IF(N66="","",SUM(H66:M66)*2) -> 34651.86 | P66: =IF(O66="","",SUM(K66:M66)*4) -> 30876.72
A67: TOTAL RECOVERABLE EXPENSES | B67: 0 | C67: 0 | D67: 0 | E67: 0 | F67: 0 | G67: 6161.32 | H67: 10265.67 | I67: 17492.96 | J67: 16591.08 | K67: 15802.4 | L67: 12754.11 | M67: 21605.02 | N67: =IF(SUM(B67:M67)=0,"",SUM(B67:M67))/$N$3*12 -> 172581.53 | O67: =IF(N67="","",SUM(H67:M67)*2) -> 189022.48 | P67: =IF(O67="","",SUM(K67:M67)*4) -> 200646.12
N68: =IF(SUM(B68:M68)=0,"",SUM(B68:M68))/$N$3*12 -> #VALUE! | O68: =IF(N68="","",SUM(H68:M68)*2) -> #VALUE! | P68: =IF(O68="","",SUM(K68:M68)*4) -> #VALUE!
A69: NON-RECOVERABLE EXPENSES | N69: =IF(SUM(B69:M69)=0,"",SUM(B69:M69))/$N$3*12 -> #VALUE! | O69: =IF(N69="","",SUM(H69:M69)*2) -> #VALUE! | P69: =IF(O69="","",SUM(K69:M69)*4) -> #VALUE!
N70: =IF(SUM(B70:M70)=0,"",SUM(B70:M70))/$N$3*12 -> #VALUE! | O70: =IF(N70="","",SUM(H70:M70)*2) -> #VALUE! | P70: =IF(O70="","",SUM(K70:M70)*4) -> #VALUE!
A71: NON-RECOVERABLE RENTAL EXP | N71: =IF(SUM(B71:M71)=0,"",SUM(B71:M71))/$N$3*12 -> #VALUE! | O71: =IF(N71="","",SUM(H71:M71)*2) -> #VALUE! | P71: =IF(O71="","",SUM(K71:M71)*4) -> #VALUE!
A72: NR - Consulting Services | B72: 0 | C72: 0 | D72: 0 | E72: 0 | F72: 0 | G72: 0 | H72: 0 | I72: 0 | J72: 0 | K72: 0 | L72: 1200 | M72: 78.82 | N72: =IF(SUM(B72:M72)=0,"",SUM(B72:M72))/$N$3*12 -> 2192.2629 | O72: =IF(N72="","",SUM(H72:M72)*2) -> 2557.64 | P72: =IF(O72="","",SUM(K72:M72)*4) -> 5115.28
A73: NR - Bank Fees | B73: 0 | C73: 0 | D73: 0 | E73: 0 | F73: 0 | G73: 0 | H73: 0 | I73: 398.23 | J73: 5124.92 | K73: 1762.4 | L73: 1755.2 | M73: 1797.19 | N73: =IF(SUM(B73:M73)=0,"",SUM(B73:M73))/$N$3*12 -> 18579.326 | O73: =IF(N73="","",SUM(H73:M73)*2) -> 21675.88 | P73: =IF(O73="","",SUM(K73:M73)*4) -> 21259.16
A74: TOTAL NON-RECOVERABLE RENT EXP | B74: 0 | C74: 0 | D74: 0 | E74: 0 | F74: 0 | G74: 0 | H74: 0 | I74: 398.23 | J74: 5124.92 | K74: 1762.4 | L74: 2955.2 | M74: 1876.01 | N74: =IF(SUM(B74:M74)=0,"",SUM(B74:M74))/$N$3*12 -> 20771.589 | O74: =IF(N74="","",SUM(H74:M74)*2) -> 24233.52 | P74: =IF(O74="","",SUM(K74:M74)*4) -> 26374.44
A75: TOTAL NON-RECOVERABLE OPER EXP | B75: 0 | C75: 0 | D75: 0 | E75: 0 | F75: 0 | G75: 0 | H75: 0 | I75: 398.23 | J75: 5124.92 | K75: 1762.4 | L75: 2955.2 | M75: 1876.01 | N75: =IF(SUM(B75:M75)=0,"",SUM(B75:M75))/$N$3*12 -> 20771.589 | O75: =IF(N75="","",SUM(H75:M75)*2) -> 24233.52 | P75: =IF(O75="","",SUM(K75:M75)*4) -> 26374.44
A76: NET OPERATING INCOME | B76: 0 | C76: 0 | D76: 0 | E76: 0 | F76: 0 | G76: 42965 | H76: 66164.96 | I76: 62153.18 | J76: 69677.3 | K76: 65914.39 | L76: 70857.99 | M76: 68795.37 | N76: =IF(SUM(B76:M76)=0,"",SUM(B76:M76))/$N$3*12 -> 765476.9 | O76: =IF(N76="","",SUM(H76:M76)*2) -> 807126.38 | P76: =IF(O76="","",SUM(K76:M76)*4) -> 822271
A77: NET OPERATING INCOME AFTER DEPR | B77: 0 | C77: 0 | D77: 0 | E77: 0 | F77: 0 | G77: 42965 | H77: 66164.96 | I77: 62153.18 | J77: 69677.3 | K77: 65914.39 | L77: 70857.99 | M77: 68795.37 | N77: =IF(SUM(B77:M77)=0,"",SUM(B77:M77))/$N$3*12 -> 765476.9 | O77: =IF(N77="","",SUM(H77:M77)*2) -> 807126.38 | P77: =IF(O77="","",SUM(K77:M77)*4) -> 822271
N78: =IF(SUM(B78:M78)=0,"",SUM(B78:M78))/$N$3*12 -> #VALUE! | O78: =IF(N78="","",SUM(H78:M78)*2) -> #VALUE! | P78: =IF(O78="","",SUM(K78:M78)*4) -> #VALUE!
A79: OTHER INCOME & EXPENSES | N79: =IF(SUM(B79:M79)=0,"",SUM(B79:M79))/$N$3*12 -> #VALUE! | O79: =IF(N79="","",SUM(H79:M79)*2) -> #VALUE! | P79: =IF(O79="","",SUM(K79:M79)*4) -> #VALUE!
N80: =IF(SUM(B80:M80)=0,"",SUM(B80:M80))/$N$3*12 -> #VALUE! | O80: =IF(N80="","",SUM(H80:M80)*2) -> #VALUE! | P80: =IF(O80="","",SUM(K80:M80)*4) -> #VALUE!
A81: INTEREST EXPENSE | N81: =IF(SUM(B81:M81)=0,"",SUM(B81:M81))/$N$3*12 -> #VALUE! | O81: =IF(N81="","",SUM(H81:M81)*2) -> #VALUE! | P81: =IF(O81="","",SUM(K81:M81)*4) -> #VALUE!
A82: Int Exp - Mortgage Notes | B82: 0 | C82: 0 | D82: 0 | E82: 0 | F82: 0 | G82: 0 | H82: 56488.79 | I82: 55011.84 | J82: 74622.9 | K82: 59052.16 | L82: 48385.28 | M82: 56199.36 | N82: =IF(SUM(B82:M82)=0,"",SUM(B82:M82))/$N$3*12 -> 599589.14 | O82: =IF(N82="","",SUM(H82:M82)*2) -> 699520.66 | P82: =IF(O82="","",SUM(K82:M82)*4) -> 654547.2
A83: TOTAL INTEREST EXPENSE | B83: 0 | C83: 0 | D83: 0 | E83: 0 | F83: 0 | G83: 0 | H83: 56488.79 | I83: 55011.84 | J83: 74622.9 | K83: 59052.16 | L83: 48385.28 | M83: 56199.36 | N83: =IF(SUM(B83:M83)=0,"",SUM(B83:M83))/$N$3*12 -> 599589.14 | O83: =IF(N83="","",SUM(H83:M83)*2) -> 699520.66 | P83: =IF(O83="","",SUM(K83:M83)*4) -> 654547.2
A84: TOTAL OTHER INCOME & EXPENSES | B84: 0 | C84: 0 | D84: 0 | E84: 0 | F84: 0 | G84: 0 | H84: 56488.79 | I84: 55011.84 | J84: 74622.9 | K84: 59052.16 | L84: 48385.28 | M84: 56199.36 | N84: =IF(SUM(B84:M84)=0,"",SUM(B84:M84))/$N$3*12 -> 599589.14 | O84: =IF(N84="","",SUM(H84:M84)*2) -> 699520.66 | P84: =IF(O84="","",SUM(K84:M84)*4) -> 654547.2
A85: NET INCOME | B85: 0 | C85: 0 | D85: 0 | E85: 0 | F85: 0 | G85: 42965 | H85: 9676.17 | I85: 7141.34 | J85: -4945.6 | K85: 6862.23 | L85: 22472.71 | M85: 12596.01 | N85: =IF(SUM(B85:M85)=0,"",SUM(B85:M85))/$N$3*12 -> 165887.76 | O85: =IF(N85="","",SUM(H85:M85)*2) -> 107605.72 | P85: =IF(O85="","",SUM(K85:M85)*4) -> 167723.8
N86: =IF(SUM(B86:M86)=0,"",SUM(B86:M86))/$N$3*12 -> #VALUE! | O86: =IF(N86="","",SUM(H86:M86)*2) -> #VALUE! | P86: =IF(O86="","",SUM(K86:M86)*4) -> #VALUE!
N87: =IF(SUM(B87:M87)=0,"",SUM(B87:M87))/$N$3*12 -> #VALUE! | O87: =IF(N87="","",SUM(H87:M87)*2) -> #VALUE! | P87: =IF(O87="","",SUM(K87:M87)*4) -> #VALUE!
N88: =IF(SUM(B88:M88)=0,"",SUM(B88:M88))/$N$3*12 -> #VALUE! | O88: =IF(N88="","",SUM(H88:M88)*2) -> #VALUE! | P88: =IF(O88="","",SUM(K88:M88)*4) -> #VALUE!
N89: =IF(SUM(B89:M89)=0,"",SUM(B89:M89))/$N$3*12 -> #VALUE! | O89: =IF(N89="","",SUM(H89:M89)*2) -> #VALUE! | P89: =IF(O89="","",SUM(K89:M89)*4) -> #VALUE!
N90: =IF(SUM(B90:M90)=0,"",SUM(B90:M90))/$N$3*12 -> #VALUE! | O90: =IF(N90="","",SUM(H90:M90)*2) -> #VALUE! | P90: =IF(O90="","",SUM(K90:M90)*4) -> #VALUE!

Sheet RR
B1: As of 3/31/2026
B3: Property | C3: Unit(s) | D3: Lease | E3: Lease From | F3: Lease To | G3: Term | H3: Tenancy | I3: Lease Area | J3: Annual Rent | K3: Annual | L3: Lease Type | M3: LOC Amount/ | N3: Amendment | O3: Status | P3: From | Q3: To | R3: Move In | S3: Move Out | T3: Move Out | U3: Term | V3: Area | W3: Description | X3: Notes | Y3: Rent | Z3: Start Date | AA3: Unit | AB3: Area Label | AC3: Area | AD3: Rent Step | AE3: Monthly | AF3: Rent Step | AG3: Annual | AH3: Management | AI3: Annual Gross | AJ3: Next | AK3: Increase Type | AL3: Increase Value / Percent | AM3: Review Type | AN3: Market Rent | AO3: Who | AP3: Min Increase Type | AQ3: Min Increase Value | AR3: Max Increase Type | AS3: Max Increase Value
H4: Years | K4: Rent/Area | M4: Bank Guarantee | N4: Type | T4: Reason | Y4: Steps | AD4: Monthly | AE4: Rent/Area | AF4: Annual | AG4: Rent/Area | AH4: Fee | AI4: Amount | AJ4: Review Date
AD5: Amount | AE5: Amount | AF5: Amount | AG5: Amount
B8: 601 S. 55th Avenue (v1103001) | C8: 100 | D8: S&M Moving Systems West, Inc. (t0084001) | E8: 44545 | F8: 46568 | G8: 67 | H8: 4.08 | I8: 100000 | J8: 796403.76 | K8: 7.96 | L8: Industrial - Net | M8: 0 | N8: Original Lease | O8: Activated | P8: 44545 | Q8: 46568 | R8: 44545 | U8: 67 | V8: 100000 | W8: Original Lease | Y8: con | Z8: 44743 | AA8: 100 | AB8: Rentable Area | AC8: 100000 | AD8: 0 | AE8: 0 | AF8: 0 | AG8: 0 | AH8: 0 | AI8: 0 | AJ8: 1057624.4 | AK8: 10.57 | AL8: 44743 | AM8: Fixed Amount | AN8: 0 | AQ8: N/A
Y9: rnt | Z9: 45839 | AA9: 100 | AB9: Rentable Area | AC9: 100000 | AD9: 66366.98 | AE9: 0.664 | AF9: 796403.76 | AG9: 7.964 | AH9: 0 | AI9: 796403.76 | AL9: 45839 | AM9: Fixed Amount | AN9: 0 | AQ9: N/A
Y10: rnt | Z10: 46204 | AA10: 100 | AB10: Rentable Area | AC10: 100000 | AD10: 69021.66 | AE10: 0.69 | AF10: 828259.92 | AG10: 8.283 | AH10: 0 | AI10: 828259.92 | AL10: 46204 | AM10: Fixed Amount | AN10: 0 | AQ10: N/A

Sheet Debt Service
B2: Debt Service Calc
B4: UPB | C4: 10409000
B5: NCF | C5: ='Comm OSAR'!I62 -> 737825.96
B6: Whole Loan Spread | C6: 0.0255
B7: Rate Cap | C7: 0.05
B8: SOFR | C8: 0.0368
B9: Interest Rate | C9: =SUM(C6,MIN(C7,C8)) -> 0.0623
B11: Debt Service | C11: =((C6+C8)*C4*(365/360)) -> 657487.38
B12: Capped Debt Service | C12: =(C9)*C4*(365/360) -> 657487.38
B14: DY Event | C14: 0.065
B15: DSCR Event | C15: 1
B17: Capped DSCR | C17: =+C5/C12 -> 1.1221903
B18: DSCR w/o Rate Cap | C18: =+C5/C11 -> 1.1221903
B20: Rate Cap Renewal Calculation
B21: Current Capped DSCR | C21: =C17 -> 1.1221903
B22: Target Capped DSCR | C22: 1.05
B24: Rate Cap
B25: Spread | C25: =C6 -> 0.0255
B26: Effective Capped Interest Rate | C26: =SUM(C24:C25) -> 0.0255
B28: UPB
B29: Debt Service Capped | C29: =(C28*C26)*(365/360) -> 0
B30: Current Net Cash Flow
B32: Resulting Capped DSCR | C32: =C30/C29 -> #DIV/0!

Sheet RE Taxes
B2: Tax Bill From | C2: 45717 | D2: 46082
B3: Tax Amount | C3: =(T5)/C4 -> 0.10309334 | S3: Parcel ID: | T3: 104-20-022
B4: Factor | C4: 1000000 | S4: Link: | T4: https://www.mcassessor.maricopa.gov/
S5: Amt: | T5: =13748.26+89345.08 -> 103093.34

Sheet Insurance
B2: Insurance Policy From | C2: 46113 | D2: 46478
B3: Insurance Amount | C3: =Y41/C4 -> 0.00917582
B4: Factor | C4: 1000000
Y41: 9175.82
