Workbook
Name CMNOTES: #REF!
Name RESULTS: #REF!

Sheet NEW OSAR
B1: CREFC Investor Reporting Package
C2: MULTIFAMILY OPERATING STATEMENT ANALYSIS REPORT (includes Mobile Home Parks, Single Family Rentals, and Co-ops)
C3: as of 3/31/2026
C4: PROPERTY OVERVIEW | H4: Allocated Loan Amount/Percentage
C5: Property ID | E5: 1001-001 | F5: Paid Thru Date | G5: Debt Outside Trust (1) | H5: $ | I5: %
C6: Note A-Scheduled Loan Balance | E6: 52400000 | F6: MM/DD/YY | G6: X or Blank | H6: 0 | I6: 0 | L6: =E7/E12 -> 233971.29
C7: Note B-Scheduled Loan Balance | E7: =E6-3500000 -> 48900000 | F7: MM/DD/YY | G7: X or Blank | H7: 0 | I7: 0
C8: Note C-Scheduled Loan Balance | E8: 0 | F8: MM/DD/YY | G8: X or Blank | H8: 0 | I8: 0
C9: Property Name | E9: Lydian Apartments
C10: Property Type | E10: Multifamily
C11: Property Address, City, State
C12: Current Net Rentable SF/Units/Beds/Rooms | E12: 209 | G12: Use second box to specify sqft.,units…
C13: Year Built/Year Renovated | E13: YYYY | F13: YYYY
C14: Cap Ex Reserve (annually)/per Unit.etc. (2) | E14: 200 | F14: 0 | G14: specify annual/per unit…
C15: Statement Ending Date | E15: Underwriting | F15: 45930 | G15: 46022 | H15: 46112 | I15: =H15 -> 46112
C16: Occupancy Rate (physical) | E16: 0 | F16: 0.92344498 | G16: 0.9138756 | H16: 0.91866029 | I16: =RR!F262 -> 0.91866029 | M16: =I16-H16 -> 0
C17: Occupancy Date | E17: MM/DD/YY | F17: 45930 | G17: 46022 | H17: 46112 | I17: =I15 -> 46112
E18: (1) "X" if debt is outside of the trust, otherwise leave blank
E19: (2) Total $ amount of Capital Reserves required annually by loan documents
C20: INCOME:
C21: Number of Mos. Covered | F21: 12 | G21: 12 | H21: 12 | I21: 12 | J21: (prcdng yr to base) | K21: (prcdng yr to 2nd prcdng)
C22: Period Ended | E22: At Contribution | F22: DY TEST | G22: DY TEST | H22: TTM | I22: DY TEST | J22: YYYY-U/W | K22: YYYY-YYYY
C23: Statement Ending Date | E23: Information | F23: as of 09/30/2025 | G23: as of 12/31/2025 | H23: =I23 -> as of 03/31/2026 | I23: ="as of "&TEXT(I15,"MM/DD/YYYY") -> as of 03/31/2026 | J23: Variance | K23: Variance | L23: Notes
C24: Gross Potential Rent (3) | E24: 4156426 | F24: 4154232 | G24: 4135728 | H24: =INDEX('T12'!$W$13:$W$45,MATCH('NEW OSAR'!C24,'T12'!$V$13:$V$45,0)) -> 3975944.4 | I24: =RR!G259*12 -> 4653828 | J24: =IF(E24=0, " ",(H24-E24)/E24) -> -0.043422306 | K24: =IF(G24=0, " ",(H24-G24)/G24) -> -0.038634939 | L24: Rent Roll as of 3/31/2026 | N24: =I24-G24 -> 518100 | O24: =(I24-G24)/G24 -> 0.1252742
C25: Less: Vacancy Loss | E25: 346369 | F25: 0 | G25: 0 | H25: =INDEX('T12'!$W$13:$W$45,MATCH('NEW OSAR'!C25,'T12'!$V$13:$V$45,0)) -> 0 | I25: =IF(I16>0.95,I24*M25,0) -> 0 | J25: =IF(E25=0, " ",(H25-E25)/E25) -> -1 | K25: =IF(G25=0, " ",(H25-G25)/G25) | L25: ="Greater of actual vacancy ("&TEXT(1-I16,"0.00%")&") and 5.00%" -> Greater of actual vacancy (8.13%) and 5.00% | M25: =5%-(1-I16) -> -0.031339713
C26: OR
C27: Base Rent (3) | H27: =INDEX('T12'!$W$13:$W$45,MATCH('NEW OSAR'!C27,'T12'!$V$13:$V$45,0)) -> 0 | I27: =SUMIF('T12'!A:A,'NEW OSAR'!C27,'T12'!S:S) -> 0 | J27: =IF(E27=0, " ",(H27-E27)/E27) | K27: =IF(G27=0, " ",(H27-G27)/G27) | L27: =IF(G27=0, " ",(J27-G27)/G27)
C28: Laundry/Vending Income | E28: 0 | F28: 0 | H28: =INDEX('T12'!$W$13:$W$45,MATCH('NEW OSAR'!C28,'T12'!$V$13:$V$45,0)) -> 0 | I28: =SUMIF('T12'!A:A,'NEW OSAR'!C28,'T12'!S:S) -> 0 | J28: =IF(E28=0, " ",(H28-E28)/E28) | K28: =IF(G28=0, " ",(H28-G28)/G28) | L28: =IF(G28=0, " ",(J28-G28)/G28)
C29: Parking Income | E29: 0 | F29: 15470.72 | G29: 16313.92 | H29: =INDEX('T12'!$W$13:$W$45,MATCH('NEW OSAR'!C29,'T12'!$V$13:$V$45,0)) -> 19157.7 | I29: =SUMIF('T12'!A:A,'NEW OSAR'!C29,'T12'!S:S) -> 21098.36 | J29: =IF(E29=0, " ",(H29-E29)/E29) | K29: =IF(G29=0, " ",(H29-G29)/G29) -> 0.17431617 | L29: T3M Annualized | N29: =I29-G29 -> 4784.44 | O29: =(I29-G29)/G29 -> 0.29327347
C30: Other Income | E30: 335067 | F30: 323301.52 | G30: 359351.56 | H30: =INDEX('T12'!$W$13:$W$45,MATCH('NEW OSAR'!C30,'T12'!$V$13:$V$45,0)) -> 391050.98 | I30: ='T12'!R42 -> 388447.64 | J30: =IF(E30=0, " ",(H30-E30)/E30) -> 0.16708294 | K30: =IF(G30=0, " ",(H30-G30)/G30) -> 0.088212835 | L30: T3 other income less T3 concessions | N30: =I30-G30 -> 29096.08 | O30: =(I30-G30)/G30 -> 0.080968286
C32: *Effective Gross Income | E32: =SUM(E24:E30) -> 4837862 | F32: 4493004.2 | G32: 4511393.5 | H32: =INDEX('T12'!$W$13:$W$45,MATCH('NEW OSAR'!C32,'T12'!$V$13:$V$45,0)) -> 4386153.1 | I32: =SUM(I24:I30) -> 5063374 | J32: =IF(E32=0, " ",(H32-E32)/E32) -> -0.093369534 | K32: =IF(G32=0, " ",(H32-G32)/G32) -> -0.027760913 | L32: =IF(G32=0, " ",(I32-G32)/G32) -> 0.12235256 | N32: =I32-G32 -> 551980.52 | O32: =(I32-G32)/G32 -> 0.12235256
E33: (3) Use either Gross Potential (with Vacancy Loss) or Base Rents; use negative $amt for Vacancy Loss
C35: OPERATING EXPENSES: | J35: =IF(E35=0, " ",(H35-E35)/E35) | L35: =IF(G35=0, " ",(J35-G35)/G35)
C36: Real Estate Taxes | E36: 351064 | F36: 473998 | G36: 473998 | H36: =INDEX('T12'!$W$13:$W$45,MATCH('NEW OSAR'!C36,'T12'!$V$13:$V$45,0)) -> 516381.63 | I36: =MAX(H36,'Tax Statement'!Y34) -> 516381.63 | J36: =IF(E36=0, " ",(H36-E36)/E36) -> 0.47090454 | K36: =IF(G36=0, " ",(H36-G36)/G36) -> 0.089417318 | L36: Greater of actual tax bill from 3/1/2025-3/1/2026 ($474.0K) and T12 ended 3/31/2026 | N36: =I36-G36 -> 42383.63 | O36: =(I36-G36)/G36 -> 0.089417318
C37: Property Insurance | E37: 51224 | F37: 68100.36 | G37: 67955.4 | H37: =INDEX('T12'!$W$13:$W$45,MATCH('NEW OSAR'!C37,'T12'!$V$13:$V$45,0)) -> 67810.44 | I37: =MAX(H37,Insurance!P20) -> 67810.44 | J37: =IF(E37=0, " ",(H37-E37)/E37) -> 0.32380212 | K37: =IF(G37=0, " ",(H37-G37)/G37) -> -0.0021331638 | L37: Greater of actual insurance premium from 6/28/2025-6/28/2026 ($67.2K) and T12 ended 3/31/2026 | N37: =I37-G37 -> -144.96 | O37: =(I37-G37)/G37 -> -0.0021331638
C38: Utilities | E38: 208625 | F38: 219870.24 | G38: 222876.36 | H38: =INDEX('T12'!$W$13:$W$45,MATCH('NEW OSAR'!C38,'T12'!$V$13:$V$45,0)) -> 232766.67 | I38: =H38 -> 232766.67 | J38: =IF(E38=0, " ",(H38-E38)/E38) -> 0.11571801 | K38: =IF(G38=0, " ",(H38-G38)/G38) -> 0.04437577 | L38: T12 ended 3/31/2026 | N38: =I38-G38 -> 9890.31 | O38: =(I38-G38)/G38 -> 0.04437577
C39: Repairs and Maintenance | E39: 94050 | F39: 167454.19 | G39: 178154.19 | H39: =INDEX('T12'!$W$13:$W$45,MATCH('NEW OSAR'!C39,'T12'!$V$13:$V$45,0)) -> 161952.36 | I39: =H39 -> 161952.36 | J39: =IF(E39=0, " ",(H39-E39)/E39) -> 0.7219815 | K39: =IF(G39=0, " ",(H39-G39)/G39) -> -0.090942739 | L39: T12 ended 3/31/2026 | N39: =I39-G39 -> -16201.83 | O39: =(I39-G39)/G39 -> -0.090942739
C40: Management Fees | E40: 124354 | F40: 134790.13 | G40: 135341.8 | H40: =INDEX('T12'!$W$13:$W$45,MATCH('NEW OSAR'!C40,'T12'!$V$13:$V$45,0)) -> 132211.42 | I40: =MAX(H40,(I32*M40)) -> 151901.22 | J40: =IF(E40=0, " ",(H40-E40)/E40) -> 0.063185905 | K40: =IF(G40=0, " ",(H40-G40)/G40) -> -0.023129471 | L40: Greater of actual fees annualized and 3% of gross revenue | M40: 0.03 | N40: =I40-G40 -> 16559.416 | O40: =(I40-G40)/G40 -> 0.12235256
C41: Payroll & Benefits | E41: 447914 | F41: 335745.19 | G41: 344286.06 | H41: =INDEX('T12'!$W$13:$W$45,MATCH('NEW OSAR'!C41,'T12'!$V$13:$V$45,0)) -> 343527.32 | I41: =H41 -> 343527.32 | J41: =IF(E41=0, " ",(H41-E41)/E41) -> -0.23305072 | K41: =IF(G41=0, " ",(H41-G41)/G41) -> -0.0022038069 | L41: T12 ended 3/31/2026 | N41: =I41-G41 -> -758.74 | O41: =(I41-G41)/G41 -> -0.0022038069
C42: Advertising & Marketing | E42: 102380 | F42: 67982.66 | G42: 67039.78 | H42: =INDEX('T12'!$W$13:$W$45,MATCH('NEW OSAR'!C42,'T12'!$V$13:$V$45,0)) -> 72834.67 | I42: =H42 -> 72834.67 | J42: =IF(E42=0, " ",(H42-E42)/E42) -> -0.28858498 | K42: =IF(G42=0, " ",(H42-G42)/G42) -> 0.086439574 | L42: T12 ended 3/31/2026 | N42: =I42-G42 -> 5794.89 | O42: =(I42-G42)/G42 -> 0.086439574
C43: Professional Fees | E43: 0 | F43: 6674 | G43: 0 | H43: =INDEX('T12'!$W$13:$W$45,MATCH('NEW OSAR'!C43,'T12'!$V$13:$V$45,0)) -> 0 | I43: =H43 -> 0 | J43: =IF(E43=0, " ",(H43-E43)/E43) | K43: =IF(G43=0, " ",(H43-G43)/G43) | L43: T12 ended 3/31/2026
C44: General and Administrative | E44: 102380 | F44: 121353.7 | G44: 131976.84 | H44: =INDEX('T12'!$W$13:$W$45,MATCH('NEW OSAR'!C44,'T12'!$V$13:$V$45,0)) -> 136342.22 | I44: =H44 -> 136342.22 | J44: =IF(E44=0, " ",(H44-E44)/E44) -> 0.3317271 | K44: =IF(G44=0, " ",(H44-G44)/G44) -> 0.033076864 | L44: T12 ended 3/31/2026 | N44: =I44-G44 -> 4365.38 | O44: =(I44-G44)/G44 -> 0.033076864
C45: Other Expenses | E45: 36000 | F45: 0 | G45: 0 | H45: =INDEX('T12'!$W$13:$W$45,MATCH('NEW OSAR'!C45,'T12'!$V$13:$V$45,0)) -> 0 | I45: =H45 -> 0 | J45: =IF(E45=0, " ",(H45-E45)/E45) -> -1 | K45: =IF(G45=0, " ",(H45-G45)/G45) | L45: T12 ended 3/31/2026
C46: Ground Rent | H46: =INDEX('T12'!$W$13:$W$45,MATCH('NEW OSAR'!C46,'T12'!$V$13:$V$45,0)) -> 0 | I46: =H46 -> 0 | J46: =IF(E46=0, " ",(H46-E46)/E46) | K46: =IF(G46=0, " ",(H46-G46)/G46)
C47: *Total Operating Expenses | E47: =SUM(E36:E46) -> 1517991 | F47: 1595968.5 | G47: 1621628.4 | H47: =INDEX('T12'!$W$13:$W$45,MATCH('NEW OSAR'!C47,'T12'!$V$13:$V$45,0)) -> 1663826.7 | I47: =SUM(I36:I46) -> 1683516.5 | J47: =IF(E47=0, " ",(H47-E47)/E47) -> 0.096071538 | K47: =IF(G47=0, " ",(H47-G47)/G47) -> 0.026022173 | N47: =I47-G47 -> 61888.096 | O47: =(I47-G47)/G47 -> 0.038164165
C49: Operating Expense Ratio | E49: =E47/E32 -> 0.31377311 | F49: 0.35521188 | G49: 0.35945178 | H49: =H47/H32 -> 0.37933622 | I49: =I47/I32 -> 0.33248907 | J49: =IF(E49=0, " ",(H49-E49)/E49) -> 0.2089507 | K49: =IF(G49=0, " ",(H49-G49)/G49) -> 0.055318786 | N49: =I49-G49 -> -0.02696271 | O49: =(I49-G49)/G49 -> -0.075010646
C51: *Net Operating Income | E51: =E32-E47 -> 3319871 | F51: 2897035.8 | G51: 2889765 | H51: =INDEX('T12'!$W$13:$W$45,MATCH('NEW OSAR'!C51,'T12'!$V$13:$V$45,0)) -> 2722326.4 | I51: =I32-I47 -> 3379857.5 | J51: =IF(E51=0, " ",(H51-E51)/E51) -> -0.17999032 | K51: =IF(G51=0, " ",(H51-G51)/G51) -> -0.057941976 | N51: =I51-G51 -> 490092.42 | O51: =(I51-G51)/G51 -> 0.16959594
C53: Capital Expenditures | E53: 0 | F53: 41800 | G53: 41800 | H53: =I53 -> 41800 | I53: =E14*E12 -> 41800 | J53: =IF(E53=0, " ",(H53-E53)/E53) | K53: =IF(G53=0, " ",(H53-G53)/G53) -> 0 | L53: $200 per unit
C54: Extraordinary Capital Expenditures
C55: Total Capital Items | E55: =SUM(E53:E54) -> 0 | F55: 41800 | G55: 41800 | H55: =SUM(H53:H54) -> 41800 | I55: =SUM(I53:I54) -> 41800 | J55: =IF(E55=0, " ",(H55-E55)/E55) | K55: =IF(G55=0, " ",(H55-G55)/G55) -> 0
C57: *Net Cash Flow | E57: =E51-E55 -> 3319871 | F57: 2855235.8 | G57: 2847965 | H57: =H51-H55 -> 2680526.4 | I57: =I51-I55 -> 3338057.5 | J57: =IF(E57=0, " ",(H57-E57)/E57) -> -0.19258117 | K57: =IF(G57=0, " ",(H57-G57)/G57) -> -0.058792398 | L57: =IF(G57=0, " ",(I57-G57)/G57) -> 0.17208513
C59: Debt Service - A Note | F59: 2629825 | G59: 2629825 | H59: ='Debt Service'!C11 -> 2629825 | I59: ='Debt Service'!C11 -> 2629825 | L59: Current 2.5% Cap Rate +2.45% Spread
C60: Debt Service - B Note
C61: Debt Service - C Note
C63: *Net Cash Flow after Debt Service | E63: =E57-E59 -> 3319871 | F63: 225410.77 | G63: 218140.05 | H63: =H57-H59 -> 50701.35 | I63: =I57-I59 -> 708232.47 | J63: =IF(E63=0, " ",(H63-E63)/E63) -> -0.98472792 | K63: =IF(G63=0, " ",(H63-G63)/G63) -> -0.76757431 | L63: =IF(G63=0, " ",(I63-G63)/G63) -> 2.2466871
C65: *DSCR: (NOI/Debt Service) - A Note | F65: 1.1016078 | G65: 1.0988431 | H65: =H51/H59 -> 1.035174 | I65: =I51/I59 -> 1.2852024 | K65: =IF(G65=0, " ",(H65-G65)/G65) -> -0.057941976 | L65: =IF(G65=0, " ",(I65-G65)/G65) -> 0.16959594
C66: *DSCR: (NOI/Debt Service) - A & B Note
C67: *DSCR: (NOI/Debt Service) - A, B & C Note
C69: *DSCR: (NCF/Debt Service) - A Note | F69: 1.0857132 | G69: 1.0829485 | H69: =H57/H59 -> 1.0192794 | I69: =I57/I59 -> 1.2693078 | K69: =IF(G69=0, " ",(H69-G69)/G69) -> -0.058792398 | L69: =IF(G69=0, " ",(I69-G69)/G69) -> 0.17208513
C70: *DSCR: (NCF/Debt Service) - A & B Note
C71: *DSCR: (NCF/Debt Service) - A, B & C Note
C73: *Debt Yield (NCF/Debt Balance) | E73: =E51/E6 -> 0.063356317 | F73: 0.054489232 | G73: 0.054350478 | H73: =H57/E6 -> 0.051155083 | I73: =I57/$E$6 -> 0.063703387 | J73: =J63/$E$6 -> -1.8792517e-08 | K73: 6.00% through April 2026 | L73: 6.00% through April 2026 | N73: =I73-G73 -> 0.0093529089
I74: =I57/E7 -> 0.068262934 | J74: Post Paydown | L74: Post Paydown
C75: Source of Financial Data:
E76: (ie. operating statements, financial statements, tax return, other)
C77: Notes and Assumptions: Years above will roll, always showing a 3yr sequential history. Comments from the most recent NOI Adjustment Worksheet should be carried forward to Operating Statement
C78: Analysis Report. Year-over-year variances (either higher or lower) must be explained and noted for the following: >20% DSCR change, >20% EGI/Total Operating Expenses or Total Capital
C79: Items. Quarterly variance comments may be necessary if the loan is on the Watch List.
C80: Income: Comments
C83: Expense: Comments
C86: Capital Items: Comments
C89: DSCR: Comments
C92: * Used in the CREFC Comparative Financial Status Report/CREFC Property File/CREFC Loan Periodic Update File. Note that information for multiple property loans must be consolidated (if available)
C93: for reporting to the CREFC Loan Periodic Update file.

Sheet T12
B1: Lydian Apartments
B2: 12 Month Income Statement
B3: Reporting Book: | C3: CASH
B4: As of Date: | C4: 03/31/2026
B5: Location: | C5: Lydian Apartments
C7: Month Ending | D7: Month Ending | E7: Month Ending | F7: Month Ending | G7: Month Ending | H7: Month Ending | I7: Month Ending | J7: Month Ending | K7: Month Ending | L7: Month Ending | M7: Month Ending | N7: Month Ending | O7: Total
C8: 04/30/2025 | D8: 05/31/2025 | E8: 06/30/2025 | F8: 07/31/2025 | G8: 08/31/2025 | H8: 09/30/2025 | I8: 10/31/2025 | J8: 11/30/2025 | K8: 12/31/2025 | L8: 01/31/2026 | M8: 02/28/2026 | N8: 03/31/2026 | O8: 03/31/2026
C9: Actual | D9: Actual | E9: Actual | F9: Actual | G9: Actual | H9: Actual | I9: Actual | J9: Actual | K9: Actual | L9: Actual | M9: Actual | N9: Actual | O9: Actual
B10: INCOME
B12: RENTAL REVENUE | Q12: Annualized T12 | R12: Annualized T6 | S12: Annualized T3 | V12: 46112
A13: Gross Potential Rent (3) | B13: 4010.000 - Rent | C13: 330533.89 | D13: 333988.81 | E13: 336658.47 | F13: 318379.58 | G13: 319407.19 | H13: 330944.81 | I13: 335956.73 | J13: 323336.98 | K13: 343700 | L13: 343279.25 | M13: 326666.73 | N13: 318552.66 | O13: 3961405.1 | Q13: =IF(SUM(C13:N13)=0,"",SUM(C13:N13)) -> 3961405.1 | R13: =IF(Q13=0,"",SUM(I13:N13)*2) -> 3982984.7 | S13: =IF(Q13=0,"",SUM(L13:N13)*4) -> 3953994.6 | V13: Gross Potential Rent (3) | W13: =SUMIF(A:A,$V13,O:O) -> 3975944.4
A14: Gross Potential Rent (3) | B14: 4011.100 - Month to Month Rent | C14: 1375 | D14: 1600.87 | E14: 1040.25 | F14: 1136.27 | G14: 588.71 | H14: 735.48 | I14: 1443.54 | J14: 1959.67 | K14: 1511.81 | L14: 1457.02 | M14: 865.83 | N14: 824.85 | O14: 14539.3 | Q14: =IF(SUM(C14:N14)=0,"",SUM(C14:N14)) -> 14539.3 | R14: =IF(Q14=0,"",SUM(I14:N14)*2) -> 16125.44 | S14: =IF(Q14=0,"",SUM(L14:N14)*4) -> 12590.8 | V14: Less: Vacancy Loss | W14: =SUMIF(A:A,$V14,O:O) -> 0
B15: NET RENTAL REVENUE | C15: 331908.89 | D15: 335589.68 | E15: 337698.72 | F15: 319515.85 | G15: 319995.9 | H15: 331680.29 | I15: 337400.27 | J15: 325296.65 | K15: 345211.81 | L15: 344736.27 | M15: 327532.56 | N15: 319377.51 | O15: 3975944.4 | Q15: =SUM(Q13:Q14) -> 3975944.4 | R15: =SUM(R13:R14) -> 3999110.1 | S15: =SUM(S13:S14) -> 3966585.4
V16: Base Rent (3) | W16: =SUMIF(A:A,$V16,O:O) -> 0
B17: OTHER TENANT INCOME | V17: Laundry/Vending Income | W17: =SUMIF(A:A,$V17,O:O) -> 0
A18: Other Income | B18: 4100.000 - Late Charges | C18: 1710 | D18: 2070 | E18: 2248 | F18: 2792 | G18: 2579.79 | H18: 4200 | I18: 4273 | J18: 2222 | K18: 3615 | L18: 3405 | M18: 2565 | N18: 2273.92 | O18: 33953.71 | Q18: =IF(SUM(C18:N18)=0,"",SUM(C18:N18)) -> 33953.71 | R18: =IF(Q18=0,"",SUM(I18:N18)*2) -> 36707.84 | S18: =IF(Q18=0,"",SUM(L18:N18)*4) -> 32975.68 | V18: Parking Income | W18: =SUMIF(A:A,$V18,O:O) -> 19157.7
A19: Other Income | B19: 4120.000 - Application Fee Income | C19: 1100 | D19: 1200 | E19: 700 | F19: 300 | G19: 800 | H19: 550 | I19: 200 | J19: 100 | K19: 150 | L19: 0 | M19: 0 | N19: 0 | O19: 5100 | Q19: =IF(SUM(C19:N19)=0,"",SUM(C19:N19)) -> 5100 | R19: =IF(Q19=0,"",SUM(I19:N19)*2) -> 900 | S19: =IF(Q19=0,"",SUM(L19:N19)*4) -> 0 | T19: Recurring | V19: Other Income | W19: =SUMIF(A:A,$V19,O:O) -> 391050.98
A20: Other Income | B20: 4120.100 - Pet Fees | C20: 1499.45 | D20: 660.48 | E20: 630 | F20: 700 | G20: 966.45 | H20: 649.83 | I20: 945 | J20: 1254.16 | K20: 595 | L20: 595 | M20: 667.5 | N20: 1253.71 | O20: 10416.58 | P20: 0 | Q20: =IF(SUM(C20:N20)=0,"",SUM(C20:N20)) -> 10416.58 | R20: =IF(Q20=0,"",SUM(I20:N20)*2) -> 10620.74 | S20: =IF(Q20=0,"",SUM(L20:N20)*4) -> 10064.84 | T20: Recurring
A21: Other Income | B21: 4120.200 - Administrative Fees | C21: 3450 | D21: 4300 | E21: 1900 | F21: 1300 | G21: 3105.75 | H21: 1250 | I21: 400 | J21: 450 | K21: 1000 | L21: 1000 | M21: 6750 | N21: 2000 | O21: 26905.75 | Q21: =IF(SUM(C21:N21)=0,"",SUM(C21:N21)) -> 26905.75 | R21: =IF(Q21=0,"",SUM(I21:N21)*2) -> 23200 | S21: =IF(Q21=0,"",SUM(L21:N21)*4) -> 39000 | T21: Recurring | V21: *Effective Gross Income | W21: =SUM(W13:W19) -> 4386153.1 | Y21: =IF(W21=O37,"YES","NO") -> YES
A22: Other Income | B22: 4124.000 - Lease Termination Fees | C22: 609.19 | D22: 3911.49 | E22: 784.96 | F22: 183.65 | G22: 207.48 | H22: 323.69 | I22: 7049.78 | J22: 1142.75 | K22: 3253.65 | L22: 399.87 | M22: 5438.6 | N22: 4029.2 | O22: 27334.31 | Q22: =IF(SUM(C22:N22)=0,"",SUM(C22:N22)) -> 27334.31 | R22: =IF(Q22=0,"",SUM(I22:N22)*2) -> 42627.7 | S22: =IF(Q22=0,"",SUM(L22:N22)*4) -> 39470.68 | T22: Recurring
A23: Parking Income | B23: 4140.000 - Reserved/ Covered Parking Fees | C23: 2463.74 | D23: -492.84 | E23: 3966.05 | F23: 1298.33 | G23: 1169.35 | H23: 1400 | I23: 1512.42 | J23: 1288.81 | K23: 1277.25 | L23: 1283.01 | M23: 1830.28 | N23: 2161.3 | O23: 19157.7 | Q23: =IF(SUM(C23:N23)=0,"",SUM(C23:N23)) -> 19157.7 | R23: =IF(Q23=0,"",SUM(I23:N23)*2) -> 18706.14 | S23: =IF(Q23=0,"",SUM(L23:N23)*4) -> 21098.36 | T23: Recurring | V23: OPERATING EXPENSES: | W23: =SUMIF(A:A,$V23,O:O) -> 0
A24: Other Income | B24: 4150.000 - Miscellaneous Income | C24: 11321.59 | D24: -7435.76 | E24: 9396.84 | F24: -9196.74 | G24: 1361.5 | H24: 1925.94 | I24: 1307.59 | J24: 1207.6 | K24: 2105.24 | L24: 1255.94 | M24: 1231.29 | N24: 1081.9 | O24: 15562.93 | Q24: =IF(SUM(C24:N24)=0,"",SUM(C24:N24)) -> 15562.93 | R24: =IF(Q24=0,"",SUM(I24:N24)*2) -> 16379.12 | S24: =IF(Q24=0,"",SUM(L24:N24)*4) -> 14276.52 | T24: Recurring | V24: Real Estate Taxes | W24: =SUMIF(A:A,$V24,O:O) -> 516381.63
A25: Other Income | B25: 4150.200 - Renters Insurance Charges | C25: 3013.13 | D25: 2921.4 | E25: 2942.95 | F25: 3058.62 | G25: 3089.03 | H25: 3048.11 | I25: 3202.55 | J25: 2725.55 | K25: 3174.4 | L25: 3073.48 | M25: 3043.72 | N25: 3039.82 | O25: 36332.76 | Q25: =IF(SUM(C25:N25)=0,"",SUM(C25:N25)) -> 36332.76 | R25: =IF(Q25=0,"",SUM(I25:N25)*2) -> 36519.04 | S25: =IF(Q25=0,"",SUM(L25:N25)*4) -> 36628.08 | T25: Recurring | V25: Property Insurance | W25: =SUMIF(A:A,$V25,O:O) -> 67810.44
A26: Other Income | B26: 4150.300 - Transfer Fee | C26: 0 | D26: 0 | E26: 0 | F26: 500 | G26: 0 | H26: 1500 | I26: -750 | J26: 0 | K26: 0 | L26: 250 | M26: 750 | N26: 250 | O26: 2500 | Q26: =IF(SUM(C26:N26)=0,"",SUM(C26:N26)) -> 2500 | R26: =IF(Q26=0,"",SUM(I26:N26)*2) -> 1000 | S26: =IF(Q26=0,"",SUM(L26:N26)*4) -> 5000 | T26: Recurring | V26: Utilities | W26: =SUMIF(A:A,$V26,O:O) -> 232766.67
A27: Other Income | B27: 4150.400 - Keys, Cards and Remotes | C27: 0 | D27: 125 | E27: 0 | F27: 0 | G27: 0 | H27: 0 | I27: 10 | J27: 150 | K27: 100 | L27: 0 | M27: 10 | N27: 0 | O27: 395 | Q27: =IF(SUM(C27:N27)=0,"",SUM(C27:N27)) -> 395 | R27: =IF(Q27=0,"",SUM(I27:N27)*2) -> 540 | S27: =IF(Q27=0,"",SUM(L27:N27)*4) -> 40 | T27: Recurring | V27: Repairs and Maintenance | W27: =SUMIF(A:A,$V27,O:O) -> 161952.36
A28: Other Income | B28: 4150.600 - Technology Fee | C28: 1299.36 | D28: 1591.25 | E28: 1979.16 | F28: 2265.31 | G28: 2555.65 | H28: 2628.34 | I28: 2591.13 | J28: 2601.4 | K28: 2615.35 | L28: 2696.75 | M28: 2814.94 | N28: 2821.22 | O28: 28459.86 | Q28: =IF(SUM(C28:N28)=0,"",SUM(C28:N28)) -> 28459.86 | R28: =IF(Q28=0,"",SUM(I28:N28)*2) -> 32281.58 | S28: =IF(Q28=0,"",SUM(L28:N28)*4) -> 33331.64 | T28: Recurring | V28: Management Fees | W28: =SUMIF(A:A,$V28,O:O) -> 132211.42
A29: Other Income | B29: 4160.000 - Utility Reimb/Water | C29: 4018.59 | D29: 4318.17 | E29: 3434.89 | F29: 3941.22 | G29: 3923.44 | H29: 4778.39 | I29: 4800 | J29: 5250.99 | K29: 5806.61 | L29: 6447.45 | M29: 6500.31 | N29: 5930.67 | O29: 59150.73 | Q29: =IF(SUM(C29:N29)=0,"",SUM(C29:N29)) -> 59150.73 | R29: =IF(Q29=0,"",SUM(I29:N29)*2) -> 69472.06 | S29: =IF(Q29=0,"",SUM(L29:N29)*4) -> 75513.72 | T29: Recurring | V29: Payroll & Benefits | W29: =SUMIF(A:A,$V29,O:O) -> 343527.32
A30: Other Income | B30: 4161.000 - Utility Reimb/Electric | C30: 3427.72 | D30: 3579.72 | E30: 3222.95 | F30: 3109.55 | G30: 3928 | H30: 4494.34 | I30: 4684.53 | J30: 5028.43 | K30: 5711.33 | L30: 5126.14 | M30: 5744.42 | N30: 5252.8 | O30: 53309.93 | Q30: =IF(SUM(C30:N30)=0,"",SUM(C30:N30)) -> 53309.93 | R30: =IF(Q30=0,"",SUM(I30:N30)*2) -> 63095.3 | S30: =IF(Q30=0,"",SUM(L30:N30)*4) -> 64493.44 | T30: Recurring | V30: Advertising & Marketing | W30: =SUMIF(A:A,$V30,O:O) -> 72834.67
A31: Other Income | B31: 4162.000 - Utility Reimb/Trash | C31: 1469.34 | D31: 1438.69 | E31: 1484.26 | F31: 1463.75 | G31: 1477.7 | H31: 1459.44 | I31: 1533.93 | J31: 1477.41 | K31: 1521.3 | L31: 1526.97 | M31: 1493.55 | N31: 1459.1 | O31: 17805.44 | Q31: =IF(SUM(C31:N31)=0,"",SUM(C31:N31)) -> 17805.44 | R31: =IF(Q31=0,"",SUM(I31:N31)*2) -> 18024.52 | S31: =IF(Q31=0,"",SUM(L31:N31)*4) -> 17918.48 | T31: Recurring | V31: Professional Fees | W31: =SUMIF(A:A,$V31,O:O) -> 0
A32: Other Income | B32: 4163.000 - Utility Reimb/Pest Control | C32: 552.4 | D32: 539.51 | E32: 556.6 | F32: 548.9 | G32: 554.13 | H32: 547.29 | I32: 575.24 | J32: 554.03 | K32: 570.5 | L32: 572.63 | M32: 560.06 | N32: 547.16 | O32: 6678.45 | Q32: =IF(SUM(C32:N32)=0,"",SUM(C32:N32)) -> 6678.45 | R32: =IF(Q32=0,"",SUM(I32:N32)*2) -> 6759.24 | S32: =IF(Q32=0,"",SUM(L32:N32)*4) -> 6719.4 | T32: Recurring | V32: General and Administrative | W32: =SUMIF(A:A,$V32,O:O) -> 136342.22
A33: Other Income | B33: 4164.000 - Utility/Gas | C33: 920.67 | D33: 899.19 | E33: 927.66 | F33: 909.85 | G33: 928.56 | H33: 912.14 | I33: 958.71 | J33: 923.38 | K33: 950.81 | L33: 954.37 | M33: 933.49 | N33: 911.93 | O33: 11130.76 | Q33: =IF(SUM(C33:N33)=0,"",SUM(C33:N33)) -> 11130.76 | R33: =IF(Q33=0,"",SUM(I33:N33)*2) -> 11265.38 | S33: =IF(Q33=0,"",SUM(L33:N33)*4) -> 11199.16 | T33: Recurring | V33: Other Expenses | W33: =SUMIF(A:A,$V33,O:O) -> 0
A34: Other Income | B34: 4165.000 - Valet Trash | C34: 4591.63 | D34: 4495.94 | E34: 4613.34 | F34: 4552.21 | G34: 4639.77 | H34: 4560.79 | I34: 4793.55 | J34: 4616.91 | K34: 4754.06 | L34: 4771.78 | M34: 4667.36 | N34: 4559.66 | O34: 55617 | Q34: =IF(SUM(C34:N34)=0,"",SUM(C34:N34)) -> 55617 | R34: =IF(Q34=0,"",SUM(I34:N34)*2) -> 56326.64 | S34: =IF(Q34=0,"",SUM(L34:N34)*4) -> 55995.2 | T34: Recurring | V34: Ground Rent | W34: =SUMIF(A:A,$V34,O:O) -> 0
A35: Other Income | B35: 4170.000 - Security Deposit Forfeiture | C35: 5.97 | D35: 0 | E35: 0.75 | F35: 0 | G35: 0 | H35: 491.05 | I35: -200 | J35: 0 | K35: 0 | L35: 0 | M35: 100 | N35: 0 | O35: 397.77 | Q35: =IF(SUM(C35:N35)=0,"",SUM(C35:N35)) -> 397.77 | R35: =IF(Q35=0,"",SUM(I35:N35)*2) -> -200 | S35: =IF(Q35=0,"",SUM(L35:N35)*4) -> 400 | T35: Recurring | V35: *Total Operating Expenses | W35: =SUM(W24:W34) -> 1663826.7 | Y35: =IF(W35=O121,"YES","NO") -> YES
B36: TOTAL OTHER TENANT INCOME | C36: 41452.78 | D36: 24122.24 | E36: 38788.41 | F36: 17726.65 | G36: 31286.6 | H36: 34719.35 | I36: 37887.43 | J36: 30993.42 | K36: 37200.5 | L36: 33358.39 | M36: 45100.52 | N36: 37572.39 | O36: 410208.68 | Q36: =SUM(Q18:Q35) -> 410208.68 | R36: =SUM(R18:R35) -> 444225.3 | S36: =SUM(S18:S35) -> 464125.2 | T36: Recurring
B37: TOTAL INCOME | C37: 373361.67 | D37: 359711.92 | E37: 376487.13 | F37: 337242.5 | G37: 351282.5 | H37: 366399.64 | I37: 375287.7 | J37: 356290.07 | K37: 382412.31 | L37: 378094.66 | M37: 372633.08 | N37: 356949.9 | O37: 4386153.1 | Q37: =Q36+Q15 -> 4386153.1 | R37: =R36+R15 -> 4443335.4 | S37: =S36+S15 -> 4430710.6 | V37: Operating Expense Ratio | W37: =W35/W21 -> 0.37933622
Q39: Other Income | R39: =S14+S36-S23 -> 455617.64 | V39: *Net Operating Income | W39: =W21-W35 -> 2722326.4 | Y39: =IF(W39=O123,"YES","NO") -> YES
B40: EXPENSES | Q40: Concessions | R40: =RR!AO11 -> -67170
Q41: AR | V41: Capital Expenditures | W41: =SUMIF(A:A,$V41,O:O) -> 0
B42: UTILITIES | Q42: Total | R42: =SUM(R39:R40) -> 388447.64 | V42: Extraordinary Capital Expenditures | W42: =SUMIF(A:A,$V42,O:O) -> 0
B43: 6010.000 - Utilities - Electric / Vacant | C43: 996.61 | D43: 613.95 | E43: 1396.69 | F43: 1451.57 | G43: 1423.5 | H43: 1670.22 | I43: 684.36 | J43: 1788.88 | K43: 1478.67 | L43: -471.26 | M43: 527.01 | N43: 1687.45 | O43: 13247.65 | V43: Total Capital Items | W43: =SUM(W41:W42) -> 0
B44: 6015.000 - Utilities - Electric / House | C44: 4391.18 | D44: 5612.98 | E44: 6478.68 | F44: 6687.19 | G44: 6767.11 | H44: 7189.16 | I44: 6314.56 | J44: 4967.55 | K44: 4739.1 | L44: 4361.03 | M44: 4653.02 | N44: 4754.52 | O44: 66916.08 | R44: Annualized T6
B45: 6025.000 - Utilities - Gas/ Heating Oil | C45: 206.06 | D45: 232.25 | E45: 234.79 | F45: 226.27 | G45: 217.45 | H45: 230.2 | I45: 230.33 | J45: 239.46 | K45: 266.92 | L45: 236.68 | M45: 230.5 | N45: 210.76 | O45: 2761.67 | Q45: Total | R45: {=_xlfn.IFS(R44="Annualized T6",SUM(R19:R36),R44="Annualized T3",SUM(S19:S36))} -> 851742.76 | V45: *Net Cash Flow | W45: =W39-W43 -> 2722326.4
B46: 6050.000 - Utilities - Water/Sewer | C46: 5316.31 | D46: 6407.18 | E46: 6273.78 | F46: 11142.53 | G46: 8231.46 | H46: 6678.01 | I46: 6408.19 | J46: 5779.6 | K46: 5436.94 | L46: 5345.33 | M46: 5145.55 | N46: 5043.31 | O46: 77208.19 | Q46: Less: Non-Recurring | R46: {=-_xlfn.IFS(R44="Annualized T6",SUMIF(T19:T36,"Non-Recurring",R19:R36),R44="Annualized T3",SUMIF(T19:T36,"Non-Recurring",S19:S36))} -> 0
B47: 6090.000 - Telephone | C47: 464.07 | D47: 658.83 | E47: 1193.26 | F47: 640.39 | G47: 690.88 | H47: 612.88 | I47: 619.26 | J47: 3162.77 | K47: 1118.84 | L47: 0 | M47: 0 | N47: 0 | O47: 9161.18 | Q47: Net Total | R47: =SUM(R45:R46) -> 851742.76 | V47: Debt Service - A Note
B48: 6090.100 - Telephone Internet | C48: 0 | D48: 0 | E48: 0 | F48: 0 | G48: 0 | H48: 0 | I48: 0 | J48: 0 | K48: 0 | L48: 347.83 | M48: 1123.18 | N48: 1112.7 | O48: 2583.71 | V48: Debt Service - B Note
B49: 6100.000 - Waste Disposal | C49: 3198.9 | D49: 2523.9 | E49: 2647.9 | F49: 2523.9 | G49: 2472.9 | H49: 1687 | I49: 1623.9 | J49: 2073.9 | K49: 2073.9 | L49: 2748.9 | M49: 4098.9 | N49: 2853.42 | O49: 30527.42 | V49: Debt Service - C Note
B50: 6100.100 - Valet Trash Service | C50: 2487.99 | D50: 2487.99 | E50: 2487.99 | F50: 2418.88 | G50: 2487.99 | H50: 2487.99 | I50: 2487.99 | J50: 2487.99 | K50: 3061.99 | L50: 2487.99 | M50: 2487.99 | N50: 2487.99 | O50: 30360.77
A51: Utilities | B51: TOTAL UTILITIES | C51: 17061.12 | D51: 18537.08 | E51: 20713.09 | F51: 25090.73 | G51: 22291.29 | H51: 20555.46 | I51: 18368.59 | J51: 20500.15 | K51: 18176.36 | L51: 15056.5 | M51: 18266.15 | N51: 18150.15 | O51: 232766.67 | V51: *Net Cash Flow after Debt Service
B53: CONTRACT SERVICES | V53: *DSCR: (NOI/Debt Service) - A Note
B54: 6110.000 - Contract - Landscape Contract | C54: 722.8 | D54: 722.8 | E54: 722.8 | F54: 722.8 | G54: 722.8 | H54: 722.8 | I54: 722.8 | J54: 722.8 | K54: 722.8 | L54: 722.96 | M54: 722.8 | N54: 722.8 | O54: 8673.76 | V54: *DSCR: (NOI/Debt Service) - A & B Note
B55: 6111.000 - Contract - Other Landscape/Irr | C55: 600 | D55: 250 | E55: 100 | F55: 0 | G55: 350 | H55: 0 | I55: 2090 | J55: 0 | K55: 400 | L55: 0 | M55: 0 | N55: 200 | O55: 3990 | V55: *DSCR: (NOI/Debt Service) - A, B & C Note
B56: 6120.000 - Contract - Security Patrol | C56: 2911.3 | D56: 1425 | E56: 2004.67 | F56: 1487.97 | G56: 1485.39 | H56: 1425 | I56: 1590 | J56: 1500 | K56: 1847.26 | L56: 400 | M56: 1400 | N56: 1400 | O56: 18876.59
B57: 6121.000 - Contract - Alarm Monitor | C57: 0 | D57: 0 | E57: 105 | F57: 0 | G57: 0 | H57: 0 | I57: 0 | J57: 0 | K57: 0 | L57: 0 | M57: 0 | N57: 105 | O57: 210 | V57: *DSCR: (NCF/Debt Service) - A Note
B58: 6140.000 - Contract - Pest Control | C58: 300 | D58: 450 | E58: 300 | F58: 330 | G58: 300 | H58: 300 | I58: 450 | J58: 300 | K58: 600 | L58: 400 | M58: 300 | N58: 400 | O58: 4430 | V58: *DSCR: (NCF/Debt Service) - A & B Note
B59: 6210.000 - Contract - Repair Services | C59: 1519.22 | D59: 1527.86 | E59: 1482.77 | F59: 1292.78 | G59: 2030.29 | H59: 1417.73 | I59: 3635.33 | J59: 1774.3 | K59: 1560.37 | L59: 3370.66 | M59: 1698.86 | N59: 1474.85 | O59: 22785.02 | V59: *DSCR: (NCF/Debt Service) - A, B & C Note
A60: Repairs and Maintenance | B60: TOTAL CONTRACT SERVICES | C60: 6053.32 | D60: 4375.66 | E60: 4715.24 | F60: 3833.55 | G60: 4888.48 | H60: 3865.53 | I60: 8488.13 | J60: 4297.1 | K60: 5130.43 | L60: 4893.62 | M60: 4121.66 | N60: 4302.65 | O60: 58965.37
B62: REPAIRS & MAINTENANCE
B63: 6230.000 - HVAC Repairs & Supplies | C63: 301.95 | D63: 148.7 | E63: 121.45 | F63: 24.15 | G63: 741.78 | H63: 0 | I63: 386.46 | J63: 0 | K63: 848.39 | L63: 121.68 | M63: 1725.24 | N63: 0 | O63: 4419.8
B64: 6240.000 - Pool Supplies | C64: 342.14 | D64: 29.21 | E64: 238.26 | F64: 257.55 | G64: 1428 | H64: 0 | I64: 261.8 | J64: 0 | K64: 450 | L64: 55.66 | M64: 0 | N64: 0 | O64: 3062.62
B65: 6250.000 - Paint Service & Supplies | C65: 2626.18 | D65: 3376.52 | E65: 2455.81 | F65: 2821.53 | G65: 249.69 | H65: 1170 | I65: 2630.06 | J65: 1340 | K65: 1057.5 | L65: 1297.72 | M65: 62.03 | N65: 259.15 | O65: 19346.19
B66: 6251.000 - Resurface | C66: 1360 | D66: 1190 | E66: 0 | F66: 420 | G66: 420 | H66: 0 | I66: 1280 | J66: 560 | K66: 170 | L66: 850 | M66: 340 | N66: 0 | O66: 6590
B67: 6252.000 - Gate Repairs | C67: 0 | D67: 0 | E67: 293.94 | F67: 0 | G67: 0 | H67: 0 | I67: 0 | J67: 0 | K67: 0 | L67: 0 | M67: 0 | N67: 0 | O67: 293.94
B68: 6260.000 - Plumbing Repairs/Supplies | C68: 915.21 | D68: -13.1 | E68: 93.95 | F68: 1127.43 | G68: 159.56 | H68: 337.97 | I68: 468.17 | J68: 411.28 | K68: 0 | L68: 414.2 | M68: 0 | N68: 79.35 | O68: 3994.02
B69: 6270.000 - Electrical Repairs/Supplies | C69: 638.33 | D69: 337.02 | E69: 713.13 | F69: 858.75 | G69: 964.12 | H69: 70.87 | I69: 629.55 | J69: 0 | K69: 1551.23 | L69: 1045.33 | M69: 0 | N69: 1464.04 | O69: 8272.37
B70: 6272.000 - Small Tools | C70: 56.01 | D70: 1.93 | E70: 419.43 | F70: 205.76 | G70: 140.23 | H70: 0 | I70: 60.56 | J70: 58 | K70: 28.96 | L70: 48.3 | M70: 0 | N70: 970.14 | O70: 1989.32
B71: 6273.000 - Keys & Locks | C71: 0 | D71: 0 | E71: 0 | F71: 0 | G71: 0 | H71: 0 | I71: 0 | J71: 295.21 | K71: 0 | L71: 0 | M71: 0 | N71: 0 | O71: 295.21
B72: 6330.000 - Window and Door Repairs | C72: 0 | D72: 0 | E72: 0 | F72: 0 | G72: 0 | H72: 0 | I72: 330.42 | J72: 1425 | K72: 0 | L72: 0 | M72: 0 | N72: 0 | O72: 1755.42
B73: 6350.000 - Floor Clean & Repair | C73: 1780 | D73: 630 | E73: 1274.86 | F73: 1380 | G73: 0 | H73: 990 | I73: 240 | J73: 720 | K73: 0 | L73: 1724.58 | M73: 0 | N73: 0 | O73: 8739.44
B74: 6352.000 - Housekeeping/Apt Cleaning | C74: 2939.57 | D74: 5245.68 | E74: 578.15 | F74: 5491.14 | G74: 2359.69 | H74: 184.11 | I74: 3487.62 | J74: 260 | K74: 1006.78 | L74: 8314.81 | M74: 1613.11 | N74: 1529.57 | O74: 33010.23
... B76: 6355.000 - General Interior Repairs | C76: 702.73 | D76: 98.01 | E76: 317.21 | F76: 135.11 | G76: 225.46 | H76: 671.27 | I76: 133.53 | J76: 53.45 | K76: 3.55 | L76: 110.88 | M76: 0 | N76: 14.43 | O76: 2465.63
A77: Repairs and Maintenance | B77: TOTAL REPAIRS & MAINTENANCE | C77: 12547.75 | D77: 11043.97 | E77: 7773.59 | F77: 13871.03 | G77: 7798.08 | H77: 3678.82 | I77: 10590.82 | J77: 5122.94 | K77: 6484.99 | L77: 15951.23 | M77: 3807.09 | N77: 4316.68 | O77: 102986.99
B79: PAYROLL
B80: 6410.000 - Payroll - Administrative | C80: 37698.61 | D80: 24120.62 | E80: 28411.2 | F80: 22763.65 | G80: 20092.13 | H80: 20345.8 | I80: 38961.19 | J80: 21019.55 | K80: 35094.67 | L80: 21016.71 | M80: 21084.36 | N80: 30392.28 | O80: 321000.77
B81: 6410.700 - Payroll Rent Credit | C81: -400.29 | D81: 1323.03 | E81: 1583.33 | F81: 727.44 | G81: 677.42 | H81: 654.11 | I81: 880.52 | J81: 650 | K81: 1104.52 | L81: 1709.04 | M81: 2154.52 | N81: 2398.07 | O81: 13461.71
B82: 6460.000 - Group Health Insurance | C82: 532.74 | D82: 532.74 | E82: 0 | F82: 0 | G82: 0 | H82: 0 | I82: 0 | J82: 0 | K82: 1434.84 | L82: 1454.11 | M82: 1473.91 | N82: 1475.64 | O82: 6903.98
B83: 6470.000 - Worker’s Compensation | C83: 215 | D83: 139.71 | E83: 185.5 | F83: 114.79 | G83: 115.12 | H83: 114.61 | I83: 216.7 | J83: 116.77 | K83: 224.74 | L83: 125.86 | M83: 121.6 | N83: 183.65 | O83: 1874.05
B84: 6480.000 - Drug Screening | C84: 0 | D84: 0 | E84: 0 | F84: 109.02 | G84: 0 | H84: 109.02 | I84: 68.77 | J84: 0 | K84: 0 | L84: 0 | M84: 0 | N84: 0 | O84: 286.81
A85: Payroll & Benefits | B85: TOTAL PAYROLL | C85: 38046.06 | D85: 26116.1 | E85: 30180.03 | F85: 23714.9 | G85: 20884.67 | H85: 21223.54 | I85: 40127.18 | J85: 21786.32 | K85: 37858.77 | L85: 24305.72 | M85: 24834.39 | N85: 34449.64 | O85: 343527.32
B87: TAXES AND INSURANCE
A88: Property Insurance | B88: 6510.000 - Insurance | C88: 5687.11 | D88: 5687.11 | E88: 5687.11 | F88: 5638.79 | G88: 5638.79 | H88: 5638.79 | I88: 5638.79 | J88: 5638.79 | K88: 5638.79 | L88: 5638.79 | M88: 5638.79 | N88: 5638.79 | O88: 67810.44
A89: Real Estate Taxes | B89: 6520.000 - Ad Valorem (Property) Taxes | C89: 27546.94 | D89: 27546.94 | E89: 27546.94 | F89: 27546.94 | G89: 27546.94 | H89: 27546.94 | I89: 75358.51 | J89: 75358.51 | K89: 75358.51 | L89: 41474.82 | M89: 41474.82 | N89: 41474.82 | O89: 515781.63
A90: Real Estate Taxes | B90: 6530.000 - Other Taxes | C90: 600 | D90: 0 | E90: 0 | F90: 0 | G90: 0 | H90: 0 | I90: 0 | J90: 0 | K90: 0 | L90: 0 | M90: 0 | N90: 0 | O90: 600
B91: TOTAL TAXES AND INSURANCE | C91: 33834.05 | D91: 33234.05 | E91: 33234.05 | F91: 33185.73 | G91: 33185.73 | H91: 33185.73 | I91: 80997.3 | J91: 80997.3 | K91: 80997.3 | L91: 47113.61 | M91: 47113.61 | N91: 47113.61 | O91: 584192.07
B93: MANAGEMENT FEES
B94: 6540.000 - Management Fees | C94: 11335.32 | D94: 11200.85 | E94: 10791.36 | F94: 11294.61 | G94: 10117.28 | H94: 10538.48 | I94: 10991.99 | J94: 11258.63 | K94: 10688.7 | L94: 11472.37 | M94: 11342.84 | N94: 11178.99 | O94: 132211.42
A95: Management Fees | B95: TOTAL MANAGEMENT FEES | C95: 11335.32 | D95: 11200.85 | E95: 10791.36 | F95: 11294.61 | G95: 10117.28 | H95: 10538.48 | I95: 10991.99 | J95: 11258.63 | K95: 10688.7 | L95: 11472.37 | M95: 11342.84 | N95: 11178.99 | O95: 132211.42
B97: ADMINISTRATIVE EXPENSE
B98: 6600.000 - Eviction Costs | C98: 422 | D98: 750 | E98: 342 | F98: 316 | G98: 1174 | H98: 96 | I98: 660 | J98: 164 | K98: 1588 | L98: 473 | M98: 353.98 | N98: 458 | O98: 6796.98
B99: 6605.000 - Utility Billing | C99: 526.68 | D99: 526.68 | E99: 526.68 | F99: 526.68 | G99: 549.67 | H99: 549.67 | I99: 549.67 | J99: 549.67 | K99: 549.67 | L99: 549.67 | M99: 549.67 | N99: 549.67 | O99: 6504.08
B100: 6606.000 - Tenant Liability Insurance | C100: 2610 | D100: 2535 | E100: 2625 | F100: 0 | G100: 5400 | H100: 2640 | I100: 2670 | J100: 2745 | K100: 2700 | L100: 2655 | M100: 2640 | N100: 2670 | O100: 31890
B101: 6610.000 - Resident Screening | C101: 336.49 | D101: 336.49 | E101: 336.49 | F101: 336.49 | G101: 353.21 | H101: 353.21 | I101: 353.21 | J101: 353.21 | K101: 353.21 | L101: 418 | M101: 0 | N101: 836 | O101: 4366.01
B102: 6616.000 - Bank Fees | C102: 2187.73 | D102: 3735.54 | E102: 2317.05 | F102: 2210.47 | G102: 2333.98 | H102: 2324.68 | I102: 2550.79 | J102: -823.82 | K102: 1131.59 | L102: 3757.06 | M102: 2414.35 | N102: 2383.83 | O102: 26523.25
B103: 6620.000 - Office Supplies and Equipment | C103: 316.25 | D103: 0 | E103: 421.66 | F103: 204.37 | G103: 0 | H103: 0 | I103: 552.37 | J103: 109.08 | K103: 1042.83 | L103: 771.17 | M103: 51.27 | N103: 1328.32 | O103: 4797.32
B104: 6621.000 - Answering Service | C104: 100.64 | D104: 100.64 | E104: 100.64 | F104: 100.64 | G104: 100.77 | H104: 100.77 | I104: 100.77 | J104: 97.09 | K104: 97.09 | L104: 97.09 | M104: 97.09 | N104: 97.09 | O104: 1190.32
B105: 6622.000 - Uniforms | C105: 0 | D105: 0 | E105: 0 | F105: 527 | G105: 20.79 | H105: 0 | I105: 722.44 | J105: 0 | K105: 0 | L105: 117.68 | M105: 0 | N105: 0 | O105: 1387.91
B106: 6625.000 - Data Processing and Software | C106: 2264.57 | D106: 3064.14 | E106: 2399.09 | F106: 2348.72 | G106: 3004.04 | H106: 2405.18 | I106: 2531.81 | J106: 3323.6 | K106: 3328.81 | L106: 2726.75 | M106: 2563.83 | N106: 2843.45 | O106: 32803.99
B107: 6626.000 - IT Support Website | C107: 401.35 | D107: 401.35 | E107: 401.35 | F107: 402.79 | G107: 402.79 | H107: 402.79 | I107: 402.79 | J107: 402.79 | K107: 402.79 | L107: 444.51 | M107: 444.51 | N107: 498.95 | O107: 5008.76
B108: 6630.000 - Postage, Courier, and Freight | C108: 0 | D108: 0 | E108: 0 | F108: 0 | G108: 0 | H108: 12.85 | I108: 0 | J108: 0 | K108: 0 | L108: 41.05 | M108: 0 | N108: 0 | O108: 53.9
B109: 6635.000 - Meetings and Training Classes | C109: 47.66 | D109: 47.66 | E109: 47.66 | F109: 47.66 | G109: 50.16 | H109: 50.16 | I109: 107.03 | J109: 50.16 | K109: 50.16 | L109: 50.16 | M109: 50.16 | N109: 50.16 | O109: 648.79
... B113: 6670.000 - Meals & Entertainment | C113: 0 | D113: 0 | E113: 0 | F113: 0 | G113: 208.84 | H113: 243.86 | I113: 0 | J113: 0 | K113: 168.34 | L113: 9.71 | M113: 0 | N113: 63 | O113: 693.75
...

Sheet RR
A1: Knightvest Management LLC - Lydian
A2: RENT ROLL DETAIL
A3: 03/31/2026 05:06 PM
A4: As of Date: 03/31/2026
A5: Parameters: Properties: - all subproperties-; Show All Unit Designations or Filter by: ALL; Subjournals: ALL; Sort by: Unit; Report Type: Details + Summary; Exclude Formers?: Yes; Show Unit Rent as: Market Rent; Hide all PII Data?: No
A6: Resh ID | B6: Lease ID | C6: Unit | D6: Floorplan | E6: Unit Designation | F6: SQFT | G6: Unit/Lease Status | H6: Name | I6: Move-In | J6: Move-Out | K6: Lease Start | L6: Lease End | M6: Market Rent | N6: Sub Journal | O6: Required Deposit | P6: Dep On Hand | Q6: Balance | R6: Lease Rent | S6: RENT | T6: VALETTRASH | U6: TRASHREIMB | V6: GASREIMB | W6: UTILITY | X6: PESTREIMNB | Y6: RENTERSINS | Z6: SMARTHOME | AA6: PARKING | AB6: PETRENT | AC6: SHRTTERM | AD6: EMPLCRED | AE6: CONC/SPECL | AF6: CARPORT | AG6: MTOM | AH6: GARAGE | AI6: CORPEMPLCRED | AJ6: Total Billing | AN6: Concessions | AS6: Investment Year | AT6: 3 | AU6: 4 | AW6: Investment Year | AX6: 3 | AY6: 4
A7: 40704 | B7: 41133 | C7: 1101 | D7: B1T | E7: N/A | F7: 1080 | G7: Occupied | H7: Gervais, Kenneth | I7: 10/28/2024 | K7: 10/28/2025 | L7: 10/27/2026 | M7: 1940 | N7: RESIDENT | O7: 0 | P7: 0 | Q7: 0 | R7: 2085 | S7: 2085 | T7: 25 | U7: 8 | V7: 5 | W7: 5 | X7: 3 | Y7: 18 | Z7: 25 | AA7: 0 | AB7: 0 | AC7: 0 | AD7: 0 | AE7: 0 | AF7: 0 | AG7: 0 | AH7: 0 | AI7: 0 | AJ7: 2174 | AN7: Jan | AO7: -1000 | AS7: Year Ending | AT7: 45747 | AU7: 46112 | AW7: Year Ending | AX7: 45747 | AY7: 46112 | BB7: 2 | BC7: 3 | BD7: 4 | BE7: 5 | BF7: 6 | BG7: 7 | BH7: 8 | BI7: 9 | BJ7: 10
A8: 40418 | B8: 41220 | C8: 1102 | D8: A2T | E8: N/A | F8: 690 | G8: Occupied | H8: Cornelius, Erica | I8: 03/28/2023 | K8: 03/25/2026 | L8: 03/24/2027 | M8: 1515 | N8: RESIDENT | O8: 0 | P8: 0 | Q8: -25 | R8: 1683 | S8: 1683 | T8: 25 | U8: 8 | V8: 5 | W8: 5 | X8: 3 | Y8: 18 | Z8: 25 | AA8: 0 | AB8: 0 | AC8: 0 | AD8: 0 | AE8: 0 | AF8: 0 | AG8: 0 | AH8: 0 | AI8: 0 | AJ8: 1772 | AN8: Feb | AO8: -5460 | AS8: Annual Base Rent | AT8: 5084648.4 | AU8: 5221028.7 | AW8: Annual OpEx | AX8: 1653335.1 | AY8: 1714345.3 | BB8: 45382 | BC8: 45747 | BD8: 46112 | BE8: 46477 | BF8: 46843 | BG8: 47208 | BH8: 47573 | BI8: 47938 | BJ8: 48304
A9: 40756 | B9: 41142 | C9: 1103 | D9: A2T | E9: N/A | F9: 690 | G9: Occupied | H9: Ortiz Alvarez, Fabian | I9: 11/30/2024 | K9: 11/29/2025 | L9: 05/28/2026 | M9: 1515 | N9: RESIDENT | O9: 0 | P9: 0 | Q9: 0 | R9: 1612 | S9: 1612 | T9: 25 | U9: 8 | V9: 5 | W9: 5 | X9: 3 | Y9: 18 | Z9: 0 | AA9: 0 | AB9: 0 | AC9: 75 | AD9: 0 | AE9: 0 | AF9: 0 | AG9: 0 | AH9: 0 | AI9: 0 | AJ9: 1751 | AN9: March | AO9: -10332.5 | AS9: Monthly Base Rent | AT9: =AT8/12 -> 423720.7 | AU9: =AU8/12 -> 435085.72 | AW9: Multiplier | AX9: =+AT12 -> 0.25 | AY9: =+AU12 -> 0.75
A10: 40857 | B10: 41030 | C10: 1104 | D10: A2T | E10: N/A | F10: 690 | G10: Occupied | H10: Ismond, Diane | I10: 06/10/2025 | K10: 06/10/2025 | L10: 09/09/2026 | M10: 1515 | N10: RESIDENT | O10: 0 | P10: 0 | Q10: -318.7 | R10: 1565 | S10: 1565 | T10: 25 | U10: 8 | V10: 5 | W10: 5 | X10: 3 | Y10: 18 | Z10: 25 | AA10: 0 | AB10: 0 | AC10: 0 | AD10: 0 | AE10: 0 | AF10: 0 | AG10: 0 | AH10: 0 | AI10: 0 | AJ10: 1654 | AN10: Quarterly | AO10: =SUM(AO7:AO9) -> -16792.5 | AS10: % Occ. | AT10: 1 | AU10: 1 | AW10: UW OpEx | AY10: =SUMPRODUCT(AX8:AY8,AX9:AY9) -> 1699092.7 | BA10: INCOME
A11: 40615 | B11: 40971 | C11: 1105 | D11: B1T | E11: N/A | F11: 1080 | G11: Occupied | H11: Harvey, Chauncey | I11: 04/11/2024 | K11: 05/10/2025 | L11: 05/08/2026 | M11: 1940 | N11: RESIDENT | O11: 0 | P11: 0 | Q11: -2305.39 | R11: 2100 | S11: 2100 | T11: 25 | U11: 8 | V11: 5 | W11: 5 | X11: 3 | Y11: 18 | Z11: 25 | AA11: 0 | AB11: 0 | AC11: 0 | AD11: 0 | AE11: 0 | AF11: 0 | AG11: 0 | AH11: 0 | AI11: 0 | AJ11: 2189 | AN11: Yearly | AO11: =+AO10*4 -> -67170 | AS11: Rent/Occ. Unit | AT11: =AT9/(209*AT10) -> 2027.3718 | AU11: =AU9/(209*AU10) -> 2081.7499 | AW11: Actual OpEx | AY11: =#REF! -> #REF! | BA11: Potential Rental Revenue | BB11: 5003799.2 | BC11: 5149491.3 | BD11: 5279975.4 | BE11: 5409303.2 | BF11: 5558631.9 | BG11: 5725390.8 | BH11: 5897152.5 | BI11: 6074067.1 | BJ11: 6256289.1
A12: 40525 | B12: 41101 | C12: 1106 | D12: A1T | E12: N/A | F12: 630 | G12: Occupied | H12: Anthony, Jacques | I12: 10/28/2023 | K12: 10/28/2025 | L12: 10/27/2026 | M12: 1485 | N12: RESIDENT | O12: 0 | P12: 0 | Q12: 0 | R12: 1650 | S12: 1650 | T12: 25 | U12: 8 | V12: 5 | W12: 5 | X12: 3 | Y12: 18 | Z12: 0 | AA12: 0 | AB12: 0 | AC12: 0 | AD12: 0 | AE12: 0 | AF12: 0 | AG12: 0 | AH12: 0 | AI12: 0 | AJ12: 1714 | AS12: Multiplier | AT12: 0.25 | AU12: 0.75 | AW12: Variance % | AY12: =(AY11/AY10)-1 -> #REF! | BA12: Loss To Lease | BB12: -89597.677 | BC12: -64842.873 | BD12: -58946.768 | BE12: -59824.745 | BF12: -71297.891 | BG12: -76873.487 | BH12: -79179.692 | BI12: -81555.082 | BJ12: -84001.735
A13: 0 | B13: 0 | C13: 1108 | D13: B1T | E13: N/A | F13: 1080 | G13: Vacant-Leased | H13: VACANT | M13: 1940 | O13: 0 | P13: 0 | Q13: 0 | R13: 0 | S13: 0 | T13: 0 | U13: 0 | V13: 0 | W13: 0 | X13: 0 | Y13: 0 | Z13: 0 | AA13: 0 | AB13: 0 | AC13: 0 | AD13: 0 | AE13: 0 | AF13: 0 | AG13: 0 | AH13: 0 | AI13: 0 | AJ13: 0 | AS13: Average UW Rent | AU13: =SUMPRODUCT(AT12:AU12,AT11:AU11) -> 2068.1553 | BA13: Scheduled Base Rental Revenue | BB13: 4914201.6 | BC13: 5084648.4 | BD13: 5221028.7 | BE13: 5349478.5 | BF13: 5487334 | BG13: 5648517.3 | BH13: 5817972.9 | BI13: 5992512 | BJ13: 6172287.4
A14: 40950 | B14: 41196 | C14: 1108 | D14: B1T | E14: N/A | F14: 1080 | G14: Applicant | H14: Gray, Reece | I14: 04/15/2026 | K14: 04/15/2026 | L14: 04/14/2027 | M14: 0 | N14: RESIDENT | O14: 0 | P14: 0 | Q14: 0 | R14: 1940 | S14: 1940 | T14: 25 | U14: 8 | V14: 5 | W14: 5 | X14: 3 | Y14: 18 | Z14: 25 | AA14: 0 | AB14: 0 | AC14: 0 | AD14: 0 | AE14: 0 | AF14: 0 | AG14: 0 | AH14: 0 | AI14: 0 | AJ14: 2029 | AS14: In-Place Rent | AU14: =AVERAGEIF(T7:T215,">0") -> 25 | AV14: =(AU14/AU13)-1 -> -0.98791193 | BA14: Other Income | BB14: 388846.63 | BC14: 400512.03 | BD14: 412527.39 | BE14: 424903.21 | BF14: 437650.31 | BG14: 450779.82 | BH14: 464303.21 | BI14: 478232.31 | BJ14: 492579.28
A15: 40607 | B15: 41057 | C15: 1109 | D15: A1T | E15: N/A | F15: 630 | G15: Occupied | H15: Whiteman, Elizabeth | I15: 03/08/2024 | K15: 05/16/2025 | L15: 05/22/2026 | M15: 1485 | N15: RESIDENT | O15: 0 | P15: 0 | Q15: -1785.76 | R15: 1625 | S15: 1625 | T15: 25 | U15: 8 | V15: 5 | W15: 5 | X15: 3 | Y15: 18 | Z15: 25 | AA15: 0 | AB15: 0 | AC15: 0 | AD15: 0 | AE15: 0 | AF15: 0 | AG15: 0 | AH15: 0 | AI15: 0 | AJ15: 1714 | AS15: Market Rent | AU15: =AVERAGEIF(P7:P215,">0") -> #DIV/0! | AV15: =(AU14/AU15)-1 -> #DIV/0! | BA15: Potential Gross Income | BB15: 5303048.2 | BC15: 5485160.5 | BD15: 5633556 | BE15: 5774381.7 | BF15: 5924984.3 | BG15: 6099297.1 | BH15: 6282276.1 | BI15: 6470744.3 | BJ15: 6664866.7
A16: 40607 | B16: 41244 | C16: 1109 | D16: A1T | E16: N/A | F16: 630 | G16: Pending renewal | H16: Whiteman, Elizabeth | I16: 03/08/2024 | K16: 05/23/2026 | L16: 05/21/2027 | M16: 0 | N16: RESIDENT | O16: 0 | P16: 0 | Q16: 0 | R16: 1674 | S16: 1674 | T16: 25 | U16: 8 | V16: 5 | W16: 5 | X16: 3 | Y16: 18 | Z16: 25 | AA16: 0 | AB16: 0 | AC16: 0 | AD16: 0 | AE16: 0 | AF16: 0 | AG16: 0 | AH16: 0 | AI16: 0 | AJ16: 1763 | BA16: Minus: Vacancy | BB16: -245710.08 | BC16: -254232.42 | BD16: -261051.43 | BE16: -267473.92 | BF16: -274366.7 | BG16: -282425.87 | BH16: -290898.64 | BI16: -299625.6 | BJ16: -308614.37
A17: 40959 | B17: 41212 | C17: 1110 | D17: A2T | E17: N/A | F17: 690 | G17: Occupied | H17: Dennis, Ezzerianna | I17: 03/06/2026 | K17: 03/06/2026 | L17: 03/05/2027 | M17: 1515 | N17: RESIDENT | O17: 0 | P17: 0 | Q17: -4.7 | R17: 1515 | S17: 1515 | T17: 25 | U17: 8 | V17: 5 | W17: 5 | X17: 3 | Y17: 18 | Z17: 25 | AA17: 0 | AB17: 0 | AC17: 0 | AD17: 0 | AE17: 0 | AF17: 0 | AG17: 0 | AH17: 0 | AI17: 0 | AJ17: 1604 | BA17: Minus: Credit Loss | BB17: -24571.008 | BC17: -25423.242 | BD17: -26105.143 | BE17: -26747.392 | BF17: -27436.67 | BG17: -28242.587 | BH17: -29089.864 | BI17: -29962.56 | BJ17: -30861.437
A18: 40918 | B18: 41134 | C18: 1111 | D18: A1T | E18: N/A | F18: 630 | G18: Occupied | H18: Trinh, Sarah | I18: 11/01/2025 | K18: 11/01/2025 | L18: 11/02/2026 | M18: 1485 | N18: RESIDENT | O18: 0 | P18: 0 | Q18: 0 | R18: 1485 | S18: 1485 | T18: 25 | U18: 8 | V18: 5 | W18: 5 | X18: 3 | Y18: 18 | Z18: 0 | AA18: 0 | AB18: 0 | AC18: 0 | AD18: 0 | AE18: 0 | AF18: 0 | AG18: 0 | AH18: 0 | AI18: 0 | AJ18: 1549 | BA18: Minus: Model Unit | BB18: 0 | BC18: 0 | BD18: 0 | BE18: 0 | BF18: 0 | BG18: 0 | BH18: 0 | BI18: 0 | BJ18: 0
A19: 40760 | B19: 41158 | C19: 1112 | D19: A3T | E19: N/A | F19: 750 | G19: Occupied | H19: Alanis, Victor | I19: 02/01/2025 | K19: 01/31/2026 | L19: 04/29/2027 | M19: 1610 | N19: RESIDENT | O19: 0 | P19: 0 | Q19: 0 | R19: 1665 | S19: 1665 | T19: 25 | U19: 8 | V19: 5 | W19: 5 | X19: 3 | Y19: 18 | Z19: 0 | AA19: 50 | AB19: 35 | AC19: 0 | AD19: 0 | AE19: 0 | AF19: 0 | AG19: 0 | AH19: 0 | AI19: 0 | AJ19: 1814 | BA19: Minus: Concessions Initial Lease Up | BB19: 0 | BC19: 0 | BD19: 0 | BE19: 0 | BF19: 0 | BG19: 0 | BH19: 0 | BI19: 0 | BJ19: 0
A20: 40897 | B20: 41097 | C20: 1113 | D20: A1T | E20: N/A | F20: 630 | G20: Occupied | H20: Voss, Neil | I20: 09/02/2025 | K20: 09/02/2025 | L20: 11/02/2026 | M20: 1485 | N20: RESIDENT | O20: 0 | P20: 0 | Q20: 0 | R20: 1515 | S20: 1515 | T20: 25 | U20: 8 | V20: 5 | W20: 5 | X20: 3 | Y20: 18 | Z20: 25 | AA20: 0 | AB20: 0 | AC20: 0 | AD20: 0 | AE20: 0 | AF20: 0 | AG20: 0 | AH20: 0 | AI20: 0 | AJ20: 1604 | AS20: Emp Credit | BA20: Minus: Concessions Ongoing | BB20: -207889.1 | BC20: -53510.637 | BD20: -54879.073 | BE20: -56220.361 | BF20: -57745.273 | BG20: -59477.631 | BH20: -61261.96 | BI20: -63099.819 | BJ20: -64992.813
A21: 40905 | B21: 41110 | C21: 1114 | D21: A5 | E21: N/A | F21: 780 | G21: Occupied | H21: Stuart, Breyana | I21: 10/06/2025 | K21: 10/06/2025 | L21: 11/05/2026 | M21: 1695 | N21: RESIDENT | O21: 0 | P21: 0 | Q21: 0 | R21: 1695 | S21: 1695 | T21: 25 | U21: 8 | V21: 5 | W21: 5 | X21: 3 | Y21: 18 | Z21: 0 | AA21: 0 | AB21: 0 | AC21: 0 | AD21: 0 | AE21: 0 | AF21: 0 | AG21: 0 | AH21: 0 | AI21: 0 | AJ21: 1759 | AS21: Concessions | BA21: Effective Gross Income | BB21: 4824878 | BC21: 5151994.2 | BD21: 5291520.4 | BE21: 5423940 | BF21: 5565435.6 | BG21: 5729151.1 | BH21: 5901025.6 | BI21: 6078056.4 | BJ21: 6260398.1
A22: 40919 | B22: 41135 | C22: 1115 | D22: E1T | E22: N/A | F22: 540 | G22: Occupied | H22: Toscano, Ariana | I22: 11/14/2025 | K22: 11/14/2025 | L22: 04/01/2026 | M22: 1365 | N22: RESIDENT | O22: 0 | P22: 0 | Q22: 0 | R22: 1365 | S22: 1365 | T22: 25 | U22: 8 | V22: 5 | W22: 5 | X22: 3 | Y22: 18 | Z22: 0 | AA22: 0 | AB22: 0 | AC22: 200 | AD22: 0 | AE22: 0 | AF22: 0 | AG22: 0 | AH22: 0 | AI22: 0 | AJ22: 1629 | AS22: Oct | AT22: 0
A23: 40743 | B23: 41129 | C23: 1116 | D23: B1T | E23: N/A | F23: 1080 | G23: Occupied | H23: mwansa, bwalya | I23: 11/29/2024 | K23: 11/29/2025 | L23: 11/27/2026 | M23: 1940 | N23: RESIDENT | O23: 0 | P23: 0 | Q23: 0 | R23: 2148 | S23: 2148 | T23: 25 | U23: 8 | V23: 5 | W23: 5 | X23: 3 | Y23: 18 | Z23: 0 | AA23: 0 | AB23: 0 | AC23: 0 | AD23: 0 | AE23: 0 | AF23: 0 | AG23: 0 | AH23: 0 | AI23: 0 | AJ23: 2212 | AS23: Nov | AT23: -14200 | BA23: OPERATING EXPENSES
A24: 40964 | B24: 41218 | C24: 1117 | D24: A1T | E24: N/A | F24: 630 | G24: Occupied | H24: Brustad, Grace | I24: 03/10/2026 | K24: 03/10/2026 | L24: 03/08/2027 | M24: 1485 | N24: RESIDENT | O24: 0 | P24: 0 | Q24: 0 | R24: 1485 | S24: 1485 | T24: 25 | U24: 8 | V24: 5 | W24: 5 | X24: 3 | Y24: 18 | Z24: 25 | AA24: 0 | AB24: 0 | AC24: 0 | AD24: 0 | AE24: 0 | AF24: 0 | AG24: 0 | AH24: 0 | AI24: 0 | AJ24: 1574 | AS24: Dec | AT24: -2880 | BA24: Payroll | BB24: 358873 | BC24: 369639.19 | BD24: 380728.37 | BE24: 392150.22 | BF24: 403914.72 | BG24: 416032.16 | BH24: 428513.13 | BI24: 441368.52 | BJ24: 454609.58
A25: 40793 | B25: 40934 | C25: 1118 | D25: E1T | E25: N/A | F25: 540 | G25: Occupied | H25: Newman, Ashley | I25: 02/27/2025 | K25: 02/27/2025 | L25: 04/27/2026 | M25: 1365 | N25: RESIDENT | O25: 0 | P25: 0 | Q25: 0 | R25: 1475 | S25: 1475 | T25: 25 | U25: 8 | V25: 5 | W25: 5 | X25: 3 | Y25: 18 | Z25: 25 | AA25: 0 | AB25: 0 | AC25: 0 | AD25: 0 | AE25: 0 | AF25: 0 | AG25: 0 | AH25: 0 | AI25: 0 | AJ25: 1564 | AS25: Quarterly | AT25: =SUM(AT22:AT24) -> -17080 | BA25: Employee Units | BB25: 0 | BC25: 0 | BD25: 0 | BE25: 0 | BF25: 0 | BG25: 0 | BH25: 0 | BI25: 0 | BJ25: 0
A26: 40793 | B26: 41199 | C26: 1118 | D26: E1T | E26: N/A | F26: 540 | G26: Pending renewal | H26: Newman, Ashley | I26: 02/27/2025 | K26: 04/28/2026 | L26: 06/28/2027 | M26: 0 | N26: RESIDENT | O26: 0 | P26: 0 | Q26: 0 | R26: 1475 | S26: 1475 | T26: 25 | U26: 8 | V26: 5 | W26: 5 | X26: 3 | Y26: 18 | Z26: 25 | AA26: 0 | AB26: 0 | AC26: 0 | AD26: 0 | AE26: 0 | AF26: 0 | AG26: 0 | AH26: 0 | AI26: 0 | AJ26: 1564 | AS26: Yearly | AT26: =+AT25*4 -> -68320 | BA26: Marketing | BB26: 42075 | BC26: 43337.25 | BD26: 44637.368 | BE26: 45976.489 | BF26: 47355.783 | BG26: 48776.457 | BH26: 50239.75 | BI26: 51746.943 | BJ26: 53299.351
A27: 40640 | B27: 40997 | C27: 1119 | D27: B2T | E27: N/A | F27: 1144 | G27: Occupied | H27: Castillo, Isabella | I27: 05/12/2025 | K27: 05/12/2025 | L27: 05/11/2026 | M27: 1960 | N27: RESIDENT | O27: 0 | P27: 0 | Q27: 0 | R27: 2065 | S27: 2065 | T27: 25 | U27: 8 | V27: 5 | W27: 5 | X27: 3 | Y27: 18 | Z27: 0 | AA27: 50 | AB27: 0 | AC27: 0 | AD27: 0 | AE27: 0 | AF27: 0 | AG27: 0 | AH27: 0 | AI27: 0 | AJ27: 2179 | BA27: General & Admin. | BB27: 105451.4 | BC27: 108614.94 | BD27: 111873.39 | BE27: 115229.59 | BF27: 118686.48 | BG27: 122247.07 | BH27: 125914.49 | BI27: 129691.92 | BJ27: 133582.68
A28: 40640 | B28: 41222 | C28: 1119 | D28: B2T | E28: N/A | F28: 1144 | G28: Pending renewal | H28: Castillo, Isabella | I28: 05/12/2025 | K28: 05/12/2026 | L28: 07/12/2027 | M28: 0 | N28: RESIDENT | O28: 0 | P28: 0 | Q28: 0 | R28: 2065 | S28: 2065 | T28: 25 | U28: 8 | V28: 5 | W28: 5 | X28: 3 | Y28: 18 | Z28: 25 | AA28: 0 | AB28: 0 | AC28: 0 | AD28: 0 | AE28: 0 | AF28: 0 | AG28: 0 | AH28: 0 | AI28: 0 | AJ28: 2154 | BA28: Miscellaneous | BB28: 0 | BC28: 0 | BD28: 0 | BE28: 0 | BF28: 0 | BG28: 0 | BH28: 0 | BI28: 0 | BJ28: 0
A29: 40633 | B29: 41169 | C29: 1120 | D29: B1T | E29: N/A | F29: 1080 | G29: Occupied | H29: Williams, Alexa | I29: 03/21/2025 | K29: 03/21/2026 | L29: 05/20/2027 | M29: 1940 | N29: RESIDENT | O29: 0 | P29: 0 | Q29: 0 | R29: 2085 | S29: 2085 | T29: 25 | U29: 8 | V29: 5 | W29: 5 | X29: 3 | Y29: 18 | Z29: 25 | AA29: 0 | AB29: 35 | AC29: 0 | AD29: 0 | AE29: 0 | AF29: 0 | AG29: 0 | AH29: 0 | AI29: 0 | AJ29: 2209 | BA29: Landscaping/Grounds | BB29: 37080 | BC29: 38192.4 | BD29: 39338.172 | BE29: 40518.317 | BF29: 41733.867 | BG29: 42985.883 | BH29: 44275.459 | BI29: 45603.723 | BJ29: 46971.835
A30: 40961 | B30: 41215 | C30: 1121 | D30: A3T | E30: N/A | F30: 750 | G30: Occupied | H30: Gastelum - EMP, Xavier | I30: 03/28/2026 | K30: 03/28/2026 | L30: 06/30/2027 | M30: 1610 | N30: RESIDENT | O30: 0 | P30: 0 | Q30: 0 | R30: 1610 | S30: 1610 | T30: 25 | U30: 8 | V30: 5 | W30: 5 | X30: 3 | Y30: 18 | Z30: 25 | AA30: 0 | AB30: 0 | AC30: 0 | AD30: 0 | AE30: 0 | AF30: 0 | AG30: 0 | AH30: 0 | AI30: -600 | AJ30: 1099 | BA30: Make-ready | BB30: 0 | BC30: 0 | BD30: 0 | BE30: 0 | BF30: 0 | BG30: 0 | BH30: 0 | BI30: 0 | BJ30: 0
A31: 40909 | B31: 41117 | C31: 1122 | D31: E1T | E31: N/A | F31: 540 | G31: Occupied | H31: Nurse, Kiaya | I31: 10/07/2025 | K31: 10/07/2025 | L31: 11/06/2026 | M31: 1365 | N31: RESIDENT | O31: 0 | P31: 0 | Q31: -2404.75 | R31: 1275 | S31: 1275 | T31: 25 | U31: 8 | V31: 5 | W31: 5 | X31: 3 | Y31: 18 | Z31: 0 | AA31: 50 | AB31: 0 | AC31: 0 | AD31: 0 | AE31: 0 | AF31: 0 | AG31: 0 | AH31: 0 | AI31: 0 | AJ31: 1389 | BA31: Repairs & Maint. | BB31: 96871.5 | BC31: 99777.645 | BD31: 102770.97 | BE31: 105854.1 | BF31: 109029.73 | BG31: 112300.62 | BH31: 115669.64 | BI31: 119139.73 | BJ31: 122713.92
A32: 0 | B32: 0 | C32: 1123 | D32: A6T | E32: N/A | F32: 840 | G32: Vacant | H32: VACANT | M32: 1815 | O32: 0 | P32: 0 | Q32: 0 | R32: 0 | S32: 0 | T32: 0 | U32: 0 | V32: 0 | W32: 0 | X32: 0 | Y32: 0 | Z32: 0 | AA32: 0 | AB32: 0 | AC32: 0 | AD32: 0 | AE32: 0 | AF32: 0 | AG32: 0 | AH32: 0 | AI32: 0 | AJ32: 0 | BA32: Janitorial | BB32: 0 | BC32: 0 | BD32: 0 | BE32: 0 | BF32: 0 | BG32: 0 | BH32: 0 | BI32: 0 | BJ32: 0
A33: 40479 | B33: 41075 | C33: 1124 | D33: A1T | E33: N/A | F33: 630 | G33: Occupied | H33: Hopkins, Alyssa | I33: 08/01/2025 | K33: 08/01/2025 | L33: 07/30/2026 | M33: 1485 | N33: RESIDENT | O33: 0 | P33: 0 | Q33: 0 | R33: 1535 | S33: 1535 | T33: 25 | U33: 8 | V33: 5 | W33: 5 | X33: 3 | Y33: 18 | Z33: 0 | AA33: 0 | AB33: 0 | AC33: 0 | AD33: 0 | AE33: 0 | AF33: 0 | AG33: 0 | AH33: 0 | AI33: 0 | AJ33: 1599 | BA33: Security/Life Safety | BB33: 0 | BC33: 0 | BD33: 0 | BE33: 0 | BF33: 0 | BG33: 0 | BH33: 0 | BI33: 0 | BJ33: 0
A34: 40520 | B34: 41108 | C34: 1125 | D34: A5T | E34: N/A | F34: 780 | G34: Occupied | H34: Acuna, Rafael | I34: 10/26/2023 | K34: 11/26/2025 | L34: 11/25/2026 | M34: 1695 | N34: RESIDENT | O34: 0 | P34: 0 | Q34: 0 | R34: 1921 | S34: 1921 | T34: 25 | U34: 8 | V34: 5 | W34: 5 | X34: 3 | Y34: 18 | Z34: 0 | AA34: 0 | AB34: 0 | AC34: 0 | AD34: 0 | AE34: 0 | AF34: 0 | AG34: 0 | AH34: 0 | AI34: 0 | AJ34: 1985 | BA34: Utilities | BB34: 214883.75 | BC34: 221330.26 | BD34: 227970.17 | BE34: 234809.28 | BF34: 241853.55 | BG34: 249109.16 | BH34: 256582.44 | BI34: 264279.91 | BJ34: 272208.31
A35: 40938 | B35: 41178 | C35: 1126 | D35: E1T | E35: N/A | F35: 540 | G35: Occupied | H35: Kadovik, Daria | I35: 02/06/2026 | K35: 02/06/2026 | L35: 02/05/2027 | M35: 1365 | N35: RESIDENT | O35: 0 | P35: 0 | Q35: -824.39 | R35: 1365 | S35: 1365 | T35: 25 | U35: 8 | V35: 5 | W35: 5 | X35: 3 | Y35: 18 | Z35: 25 | AA35: 0 | AB35: 35 | AC35: 0 | AD35: 0 | AE35: 0 | AF35: 0 | AG35: 0 | AH35: 0 | AI35: 0 | AJ35: 1489 | BA35: Insurance | BB35: 52760.72 | BC35: 54343.542 | BD35: 55973.848 | BE35: 57653.063 | BF35: 59382.655 | BG35: 61164.135 | BH35: 62999.059 | BI35: 64889.031 | BJ35: 66835.702
A36: 40885 | B36: 41078 | C36: 1127 | D36: A1T | E36: N/A | F36: 630 | G36: Occupied | H36: Nop, Donna | I36: 07/18/2025 | K36: 07/18/2025 | L36: 07/16/2026 | M36: 1485 | N36: RESIDENT | O36: 0 | P36: 0 | Q36: 0 | R36: 1535 | S36: 1535 | T36: 25 | U36: 8 | V36: 5 | W36: 5 | X36: 3 | Y36: 18 | Z36: 0 | AA36: 0 | AB36: 0 | AC36: 0 | AD36: 0 | AE36: 0 | AF36: 0 | AG36: 0 | AH36: 0 | AI36: 0 | AJ36: 1599 | BA36: Replacement Reserves | BB36: 0 | BC36: 0 | BD36: 0 | BE36: 0 | BF36: 0 | BG36: 0 | BH36: 0 | BI36: 0 | BJ36: 0
A37: 40762 | B37: 41076 | C37: 1128 | D37: B2T | E37: N/A | F37: 1144 | G37: Occupied | H37: Bernal, Cristina | I37: 08/30/2025 | K37: 08/30/2025 | L37: 08/28/2026 | M37: 1960 | N37: RESIDENT | O37: 0 | P37: 0 | Q37: -6.74 | R37: 2065 | S37: 2065 | T37: 25 | U37: 8 | V37: 5 | W37: 5 | X37: 3 | Y37: 18 | Z37: 0 | AA37: 0 | AB37: 0 | AC37: 0 | AD37: 0 | AE37: 0 | AF37: 0 | AG37: 0 | AH37: 0 | AI37: 0 | AJ37: 2129 | BA37: Misc #2 (GL Expense) | BB37: 0 | BC37: 0 | BD37: 0 | BE37: 0 | BF37: 0 | BG37: 0 | BH37: 0 | BI37: 0 | BJ37: 0
A38: 40924 | B38: 41149 | C38: 1129 | D38: B4T | E38: N/A | F38: 1240 | G38: Occupied | H38: Miller-Cruz - EMP, Anthony | I38: 02/07/2026 | K38: 02/07/2026 | L38: 06/30/2027 | M38: 2540 | N38: RESIDENT | O38: 0 | P38: 0 | Q38: -1904 | R38: 2540 | S38: 2540 | T38: 25 | U38: 8 | V38: 5 | W38: 5 | X38: 3 | Y38: 18 | Z38: 0 | AA38: 0 | AB38: 0 | AC38: 0 | AD38: -700 | AE38: 0 | AF38: 0 | AG38: 0 | AH38: 0 | AI38: 0 | AJ38: 1904 | BA38: RE Taxes | BB38: 555680.99 | BC38: 589300 | BD38: 618765 | BE38: 649703.25 | BF38: 682188.41 | BG38: 716297.83 | BH38: 752112.72 | BI38: 789718.36 | BJ38: 829204.28
A39: 40850 | B39: 41020 | C39: 1130 | D39: A3T | E39: N/A | F39: 750 | G39: Occupied | H39: Connell, Abbey | I39: 05/24/2025 | K39: 05/24/2025 | L39: 07/23/2026 | M39: 1610 | N39: RESIDENT | O39: 0 | P39: 0 | Q39: -770.5 | R39: 1665 | S39: 1665 | T39: 25 | U39: 8 | V39: 5 | W39: 5 | X39: 3 | Y39: 18 | Z39: 25 | AA39: 0 | AB39: 0 | AC39: 0 | AD39: 0 | AE39: 0 | AF39: 0 | AG39: 0 | AH39: 0 | AI39: 0 | AJ39: 1754 | BA39: Management Fee | BB39: 120621.95 | BC39: 128799.85 | BD39: 132288.01 | BE39: 135598.5 | BF39: 139135.89 | BG39: 143228.78 | BH39: 147525.64 | BI39: 151951.41 | BJ39: 156509.95
A40: 40849 | B40: 41019 | C40: 1131 | D40: A2T | E40: N/A | F40: 690 | G40: Occupied | H40: Wilson, Kaylie | I40: 06/28/2025 | K40: 06/28/2025 | L40: 06/29/2026 | M40: 1515 | N40: RESIDENT | O40: 0 | P40: 0 | Q40: -2092.5 | R40: 1565 | S40: 1565 | T40: 25 | U40: 8 | V40: 5 | W40: 5 | X40: 3 | Y40: 18 | Z40: 0 | AA40: 0 | AB40: 0 | AC40: 0 | AD40: 0 | AE40: 0 | AF40: 0 | AG40: 0 | AH40: 0 | AI40: 0 | AJ40: 1629 | BA40: Total Operating Expenses | BB40: 1584298.3 | BC40: 1653335.1 | BD40: 1714345.3 | BE40: 1777492.8 | BF40: 1843281.1 | BG40: 1912142.1 | BH40: 1983832.3 | BI40: 2058389.5 | BJ40: 2135935.6
A41: 40835 | B41: 41011 | C41: 1132 | D41: B1T | E41: N/A | F41: 1080 | G41: Occupied | H41: Crossley, Ryan | I41: 05/28/2025 | K41: 05/28/2025 | L41: 05/27/2026 | M41: 1940 | N41: RESIDENT | O41: 0 | P41: 0 | Q41: -1788.5 | R41: 2045 | S41: 2045 | T41: 25 | U41: 8 | V41: 5 | W41: 5 | X41: 3 | Y41: 18 | Z41: 0 | AA41: 50 | AB41: 0 | AC41: 0 | AD41: 0 | AE41: 0 | AF41: 0 | AG41: 0 | AH41: 0 | AI41: 0 | AJ41: 2159 | BA41: Operating Expenses % EGR | BB41: 0.32836028 | BC41: 0.32091168 | BD41: 0.32397972 | BE41: 0.32771247 | BF41: 0.33120158 | BG41: 0.33375662 | BH41: 0.33618433 | BI41: 0.33865917 | BJ41: 0.34118208
A42: 40835 | B42: 41248 | C42: 1132 | D42: B1T | E42: N/A | F42: 1080 | G42: Pending renewal | H42: Crossley, Ryan | I42: 05/28/2025 | K42: 05/28/2026 | L42: 05/27/2027 | M42: 0 | N42: RESIDENT | O42: 0 | P42: 0 | Q42: 0 | R42: 2106 | S42: 2106 | T42: 25 | U42: 8 | V42: 5 | W42: 5 | X42: 3 | Y42: 18 | Z42: 25 | AA42: 50 | AB42: 0 | AC42: 0 | AD42: 0 | AE42: 0 | AF42: 0 | AG42: 0 | AH42: 0 | AI42: 0 | AJ42: 2245 | BA42: Real Estate Taxes %/EGR | BB42: 0.11516996 | BC42: 0.11438289 | BD42: 0.1169352 | BE42: 0.11978437 | BF42: 0.12257592 | BG42: 0.12502687 | BH42: 0.12745458 | BI42: 0.12992942 | BJ42: 0.13245233
A43: 0 | B43: 0 | C43: 1133 | D43: A1T | E43: N/A | F43: 630 | G43: Vacant | H43: VACANT | M43: 1485 | O43: 0 | P43: 0 | Q43: 0 | R43: 0 | S43: 0 | T43: 0 | U43: 0 | V43: 0 | W43: 0 | X43: 0 | Y43: 0 | Z43: 0 | AA43: 0 | AB43: 0 | AC43: 0 | AD43: 0 | AE43: 0 | AF43: 0 | AG43: 0 | AH43: 0 | AI43: 0 | AJ43: 0
A44: 40953 | B44: 41202 | C44: 1134 | D44: E1T | E44: N/A | F44: 540 | G44: Occupied | H44: Cynova, Alec | I44: 02/24/2026 | K44: 02/24/2026 | L44: 02/22/2027 | M44: 1365 | N44: RESIDENT | O44: 0 | P44: 0 | Q44: 0 | R44: 1365 | S44: 1365 | T44: 25 | U44: 8 | V44: 5 | W44: 5 | X44: 3 | Y44: 18 | Z44: 25 | AA44: 0 | AB44: 0 | AC44: 0 | AD44: 0 | AE44: 0 | AF44: 0 | AG44: 0 | AH44: 0 | AI44: 0 | AJ44: 1454 | BA44: Net Operating Income | BB44: 3240579.7 | BC44: 3498659.1 | BD44: 3577175.1 | BE44: 3646447.2 | BF44: 3722154.5 | BG44: 3817009 | BH44: 3917193.3 | BI44: 4019666.8 | BJ44: 4124462.5
A45: 40907 | B45: 41115 | C45: 1135 | D45: E1T | E45: N/A | F45: 540 | G45: Occupied | H45: Sais, Monique | I45: 10/03/2025 | K45: 10/03/2025 | L45: 10/02/2026 | M45: 1365 | N45: RESIDENT | O45: 0 | P45: 0 | Q45: 0 | R45: 1275 | S45: 1275 | T45: 25 | U45: 8 | V45: 5 | W45: 5 | X45: 3 | Y45: 18 | Z45: 0 | AA45: 0 | AB45: 0 | AC45: 0 | AD45: 0 | AE45: 0 | AF45: 0 | AG45: 0 | AH45: 0 | AI45: 0 | AJ45: 1339
A46: 0 | B46: 0 | C46: 1136 | D46: A3T | E46: N/A | F46: 750 | G46: Vacant-Leased | H46: VACANT | M46: 1610 | O46: 0 | P46: 0 | Q46: 0 | R46: 0 | S46: 0 | T46: 0 | U46: 0 | V46: 0 | W46: 0 | X46: 0 | Y46: 0 | Z46: 0 | AA46: 0 | AB46: 0 | AC46: 0 | AD46: 0 | AE46: 0 | AF46: 0 | AG46: 0 | AH46: 0 | AI46: 0 | AJ46: 0
A47: 40971 | B47: 41232 | C47: 1136 | D47: A3T | E47: N/A | F47: 750 | G47: Applicant | H47: Amador - EMP, Ashley | I47: 04/04/2026 | K47: 04/04/2026 | L47: 06/30/2027 | M47: 0 | N47: RESIDENT | O47: 0 | P47: 0 | Q47: 0 | R47: 1610 | S47: 1610 | T47: 25 | U47: 8 | V47: 5 | W47: 5 | X47: 3 | Y47: 18 | Z47: 25 | AA47: 0 | AB47: 0 | AC47: 0 | AD47: -500 | AE47: 0 | AF47: 0 | AG47: 0 | AH47: 0 | AI47: 0 | AJ47: 1199
A48: 40937 | B48: 41177 | C48: 1137 | D48: B2T | E48: N/A | F48: 1144 | G48: Occupied | H48: Reyes Esquilin, Ian | I48: 03/06/2026 | K48: 03/06/2026 | L48: 03/05/2027 | M48: 1960 | N48: RESIDENT | O48: 0 | P48: 0 | Q48: 0 | R48: 1960 | S48: 1960 | T48: 25 | U48: 8 | V48: 5 | W48: 5 | X48: 3 | Y48: 0 | Z48: 25 | AA48: 50 | AB48: 0 | AC48: 0 | AD48: 0 | AE48: 0 | AF48: 0 | AG48: 0 | AH48: 0 | AI48: 0 | AJ48: 2081
A49: 30287 | B49: 41021 | C49: 1138 | D49: A2T | E49: N/A | F49: 690 | G49: Occupied | H49: Owaka, Jessica | I49: 06/01/2022 | K49: 06/03/2025 | L49: 06/02/2026 | M49: 1515 | N49: RESIDENT | O49: 0 | P49: 0 | Q49: 0 | R49: 1775 | S49: 1775 | T49: 25 | U49: 8 | V49: 5 | W49: 5 | X49: 3 | Y49: 18 | Z49: 25 | AA49: 0 | AB49: 0 | AC49: 0 | AD49: 0 | AE49: 0 | AF49: 0 | AG49: 0 | AH49: 0 | AI49: 0 | AJ49: 1864
A50: 30261 | B50: 41172 | C50: 1139 | D50: A7 | E50: N/A | F50: 850 | G50: Occupied | H50: Azzad, Yalile | I50: 03/25/2022 | K50: 03/11/2026 | L50: 05/10/2027 | M50: 1940 | N50: RESIDENT | O50: 0 | P50: 0 | Q50: 0 | R50: 1985 | S50: 1985 | T50: 25 | U50: 8 | V50: 5 | W50: 5 | X50: 3 | Y50: 18 | Z50: 0 | AA50: 0 | AB50: 35 | AC50: 0 | AD50: 0 | AE50: 0 | AF50: 0 | AG50: 0 | AH50: 0 | AI50: 0 | AJ50: 2084
A51: 40523 | B51: 41122 | C51: 1201 | D51: B1T | E51: N/A | F51: 1080 | G51: Occupied | H51: Lusty, Connor | I51: 11/08/2023 | K51: 11/08/2025 | L51: 11/06/2026 | M51: 1940 | N51: RESIDENT | O51: 0 | P51: 0 | Q51: 0 | R51: 2343 | S51: 2343 | T51: 25 | U51: 8 | V51: 5 | W51: 5 | X51: 3 | Y51: 18 | Z51: 0 | AA51: 0 | AB51: 0 | AC51: 0 | AD51: 0 | AE51: 0 | AF51: 0 | AG51: 0 | AH51: 0 | AI51: 0 | AJ51: 2407
A52: 40711 | B52: 41081 | C52: 1202 | D52: A2T | E52: N/A | F52: 690 | G52: Occupied | H52: Herrera Arriaga, Gabriel | I52: 08/17/2024 | K52: 08/16/2025 | L52: 08/14/2026 | M52: 1515 | N52: RESIDENT | O52: 0 | P52: 0 | Q52: 0 | R52: 1565 | S52: 1565 | T52: 25 | U52: 8 | V52: 5 | W52: 5 | X52: 3 | Y52: 18 | Z52: 25 | AA52: 0 | AB52: 0 | AC52: 0 | AD52: 0 | AE52: 0 | AF52: 50 | AG52: 0 | AH52: 0 | AI52: 0 | AJ52: 1704
A53: 40751 | B53: 41141 | C53: 1203 | D53: A2T | E53: N/A | F53: 690 | G53: Occupied | H53: Cordis, Ricardo | I53: 01/30/2025 | K53: 11/29/2025 | L53: 11/27/2026 | M53: 1515 | N53: RESIDENT | O53: 0 | P53: 0 | Q53: 0 | R53: 1612 | S53: 1612 | T53: 25 | U53: 8 | V53: 5 | W53: 5 | X53: 3 | Y53: 18 | Z53: 25 | AA53: 0 | AB53: 0 | AC53: 0 | AD53: 0 | AE53: 0 | AF53: 0 | AG53: 0 | AH53: 0 | AI53: 0 | AJ53: 1701
A54: 40887 | B54: 41084 | C54: 1204 | D54: A2T | E54: N/A | F54: 690 | G54: Occupied | H54: Rodriguez, Michelle | I54: 08/01/2025 | K54: 08/01/2025 | L54: 07/30/2026 | M54: 1515 | N54: RESIDENT | O54: 0 | P54: 0 | Q54: -1654 | R54: 1565 | S54: 1565 | T54: 25 | U54: 8 | V54: 5 | W54: 5 | X54: 3 | Y54: 18 | Z54: 25 | AA54: 0 | AB54: 0 | AC54: 0 | AD54: 0 | AE54: 0 | AF54: 0 | AG54: 0 | AH54: 0 | AI54: 0 | AJ54: 1654
A55: 40821 | B55: 40983 | C55: 1205 | D55: B1T | E55: N/A | F55: 1080 | G55: Occupied-NTVL | H55: Urbina, Briana | I55: 04/28/2025 | J55: 04/27/2026 | K55: 04/28/2025 | L55: 04/27/2026 | M55: 1940 | N55: RESIDENT | O55: 0 | P55: 0 | Q55: -271.37 | R55: 2045 | S55: 2045 | T55: 25 | U55: 8 | V55: 5 | W55: 5 | X55: 3 | Y55: 18 | Z55: 25 | AA55: 100 | AB55: 0 | AC55: 0 | AD55: 0 | AE55: 0 | AF55: 0 | AG55: 0 | AH55: 0 | AI55: 0 | AJ55: 2234
A56: 40970 | B56: 41231 | C56: 1205 | D56: B1T | E56: N/A | F56: 1080 | G56: Applicant | H56: Goody, Ashley | I56: 05/11/2026 | K56: 05/11/2026 | L56: 05/10/2027 | M56: 0 | N56: RESIDENT | O56: 0 | P56: 0 | Q56: 0 | R56: 1940 | S56: 1940 | T56: 25 | U56: 8 | V56: 5 | W56: 5 | X56: 3 | Y56: 18 | Z56: 25 | AA56: 0 | AB56: 0 | AC56: 0 | AD56: 0 | AE56: 0 | AF56: 0 | AG56: 0 | AH56: 0 | AI56: 0 | AJ56: 2029
A57: 40788 | B57: 40925 | C57: 1206 | D57: A1T | E57: N/A | F57: 630 | G57: Occupied | H57: Hermanson, Camille | I57: 03/15/2025 | K57: 03/15/2025 | L57: 06/29/2026 | M57: 1485 | N57: RESIDENT | O57: 0 | P57: 0 | Q57: 0 | R57: 1535 | S57: 1535 | T57: 25 | U57: 8 | V57: 5 | W57: 5 | X57: 3 | Y57: 18 | Z57: 25 | AA57: 0 | AB57: 0 | AC57: 0 | AD57: 0 | AE57: 0 | AF57: 0 | AG57: 0 | AH57: 0 | AI57: 0 | AJ57: 1624
A58: 0 | B58: 0 | C58: 1207 | D58: B4T | E58: N/A | F58: 1240 | G58: Vacant | H58: VACANT | M58: 2540 | O58: 0 | P58: 0 | Q58: 0 | R58: 0 | S58: 0 | T58: 0 | U58: 0 | V58: 0 | W58: 0 | X58: 0 | Y58: 0 | Z58: 0 | AA58: 0 | AB58: 0 | AC58: 0 | AD58: 0 | AE58: 0 | AF58: 0 | AG58: 0 | AH58: 0 | AI58: 0 | AJ58: 0
A59: 40732 | B59: 41126 | C59: 1208 | D59: B1T | E59: N/A | F59: 1080 | G59: Occupied | H59: Edwards, Amanda | I59: 12/10/2024 | K59: 11/22/2025 | L59: 02/22/2027 | M59: 1940 | N59: RESIDENT | O59: 0 | P59: 0 | Q59: 0 | R59: 2127 | S59: 2127 | T59: 25 | U59: 8 | V59: 5 | W59: 5 | X59: 3 | Y59: 18 | Z59: 25 | AA59: 0 | AB59: 0 | AC59: 0 | AD59: 0 | AE59: 0 | AF59: 0 | AG59: 0 | AH59: 0 | AI59: 0 | AJ59: 2216
A60: 40941 | B60: 41181 | C60: 1209 | D60: A1T | E60: N/A | F60: 630 | G60: Occupied | H60: Moore, Megan | I60: 01/31/2026 | K60: 01/31/2026 | L60: 01/29/2027 | M60: 1485 | N60: RESIDENT | O60: 0 | P60: 0 | Q60: -740.26 | R60: 1485 | S60: 1485 | T60: 25 | U60: 8 | V60: 5 | W60: 5 | X60: 3 | Y60: 0 | Z60: 25 | AA60: 0 | AB60: 0 | AC60: 0 | AD60: 0 | AE60: 0 | AF60: 0 | AG60: 0 | AH60: 0 | AI60: 0 | AJ60: 1556
A61: 40761 | B61: 41136 | C61: 1210 | D61: A2T | E61: N/A | F61: 690 | G61: Occupied | H61: Hernandez Guillen, Angelica | I61: 12/28/2024 | K61: 12/28/2025 | L61: 12/28/2026 | M61: 1515 | N61: RESIDENT | O61: 0 | P61: 0 | Q61: 0 | R61: 1565 | S61: 1565 | T61: 25 | U61: 8 | V61: 5 | W61: 5 | X61: 3 | Y61: 18 | Z61: 0 | AA61: 0 | AB61: 0 | AC61: 0 | AD61: 0 | AE61: 0 | AF61: 0 | AG61: 0 | AH61: 0 | AI61: 0 | AJ61: 1629
A62: 40482 | B62: 41150 | C62: 1211 | D62: A1T | E62: N/A | F62: 630 | G62: Occupied | H62: Koop, Vanessa | I62: 07/12/2023 | K62: 01/14/2026 | L62: 01/13/2027 | M62: 1485 | N62: RESIDENT | O62: 0 | P62: 0 | Q62: 0 | R62: 1675 | S62: 1675 | T62: 25 | U62: 8 | V62: 5 | W62: 5 | X62: 3 | Y62: 18 | Z62: 0 | AA62: 0 | AB62: 0 | AC62: 0 | AD62: 0 | AE62: 0 | AF62: 0 | AG62: 0 | AH62: 0 | AI62: 0 | AJ62: 1739
A63: 40648 | B63: 41055 | C63: 1212 | D63: A3T | E63: N/A | F63: 750 | G63: Occupied | H63: FARHAT, NADIM | I63: 06/12/2024 | K63: 07/11/2025 | L63: 07/10/2026 | M63: 1610 | N63: RESIDENT | O63: 0 | P63: 0 | Q63: 0 | R63: 1725 | S63: 1725 | T63: 25 | U63: 8 | V63: 5 | W63: 5 | X63: 3 | Y63: 18 | Z63: 25 | AA63: 0 | AB63: 0 | AC63: 0 | AD63: 0 | AE63: 0 | AF63: 0 | AG63: 0 | AH63: 0 | AI63: 0 | AJ63: 1814
A64: 40715 | B64: 41119 | C64: 1213 | D64: A1T | E64: N/A | F64: 630 | G64: Occupied | H64: Travis, Michael | I64: 08/30/2024 | K64: 09/30/2025 | L64: 09/29/2026 | M64: 1485 | N64: RESIDENT | O64: 0 | P64: 0 | Q64: 0 | R64: 1535 | S64: 1535 | T64: 25 | U64: 8 | V64: 5 | W64: 5 | X64: 3 | Y64: 18 | Z64: 25 | AA64: 0 | AB64: 35 | AC64: 0 | AD64: 0 | AE64: 0 | AF64: 0 | AG64: 0 | AH64: 0 | AI64: 0 | AJ64: 1659
A65: 0 | B65: 0 | C65: 1214 | D65: A5T | E65: N/A | F65: 780 | G65: Vacant-Leased | H65: VACANT | M65: 1695 | O65: 0 | P65: 0 | Q65: 0 | R65: 0 | S65: 0 | T65: 0 | U65: 0 | V65: 0 | W65: 0 | X65: 0 | Y65: 0 | Z65: 0 | AA65: 0 | AB65: 0 | AC65: 0 | AD65: 0 | AE65: 0 | AF65: 0 | AG65: 0 | AH65: 0 | AI65: 0 | AJ65: 0
A66: 40975 | B66: 41242 | C66: 1214 | D66: A5T | E66: N/A | F66: 780 | G66: Applicant | H66: Martinez, Bianca | I66: 04/07/2026 | K66: 04/07/2026 | L66: 04/06/2027 | M66: 0 | N66: RESIDENT | O66: 0 | P66: 0 | Q66: 0 | R66: 1695 | S66: 1695 | T66: 25 | U66: 8 | V66: 5 | W66: 5 | X66: 3 | Y66: 18 | Z66: 25 | AA66: 0 | AB66: 0 | AC66: 0 | AD66: 0 | AE66: 0 | AF66: 0 | AG66: 0 | AH66: 0 | AI66: 0 | AJ66: 1784
A67: 40764 | B67: 41114 | C67: 1215 | D67: E1T | E67: N/A | F67: 540 | G67: Occupied | H67: King, Jordan | I67: 12/23/2024 | K67: 11/25/2025 | L67: 11/24/2026 | M67: 1365 | N67: RESIDENT | O67: 0 | P67: 0 | Q67: 0 | R67: 1519 | S67: 1519 | T67: 25 | U67: 8 | V67: 5 | W67: 5 | X67: 3 | Y67: 18 | Z67: 25 | AA67: 0 | AB67: 0 | AC67: 0 | AD67: 0 | AE67: 0 | AF67: 0 | AG67: 0 | AH67: 0 | AI67: 0 | AJ67: 1608
A68: 0 | B68: 0 | C68: 1216 | D68: B1T | E68: N/A | F68: 1080 | G68: Vacant | H68: VACANT | M68: 1940 | O68: 0 | P68: 0 | Q68: 0 | R68: 0 | S68: 0 | T68: 0 | U68: 0 | V68: 0 | W68: 0 | X68: 0 | Y68: 0 | Z68: 0 | AA68: 0 | AB68: 0 | AC68: 0 | AD68: 0 | AE68: 0 | AF68: 0 | AG68: 0 | AH68: 0 | AI68: 0 | AJ68: 0
A69: 40543 | B69: 41165 | C69: 1217 | D69: A1T | E69: N/A | F69: 630 | G69: Occupied | H69: Fields, Zarian | I69: 02/19/2025 | K69: 02/19/2026 | L69: 05/18/2027 | M69: 1485 | N69: RESIDENT | O69: 0 | P69: 0 | Q69: 0 | R69: 1535 | S69: 1535 | T69: 25 | U69: 8 | V69: 5 | W69: 5 | X69: 3 | Y69: 18 | Z69: 25 | AA69: 0 | AB69: 0 | AC69: 0 | AD69: 0 | AE69: 0 | AF69: 0 | AG69: 0 | AH69: 0 | AI69: 0 | AJ69: 1624
A70: 40462 | B70: 41008 | C70: 1218 | D70: E1T | E70: N/A | F70: 540 | G70: Occupied-NTVL | H70: Rivas, Ana | I70: 06/27/2025 | J70: 04/06/2026 | K70: 06/27/2025 | L70: 06/26/2026 | M70: 1365 | N70: RESIDENT | O70: 0 | P70: 0 | Q70: 0 | R70: 1475 | S70: 1475 | T70: 25 | U70: 8 | V70: 5 | W70: 5 | X70: 3 | Y70: 18 | Z70: 0 | AA70: 50 | AB70: 0 | AC70: 0 | AD70: 0 | AE70: 0 | AF70: 0 | AG70: 0 | AH70: 0 | AI70: 0 | AJ70: 1589
A71: 40978 | B71: 41247 | C71: 1218 | D71: E1T | E71: N/A | F71: 540 | G71: Applicant | H71: Idi, Onoriode | I71: 04/18/2026 | K71: 04/18/2026 | L71: 04/19/2027 | M71: 0 | N71: RESIDENT | O71: 0 | P71: 0 | Q71: 0 | R71: 1365 | S71: 1365 | T71: 25 | U71: 8 | V71: 5 | W71: 5 | X71: 3 | Y71: 18 | Z71: 25 | AA71: 0 | AB71: 0 | AC71: 0 | AD71: 0 | AE71: 0 | AF71: 0 | AG71: 0 | AH71: 0 | AI71: 0 | AJ71: 1454
A72: 40882 | B72: 41062 | C72: 1219 | D72: B2 | E72: N/A | F72: 1144 | G72: Occupied | H72: Cruz Sanchez, Karla | I72: 07/25/2025 | K72: 07/25/2025 | L72: 07/24/2026 | M72: 1960 | N72: RESIDENT | O72: 0 | P72: 0 | Q72: 0 | R72: 2065 | S72: 2065 | T72: 25 | U72: 8 | V72: 5 | W72: 5 | X72: 3 | Y72: 18 | Z72: 0 | AA72: 0 | AB72: 0 | AC72: 0 | AD72: 0 | AE72: 0 | AF72: 0 | AG72: 0 | AH72: 0 | AI72: 0 | AJ72: 2129
A73: 0 | B73: 0 | C73: 1220 | D73: B1T | E73: N/A | F73: 1080 | G73: Vacant-Leased | H73: VACANT | M73: 1940 | O73: 0 | P73: 0 | Q73: 0 | R73: 0 | S73: 0 | T73: 0 | U73: 0 | V73: 0 | W73: 0 | X73: 0 | Y73: 0 | Z73: 0 | AA73: 0 | AB73: 0 | AC73: 0 | AD73: 0 | AE73: 0 | AF73: 0 | AG73: 0 | AH73: 0 | AI73: 0 | AJ73: 0
A74: 40934 | B74: 41171 | C74: 1220 | D74: B1T | E74: N/A | F74: 1080 | G74: Applicant | H74: Renteria - EMP, Stephanie | I74: 04/10/2026 | K74: 04/10/2026 | L74: 06/30/2027 | M74: 0 | N74: RESIDENT | O74: 0 | P74: 0 | Q74: 0 | R74: 1940 | S74: 1940 | T74: 25 | U74: 8 | V74: 5 | W74: 5 | X74: 3 | Y74: 18 | Z74: 25 | AA74: 0 | AB74: 0 | AC74: 0 | AD74: -500 | AE74: 0 | AF74: 0 | AG74: 0 | AH74: 0 | AI74: 0 | AJ74: 1529
A75: 40826 | B75: 40995 | C75: 1221 | D75: B3T | E75: N/A | F75: 1151 | G75: Occupied-NTVL | H75: Ramirez, Noelia | I75: 05/02/2025 | J75: 05/02/2026 | K75: 05/02/2025 | L75: 05/02/2026 | M75: 2100 | N75: RESIDENT | O75: 0 | P75: 0 | Q75: -100 | R75: 2215 | S75: 2215 | T75: 25 | U75: 8 | V75: 5 | W75: 5 | X75: 3 | Y75: 18 | Z75: 0 | AA75: 0 | AB75: 0 | AC75: 0 | AD75: 0 | AE75: 0 | AF75: 0 | AG75: 0 | AH75: 0 | AI75: 0 | AJ75: 2279
A76: 40976 | B76: 41243 | C76: 1221 | D76: B3T | E76: N/A | F76: 1151 | G76: Applicant | H76: Miller, Nathan | I76: 05/09/2026 | K76: 05/09/2026 | L76: 05/10/2027 | M76: 0 | N76: RESIDENT | O76: 0 | P76: 0 | Q76: 0 | R76: 2100 | S76: 2100 | T76: 25 | U76: 8 | V76: 5 | W76: 5 | X76: 3 | Y76: 18 | Z76: 25 | AA76: 50 | AB76: 0 | AC76: 0 | AD76: 0 | AE76: 0 | AF76: 0 | AG76: 0 | AH76: 0 | AI76: 0 | AJ76: 2239
A77: 40910 | B77: 41118 | C77: 1222 | D77: E1T | E77: N/A | F77: 540 | G77: Occupied | H77: Roscoe, Mackenzie | I77: 11/21/2025 | K77: 11/21/2025 | L77: 11/20/2026 | M77: 1365 | N77: RESIDENT | O77: 0 | P77: 0 | Q77: 0 | R77: 1395 | S77: 1395 | T77: 25 | U77: 8 | V77: 5 | W77: 5 | X77: 3 | Y77: 18 | Z77: 0 | AA77: 0 | AB77: 0 | AC77: 0 | AD77: 0 | AE77: 0 | AF77: 0 | AG77: 0 | AH77: 0 | AI77: 0 | AJ77: 1459
A78: 40820 | B78: 40979 | C78: 1223 | D78: A3T | E78: N/A | F78: 750 | G78: Occupied-NTV | H78: Becerra, Macie | I78: 05/01/2025 | J78: 04/29/2026 | K78: 05/01/2025 | L78: 04/29/2026 | M78: 1610 | N78: RESIDENT | O78: 0 | P78: 0 | Q78: 0 | R78: 1665 | S78: 1665 | T78: 25 | U78: 8 | V78: 5 | W78: 5 | X78: 3 | Y78: 18 | Z78: 0 | AA78: 0 | AB78: 0 | AC78: 0 | AD78: 0 | AE78: 0 | AF78: 0 | AG78: 0 | AH78: 0 | AI78: 0 | AJ78: 1729
A79: 40922 | B79: 41147 | C79: 1224 | D79: E1T | E79: N/A | F79: 540 | G79: Occupied | H79: Massengale, Dylan | I79: 01/20/2026 | K79: 01/20/2026 | L79: 01/19/2027 | M79: 1365 | N79: RESIDENT | O79: 0 | P79: 0 | Q79: 0 | R79: 1365 | S79: 1365 | T79: 25 | U79: 8 | V79: 5 | W79: 5 | X79: 3 | Y79: 18 | Z79: 25 | AA79: 0 | AB79: 0 | AC79: 0 | AD79: 0 | AE79: 0 | AF79: 0 | AG79: 0 | AH79: 0 | AI79: 0 | AJ79: 1454
A80: 40477 | B80: 41085 | C80: 1225 | D80: A6T | E80: N/A | F80: 840 | G80: Occupied | H80: Tekle, Luwam | I80: 07/19/2023 | K80: 08/23/2025 | L80: 08/21/2026 | M80: 1815 | N80: RESIDENT | O80: 0 | P80: 0 | Q80: 0 | R80: 1950 | S80: 1950 | T80: 25 | U80: 8 | V80: 5 | W80: 5 | X80: 3 | Y80: 18 | Z80: 25 | AA80: 0 | AB80: 0 | AC80: 0 | AD80: 0 | AE80: 0 | AF80: 0 | AG80: 0 | AH80: 0 | AI80: 0 | AJ80: 2039
A81: 40796 | B81: 41230 | C81: 1226 | D81: A1 | E81: N/A | F81: 630 | G81: Occupied | H81: Larrick, Robert | I81: 03/27/2025 | K81: 03/27/2026 | L81: 03/26/2027 | M81: 1485 | N81: RESIDENT | O81: 0 | P81: 0 | Q81: -32.9 | R81: 1581 | S81: 1581 | T81: 25 | U81: 8 | V81: 5 | W81: 5 | X81: 3 | Y81: 18 | Z81: 25 | AA81: 0 | AB81: 0 | AC81: 0 | AD81: 0 | AE81: 0 | AF81: 0 | AG81: 0 | AH81: 0 | AI81: 0 | AJ81: 1670
A82: 40763 | B82: 41156 | C82: 1227 | D82: A5T | E82: N/A | F82: 780 | G82: Occupied | H82: DeCoursey, Matthew | I82: 12/30/2025 | K82: 12/30/2025 | L82: 03/29/2027 | M82: 1695 | N82: RESIDENT | O82: 0 | P82: 0 | Q82: 0 | R82: 1695 | S82: 1695 | T82: 25 | U82: 8 | V82: 5 | W82: 5 | X82: 3 | Y82: 18 | Z82: 25 | AA82: 50 | AB82: 0 | AC82: 0 | AD82: 0 | AE82: 0 | AF82: 0 | AG82: 0 | AH82: 0 | AI82: 0 | AJ82: 1834
A83: 40768 | B83: 40885 | C83: 1228 | D83: E1T | E83: N/A | F83: 540 | G83: Occupied | H83: Gray - EMP, Recco | I83: 12/13/2024 | K83: 12/13/2024 | L83: 06/30/2026 | M83: 1365 | N83: RESIDENT | O83: 0 | P83: 0 | Q83: 0 | R83: 1475 | S83: 1475 | T83: 25 | U83: 8 | V83: 5 | W83: 5 | X83: 3 | Y83: 18 | Z83: 0 | AA83: 0 | AB83: 0 | AC83: 0 | AD83: -500 | AE83: 0 | AF83: 0 | AG83: 0 | AH83: 0 | AI83: 0 | AJ83: 1039
A84: 40932 | B84: 41168 | C84: 1229 | D84: A1T | E84: N/A | F84: 630 | G84: Occupied | H84: Diaz Villalpando, Eric | I84: 01/16/2026 | K84: 01/16/2026 | L84: 01/15/2027 | M84: 1485 | N84: RESIDENT | O84: 0 | P84: 0 | Q84: -653.5 | R84: 1485 | S84: 1485 | T84: 25 | U84: 8 | V84: 5 | W84: 5 | X84: 3 | Y84: 18 | Z84: 25 | AA84: 0 | AB84: 0 | AC84: 0 | AD84: 0 | AE84: 0 | AF84: 0 | AG84: 0 | AH84: 0 | AI84: 0 | AJ84: 1574
A85: 40916 | B85: 41131 | C85: 1230 | D85: B2T | E85: N/A | F85: 1144 | G85: Occupied | H85: Lopez Medina, Arian | I85: 10/20/2025 | K85: 10/20/2025 | L85: 11/19/2026 | M85: 1960 | N85: RESIDENT | O85: 0 | P85: 0 | Q85: 0 | R85: 1960 | S85: 1960 | T85: 25 | U85: 8 | V85: 5 | W85: 5 | X85: 3 | Y85: 18 | Z85: 0 | AA85: 0 | AB85: 0 | AC85: 0 | AD85: 0 | AE85: 0 | AF85: 0 | AG85: 0 | AH85: 0 | AI85: 0 | AJ85: 2024
A86: 40908 | B86: 41116 | C86: 1231 | D86: B4T | E86: N/A | F86: 1240 | G86: Occupied | H86: Dupree - EMP, Valentino | I86: 11/22/2025 | K86: 11/22/2025 | L86: 06/30/2026 | M86: 2540 | N86: RESIDENT | O86: 0 | P86: 0 | Q86: 39.08 | R86: 2540 | S86: 2540 | T86: 25 | U86: 8 | V86: 5 | W86: 5 | X86: 3 | Y86: 18 | Z86: 0 | AA86: 0 | AB86: 0 | AC86: 0 | AD86: -500 | AE86: 0 | AF86: 0 | AG86: 0 | AH86: 0 | AI86: 0 | AJ86: 2104
A87: 40899 | B87: 41099 | C87: 1232 | D87: A3T | E87: N/A | F87: 750 | G87: Occupied | H87: Gura, Jena | I87: 09/19/2025 | K87: 09/19/2025 | L87: 09/21/2026 | M87: 1610 | N87: RESIDENT | O87: 0 | P87: 0 | Q87: -1303.52 | R87: 1645 | S87: 1645 | T87: 25 | U87: 8 | V87: 5 | W87: 5 | X87: 3 | Y87: 18 | Z87: 0 | AA87: 0 | AB87: 0 | AC87: 0 | AD87: 0 | AE87: 0 | AF87: 0 | AG87: 0 | AH87: 0 | AI87: 0 | AJ87: 1709
A88: 40825 | B88: 40992 | C88: 1233 | D88: A2T | E88: N/A | F88: 690 | G88: Occupied | H88: Garcia, Kassandra | I88: 06/03/2025 | K88: 06/03/2025 | L88: 06/02/2026 | M88: 1515 | N88: RESIDENT | O88: 0 | P88: 0 | Q88: 0 | R88: 1565 | S88: 1565 | T88: 25 | U88: 8 | V88: 5 | W88: 5 | X88: 3 | Y88: 18 | Z88: 0 | AA88: 0 | AB88: 0 | AC88: 0 | AD88: 0 | AE88: 0 | AF88: 0 | AG88: 0 | AH88: 0 | AI88: 0 | AJ88: 1629
A89: 40626 | B89: 41016 | C89: 1234 | D89: B1T | E89: N/A | F89: 1080 | G89: Occupied | H89: Moyers, Nathan | I89: 05/11/2024 | K89: 06/11/2025 | L89: 06/10/2026 | M89: 1940 | N89: RESIDENT | O89: 0 | P89: 0 | Q89: 0 | R89: 2085 | S89: 2085 | T89: 25 | U89: 8 | V89: 5 | W89: 5 | X89: 3 | Y89: 18 | Z89: 25 | AA89: 0 | AB89: 0 | AC89: 0 | AD89: 0 | AE89: 0 | AF89: 0 | AG89: 0 | AH89: 0 | AI89: 0 | AJ89: 2174
A90: 40644 | B90: 40986 | C90: 1235 | D90: A1T | E90: N/A | F90: 630 | G90: Occupied | H90: White, Bayley | I90: 05/24/2024 | K90: 06/24/2025 | L90: 06/23/2026 | M90: 1485 | N90: RESIDENT | O90: 0 | P90: 0 | Q90: -1715.04 | R90: 1575 | S90: 1575 | T90: 25 | U90: 8 | V90: 5 | W90: 5 | X90: 3 | Y90: 18 | Z90: 25 | AA90: 0 | AB90: 0 | AC90: 0 | AD90: 0 | AE90: 0 | AF90: 0 | AG90: 0 | AH90: 0 | AI90: 0 | AJ90: 1664
A91: 0 | B91: 0 | C91: 1236 | D91: A2T | E91: N/A | F91: 690 | G91: Vacant | H91: VACANT | M91: 1515 | O91: 0 | P91: 0 | Q91: 0 | R91: 0 | S91: 0 | T91: 0 | U91: 0 | V91: 0 | W91: 0 | X91: 0 | Y91: 0 | Z91: 0 | AA91: 0 | AB91: 0 | AC91: 0 | AD91: 0 | AE91: 0 | AF91: 0 | AG91: 0 | AH91: 0 | AI91: 0 | AJ91: 0
A92: 40823 | B92: 40985 | C92: 1237 | D92: A5T | E92: N/A | F92: 780 | G92: Occupied | H92: Lawrence, Karlisa | I92: 05/15/2025 | K92: 05/15/2025 | L92: 05/14/2026 | M92: 1695 | N92: RESIDENT | O92: 0 | P92: 0 | Q92: 0 | R92: 1750 | S92: 1750 | T92: 25 | U92: 8 | V92: 5 | W92: 5 | X92: 3 | Y92: 0 | Z92: 0 | AA92: 0 | AB92: 0 | AC92: 0 | AD92: 0 | AE92: 0 | AF92: 0 | AG92: 0 | AH92: 0 | AI92: 0 | AJ92: 1796
A93: 40946 | B93: 41189 | C93: 1238 | D93: A3T | E93: N/A | F93: 750 | G93: Occupied | H93: Anderson, Marlo | I93: 02/13/2026 | K93: 02/13/2026 | L93: 02/12/2027 | M93: 1610 | N93: RESIDENT | O93: 0 | P93: 0 | Q93: -3716 | R93: 1610 | S93: 1610 | T93: 25 | U93: 8 | V93: 5 | W93: 5 | X93: 3 | Y93: 18 | Z93: 25 | AA93: 0 | AB93: 0 | AC93: 0 | AD93: 0 | AE93: 0 | AF93: 0 | AG93: 0 | AH93: 0 | AI93: 0 | AJ93: 1699
A94: 40827 | B94: 40996 | C94: 1239 | D94: B2T | E94: N/A | F94: 1144 | G94: Occupied | H94: Lemerand, Stephen | I94: 07/01/2025 | K94: 07/01/2025 | L94: 06/29/2026 | M94: 1960 | N94: RESIDENT | O94: 0 | P94: 0 | Q94: -50 | R94: 2065 | S94: 2065 | T94: 25 | U94: 8 | V94: 5 | W94: 5 | X94: 3 | Y94: 18 | Z94: 0 | AA94: 0 | AB94: 0 | AC94: 0 | AD94: 0 | AE94: 0 | AF94: 0 | AG94: 0 | AH94: 0 | AI94: 0 | AJ94: 2129
A95: 40441 | B95: 41031 | C95: 1240 | D95: A2T | E95: N/A | F95: 690 | G95: Occupied | H95: Judd, Kenneth | I95: 05/09/2023 | K95: 06/03/2025 | L95: 06/02/2026 | M95: 1515 | N95: RESIDENT | O95: 0 | P95: 0 | Q95: 0 | R95: 1615 | S95: 1615 | T95: 25 | U95: 8 | V95: 5 | W95: 5 | X95: 3 | Y95: 18 | Z95: 25 | AA95: 50 | AB95: 0 | AC95: 0 | AD95: 0 | AE95: 0 | AF95: 0 | AG95: 0 | AH95: 0 | AI95: 0 | AJ95: 1754
A96: 40834 | B96: 41010 | C96: 1241 | D96: A4T | E96: N/A | F96: 765 | G96: Occupied-NTV | H96: Randolph, John | I96: 05/24/2025 | J96: 05/25/2026 | K96: 05/24/2025 | L96: 05/25/2026 | M96: 1650 | N96: RESIDENT | O96: 0 | P96: 0 | Q96: 0 | R96: 1705 | S96: 1705 | T96: 25 | U96: 8 | V96: 5 | W96: 5 | X96: 3 | Y96: 18 | Z96: 25 | AA96: 0 | AB96: 0 | AC96: 0 | AD96: 0 | AE96: 0 | AF96: 0 | AG96: 0 | AH96: 0 | AI96: 0 | AJ96: 1794
A97: 40898 | B97: 41098 | C97: 1242 | D97: A4T | E97: N/A | F97: 765 | G97: Occupied | H97: ivy, jerome | I97: 08/30/2025 | K97: 08/30/2025 | L97: 10/29/2026 | M97: 1650 | N97: RESIDENT | O97: 0 | P97: 0 | Q97: 0 | R97: 1685 | S97: 1685 | T97: 25 | U97: 8 | V97: 5 | W97: 5 | X97: 3 | Y97: 18 | Z97: 0 | AA97: 0 | AB97: 0 | AC97: 0 | AD97: 0 | AE97: 0 | AF97: 0 | AG97: 0 | AH97: 0 | AI97: 0 | AJ97: 1749
A98: 40614 | B98: 40968 | C98: 1243 | D98: B2T | E98: N/A | F98: 1144 | G98: Occupied | H98: Baez, Ryan | I98: 04/09/2024 | K98: 05/09/2025 | L98: 05/08/2026 | M98: 1960 | N98: RESIDENT | O98: 0 | P98: 0 | Q98: 0 | R98: 2105 | S98: 2105 | T98: 25 | U98: 8 | V98: 5 | W98: 5 | X98: 3 | Y98: 18 | Z98: 25 | AA98: 0 | AB98: 35 | AC98: 0 | AD98: 0 | AE98: 0 | AF98: 0 | AG98: 0 | AH98: 0 | AI98: 0 | AJ98: 2229
A99: 40328 | B99: 41137 | C99: 1301 | D99: B1 | E99: N/A | F99: 1080 | G99: Occupied | H99: Lee, Alex | I99: 01/18/2025 | K99: 01/20/2026 | L99: 04/19/2027 | M99: 1940 | N99: RESIDENT | O99: 0 | P99: 0 | Q99: -2261.57 | R99: 2085 | S99: 2085 | T99: 25 | U99: 8 | V99: 5 | W99: 5 | X99: 3 | Y99: 18 | Z99: 0 | AA99: 0 | AB99: 0 | AC99: 0 | AD99: 0 | AE99: 0 | AF99: 0 | AG99: 0 | AH99: 0 | AI99: 0 | AJ99: 2149
A100: 40335 | B100: 40899 | C100: 1302 | D100: A2T | E100: N/A | F100: 690 | G100: Occupied-NTV | H100: Day, Savannah | I100: 12/15/2022 | J100: 05/30/2026 | K100: 01/16/2025 | L100: 04/15/2026 | M100: 1515 | N100: RESIDENT | O100: 0 | P100: 0 | Q100: -1844.33 | R100: 1710 | S100: 1710 | T100: 25 | U100: 8 | V100: 5 | W100: 5 | X100: 3 | Y100: 18 | Z100: 0 | AA100: 0 | AB100: 0 | AC100: 0 | AD100: 0 | AE100: 0 | AF100: 0 | AG100: 0 | AH100: 0 | AI100: 0 | AJ100: 1774
...

Sheet AR
B2: OneSite Rents v3.0 | O2: Knightvest Management LLC - Lydian | BO2: Page 1 of 12
B3: 04/29/2026 10:27:48AM | O3: DELINQUENT AND PREPAID | BO3: 120.080.106
O4: Fiscal Period 032026 As of 04/29/2026
B6: Parameters: Report Type: Details
B8: Subproperties: ALL
B11: Subjournals: ALL
B13: Statuses to include: Current resident; Include delinquencies that equal NTV Credit? Yes; Exclude transactions payable in arrears: Yes***; Delinquency range 0.00 through 99999999.00; Aging Columns: Fiscal; Filter type: ALL; Summaries: ALL; Show Prepaid As Allocated: Yes; Include outstanding deposits: No; Hide all PII data: No;
B16: Detail - 56 Account(s)
F18: Name Phone Number Email
B19: Unit | J19: Status | N19: Move-In/ Out | S19: Code Description | Y19: Total Prepaid | AE19: Total Delinquent | AN19: Net Balance | AR19: Current | AW19: 30 Days | BA19: 60 Days | BD19: 90+ Days | BH19: Prorate Credits | BM19: Deposits Held | BS19: Outstanding Deposit | BX19: # Late/ # NSF
B24: 1102 | F24: Cornelius, Erica Elizabeth (480) 466-4039 erica.cornelius2@icloud.com | J24: Current resident | N24: 03/28/2023 | BN24: 0 | BS24: 0 | BX24: 15/0
S25: PMTOPCARD | X25: -25 | AD25: 0 | AN25: -25 | AR25: -25 | AW25: 0 | BA25: 0 | BD25: 0 | BI25: 0
B36: 1104 | F36: Ismond, Diane Roslyn (623) 986-4177 ypriest02@gmail.com | J36: Current resident | N36: 06/10/2025 | BN36: 0 | BS36: 0 | BX36: 0/0
S37: PMTOPACH | X37: -318.7 | AD37: 0 | AN37: -318.7 | AR37: -318.7 | AW37: 0 | BA37: 0 | BD37: 0 | BI37: 0
B47: 1105 | F47: Harvey, Chauncey T chaunceyharvey84@gmail.com | J47: Current resident | N47: 04/11/2024 | BN47: 0 | BS47: 0 | BX47: 10/3
S48: PMTOPCARD | X48: -2305.39 | AD48: 0 | AK48: † | AN48: -2305.39 | AR48: 0 | AW48: -2305.39 | BA48: 0 | BD48: 0 | BI48: 0
B57: 1109 | F57: Whiteman, Elizabeth Anne (602) 402-8522 4elizabeth.whiteman@gmail.com | J57: Current resident | N57: 03/08/2024 | BN57: 0 | BS57: 0 | BX57: 0/0
S58: PMTOPACH | X58: -1785.76 | AD58: 0 | AN58: -1785.76 | AR58: -1785.76 | AW58: 0 | BA58: 0 | BD58: 0 | BI58: 0
B69: 1110 | F69: Dennis, Ezzerianna Keosha (480) 796-4343 ezzerianna@gmail.com | J69: Current resident | N69: 03/06/2026 | BN69: 0 | BS69: 0 | BX69: 0/1
S70: PMTOPIRD | X70: -4.7 | AD70: 0 | AN70: -4.7 | AR70: -4.7 | AW70: 0 | BA70: 0 | BD70: 0 | BI70: 0
B81: 1121 | F81: Gastelum, Xavier (928) 278-3682 gastelumx3@gmail.com | J81: Current resident | N81: 03/28/2026 | BN81: 0 | BS81: 0 | BX81: 0/1
S82: RENTERSINS | X82: 0 | AD82: 2.32 | AR82: 2.32 | AW82: 0 | BA82: 0 | BD82: 0 | BI82: 0
S88: VALETTRASH | X88: 0 | AD88: 3.23 | AR88: 3.23 | AW88: 0 | BA88: 0 | BD88: 0 | BI88: 0
S93: TRASHREIMB | X93: 0 | AD93: 1.03 | AR93: 1.03 | AW93: 0 | BA93: 0 | BD93: 0 | BI93: 0
S97: GASREIMB | X97: 0 | AD97: 0.65 | AR97: 0.65 | AW97: 0 | BA97: 0 | BD97: 0 | BI97: 0
S100: UTILITY | X100: 0 | AD100: 0.65 | AR100: 0.65 | AW100: 0 | BA100: 0 | BD100: 0 | BI100: 0
S103: PESTREIMNB | X103: 0 | AD103: 0.39 | AR103: 0.39 | AW103: 0 | BA103: 0 | BD103: 0 | BI103: 0
S106: SMARTHOME | X106: 0 | AD106: 3.23 | AR106: 3.23 | AW106: 0 | BA106: 0 | BD106: 0 | BI106: 0
B109: Detail - 56 Account(s)
F111: Name Phone Number Email
B112: Unit | J112: Status | N112: Move-In/ Out | S112: Code Description | Y112: Total Prepaid | AE112: Total Delinquent | AN112: Net Balance | AR112: Current | AW112: 30 Days | BA112: 60 Days | BD112: 90+ Days | BH112: Prorate Credits | BM112: Deposits Held | BS112: Outstanding Deposit | BX112: # Late/ # NSF
S116: CORPEMPLCRED | X116: -11.5 | AD116: 0 | AR116: -11.5 | AW116: 0 | BA116: 0 | BD116: 0 | BI116: 0
S119: Subtotals: | X119: -11.5 | AD119: 11.5 | AN119: 0 | AR119: 0 | AW119: 0 | BA119: 0 | BD119: 0 | BH119: 0
B122: 1122 | F122: Nurse, Kiaya Reece (425)760-7447 kiaya.nurse@gmail.com | J122: Current resident | N122: 10/07/2025 | BN122: 0 | BS122: 0 | BX122: 0/0
S123: RNTGRAREF | X123: -50 | AD123: 0 | AR123: -50 | AW123: 0 | BA123: 0 | BD123: 0 | BI123: 0
S129: PMTOPACH | X129: -1250 | AD129: 0 | AR129: -1250 | AW129: 0 | BA129: 0 | BD129: 0 | BI129: 0
S134: PMTOPCARD | X134: -1104.75 | AD134: 0 | AR134: -600 | AW134: -504.75 | BA134: 0 | BD134: 0 | BI134: 0
S138: Subtotals: | X138: -2404.75 | AD138: 0 | AN138: -2404.75 | AR138: -1900 | AW138: -504.75 | BA138: 0 | BD138: 0 | BH138: 0
B141: 1126 | F141: Kadovik, Daria (602) 592-8126 d.kadovik@gmail.com | J141: Current resident | N141: 02/06/2026 | BN141: 0 | BS141: 0 | BX141: 0/0
S142: CONC/SPECL | X142: -824.39 | AD142: 0 | AN142: -824.39 | AR142: -824.39 | AW142: 0 | BA142: 0 | BD142: 0 | BI142: 0
B152: 1128 | F152: Bernal, Cristina (619) 822-4371 Crstnbernal09@gmail.com | J152: Current resident | N152: 08/30/2025 | BN152: 0 | BS152: 0 | BX152: 3/3
S153: PMTOPIRD | X153: -6.74 | AD153: 0 | AN153: -6.74 | AR153: -6.74 | AW153: 0 | BA153: 0 | BD153: 0 | BI153: 0
B163: 1129 | F163: Miller-Cruz, Anthony (916) 583-2814 anthonymm22@yahoo.com | J163: Current resident | N163: 02/07/2026 | BN163: 0 | BS163: 0 | BX163: 0/0
S164: EMPLCRED | X164: -64 | AD164: 0 | AR164: -64 | AW164: 0 | BA164: 0 | BD164: 0 | BI164: 0
S170: PMTOPCARD | X170: -1840 | AD170: 0 | AR170: -1840 | AW170: 0 | BA170: 0 | BD170: 0 | BI170: 0
S175: Subtotals: | X175: -1904 | AD175: 0 | AN175: -1904 | AR175: -1904 | AW175: 0 | BA175: 0 | BD175: 0 | BH175: 0
B179: 1130 | F179: Connell, Abbey Kathryn (916)541-9480 abbey.connell@yahoo.com | J179: Current resident | N179: 05/24/2025 | BN179: 0 | BS179: 0 | BX179: 0/0
S180: PMTOPACH | X180: -770.5 | AD180: 0 | AN180: -770.5 | AR180: -770.5 | AW180: 0 | BA180: 0 | BD180: 0 | BI180: 0
B191: 1131 | F191: Wilson, Kaylie Lynne (623)703-7702 kayliewilson@live.com | J191: Current resident | N191: 06/28/2025 | BN191: 0 | BS191: 0 | BX191: 0/0
S192: PMTOPACH | X192: -2092.5 | AD192: 0 | AN192: -2092.5 | AR192: -1484 | AW192: -608.5 | BA192: 0 | BD192: 0 | BI192: 0
B203: Detail - 56 Account(s)
F205: Name Phone Number Email
B206: Unit | J206: Status | N206: Move-In/ Out | S206: Code Description | Y206: Total Prepaid | AE206: Total Delinquent | AN206: Net Balance | AR206: Current | AW206: 30 Days | BA206: 60 Days | BD206: 90+ Days | BH206: Prorate Credits | BM206: Deposits Held | BS206: Outstanding Deposit | BX206: # Late/ # NSF
B210: 1132 | F210: Crossley, Ryan Morgan (505)947-2081 ryancrossley60@gmail.com | J210: Current resident | N210: 05/28/2025 | BN210: 0 | BS210: 0 | BX210: 0/0
S211: PMTOPACH | X211: -1788.5 | AD211: 0 | AN211: -1788.5 | AR211: -1788.5 | AW211: 0 | BA211: 0 | BD211: 0 | BI211: 0
B222: 1204 | F222: Rodriguez, Michelle Yesenia (602)516-6029 mrvalenzuela20@yahoo.com | J222: Current resident | N222: 08/01/2025 | BN222: 0 | BS222: 0 | BX222: 0/1
S223: PMTOPACH | X223: -1654 | AD223: 0 | AN223: -1654 | AR223: -1654 | AW223: 0 | BA223: 0 | BD223: 0 | BI223: 0
B234: 1209 | F234: Moore, Megan (503) 616-8492 mooremegan74@gmail.com | J234: Current resident | N234: 01/31/2026 | BN234: 0 | BS234: 0 | BX234: 0/0
S235: CONC/SPECL | X235: -722.26 | AD235: 0 | AR235: -722.26 | AW235: 0 | BA235: 0 | BD235: 0 | BI235: 0
S241: PMTOPIRD | X241: -18 | AD241: 0 | AR241: 0 | AW241: 0 | BA241: -18 | BD241: 0 | BI241: 0
S246: Subtotals: | X246: -740.26 | AD246: 0 | AN246: -740.26 | AR246: -722.26 | AW246: 0 | BA246: -18 | BD246: 0 | BH246: 0
B250: 1221 | F250: Ramirez, Noelia K noeliaramirez1990@hotmail.com | J250: NTV | N250: 05/02/2025 05/02/2026 | BN250: 0 | BS250: 0 | BX250: 1/0
S251: PMTOPACH | X251: -100 | AD251: 0 | AN251: -100 | AR251: -100 | AW251: 0 | BA251: 0 | BD251: 0 | BI251: 0
B260: 1226 | F260: Larrick, Robert E (614)791-8476 bob.larrick@yahoo.com | J260: Current resident | N260: 03/27/2025 | BN260: 0 | BS260: 0 | BX260: 0/0
S261: PMTETF | X261: -32.9 | AD261: 0 | AN261: -32.9 | AR261: -32.9 | AW261: 0 | BA261: 0 | BD261: 0 | BI261: 0
B271: 1229 | F271: Diaz Villalpando, Eric Brian (480) 364-3773 ediazvx@gmail.com | J271: Current resident | N271: 01/16/2026 | BN271: 0 | BS271: 0 | BX271: 0/0
S272: CONC/SPECL | X272: -653.5 | AD272: 0 | AN272: -653.5 | AR272: -653.5 | AW272: 0 | BA272: 0 | BD272: 0 | BI272: 0
B282: 1231 | F282: Dupree, Valentino (316) 559-6312 valentinodupree2308@gmail.com | J282: NTV | N282: 11/22/2025 05/01/2026 | BN282: 0 | BS282: 0 | BX282: 4/3
S283: LATEFEE | X283: 0 | AD283: 21.08 | AR283: 21.08 | AW283: 0 | BA283: 0 | BD283: 0 | BI283: 0
S289: RENTERSINS | X289: 0 | AD289: 18 | AR289: 18 | AW289: 0 | BA289: 0 | BD289: 0 | BI289: 0
S294: Subtotals: | X294: 0 | AD294: 39.08 | AN294: 39.08 | AR294: 39.08 | AW294: 0 | BA294: 0 | BD294: 0 | BH294: 0
B296: DEL Comment: Small balance. Sent balance due email(03/24/2026;SRenteria)
B299: 1232 | F299: Gura, Jena Brooke (216)978-2360 jenag23@yahoo.com | J299: Current resident | N299: 09/19/2025 | BN299: 0 | BS299: 0 | BX299: 0/0
S300: PMTOPACH | X300: -1303.52 | AD300: 0 | AN300: -1303.52 | AR300: -1303.52 | AW300: 0 | BA300: 0 | BD300: 0 | BI300: 0
B309: Detail - 56 Account(s)
F311: Name Phone Number Email
B312: Unit | J312: Status | N312: Move-In/ Out | S312: Code Description | Y312: Total Prepaid | AE312: Total Delinquent | AN312: Net Balance | AR312: Current | AW312: 30 Days | BA312: 60 Days | BD312: 90+ Days | BH312: Prorate Credits | BM312: Deposits Held | BS312: Outstanding Deposit | BX312: # Late/ # NSF
B316: 1235 | F316: White, Bayley (308)370-1721 bayley177@gmail.com | J316: Current resident | N316: 05/24/2024 | BN316: 0 | BS316: 0 | BX316: 0/0
S317: PMTOPACH | X317: -1715.04 | AD317: 0 | AN317: -1715.04 | AR317: -1715.04 | AW317: 0 | BA317: 0 | BD317: 0 | BI317: 0
B327: 1238 | F327: Anderson, Marlo Mae (303) 549-3916 marlomanderson02@gmail.com | J327: Current resident | N327: 02/13/2026 | BN327: 0 | BS327: 0 | BX327: 0/0
S328: CONC/SPECL | X328: -2216 | AD328: 0 | AR328: -2216 | AW328: 0 | BA328: 0 | BD328: 0 | BI328: 0
S334: PMTOPACH | X334: -1500 | AD334: 0 | AR334: -1500 | AW334: 0 | BA334: 0 | BD334: 0 | BI334: 0
S339: Subtotals: | X339: -3716 | AD339: 0 | AN339: -3716 | AR339: -3716 | AW339: 0 | BA339: 0 | BD339: 0 | BH339: 0
B343: 1239 | F343: Lemerand, Stephen Michael (443)945-6849 stevelem17@gmail.com | J343: NTV | N343: 07/01/2025 06/29/2026 | BN343: 0 | BS343: 0 | BX343: 0/0
S344: RNTGRAREF | X344: -50 | AD344: 0 | AN344: -50 | AR344: -50 | AW344: 0 | BA344: 0 | BD344: 0 | BI344: 0
B355: 1301 | F355: Lee, Alex (315) 244-9114 alex@alexmlee.com | J355: Current resident | N355: 01/18/2025 | BN355: 0 | BS355: 0 | BX355: 0/0
S356: PMTOPACH | X356: -2261.57 | AD356: 0 | AN356: -2261.57 | AR356: -2261.57 | AW356: 0 | BA356: 0 | BD356: 0 | BI356: 0
B365: 1302 | F365: Day, Savannah (702) 815-3241 savannahdayyy@gmail.com | J365: NTV | N365: 12/15/2022 07/02/2026 | BN365: 0 | BS365: 0 | BX365: 0/0
S366: PMTOPACH | X366: -1844.33 | AD366: 0 | AN366: -1844.33 | AR366: -1844.33 | AW366: 0 | BA366: 0 | BD366: 0 | BI366: 0
B376: 1304 | F376: Zepeda, Rene (602) 327-6005 renezepeda10@gmail.com | J376: Current resident | N376: 03/11/2026 | BN376: 0 | BS376: 0 | BX376: 0/0
S377: PMTOPCARD | X377: -203.23 | AD377: 0 | AN377: -203.23 | AR377: -203.23 | AW377: 0 | BA377: 0 | BD377: 0 | BI377: 0
B387: 1306 | F387: Stohlmann Hekl, Simone Darrien Louise simone.hekl@yahoo.com | J387: Current resident | N387: 11/11/2024 | BN387: 0 | BS387: 0 | BX387: 1/0
S388: PMTOPACH | X388: -1650.04 | AD388: 0 | AN388: -1650.04 | AR388: -1650.04 | AW388: 0 | BA388: 0 | BD388: 0 | BI388: 0
B399: 1310 | F399: Doyal, Harold (404) 974-8075 hd9229@gmail.com | J399: Current resident | N399: 01/30/2026 | BN399: 0 | BS399: 0 | BX399: 0/0
S400: CONC/SPECL | X400: -768.5 | AD400: 0 | AR400: -768.5 | AW400: 0 | BA400: 0 | BD400: 0 | BI400: 0
S406: PMTOPACH | X406: -935.5 | AD406: 0 | AR406: -935.5 | AW406: 0 | BA406: 0 | BD406: 0 | BI406: 0
S411: Subtotals: | X411: -1704 | AD411: 0 | AN411: -1704 | AR411: -1704 | AW411: 0 | BA411: 0 | BD411: 0 | BH411: 0
B414: Detail - 56 Account(s)
F416: Name Phone Number Email
B417: Unit | J417: Status | N417: Move-In/ Out | S417: Code Description | Y417: Total Prepaid | AE417: Total Delinquent | AN417: Net Balance | AR417: Current | AW417: 30 Days | BA417: 60 Days | BD417: 90+ Days | BH417: Prorate Credits | BM417: Deposits Held | BS417: Outstanding Deposit | BX417: # Late/ # NSF
...

Sheet Tax Statement
Y34: 473998
Y35: Tax Summary

Sheet Debt Service
B2: Interest Rate Cap | C2: 0.025 | D2: =IF(C2=C3,"At-the-Money",IF(C2<C3,"In-the-Money",IF(C2>C3,"Out-of-the-Money"))) -> In-the-Money
B3: SOFR | C3: 0.0368 | D3: 46112
B4: Spread | C4: 0.0245
B5: Effective Interest Rate | C5: =SUM(MIN(C3,C2),C4) -> 0.0495
B7: Current Principal Balance | C7: ='NEW OSAR'!E6 -> 52400000
B9: NOI | C9: ='NEW OSAR'!I57 -> 3338057.5
B10: Debt Service (w/o Cap) | C10: =C7*(C3+C4)*(365/360) -> 3256732.8
B11: Debt Service (w/Cap) | C11: =C7*C5*(365/360) -> 2629825
B13: DSCR (w/o Cap) | C13: =C9/C10 -> 1.0249713
B14: DSCR (w/Cap) | C14: =C9/C11 -> 1.2693078
B17: Mod Proposal
B18: Interest Rate Cap | C18: 0.0295
B19: SOFR | C19: 0.0430757
B20: Spread | C20: 0.0255
B21: Effective Interest Rate | C21: =SUM(MIN(C19,C18),C20) -> 0.055
B23: Current Principal Balance | C23: ='NEW OSAR'!E7 -> 48900000
B25: NOI | C25: ='NEW OSAR'!I57 -> 3338057.5
B26: Debt Service (w/o Cap) | C26: =C23*(C19+C20)*(365/360) -> 3399926.1
B27: Debt Service (w/Cap) | C27: =C23*C21*(365/360) -> 2726854.2
B29: DSCR (w/o Cap) | C29: =C25/C26 -> 0.98180296
B30: DSCR (w/Cap) | C30: =C25/C27 -> 1.2241423

Sheet Variance Analysis
A1: 1
C2: 3Q 2025 | G2: 45962 | K2: 4Q 2025 | O2: QoQ ∆ | S2: Cash Management
B3: Property | C3: Occupancy | D3: NOI | E3: DY | F3: DSCR | G3: Occupancy | H3: NOI | I3: DY | J3: DSCR | K3: Occupancy | L3: NOI | M3: DY | N3: DSCR | O3: Occupancy | P3: NOI | Q3: DY | R3: DSCR | S3: In CM? | T3: Threshold
B4: =+#REF! -> #REF! | C4: 0.92344498 | D4: 2855235.8 | E4: 0.054489232 | F4: 1.0857132 | G4: 0.92344498 | H4: 2894344.7 | I4: 0.055235585 | J4: 1.1005845 | K4: =#REF! -> #REF! | L4: =+#REF! -> #REF! | M4: =#REF! -> #REF! | N4: =#REF! -> #REF! | O4: =IF(K4="","-",K4-G4) -> #REF! | P4: =IF(L4="","-",L4-H4) -> #REF! | Q4: =IF(M4="","-",M4-I4) -> #REF! | R4: =IF(N4="","-",N4-J4) -> #REF! | S4: No | T4: 0.06
B6: Notes:
B7: NOI adjusted per the loan agreement.
B8: DSCR inclusive of benefit from in-the-money rate cap.
B9: Cash management testing begins in October 2023

Sheet Paydown Scenario
B2: DY
B3: Target DY | D3: 0.0675
B5: Current Principal | D5: =#REF! -> #REF!
B6: Paydown | D6: =+IF(D9/D5<D3,D5-(D9/D3),0) -> #REF!
B7: Total Principal | D7: =+D5-D6 -> #REF!
B9: Current Net Cash Flow | D9: =#REF!+ABS(F9) -> #REF!
B11: Needed Net Cash Flow | D11: 3535000
B12: DY | D12: =D11/D5 -> #REF!
B13: NCF Change | D13: =D11-D9 -> #REF!

Sheet Insurance
P20: 67264.33

Sheet Definitions
