Workbook
Name Benchmark: '1'!#REF!
Name Benchmark: [1]UPB!$C$8
Name Benchmark: [1]UPB!$C$8
Name Benchmark: 'Old OSAR'!#REF!
Name Capped_Benchmark: '1'!#REF!
Name Capped_Benchmark: '[2]Debt Service'!$C$10
Name Capped_Benchmark: [1]UPB!$C$10
Name Capped_Benchmark: [1]UPB!$C$10
Name Capped_Benchmark: 'Old OSAR'!#REF!
Name CMNOTES: #REF!
Name CMNOTES: #REF!
Name CMNOTES: #REF!
Name CMNOTES: #REF!
Name CMNOTES.: #REF!
Name CMNOTES.: #REF!
Name CMNOTES.: #REF!
Name CMNOTES..: #REF!
Name CMNOTES..: #REF!
Name CMNOTES..: #REF!
Name RESULTS: #REF!
Name RESULTS: #REF!
Name RESULTS: #REF!
Name RESULTS: #REF!

Sheet MF OSAR
B1: CREFC Investor Reporting Package
C2: MULTIFAMILY OPERATING STATEMENT ANALYSIS REPORT (includes Mobile Home Parks, Single Family Rentals, and Co-ops)
C3: ="as of" &TEXT(F6," mm/dd/yyyy") -> as of 03/31/2026
C4: PROPERTY OVERVIEW | H4: Allocated Loan Amount/Percentage
C5: Property ID | E5: 1001-001 | F5: Paid Thru Date | G5: Debt Outside Trust (1) | H5: $ | I5: %
C6: Note A-Scheduled Loan Balance | E6: =+'DSCR Calc'!H5 -> 47626516 | F6: 46112 | G6: X or Blank | H6: 0 | I6: 1
C7: Note B-Scheduled Loan Balance
C8: Note C-Scheduled Loan Balance
C9: Property Name | E9: Memorial Hills
C10: Property Type | E10: Multifamily
C11: Property Address, City, State | E11: 4200 Scotland Street, Houston, TX 77007
C12: Current Net Rentable SF/Units/Beds/Rooms | E12: 308 | F12: units | G12: Use second box to specify sqft.,units…
C13: Year Built/Year Renovated | E13: 2009 | F13: 2026
C14: Cap Ex Reserve (annually)/per Unit.etc. (2) | E14: 200 | F14: Per unit | G14: specify annual/per unit…
C15: Statement Ending Date | E15: Underwriting | F15: 45930 | G15: 46022 | H15: =+I15 -> 46112 | I15: 46112
C16: Occupancy Rate (physical) | E16: 0.94155844 | F16: 0.8961 | G16: 0.8896 | H16: =+I16 -> 0.8604 | I16: ='Rent Roll'!I389/100 -> 0.8604 | N16: Actual | O16: =1-I16 -> 0.1396
C17: Occupancy Date | E17: 45793 | F17: 45930 | G17: 46022 | H17: =+H15 -> 46112 | I17: =+I15 -> 46112 | N17: Factor | O17: 0.05
E18: (1) "X" if debt is outside of the trust, otherwise leave blank
E19: (2) Total $ amount of Capital Reserves required annually by loan documents
C20: INCOME:
C21: Number of Mos. Covered | J21: (prcdng yr to base) | K21: (prcdng yr to 2nd prcdng)
C22: Period Ended | E22: At Contribution | F22: DY Test | G22: DY Test | H22: T10 | I22: DY Test | J22: =TEXT(H15," mm/dd/yyyy")& "-U/W" -> 03/31/2026-U/W | K22: =TEXT(G15," mm/dd/yyyy -") & TEXT(H15,"mm/dd/yyyy") -> 12/31/2025 -03/31/2026
C23: Statement Ending Date | E23: Information | F23: 45930 | G23: 46022 | H23: 46112 | I23: =+I15 -> 46112 | J23: Variance | K23: Variance | L23: Notes | N23: Var $ | O23: Var %
C24: Gross Potential Rent (3) | E24: 6960534.1 | F24: 6181628.7 | G24: 6033557.5 | H24: =+SUMIF('Operating Statement'!U:U,'MF OSAR'!C24,'Operating Statement'!V:V) -> 7109950.2 | I24: =(('Rent Roll'!Z364+'Rent Roll'!Z362+'Rent Roll'!Z358)*12)+'Operating Statement'!V57 -> 5790122.7 | J24: =IF(E24=0, " ",(H24-E24)/E24) -> 0.021466188 | K24: =IF(G24=0, " ",(H24-G24)/G24) -> 0.17840101 | L24: ="Annualized RR as of "&TEXT(I15,"MM/DD/YYYY") & " less T6 concessions" -> Annualized RR as of 03/31/2026 less T6 concessions | N24: =+IFERROR(I24-G24,"") -> -243434.76 | O24: =+IFERROR(N24/G24,"") -> -0.040346804
C25: Less: Vacancy Loss | E25: -406784.46 | F25: 0 | H25: =+SUMIF('Operating Statement'!U:U,'MF OSAR'!C25,'Operating Statement'!V:V) -> -756218.51 | I25: =+IF(O16>O17,"",(O17-O16)*-I24) | J25: =IF(E25=0, " ",(H25-E25)/E25) -> 0.85901524 | K25: =IF(G25=0, " ",(H25-G25)/G25) -> #VALUE! | L25: ="Greater of actual vacancy ("&TEXT(1-I16,"#.0%")&") or "&TEXT(O17,"#.0%") -> Greater of actual vacancy (14.0%) or 5.0% | N25: =+IFERROR(I25-G25,"") | O25: =+IFERROR(N25/G25,"")
C26: OR | H26: =+SUMIF('Operating Statement'!U:U,'MF OSAR'!C26,'Operating Statement'!V:V) -> 0 | N26: =+IFERROR(I26-G26,"") -> 0 | O26: =+IFERROR(N26/G26,"")
C27: Base Rent (3) | E27: 0 | F27: 0 | G27: 0 | H27: =+SUMIF('Operating Statement'!U:U,'MF OSAR'!C27,'Operating Statement'!V:V) -> 0 | I27: =+H27 -> 0 | J27: =IF(E27=0, " ",(H27-E27)/E27) | K27: =IF(G27=0, " ",(H27-G27)/G27) | L27: =$H$22& " ended" &TEXT($I$15," mm/dd/yyyy") -> T10 ended 03/31/2026 | N27: =+IFERROR(I27-G27,"") -> 0 | O27: =+IFERROR(N27/G27,"")
C28: Laundry/Vending Income | E28: 0 | F28: 0 | G28: 0 | H28: =+SUMIF('Operating Statement'!U:U,'MF OSAR'!C28,'Operating Statement'!V:V) -> 0 | I28: =+H28 -> 0 | J28: =IF(E28=0, " ",(H28-E28)/E28) | K28: =IF(G28=0, " ",(H28-G28)/G28) | L28: =$I$22& " ended" &TEXT($I$15," mm/dd/yyyy") -> DY Test ended 03/31/2026 | N28: =+IFERROR(I28-G28,"") -> 0 | O28: =+IFERROR(N28/G28,"")
C29: Parking Income | E29: =+'Old OSAR'!E29 -> 17787.24 | F29: 15657 | G29: 16552.286 | H29: =+SUMIF('Operating Statement'!U:U,'MF OSAR'!C29,'Operating Statement'!V:V) -> 16272.576 | I29: =+H29 -> 16272.576 | J29: =IF(E29=0, " ",(H29-E29)/E29) -> -0.085154527 | K29: =IF(G29=0, " ",(H29-G29)/G29) -> -0.016898555 | L29: =$I$22& " ended" &TEXT($I$15," mm/dd/yyyy") -> DY Test ended 03/31/2026 | N29: =+IFERROR(I29-G29,"") -> -279.70971 | O29: =+IFERROR(N29/G29,"") -> -0.016898555
C30: Other Income | E30: ='Old OSAR'!E30+'Old OSAR'!E27 -> 528398.78 | F30: 637495.8 | G30: 592415.5 | H30: =+SUMIF('Operating Statement'!U:U,'MF OSAR'!C30,'Operating Statement'!V:V) -> 580172.36 | I30: =+H30 -> 580172.36 | J30: =IF(E30=0, " ",(H30-E30)/E30) -> 0.097982028 | K30: =IF(G30=0, " ",(H30-G30)/G30) -> -0.020666473 | L30: =$I$22& " ended" &TEXT($I$15," mm/dd/yyyy") -> DY Test ended 03/31/2026 | N30: =+IFERROR(I30-G30,"") -> -12243.139 | O30: =+IFERROR(N30/G30,"") -> -0.020666473
O31: =+IFERROR(N31/G31,"")
C32: *Effective Gross Income | E32: 7099935.6 | F32: 6834781.5 | G32: 6642525.2 | H32: =+SUM(H24:H30) -> 6950176.6 | I32: =+SUM(I24:I30) -> 6386567.6 | J32: =IF(E32=0, " ",(H32-E32)/E32) -> -0.021093008 | K32: =IF(G32=0, " ",(H32-G32)/G32) -> 0.046315424 | N32: =+IFERROR(I32-G32,"") -> -255957.61 | O32: =+IFERROR(N32/G32,"") -> -0.038533178
E33: (3) Use either Gross Potential (with Vacancy Loss) or Base Rents; use negative $amt for Vacancy Loss
C35: OPERATING EXPENSES: | J35: =IF(E35=0, " ",(H35-E35)/E35)
C36: Real Estate Taxes | E36: 1485043.6 | F36: 1583361.8 | G36: 1506316.6 | H36: =+SUMIF('Operating Statement'!U:U,'MF OSAR'!C36,'Operating Statement'!V:V) -> 1521691.7 | I36: =+MAX(H36,'RE Tax'!C2) -> 1521691.7 | J36: =IF(E36=0, " ",(H36-E36)/E36) -> 0.024678117 | K36: =IF(G36=0, " ",(H36-G36)/G36) -> 0.010207024 | L36: ="Greater of actual tax bill from " & TEXT('RE Tax'!$C$3,"mm/d/yyyy") & "-" & TEXT('RE Tax'!$C$4,"mm/d/yyyy") & " (" & TEXT('RE Tax'!$C$2/1000000,"$0.0""MM""") & ") and T10 ended " & TEXT($I$15,"mm/d/yyyy") -> Greater of actual tax bill from 11/15/2025-11/15/2026 ($1.4MM) and T10 ended 03/31/2026 | N36: =+IFERROR(I36-G36,"") -> 15375.01 | O36: =+IFERROR(N36/G36,"") -> 0.010207024
C37: Property Insurance | E37: 215600 | F37: 81669.58 | G37: 81669.58 | H37: =+SUMIF('Operating Statement'!U:U,'MF OSAR'!C37,'Operating Statement'!V:V) -> 68540.496 | I37: =+Insurance!C5 -> 81669.58 | J37: =IF(E37=0, " ",(H37-E37)/E37) -> -0.68209417 | K37: =IF(G37=0, " ",(H37-G37)/G37) -> -0.16075856 | L37: ="Actual insurance premium from " & TEXT(Insurance!$F$2,"mm/d/yyyy") & "-" & TEXT(Insurance!$F$3,"mm/d/yyyy") & " (" & TEXT(Insurance!$C$5/1000,"$00.0""K"")") -> Actual insurance premium from 06/26/2025-06/26/2026 ($81.7K) | N37: =+IFERROR(I37-G37,"") -> 0 | O37: =+IFERROR(N37/G37,"") -> 0
C38: Utilities | E38: 378063.92 | F38: 435251.49 | G38: 382429.13 | H38: =+SUMIF('Operating Statement'!U:U,'MF OSAR'!C38,'Operating Statement'!V:V) -> 423119.88 | I38: =+SUMIF('Operating Statement'!$U:$U,'MF OSAR'!C38,'Operating Statement'!$V:$V) -> 423119.88 | J38: =IF(E38=0, " ",(H38-E38)/E38) -> 0.11917551 | K38: =IF(G38=0, " ",(H38-G38)/G38) -> 0.10640076 | L38: =$H$22& " ended" &TEXT($I$15," mm/dd/yyyy") -> T10 ended 03/31/2026 | N38: =+IFERROR(I38-G38,"") -> 40690.749 | O38: =+IFERROR(N38/G38,"") -> 0.10640076
C39: Repairs and Maintenance | E39: 358377.1 | F39: 276857.22 | G39: 343370.95 | H39: =+SUMIF('Operating Statement'!U:U,'MF OSAR'!C39,'Operating Statement'!V:V) -> 333494.4 | I39: =+SUMIF('Operating Statement'!$U:$U,'MF OSAR'!C39,'Operating Statement'!$V:$V) -> 333494.4 | J39: =IF(E39=0, " ",(H39-E39)/E39) -> -0.069431613 | K39: =IF(G39=0, " ",(H39-G39)/G39) -> -0.028763495 | L39: =$H$22& " ended" &TEXT($I$15," mm/dd/yyyy") -> T10 ended 03/31/2026 | N39: =+IFERROR(I39-G39,"") -> -9876.5486 | O39: =+IFERROR(N39/G39,"") -> -0.028763495
C40: Management Fees | E40: 177498.39 | F40: 170869.54 | G40: 166063.13 | H40: =+SUMIF('Operating Statement'!U:U,'MF OSAR'!C40,'Operating Statement'!V:V) -> 125036.59 | I40: =+MAX(H40,0.025*I32) -> 159664.19 | J40: =IF(E40=0, " ",(H40-E40)/E40) -> -0.29556211 | K40: =IF(G40=0, " ",(H40-G40)/G40) -> -0.24705387 | L40: 0.025 | N40: =+IFERROR(I40-G40,"") -> -6398.9402 | O40: =+IFERROR(N40/G40,"") -> -0.038533178
C41: Payroll & Benefits | E41: 688888.39 | F41: 431244.93 | G41: 475945.49 | H41: =+SUMIF('Operating Statement'!U:U,'MF OSAR'!C41,'Operating Statement'!V:V) -> 510450.74 | I41: =+SUMIF('Operating Statement'!$U:$U,'MF OSAR'!C41,'Operating Statement'!$V:$V) -> 510450.74 | J41: =IF(E41=0, " ",(H41-E41)/E41) -> -0.25902258 | K41: =IF(G41=0, " ",(H41-G41)/G41) -> 0.072498328 | L41: =$H$22& " ended" &TEXT($I$15," mm/dd/yyyy") -> T10 ended 03/31/2026 | N41: =+IFERROR(I41-G41,"") -> 34505.253 | O41: =+IFERROR(N41/G41,"") -> 0.072498328
C42: Advertising & Marketing | E42: 265543.06 | F42: 172875.81 | G42: 216404.33 | H42: =+SUMIF('Operating Statement'!U:U,'MF OSAR'!C42,'Operating Statement'!V:V) -> 233007.19 | I42: =+SUMIF('Operating Statement'!$U:$U,'MF OSAR'!C42,'Operating Statement'!$V:$V) -> 233007.19 | J42: =IF(E42=0, " ",(H42-E42)/E42) -> -0.12252577 | K42: =IF(G42=0, " ",(H42-G42)/G42) -> 0.07672148 | L42: =$H$22& " ended" &TEXT($I$15," mm/dd/yyyy") -> T10 ended 03/31/2026 | N42: =+IFERROR(I42-G42,"") -> 16602.861 | O42: =+IFERROR(N42/G42,"") -> 0.07672148
C43: Professional Fees | E43: 0 | F43: 27744.24 | G43: 8355.5657 | H43: =+SUMIF('Operating Statement'!U:U,'MF OSAR'!C43,'Operating Statement'!V:V) -> 5848.896 | I43: =+SUMIF('Operating Statement'!$U:$U,'MF OSAR'!C43,'Operating Statement'!$V:$V) -> 5848.896 | J43: =IF(E43=0, " ",(H43-E43)/E43) | K43: =IF(G43=0, " ",(H43-G43)/G43) -> -0.3 | L43: =$H$22& " ended" &TEXT($I$15," mm/dd/yyyy") -> T10 ended 03/31/2026 | N43: =+IFERROR(I43-G43,"") -> -2506.6697 | O43: =+IFERROR(N43/G43,"") -> -0.3
C44: General and Administrative | E44: 122141.06 | F44: 116703 | G44: 63131.743 | H44: =+SUMIF('Operating Statement'!U:U,'MF OSAR'!C44,'Operating Statement'!V:V) -> 82527.912 | I44: =+SUMIF('Operating Statement'!$U:$U,'MF OSAR'!C44,'Operating Statement'!$V:$V) -> 82527.912 | J44: =IF(E44=0, " ",(H44-E44)/E44) -> -0.32432294 | K44: =IF(G44=0, " ",(H44-G44)/G44) -> 0.30723323 | L44: =$H$22& " ended" &TEXT($I$15," mm/dd/yyyy") -> T10 ended 03/31/2026 | N44: =+IFERROR(I44-G44,"") -> 19396.169 | O44: =+IFERROR(N44/G44,"") -> 0.30723323
C45: Other Expenses | E45: 59939.11 | G45: 0 | H45: =+SUMIF('Operating Statement'!U:U,'MF OSAR'!C45,'Operating Statement'!V:V) -> 0 | I45: =+SUMIF('Operating Statement'!$U:$U,'MF OSAR'!C45,'Operating Statement'!$V:$V) -> 0 | J45: =IF(E45=0, " ",(H45-E45)/E45) -> -1 | K45: =IF(G45=0, " ",(H45-G45)/G45) | L45: =$H$22& " ended" &TEXT($I$15," mm/dd/yyyy") -> T10 ended 03/31/2026 | N45: =+IFERROR(I45-G45,"") -> 0 | O45: =+IFERROR(N45/G45,"")
C46: Ground Rent | E46: 0 | G46: 0 | H46: =+SUMIF('Operating Statement'!U:U,'MF OSAR'!C46,'Operating Statement'!V:V) -> 0 | I46: =+SUMIF('Operating Statement'!$U:$U,'MF OSAR'!C46,'Operating Statement'!$V:$V) -> 0 | J46: =IF(E46=0, " ",(H46-E46)/E46) | K46: =IF(G46=0, " ",(H46-G46)/G46) | L46: =$H$22& " ended" &TEXT($I$15," mm/dd/yyyy") -> T10 ended 03/31/2026 | N46: =+IFERROR(I46-G46,"") -> 0 | O46: =+IFERROR(N46/G46,"")
C47: *Total Operating Expenses | E47: 3751094.6 | F47: 3296577.6 | G47: 3243686.6 | H47: =+SUM(H36:H45) -> 3303717.8 | I47: =+SUM(I36:I45) -> 3351474.5 | J47: =IF(E47=0, " ",(H47-E47)/E47) -> -0.11926568 | K47: =IF(G47=0, " ",(H47-G47)/G47) -> 0.01850709 | N47: =+IFERROR(I47-G47,"") -> 107787.88 | O47: =+IFERROR(N47/G47,"") -> 0.033230055
C49: Operating Expense Ratio | E49: 0.52832797 | F49: 0.48232377 | G49: 0.4883213 | H49: 0.48232377 | I49: =+I47/I32 -> 0.52476927 | J49: =IF(E49=0, " ",(H49-E49)/E49) -> -0.087075086 | K49: =IF(G49=0, " ",(H49-G49)/G49) -> -0.012281933
C51: *Net Operating Income | E51: 3348841 | F51: 3538203.9 | G51: 3398838.7 | H51: =+H32-H47 -> 3646458.9 | I51: =+I32-I47 -> 3035093.2 | J51: =IF(E51=0, " ",(H51-E51)/E51) -> 0.088871893 | K51: =IF(G51=0, " ",(H51-G51)/G51) -> 0.072854347 | N51: =+IFERROR(I51-G51,"") -> -363745.49 | O51: =+IFERROR(N51/G51,"") -> -0.10702052
C53: Capital Expenditures | E53: 61600 | F53: 61600 | G53: 61600 | H53: =I53 -> 61600 | I53: =+E14*E12 -> 61600 | J53: =IF(E53=0, " ",(H53-E53)/E53) -> 0 | K53: =IF(G53=0, " ",(H53-G53)/G53) -> 0 | L53: 200
C54: Extraordinary Capital Expenditures
C55: Total Capital Items | E55: 61600 | F55: 61600 | G55: 61600 | H55: =+SUM(H53:H54) -> 61600 | I55: =+SUM(I53:I54) -> 61600 | J55: =IF(E55=0, " ",(H55-E55)/E55) -> 0 | K55: =IF(G55=0, " ",(H55-G55)/G55) -> 0
C57: *Net Cash Flow | E57: 3287241 | F57: 3476603.9 | G57: 3337238.7 | H57: =+H51-H55 -> 3584858.9 | I57: =+I51-I55 -> 2973493.2 | J57: =IF(E57=0, " ",(H57-E57)/E57) -> 0.090537274 | K57: =IF(G57=0, " ",(H57-G57)/G57) -> 0.07419912
C59: Debt Service - A Note | F59: 3138899.6 | G59: 2914948.3 | H59: =+I59 -> 2863478.1 | I59: =+'DSCR Calc'!H17 -> 2863478.1 | L59: ="S+"&TEXT('DSCR Calc'!H10*10000,"000")&", SOFR as of "&TEXT($I$15,"MM/DD/YYYY") -> S+225, SOFR as of 03/31/2026
C60: Debt Service - B Note
C61: Debt Service - C Note
C63: *Net Cash Flow after Debt Service | F63: 337704.36 | G63: 422290.38 | H63: =+H57-H59 -> 721380.73 | I63: =+I57-I59 -> 110015.06 | J63: =IF(E63=0, " ",(H63-E63)/E63) | K63: =IF(G63=0, " ",(H63-G63)/G63) -> 0.70825754
C65: *DSCR: (NOI/Debt Service) - A Note | F65: 1.1272116 | G65: 1.1660031 | H65: =+H51/H59 -> 1.273437 | I65: =+I51/I59 -> 1.0599324 | K65: =IF(G65=0, " ",(H65-G65)/G65) -> 0.092138587
C66: *DSCR: (NOI/Debt Service) - A & B Note
C67: *DSCR: (NOI/Debt Service) - A, B & C Note
C69: *DSCR: (NCF/Debt Service) - A Note | F69: 1.1075869 | G69: 1.1448706 | H69: =+H57/H59 -> 1.2519247 | I69: =+I57/I59 -> 1.0384201 | K69: =IF(G69=0, " ",(H69-G69)/G69) -> 0.093507532
C70: *DSCR: (NCF/Debt Service) - A & B Note
C71: *DSCR: (NCF/Debt Service) - A, B & C Note
C73: Debt Yield (NCF/UPB) | F73: 0.097246376 | G73: 0.070071023 | H73: 0.073639545 | I73: =+I57/E6 -> 0.062433565
C75: Source of Financial Data:
E76: (ie. operating statements, financial statements, tax return, other)
C77: Notes and Assumptions: Years above will roll, always showing a 3yr sequential history. Comments from the most recent NOI Adjustment Worksheet should be carried forward to Operating Statement
C78: Analysis Report. Year-over-year variances (either higher or lower) must be explained and noted for the following: >20% DSCR change, >20% EGI/Total Operating Expenses or Total Capital
C79: Items. Quarterly variance comments may be necessary if the loan is on the Watch List.
C80: Income: Comments
C83: Expense: Comments
C86: Capital Items: Comments
C89: DSCR: Comments
C92: * Used in the CREFC Comparative Financial Status Report/CREFC Property File/CREFC Loan Periodic Update File. Note that information for multiple property loans must be consolidated (if available)
C93: for reporting to the CREFC Loan Periodic Update file.

Sheet Old OSAR
D1: CREFC Investor Reporting Package
A2: 1 | D2: MULTIFAMILY OPERATING STATEMENT ANALYSIS REPORT (includes Mobile Home Parks, Single Family Rentals, and Co-ops)
D3: ="as of "&TEXT($J$14,"m/dd/yyyy") -> as of 12/31/2025
D4: PROPERTY OVERVIEW | H4: Allocated Loan Amount/Percentage
D5: Property ID | E5: 1001-001 | F5: Paid Thru Date | G5: Debt Outside Trust (1) | H5: $ | I5: %
D6: Note A-Scheduled Loan Balance | E6: ='DSCR Calc'!H5 -> 47626516 | F6: =J14 -> 46022 | H6: 0 | I6: 1
D7: Note B-Scheduled Loan Balance | E7: 0 | H7: 0
D8: Property Name | E8: Memorial Hills
D9: Property Type | E9: MF
D10: Property Address, City, State | E10: 4200 Scotland Street, Houston, TX 77007
D11: Current Net Rentable SF/Units/Beds/Rooms | E11: 308 | F11: Units
D12: Year Built/Year Renovated | E12: 2009
D13: Cap Ex Reserve (annually)/per Unit.etc. (2) | E13: 200 | F13: per unit
D14: Statement Ending Date | E14: ='UW Pro Forma CF'!C3 -> At Close (In Place) | F14: ='UW Pro Forma CF'!E12 -> 46173 | G14: ='UW Pro Forma CF'!F12 -> 46538 | H14: 45838 | I14: 45930 | J14: 46022 | K14: =J14 -> 46022
D15: Occupancy Rate (physical) | E15: ='UW Pro Forma CF'!C8 -> 0.94155844 | F15: ='UW Pro Forma CF'!E8 -> 0.90191795 | G15: ='UW Pro Forma CF'!F8 -> 0.88636364 | H15: 0.9188 | I15: 0.8961 | J15: ='Rent Roll'!#REF!/100 -> #REF! | K15: =J15 -> #REF! | M15: Vacancy Factor | N15: Actual
D16: Occupancy Date | E16: 45793 | F16: ='UW Pro Forma CF'!E12 -> 46173 | G16: ='UW Pro Forma CF'!F12 -> 46538 | H16: 45838 | I16: 45930 | J16: =J14 -> 46022 | K16: =K14 -> 46022 | M16: 0.05 | N16: =1-J15 -> #REF!
E17: Information
E18: (2) Total $ amount of Capital Reserves required annually by loan documents
D19: INCOME:
D20: Number of Mos. Covered
D21: Period Ended | E21: At Contribution | F21: UW Year 1 | G21: UW Year 2 | H21: DY 2Q 2025 | I21: DY 3Q 2025 | J21: ='Operating Statement'!V11 -> T10 | K21: DY 4Q 2025 | L21: Notes | N21: In place to UW Year 1
D22: Statement Ending Date | E22: Information | F22: ='UW Pro Forma CF'!E12 -> 46173 | G22: ='UW Pro Forma CF'!F12 -> 46538 | H22: 45838 | I22: 45930 | J22: =$J$14 -> 46022 | K22: =$J$14 -> 46022 | N22: Variance ($) | O22: Variance (%)
D23: Gross Potential Rent (3) | E23: ='UW Pro Forma CF'!C13 -> 6960534.1 | F23: ='UW Pro Forma CF'!E13 -> 7125090.4 | G23: ='UW Pro Forma CF'!F13 -> 7547179.1 | H23: 6437938.1 | I23: 6181628.7 | J23: =SUMIFS('Operating Statement'!Q:Q,'Operating Statement'!S:S,'Old OSAR'!D23) -> 0 | K23: =('Rent Roll'!Z363*12)+'Operating Statement'!V57 -> -327351.3 | L23: ="Annualized RR as of "&TEXT(J14,"MM/DD/YYYY") & " less T6 concessions" -> Annualized RR as of 12/31/2025 less T6 concessions | N23: =IFERROR(K23-I23,"N/A") -> -6508980 | O23: =IFERROR(N23/I23,"N/A") -> -1.0529555
D24: Less: Vacancy Loss | E24: ='UW Pro Forma CF'!C14 -> -406784.46 | F24: ='UW Pro Forma CF'!E14 -> -698843.45 | G24: ='UW Pro Forma CF'!F14 -> -857633.98 | J24: =SUMIFS('Operating Statement'!Q:Q,'Operating Statement'!S:S,'Old OSAR'!D24) -> 0 | K24: =IF(N16<M16,(-M16+N16)*K23,"") -> #REF! | L24: ="Greater of actual vacancy ("&TEXT(N16,"#.0%")&") or "&TEXT(M16,"#.0%") -> #REF! | N24: =IFERROR(K24-I24,"N/A") -> N/A | O24: =IFERROR(N24/I24,"N/A") -> N/A
D25: OR | N25: =IFERROR(K25-I25,"N/A") -> 0 | O25: =IFERROR(N25/I25,"N/A") -> N/A
D26: Base Rent (3) | E26: ='UW Pro Forma CF'!C16 -> 0 | N26: =IFERROR(K26-I26,"N/A") -> 0 | O26: =IFERROR(N26/I26,"N/A") -> N/A
D27: Delinquent Rent | E27: ='UW Pro Forma CF'!C17 -> -25478.68 | F27: ='UW Pro Forma CF'!E17 -> -16911.176 | G27: ='UW Pro Forma CF'!F17 -> -17604.066 | H27: -3334.08 | I27: -10224.39 | J27: =SUMIFS('Operating Statement'!Q:Q,'Operating Statement'!S:S,'Old OSAR'!D27) -> 0 | K27: =J27 -> 0 | L27: =TEXT($J$21,0) &" ended "&TEXT($J$14,"MM/DD/YYYY") -> T10 ended 12/31/2025 | N27: =IFERROR(K27-I27,"N/A") -> 10224.39 | O27: =IFERROR(N27/I27,"N/A") -> -1
D28: Expense Reimbursement | H28: 0 | I28: 370468.05 | J28: =SUMIFS('Operating Statement'!Q:Q,'Operating Statement'!S:S,'Old OSAR'!D28) -> 0 | K28: =J28 -> 0 | L28: =TEXT($J$21,0) &" ended "&TEXT($J$14,"MM/DD/YYYY") -> T10 ended 12/31/2025 | N28: =IFERROR(K28-I28,"N/A") -> -370468.05 | O28: =IFERROR(N28/I28,"N/A") -> -1
D29: Parking Income | E29: ='UW Pro Forma CF'!C18 -> 17787.24 | F29: ='UW Pro Forma CF'!E18 -> 22176 | G29: ='UW Pro Forma CF'!F18 -> 22841.28 | H29: 15060 | I29: 15657 | J29: =SUMIFS('Operating Statement'!Q:Q,'Operating Statement'!S:S,'Old OSAR'!D29) -> 0 | K29: =J29 -> 0 | L29: =TEXT($J$21,0) &" ended "&TEXT($J$14,"MM/DD/YYYY") -> T10 ended 12/31/2025 | N29: =IFERROR(K29-I29,"N/A") -> -15657 | O29: =IFERROR(N29/I29,"N/A") -> -1
D30: Other Income | E30: ='UW Pro Forma CF'!C19 -> 553877.46 | F30: ='UW Pro Forma CF'!E19 -> 363880.87 | G30: ='UW Pro Forma CF'!F19 -> 454679.07 | H30: 782824.2 | I30: 277252.14 | J30: =SUMIFS('Operating Statement'!Q:Q,'Operating Statement'!S:S,'Old OSAR'!D30) -> 0 | K30: =J30 -> 0 | L30: =TEXT($J$21,0) &" ended "&TEXT($J$14,"MM/DD/YYYY") -> T10 ended 12/31/2025 | N30: =IFERROR(K30-I30,"N/A") -> -277252.14 | O30: =IFERROR(N30/I30,"N/A") -> -1
N31: =IFERROR(K31-I31,"N/A") -> 0 | O31: =IFERROR(N31/I31,"N/A") -> N/A
D32: *Effective Gross Income | E32: ='UW Pro Forma CF'!C21 -> 7099935.6 | F32: ='UW Pro Forma CF'!E21 -> 6795392.6 | G32: ='UW Pro Forma CF'!F21 -> 7149461.4 | H32: 7232488.2 | I32: 6834781.5 | J32: =SUM(J23:J30) -> 0 | K32: =SUM(K23:K30) -> #REF! | N32: =IFERROR(K32-I32,"N/A") -> N/A | O32: =IFERROR(N32/I32,"N/A") -> N/A
E33: (3) Use either Gross Potential (with Vacancy Loss) or Base Rents; use negative $amt for Vacancy Loss
D35: OPERATING EXPENSES:
D36: Real Estate Taxes | E36: ='UW Pro Forma CF'!C25 -> 1485043.6 | F36: ='UW Pro Forma CF'!E25 -> 1484035.5 | G36: ='UW Pro Forma CF'!F25 -> 1529382.6 | H36: 1318188.1 | I36: 1583361.8 | J36: =SUMIFS('Operating Statement'!Q:Q,'Operating Statement'!S:S,'Old OSAR'!D36) -> 0 | K36: =+MAX(J36,'RE Tax'!C2) -> 1425631.4 | L36: Greater of T12 taxes & 2025 actual taxes | N36: =IFERROR(K36-I36,"N/A") -> -157730.35 | O36: =IFERROR(N36/I36,"N/A") -> -0.099617379
D37: Property Insurance | E37: ='UW Pro Forma CF'!C26 -> 215600 | F37: ='UW Pro Forma CF'!E26 -> 215600 | G37: ='UW Pro Forma CF'!F26 -> 226380 | H37: 76674.58 | I37: 81669.58 | J37: =SUMIFS('Operating Statement'!Q:Q,'Operating Statement'!S:S,'Old OSAR'!D37) -> 0 | K37: =Insurance!C5 -> 81669.58 | L37: 2025 insurance premium | M37: =K37/E37-1 -> -0.62119861 | N37: =IFERROR(K37-I37,"N/A") -> 0 | O37: =IFERROR(N37/I37,"N/A") -> 0
D38: Utilities | E38: ='UW Pro Forma CF'!C27 -> 378063.92 | F38: ='UW Pro Forma CF'!E27 -> 369600 | G38: ='UW Pro Forma CF'!F27 -> 388080 | H38: 388047.24 | I38: 435251.49 | J38: =SUMIFS('Operating Statement'!Q:Q,'Operating Statement'!S:S,'Old OSAR'!D38) -> 0 | K38: =J38 -> 0 | L38: =TEXT($J$21,0) &" ended "&TEXT($J$14,"MM/DD/YYYY") -> T10 ended 12/31/2025 | N38: =IFERROR(K38-I38,"N/A") -> -435251.49 | O38: =IFERROR(N38/I38,"N/A") -> -1
D39: Repairs and Maintenance | E39: ='UW Pro Forma CF'!C28 -> 358377.1 | F39: ='UW Pro Forma CF'!E28 -> 377300 | G39: ='UW Pro Forma CF'!F28 -> 396165 | H39: 102901.92 | I39: 276857.22 | J39: =SUMIFS('Operating Statement'!Q:Q,'Operating Statement'!S:S,'Old OSAR'!D39) -> 0 | K39: =J39 -> 0 | L39: =TEXT($J$21,0) &" ended "&TEXT($J$14,"MM/DD/YYYY") -> T10 ended 12/31/2025 | N39: =IFERROR(K39-I39,"N/A") -> -276857.22 | O39: =IFERROR(N39/I39,"N/A") -> -1
D40: Management Fees | E40: ='UW Pro Forma CF'!C29 -> 177498.39 | F40: ='UW Pro Forma CF'!E29 -> 169884.82 | G40: ='UW Pro Forma CF'!F29 -> 178736.53 | H40: 188251.8 | I40: 170869.54 | J40: =SUMIFS('Operating Statement'!Q:Q,'Operating Statement'!S:S,'Old OSAR'!D40) -> 0 | K40: =+MAX(J40,L40*K32) -> #REF! | L40: 0.025 | N40: =IFERROR(K40-I40,"N/A") -> N/A | O40: =IFERROR(N40/I40,"N/A") -> N/A
D41: Payroll & Benefits | E41: ='UW Pro Forma CF'!C30 -> 688888.39 | F41: ='UW Pro Forma CF'!E30 -> 646800 | G41: ='UW Pro Forma CF'!F30 -> 679140 | H41: 172441.56 | I41: 431244.93 | J41: =SUMIFS('Operating Statement'!Q:Q,'Operating Statement'!S:S,'Old OSAR'!D41) -> 0 | K41: =J41 -> 0 | L41: =TEXT($J$21,0) &" ended "&TEXT($J$14,"MM/DD/YYYY") -> T10 ended 12/31/2025 | N41: =IFERROR(K41-I41,"N/A") -> -431244.93 | O41: =IFERROR(N41/I41,"N/A") -> -1
D42: Advertising & Marketing | E42: ='UW Pro Forma CF'!C31 -> 265543.06 | F42: ='UW Pro Forma CF'!E31 -> 261800 | G42: ='UW Pro Forma CF'!F31 -> 154000 | H42: 17199.96 | I42: 172875.81 | J42: =SUMIFS('Operating Statement'!Q:Q,'Operating Statement'!S:S,'Old OSAR'!D42) -> 0 | K42: =J42 -> 0 | L42: =TEXT($J$21,0) &" ended "&TEXT($J$14,"MM/DD/YYYY") -> T10 ended 12/31/2025 | N42: =IFERROR(K42-I42,"N/A") -> -172875.81 | O42: =IFERROR(N42/I42,"N/A") -> -1
D43: Professional Fees | E43: ='UW Pro Forma CF'!C32 -> 0 | F43: ='UW Pro Forma CF'!E32 -> 0 | G43: ='UW Pro Forma CF'!F32 -> 0 | H43: 179175.12 | I43: 27744.24 | J43: =SUMIFS('Operating Statement'!Q:Q,'Operating Statement'!S:S,'Old OSAR'!D43) -> 0 | K43: =J43 -> 0 | L43: =TEXT($J$21,0) &" ended "&TEXT($J$14,"MM/DD/YYYY") -> T10 ended 12/31/2025 | N43: =IFERROR(K43-I43,"N/A") -> -27744.24 | O43: =IFERROR(N43/I43,"N/A") -> -1
D44: General and Administrative | E44: ='UW Pro Forma CF'!C33 -> 122141.06 | F44: ='UW Pro Forma CF'!E33 -> 123200 | G44: ='UW Pro Forma CF'!F33 -> 129360 | H44: 198499.56 | I44: 116703 | J44: =SUMIFS('Operating Statement'!Q:Q,'Operating Statement'!S:S,'Old OSAR'!D44) -> 0 | K44: =J44 -> 0 | L44: =TEXT($J$21,0) &" ended "&TEXT($J$14,"MM/DD/YYYY") -> T10 ended 12/31/2025 | N44: =IFERROR(K44-I44,"N/A") -> -116703 | O44: =IFERROR(N44/I44,"N/A") -> -1
D45: Other Expenses | E45: ='UW Pro Forma CF'!C34 -> 59939.11 | N45: =IFERROR(K45-I45,"N/A") -> 0 | O45: =IFERROR(N45/I45,"N/A") -> N/A
D46: Ground Rent | N46: =IFERROR(K46-I46,"N/A") -> 0 | O46: =IFERROR(N46/I46,"N/A") -> N/A
D47: Total Operating Expenses | E47: ='UW Pro Forma CF'!C36 -> 3751094.6 | F47: ='UW Pro Forma CF'!E36 -> 3648220.4 | G47: ='UW Pro Forma CF'!F36 -> 3681244.2 | H47: 2641379.8 | I47: 3296577.6 | J47: =SUM(J36:J46) -> 0 | K47: =SUM(K36:K46) -> #REF! | N47: =IFERROR(K47-I47,"N/A") -> N/A | O47: =IFERROR(N47/I47,"N/A") -> N/A
D49: Operating Expense Ratio | E49: ='UW Pro Forma CF'!C38 -> 0.52832797 | F49: ='UW Pro Forma CF'!E38 -> 0.53686675 | G49: ='UW Pro Forma CF'!F38 -> 0.51489811 | H49: 0.36521038 | I49: 0.48232377 | J49: =J47/J32 -> #DIV/0! | K49: =K47/K32 -> #REF!
D51: *Net Operating Income | E51: ='UW Pro Forma CF'!C40 -> 3348841 | F51: ='UW Pro Forma CF'!E40 -> 3147172.3 | G51: ='UW Pro Forma CF'!F40 -> 3468217.2 | H51: 4591108.4 | I51: 3538203.9 | J51: =J32-J47 -> 0 | K51: =K32-K47 -> #REF! | N51: =IFERROR(K51-I51,"N/A") -> N/A | O51: =IFERROR(N51/I51,"N/A") -> N/A
D53: Capital Expenditures | E53: ='UW Pro Forma CF'!C42 -> 61600 | F53: ='UW Pro Forma CF'!E42 -> 61600 | G53: ='UW Pro Forma CF'!F42 -> 61600 | H53: 61600 | I53: 61600 | J53: =K53 -> 61600 | K53: =L53*E11 -> 61600 | L53: 200
D54: Extraordinary Capital Expenditures
D55: Total Capital Items | E55: ='UW Pro Forma CF'!C44 -> 61600 | F55: ='UW Pro Forma CF'!E44 -> 61600 | G55: ='UW Pro Forma CF'!F44 -> 61600 | H55: 61600 | I55: 61600 | J55: =SUM(J53:J54) -> 61600 | K55: =SUM(K53:K54) -> 61600
D57: *Net Cash Flow | E57: ='UW Pro Forma CF'!C46 -> 3287241 | F57: ='UW Pro Forma CF'!E46 -> 3085572.3 | G57: ='UW Pro Forma CF'!F46 -> 3406617.2 | H57: 4529508.4 | I57: 3476603.9 | J57: =J51-J55 -> -61600 | K57: =K51-K55 -> #REF!
D59: Debt Service - A Note | E59: ='UW Pro Forma CF'!C48 -> 3102916.5 | F59: ='UW Pro Forma CF'!E48 -> 2962470.6 | G59: ='UW Pro Forma CF'!F48 -> 2818742.7 | H59: 3144495.2 | I59: 3138899.6 | J59: ='Operating Statement'!Q183 -> 160683.34 | K59: ='DSCR Calc'!H16 -> 2863478.1 | L59: ="S+"&TEXT('DSCR Calc'!H10*10000,"000")&", SOFR as of "&TEXT($J$14,"MM/DD/YYYY") -> S+225, SOFR as of 12/31/2025
D61: *Net Cash Flow after Debt Service | E61: ='UW Pro Forma CF'!C52 -> 184324.51 | F61: ='UW Pro Forma CF'!E52 -> 123101.67 | G61: ='UW Pro Forma CF'!F52 -> 587874.47 | H61: 1385013.2 | I61: 337704.36 | J61: =J57-J59 -> -222283.34 | K61: =K57-K59 -> #REF!
D63: *DSCR: (Excluding Rate Cap) - A Note | E63: ='UW Pro Forma CF'!C54 -> 1.0594036 | F63: ='UW Pro Forma CF'!E54 -> 1.0415537 | G63: ='UW Pro Forma CF'!F54 -> 1.2085591 | H63: 1.4600462 | I63: 1.1272116 | J63: =J51/J59 -> 0 | K63: =K51/K59 -> #REF!
D65: *DSCR: (Including Rate Cap) - A Note | E65: ='UW Pro Forma CF'!C56 -> 1.25 | F65: ='UW Pro Forma CF'!E56 -> 1.25 | G65: ='UW Pro Forma CF'!F56 -> 1.25 | H65: 1.2209978 | I65: 1.1075869 | J65: =+J57/'DSCR Calc'!$H$17 -> -0.0215123 | K65: ='DSCR Calc'!H20 -> 1.0384201 | L65: DSCR Calc tab
D67: UPB | E67: 47211100 | F67: 49923200 | G67: 52018866 | H67: 46577657 | I67: 47211100 | J67: =E6 -> 47626516 | K67: =J67 -> 47626516 | N67: =K67-I67 -> 415416 | O67: =N67/I67 -> 0.0087991172
D69: *Debt Yield (NCF/Debt Balance) | E69: =E57/E67 -> 0.069628562 | F69: =F57/F67 -> 0.061806381 | G69: =G57/G67 -> 0.06548811 | H69: =H57/H67 -> 0.097246376 | I69: =I57/I67 -> 0.073639545 | J69: =J57/($E$6) -> -0.0012933971 | K69: =K57/$E$6 -> #REF! | L69: 0.065
D71: Source of Financial Data:

Sheet DSCR Calc
A1: 0 | G1: Previous | H1: Current
G2: DY 4Q 2025 | H2: DY 1Q 2026
G3: 46022 | H3: ='MF OSAR'!F6 -> 46112
B5: UPB | G5: 47626516 | H5: =+G5 -> 47626516
B6: Occupancy | G6: 0.8896 | H6: ='MF OSAR'!I16 -> 0.8604
B8: Rate Cap | G8: 0.055 | H8: 0.055
B9: SOFR | G9: 0.0378659 | H9: 0.0368
B10: Spread | G10: 0.0225 | H10: 0.0225
B11: Effective Interest Rate | G11: 0.0603659 | H11: =H9+H10 -> 0.0593
B12: Effective Capped Interest Rate | G12: 0.0603659 | H12: =MIN(H8,H9)+H10 -> 0.0593
B14: Net Cash Flow | G14: 3337238.7 | H14: ='MF OSAR'!I57 -> 2973493.2
B16: Debt Service (Excluding Rate Cap) | G16: 2914948.3 | H16: =(H5*H11)*(365/360) -> 2863478.1
B17: Debt Service (Including Rate Cap) | G17: 2914948.3 | H17: =(H5*H12)*(365/360) -> 2863478.1
B19: DSCR (Excluding Rate Cap) | G19: 1.1448706 | H19: =H14/H16 -> 1.0384201
B20: DSCR (Including Rate Cap) | G20: 1.1448706 | H20: =H14/H17 -> 1.0384201
B22: DY | G22: 0.070071023 | H22: =H14/H5 -> 0.062433565
B25: Notes:

Sheet QoQ Variance
A1: 1
D2: 4Q 2025 | H2: =RIGHT('DSCR Calc'!H2,7) -> 1Q 2026 | L2: QoQ ∆ | P2: Cash Management
C3: Property | D3: Occupancy | E3: NOI | F3: DY | G3: DSCR | H3: Occupancy | I3: NOI | J3: DY | K3: DSCR | L3: Occupancy | M3: NOI | N3: DY | O3: DSCR | P3: In CM? | Q3: Threshold
C4: Memorial Hills [1] | D4: 0.8896 | E4: 3337238.7 | F4: 0.070071023 | G4: 1.1448706 | H4: =+'MF OSAR'!I16 -> 0.8604 | I4: =+'MF OSAR'!I57 -> 2973493.2 | J4: =+'MF OSAR'!I73 -> 0.062433565 | K4: =+'MF OSAR'!I69 -> 1.0384201 | L4: =IF(H4="","-",H4-D4) -> -0.0292 | M4: =IF(I4="","-",I4-E4) -> -363745.49 | N4: =IF(J4="","-",J4-F4) -> -0.0076374575 | O4: =IF(K4="","-",K4-G4) -> -0.10645054 | P4: No | Q4: ='Old OSAR'!L69 -> 0.065
C6: Notes:
C7: [1] 3Q 2025 and 4Q 2025 metrics are based on annnualized T4 as of 09/30/2025 and annualized T7 as of 12/31/2025, respectively.
C8: NOI adjusted per the Loan Agreement.
C9: DSCR includes the benefit of the rate cap.
C10: DY declined 88bps QoQ, driven by a $297.8K (5%) drop in GPR. In February, a flood incident occurred at the Property, which resulted in various units being shifted offline. Consequently, occupancy dropped ~3% QoQ as remidiation work continues to the damaged units.

Sheet Operating Statement
S10: OSAR Code | V10: ='Old OSAR'!J14 -> 46022 | W10: Prior
C11: 04/30/2025 | D11: 05/31/2025 | E11: 06/30/2025 | F11: 07/31/2025 | G11: 08/31/2025 | H11: 09/30/2025 | I11: 10/31/2025 | J11: 11/30/2025 | K11: 12/31/2025 | L11: 01/31/2026 | M11: 02/28/2026 | N11: 03/31/2026 | Q11: T10 Annualized | U11: Line Item | V11: T10 | W11: T7
U12: Gross Potential Rent (3) | V12: =SUMIF($S:$S,U12,$Q:$Q) -> 7109950.2 | W12: 7325240
U13: Less: Vacancy Loss | V13: =SUMIF($S:$S,U13,$Q:$Q) -> -756218.51 | W13: -732311.73
U14: Base Rent (3) | V14: =SUMIF($S:$S,U14,$Q:$Q) -> 0 | W14: 0
Q15: =IF(O15="","",N15*12) | U15: Laundry/Vending Income | V15: =SUMIF($S:$S,U15,$Q:$Q) -> 0 | W15: 0
U16: Parking Income | V16: =SUMIF($S:$S,U16,$Q:$Q) -> 16272.576 | W16: 16552.286
U17: Other Income | V17: =SUMIF($S:$S,U17,$Q:$Q) -> 580172.36 | W17: =359760.69+245805.27 -> 605565.96
B19: INCOME
U20: Effective Gross Income | V20: =SUM(V12:V18) -> 6950176.6 | W20: 7215046.5 | Y20: =V20/W20-1 -> -0.036710771
B21: 4000-000 - Market Rent | C21: 0 | D21: 0 | E21: 899741.5 | F21: 604344 | G21: 600176 | H21: 599866 | I21: 592100 | J21: 594725 | K21: 595038 | L21: 594638 | M21: 596758 | N21: 599233 | Q21: =IFERROR(SUM(E21:N21)*(12/10),"") -> 7531943.4 | S21: =_xlfn.XLOOKUP($B21,Coding!$D:$D,Coding!$F:$F,"x") -> Gross Potential Rent (3)
B22: 4010-000 - Gain/Loss to Lease | C22: 0 | D22: 0 | E22: -39367.52 | F22: -16403.46 | G22: -12324.43 | H22: -11233.73 | I22: -274.56 | J22: -6168.23 | K22: -5337.08 | L22: -6218 | M22: -5778.44 | N22: -8758.25 | Q22: =IFERROR(SUM(E22:N22)*(12/10),"") -> -134236.44 | S22: =_xlfn.XLOOKUP($B22,Coding!$D:$D,Coding!$F:$F,"x") -> Gross Potential Rent (3) | U22: OPERATING EXPENSES
U23: Real Estate Taxes | V23: =SUMIF($S:$S,U23,$Q:$Q) -> 1521691.7 | W23: 1506316.6
B24: Gross Possible | C24: 0 | D24: 0 | E24: 860373.98 | F24: 587940.54 | G24: 587851.57 | H24: 588632.27 | I24: 591825.44 | J24: 588556.77 | K24: 589700.92 | L24: 588420 | M24: 590979.56 | N24: 590474.75 | Q24: =IFERROR(SUM(E24:N24)*(12/10),"") -> 7397707 | U24: Property Insurance | V24: =SUMIF($S:$S,U24,$Q:$Q) -> 68540.496 | W24: 103490.9
U25: Utilities | V25: =SUMIF($S:$S,U25,$Q:$Q) -> 423119.88 | W25: 382429.13
B26: LESS DEDUCTIONS | U26: Repairs and Maintenance | V26: =SUMIF($S:$S,U26,$Q:$Q) -> 333494.4 | W26: 343370.95
B27: 4100-000 - Vacancy Loss | C27: 0 | D27: 0 | E27: -52293.8 | F27: -51385.87 | G27: -52569.63 | H27: -61876.78 | I27: -62929.87 | J27: -65039.73 | K27: -81086.16 | L27: -69354.19 | M27: -52620.42 | N27: -49406.16 | Q27: =IFERROR(SUM(E27:N27)*(12/10),"") -> -718275.13 | S27: =_xlfn.XLOOKUP($B27,Coding!$D:$D,Coding!$F:$F,"x") -> Less: Vacancy Loss | U27: Management Fees | V27: =SUMIF($S:$S,U27,$Q:$Q) -> 125036.59 | W27: 129714.72
B28: 4101-000 - Vacancy-Down Units | C28: 0 | D28: 0 | E28: 0 | F28: 0 | G28: 0 | H28: 0 | I28: 0 | J28: 0 | K28: 0 | L28: 0 | M28: 0 | N28: -31619.48 | Q28: =IFERROR(SUM(E28:N28)*(12/10),"") -> -37943.376 | S28: =_xlfn.XLOOKUP($B28,Coding!$D:$D,Coding!$F:$F,"x") -> Less: Vacancy Loss | U28: Payroll & Benefits | V28: =SUMIF($S:$S,U28,$Q:$Q) -> 510450.74 | W28: 475945.49
B29: 4110-000 - Concessions Market | C29: 0 | D29: 0 | E29: -4460.5 | F29: -13342.5 | G29: -12728.82 | H29: -17006.02 | I29: -21037.15 | J29: 79907.99 | K29: -14200 | L29: 0 | M29: 0 | N29: -8386.75 | Q29: =IFERROR(SUM(E29:N29)*(12/10),"") -> -13504.5 | S29: =_xlfn.XLOOKUP($B29,Coding!$D:$D,Coding!$F:$F,"x") -> Gross Potential Rent (3) | U29: Advertising & Marketing | V29: =SUMIF($S:$S,U29,$Q:$Q) -> 233007.19 | W29: 216404.33
B30: 4110-100 - Concessions-One Time | C30: 0 | D30: 0 | E30: 0 | F30: 0 | G30: -100 | H30: 0 | I30: -1000 | J30: -91240.99 | K30: -5579 | L30: -17874.11 | M30: -29857.75 | N30: -2586 | Q30: =IFERROR(SUM(E30:N30)*(12/10),"") -> -177885.42 | S30: =_xlfn.XLOOKUP($B30,Coding!$D:$D,Coding!$F:$F,"x") -> Gross Potential Rent (3) | U30: Professional Fees | V30: =SUMIF($S:$S,U30,$Q:$Q) -> 5848.896 | W30: 8355.5657
B31: 4110-300 - Concessions -Other | C31: 0 | D31: 0 | E31: 0 | F31: -1000 | G31: -275 | H31: -75.78 | I31: 0 | J31: 0 | K31: 0 | L31: -750 | M31: -225 | N31: -50876.89 | Q31: =IFERROR(SUM(E31:N31)*(12/10),"") -> -63843.204 | S31: =_xlfn.XLOOKUP($B31,Coding!$D:$D,Coding!$F:$F,"x") -> Gross Potential Rent (3) | U31: General and Administrative | V31: =SUMIF($S:$S,U31,$Q:$Q) -> 82527.912 | W31: 63131.743
B32: 4120-000 - Model/Guest Suite | C32: 0 | D32: 0 | E32: -1340 | F32: -3043 | G32: -4041 | H32: -2689.63 | I32: -1645 | J32: -1725 | K32: -3193.65 | L32: -3622 | M32: -1897 | N32: -1897 | Q32: =IFERROR(SUM(E32:N32)*(12/10),"") -> -30111.936 | S32: =_xlfn.XLOOKUP($B32,Coding!$D:$D,Coding!$F:$F,"x") -> Gross Potential Rent (3) | U32: Other Expenses | V32: =SUMIF($S:$S,U32,$Q:$Q) -> 0 | W32: 0
B33: 4130-000 - Employee Units | C33: 0 | D33: 0 | E33: -121.76 | F33: -472 | G33: -472 | H33: -472 | I33: -472 | J33: 0 | K33: 0 | L33: 0 | M33: 0 | N33: 0 | Q33: =IFERROR(SUM(E33:N33)*(12/10),"") -> -2411.712 | S33: =_xlfn.XLOOKUP($B33,Coding!$D:$D,Coding!$F:$F,"x") -> Gross Potential Rent (3) | U33: Ground Rent | V33: =SUMIF($S:$S,U33,$Q:$Q) -> 0 | W33: 0
W34: 0
B35: Total Deductions | C35: 0 | D35: 0 | E35: -58216.06 | F35: -69243.37 | G35: -70186.45 | H35: -82120.21 | I35: -87084.02 | J35: -78097.73 | K35: -104058.81 | L35: -91600.3 | M35: -84600.17 | N35: -144772.28 | Q35: =IFERROR(SUM(E35:N35)*(12/10),"") -> -1043975.3 | U35: Total Operating Expenses | V35: =SUM(V23:V34) -> 3303717.8 | W35: 3229159.5 | Y35: =V35/W35-1 -> 0.023089071
B37: EFFECTIVE ECONOMIC OCCUPANCY | C37: 0 | D37: 0 | E37: 802157.92 | F37: 518697.17 | G37: 517665.12 | H37: 506512.06 | I37: 504741.42 | J37: 510459.04 | K37: 485642.11 | L37: 496819.7 | M37: 506379.39 | N37: 445702.47 | Q37: =IFERROR(SUM(E37:N37)*(12/10),"") -> 6353731.7 | U37: NOI | V37: =V20-V35 -> 3646458.9 | W37: 3985887.1 | Y37: =V37/W37-1 -> -0.08515751
B39: 4140-000 - Rent Write Off | C39: 0 | D39: 0 | E39: -277.84 | F39: 47.19 | G39: -1110.37 | H39: -2067.11 | I39: -210.13 | J39: -4356.76 | K39: 303.92 | L39: -7347.68 | M39: 89.72 | N39: -595.36 | Q39: =IFERROR(SUM(E39:N39)*(12/10),"") -> -18629.304 | S39: =_xlfn.XLOOKUP($B39,Coding!$D:$D,Coding!$F:$F,"x") -> Other Income | U39: Non-Operating Expenses | V39: =SUMIF($S:$S,U39,$O:$O)*12 -> 0 | W39: 0
U40: Interest Expense | V40: =SUMIF($S:$S,U40,$O:$O)*12 -> 0 | W40: 0
B41: . | C41: 0 | D41: 0 | E41: -277.84 | F41: 47.19 | G41: -1110.37 | H41: -2067.11 | I41: -210.13 | J41: -4356.76 | K41: 303.92 | L41: -7347.68 | M41: 89.72 | N41: -595.36 | Q41: =IFERROR(SUM(E41:N41)*(12/10),"") -> -18629.304 | U41: Debt Service | V41: =SUMIF($S:$S,U41,$O:$O)*12 -> 0 | W41: 0
B43: Total Rental Income | C43: 0 | D43: 0 | E43: 801880.08 | F43: 518744.36 | G43: 516554.75 | H43: 504444.95 | I43: 504531.29 | J43: 506102.28 | K43: 485946.03 | L43: 489472.02 | M43: 506469.11 | N43: 445107.11 | Q43: =IFERROR(SUM(E43:N43)*(12/10),"") -> 6335102.4 | U43: Non-Recurring Expenses
U44: HVAC R&M
B45: OTHER INCOME | U45: Plumbing R&M
B46: 4200-000 - Application Fees | C46: 0 | D46: 0 | E46: 600 | F46: 450 | G46: 525 | H46: 450 | I46: 450 | J46: 600 | K46: 1275 | L46: 1050 | M46: 1725 | N46: 75 | Q46: =IFERROR(SUM(E46:N46)*(12/10),"") -> 8640 | S46: =_xlfn.XLOOKUP($B46,Coding!$D:$D,Coding!$F:$F,"x") -> Other Income | U46: FLS R&M
B47: 4201-000 - Administrative Fees | C47: 0 | D47: 0 | E47: 4339.93 | F47: 400 | G47: 1213.95 | H47: 1400 | I47: -200 | J47: 675 | K47: 400 | L47: 0 | M47: 1050 | N47: 0 | Q47: =IFERROR(SUM(E47:N47)*(12/10),"") -> 11134.656 | S47: =_xlfn.XLOOKUP($B47,Coding!$D:$D,Coding!$F:$F,"x") -> Other Income | U47: Bldg Interior - Painting
B48: 4205-000 - Month to Month Fees | C48: 0 | D48: 0 | E48: 1703.34 | F48: 926.17 | G48: 925.82 | H48: 2302.86 | I48: 1823.39 | J48: 1369.51 | K48: 1173.83 | L48: 1908.07 | M48: 603.23 | N48: 2267.73 | Q48: =IFERROR(SUM(E48:N48)*(12/10),"") -> 18004.74 | S48: =_xlfn.XLOOKUP($B48,Coding!$D:$D,Coding!$F:$F,"x") -> Other Income | U48: Tree Trimming
B49: 4210-000 - Late Fees | C49: 0 | D49: 0 | E49: 3121.89 | F49: 2173.34 | G49: 1134.35 | H49: 969.56 | I49: 2007.31 | J49: 736.25 | K49: 1385.22 | L49: 307.34 | M49: 1204.75 | N49: 1144.2 | Q49: =IFERROR(SUM(E49:N49)*(12/10),"") -> 17021.052 | S49: =_xlfn.XLOOKUP($B49,Coding!$D:$D,Coding!$F:$F,"x") -> Other Income | U49: Bldg Exterior R&M
B50: 4211-000 - NSF Fees | C50: 0 | D50: 0 | E50: 200 | F50: -100 | G50: 400 | H50: 400 | I50: 500 | J50: 0 | K50: 100 | L50: 77.38 | M50: 200 | N50: 100 | Q50: =IFERROR(SUM(E50:N50)*(12/10),"") -> 2252.856 | S50: =_xlfn.XLOOKUP($B50,Coding!$D:$D,Coding!$F:$F,"x") -> Other Income | U50: T12 Total
B51: 4238-000 - Amenity Fee | C51: 0 | D51: 0 | E51: 0 | F51: 0 | G51: 5390 | H51: 0 | I51: 9824.1 | J51: -24995.33 | K51: 0 | L51: 0 | M51: 4281.93 | N51: 0 | Q51: =IFERROR(SUM(E51:N51)*(12/10),"") -> -6599.16 | S51: =_xlfn.XLOOKUP($B51,Coding!$D:$D,Coding!$F:$F,"x") -> Other Income
B52: 4244-000 - Cleaning/Damages | C52: 0 | D52: 0 | E52: 125 | F52: 0 | G52: 0 | H52: 135.89 | I52: 1190 | J52: 0 | K52: 215.31 | L52: 300 | M52: 108.08 | N52: 0 | Q52: =IFERROR(SUM(E52:N52)*(12/10),"") -> 2489.136 | S52: =_xlfn.XLOOKUP($B52,Coding!$D:$D,Coding!$F:$F,"x") -> Other Income
B53: 4252-000 - Legal Fees | C53: 0 | D53: 0 | E53: 0 | F53: 368 | G53: 184 | H53: 224 | I53: -1127.9 | J53: 224 | K53: -845.48 | L53: -363 | M53: 278 | N53: 0 | Q53: =IFERROR(SUM(E53:N53)*(12/10),"") -> -1270.056 | S53: =_xlfn.XLOOKUP($B53,Coding!$D:$D,Coding!$F:$F,"x") -> Other Income | U53: NOI Check | V53: =V37+Q38 -> 3646458.9
B54: 4254-000 - Pet Rent | C54: 0 | D54: 0 | E54: 1570.42 | F54: 1545.35 | G54: 1574.52 | H54: 1529.3 | I54: 1476.82 | J54: 1438.85 | K54: 1403.51 | L54: 1407.25 | M54: 1568.69 | N54: 1319.71 | Q54: =IFERROR(SUM(E54:N54)*(12/10),"") -> 17801.304 | S54: =_xlfn.XLOOKUP($B54,Coding!$D:$D,Coding!$F:$F,"x") -> Other Income
B55: 4254-500 - Pet Fees | C55: 0 | D55: 0 | E55: 1782.97 | F55: 0 | G55: 1000 | H55: 500 | I55: 500 | J55: 0 | K55: 1000 | L55: 0 | M55: 2000 | N55: -500 | Q55: =IFERROR(SUM(E55:N55)*(12/10),"") -> 7539.564 | S55: =_xlfn.XLOOKUP($B55,Coding!$D:$D,Coding!$F:$F,"x") -> Other Income
B56: 4256-000 - Key/Lockout Fees | C56: 0 | D56: 0 | E56: 0 | F56: 0 | G56: 0 | H56: 0 | I56: 0 | J56: 0 | K56: 100 | L56: 0 | M56: 0 | N56: 0 | Q56: =IFERROR(SUM(E56:N56)*(12/10),"") -> 120 | S56: =_xlfn.XLOOKUP($B56,Coding!$D:$D,Coding!$F:$F,"x") -> Other Income
B57: 4257-000 - Termination/Notice Fees | C57: 0 | D57: 0 | E57: 3042.15 | F57: 0 | G57: 0 | H57: 0 | I57: 3296 | J57: 3974 | K57: 26812.6 | L57: -18974 | M57: 3614.64 | N57: 921.28 | Q57: =IFERROR(SUM(E57:N57)*(12/10),"") -> 27224.004 | S57: N/A - non recurring | U57: T6 | V57: =SUM(I29:N31)*2 -> -327411.3
B58: 4260-000 - Other Income | C58: 0 | D58: 0 | E58: 8753.1 | F58: 5390.2 | G58: 4915.69 | H58: 5358.88 | I58: -4477.5 | J58: 25394.31 | K58: 5506.96 | L58: 5416.84 | M58: 8009.03 | N58: 16179.91 | Q58: =IFERROR(SUM(E58:N58)*(12/10),"") -> 96536.904 | S58: =_xlfn.XLOOKUP($B58,Coding!$D:$D,Coding!$F:$F,"x") -> Other Income
B59: 4261-000 - Transfer Fees | C59: 0 | D59: 0 | E59: 0 | F59: 0 | G59: 0 | H59: 0 | I59: 0 | J59: 0 | K59: 0 | L59: 500 | M59: 500 | N59: 500 | Q59: =IFERROR(SUM(E59:N59)*(12/10),"") -> 1800 | S59: =_xlfn.XLOOKUP($B59,Coding!$D:$D,Coding!$F:$F,"x") -> Other Income
B60: 4267-000 - Package Locker Fee | C60: 0 | D60: 0 | E60: 4821.91 | F60: 4667.42 | G60: 4581.79 | H60: 4565.84 | I60: 4573.65 | J60: 4587.08 | K60: 4631.15 | L60: 4821.42 | M60: 5133.35 | N60: 4847.54 | Q60: =IFERROR(SUM(E60:N60)*(12/10),"") -> 56677.38 | S60: =_xlfn.XLOOKUP($B60,Coding!$D:$D,Coding!$F:$F,"x") -> Other Income
B61: 4271-000 - Deposit Alternative Income | C61: 0 | D61: 0 | E61: 0 | F61: 0 | G61: 0 | H61: 0 | I61: 0 | J61: 0 | K61: 250 | L61: 0 | M61: 0 | N61: 0 | Q61: =IFERROR(SUM(E61:N61)*(12/10),"") -> 300 | S61: =_xlfn.XLOOKUP($B61,Coding!$D:$D,Coding!$F:$F,"x") -> Other Income
B62: 4272-000 - Pest Control Income | C62: 0 | D62: 0 | E62: 1695.15 | F62: 1739.93 | G62: 1807.89 | H62: 1793.99 | I62: 1748.19 | J62: 1715.28 | K62: 1159.92 | L62: 1574.51 | M62: 1614.55 | N62: 384.03 | Q62: =IFERROR(SUM(E62:N62)*(12/10),"") -> 18280.128 | S62: =_xlfn.XLOOKUP($B62,Coding!$D:$D,Coding!$F:$F,"x") -> Other Income
B63: 4273-000 - Trash Income | C63: 0 | D63: 0 | E63: 13298.98 | F63: 9533.44 | G63: 9567.95 | H63: 9562.18 | I63: 9615.5 | J63: 9972.64 | K63: 9837.66 | L63: 9633.5 | M63: 9921.46 | N63: 7735.21 | Q63: =IFERROR(SUM(E63:N63)*(12/10),"") -> 118414.22 | S63: =_xlfn.XLOOKUP($B63,Coding!$D:$D,Coding!$F:$F,"x") -> Other Income
B64: 4274-000 - Resident Liability Ins. Inc | C64: 0 | D64: 0 | E64: 1046.43 | F64: 139.5 | G64: 837 | H64: 837 | I64: 878.85 | J64: 1088.1 | K64: 1213.65 | L64: 1436.85 | M64: 1760.4 | N64: 1520.55 | Q64: =IFERROR(SUM(E64:N64)*(12/10),"") -> 12909.996 | S64: =_xlfn.XLOOKUP($B64,Coding!$D:$D,Coding!$F:$F,"x") -> Other Income
B65: 4277-000 - Covered Pkng/Carport Inc | C65: 0 | D65: 0 | E65: 1255 | F65: 1255 | G65: -2510 | H65: 1454 | I65: -1454 | J65: 2973.46 | K65: 1381.61 | L65: 1343.87 | M65: 1345 | N65: 1216.11 | Q65: =IFERROR(SUM(E65:N65)*(12/10),"") -> 9912.06 | S65: =_xlfn.XLOOKUP($B65,Coding!$D:$D,Coding!$F:$F,"x") -> Parking Income
B66: 4277-500 - Parking Income | C66: 0 | D66: 0 | E66: 0 | F66: 0 | G66: 3765 | H66: 0 | I66: 3022.06 | J66: -1486.63 | K66: 0 | L66: 0 | M66: 0 | N66: 0 | Q66: =IFERROR(SUM(E66:N66)*(12/10),"") -> 6360.516 | S66: =_xlfn.XLOOKUP($B66,Coding!$D:$D,Coding!$F:$F,"x") -> Parking Income
B67: 4280-000 - Utility Reimbursement Inc | C67: 0 | D67: 0 | E67: 6154.78 | F67: 5818.11 | G67: 5918.1 | H67: 5756.72 | I67: 5772.23 | J67: 5842.33 | K67: 5840.96 | L67: 6032.4 | M67: 6669.94 | N67: 3673.52 | Q67: =IFERROR(SUM(E67:N67)*(12/10),"") -> 68974.908 | S67: =_xlfn.XLOOKUP($B67,Coding!$D:$D,Coding!$F:$F,"x") -> Other Income
B68: 4280-500 - Water/Sewer Income | C68: 0 | D68: 0 | E68: 17439.8 | F68: 14476.41 | G68: 13099.13 | H68: 12863.75 | I68: 13206.36 | J68: 12302.96 | K68: 13980.41 | L68: 14893.65 | M68: 11406.01 | N68: -523.45 | Q68: =IFERROR(SUM(E68:N68)*(12/10),"") -> 147774.04 | S68: =_xlfn.XLOOKUP($B68,Coding!$D:$D,Coding!$F:$F,"x") -> Other Income
B70: Total Other Income | C70: 0 | D70: 0 | E70: 70950.85 | F70: 48782.87 | G70: 54330.19 | H70: 50103.97 | I70: 52625.06 | J70: 46411.81 | K70: 76822.31 | L70: 31366.08 | M70: 62994.06 | N70: 40861.34 | Q70: =IFERROR(SUM(E70:N70)*(12/10),"") -> 642298.25
B72: TOTAL INCOME | C72: 0 | D72: 0 | E72: 872830.93 | F72: 567527.23 | G72: 570884.94 | H72: 554548.92 | I72: 557156.35 | J72: 552514.09 | K72: 562768.34 | L72: 520838.1 | M72: 569463.17 | N72: 485968.45 | Q72: =IFERROR(SUM(E72:N72)*(12/10),"") -> 6977400.6
B74: EXPENSES
B76: MARKETING & LEASING EXPENSES
B77: 5100-000 - Advertising | C77: 0 | D77: 0 | E77: 0 | F77: 7670.08 | G77: 7860.82 | H77: 14597.75 | I77: 8472.26 | J77: 8597.29 | K77: 12229.55 | L77: 1746.56 | M77: 3107 | N77: 2694 | Q77: =IFERROR(SUM(E77:N77)*(12/10),"") -> 80370.372 | S77: =_xlfn.XLOOKUP($B77,Coding!$D:$D,Coding!$F:$F,"x") -> Advertising & Marketing
B78: 5101-000 - PPC/SEM Advertising | C78: 0 | D78: 0 | E78: 0 | F78: 0 | G78: 0 | H78: 0 | I78: 0 | J78: 0 | K78: 0 | L78: 6469.49 | M78: 3000 | N78: 4585.21 | Q78: =IFERROR(SUM(E78:N78)*(12/10),"") -> 16865.64 | S78: =_xlfn.XLOOKUP($B78,Coding!$D:$D,Coding!$F:$F,"x") -> Advertising & Marketing
B79: 5102-000 - Community Website Exp | C79: 0 | D79: 0 | E79: 0 | F79: 0 | G79: 1499.47 | H79: 463.23 | I79: 3746.34 | J79: 5052.34 | K79: 374.1 | L79: 614.98 | M79: 73.76 | N79: -73.76 | Q79: =IFERROR(SUM(E79:N79)*(12/10),"") -> 14100.552 | S79: =_xlfn.XLOOKUP($B79,Coding!$D:$D,Coding!$F:$F,"x") -> Advertising & Marketing
B80: 5110-000 - Locator Fees | C80: 0 | D80: 0 | E80: 0 | F80: 0 | G80: 1134.5 | H80: 2284 | I80: 2570.25 | J80: 7572.29 | K80: -2281.5 | L80: 2922.75 | M80: 9616.25 | N80: 2483.75 | Q80: =IFERROR(SUM(E80:N80)*(12/10),"") -> 31562.748 | S80: =_xlfn.XLOOKUP($B80,Coding!$D:$D,Coding!$F:$F,"x") -> Advertising & Marketing
B81: 5130-000 - Other Marketing | C81: 0 | D81: 0 | E81: 162.58 | F81: 0 | G81: 0 | H81: 0 | I81: 0 | J81: 0 | K81: 0 | L81: 279.23 | M81: 0 | N81: 0 | Q81: =IFERROR(SUM(E81:N81)*(12/10),"") -> 530.172 | S81: =_xlfn.XLOOKUP($B81,Coding!$D:$D,Coding!$F:$F,"x") -> Advertising & Marketing
B82: 5155-000 - Prospect Refreshments | C82: 0 | D82: 0 | E82: 0 | F82: 0 | G82: 0 | H82: 0 | I82: 1132.1 | J82: 3766.61 | K82: 274.23 | L82: 5692.29 | M82: 1681.88 | N82: 1570.07 | Q82: =IFERROR(SUM(E82:N82)*(12/10),"") -> 16940.616 | S82: =_xlfn.XLOOKUP($B82,Coding!$D:$D,Coding!$F:$F,"x") -> Advertising & Marketing
B83: 5160-000 - Resident Promotion/Events | C83: 0 | D83: 0 | E83: 1270.75 | F83: 536.98 | G83: 831.6 | H83: 3588.08 | I83: -1471.07 | J83: -2550.97 | K83: 0 | L83: 0 | M83: 0 | N83: 529.52 | Q83: =IFERROR(SUM(E83:N83)*(12/10),"") -> 3281.868 | S83: =_xlfn.XLOOKUP($B83,Coding!$D:$D,Coding!$F:$F,"x") -> Advertising & Marketing
B84: 5165-000 - Resident Services | C84: 0 | D84: 0 | E84: 0 | F84: 0 | G84: 10210.2 | H84: 5515.23 | I84: 4956.77 | J84: 10703 | K84: 5467 | L84: 9730.59 | M84: 5746.23 | N84: 5467 | Q84: =IFERROR(SUM(E84:N84)*(12/10),"") -> 69355.224 | S84: =_xlfn.XLOOKUP($B84,Coding!$D:$D,Coding!$F:$F,"x") -> Advertising & Marketing
B86: Total Marketing & Leasing | C86: 0 | D86: 0 | E86: 1433.33 | F86: 8207.06 | G86: 21536.59 | H86: 26448.29 | I86: 19406.65 | J86: 33140.56 | K86: 16063.38 | L86: 27455.89 | M86: 23225.12 | N86: 17255.79 | Q86: =IFERROR(SUM(E86:N86)*(12/10),"") -> 233007.19
B88: GENERAL & ADMINISTRATIVE EXP
B89: 5200-000 - Office Supplies | C89: 0 | D89: 0 | E89: 0 | F89: 152.07 | G89: 0 | H89: 249.76 | I89: 5.55 | J89: 190.59 | K89: 91.35 | L89: 174.54 | M89: 572.52 | N89: 0 | Q89: =IFERROR(SUM(E89:N89)*(12/10),"") -> 1723.656 | S89: =_xlfn.XLOOKUP($B89,Coding!$D:$D,Coding!$F:$F,"x") -> General and Administrative
B90: 5210-000 - Office Furn/Equip Rental | C90: 0 | D90: 0 | E90: 0 | F90: 0 | G90: 0 | H90: 0 | I90: 844.1 | J90: 616.86 | K90: 0 | L90: 0 | M90: 0 | N90: 0 | Q90: =IFERROR(SUM(E90:N90)*(12/10),"") -> 1753.152 | S90: =_xlfn.XLOOKUP($B90,Coding!$D:$D,Coding!$F:$F,"x") -> General and Administrative
B91: 5216-000 - Printing & Copier Exp. | C91: 0 | D91: 0 | E91: 264.13 | F91: 265 | G91: 278.37 | H91: 278.37 | I91: -446.2 | J91: 0 | K91: 737.47 | L91: 365.43 | M91: 300 | N91: 0 | Q91: =IFERROR(SUM(E91:N91)*(12/10),"") -> 2451.084 | S91: =_xlfn.XLOOKUP($B91,Coding!$D:$D,Coding!$F:$F,"x") -> General and Administrative
B92: 5217-000 - Computer/Network Exp | C92: 0 | D92: 0 | E92: 0 | F92: 92 | G92: 92 | H92: 156 | I92: 156 | J92: 130 | K92: 156 | L92: 130 | M92: 104 | N92: 156 | Q92: =IFERROR(SUM(E92:N92)*(12/10),"") -> 1406.4 | S92: =_xlfn.XLOOKUP($B92,Coding!$D:$D,Coding!$F:$F,"x") -> General and Administrative
B93: 5218-000 - On-Site Sftwre & Support | C93: 0 | D93: 0 | E93: 10023.79 | F93: 7819.04 | G93: 1240.52 | H93: 510.57 | I93: -6693.17 | J93: -6835.13 | K93: 1585.19 | L93: 4404.23 | M93: 3142.18 | N93: 6271.27 | Q93: =IFERROR(SUM(E93:N93)*(12/10),"") -> 25762.188 | S93: =_xlfn.XLOOKUP($B93,Coding!$D:$D,Coding!$F:$F,"x") -> General and Administrative
B94: 5220-000 - Telephone/Fax | C94: 0 | D94: 0 | E94: 0 | F94: 811.87 | G94: 241.79 | H94: 694.15 | I94: 2521.27 | J94: 2060.52 | K94: -1520.1 | L94: -63.63 | M94: 1515.84 | N94: 3089.43 | Q94: =IFERROR(SUM(E94:N94)*(12/10),"") -> 11221.368 | S94: =_xlfn.XLOOKUP($B94,Coding!$D:$D,Coding!$F:$F,"x") -> General and Administrative
B95: 5225-000 - Answering Service | C95: 0 | D95: 0 | E95: 61.59 | F95: 0 | G95: 311.87 | H95: 425.26 | I95: -244.67 | J95: 0 | K95: 0 | L95: 180.59 | M95: 180.59 | N95: 180.59 | Q95: =IFERROR(SUM(E95:N95)*(12/10),"") -> 1314.984 | S95: =_xlfn.XLOOKUP($B95,Coding!$D:$D,Coding!$F:$F,"x") -> General and Administrative
B96: 5230-000 - Postage & Delivery | C96: 0 | D96: 0 | E96: 25.5 | F96: 56.46 | G96: 138.6 | H96: 0 | I96: 72.35 | J96: 10.45 | K96: 64.36 | L96: 63.14 | M96: 30.17 | N96: 80.12 | Q96: =IFERROR(SUM(E96:N96)*(12/10),"") -> 649.38 | S96: =_xlfn.XLOOKUP($B96,Coding!$D:$D,Coding!$F:$F,"x") -> General and Administrative
B97: 5235-000 - Dues/Meeting | C97: 0 | D97: 0 | E97: 0 | F97: 0 | G97: 1068.8 | H97: 0 | I97: 0 | J97: 0 | K97: 0 | L97: 0 | M97: 0 | N97: 0 | Q97: =IFERROR(SUM(E97:N97)*(12/10),"") -> 1282.56 | S97: =_xlfn.XLOOKUP($B97,Coding!$D:$D,Coding!$F:$F,"x") -> General and Administrative
B98: 5240-000 - Eviction Costs | C98: 0 | D98: 0 | E98: 0 | F98: 0 | G98: 271.72 | H98: 1678.8 | I98: -1127.9 | J98: 2802.34 | K98: 1808.35 | L98: 232.49 | M98: 0 | N98: 611.38 | Q98: =IFERROR(SUM(E98:N98)*(12/10),"") -> 7532.616 | S98: =_xlfn.XLOOKUP($B98,Coding!$D:$D,Coding!$F:$F,"x") -> General and Administrative
B99: 5245-000 - Vehicle/Travel Expense | C99: 0 | D99: 0 | E99: 0 | F99: 0 | G99: 431.32 | H99: 388.68 | I99: 0 | J99: -879.56 | K99: 0 | L99: 998.32 | M99: 366.66 | N99: 0 | Q99: =IFERROR(SUM(E99:N99)*(12/10),"") -> 1566.504 | S99: =_xlfn.XLOOKUP($B99,Coding!$D:$D,Coding!$F:$F,"x") -> General and Administrative
B100: 5250-000 - Permits & Licenses | C100: 0 | D100: 0 | E100: 349.72 | F100: 0 | G100: 224.76 | H100: 581.67 | I100: -449.52 | J100: 640.62 | K100: 0 | L100: 0 | M100: 0 | N100: 1137.75 | Q100: =IFERROR(SUM(E100:N100)*(12/10),"") -> 2982 | S100: =_xlfn.XLOOKUP($B100,Coding!$D:$D,Coding!$F:$F,"x") -> General and Administrative
... B106: 5280-000 - Training/Seminars | C106: 0 | D106: 0 | E106: 0 | F106: 269.4 | G106: 269.4 | H106: 619.4 | I106: 269.4 | J106: 956.6 | K106: 269.4 | L106: 455.17 | M106: 684.73 | N106: 684.73 | Q106: =IFERROR(SUM(E106:N106)*(12/10),"") -> 5373.876 | S106: =_xlfn.XLOOKUP($B106,Coding!$D:$D,Coding!$F:$F,"x") -> General and Administrative
B108: Total General & Administrative Exp | C108: 0 | D108: 0 | E108: 10886.21 | F108: 9877.32 | G108: 5443.66 | H108: 6978.68 | I108: -3396.03 | J108: 1227.91 | K108: 5809.1 | L108: 9841.46 | M108: 8087.77 | N108: 14017.18 | Q108: =IFERROR(SUM(E108:N108)*(12/10),"") -> 82527.912
B110: CONTRACT SERVICES
B111: 5303-000 - Internet Service | C111: 0 | D111: 0 | E111: 0 | F111: 0 | G111: 282.5 | H111: 6250.07 | I111: 290.7 | J111: 1783.7 | K111: 0 | L111: 0 | M111: 2223.9 | N111: 682.55 | Q111: =IFERROR(SUM(E111:N111)*(12/10),"") -> 13816.104 | S111: =_xlfn.XLOOKUP($B111,Coding!$D:$D,Coding!$F:$F,"x") -> Repairs and Maintenance
B112: 5305-000 - Common Area Cleaning | C112: 0 | D112: 0 | E112: 0 | F112: 0 | G112: 0 | H112: 1080 | I112: 1080 | J112: 6830 | K112: 0 | L112: 900 | M112: 2520 | N112: 900 | Q112: =IFERROR(SUM(E112:N112)*(12/10),"") -> 15972 | S112: =_xlfn.XLOOKUP($B112,Coding!$D:$D,Coding!$F:$F,"x") -> Repairs and Maintenance
B113: 5310-000 - Elevator Service | C113: 0 | D113: 0 | E113: 0 | F113: 0 | G113: 0 | H113: 0 | I113: 0 | J113: 0 | K113: 0 | L113: 13749.51 | M113: 0 | N113: 0 | Q113: =IFERROR(SUM(E113:N113)*(12/10),"") -> 16499.412 | S113: =_xlfn.XLOOKUP($B113,Coding!$D:$D,Coding!$F:$F,"x") -> Repairs and Maintenance
B114: 5316-000 - Equipment Service | C114: 0 | D114: 0 | E114: 2002.99 | F114: 0 | G114: 0 | H114: 0 | I114: 19400 | J114: 3880.8 | K114: 0 | L114: 0 | M114: 0 | N114: 270.63 | Q114: =IFERROR(SUM(E114:N114)*(12/10),"") -> 30665.304 | S114: =_xlfn.XLOOKUP($B114,Coding!$D:$D,Coding!$F:$F,"x") -> Repairs and Maintenance
B115: 5320-000 - Exterminating | C115: 0 | D115: 0 | E115: 2232.14 | F115: 566.8 | G115: 2834 | H115: -1133.6 | I115: 1145.28 | J115: 603.62 | K115: 0 | L115: 0 | M115: 567 | N115: 1183.61 | Q115: =IFERROR(SUM(E115:N115)*(12/10),"") -> 9598.62 | S115: =_xlfn.XLOOKUP($B115,Coding!$D:$D,Coding!$F:$F,"x") -> Repairs and Maintenance
B116: 5324-000 - Termite Treatment | C116: 0 | D116: 0 | E116: 0 | F116: 0 | G116: 1136.63 | H116: 0 | I116: 0 | J116: 0 | K116: 0 | L116: 0 | M116: 0 | N116: 0 | Q116: =IFERROR(SUM(E116:N116)*(12/10),"") -> 1363.956 | S116: =_xlfn.XLOOKUP($B116,Coding!$D:$D,Coding!$F:$F,"x") -> Repairs and Maintenance
B117: 5325-000 - Landscaping Contract | C117: 0 | D117: 0 | E117: 1180.15 | F117: 1900 | G117: 1900 | H117: 2137.94 | I117: -1662.06 | J117: 5344.85 | K117: 2137.94 | L117: 2137.94 | M117: 2137.94 | N117: 2137.94 | Q117: =IFERROR(SUM(E117:N117)*(12/10),"") -> 23223.168 | S117: =_xlfn.XLOOKUP($B117,Coding!$D:$D,Coding!$F:$F,"x") -> Repairs and Maintenance
B118: 5327-000 - Landscaping Services | C118: 0 | D118: 0 | E118: 0 | F118: 0 | G118: 0 | H118: 52.33 | I118: 3568.66 | J118: 52.33 | K118: 52.33 | L118: 0 | M118: 0 | N118: 0 | Q118: =IFERROR(SUM(E118:N118)*(12/10),"") -> 4470.78 | S118: =_xlfn.XLOOKUP($B118,Coding!$D:$D,Coding!$F:$F,"x") -> Repairs and Maintenance
B119: 5330-000 - Pool Service | C119: 0 | D119: 0 | E119: 948.38 | F119: 0 | G119: 1092.24 | H119: 364.08 | I119: -364.08 | J119: -910.92 | K119: -302.71 | L119: 238.11 | M119: 655.35 | N119: 245.47 | Q119: =IFERROR(SUM(E119:N119)*(12/10),"") -> 2359.104 | S119: =_xlfn.XLOOKUP($B119,Coding!$D:$D,Coding!$F:$F,"x") -> Repairs and Maintenance
B120: 5335-000 - Security Service | C120: 0 | D120: 0 | E120: 2247.05 | F120: 7447.05 | G120: 7447.05 | H120: 7447.05 | I120: 7447.05 | J120: 7447.05 | K120: -23752.95 | L120: 2247.05 | M120: 7347.05 | N120: 2247.05 | Q120: =IFERROR(SUM(E120:N120)*(12/10),"") -> 33084.6 | S120: =_xlfn.XLOOKUP($B120,Coding!$D:$D,Coding!$F:$F,"x") -> Repairs and Maintenance
B121: 5337-000 - Key Control Contract | C121: 0 | D121: 0 | E121: 0 | F121: 0 | G121: 0 | H121: 0 | I121: 156.89 | J121: 783.45 | K121: -783.45 | L121: 3151.91 | M121: 0 | N121: 0 | Q121: =IFERROR(SUM(E121:N121)*(12/10),"") -> 3970.56 | S121: =_xlfn.XLOOKUP($B121,Coding!$D:$D,Coding!$F:$F,"x") -> Repairs and Maintenance
B122: 5347-000 - Valet Trash Pick-up | C122: 0 | D122: 0 | E122: 0 | F122: 3950.91 | G122: 3950.91 | H122: 3950.51 | I122: 0 | J122: 5017.56 | K122: -9790.02 | L122: 0 | M122: -6976.51 | N122: 3500 | Q122: =IFERROR(SUM(E122:N122)*(12/10),"") -> 4324.032 | S122: =_xlfn.XLOOKUP($B122,Coding!$D:$D,Coding!$F:$F,"x") -> Repairs and Maintenance
... B127: 5390-000 - GAP Renter's Liability Ins | C127: 0 | D127: 0 | E127: 0 | F127: 63.98 | G127: 255.92 | H127: 877.44 | I127: 557.54 | J127: 1169.92 | K127: -237.64 | L127: 831.74 | M127: 941.42 | N127: 1105.94 | Q127: =IFERROR(SUM(E127:N127)*(12/10),"") -> 6679.512 | S127: =_xlfn.XLOOKUP($B127,Coding!$D:$D,Coding!$F:$F,"x") -> Repairs and Maintenance
B129: Total Contract Services | C129: 0 | D129: 0 | E129: 8829.9 | F129: 14049.1 | G129: 21804.76 | H129: 18359.46 | I129: 31992.78 | J129: 32773.59 | K129: -33513.7 | L129: 24371.44 | M129: 9736.51 | N129: 12513.91 | Q129: =IFERROR(SUM(E129:N129)*(12/10),"") -> 169101.3
B131: REPAIR & MAINTENANCE EXPENSES
B132: 5500-000 - Appliance Supplies & Rprs | C132: 0 | D132: 0 | E132: 902.98 | F132: 151.74 | G132: 178.22 | H132: 337.04 | I132: -339.42 | J132: 2823.07 | K132: 6728.78 | L132: 3092.7 | M132: 1220.22 | N132: 177.84 | Q132: =IFERROR(SUM(E132:N132)*(12/10),"") -> 18327.804 | S132: =_xlfn.XLOOKUP($B132,Coding!$D:$D,Coding!$F:$F,"x") -> Repairs and Maintenance
...

Sheet Rent Roll
A1: ASSET LIVING SOUTHEAST, LLC dba JMG REALTY LLC - Memorial Hills
A2: RENT ROLL DETAIL
A3: 05/15/2026 04:22 PM
A4: As of Date: 03/31/2025
A5: Parameters: Properties: - all subproperties-; Show All Unit Designations or Filter by: ALL; Subjournals: ALL; Sort by: Unit; Report Type: Details + Summary; Exclude Formers?: Yes; Show Unit Rent as: Market Rent
A6: Resh ID | B6: Lease ID | C6: Unit | D6: Floorplan | E6: Unit Designation | F6: SQFT | G6: Unit/Lease Status | H6: Name | I6: Move-In | J6: Move-Out | K6: Lease Start | L6: Lease End | M6: Market + Addl. | N6: Required Deposit | O6: Dep On Hand | P6: Balance | Q6: Lease Rent | R6: RENT | S6: TRV | T6: GAS | U6: PACKAGE | V6: AMEN | W6: PET RENT | X6: CARPORT | Y6: TECH FEE | Z6: UTL | AA6: MTOM | AB6: CONo | AC6: CON | AD6: PST | AE6: MOD | AF6: Total Billing
A7: 69 | B7: 424 | C7: 104 | D7: A9b | E7: Conventional | F7: 892 | G7: Occupied | H7: Castro, Sergio | I7: 07/04/2021 | K7: 08/04/2025 | L7: 09/07/2026 | M7: 2025.6 | N7: 0 | O7: 0 | P7: 89.6 | Q7: 1696 | R7: 1696 | S7: 25 | T7: 12.6 | U7: 17 | V7: 20 | W7: 25 | X7: 35 | Y7: 0 | Z7: 0 | AA7: 0 | AB7: 0 | AC7: 0 | AD7: 0 | AE7: 0 | AF7: 1830.6
A8: 171 | B8: 616 | C8: 105 | D8: A10c | E8: Conventional | F8: 1036 | G8: Occupied | H8: Nelson, Ryan | I8: 02/01/2026 | K8: 02/01/2026 | L8: 01/31/2027 | M8: 2370.6 | N8: 0 | O8: 0 | P8: 0 | Q8: 2236 | R8: 2236 | S8: 30 | T8: 12.6 | U8: 22 | V8: 20 | W8: 25 | X8: 35 | Y8: 0 | Z8: 0 | AA8: 0 | AB8: 0 | AC8: 0 | AD8: 0 | AE8: 0 | AF8: 2380.6
A9: 431 | B9: 633 | C9: 106 | D9: B1 | E9: Conventional | F9: 1156 | G9: Occupied | H9: Pumala, Chelsea | I9: 03/21/2026 | K9: 03/21/2026 | L9: 03/20/2027 | M9: 2533.6 | N9: 250 | O9: 250 | P9: 0 | Q9: 2124 | R9: 2124 | S9: 30 | T9: 12.6 | U9: 22 | V9: 20 | W9: 0 | X9: 0 | Y9: 50 | Z9: 0 | AA9: 0 | AB9: 0 | AC9: 0 | AD9: 0 | AE9: 0 | AF9: 2258.6
A10: 160 | B10: 447 | C10: 107 | D10: A13 | E10: Conventional | F10: 1000 | G10: Occupied | H10: Breese, Matt | I10: 08/17/2023 | K10: 07/17/2025 | L10: 07/16/2026 | M10: 2070.6 | N10: 0 | O10: 0 | P10: 57.35 | Q10: 1737 | R10: 1737 | S10: 25 | T10: 12.6 | U10: 17 | V10: 20 | W10: 0 | X10: 0 | Y10: 0 | Z10: 0 | AA10: 0 | AB10: 0 | AC10: 0 | AD10: 0 | AE10: 0 | AF10: 1811.6
A11: 329 | B11: 356 | C11: 108 | D11: B1b | E11: Conventional | F11: 1211 | G11: Occupied | H11: Perez Alvarez, Leonardo | I11: 07/01/2025 | K11: 07/01/2025 | L11: 06/30/2026 | M11: 2363.6 | N11: 0 | O11: 0 | P11: 85.29 | Q11: 2304 | R11: 2304 | S11: 25 | T11: 12.6 | U11: 0 | V11: 0 | W11: 0 | X11: 50 | Y11: 0 | Z11: 0 | AA11: 0 | AB11: 0 | AC11: 0 | AD11: 0 | AE11: 0 | AF11: 2391.6
A12: 394 | B12: 564 | C12: 109 | D12: A5a | E12: Conventional | F12: 730 | G12: Occupied | H12: Maldonado, Arely | I12: 01/23/2026 | K12: 01/23/2026 | L12: 01/22/2027 | M12: 1571.6 | N12: 500 | O12: 500 | P12: 0 | Q12: 1437 | R12: 1437 | S12: 30 | T12: 12.6 | U12: 22 | V12: 0 | W12: 0 | X12: 0 | Y12: 0 | Z12: 0 | AA12: 0 | AB12: 0 | AC12: 0 | AD12: 0 | AE12: 0 | AF12: 1501.6
A13: 0 | B13: 0 | C13: 110 | D13: B1 | E13: Conventional | F13: 1156 | G13: Vacant-Leased | H13: VACANT | M13: 2533.6 | N13: 0 | O13: 0 | P13: 0 | Q13: 0 | R13: 0 | S13: 0 | T13: 0 | U13: 0 | V13: 0 | W13: 0 | X13: 0 | Y13: 0 | Z13: 0 | AA13: 0 | AB13: 0 | AC13: 0 | AD13: 0 | AE13: 0 | AF13: 0
A14: 441 | B14: 691 | C14: 110 | D14: B1 | E14: Conventional | F14: 1156 | G14: Applicant | H14: Olson, Corey | I14: 04/18/2026 | K14: 04/18/2026 | L14: 04/17/2027 | M14: 0 | N14: 250 | O14: 0 | P14: -250 | Q14: 2399 | R14: 2399 | S14: 30 | T14: 12.6 | U14: 22 | V14: 20 | W14: 0 | X14: 0 | Y14: 50 | Z14: 0 | AA14: 0 | AB14: 0 | AC14: 0 | AD14: 0 | AE14: 0 | AF14: 2533.6
A15: 30 | B15: 682 | C15: 111 | D15: B1c | E15: Conventional | F15: 1102 | G15: Occupied | H15: Suarato, Alison | I15: 03/11/2026 | K15: 03/11/2026 | L15: 04/12/2026 | M15: 2488.6 | N15: 250 | O15: 250 | P15: -935.88 | Q15: 2354 | R15: 2354 | S15: 30 | T15: 12.6 | U15: 22 | V15: 20 | W15: 30 | X15: 0 | Y15: 0 | Z15: 0 | AA15: 0 | AB15: 0 | AC15: 0 | AD15: 0 | AE15: 0 | AF15: 2468.6
A16: 401 | B16: 580 | C16: 112 | D16: A11 | E16: Conventional | F16: 908 | G16: Occupied | H16: Fields, Roshanti | I16: 01/02/2026 | K16: 01/02/2026 | L16: 01/02/2027 | M16: 1522.6 | N16: 250 | O16: 250 | P16: 0 | Q16: 1388 | R16: 1388 | S16: 30 | T16: 12.6 | U16: 22 | V16: 0 | W16: 0 | X16: 0 | Y16: 0 | Z16: 0 | AA16: 0 | AB16: 0 | AC16: 0 | AD16: 0 | AE16: 0 | AF16: 1452.6
A17: 111 | B17: 117 | C17: 113 | D17: A6a | E17: Conventional | F17: 791 | G17: Occupied | H17: Brittain III, David | I17: 11/16/2022 | K17: 04/16/2025 | L17: 04/15/2026 | M17: 1791.6 | N17: 0 | O17: 0 | P17: 73.89 | Q17: 1761 | R17: 1761 | S17: 25 | T17: 11.5 | U17: 20 | V17: 20 | W17: 0 | X17: 35 | Y17: 0 | Z17: 0 | AA17: 0 | AB17: 0 | AC17: 0 | AD17: 0 | AE17: 0 | AF17: 1872.5
A18: 248 | B18: 670 | C18: 114 | D18: A9d | E18: Conventional | F18: 958 | G18: Occupied | H18: Scheurich, Alissa | I18: 02/26/2026 | K18: 02/26/2026 | L18: 08/03/2026 | M18: 2280.6 | N18: 0 | O18: 0 | P18: -1708.62 | Q18: 2146 | R18: 2146 | S18: 30 | T18: 12.6 | U18: 22 | V18: 20 | W18: 50 | X18: 0 | Y18: 50 | Z18: 0 | AA18: 0 | AB18: -2059.61 | AC18: 0 | AD18: 0 | AE18: 0 | AF18: 270.99
A19: 37 | B19: 38 | C19: 115 | D19: A3 | E19: Conventional | F19: 609 | G19: Occupied | H19: Bowden, Alethe | I19: 10/18/2019 | K19: 03/27/2025 | L19: 06/26/2026 | M19: 1631.6 | N19: 0 | O19: 0 | P19: 64.09 | Q19: 1493 | R19: 1493 | S19: 25 | T19: 12.6 | U19: 21 | V19: 20 | W19: 0 | X19: 0 | Y19: 0 | Z19: 0 | AA19: 0 | AB19: 0 | AC19: 0 | AD19: 0 | AE19: 0 | AF19: 1571.6
A20: 35 | B20: 416 | C20: 116 | D20: A9 | E20: Conventional | F20: 813 | G20: Occupied-NTV | H20: Stone, Brittany | I20: 05/04/2019 | J20: 04/03/2026 | K20: 07/26/2025 | L20: 02/25/2026 | M20: 2195.6 | N20: 0 | O20: 0 | P20: 83.17 | Q20: 2026 | R20: 2026 | S20: 30 | T20: 12.6 | U20: 22 | V20: 20 | W20: 0 | X20: 0 | Y20: 0 | Z20: 0 | AA20: 350 | AB20: 0 | AC20: 0 | AD20: 0 | AE20: 0 | AF20: 2460.6
A21: 0 | B21: 0 | C21: 121 | D21: A6b | E21: Conventional | F21: 728 | G21: Admin/Down | H21: VACANT | M21: 1891.6 | N21: 0 | O21: 0 | P21: 0 | Q21: 0 | R21: 0 | S21: 0 | T21: 0 | U21: 0 | V21: 0 | W21: 0 | X21: 0 | Y21: 0 | Z21: 0 | AA21: 0 | AB21: 0 | AC21: 0 | AD21: 0 | AE21: 0 | AF21: 0
A22: 0 | B22: 0 | C22: 122 | D22: A8 | E22: Conventional | F22: 787 | G22: Admin/Down | H22: VACANT | M22: 1814.6 | N22: 0 | O22: 0 | P22: 0 | Q22: 0 | R22: 0 | S22: 0 | T22: 0 | U22: 0 | V22: 0 | W22: 0 | X22: 0 | Y22: 0 | Z22: 0 | AA22: 0 | AB22: 0 | AC22: 0 | AD22: 0 | AE22: 0 | AF22: 0
A23: 0 | B23: 0 | C23: 123 | D23: A10b | E23: Conventional | F23: 1037 | G23: Admin/Down | H23: VACANT | M23: 1859.6 | N23: 0 | O23: 0 | P23: 0 | Q23: 0 | R23: 0 | S23: 0 | T23: 0 | U23: 0 | V23: 0 | W23: 0 | X23: 0 | Y23: 0 | Z23: 0 | AA23: 0 | AB23: 0 | AC23: 0 | AD23: 0 | AE23: 0 | AF23: 0
A24: 0 | B24: 0 | C24: 124 | D24: A12 | E24: Conventional | F24: 937 | G24: Admin/Down | H24: VACANT | M24: 1985.6 | N24: 0 | O24: 0 | P24: 0 | Q24: 0 | R24: 0 | S24: 0 | T24: 0 | U24: 0 | V24: 0 | W24: 0 | X24: 0 | Y24: 0 | Z24: 0 | AA24: 0 | AB24: 0 | AC24: 0 | AD24: 0 | AE24: 0 | AF24: 0
A25: 0 | B25: 0 | C25: 125 | D25: B3 | E25: Conventional | F25: 1219 | G25: Admin/Down | H25: VACANT | M25: 2418.6 | N25: 0 | O25: 0 | P25: 0 | Q25: 0 | R25: 0 | S25: 0 | T25: 0 | U25: 0 | V25: 0 | W25: 0 | X25: 0 | Y25: 0 | Z25: 0 | AA25: 0 | AB25: 0 | AC25: 0 | AD25: 0 | AE25: 0 | AF25: 0
A26: 0 | B26: 0 | C26: 126 | D26: B6 | E26: Conventional | F26: 1429 | G26: Admin/Down | H26: VACANT | M26: 2308.6 | N26: 0 | O26: 0 | P26: 0 | Q26: 0 | R26: 0 | S26: 0 | T26: 0 | U26: 0 | V26: 0 | W26: 0 | X26: 0 | Y26: 0 | Z26: 0 | AA26: 0 | AB26: 0 | AC26: 0 | AD26: 0 | AE26: 0 | AF26: 0
A27: 124 | B27: 131 | C27: 127 | D27: A4 | E27: Conventional | F27: 698 | G27: Occupied | H27: Quinn, Megan | I27: 04/01/2023 | K27: 04/01/2025 | L27: 03/31/2026 | M27: 1806.6 | N27: 0 | O27: 0 | P27: -413.67 | Q27: 1730 | R27: 1730 | S27: 25 | T27: 12.6 | U27: 21 | V27: 20 | W27: 30 | X27: 0 | Y27: 0 | Z27: 0 | AA27: 0 | AB27: 0 | AC27: 0 | AD27: 0 | AE27: 0 | AF27: 1838.6
A28: 0 | B28: 0 | C28: 128 | D28: A2 | E28: Conventional | F28: 645 | G28: Admin/Down | H28: VACANT | M28: 1636.6 | N28: 0 | O28: 0 | P28: 0 | Q28: 0 | R28: 0 | S28: 0 | T28: 0 | U28: 0 | V28: 0 | W28: 0 | X28: 0 | Y28: 0 | Z28: 0 | AA28: 0 | AB28: 0 | AC28: 0 | AD28: 0 | AE28: 0 | AF28: 0
A29: 402 | B29: 582 | C29: 129 | D29: A4 | E29: Conventional | F29: 698 | G29: Occupied | H29: Model, Model | I29: 12/08/2025 | K29: 12/08/2025 | L29: 12/07/2026 | M29: 2031.6 | N29: 0 | O29: 0 | P29: -1871.16 | Q29: 0 | R29: 0 | S29: 0 | T29: 0 | U29: 0 | V29: 0 | W29: 0 | X29: 0 | Y29: 0 | Z29: 0 | AA29: 0 | AB29: 0 | AC29: 0 | AD29: 0 | AE29: -1897 | AF29: -1897
A30: 0 | B30: 0 | C30: 130 | D30: A7 | E30: Conventional | F30: 731 | G30: Admin/Down | H30: VACANT | M30: 1756.6 | N30: 0 | O30: 0 | P30: 0 | Q30: 0 | R30: 0 | S30: 0 | T30: 0 | U30: 0 | V30: 0 | W30: 0 | X30: 0 | Y30: 0 | Z30: 0 | AA30: 0 | AB30: 0 | AC30: 0 | AD30: 0 | AE30: 0 | AF30: 0
A31: 326 | B31: 353 | C31: 131 | D31: B5 | E31: Conventional | F31: 1399 | G31: Occupied | H31: Perez, Jennifer | I31: 06/04/2025 | K31: 06/04/2025 | L31: 06/08/2026 | M31: 2713.6 | N31: 0 | O31: 0 | P31: 93.47 | Q31: 2579 | R31: 2579 | S31: 25 | T31: 12.6 | U31: 0 | V31: 0 | W31: 25 | X31: 0 | Y31: 0 | Z31: 0 | AA31: 0 | AB31: 0 | AC31: 0 | AD31: 0 | AE31: 0 | AF31: 2641.6
A32: 208 | B32: 226 | C32: 132 | D32: A1 | E32: Conventional | F32: 570 | G32: Occupied | H32: Richey, Hudson | I32: 03/05/2024 | K32: 05/04/2025 | L32: 08/03/2026 | M32: 1576.6 | N32: 0 | O32: 0 | P32: 79.92 | Q32: 1457 | R32: 1457 | S32: 25 | T32: 11.5 | U32: 17 | V32: 20 | W32: 0 | X32: 0 | Y32: 0 | Z32: 0 | AA32: 0 | AB32: 0 | AC32: 0 | AD32: 0 | AE32: 0 | AF32: 1530.5
A33: 231 | B33: 257 | C33: 133 | D33: A7 | E33: Conventional | F33: 731 | G33: Occupied | H33: Bazzle, Jennifer | I33: 06/24/2024 | K33: 06/24/2025 | L33: 06/23/2026 | M33: 1771.6 | N33: 0 | O33: 0 | P33: -1756.2 | Q33: 1686 | R33: 1686 | S33: 25 | T33: 12.6 | U33: 21 | V33: 20 | W33: 0 | X33: 0 | Y33: 0 | Z33: 0 | AA33: 0 | AB33: 0 | AC33: 0 | AD33: 0 | AE33: 0 | AF33: 1764.6
A34: 286 | B34: 613 | C34: 134 | D34: A5 | E34: Conventional | F34: 698 | G34: Occupied | H34: Sandonato, Austin | I34: 11/26/2024 | K34: 01/01/2026 | L34: 06/30/2026 | M34: 1806.6 | N34: 0 | O34: 0 | P34: 28.32 | Q34: 1822 | R34: 1822 | S34: 30 | T34: 12.6 | U34: 22 | V34: 20 | W34: 30 | X34: 0 | Y34: 0 | Z34: 0 | AA34: 0 | AB34: 0 | AC34: 0 | AD34: 0 | AE34: 0 | AF34: 1936.6
A35: 396 | B35: 566 | C35: 135 | D35: A5 | E35: Conventional | F35: 698 | G35: Occupied | H35: Spuches, Maria | I35: 12/20/2025 | K35: 12/20/2025 | L35: 12/19/2026 | M35: 1656.6 | N35: 250 | O35: 250 | P35: 46.94 | Q35: 1522 | R35: 1522 | S35: 30 | T35: 12.6 | U35: 22 | V35: 0 | W35: 0 | X35: 0 | Y35: 0 | Z35: 0 | AA35: 0 | AB35: 0 | AC35: 0 | AD35: 0 | AE35: 0 | AF35: 1586.6
A36: 27 | B36: 530 | C36: 136 | D36: A13 | E36: Conventional | F36: 1000 | G36: Occupied | H36: Heard, Nehemiah | I36: 02/26/2018 | K36: 10/27/2025 | L36: 04/27/2026 | M36: 2070.6 | N36: 350 | O36: 350 | P36: 42.34 | Q36: 2024 | R36: 2024 | S36: 30 | T36: 12.6 | U36: 22 | V36: 20 | W36: 25 | X36: 35 | Y36: 0 | Z36: 0 | AA36: 0 | AB36: 0 | AC36: 0 | AD36: 0 | AE36: 0 | AF36: 2168.6
A37: 250 | B37: 546 | C37: 137 | D37: A5 | E37: Conventional | F37: 698 | G37: Occupied | H37: Cornavaca, Julio | I37: 08/15/2024 | K37: 11/15/2025 | L37: 02/15/2027 | M37: 1806.6 | N37: 0 | O37: 0 | P37: 96.57 | Q37: 1722 | R37: 1722 | S37: 30 | T37: 12.6 | U37: 22 | V37: 20 | W37: 30 | X37: 35 | Y37: 0 | Z37: 0 | AA37: 0 | AB37: 0 | AC37: 0 | AD37: 0 | AE37: 0 | AF37: 1871.6
A38: 225 | B38: 247 | C38: 138 | D38: A10 | E38: Conventional | F38: 934 | G38: Occupied | H38: Batemon, Jeremy | I38: 06/06/2024 | K38: 06/05/2025 | L38: 06/04/2026 | M38: 2065.6 | N38: 1756 | O38: 1756 | P38: 101.54 | Q38: 1896 | R38: 1896 | S38: 25 | T38: 12.6 | U38: 21 | V38: 20 | W38: 0 | X38: 35 | Y38: 0 | Z38: 0 | AA38: 0 | AB38: 0 | AC38: 0 | AD38: 0 | AE38: 0 | AF38: 2009.6
A39: 84 | B39: 88 | C39: 139 | D39: A12 | E39: Conventional | F39: 937 | G39: Occupied | H39: Travis, Amelia | I39: 02/15/2022 | K39: 02/01/2025 | L39: 03/31/2026 | M39: 1985.6 | N39: 0 | O39: 0 | P39: 63.07 | Q39: 1793 | R39: 1793 | S39: 25 | T39: 12.6 | U39: 20 | V39: 20 | W39: 0 | X39: 35 | Y39: 0 | Z39: 0 | AA39: 0 | AB39: 0 | AC39: 0 | AD39: 0 | AE39: 0 | AF39: 1905.6
A40: 380 | B40: 534 | C40: 140 | D40: B4 | E40: Conventional | F40: 1235 | G40: Occupied | H40: Contreras, Luz | I40: 11/07/2025 | K40: 11/07/2025 | L40: 01/06/2027 | M40: 2493.6 | N40: 250 | O40: 250 | P40: 0 | Q40: 2359 | R40: 2359 | S40: 30 | T40: 12.6 | U40: 22 | V40: 0 | W40: 0 | X40: 0 | Y40: 0 | Z40: 0 | AA40: 0 | AB40: 0 | AC40: 0 | AD40: 0 | AE40: 0 | AF40: 2423.6
A41: 421 | B41: 674 | C41: 141 | D41: B4 | E41: Conventional | F41: 1235 | G41: Occupied | H41: Vaca, Andrea | I41: 03/07/2026 | K41: 03/07/2026 | L41: 06/06/2027 | M41: 2718.6 | N41: 500 | O41: 500 | P41: -2432.3 | Q41: 2159 | R41: 2159 | S41: 30 | T41: 12.6 | U41: 22 | V41: 20 | W41: 0 | X41: 0 | Y41: 50 | Z41: 0 | AA41: 0 | AB41: 0 | AC41: 0 | AD41: 0 | AE41: 0 | AF41: 2293.6
A42: 185 | B42: 199 | C42: 141 | D42: B4 | E42: Conventional | F42: 1235 | G42: Former resident | H42: Bloom, Evelyn | I42: 10/24/2023 | J42: 12/01/2025 | K42: 01/24/2025 | L42: 01/23/2026 | M42: 0 | N42: 0 | O42: 0 | P42: -48.54 | Q42: 2323 | R42: 2323 | S42: 25 | T42: 12.6 | U42: 17 | V42: 20 | W42: 0 | X42: 0 | Y42: 0 | Z42: 0 | AA42: 0 | AB42: 0 | AC42: 0 | AD42: 0 | AE42: 0 | AF42: 2397.6
A43: 207 | B43: 225 | C43: 142 | D43: A12 | E43: Conventional | F43: 937 | G43: Occupied | H43: Bateman, Jennifer | I43: 03/01/2024 | K43: 05/06/2025 | L43: 08/05/2026 | M43: 2000.6 | N43: 0 | O43: 0 | P43: 24.83 | Q43: 1851 | R43: 1851 | S43: 25 | T43: 12.6 | U43: 21 | V43: 20 | W43: 0 | X43: 0 | Y43: 0 | Z43: 0 | AA43: 0 | AB43: 0 | AC43: 0 | AD43: 0 | AE43: 0 | AF43: 1929.6
A44: 0 | B44: 0 | C44: 203 | D44: A9a | E44: Conventional | F44: 833 | G44: Vacant | H44: VACANT | M44: 2080.6 | N44: 0 | O44: 0 | P44: 0 | Q44: 0 | R44: 0 | S44: 0 | T44: 0 | U44: 0 | V44: 0 | W44: 0 | X44: 0 | Y44: 0 | Z44: 0 | AA44: 0 | AB44: 0 | AC44: 0 | AD44: 0 | AE44: 0 | AF44: 0
A45: 104 | B45: 110 | C45: 204 | D45: A9b | E45: Conventional | F45: 892 | G45: Occupied | H45: Phillip, Atiba | I45: 09/13/2022 | K45: 12/07/2024 | L45: 03/06/2026 | M45: 1890.6 | N45: 0 | O45: 0 | P45: -1863.24 | Q45: 1756 | R45: 1756 | S45: 30 | T45: 12.6 | U45: 22 | V45: 20 | W45: 0 | X45: 35 | Y45: 50 | Z45: 0 | AA45: 350 | AB45: 0 | AC45: 0 | AD45: 0 | AE45: 0 | AF45: 2275.6
A46: 317 | B46: 505 | C46: 205 | D46: A10c | E46: Conventional | F46: 1036 | G46: Occupied | H46: Hervey, Dajaunna | I46: 09/11/2025 | K46: 09/11/2025 | L46: 12/10/2026 | M46: 1820.6 | N46: 250 | O46: 250 | P46: 30.13 | Q46: 1595 | R46: 1595 | S46: 30 | T46: 12.6 | U46: 22 | V46: 20 | W46: 0 | X46: 0 | Y46: 0 | Z46: 0 | AA46: 0 | AB46: 0 | AC46: 0 | AD46: 0 | AE46: 0 | AF46: 1679.6
A47: 427 | B47: 627 | C47: 206 | D47: B1 | E47: Conventional | F47: 1156 | G47: Occupied | H47: Ritz, Nicholas | I47: 03/12/2026 | K47: 03/12/2026 | L47: 03/11/2027 | M47: 1973.6 | N47: 250 | O47: 250 | P47: -1889.93 | Q47: 1839 | R47: 1839 | S47: 30 | T47: 12.6 | U47: 22 | V47: 0 | W47: 0 | X47: 0 | Y47: 0 | Z47: 0 | AA47: 0 | AB47: 0 | AC47: 0 | AD47: 0 | AE47: 0 | AF47: 1903.6
A48: 115 | B48: 121 | C48: 207 | D48: A13 | E48: Conventional | F48: 1000 | G48: Occupied | H48: Olson, Ana | I48: 12/16/2022 | K48: 02/15/2025 | L48: 05/14/2026 | M48: 2070.6 | N48: 0 | O48: 0 | P48: 46.28 | Q48: 1991 | R48: 1991 | S48: 25 | T48: 12.6 | U48: 20 | V48: 20 | W48: 25 | X48: 35 | Y48: 0 | Z48: 0 | AA48: 0 | AB48: 0 | AC48: 0 | AD48: 0 | AE48: 0 | AF48: 2128.6
A49: 366 | B49: 493 | C49: 208 | D49: B1b | E49: Conventional | F49: 1211 | G49: Occupied | H49: Truong, Preston | I49: 10/04/2025 | K49: 10/04/2025 | L49: 10/03/2026 | M49: 2028.6 | N49: 250 | O49: 250 | P49: 14.56 | Q49: 1795 | R49: 1795 | S49: 30 | T49: 12.6 | U49: 22 | V49: 0 | W49: 30 | X49: 0 | Y49: 0 | Z49: 0 | AA49: 0 | AB49: 0 | AC49: 0 | AD49: 0 | AE49: 0 | AF49: 1889.6
A50: 186 | B50: 614 | C50: 209 | D50: A11 | E50: Conventional | F50: 908 | G50: Occupied | H50: Sherrill, Justin | I50: 10/28/2023 | K50: 01/01/2026 | L50: 03/31/2026 | M50: 1956.6 | N50: 0 | O50: 0 | P50: 45.04 | Q50: 2030 | R50: 2030 | S50: 0 | T50: 0 | U50: 0 | V50: 20 | W50: 0 | X50: 0 | Y50: 0 | Z50: 0 | AA50: 0 | AB50: 0 | AC50: 0 | AD50: 0 | AE50: 0 | AF50: 2050
A51: 399 | B51: 578 | C51: 210 | D51: B1a | E51: Conventional | F51: 1189 | G51: Occupied | H51: Wallace, Dorothy | I51: 01/20/2026 | K51: 01/20/2026 | L51: 04/19/2027 | M51: 1959.6 | N51: 250 | O51: 250 | P51: 0 | Q51: 1825 | R51: 1825 | S51: 30 | T51: 12.6 | U51: 22 | V51: 0 | W51: 0 | X51: 0 | Y51: 0 | Z51: 0 | AA51: 0 | AB51: 0 | AC51: 0 | AD51: 0 | AE51: 0 | AF51: 1889.6
A52: 275 | B52: 585 | C52: 211 | D52: B1c | E52: Conventional | F52: 1102 | G52: Occupied | H52: Antholzner, Elizabeth | I52: 10/13/2024 | K52: 01/13/2026 | L52: 04/12/2027 | M52: 2128.6 | N52: 0 | O52: 0 | P52: -1086.89 | Q52: 2100 | R52: 2100 | S52: 30 | T52: 12.6 | U52: 22 | V52: 20 | W52: 0 | X52: 0 | Y52: 0 | Z52: 0 | AA52: 0 | AB52: 0 | AC52: 0 | AD52: 0 | AE52: 0 | AF52: 2184.6
A53: 218 | B53: 423 | C53: 212 | D53: A11 | E53: Conventional | F53: 908 | G53: Occupied | H53: Nguyen, Minh Quan | I53: 05/09/2024 | K53: 08/09/2025 | L53: 09/07/2026 | M53: 1956.6 | N53: 0 | O53: 0 | P53: 50.9 | Q53: 1665 | R53: 1665 | S53: 25 | T53: 11.5 | U53: 17 | V53: 20 | W53: 50 | X53: 0 | Y53: 0 | Z53: 0 | AA53: 0 | AB53: 0 | AC53: 0 | AD53: 0 | AE53: 0 | AF53: 1788.5
A54: 83 | B54: 498 | C54: 213 | D54: A6a | E54: Conventional | F54: 791 | G54: Occupied-NTV | H54: Anderson, Craig | I54: 01/31/2022 | J54: 04/19/2026 | K54: 09/06/2025 | L54: 02/05/2026 | M54: 2016.6 | N54: 0 | O54: 0 | P54: 87.3 | Q54: 1820 | R54: 1820 | S54: 30 | T54: 12.6 | U54: 22 | V54: 20 | W54: 0 | X54: 35 | Y54: 0 | Z54: 0 | AA54: 350 | AB54: 0 | AC54: 0 | AD54: 0 | AE54: 0 | AF54: 2289.6
A55: 255 | B55: 700 | C55: 214 | D55: A9d | E55: Conventional | F55: 958 | G55: Occupied | H55: Moss, Blake | I55: 08/17/2024 | K55: 03/30/2026 | L55: 03/29/2027 | M55: 1920.6 | N55: 0 | O55: 0 | P55: 48.43 | Q55: 1891 | R55: 1891 | S55: 30 | T55: 12.6 | U55: 22 | V55: 20 | W55: 0 | X55: 0 | Y55: 0 | Z55: 0 | AA55: 0 | AB55: 0 | AC55: 0 | AD55: 0 | AE55: 0 | AF55: 1975.6
A56: 201 | B56: 216 | C56: 215 | D56: A3 | E56: Conventional | F56: 609 | G56: Occupied | H56: Henderson, Steven | I56: 02/16/2024 | K56: 05/16/2025 | L56: 08/15/2026 | M56: 1631.6 | N56: 0 | O56: 0 | P56: 29.15 | Q56: 1467 | R56: 1467 | S56: 25 | T56: 12.6 | U56: 21 | V56: 20 | W56: 0 | X56: 0 | Y56: 0 | Z56: 0 | AA56: 0 | AB56: 0 | AC56: 0 | AD56: 0 | AE56: 0 | AF56: 1545.6
A57: 92 | B57: 463 | C57: 216 | D57: A9 | E57: Conventional | F57: 813 | G57: Occupied | H57: Cole, Celeste | I57: 06/24/2022 | K57: 09/24/2025 | L57: 09/21/2026 | M57: 1651.6 | N57: 1670 | O57: 1670 | P57: 79.03 | Q57: 1731 | R57: 1731 | S57: 25 | T57: 12.6 | U57: 17 | V57: 20 | W57: 0 | X57: 0 | Y57: 0 | Z57: 11.5 | AA57: 0 | AB57: 0 | AC57: 0 | AD57: 0 | AE57: 0 | AF57: 1817.1
A58: 125 | B58: 412 | C58: 217 | D58: B7 | E58: Conventional | F58: 1539 | G58: Occupied-NTV | H58: Gilmore, Patricia | I58: 04/14/2023 | J58: 05/18/2026 | K58: 07/14/2025 | L58: 05/18/2026 | M58: 2993.6 | N58: 0 | O58: 0 | P58: 90.43 | Q58: 2567 | R58: 2567 | S58: 25 | T58: 11.5 | U58: 17 | V58: 20 | W58: 0 | X58: 0 | Y58: 0 | Z58: 0 | AA58: 0 | AB58: 0 | AC58: 0 | AD58: 0 | AE58: 0 | AF58: 2640.5
A59: 323 | B59: 350 | C59: 218 | D59: B3a | E59: Conventional | F59: 1238 | G59: Occupied-NTV | H59: Martin, Danielle | I59: 05/18/2025 | J59: 05/17/2026 | K59: 05/18/2025 | L59: 05/17/2026 | M59: 2663.6 | N59: 0 | O59: 0 | P59: 99.13 | Q59: 2304 | R59: 2304 | S59: 25 | T59: 12.6 | U59: 0 | V59: 0 | W59: 0 | X59: 0 | Y59: 0 | Z59: 0 | AA59: 0 | AB59: 0 | AC59: 0 | AD59: 0 | AE59: 0 | AF59: 2341.6
A60: 0 | B60: 0 | C60: 220 | D60: B4 | E60: Conventional | F60: 1235 | G60: Admin/Down | H60: VACANT | M60: 2718.6 | N60: 0 | O60: 0 | P60: 0 | Q60: 0 | R60: 0 | S60: 0 | T60: 0 | U60: 0 | V60: 0 | W60: 0 | X60: 0 | Y60: 0 | Z60: 0 | AA60: 0 | AB60: 0 | AC60: 0 | AD60: 0 | AE60: 0 | AF60: 0
A61: 0 | B61: 0 | C61: 221 | D61: A10a | E61: Conventional | F61: 932 | G61: Admin/Down | H61: VACANT | M61: 1930.6 | N61: 0 | O61: 0 | P61: 0 | Q61: 0 | R61: 0 | S61: 0 | T61: 0 | U61: 0 | V61: 0 | W61: 0 | X61: 0 | Y61: 0 | Z61: 0 | AA61: 0 | AB61: 0 | AC61: 0 | AD61: 0 | AE61: 0 | AF61: 0
A62: 0 | B62: 0 | C62: 222 | D62: B4 | E62: Conventional | F62: 1235 | G62: Admin/Down | H62: VACANT | M62: 2718.6 | N62: 0 | O62: 0 | P62: 0 | Q62: 0 | R62: 0 | S62: 0 | T62: 0 | U62: 0 | V62: 0 | W62: 0 | X62: 0 | Y62: 0 | Z62: 0 | AA62: 0 | AB62: 0 | AC62: 0 | AD62: 0 | AE62: 0 | AF62: 0
A63: 0 | B63: 0 | C63: 223 | D63: A10b | E63: Conventional | F63: 1037 | G63: Admin/Down | H63: VACANT | M63: 2010.6 | N63: 0 | O63: 0 | P63: 0 | Q63: 0 | R63: 0 | S63: 0 | T63: 0 | U63: 0 | V63: 0 | W63: 0 | X63: 0 | Y63: 0 | Z63: 0 | AA63: 0 | AB63: 0 | AC63: 0 | AD63: 0 | AE63: 0 | AF63: 0
A64: 0 | B64: 0 | C64: 224 | D64: A12 | E64: Conventional | F64: 937 | G64: Admin/Down | H64: VACANT | M64: 2225.6 | N64: 0 | O64: 0 | P64: 0 | Q64: 0 | R64: 0 | S64: 0 | T64: 0 | U64: 0 | V64: 0 | W64: 0 | X64: 0 | Y64: 0 | Z64: 0 | AA64: 0 | AB64: 0 | AC64: 0 | AD64: 0 | AE64: 0 | AF64: 0
A65: 0 | B65: 0 | C65: 225 | D65: B3 | E65: Conventional | F65: 1219 | G65: Admin/Down | H65: VACANT | M65: 2203.6 | N65: 0 | O65: 0 | P65: 0 | Q65: 0 | R65: 0 | S65: 0 | T65: 0 | U65: 0 | V65: 0 | W65: 0 | X65: 0 | Y65: 0 | Z65: 0 | AA65: 0 | AB65: 0 | AC65: 0 | AD65: 0 | AE65: 0 | AF65: 0
A66: 0 | B66: 0 | C66: 226 | D66: B6 | E66: Conventional | F66: 1429 | G66: Admin/Down | H66: VACANT | M66: 2658.6 | N66: 0 | O66: 0 | P66: 0 | Q66: 0 | R66: 0 | S66: 0 | T66: 0 | U66: 0 | V66: 0 | W66: 0 | X66: 0 | Y66: 0 | Z66: 0 | AA66: 0 | AB66: 0 | AC66: 0 | AD66: 0 | AE66: 0 | AF66: 0
A67: 0 | B67: 0 | C67: 227 | D67: A4 | E67: Conventional | F67: 698 | G67: Admin/Down | H67: VACANT | M67: 1656.6 | N67: 0 | O67: 0 | P67: 0 | Q67: 0 | R67: 0 | S67: 0 | T67: 0 | U67: 0 | V67: 0 | W67: 0 | X67: 0 | Y67: 0 | Z67: 0 | AA67: 0 | AB67: 0 | AC67: 0 | AD67: 0 | AE67: 0 | AF67: 0
A68: 0 | B68: 0 | C68: 228 | D68: A2 | E68: Conventional | F68: 645 | G68: Admin/Down | H68: VACANT | M68: 1876.6 | N68: 0 | O68: 0 | P68: 0 | Q68: 0 | R68: 0 | S68: 0 | T68: 0 | U68: 0 | V68: 0 | W68: 0 | X68: 0 | Y68: 0 | Z68: 0 | AA68: 0 | AB68: 0 | AC68: 0 | AD68: 0 | AE68: 0 | AF68: 0
A69: 0 | B69: 0 | C69: 229 | D69: A4 | E69: Conventional | F69: 698 | G69: Admin/Down | H69: VACANT | M69: 1656.6 | N69: 0 | O69: 0 | P69: 0 | Q69: 0 | R69: 0 | S69: 0 | T69: 0 | U69: 0 | V69: 0 | W69: 0 | X69: 0 | Y69: 0 | Z69: 0 | AA69: 0 | AB69: 0 | AC69: 0 | AD69: 0 | AE69: 0 | AF69: 0
A70: 0 | B70: 0 | C70: 230 | D70: A7 | E70: Conventional | F70: 731 | G70: Admin/Down | H70: VACANT | M70: 1771.6 | N70: 0 | O70: 0 | P70: 0 | Q70: 0 | R70: 0 | S70: 0 | T70: 0 | U70: 0 | V70: 0 | W70: 0 | X70: 0 | Y70: 0 | Z70: 0 | AA70: 0 | AB70: 0 | AC70: 0 | AD70: 0 | AE70: 0 | AF70: 0
A71: 424 | B71: 624 | C71: 231 | D71: B5 | E71: Conventional | F71: 1399 | G71: Occupied | H71: Mabane, Johnathan | I71: 01/26/2026 | K71: 01/26/2026 | L71: 04/25/2027 | M71: 1953.6 | N71: 250 | O71: 200 | P71: 0 | Q71: 1819 | R71: 1819 | S71: 30 | T71: 12.6 | U71: 22 | V71: 0 | W71: 0 | X71: 0 | Y71: 0 | Z71: 0 | AA71: 0 | AB71: 0 | AC71: 0 | AD71: 0 | AE71: 0 | AF71: 1883.6
A72: 0 | B72: 0 | C72: 232 | D72: A7 | E72: Conventional | F72: 731 | G72: Admin/Down | H72: VACANT | M72: 1771.6 | N72: 0 | O72: 0 | P72: 0 | Q72: 0 | R72: 0 | S72: 0 | T72: 0 | U72: 0 | V72: 0 | W72: 0 | X72: 0 | Y72: 0 | Z72: 0 | AA72: 0 | AB72: 0 | AC72: 0 | AD72: 0 | AE72: 0 | AF72: 0
A73: 0 | B73: 0 | C73: 233 | D73: A7 | E73: Conventional | F73: 731 | G73: Admin/Down | H73: VACANT | M73: 1771.6 | N73: 0 | O73: 0 | P73: 0 | Q73: 0 | R73: 0 | S73: 0 | T73: 0 | U73: 0 | V73: 0 | W73: 0 | X73: 0 | Y73: 0 | Z73: 0 | AA73: 0 | AB73: 0 | AC73: 0 | AD73: 0 | AE73: 0 | AF73: 0
A74: 29 | B74: 639 | C74: 234 | D74: A5 | E74: Conventional | F74: 698 | G74: Occupied | H74: Consulate General of India Hou, * | I74: 04/01/2018 | K74: 03/12/2026 | L74: 03/11/2027 | M74: 1656.6 | N74: 250 | O74: 250 | P74: 0 | Q74: 1458 | R74: 1458 | S74: 25 | T74: 12.6 | U74: 17 | V74: 20 | W74: 0 | X74: 0 | Y74: 50 | Z74: 0 | AA74: 0 | AB74: 0 | AC74: 0 | AD74: 0 | AE74: 0 | AF74: 1582.6
A75: 246 | B75: 433 | C75: 235 | D75: A5 | E75: Conventional | F75: 698 | G75: Occupied | H75: Shaik, Zeelan Basha | I75: 07/27/2024 | K75: 08/27/2025 | L75: 08/24/2026 | M75: 1656.6 | N75: 0 | O75: 0 | P75: -1717.2 | Q75: 1572 | R75: 1572 | S75: 25 | T75: 11.5 | U75: 17 | V75: 20 | W75: 0 | X75: 0 | Y75: 0 | Z75: 0 | AA75: 0 | AB75: 0 | AC75: 0 | AD75: 0 | AE75: 0 | AF75: 1645.5
A76: 386 | B76: 555 | C76: 236 | D76: A13 | E76: Conventional | F76: 1000 | G76: Occupied | H76: Gonzales, Caroline | I76: 11/17/2025 | K76: 11/17/2025 | L76: 07/16/2026 | M76: 1779.6 | N76: 250 | O76: 250 | P76: 40.74 | Q76: 1645 | R76: 1645 | S76: 30 | T76: 12.6 | U76: 22 | V76: 0 | W76: 0 | X76: 0 | Y76: 0 | Z76: 0 | AA76: 0 | AB76: 0 | AC76: 0 | AD76: 0 | AE76: 0 | AF76: 1709.6
A77: 32 | B77: 677 | C77: 237 | D77: A5 | E77: Conventional | F77: 698 | G77: Occupied | H77: Morales, Ekaterina | I77: 03/18/2019 | K77: 03/01/2026 | L77: 10/31/2026 | M77: 1656.6 | N77: 0 | O77: 0 | P77: 94.41 | Q77: 1712 | R77: 1712 | S77: 30 | T77: 12.6 | U77: 22 | V77: 20 | W77: 0 | X77: 0 | Y77: 50 | Z77: 0 | AA77: 0 | AB77: 0 | AC77: 0 | AD77: 0 | AE77: 0 | AF77: 1846.6
A78: 338 | B78: 397 | C78: 238 | D78: A10c | E78: Conventional | F78: 1036 | G78: Occupied | H78: Weicks, Christian | I78: 07/11/2025 | K78: 07/11/2025 | L78: 06/29/2026 | M78: 1995.6 | N78: 0 | O78: 0 | P78: 40.47 | Q78: 1795 | R78: 1795 | S78: 25 | T78: 12.6 | U78: 0 | V78: 0 | W78: 0 | X78: 0 | Y78: 0 | Z78: 0 | AA78: 0 | AB78: 0 | AC78: 0 | AD78: 0 | AE78: 0 | AF78: 1832.6
A79: 434 | B79: 636 | C79: 239 | D79: A12 | E79: Conventional | F79: 937 | G79: Occupied | H79: Frank, Avery | I79: 02/07/2026 | K79: 02/07/2026 | L79: 02/06/2027 | M79: 1785.6 | N79: 250 | O79: 250 | P79: 0 | Q79: 1651 | R79: 1651 | S79: 30 | T79: 12.6 | U79: 22 | V79: 20 | W79: 30 | X79: 0 | Y79: 50 | Z79: 0 | AA79: 0 | AB79: 0 | AC79: -825.5 | AD79: 0 | AE79: 0 | AF79: 990.1
A80: 322 | B80: 349 | C80: 240 | D80: B4 | E80: Conventional | F80: 1235 | G80: Occupied | H80: Dearing, Noah | I80: 05/09/2025 | K80: 05/09/2025 | L80: 05/08/2026 | M80: 2493.6 | N80: 0 | O80: 0 | P80: 27.22 | Q80: 2259 | R80: 2259 | S80: 25 | T80: 12.6 | U80: 0 | V80: 0 | W80: 0 | X80: 0 | Y80: 0 | Z80: 0 | AA80: 0 | AB80: 0 | AC80: 0 | AD80: 0 | AE80: 0 | AF80: 2296.6
A81: 172 | B81: 473 | C81: 241 | D81: B4 | E81: Conventional | F81: 1235 | G81: Occupied | H81: Pineau, Clarissa | I81: 09/11/2023 | K81: 09/11/2025 | L81: 11/10/2026 | M81: 2493.6 | N81: 0 | O81: 0 | P81: 99.75 | Q81: 2359 | R81: 2359 | S81: 25 | T81: 11.5 | U81: 17 | V81: 20 | W81: 25 | X81: 0 | Y81: 0 | Z81: 0 | AA81: 0 | AB81: 0 | AC81: 0 | AD81: 0 | AE81: 0 | AF81: 2457.5
A82: 179 | B82: 517 | C82: 242 | D82: A12 | E82: Conventional | F82: 937 | G82: Occupied | H82: Gilmore, Emma | I82: 10/04/2023 | K82: 09/04/2025 | L82: 09/03/2026 | M82: 2000.6 | N82: 0 | O82: 0 | P82: 58.11 | Q82: 1916 | R82: 1916 | S82: 25 | T82: 12.6 | U82: 0 | V82: 0 | W82: 0 | X82: 0 | Y82: 0 | Z82: 0 | AA82: 0 | AB82: 0 | AC82: 0 | AD82: 0 | AE82: 0 | AF82: 1953.6
A83: 417 | B83: 608 | C83: 301 | D83: A7a | E83: Conventional | F83: 784 | G83: Occupied | H83: Baker, Marcelle | I83: 02/06/2026 | K83: 02/06/2026 | L83: 02/05/2027 | M83: 2001.6 | N83: 250 | O83: 250 | P83: -2.1 | Q83: 1867 | R83: 1867 | S83: 30 | T83: 12.6 | U83: 22 | V83: 0 | W83: 0 | X83: 0 | Y83: 0 | Z83: 0 | AA83: 0 | AB83: 0 | AC83: -1867 | AD83: 0 | AE83: 0 | AF83: 64.6
A84: 342 | B84: 401 | C84: 302 | D84: A6 | E84: Conventional | F84: 684 | G84: Occupied | H84: Morris, Mary | I84: 06/05/2025 | K84: 06/05/2025 | L84: 06/04/2026 | M84: 1621.6 | N84: 250 | O84: 250 | P84: 32.53 | Q84: 1557 | R84: 1557 | S84: 25 | T84: 12.6 | U84: 0 | V84: 0 | W84: 0 | X84: 0 | Y84: 0 | Z84: 0 | AA84: 0 | AB84: 0 | AC84: 0 | AD84: 0 | AE84: 0 | AF84: 1594.6
A85: 222 | B85: 445 | C85: 303 | D85: A9a | E85: Conventional | F85: 833 | G85: Occupied-NTV | H85: Misiaszek, McKenzie | I85: 05/25/2024 | J85: 04/27/2026 | K85: 08/25/2025 | L85: 04/27/2026 | M85: 2080.6 | N85: 0 | O85: 0 | P85: 56.05 | Q85: 1528 | R85: 1528 | S85: 25 | T85: 11.5 | U85: 17 | V85: 20 | W85: 0 | X85: 0 | Y85: 0 | Z85: 0 | AA85: 0 | AB85: 0 | AC85: 0 | AD85: 0 | AE85: 0 | AF85: 1601.5
A86: 206 | B86: 459 | C86: 304 | D86: A9b | E86: Conventional | F86: 892 | G86: Occupied | H86: Mares, Kendall | I86: 09/01/2025 | K86: 09/01/2025 | L86: 05/16/2026 | M86: 1689.6 | N86: 250 | O86: 250 | P86: 42.71 | Q86: 1550 | R86: 1550 | S86: 30 | T86: 12.6 | U86: 22 | V86: 20 | W86: 0 | X86: 0 | Y86: 0 | Z86: 0 | AA86: 0 | AB86: 0 | AC86: 0 | AD86: 0 | AE86: 0 | AF86: 1634.6
A87: 403 | B87: 586 | C87: 305 | D87: A10c | E87: Conventional | F87: 1036 | G87: Occupied | H87: Wells, Wesley | I87: 12/31/2025 | K87: 12/31/2025 | L87: 12/30/2026 | M87: 1716.6 | N87: 500 | O87: 500 | P87: 1.67 | Q87: 1582 | R87: 1582 | S87: 30 | T87: 12.6 | U87: 22 | V87: 0 | W87: 0 | X87: 0 | Y87: 0 | Z87: 0 | AA87: 0 | AB87: 0 | AC87: 0 | AD87: 0 | AE87: 0 | AF87: 1646.6
A88: 71 | B88: 74 | C88: 306 | D88: B1 | E88: Conventional | F88: 1156 | G88: Occupied | H88: Hernandez, David | I88: 07/20/2021 | K88: 07/28/2023 | L88: 10/19/2024 | M88: 2173.6 | N88: 0 | O88: 0 | P88: 36.61 | Q88: 1893 | R88: 1893 | S88: 25 | T88: 12.6 | U88: 17 | V88: 20 | W88: 0 | X88: 0 | Y88: 0 | Z88: 0 | AA88: 350 | AB88: 0 | AC88: 0 | AD88: 0 | AE88: 0 | AF88: 2317.6
A89: 0 | B89: 0 | C89: 307 | D89: A13 | E89: Conventional | F89: 1000 | G89: Vacant | H89: VACANT | M89: 2295.6 | N89: 0 | O89: 0 | P89: 0 | Q89: 0 | R89: 0 | S89: 0 | T89: 0 | U89: 0 | V89: 0 | W89: 0 | X89: 0 | Y89: 0 | Z89: 0 | AA89: 0 | AB89: 0 | AC89: 0 | AD89: 0 | AE89: 0 | AF89: 0
A90: 211 | B90: 229 | C90: 308 | D90: B1b | E90: Conventional | F90: 1211 | G90: Occupied | H90: Lamb III, Maurice | I90: 03/15/2024 | K90: 04/11/2025 | L90: 07/10/2026 | M90: 2228.6 | N90: 0 | O90: 0 | P90: 96.41 | Q90: 2138 | R90: 2138 | S90: 25 | T90: 12.6 | U90: 20 | V90: 20 | W90: 0 | X90: 0 | Y90: 0 | Z90: 0 | AA90: 0 | AB90: 0 | AC90: 0 | AD90: 0 | AE90: 0 | AF90: 2215.6
A91: 191 | B91: 205 | C91: 309 | D91: A11 | E91: Conventional | F91: 908 | G91: Occupied | H91: Overcash, David | I91: 11/27/2023 | K91: 02/27/2025 | L91: 05/26/2026 | M91: 1956.6 | N91: 0 | O91: 0 | P91: 0 | Q91: 1850 | R91: 1850 | S91: 25 | T91: 11.5 | U91: 20 | V91: 20 | W91: 0 | X91: 0 | Y91: 0 | Z91: 0 | AA91: 0 | AB91: 0 | AC91: 0 | AD91: 0 | AE91: 0 | AF91: 1926.5
A92: 138 | B92: 499 | C92: 310 | D92: B1a | E92: Conventional | F92: 1189 | G92: Occupied | H92: Calautti, Steven | I92: 06/20/2023 | K92: 09/20/2025 | L92: 11/19/2026 | M92: 2203.6 | N92: 0 | O92: 0 | P92: 0 | Q92: 1976 | R92: 1976 | S92: 25 | T92: 11.5 | U92: 17 | V92: 20 | W92: 0 | X92: 35 | Y92: 0 | Z92: 0 | AA92: 0 | AB92: 0 | AC92: 0 | AD92: 0 | AE92: 0 | AF92: 2084.5
A93: 126 | B93: 419 | C93: 311 | D93: B1c | E93: Conventional | F93: 1102 | G93: Occupied-NTV | H93: McNamara, Connor | I93: 04/19/2023 | J93: 04/20/2026 | K93: 07/19/2025 | L93: 04/20/2026 | M93: 2353.6 | N93: 0 | O93: 0 | P93: 61.94 | Q93: 1916 | R93: 1916 | S93: 25 | T93: 11.5 | U93: 17 | V93: 20 | W93: 0 | X93: 0 | Y93: 0 | Z93: 0 | AA93: 0 | AB93: 0 | AC93: 0 | AD93: 0 | AE93: 0 | AF93: 1989.5
A94: 347 | B94: 406 | C94: 312 | D94: A11 | E94: Conventional | F94: 908 | G94: Occupied | H94: Bollinger, James | I94: 06/24/2025 | K94: 06/24/2025 | L94: 06/23/2026 | M94: 1956.6 | N94: 250 | O94: 250 | P94: 45.31 | Q94: 1872 | R94: 1872 | S94: 25 | T94: 12.6 | U94: 0 | V94: 0 | W94: 0 | X94: 0 | Y94: 0 | Z94: 0 | AA94: 0 | AB94: 0 | AC94: 0 | AD94: 0 | AE94: 0 | AF94: 1909.6
A95: 214 | B95: 234 | C95: 313 | D95: A6a | E95: Conventional | F95: 791 | G95: Occupied-NTV | H95: Fehring, Darien | I95: 03/30/2024 | J95: 04/30/2026 | K95: 04/01/2025 | L95: 04/30/2026 | M95: 2016.6 | N95: 0 | O95: 0 | P95: 33.44 | Q95: 1566 | R95: 1566 | S95: 25 | T95: 12.6 | U95: 21 | V95: 20 | W95: 0 | X95: 0 | Y95: 0 | Z95: 0 | AA95: 0 | AB95: 0 | AC95: 0 | AD95: 0 | AE95: 0 | AF95: 1644.6
A96: 159 | B96: 527 | C96: 314 | D96: A9d | E96: Conventional | F96: 958 | G96: Occupied | H96: Smith, Gregory | I96: 08/14/2023 | K96: 11/14/2025 | L96: 02/15/2027 | M96: 1920.6 | N96: 0 | O96: 0 | P96: -6.64 | Q96: 1721 | R96: 1721 | S96: 30 | T96: 11.5 | U96: 22 | V96: 20 | W96: 0 | X96: 0 | Y96: 0 | Z96: 0 | AA96: 0 | AB96: 0 | AC96: 0 | AD96: 0 | AE96: 0 | AF96: 1804.5
A97: 54 | B97: 662 | C97: 315 | D97: A3 | E97: Conventional | F97: 609 | G97: Occupied | H97: Ubilla, Mariela | I97: 02/23/2026 | K97: 02/23/2026 | L97: 05/22/2027 | M97: 1856.6 | N97: 0 | O97: 0 | P97: -46.97 | Q97: 1500 | R97: 1500 | S97: 30 | T97: 12.6 | U97: 22 | V97: 20 | W97: 0 | X97: 0 | Y97: 0 | Z97: 0 | AA97: 0 | AB97: -500 | AC97: 0 | AD97: 0 | AE97: 0 | AF97: 1084.6
A98: 318 | B98: 345 | C98: 316 | D98: A9 | E98: Conventional | F98: 813 | G98: Occupied | H98: Infante, Laura | I98: 04/19/2025 | K98: 04/19/2025 | L98: 04/18/2026 | M98: 1835.6 | N98: 0 | O98: 0 | P98: 30.06 | Q98: 1751 | R98: 1751 | S98: 25 | T98: 12.6 | U98: 21 | V98: 20 | W98: 0 | X98: 0 | Y98: 0 | Z98: 0 | AA98: 0 | AB98: 0 | AC98: 0 | AD98: 5 | AE98: 0 | AF98: 1834.6
A99: 78 | B99: 81 | C99: 317 | D99: B7 | E99: Conventional | F99: 1539 | G99: Occupied | H99: Ahuja, Sarang | I99: 11/29/2021 | K99: 01/29/2025 | L99: 04/28/2026 | M99: 2768.6 | N99: 2425 | O99: 2425 | P99: -24.33 | Q99: 2520 | R99: 2520 | S99: 25 | T99: 12.6 | U99: 17 | V99: 20 | W99: 0 | X99: 0 | Y99: 0 | Z99: 0 | AA99: 0 | AB99: 0 | AC99: 0 | AD99: 0 | AE99: 0 | AF99: 2594.6
A100: 252 | B100: 531 | C100: 318 | D100: B3a | E100: Conventional | F100: 1238 | G100: Occupied | H100: Siroky, Allison | I100: 08/16/2024 | K100: 11/16/2025 | L100: 11/15/2026 | M100: 2438.6 | N100: 0 | O100: 0 | P100: -2033.31 | Q100: 2098 | R100: 2098 | S100: 30 | T100: 11.5 | U100: 22 | V100: 20 | W100: 0 | X100: 0 | Y100: 0 | Z100: 0 | AA100: 0 | AB100: 0 | AC100: 0 | AD100: 0 | AE100: 0 | AF100: 2181.5
...

Sheet Paydown Analysis
B2: Paydown Analysis
B3: Arboretum at South Mountain | D3: ='DSCR Calc'!H3 -> 46112
B4: Current DY | D4: ='DSCR Calc'!H22 -> 0.062433565
B5: Target DY | D5: 0.0625
B7: Current Principal | D7: ='DSCR Calc'!H5 -> 47626516
B8: Paydown | D8: -22020120
B9: Adjusted Principal | D9: =D7+D8 -> 25606396
B11: Current Net Cash Flow | D11: ='DSCR Calc'!H14 -> 2973493.2
B13: Resulting DY | D13: =D11/D9 -> 0.11612306

Sheet Aged Receivables
A1: ASSET LIVING SOUTHEAST, LLC dba JMG REALTY LLC - Memorial Hills - Central DELINQUENT AND PREPAID FISCAL PERIOD 032026 AS OF 05/17/2026 05/19/2026 09:16 AM Parameters: Report Type: Details Subproperties: ALL Subjournals: ALL Statuses to include: Applicant,Approved applicant,Former applicant,Pending resident,Current resident,Former resident; Include delinquencies that equal NTV Credit? Yes; Exclude transactions payable in arrears: Yes; Delinquency range 0.00 through 99999999.00; Aging Columns: Fiscal; Filter type: ALL; Show Prepaid As Allocated: No; Include outstanding deposits: No; Hide all PII data: No; Delinquent Comments: Current only
A2: Resh ID | B2: Lease ID | C2: Bldg/Unit | D2: Name | E2: Phone Number | F2: Email | G2: Status | H2: Move-In/Out | I2: Code Description | J2: Total Prepaid | K2: Total Delinquent | L2: D | M2: O | N2: Net Balance | O2: Current | P2: 30 Days | Q2: 60 Days | R2: 90+ Days | S2: Prorate Credit | T2: Deposits Held | U2: Outstanding Deposit | V2: #Late | W2: #NSF | X2: Comment Date | Y2: Leasing Agent
A3: 69 | B3: 424 | C3: 104 | D3: Castro, Sergio | E3: N/A | F3: Castrosergio3000@gmail.com | G3: Current resident | H3: 07/04/2021 | I3: GAS | J3: 0 | K3: 8.64 | N3: 8.64 | O3: 8.64 | P3: 0 | Q3: 0 | R3: 0 | S3: 0 | T3: 0 | U3: 0 | V3: 1 | W3: 0
A4: 69 | B4: 424 | C4: 104 | D4: Castro, Sergio | E4: N/A | F4: Castrosergio3000@gmail.com | G4: Current resident | H4: 07/04/2021 | I4: PST | J4: 0 | K4: 6.5 | N4: 6.5 | O4: 6.5 | P4: 0 | Q4: 0 | R4: 0 | S4: 0 | T4: 0 | U4: 0 | V4: 1 | W4: 0
A5: 69 | B5: 424 | C5: 104 | D5: Castro, Sergio | E5: N/A | F5: Castrosergio3000@gmail.com | G5: Current resident | H5: 07/04/2021 | I5: TRV | J5: 0 | K5: 9.83 | N5: 9.83 | O5: 9.83 | P5: 0 | Q5: 0 | R5: 0 | S5: 0 | T5: 0 | U5: 0 | V5: 1 | W5: 0
A6: 69 | B6: 424 | C6: 104 | D6: Castro, Sergio | E6: N/A | F6: Castrosergio3000@gmail.com | G6: Current resident | H6: 07/04/2021 | I6: WSR | J6: 0 | K6: 64.63 | N6: 64.63 | O6: 64.63 | P6: 0 | Q6: 0 | R6: 0 | S6: 0 | T6: 0 | U6: 0 | V6: 1 | W6: 0
A7: 160 | B7: 447 | C7: 107 | D7: Breese, Matt Thomas | E7: N/A | F7: mtbreese1@gmail.com | G7: Current resident | H7: 08/17/2023 | I7: GAS | J7: 0 | K7: 5.25 | N7: 5.25 | O7: 5.25 | P7: 0 | Q7: 0 | R7: 0 | S7: 0 | T7: 0 | U7: 0 | V7: 0 | W7: 0
A8: 160 | B8: 447 | C8: 107 | D8: Breese, Matt Thomas | E8: N/A | F8: mtbreese1@gmail.com | G8: Current resident | H8: 08/17/2023 | I8: PST | J8: 0 | K8: 6.5 | N8: 6.5 | O8: 6.5 | P8: 0 | Q8: 0 | R8: 0 | S8: 0 | T8: 0 | U8: 0 | V8: 0 | W8: 0
A9: 160 | B9: 447 | C9: 107 | D9: Breese, Matt Thomas | E9: N/A | F9: mtbreese1@gmail.com | G9: Current resident | H9: 08/17/2023 | I9: TRV | J9: 0 | K9: 9.83 | N9: 9.83 | O9: 9.83 | P9: 0 | Q9: 0 | R9: 0 | S9: 0 | T9: 0 | U9: 0 | V9: 0 | W9: 0
A10: 160 | B10: 447 | C10: 107 | D10: Breese, Matt Thomas | E10: N/A | F10: mtbreese1@gmail.com | G10: Current resident | H10: 08/17/2023 | I10: WSR | J10: 0 | K10: 35.77 | N10: 35.77 | O10: 35.77 | P10: 0 | Q10: 0 | R10: 0 | S10: 0 | T10: 0 | U10: 0 | V10: 0 | W10: 0
A11: 329 | B11: 356 | C11: 108 | D11: Perez Alvarez, Leonardo Alberto | E11: (786) 757-1399 | F11: perezleo74@gmail.com | G11: Current resident | H11: 07/01/2025 | I11: GAS | J11: 0 | K11: 11.42 | N11: 11.42 | O11: 11.42 | P11: 0 | Q11: 0 | R11: 0 | S11: 0 | T11: 0 | U11: 0 | V11: 2 | W11: 0
A12: 329 | B12: 356 | C12: 108 | D12: Perez Alvarez, Leonardo Alberto | E12: (786) 757-1399 | F12: perezleo74@gmail.com | G12: Current resident | H12: 07/01/2025 | I12: PST | J12: 0 | K12: 5 | N12: 5 | O12: 5 | P12: 0 | Q12: 0 | R12: 0 | S12: 0 | T12: 0 | U12: 0 | V12: 2 | W12: 0
A13: 329 | B13: 356 | C13: 108 | D13: Perez Alvarez, Leonardo Alberto | E13: (786) 757-1399 | F13: perezleo74@gmail.com | G13: Current resident | H13: 07/01/2025 | I13: TRV | J13: 0 | K13: 4.45 | N13: 4.45 | O13: 4.45 | P13: 0 | Q13: 0 | R13: 0 | S13: 0 | T13: 0 | U13: 0 | V13: 2 | W13: 0
A14: 329 | B14: 356 | C14: 108 | D14: Perez Alvarez, Leonardo Alberto | E14: (786) 757-1399 | F14: perezleo74@gmail.com | G14: Current resident | H14: 07/01/2025 | I14: WSR | J14: 0 | K14: 64.42 | N14: 64.42 | O14: 64.42 | P14: 0 | Q14: 0 | R14: 0 | S14: 0 | T14: 0 | U14: 0 | V14: 2 | W14: 0
A15: 30 | B15: 682 | C15: 111 | D15: Alison Suarato | F15: asuarato@gmail.com | G15: Former resident | H15: 04/12/2026 | I15: PMTFLEX | J15: -949.83 | K15: 0 | N15: -949.83 | O15: -949.83 | P15: 0 | Q15: 0 | R15: 0 | S15: 0 | T15: 0 | U15: 0 | V15: 0 | W15: 0
A16: 111 | B16: 117 | C16: 113 | D16: Brittain III, David | E16: N/A | F16: trey@tbrittain.com | G16: Current resident | H16: 11/16/2022 | I16: PST | J16: 0 | K16: 6.5 | N16: 6.5 | O16: 6.5 | P16: 0 | Q16: 0 | R16: 0 | S16: 0 | T16: 0 | U16: 0 | V16: 1 | W16: 0
A17: 111 | B17: 117 | C17: 113 | D17: Brittain III, David | E17: N/A | F17: trey@tbrittain.com | G17: Current resident | H17: 11/16/2022 | I17: TRV | J17: 0 | K17: 9.83 | N17: 9.83 | O17: 9.83 | P17: 0 | Q17: 0 | R17: 0 | S17: 0 | T17: 0 | U17: 0 | V17: 1 | W17: 0
A18: 111 | B18: 117 | C18: 113 | D18: Brittain III, David | E18: N/A | F18: trey@tbrittain.com | G18: Current resident | H18: 11/16/2022 | I18: WSR | J18: 0 | K18: 57.56 | N18: 57.56 | O18: 57.56 | P18: 0 | Q18: 0 | R18: 0 | S18: 0 | T18: 0 | U18: 0 | V18: 1 | W18: 0
A19: 248 | B19: 670 | C19: 114 | D19: Scheurich, Alissa | E19: N/A | F19: alissarscheurich@gmail.com | G19: Current resident | H19: 02/26/2026 | I19: PMTBILTACH | J19: -1588.62 | K19: 0 | N19: -1588.62 | O19: -1588.62 | P19: 0 | Q19: 0 | R19: 0 | S19: 0 | T19: 0 | U19: 0 | V19: 0 | W19: 0
A20: 37 | B20: 38 | C20: 115 | D20: Bowden, Alethe | E20: N/A | F20: alethebowden46@gmail.com | G20: Current resident | H20: 10/18/2019 | I20: GAS | J20: 0 | K20: 8.37 | N20: 8.37 | O20: 8.37 | P20: 0 | Q20: 0 | R20: 0 | S20: 0 | T20: 0 | U20: 0 | V20: 0 | W20: 0
A21: 37 | B21: 38 | C21: 115 | D21: Bowden, Alethe | E21: N/A | F21: alethebowden46@gmail.com | G21: Current resident | H21: 10/18/2019 | I21: PST | J21: 0 | K21: 6.5 | N21: 6.5 | O21: 6.5 | P21: 0 | Q21: 0 | R21: 0 | S21: 0 | T21: 0 | U21: 0 | V21: 0 | W21: 0
A22: 37 | B22: 38 | C22: 115 | D22: Bowden, Alethe | E22: N/A | F22: alethebowden46@gmail.com | G22: Current resident | H22: 10/18/2019 | I22: TRV | J22: 0 | K22: 9.83 | N22: 9.83 | O22: 9.83 | P22: 0 | Q22: 0 | R22: 0 | S22: 0 | T22: 0 | U22: 0 | V22: 0 | W22: 0
A23: 37 | B23: 38 | C23: 115 | D23: Bowden, Alethe | E23: N/A | F23: alethebowden46@gmail.com | G23: Current resident | H23: 10/18/2019 | I23: WSR | J23: 0 | K23: 39.39 | N23: 39.39 | O23: 39.39 | P23: 0 | Q23: 0 | R23: 0 | S23: 0 | T23: 0 | U23: 0 | V23: 0 | W23: 0
A24: 35 | B24: 416 | C24: 116 | D24: Brittany Stone | F24: brittanyd.stone@gmail.com | G24: Former resident | H24: 04/03/2026 | I24: GAS | J24: 0 | K24: 40.05 | N24: 40.05 | O24: 40.05 | P24: 0 | Q24: 0 | R24: 0 | S24: 0 | T24: 0 | U24: 0 | V24: 1 | W24: 1
A25: 35 | B25: 416 | C25: 116 | D25: Brittany Stone | F25: brittanyd.stone@gmail.com | G25: Former resident | H25: 04/03/2026 | I25: PST | J25: 0 | K25: 6.5 | N25: 6.5 | O25: 6.5 | P25: 0 | Q25: 0 | R25: 0 | S25: 0 | T25: 0 | U25: 0 | V25: 1 | W25: 1
A26: 35 | B26: 416 | C26: 116 | D26: Brittany Stone | F26: brittanyd.stone@gmail.com | G26: Former resident | H26: 04/03/2026 | I26: TRV | J26: 0 | K26: 9.83 | N26: 9.83 | O26: 9.83 | P26: 0 | Q26: 0 | R26: 0 | S26: 0 | T26: 0 | U26: 0 | V26: 1 | W26: 1
A27: 35 | B27: 416 | C27: 116 | D27: Brittany Stone | F27: brittanyd.stone@gmail.com | G27: Former resident | H27: 04/03/2026 | I27: WSR | J27: 0 | K27: 26.79 | N27: 26.79 | O27: 26.79 | P27: 0 | Q27: 0 | R27: 0 | S27: 0 | T27: 0 | U27: 0 | V27: 1 | W27: 1
A28: 124 | B28: 131 | C28: 127 | D28: Quinn, Megan Christine | E28: N/A | F28: meganchristinequinn@gmail.com | G28: Current resident | H28: 04/01/2023 | I28: GAS | J28: 0 | K28: 3.14 | N28: 3.14 | O28: 3.14 | P28: 0 | Q28: 0 | R28: 0 | S28: 0 | T28: 0 | U28: 0 | V28: 0 | W28: 0
A29: 124 | B29: 131 | C29: 127 | D29: Quinn, Megan Christine | E29: N/A | F29: meganchristinequinn@gmail.com | G29: Current resident | H29: 04/01/2023 | I29: PST | J29: 0 | K29: 6.5 | N29: 6.5 | O29: 6.5 | P29: 0 | Q29: 0 | R29: 0 | S29: 0 | T29: 0 | U29: 0 | V29: 0 | W29: 0
A30: 124 | B30: 131 | C30: 127 | D30: Quinn, Megan Christine | E30: N/A | F30: meganchristinequinn@gmail.com | G30: Current resident | H30: 04/01/2023 | I30: TRV | J30: 0 | K30: 9.83 | N30: 9.83 | O30: 9.83 | P30: 0 | Q30: 0 | R30: 0 | S30: 0 | T30: 0 | U30: 0 | V30: 0 | W30: 0
A31: 124 | B31: 131 | C31: 127 | D31: Quinn, Megan Christine | E31: N/A | F31: meganchristinequinn@gmail.com | G31: Current resident | H31: 04/01/2023 | I31: WSR | J31: 0 | K31: 26.21 | N31: 26.21 | O31: 26.21 | P31: 0 | Q31: 0 | R31: 0 | S31: 0 | T31: 0 | U31: 0 | V31: 0 | W31: 0
A32: 303 | B32: 330 | C32: 128 | D32: Maria Jose Santacruz Puig; April Cruz | F32: mj.sp@outlook.com | G32: Former resident | H32: 03/18/2026 | I32: PMTOPACH | J32: -561.54 | K32: 0 | N32: -561.54 | O32: -561.54 | P32: 0 | Q32: 0 | R32: 0 | S32: 0 | T32: 0 | U32: 0 | V32: 0 | W32: 0
A33: 402 | B33: 582 | C33: 129 | D33: Model, Model | E33: (832) 589-9608 | F33: Megan.Behrens@assetliving.com | G33: Current resident | H33: 12/08/2025 | I33: MOD | J33: -1871.16 | K33: 0 | N33: -1871.16 | O33: -1871.16 | P33: 0 | Q33: 0 | R33: 0 | S33: 0 | T33: 0 | U33: 0 | V33: 0 | W33: 0
A34: 326 | B34: 353 | C34: 131 | D34: Perez, Jennifer Lynn | E34: (281)881-9946 | F34: jenperez527@gmail.com | G34: Current resident | H34: 06/04/2025 | I34: GAS | J34: 0 | K34: 25.64 | N34: 25.64 | O34: 25.64 | P34: 0 | Q34: 0 | R34: 0 | S34: 0 | T34: 0 | U34: 0 | V34: 0 | W34: 0
A35: 326 | B35: 353 | C35: 131 | D35: Perez, Jennifer Lynn | E35: (281)881-9946 | F35: jenperez527@gmail.com | G35: Current resident | H35: 06/04/2025 | I35: PST | J35: 0 | K35: 6.5 | N35: 6.5 | O35: 6.5 | P35: 0 | Q35: 0 | R35: 0 | S35: 0 | T35: 0 | U35: 0 | V35: 0 | W35: 0
A36: 326 | B36: 353 | C36: 131 | D36: Perez, Jennifer Lynn | E36: (281)881-9946 | F36: jenperez527@gmail.com | G36: Current resident | H36: 06/04/2025 | I36: TRV | J36: 0 | K36: 9.83 | N36: 9.83 | O36: 9.83 | P36: 0 | Q36: 0 | R36: 0 | S36: 0 | T36: 0 | U36: 0 | V36: 0 | W36: 0
A37: 326 | B37: 353 | C37: 131 | D37: Perez, Jennifer Lynn | E37: (281)881-9946 | F37: jenperez527@gmail.com | G37: Current resident | H37: 06/04/2025 | I37: WSR | J37: 0 | K37: 51.5 | N37: 51.5 | O37: 51.5 | P37: 0 | Q37: 0 | R37: 0 | S37: 0 | T37: 0 | U37: 0 | V37: 0 | W37: 0
A38: 208 | B38: 226 | C38: 132 | D38: Richey, Hudson Lanier | E38: N/A | F38: hlrichey19@gmail.com | G38: Current resident | H38: 03/05/2024 | I38: GAS | J38: 0 | K38: 4.79 | N38: 4.79 | O38: 4.79 | P38: 0 | Q38: 0 | R38: 0 | S38: 0 | T38: 0 | U38: 0 | V38: 0 | W38: 0
A39: 208 | B39: 226 | C39: 132 | D39: Richey, Hudson Lanier | E39: N/A | F39: hlrichey19@gmail.com | G39: Current resident | H39: 03/05/2024 | I39: PST | J39: 0 | K39: 6.5 | N39: 6.5 | O39: 6.5 | P39: 0 | Q39: 0 | R39: 0 | S39: 0 | T39: 0 | U39: 0 | V39: 0 | W39: 0
A40: 208 | B40: 226 | C40: 132 | D40: Richey, Hudson Lanier | E40: N/A | F40: hlrichey19@gmail.com | G40: Current resident | H40: 03/05/2024 | I40: TRV | J40: 0 | K40: 9.83 | N40: 9.83 | O40: 9.83 | P40: 0 | Q40: 0 | R40: 0 | S40: 0 | T40: 0 | U40: 0 | V40: 0 | W40: 0
A41: 208 | B41: 226 | C41: 132 | D41: Richey, Hudson Lanier | E41: N/A | F41: hlrichey19@gmail.com | G41: Current resident | H41: 03/05/2024 | I41: WSR | J41: 0 | K41: 58.8 | N41: 58.8 | O41: 58.8 | P41: 0 | Q41: 0 | R41: 0 | S41: 0 | T41: 0 | U41: 0 | V41: 0 | W41: 0
A42: 231 | B42: 257 | C42: 133 | D42: Bazzle, Jennifer Natalie | E42: N/A | F42: jnbazzle@gmail.com | G42: Current resident | H42: 06/24/2024 | I42: GAS | J42: 0 | K42: 6.18 | N42: 6.18 | O42: 6.18 | P42: 0 | Q42: 0 | R42: 0 | S42: 0 | T42: 0 | U42: 0 | V42: 1 | W42: 0
A43: 231 | B43: 257 | C43: 133 | D43: Bazzle, Jennifer Natalie | E43: N/A | F43: jnbazzle@gmail.com | G43: Current resident | H43: 06/24/2024 | I43: PST | J43: 0 | K43: 6.5 | N43: 6.5 | O43: 6.5 | P43: 0 | Q43: 0 | R43: 0 | S43: 0 | T43: 0 | U43: 0 | V43: 1 | W43: 0
A44: 231 | B44: 257 | C44: 133 | D44: Bazzle, Jennifer Natalie | E44: N/A | F44: jnbazzle@gmail.com | G44: Current resident | H44: 06/24/2024 | I44: TRV | J44: 0 | K44: 9.83 | N44: 9.83 | O44: 9.83 | P44: 0 | Q44: 0 | R44: 0 | S44: 0 | T44: 0 | U44: 0 | V44: 1 | W44: 0
... A56: 27 | B56: 530 | C56: 136 | D56: Heard, Nehemiah | E56: N/A | F56: nmheard03@yahoo.com | G56: Current resident | H56: 02/26/2018 | I56: WSR | J56: 0 | K56: 25.09 | N56: 25.09 | O56: 25.09 | P56: 0 | Q56: 0 | R56: 0 | S56: 0 | T56: 0 | U56: 0 | V56: 0 | W56: 0
A57: 250 | B57: 546 | C57: 137 | D57: Cornavaca, Julio Alberto | F57: cornavaca@gmail.com | G57: Current resident | H57: 08/15/2024 | I57: GAS | J57: 0 | K57: 10.72 | N57: 10.72 | O57: 10.72 | P57: 0 | Q57: 0 | R57: 0 | S57: 0 | T57: 0 | U57: 0 | V57: 0 | W57: 0
A58: 250 | B58: 546 | C58: 137 | D58: Cornavaca, Julio Alberto | F58: cornavaca@gmail.com | G58: Current resident | H58: 08/15/2024 | I58: PST | J58: 0 | K58: 5 | N58: 5 | O58: 5 | P58: 0 | Q58: 0 | R58: 0 | S58: 0 | T58: 0 | U58: 0 | V58: 0 | W58: 0
A59: 250 | B59: 546 | C59: 137 | D59: Cornavaca, Julio Alberto | F59: cornavaca@gmail.com | G59: Current resident | H59: 08/15/2024 | I59: TRV | J59: 0 | K59: 6.83 | N59: 6.83 | O59: 6.83 | P59: 0 | Q59: 0 | R59: 0 | S59: 0 | T59: 0 | U59: 0 | V59: 0 | W59: 0
A60: 250 | B60: 546 | C60: 137 | D60: Cornavaca, Julio Alberto | F60: cornavaca@gmail.com | G60: Current resident | H60: 08/15/2024 | I60: WSR | J60: 0 | K60: 74.02 | N60: 74.02 | O60: 74.02 | P60: 0 | Q60: 0 | R60: 0 | S60: 0 | T60: 0 | U60: 0 | V60: 0 | W60: 0
A61: 225 | B61: 247 | C61: 138 | D61: Batemon, Jeremy | E61: (239) 281-8984 | F61: j.batemon@hotmail.com | G61: Current resident | H61: 06/06/2024 | I61: GAS | J61: 0 | K61: 32.99 | N61: 32.99 | O61: 32.99 | P61: 0 | Q61: 0 | R61: 0 | S61: 0 | T61: 1756 | U61: 0 | V61: 0 | W61: 0
A62: 225 | B62: 247 | C62: 138 | D62: Batemon, Jeremy | E62: (239) 281-8984 | F62: j.batemon@hotmail.com | G62: Current resident | H62: 06/06/2024 | I62: PST | J62: 0 | K62: 6.5 | N62: 6.5 | O62: 6.5 | P62: 0 | Q62: 0 | R62: 0 | S62: 0 | T62: 0 | U62: 0 | V62: 0 | W62: 0
A63: 225 | B63: 247 | C63: 138 | D63: Batemon, Jeremy | E63: (239) 281-8984 | F63: j.batemon@hotmail.com | G63: Current resident | H63: 06/06/2024 | I63: TRV | J63: 0 | K63: 9.83 | N63: 9.83 | O63: 9.83 | P63: 0 | Q63: 0 | R63: 0 | S63: 0 | T63: 0 | U63: 0 | V63: 0 | W63: 0
A64: 225 | B64: 247 | C64: 138 | D64: Batemon, Jeremy | E64: (239) 281-8984 | F64: j.batemon@hotmail.com | G64: Current resident | H64: 06/06/2024 | I64: WSR | J64: 0 | K64: 52.22 | N64: 52.22 | O64: 52.22 | P64: 0 | Q64: 0 | R64: 0 | S64: 0 | T64: 0 | U64: 0 | V64: 0 | W64: 0
A65: 84 | B65: 88 | C65: 139 | D65: Travis, Amelia | E65: N/A | F65: ameliaktravis@gmail.com | G65: Current resident | H65: 02/15/2022 | I65: GAS | J65: 0 | K65: 13.99 | N65: 13.99 | O65: 13.99 | P65: 0 | Q65: 0 | R65: 0 | S65: 0 | T65: 0 | U65: 0 | V65: 0 | W65: 0
A66: 84 | B66: 88 | C66: 139 | D66: Travis, Amelia | E66: N/A | F66: ameliaktravis@gmail.com | G66: Current resident | H66: 02/15/2022 | I66: PST | J66: 0 | K66: 6.5 | N66: 6.5 | O66: 6.5 | P66: 0 | Q66: 0 | R66: 0 | S66: 0 | T66: 0 | U66: 0 | V66: 0 | W66: 0
A67: 84 | B67: 88 | C67: 139 | D67: Travis, Amelia | E67: N/A | F67: ameliaktravis@gmail.com | G67: Current resident | H67: 02/15/2022 | I67: TRV | J67: 0 | K67: 9.83 | N67: 9.83 | O67: 9.83 | P67: 0 | Q67: 0 | R67: 0 | S67: 0 | T67: 0 | U67: 0 | V67: 0 | W67: 0
A68: 84 | B68: 88 | C68: 139 | D68: Travis, Amelia | E68: N/A | F68: ameliaktravis@gmail.com | G68: Current resident | H68: 02/15/2022 | I68: WSR | J68: 0 | K68: 52.75 | N68: 52.75 | O68: 52.75 | P68: 0 | Q68: 0 | R68: 0 | S68: 0 | T68: 0 | U68: 0 | V68: 0 | W68: 0
A69: 380 | B69: 534 | C69: 140 | D69: Contreras, Luz Maria | E69: (713) 815-9165 | F69: luzmacon@gmail.com | G69: Current resident | H69: 11/07/2025 | I69: GAS | J69: 0 | K69: 14.09 | N69: 14.09 | O69: 14.09 | P69: 0 | Q69: 0 | R69: 0 | S69: 0 | T69: 250 | U69: 0 | V69: 0 | W69: 0
A70: 380 | B70: 534 | C70: 140 | D70: Contreras, Luz Maria | E70: (713) 815-9165 | F70: luzmacon@gmail.com | G70: Current resident | H70: 11/07/2025 | I70: PST | J70: 0 | K70: 5 | N70: 5 | O70: 5 | P70: 0 | Q70: 0 | R70: 0 | S70: 0 | T70: 0 | U70: 0 | V70: 0 | W70: 0
A71: 380 | B71: 534 | C71: 140 | D71: Contreras, Luz Maria | E71: (713) 815-9165 | F71: luzmacon@gmail.com | G71: Current resident | H71: 11/07/2025 | I71: TRV | J71: 0 | K71: 6.83 | N71: 6.83 | O71: 6.83 | P71: 0 | Q71: 0 | R71: 0 | S71: 0 | T71: 0 | U71: 0 | V71: 0 | W71: 0
A72: 380 | B72: 534 | C72: 140 | D72: Contreras, Luz Maria | E72: (713) 815-9165 | F72: luzmacon@gmail.com | G72: Current resident | H72: 11/07/2025 | I72: WSR | J72: 0 | K72: 69.4 | N72: 69.4 | O72: 69.4 | P72: 0 | Q72: 0 | R72: 0 | S72: 0 | T72: 0 | U72: 0 | V72: 0 | W72: 0
... A111: 218 | B111: 423 | C111: 212 | D111: Nguyen, Minh Quan | E111: N/A | F111: minhquan180502@gmail.com | G111: Current resident | H111: 05/09/2024 | I111: WSR | J111: 0 | K111: 29.83 | N111: 29.83 | O111: 29.83 | P111: 0 | Q111: 0 | R111: 0 | S111: 0 | T111: 0 | U111: 0 | V111: 2 | W111: 0
A112: 83 | B112: 498 | C112: 213 | D112: Craig Anderson | F112: andersoncraig07@yahoo.com | G112: Former resident | H112: 04/19/2026 | I112: GAS | J112: 0 | K112: 12.48 | N112: 12.48 | O112: 12.48 | P112: 0 | Q112: 0 | R112: 0 | S112: 0 | T112: 0 | U112: 0 | V112: 2 | W112: 0
A113: 83 | B113: 498 | C113: 213 | D113: Craig Anderson | F113: andersoncraig07@yahoo.com | G113: Former resident | H113: 04/19/2026 | I113: PST | J113: 0 | K113: 6.5 | N113: 6.5 | O113: 6.5 | P113: 0 | Q113: 0 | R113: 0 | S113: 0 | T113: 0 | U113: 0 | V113: 2 | W113: 0
A114: 83 | B114: 498 | C114: 213 | D114: Craig Anderson | F114: andersoncraig07@yahoo.com | G114: Former resident | H114: 04/19/2026 | I114: TRV | J114: 0 | K114: 9.83 | N114: 9.83 | O114: 9.83 | P114: 0 | Q114: 0 | R114: 0 | S114: 0 | T114: 0 | U114: 0 | V114: 2 | W114: 0
A115: 83 | B115: 498 | C115: 213 | D115: Craig Anderson | F115: andersoncraig07@yahoo.com | G115: Former resident | H115: 04/19/2026 | I115: WSR | J115: 0 | K115: 58.49 | N115: 58.49 | O115: 58.49 | P115: 0 | Q115: 0 | R115: 0 | S115: 0 | T115: 0 | U115: 0 | V115: 2 | W115: 0
A116: 255 | B116: 281 | C116: 214 | D116: Moss, Blake William Edward | E116: N/A | F116: bmoss71@gmail.com | G116: Current resident | H116: 08/17/2024 | I116: GAS | J116: 0 | K116: 5.94 | N116: 5.94 | O116: 5.94 | P116: 0 | Q116: 0 | R116: 0 | S116: 0 | T116: 0 | U116: 0 | V116: 0 | W116: 0
A117: 255 | B117: 281 | C117: 214 | D117: Moss, Blake William Edward | E117: N/A | F117: bmoss71@gmail.com | G117: Current resident | H117: 08/17/2024 | I117: PST | J117: 0 | K117: 6.5 | N117: 6.5 | O117: 6.5 | P117: 0 | Q117: 0 | R117: 0 | S117: 0 | T117: 0 | U117: 0 | V117: 0 | W117: 0
A118: 255 | B118: 281 | C118: 214 | D118: Moss, Blake William Edward | E118: N/A | F118: bmoss71@gmail.com | G118: Current resident | H118: 08/17/2024 | I118: TRV | J118: 0 | K118: 9.83 | N118: 9.83 | O118: 9.83 | P118: 0 | Q118: 0 | R118: 0 | S118: 0 | T118: 0 | U118: 0 | V118: 0 | W118: 0
A119: 255 | B119: 281 | C119: 214 | D119: Moss, Blake William Edward | E119: N/A | F119: bmoss71@gmail.com | G119: Current resident | H119: 08/17/2024 | I119: WSR | J119: 0 | K119: 45.19 | N119: 45.19 | O119: 45.19 | P119: 0 | Q119: 0 | R119: 0 | S119: 0 | T119: 0 | U119: 0 | V119: 0 | W119: 0
A120: 201 | B120: 216 | C120: 215 | D120: Henderson, Steven Michael | E120: N/A | F120: smhenderson1824@gmail.com | G120: Current resident | H120: 02/16/2024 | I120: GAS | J120: 0 | K120: 4.94 | N120: 4.94 | O120: 4.94 | P120: 0 | Q120: 0 | R120: 0 | S120: 0 | T120: 0 | U120: 0 | V120: 0 | W120: 0
A121: 201 | B121: 216 | C121: 215 | D121: Henderson, Steven Michael | E121: N/A | F121: smhenderson1824@gmail.com | G121: Current resident | H121: 02/16/2024 | I121: PST | J121: 0 | K121: 6.5 | N121: 6.5 | O121: 6.5 | P121: 0 | Q121: 0 | R121: 0 | S121: 0 | T121: 0 | U121: 0 | V121: 0 | W121: 0
A122: 201 | B122: 216 | C122: 215 | D122: Henderson, Steven Michael | E122: N/A | F122: smhenderson1824@gmail.com | G122: Current resident | H122: 02/16/2024 | I122: TRV | J122: 0 | K122: 9.83 | N122: 9.83 | O122: 9.83 | P122: 0 | Q122: 0 | R122: 0 | S122: 0 | T122: 0 | U122: 0 | V122: 0 | W122: 0
A123: 201 | B123: 216 | C123: 215 | D123: Henderson, Steven Michael | E123: N/A | F123: smhenderson1824@gmail.com | G123: Current resident | H123: 02/16/2024 | I123: WSR | J123: 0 | K123: 7.88 | N123: 7.88 | O123: 7.88 | P123: 0 | Q123: 0 | R123: 0 | S123: 0 | T123: 0 | U123: 0 | V123: 0 | W123: 0
A124: 92 | B124: 463 | C124: 216 | D124: Cole, Celeste | E124: N/A | F124: celesteccole@gmail.com | G124: Current resident | H124: 06/24/2022 | I124: GAS | J124: 0 | K124: 35.91 | N124: 35.91 | O124: 35.91 | P124: 0 | Q124: 0 | R124: 0 | S124: 0 | T124: 1670 | U124: 0 | V124: 1 | W124: 1
A125: 92 | B125: 463 | C125: 216 | D125: Cole, Celeste | E125: N/A | F125: celesteccole@gmail.com | G125: Current resident | H125: 06/24/2022 | I125: PST | J125: 0 | K125: 6.5 | N125: 6.5 | O125: 6.5 | P125: 0 | Q125: 0 | R125: 0 | S125: 0 | T125: 0 | U125: 0 | V125: 1 | W125: 1
A126: 92 | B126: 463 | C126: 216 | D126: Cole, Celeste | E126: N/A | F126: celesteccole@gmail.com | G126: Current resident | H126: 06/24/2022 | I126: TRV | J126: 0 | K126: 9.83 | N126: 9.83 | O126: 9.83 | P126: 0 | Q126: 0 | R126: 0 | S126: 0 | T126: 0 | U126: 0 | V126: 1 | W126: 1
A127: 92 | B127: 463 | C127: 216 | D127: Cole, Celeste | E127: N/A | F127: celesteccole@gmail.com | G127: Current resident | H127: 06/24/2022 | I127: WSR | J127: 0 | K127: 26.79 | N127: 26.79 | O127: 26.79 | P127: 0 | Q127: 0 | R127: 0 | S127: 0 | T127: 0 | U127: 0 | V127: 1 | W127: 1
A128: 125 | B128: 412 | C128: 217 | D128: Gilmore, Patricia Davenport | F128: pdgilmore22@gmail.com | G128: NTV | H128: 04/14/2023 05/18/2026 | I128: GAS | J128: 0 | K128: 10.76 | N128: 10.76 | O128: 10.76 | P128: 0 | Q128: 0 | R128: 0 | S128: 0 | T128: 0 | U128: 0 | V128: 0 | W128: 0
A129: 125 | B129: 412 | C129: 217 | D129: Gilmore, Patricia Davenport | F129: pdgilmore22@gmail.com | G129: NTV | H129: 04/14/2023 05/18/2026 | I129: PST | J129: 0 | K129: 6.5 | N129: 6.5 | O129: 6.5 | P129: 0 | Q129: 0 | R129: 0 | S129: 0 | T129: 0 | U129: 0 | V129: 0 | W129: 0
A130: 125 | B130: 412 | C130: 217 | D130: Gilmore, Patricia Davenport | F130: pdgilmore22@gmail.com | G130: NTV | H130: 04/14/2023 05/18/2026 | I130: TRV | J130: 0 | K130: 9.83 | N130: 9.83 | O130: 9.83 | P130: 0 | Q130: 0 | R130: 0 | S130: 0 | T130: 0 | U130: 0 | V130: 0 | W130: 0
A131: 125 | B131: 412 | C131: 217 | D131: Gilmore, Patricia Davenport | F131: pdgilmore22@gmail.com | G131: NTV | H131: 04/14/2023 05/18/2026 | I131: WSR | J131: 0 | K131: 63.34 | N131: 63.34 | O131: 63.34 | P131: 0 | Q131: 0 | R131: 0 | S131: 0 | T131: 0 | U131: 0 | V131: 0 | W131: 0
A132: 323 | B132: 350 | C132: 218 | D132: Martin, Danielle Renee | F132: martindrm14@gmail.com | G132: Former resident | H132: 05/17/2026 | I132: GAS | J132: 0 | K132: 13.9 | N132: 13.9 | O132: 13.9 | P132: 0 | Q132: 0 | R132: 0 | S132: 0 | T132: 0 | U132: 0 | V132: 0 | W132: 0
A133: 323 | B133: 350 | C133: 218 | D133: Martin, Danielle Renee | F133: martindrm14@gmail.com | G133: Former resident | H133: 05/17/2026 | I133: PST | J133: 0 | K133: 6.5 | N133: 6.5 | O133: 6.5 | P133: 0 | Q133: 0 | R133: 0 | S133: 0 | T133: 0 | U133: 0 | V133: 0 | W133: 0
A134: 323 | B134: 350 | C134: 218 | D134: Martin, Danielle Renee | F134: martindrm14@gmail.com | G134: Former resident | H134: 05/17/2026 | I134: TRV | J134: 0 | K134: 9.83 | N134: 9.83 | O134: 9.83 | P134: 0 | Q134: 0 | R134: 0 | S134: 0 | T134: 0 | U134: 0 | V134: 0 | W134: 0
A135: 323 | B135: 350 | C135: 218 | D135: Martin, Danielle Renee | F135: martindrm14@gmail.com | G135: Former resident | H135: 05/17/2026 | I135: WSR | J135: 0 | K135: 68.9 | N135: 68.9 | O135: 68.9 | P135: 0 | Q135: 0 | R135: 0 | S135: 0 | T135: 0 | U135: 0 | V135: 0 | W135: 0
A136: 29 | B136: 639 | C136: 234 | D136: Consulate General of India Houston, * | E136: (346) 372-1656 | F136: trade.houston@mea.gov.in | G136: Current resident | H136: 04/01/2018 | I136: GAS | J136: 0 | K136: 5.11 | N136: 5.11 | O136: 5.11 | P136: 0 | Q136: 0 | R136: 0 | S136: 0 | T136: 250 | U136: 0 | V136: 0 | W136: 0
A137: 29 | B137: 639 | C137: 234 | D137: Consulate General of India Houston, * | E137: (346) 372-1656 | F137: trade.houston@mea.gov.in | G137: Current resident | H137: 04/01/2018 | I137: PST | J137: 0 | K137: 6.5 | N137: 6.5 | O137: 6.5 | P137: 0 | Q137: 0 | R137: 0 | S137: 0 | T137: 0 | U137: 0 | V137: 0 | W137: 0
A138: 29 | B138: 639 | C138: 234 | D138: Consulate General of India Houston, * | E138: (346) 372-1656 | F138: trade.houston@mea.gov.in | G138: Current resident | H138: 04/01/2018 | I138: TRV | J138: 0 | K138: 9.83 | N138: 9.83 | O138: 9.83 | P138: 0 | Q138: 0 | R138: 0 | S138: 0 | T138: 0 | U138: 0 | V138: 0 | W138: 0
A139: 29 | B139: 639 | C139: 234 | D139: Consulate General of India Houston, * | E139: (346) 372-1656 | F139: trade.houston@mea.gov.in | G139: Current resident | H139: 04/01/2018 | I139: WSR | J139: 0 | K139: 33.25 | N139: 33.25 | O139: 33.25 | P139: 0 | Q139: 0 | R139: 0 | S139: 0 | T139: 0 | U139: 0 | V139: 0 | W139: 0
A140: 246 | B140: 433 | C140: 235 | D140: Shaik, Zeelan Basha | E140: N/A | F140: shaikzillu@gmail.com | G140: Current resident | H140: 07/27/2024 | I140: GAS | J140: 0 | K140: 8 | N140: 8 | O140: 8 | P140: 0 | Q140: 0 | R140: 0 | S140: 0 | T140: 0 | U140: 0 | V140: 0 | W140: 0
A141: 246 | B141: 433 | C141: 235 | D141: Shaik, Zeelan Basha | E141: N/A | F141: shaikzillu@gmail.com | G141: Current resident | H141: 07/27/2024 | I141: PST | J141: 0 | K141: 6.5 | N141: 6.5 | O141: 6.5 | P141: 0 | Q141: 0 | R141: 0 | S141: 0 | T141: 0 | U141: 0 | V141: 0 | W141: 0
A142: 246 | B142: 433 | C142: 235 | D142: Shaik, Zeelan Basha | E142: N/A | F142: shaikzillu@gmail.com | G142: Current resident | H142: 07/27/2024 | I142: TRV | J142: 0 | K142: 9.83 | N142: 9.83 | O142: 9.83 | P142: 0 | Q142: 0 | R142: 0 | S142: 0 | T142: 0 | U142: 0 | V142: 0 | W142: 0
A143: 246 | B143: 433 | C143: 235 | D143: Shaik, Zeelan Basha | E143: N/A | F143: shaikzillu@gmail.com | G143: Current resident | H143: 07/27/2024 | I143: WSR | J143: 0 | K143: 28.7 | N143: 28.7 | O143: 28.7 | P143: 0 | Q143: 0 | R143: 0 | S143: 0 | T143: 0 | U143: 0 | V143: 0 | W143: 0
A144: 386 | B144: 555 | C144: 236 | D144: Gonzales, Caroline Dianne | E144: (713) 254-7125 | F144: kayrotraveler@gmail.com | G144: NTV | H144: 11/17/2025 07/16/2026 | I144: GAS | J144: 0 | K144: 2.92 | N144: 2.92 | O144: 2.92 | P144: 0 | Q144: 0 | R144: 0 | S144: 0 | T144: 250 | U144: 0 | V144: 0 | W144: 0
A145: 386 | B145: 555 | C145: 236 | D145: Gonzales, Caroline Dianne | E145: (713) 254-7125 | F145: kayrotraveler@gmail.com | G145: NTV | H145: 11/17/2025 07/16/2026 | I145: PST | J145: 0 | K145: 5 | N145: 5 | O145: 5 | P145: 0 | Q145: 0 | R145: 0 | S145: 0 | T145: 0 | U145: 0 | V145: 0 | W145: 0
A146: 386 | B146: 555 | C146: 236 | D146: Gonzales, Caroline Dianne | E146: (713) 254-7125 | F146: kayrotraveler@gmail.com | G146: NTV | H146: 11/17/2025 07/16/2026 | I146: TRV | J146: 0 | K146: 6.83 | N146: 6.83 | O146: 6.83 | P146: 0 | Q146: 0 | R146: 0 | S146: 0 | T146: 0 | U146: 0 | V146: 0 | W146: 0
A147: 386 | B147: 555 | C147: 236 | D147: Gonzales, Caroline Dianne | E147: (713) 254-7125 | F147: kayrotraveler@gmail.com | G147: NTV | H147: 11/17/2025 07/16/2026 | I147: WSR | J147: 0 | K147: 25.99 | N147: 25.99 | O147: 25.99 | P147: 0 | Q147: 0 | R147: 0 | S147: 0 | T147: 0 | U147: 0 | V147: 0 | W147: 0
... A160: 322 | B160: 349 | C160: 240 | D160: Dearing, Noah Ethan | E160: (713) 301-7396 | F160: noahdearing@yahoo.com | G160: Current resident | H160: 05/09/2025 | I160: WSR | J160: 0 | K160: 8.34 | N160: 8.34 | O160: 8.34 | P160: 0 | Q160: 0 | R160: 0 | S160: 0 | T160: 0 | U160: 0 | V160: 0 | W160: 0
A161: 172 | B161: 473 | C161: 241 | D161: Pineau, Clarissa Anna Mae | F161: clarissa.mae798@gmail.com | G161: Current resident | H161: 09/11/2023 | I161: GAS | J161: 0 | K161: 40.57 | N161: 40.57 | O161: 40.57 | P161: 0 | Q161: 0 | R161: 0 | S161: 0 | T161: 0 | U161: 0 | V161: 0 | W161: 0
...

Sheet Market Rate
B2: Broker | C2: Submarket | D2: 3Q 2023 | E2: 4Q 2023 | F2: 1Q 2024 | G2: 2Q 2024 | H2: 3Q 2024 | I2: QoQ Change | L2: MULTIFAMILY 3Q 2024 | M2: INVENTORY (UNITS) | N2: YTD DELIVERIES (UNITS) | O2: YTD % INVENTORY GROWTH | P2: UNDER CONSTR (UNITS) | Q2: YTD NET ABSORPTION (UNITS) | R2: VACANCY RATE | S2: YOY VACANCY RATE CHANGE (BPS) | T2: AVG EFFECTIVE RENT / UNIT | U2: YOY % EFFECTIVE RENT GROWTH
B3: Cushman & Wakefield | C3: Ahwatukee | D3: 1668 | E3: 1629 | I3: =E3/D3-1 -> -0.023381295 | L3: Ahwatukee | M3: 12362 | N3: 166 | O3: 1.4% | P3: 1142 | Q3: 425 | R3: 5.7% | S3: 40 | T3: 1642 | U3: -1.6%
B4: Costar | C4: Chandler | D4: 1689 | E4: 1689 | I4: =E4/D4-1 -> 0 | L4: Central Phoenix | M4: 33310 | N4: 959 | O4: 3.0% | P4: 5478 | Q4: 1305 | R4: 7.0% | S4: 50 | T4: 1598 | U4: -2.3%
L5: Chandler/Queen Creek | M5: 40264 | N5: 1389 | O5: 3.6% | P5: 5630 | Q5: 1779 | R5: 5.3% | S5: -30 | T5: 1771 | U5: -2.0%
B6: Average | D6: =AVERAGE(D3:D4) -> 1678.5 | E6: =AVERAGE(E3:E4) -> 1659 | F6: =AVERAGE(F3:F4) -> #DIV/0! | I6: =E6/D6-1 -> -0.011617516 | L6: East Phoenix | M6: 19203 | N6: 593 | O6: 3.2% | P6: 320 | Q6: 532 | R6: 7.1% | S6: 10 | T6: 1532 | U6: -1.2%
L7: Glendale/West Valley | M7: 27494 | N7: 2532 | O7: 10.1% | P7: 7444 | Q7: 1441 | R7: 7.8% | S7: 60 | T7: 1493 | U7: -0.9%
L8: Mesa/Gilbert | M8: 41651 | N8: 1426 | O8: 3.5% | P8: 3351 | Q8: 1774 | R8: 6.4% | S8: 0 | T8: 1492 | U8: -0.8%
L9: Northeast Valley | M9: 32612 | N9: 1960 | O9: 6.4% | P9: 4947 | Q9: 34 | R9: 5.9% | S9: -10 | T9: 1779 | U9: -0.4%
D10: Last Year | E10: 45261 | F10: 44986 | G10: 45473 | H10: 45565 | I10: QoQ Change | L10: Northwest Valley | M10: 39932 | N10: 2011 | O10: 5.3% | P10: 3991 | Q10: 308 | R10: 7.2% | S10: 70 | T10: 1510 | U10: -3.1%
B11: Submarket Rate ($/unit) | D11: 1668 | E11: 1629 | F11: 1614 | G11: 1643 | H11: =T3 -> 1642 | I11: =IFERROR(H11/G11-1,0%) -> -0.00060864273 | L11: Scottsdale | M11: 27759 | N11: 1930 | O11: 7.5% | P11: 574 | Q11: 1317 | R11: 5.3% | S11: -60 | T11: 1963 | U11: -1.6%
B12: Total Submarket Inventory (Units) | E12: 12181 | F12: 12196 | G12: 12196 | H12: =M3 -> 12362 | I12: =IFERROR(H12/G12-1,0%) -> 0.01361102 | L12: Tempe | M12: 36694 | N12: 1363 | O12: 3.9% | P12: 3780 | Q12: 838 | R12: 6.2% | S12: 20 | T12: 1887 | U12: -1.2%
B13: Submarket Vacancy (Units) | E13: =E12*E14 -> 791.765 | F13: =F12*F14 -> 829.328 | G13: =G12*G14 -> 731.76 | H13: =H12*H14 -> 704.634 | I13: =IFERROR(H13/G13-1,0%) -> -0.037069531 | L13: West Phoenix | M13: 41296 | N13: 1998 | O13: 5.1% | P13: 4026 | Q13: 2097 | R13: 8.3% | S13: 40 | T13: 1379 | U13: -0.9%
B14: Submarket Vacancy Rate | E14: 0.065 | F14: 0.068 | G14: 0.06 | H14: =R3 -> 5.7% | I14: =IFERROR(H14/G14-1,0%) -> -0.05 | L14: MARKET | M14: 352577 | N14: 16327 | O14: 4.9% | P14: 40683 | Q14: 11850 | R14: 6.6% | S14: 10 | T14: 1635 | U14: -1.6%
B15: Net Absorption QoQ (Units) | E15: -31 | F15: 63 | G15: 19 | H15: =H16-G16 -> 84 | I15: =IFERROR(H15/G15-1,0%) -> 3.4210526
B16: Net Absorption YTD (Units) | E16: -131 | F16: 63 | G16: 341 | H16: =Q3 -> 425 | I16: =IFERROR(H16/G16-1,0%) -> 0.24633431
B17: Under Construction (Units) | E17: 834 | F17: 834 | G17: 1136 | H17: =P3 -> 1142 | I17: =IFERROR(H17/G17-1,0%) -> 0.0052816901
B18: Planned (Units) | E18: 1111 | F18: 1558 | G18: 1478 | I18: =IFERROR(H18/G18-1,0%) -> -1
B19: Submarket Inventory Expansion | E19: =((E17+E12)/E12)-1 -> 0.068467285 | F19: =((F17+F12)/F12)-1 -> 0.068383076 | G19: =((G17+G12)/G12)-1 -> 0.093145294 | H19: =((H17+H12)/H12)-1 -> 0.092379874
B20: Notes:
B21: Below national average unemployement, and job and wage growth, in the Phoenix market, has resulted in the toal number of housholds to increase 2.2% YoY.
B23: Overall vacancy remained flat QoQ as absorption matches new deliveries. Asking rent fell slightly for the ninth quarter in a row.
B24: Construction pipeline slowed to its slowest pace since 2020; however, new inventory is still 230% above the 10-year annual average of 11.4K units.

Sheet Coding
D3: T12 | E3: Line Item | H3: Line Items
H4: Gross Potential Rent (3) | K4: Gross Potential Rent (3)
D5: INCOME | H5: Less: Vacancy Loss | K5: Less: Vacancy Loss
H6: Base Rent (3) | K6: OR
D7: 4000-000 - Market Rent | E7: Gross Potential Rent (3) | F7: Gross Potential Rent (3) | H7: Expense Reimbursement | K7: Base Rent (3)
D8: 4010-000 - Gain/Loss to Lease | E8: Gross Potential Rent (3) | F8: Gross Potential Rent (3) | H8: Percentage Rent | K8: Laundry/Vending Income
H9: Parking Income | K9: Parking Income
D10: Gross Possible | H10: Other Income | K10: Other Income
H11: Real Estate Taxes
D12: LESS DEDUCTIONS | H12: Property Insurance | K12: *Effective Gross Income
D13: 4100-000 - Vacancy Loss | E13: Less: Vacancy Loss | F13: Less: Vacancy Loss | H13: Utilities | K13: Debt Service - A Note
D14: 4101-000 - Vacancy-Down Units | E14: Less: Vacancy Loss | F14: Less: Vacancy Loss | H14: Repairs and Maintenance | K14: Capital Expenditures
D15: 4110-000 - Concessions Market | E15: Gross Potential Rent (3) | F15: Gross Potential Rent (3) | H15: Janitorial | K15: OPERATING EXPENSES:
D16: 4110-100 - Concessions-One Time | E16: Gross Potential Rent (3) | F16: Gross Potential Rent (3) | H16: Management Fees | K16: Real Estate Taxes
D17: 4110-300 - Concessions -Other | E17: Gross Potential Rent (3) | F17: Gross Potential Rent (3) | H17: Payroll & Benefits | K17: Property Insurance
D18: 4120-000 - Model/Guest Suite | E18: Gross Potential Rent (3) | F18: Gross Potential Rent (3) | H18: Advertising & Marketing | K18: Utilities
D19: 4130-000 - Employee Units | E19: Gross Potential Rent (3) | F19: Gross Potential Rent (3) | H19: Professional Fees | K19: Repairs and Maintenance
H20: General and Administrative | K20: Management Fees
D21: Total Deductions | H21: Other Expenses | K21: Payroll & Benefits
H22: Ground Rent | K22: Advertising & Marketing
D23: EFFECTIVE ECONOMIC OCCUPANCY | H23: Debt Service - A Note | K23: Professional Fees
H24: Capital Expenditures | K24: General and Administrative
D25: 4140-000 - Rent Write Off | E25: Other Income | F25: Other Income | K25: Other Expenses
K26: Ground Rent
D27: .
D29: Total Rental Income
D31: OTHER INCOME
D32: 4200-000 - Application Fees | E32: Other Income | F32: Other Income
D33: 4201-000 - Administrative Fees | E33: Other Income | F33: Other Income
D34: 4205-000 - Month to Month Fees | E34: Other Income | F34: Other Income
D35: 4210-000 - Late Fees | E35: Other Income | F35: Other Income
D36: 4211-000 - NSF Fees | E36: Other Income | F36: Other Income
D37: 4238-000 - Amenity Fee | E37: Other Income | F37: Other Income
D38: 4244-000 - Cleaning/Damages | E38: Other Income | F38: Other Income
D39: 4252-000 - Legal Fees | E39: Other Income | F39: Other Income
D40: 4254-000 - Pet Rent | E40: Other Income | F40: Other Income
D41: 4254-500 - Pet Fees | E41: Other Income | F41: Other Income
D42: 4256-000 - Key/Lockout Fees | E42: Other Income | F42: Other Income
D43: 4257-000 - Termination/Notice Fees | E43: Other Income | F43: Other Income
... D52: 4277-500 - Parking Income | E52: Parking Income | F52: Parking Income
D53: 4280-000 - Utility Reimbursement Inc | E53: Expense Reimbursement | F53: Other Income | G53: =_xlfn.XLOOKUP(D53,'[4]Operating Statement'!$B:$B,'[4]Operating Statement'!$S:$S) -> Expense Reimbursement
D54: 4280-500 - Water/Sewer Income | E54: Expense Reimbursement | F54: Other Income | G54: =_xlfn.XLOOKUP(D54,'[4]Operating Statement'!$B:$B,'[4]Operating Statement'!$S:$S) -> Expense Reimbursement
D56: Total Other Income
D58: TOTAL INCOME
D60: EXPENSES
D62: MARKETING & LEASING EXPENSES
D63: 5100-000 - Advertising | F63: Advertising & Marketing | G63: =_xlfn.XLOOKUP(D63,'[4]Operating Statement'!$B:$B,'[4]Operating Statement'!$S:$S) -> Advertising & Marketing
D64: 5101-000 - PPC/SEM Advertising | F64: Advertising & Marketing | G64: =_xlfn.XLOOKUP(D64,'[4]Operating Statement'!$B:$B,'[4]Operating Statement'!$S:$S) -> #N/A
D65: 5102-000 - Community Website Exp | F65: Advertising & Marketing | G65: =_xlfn.XLOOKUP(D65,'[4]Operating Statement'!$B:$B,'[4]Operating Statement'!$S:$S) -> Advertising & Marketing
D66: 5110-000 - Locator Fees | F66: Advertising & Marketing | G66: =_xlfn.XLOOKUP(D66,'[4]Operating Statement'!$B:$B,'[4]Operating Statement'!$S:$S) -> Advertising & Marketing
D67: 5130-000 - Other Marketing | F67: Advertising & Marketing | G67: =_xlfn.XLOOKUP(D67,'[4]Operating Statement'!$B:$B,'[4]Operating Statement'!$S:$S) -> Advertising & Marketing
D68: 5155-000 - Prospect Refreshments | F68: Advertising & Marketing | G68: =_xlfn.XLOOKUP(D68,'[4]Operating Statement'!$B:$B,'[4]Operating Statement'!$S:$S) -> Advertising & Marketing
D69: 5160-000 - Resident Promotion/Events | F69: Advertising & Marketing | G69: =_xlfn.XLOOKUP(D69,'[4]Operating Statement'!$B:$B,'[4]Operating Statement'!$S:$S) -> Advertising & Marketing
D70: 5165-000 - Resident Services | F70: Advertising & Marketing | G70: =_xlfn.XLOOKUP(D70,'[4]Operating Statement'!$B:$B,'[4]Operating Statement'!$S:$S) -> Advertising & Marketing
G71: =_xlfn.XLOOKUP(D71,'[4]Operating Statement'!$B:$B,'[4]Operating Statement'!$S:$S)
D72: Total Marketing & Leasing
G73: =_xlfn.XLOOKUP(D73,'[4]Operating Statement'!$B:$B,'[4]Operating Statement'!$S:$S)
D74: GENERAL & ADMINISTRATIVE EXP
D75: 5200-000 - Office Supplies | F75: General and Administrative | G75: =_xlfn.XLOOKUP(D75,'[4]Operating Statement'!$B:$B,'[4]Operating Statement'!$S:$S) -> General and Administrative
D76: 5210-000 - Office Furn/Equip Rental | F76: General and Administrative | G76: =_xlfn.XLOOKUP(D76,'[4]Operating Statement'!$B:$B,'[4]Operating Statement'!$S:$S) -> General and Administrative
D77: 5216-000 - Printing & Copier Exp. | F77: General and Administrative | G77: =_xlfn.XLOOKUP(D77,'[4]Operating Statement'!$B:$B,'[4]Operating Statement'!$S:$S) -> General and Administrative
D78: 5217-000 - Computer/Network Exp | F78: General and Administrative | G78: =_xlfn.XLOOKUP(D78,'[4]Operating Statement'!$B:$B,'[4]Operating Statement'!$S:$S) -> General and Administrative
D79: 5218-000 - On-Site Sftwre & Support | F79: General and Administrative | G79: =_xlfn.XLOOKUP(D79,'[4]Operating Statement'!$B:$B,'[4]Operating Statement'!$S:$S) -> General and Administrative
D80: 5220-000 - Telephone/Fax | F80: General and Administrative | G80: =_xlfn.XLOOKUP(D80,'[4]Operating Statement'!$B:$B,'[4]Operating Statement'!$S:$S) -> General and Administrative
D81: 5225-000 - Answering Service | F81: General and Administrative | G81: =_xlfn.XLOOKUP(D81,'[4]Operating Statement'!$B:$B,'[4]Operating Statement'!$S:$S) -> General and Administrative
D82: 5230-000 - Postage & Delivery | F82: General and Administrative | G82: =_xlfn.XLOOKUP(D82,'[4]Operating Statement'!$B:$B,'[4]Operating Statement'!$S:$S) -> General and Administrative
D83: 5235-000 - Dues/Meeting | F83: General and Administrative | G83: =_xlfn.XLOOKUP(D83,'[4]Operating Statement'!$B:$B,'[4]Operating Statement'!$S:$S) -> General and Administrative
D84: 5240-000 - Eviction Costs | F84: General and Administrative | G84: =_xlfn.XLOOKUP(D84,'[4]Operating Statement'!$B:$B,'[4]Operating Statement'!$S:$S) -> General and Administrative
D85: 5245-000 - Vehicle/Travel Expense | F85: General and Administrative | G85: =_xlfn.XLOOKUP(D85,'[4]Operating Statement'!$B:$B,'[4]Operating Statement'!$S:$S) -> General and Administrative
D86: 5250-000 - Permits & Licenses | F86: General and Administrative | G86: =_xlfn.XLOOKUP(D86,'[4]Operating Statement'!$B:$B,'[4]Operating Statement'!$S:$S) -> General and Administrative
... D92: 5280-000 - Training/Seminars | F92: General and Administrative | G92: =_xlfn.XLOOKUP(D92,'[4]Operating Statement'!$B:$B,'[4]Operating Statement'!$S:$S) -> General and Administrative
D94: Total General & Administrative Exp
D96: CONTRACT SERVICES
D97: 5303-000 - Internet Service | F97: Repairs and Maintenance | G97: =_xlfn.XLOOKUP(D97,'[4]Operating Statement'!$B:$B,'[4]Operating Statement'!$S:$S) -> Repairs and Maintenance
D98: 5305-000 - Common Area Cleaning | F98: Repairs and Maintenance | G98: =_xlfn.XLOOKUP(D98,'[4]Operating Statement'!$B:$B,'[4]Operating Statement'!$S:$S) -> Repairs and Maintenance
D99: 5310-000 - Elevator Service | F99: Repairs and Maintenance | G99: =_xlfn.XLOOKUP(D99,'[4]Operating Statement'!$B:$B,'[4]Operating Statement'!$S:$S) -> #N/A
D100: 5316-000 - Equipment Service | F100: Repairs and Maintenance | G100: =_xlfn.XLOOKUP(D100,'[4]Operating Statement'!$B:$B,'[4]Operating Statement'!$S:$S) -> Repairs and Maintenance
D101: 5320-000 - Exterminating | F101: Repairs and Maintenance | G101: =_xlfn.XLOOKUP(D101,'[4]Operating Statement'!$B:$B,'[4]Operating Statement'!$S:$S) -> Repairs and Maintenance
D102: 5324-000 - Termite Treatment | F102: Repairs and Maintenance | G102: =_xlfn.XLOOKUP(D102,'[4]Operating Statement'!$B:$B,'[4]Operating Statement'!$S:$S) -> Repairs and Maintenance
D103: 5325-000 - Landscaping Contract | F103: Repairs and Maintenance | G103: =_xlfn.XLOOKUP(D103,'[4]Operating Statement'!$B:$B,'[4]Operating Statement'!$S:$S) -> Repairs and Maintenance
D104: 5327-000 - Landscaping Services | F104: Repairs and Maintenance | G104: =_xlfn.XLOOKUP(D104,'[4]Operating Statement'!$B:$B,'[4]Operating Statement'!$S:$S) -> Repairs and Maintenance
D105: 5330-000 - Pool Service | F105: Repairs and Maintenance | G105: =_xlfn.XLOOKUP(D105,'[4]Operating Statement'!$B:$B,'[4]Operating Statement'!$S:$S) -> Repairs and Maintenance
D106: 5335-000 - Security Service | F106: Repairs and Maintenance | G106: =_xlfn.XLOOKUP(D106,'[4]Operating Statement'!$B:$B,'[4]Operating Statement'!$S:$S) -> Repairs and Maintenance
D107: 5337-000 - Key Control Contract | F107: Repairs and Maintenance | G107: =_xlfn.XLOOKUP(D107,'[4]Operating Statement'!$B:$B,'[4]Operating Statement'!$S:$S) -> Repairs and Maintenance
D108: 5347-000 - Valet Trash Pick-up | F108: Repairs and Maintenance | G108: =_xlfn.XLOOKUP(D108,'[4]Operating Statement'!$B:$B,'[4]Operating Statement'!$S:$S) -> Repairs and Maintenance
... D113: 5390-000 - GAP Renter's Liability Ins | F113: Repairs and Maintenance | G113: =_xlfn.XLOOKUP(D113,'[4]Operating Statement'!$B:$B,'[4]Operating Statement'!$S:$S) -> Repairs and Maintenance
D115: Total Contract Services
D117: REPAIR & MAINTENANCE EXPENSES
D118: 5500-000 - Appliance Supplies & Rprs | F118: Repairs and Maintenance | G118: =_xlfn.XLOOKUP(D118,'[4]Operating Statement'!$B:$B,'[4]Operating Statement'!$S:$S) -> Repairs and Maintenance
D119: 5505-000 - Electrical Supplies & Rprs | F119: Repairs and Maintenance | G119: =_xlfn.XLOOKUP(D119,'[4]Operating Statement'!$B:$B,'[4]Operating Statement'!$S:$S) -> Repairs and Maintenance
D120: 5510-000 - Plumbing Supplies & Rprs | F120: Repairs and Maintenance | G120: =_xlfn.XLOOKUP(D120,'[4]Operating Statement'!$B:$B,'[4]Operating Statement'!$S:$S) -> Repairs and Maintenance
D121: 5514-000 - Water Extraction/Repairs | F121: Repairs and Maintenance | G121: =_xlfn.XLOOKUP(D121,'[4]Operating Statement'!$B:$B,'[4]Operating Statement'!$S:$S) -> Repairs and Maintenance
D122: 5515-000 - HVAC Supplies & Rprs | F122: Repairs and Maintenance | G122: =_xlfn.XLOOKUP(D122,'[4]Operating Statement'!$B:$B,'[4]Operating Statement'!$S:$S) -> Repairs and Maintenance
D123: 5520-000 - Interior Supplies & Rprs | F123: Repairs and Maintenance | G123: =_xlfn.XLOOKUP(D123,'[4]Operating Statement'!$B:$B,'[4]Operating Statement'!$S:$S) -> Repairs and Maintenance
D124: 5524-000 - Plaster/Sheetrock Rprs | F124: Repairs and Maintenance | G124: =_xlfn.XLOOKUP(D124,'[4]Operating Statement'!$B:$B,'[4]Operating Statement'!$S:$S) -> Repairs and Maintenance
D125: 5525-000 - Doors/ Wndws/Glass Rprs | F125: Repairs and Maintenance | G125: =_xlfn.XLOOKUP(D125,'[4]Operating Statement'!$B:$B,'[4]Operating Statement'!$S:$S) -> Repairs and Maintenance
D126: 5530-000 - Security Locks & Keys | F126: Repairs and Maintenance | G126: =_xlfn.XLOOKUP(D126,'[4]Operating Statement'!$B:$B,'[4]Operating Statement'!$S:$S) -> Repairs and Maintenance
D127: 5535-000 - Common Area Rprs/Maint. | F127: Repairs and Maintenance | G127: =_xlfn.XLOOKUP(D127,'[4]Operating Statement'!$B:$B,'[4]Operating Statement'!$S:$S) -> Repairs and Maintenance
D128: 5540-000 - Exterior Supplies & Rprs | F128: Repairs and Maintenance | G128: =_xlfn.XLOOKUP(D128,'[4]Operating Statement'!$B:$B,'[4]Operating Statement'!$S:$S) -> Repairs and Maintenance
D129: 5550-000 - Elevator Parts & Repairs | F129: Repairs and Maintenance | G129: =_xlfn.XLOOKUP(D129,'[4]Operating Statement'!$B:$B,'[4]Operating Statement'!$S:$S) -> #N/A
...

Sheet RE Tax
B2: Actual RE Tax | C2: 1425631.4
B3: From | C3: 45976
B4: To | C4: =+C3+365 -> 46341
B5: https://www.hctax.net/Property/TaxStatement?account=kzrFbHWYJP9hz8gVllkz7ctaKFijLb96z72yEBEhQgQ=
B6: Parcel # | C6: 129-151-001-0001

Sheet Insurance
B2: Property Insurance - Global | C2: 52246 | E2: From | F2: 45834
B3: Liability Insurance - Marsh | C3: 5000 | E3: To | F3: =+F2+365 -> 46199
B4: Environmental Insurance - AON | C4: 24423.58
B5: Insurance Premium | C5: =SUM(C2:C4) -> 81669.58

Sheet NOI Projection
B2: DY
B3: Target DY | D3: 0.05 | E3: ß enter DY threshold
B5: Outstanding Principal | D5: ='Old OSAR'!E6 -> 47626516 | E5: ß link to total UPB
B7: Current Net Cash Flow | D7: ='Old OSAR'!K57 -> #REF! | E7: ß link to Net Cash Flow
B8: Additional Net Cash Flow | C8: =D9/D7-1 -> #REF! | D8: 489000 | E8: ß 'Goal Seek'
B9: Total Net Cash Flow | D9: =SUM(D7:D8) -> #REF!
B11: Resulting DY | D11: =D9/D5 -> #REF!
D12: =D3=D11 -> #REF!
B15: DSCR
B16: Target DSCR | D16: 1 | E16: ß enter DSCR threshold
B18: Debt Service | D18: ='Old OSAR'!K59 -> 2863478.1 | E18: ß link to Forward-12 Debt Service
B20: Current Net Cash Flow | D20: ='Old OSAR'!K57 -> #REF! | E20: ß link to Net Cash Flow
B21: Additional Net Cash Flow | C21: =D22/D20-1 -> #REF! | D21: 909933.43 | E21: ß 'Goal Seek'
B22: Total Net Cash Flow | D22: =SUM(D20:D21) -> #REF!
B24: Resulting DSCR | D24: =D22/D18 -> #REF!
D25: =D16=D24 -> #REF!

Sheet UW Comparison
B2: MEMORIAL HILLS
B3: INVESTMENT YEAR | C3: ='DSCR Calc'!H2 -> DY 1Q 2026 | D3: ="U/W YEAR "&Q3 -> U/W YEAR 1 | E3: Change | H3: Borrower | I3: Change | O3: Investment Year | P3: IN PLACE | Q3: 1 | R3: 2 | S3: 3 | T3: 4 | U3: 5 | V3: 6 | W3: 7 | X3: 8 | Y3: 9 | Z3: 10 | AA3: 11
B4: YEAR ENDING | C4: ='Old OSAR'!I14 -> 45930 | D4: =Q4 -> 46173 | H4: 2025 Budget | O4: Year Ending | P4: =P6 -> 45809 | Q4: =Q6 -> 46173 | R4: =EOMONTH(Q4,12) -> 46538 | S4: 45657 | T4: =E4 -> 0 | U4: 46022 | V4: 46387 | W4: 46752 | X4: 47118 | Y4: 47483 | Z4: 47848 | AA4: 48213
O5: Memorial Hills | P5: 0 | Q5: 1 | R5: 2 | S5: 3 | T5: 4 | U5: 5 | V5: 6 | W5: 7 | X5: 8 | Y5: 9 | Z5: 10 | AA5: 11 | AC5: Year | AD5: 0 | AE5: 1 | AF5: 1 | AG5: 1 | AH5: 1 | AI5: 1 | AJ5: 1 | AK5: 1 | AL5: 1 | AM5: 1 | AN5: 1 | AO5: 1 | AP5: 1 | AQ5: 2 | AR5: 2 | AS5: 2 | AT5: 2 | AU5: 2 | AV5: 2 | AW5: 2 | AX5: 2 | AY5: 2 | AZ5: 2 | BA5: 2 | BB5: 2 | BC5: 3 | BD5: 3 | BE5: 3 | BF5: 3 | BG5: 3 | BH5: 3 | BI5: 3 | BJ5: 3 | BK5: 3 | BL5: 3 | BM5: 3 | BN5: 3 | BO5: 4 | BP5: 4 | BQ5: 4 | BR5: 4 | BS5: 4 | BT5: 4 | BU5: 4 | BV5: 4 | BW5: 4 | BX5: 4 | BY5: 4 | BZ5: 4 | CA5: 5 | CB5: 5 | CC5: 5 | CD5: 5 | CE5: 5 | CF5: 5 | CG5: 5 | CH5: 5 | CI5: 5 | CJ5: 5 | CK5: 5 | CL5: 5 | CM5: 6 | CN5: 6 | CO5: 6 | CP5: 6 | CQ5: 6 | CR5: 6 | CS5: 6 | CT5: 6 | CU5: 6 | CV5: 6 | CW5: 6 | CX5: 6 | CY5: 7 | CZ5: 7 | DA5: 7 | DB5: 7 | DC5: 7 | DD5: 7 | DE5: 7 | DF5: 7 | DG5: 7 | DH5: 7 | DI5: 7 | DJ5: 7 | DK5: 8 | DL5: 8 | DM5: 8 | DN5: 8 | DO5: 8 | DP5: 8 | DQ5: 8 | DR5: 8 | DS5: 8 | DT5: 8 | DU5: 8 | DV5: 8 | DW5: 9 | DX5: 9 | DY5: 9 | DZ5: 9 | EA5: 9 | EB5: 9 | EC5: 9 | ED5: 9 | EE5: 9 | EF5: 9 | EG5: 9 | EH5: 9 | EI5: 10 | EJ5: 10 | EK5: 10 | EL5: 10 | EM5: 10 | EN5: 10 | EO5: 10 | EP5: 10 | EQ5: 10 | ER5: 10 | ES5: 10 | ET5: 10 | EU5: 11 | EV5: 11 | EW5: 11 | EX5: 11 | EY5: 11 | EZ5: 11 | FA5: 11 | FB5: 11 | FC5: 11 | FD5: 11 | FE5: 11 | FF5: 11
B6: UPB | C6: ='DSCR Calc'!H5 -> 47626516 | H6: ='2025 Budget'!U9 -> 47626516 | O6: Gross Market Rent | P6: 45809 | Q6: 46173 | R6: 46538 | S6: 46904 | T6: 47269 | U6: 47634 | V6: 47999 | W6: 48365 | X6: 48730 | Y6: 49095 | Z6: 49460 | AA6: 49826 | AC6: Month | AD6: 45809 | AE6: 1 | AF6: 2 | AG6: 3 | AH6: 4 | AI6: 5 | AJ6: 6 | AK6: 7 | AL6: 8 | AM6: 9 | AN6: 10 | AO6: 11 | AP6: 12 | AQ6: 13 | AR6: 14 | AS6: 15 | AT6: 16 | AU6: 17 | AV6: 18 | AW6: 19 | AX6: 20 | AY6: 21 | AZ6: 22 | BA6: 23 | BB6: 24 | BC6: 25 | BD6: 26 | BE6: 27 | BF6: 28 | BG6: 29 | BH6: 30 | BI6: 31 | BJ6: 32 | BK6: 33 | BL6: 34 | BM6: 35 | BN6: 36 | BO6: 37 | BP6: 38 | BQ6: 39 | BR6: 40 | BS6: 41 | BT6: 42 | BU6: 43 | BV6: 44 | BW6: 45 | BX6: 46 | BY6: 47 | BZ6: 48 | CA6: 49 | CB6: 50 | CC6: 51 | CD6: 52 | CE6: 53 | CF6: 54 | CG6: 55 | CH6: 56 | CI6: 57 | CJ6: 58 | CK6: 59 | CL6: 60 | CM6: 61 | CN6: 62 | CO6: 63 | CP6: 64 | CQ6: 65 | CR6: 66 | CS6: 67 | CT6: 68 | CU6: 69 | CV6: 70 | CW6: 71 | CX6: 72 | CY6: 73 | CZ6: 74 | DA6: 75 | DB6: 76 | DC6: 77 | DD6: 78 | DE6: 79 | DF6: 80 | DG6: 81 | DH6: 82 | DI6: 83 | DJ6: 84 | DK6: 85 | DL6: 86 | DM6: 87 | DN6: 88 | DO6: 89 | DP6: 90 | DQ6: 91 | DR6: 92 | DS6: 93 | DT6: 94 | DU6: 95 | DV6: 96 | DW6: 97 | DX6: 98 | DY6: 99 | DZ6: 100 | EA6: 101 | EB6: 102 | EC6: 103 | ED6: 104 | EE6: 105 | EF6: 106 | EG6: 107 | EH6: 108 | EI6: 109 | EJ6: 110 | EK6: 111 | EL6: 112 | EM6: 113 | EN6: 114 | EO6: 115 | EP6: 116 | EQ6: 117 | ER6: 118 | ES6: 119 | ET6: 120 | EU6: 121 | EV6: 122 | EW6: 123 | EX6: 124 | EY6: 125 | EZ6: 126 | FA6: 127 | FB6: 128 | FC6: 129 | FD6: 130 | FE6: 131 | FF6: 132
O7: Gross Market/Unit | P7: 1883.2614 | Q7: 1946.5923 | R7: 2070.3823 | S7: 2207.819 | T7: 2295.2979 | U7: 2351.3612 | V7: 2415.1875 | W7: 2487.6431 | X7: 2562.2724 | Y7: 2639.1406 | Z7: 2718.3148 | AA7: 2799.8643 | AC7: Occupancy
B8: Occuapancy | C8: ='Old OSAR'!I15 -> 0.8961 | H8: ='2025 Budget'!U11 -> 0 | O8: Gross Market/SF | P8: 1.9503588 | Q8: 2.015946 | R8: 2.1441465 | S8: 2.2864798 | T8: 2.3770754 | U8: 2.4351362 | V8: 2.5012366 | W8: 2.5762736 | X8: 2.6535619 | Y8: 2.7331687 | Z8: 2.8151638 | AA8: 2.8996187 | AC8: Beginning of Period Occupied Unit Count | AE8: 290 | AF8: 293 | AG8: 293 | AH8: 283 | AI8: 273 | AJ8: 273 | AK8: 273 | AL8: 273 | AM8: 273 | AN8: 273 | AO8: 273 | AP8: 273 | AQ8: 273 | AR8: 273 | AS8: 273 | AT8: 273 | AU8: 273 | AV8: 273 | AW8: 273 | AX8: 273 | AY8: 273 | AZ8: 273 | BA8: 273 | BB8: 273 | BC8: 273 | BD8: 273 | BE8: 273 | BF8: 273 | BG8: 273 | BH8: 273 | BI8: 273 | BJ8: 273 | BK8: 273 | BL8: 275 | BM8: 285 | BN8: 293 | BO8: 293 | BP8: 293 | BQ8: 293 | BR8: 293 | BS8: 293 | BT8: 293 | BU8: 293 | BV8: 293 | BW8: 293 | BX8: 293 | BY8: 293 | BZ8: 293 | CA8: 293 | CB8: 293 | CC8: 293 | CD8: 293 | CE8: 293 | CF8: 293 | CG8: 293 | CH8: 293 | CI8: 293 | CJ8: 293 | CK8: 293 | CL8: 293 | CM8: 293 | CN8: 293 | CO8: 293 | CP8: 293 | CQ8: 293 | CR8: 293 | CS8: 293 | CT8: 293 | CU8: 293 | CV8: 293 | CW8: 293 | CX8: 293 | CY8: 293 | CZ8: 293 | DA8: 293 | DB8: 293 | DC8: 293 | DD8: 293 | DE8: 293 | DF8: 293 | DG8: 293 | DH8: 293 | DI8: 293 | DJ8: 293 | DK8: 293 | DL8: 293 | DM8: 293 | DN8: 293 | DO8: 293 | DP8: 293 | DQ8: 293 | DR8: 293 | DS8: 293 | DT8: 293 | DU8: 293 | DV8: 293 | DW8: 293 | DX8: 293 | DY8: 293 | DZ8: 293 | EA8: 293 | EB8: 293 | EC8: 293 | ED8: 293 | EE8: 293 | EF8: 293 | EG8: 293 | EH8: 293 | EI8: 293 | EJ8: 293 | EK8: 293 | EL8: 293 | EM8: 293 | EN8: 293 | EO8: 293 | EP8: 293 | EQ8: 293 | ER8: 293 | ES8: 293 | ET8: 293 | EU8: 293 | EV8: 293 | EW8: 293 | EX8: 293 | EY8: 293 | EZ8: 293 | FA8: 293 | FB8: 293 | FC8: 293 | FD8: 293 | FE8: 293 | FF8: 293
B9: INCOME: | AC9: Net Move Ins - Online Units | AE9: 3 | AF9: 0 | AG9: 0 | AH9: 0 | AI9: 0 | AJ9: 0 | AK9: 0 | AL9: 0 | AM9: 0 | AN9: 0 | AO9: 0 | AP9: 0 | AQ9: 0 | AR9: 0 | AS9: 0 | AT9: 0 | AU9: 0 | AV9: 0 | AW9: 0 | AX9: 0 | AY9: 0 | AZ9: 0 | BA9: 0 | BB9: 0 | BC9: 0 | BD9: 0 | BE9: 0 | BF9: 0 | BG9: 0 | BH9: 0 | BI9: 0 | BJ9: 0 | BK9: 0 | BL9: 0 | BM9: 0 | BN9: 0 | BO9: 0 | BP9: 0 | BQ9: 0 | BR9: 0 | BS9: 0 | BT9: 0 | BU9: 0 | BV9: 0 | BW9: 0 | BX9: 0 | BY9: 0 | BZ9: 0 | CA9: 0 | CB9: 0 | CC9: 0 | CD9: 0 | CE9: 0 | CF9: 0 | CG9: 0 | CH9: 0 | CI9: 0 | CJ9: 0 | CK9: 0 | CL9: 0 | CM9: 0 | CN9: 0 | CO9: 0 | CP9: 0 | CQ9: 0 | CR9: 0 | CS9: 0 | CT9: 0 | CU9: 0 | CV9: 0 | CW9: 0 | CX9: 0 | CY9: 0 | CZ9: 0 | DA9: 0 | DB9: 0 | DC9: 0 | DD9: 0 | DE9: 0 | DF9: 0 | DG9: 0 | DH9: 0 | DI9: 0 | DJ9: 0 | DK9: 0 | DL9: 0 | DM9: 0 | DN9: 0 | DO9: 0 | DP9: 0 | DQ9: 0 | DR9: 0 | DS9: 0 | DT9: 0 | DU9: 0 | DV9: 0 | DW9: 0 | DX9: 0 | DY9: 0 | DZ9: 0 | EA9: 0 | EB9: 0 | EC9: 0 | ED9: 0 | EE9: 0 | EF9: 0 | EG9: 0 | EH9: 0 | EI9: 0 | EJ9: 0 | EK9: 0 | EL9: 0 | EM9: 0 | EN9: 0 | EO9: 0 | EP9: 0 | EQ9: 0 | ER9: 0 | ES9: 0 | ET9: 0 | EU9: 0 | EV9: 0 | EW9: 0 | EX9: 0 | EY9: 0 | EZ9: 0 | FA9: 0 | FB9: 0 | FC9: 0 | FD9: 0 | FE9: 0 | FF9: 0
B10: Number of Mos. Covered | O10: Memorial Hills | P10: In-Place | Q10: 1 | R10: 2 | S10: 3 | T10: 4 | U10: 5 | V10: 6 | W10: 7 | X10: 8 | Y10: 9 | Z10: 10 | AA10: 11 | AC10: Net Move Ins - Renovation Units | AE10: 0 | AF10: 0 | AG10: -10 | AH10: -10 | AI10: 0 | AJ10: 0 | AK10: 0 | AL10: 0 | AM10: 0 | AN10: 0 | AO10: 0 | AP10: 0 | AQ10: 0 | AR10: 0 | AS10: 0 | AT10: 0 | AU10: 0 | AV10: 0 | AW10: 0 | AX10: 0 | AY10: 0 | AZ10: 0 | BA10: 0 | BB10: 0 | BC10: 0 | BD10: 0 | BE10: 0 | BF10: 0 | BG10: 0 | BH10: 0 | BI10: 0 | BJ10: 0 | BK10: 2 | BL10: 10 | BM10: 8 | BN10: 0 | BO10: 0 | BP10: 0 | BQ10: 0 | BR10: 0 | BS10: 0 | BT10: 0 | BU10: 0 | BV10: 0 | BW10: 0 | BX10: 0 | BY10: 0 | BZ10: 0 | CA10: 0 | CB10: 0 | CC10: 0 | CD10: 0 | CE10: 0 | CF10: 0 | CG10: 0 | CH10: 0 | CI10: 0 | CJ10: 0 | CK10: 0 | CL10: 0 | CM10: 0 | CN10: 0 | CO10: 0 | CP10: 0 | CQ10: 0 | CR10: 0 | CS10: 0 | CT10: 0 | CU10: 0 | CV10: 0 | CW10: 0 | CX10: 0 | CY10: 0 | CZ10: 0 | DA10: 0 | DB10: 0 | DC10: 0 | DD10: 0 | DE10: 0 | DF10: 0 | DG10: 0 | DH10: 0 | DI10: 0 | DJ10: 0 | DK10: 0 | DL10: 0 | DM10: 0 | DN10: 0 | DO10: 0 | DP10: 0 | DQ10: 0 | DR10: 0 | DS10: 0 | DT10: 0 | DU10: 0 | DV10: 0 | DW10: 0 | DX10: 0 | DY10: 0 | DZ10: 0 | EA10: 0 | EB10: 0 | EC10: 0 | ED10: 0 | EE10: 0 | EF10: 0 | EG10: 0 | EH10: 0 | EI10: 0 | EJ10: 0 | EK10: 0 | EL10: 0 | EM10: 0 | EN10: 0 | EO10: 0 | EP10: 0 | EQ10: 0 | ER10: 0 | ES10: 0 | ET10: 0 | EU10: 0 | EV10: 0 | EW10: 0 | EX10: 0 | EY10: 0 | EZ10: 0 | FA10: 0 | FB10: 0 | FC10: 0 | FD10: 0 | FE10: 0 | FF10: 0
B11: Period Ended | C11: ='Old OSAR'!K21 -> DY 4Q 2025 | D11: ="U/W Year "&Q3 -> U/W Year 1 | H11: ='2025 Budget'!U14 -> Budget | O11: Rent Breakdown | P11: 45809 | Q11: 46173 | R11: 46538 | S11: 46904 | T11: 47269 | U11: 47634 | V11: 47999 | W11: 48365 | X11: 48730 | Y11: 49095 | Z11: 49460 | AA11: 49826 | AC11: End of Period Occupied Unit Count | AE11: 293 | AF11: 293 | AG11: 283 | AH11: 273 | AI11: 273 | AJ11: 273 | AK11: 273 | AL11: 273 | AM11: 273 | AN11: 273 | AO11: 273 | AP11: 273 | AQ11: 273 | AR11: 273 | AS11: 273 | AT11: 273 | AU11: 273 | AV11: 273 | AW11: 273 | AX11: 273 | AY11: 273 | AZ11: 273 | BA11: 273 | BB11: 273 | BC11: 273 | BD11: 273 | BE11: 273 | BF11: 273 | BG11: 273 | BH11: 273 | BI11: 273 | BJ11: 273 | BK11: 275 | BL11: 285 | BM11: 293 | BN11: 293 | BO11: 293 | BP11: 293 | BQ11: 293 | BR11: 293 | BS11: 293 | BT11: 293 | BU11: 293 | BV11: 293 | BW11: 293 | BX11: 293 | BY11: 293 | BZ11: 293 | CA11: 293 | CB11: 293 | CC11: 293 | CD11: 293 | CE11: 293 | CF11: 293 | CG11: 293 | CH11: 293 | CI11: 293 | CJ11: 293 | CK11: 293 | CL11: 293 | CM11: 293 | CN11: 293 | CO11: 293 | CP11: 293 | CQ11: 293 | CR11: 293 | CS11: 293 | CT11: 293 | CU11: 293 | CV11: 293 | CW11: 293 | CX11: 293 | CY11: 293 | CZ11: 293 | DA11: 293 | DB11: 293 | DC11: 293 | DD11: 293 | DE11: 293 | DF11: 293 | DG11: 293 | DH11: 293 | DI11: 293 | DJ11: 293 | DK11: 293 | DL11: 293 | DM11: 293 | DN11: 293 | DO11: 293 | DP11: 293 | DQ11: 293 | DR11: 293 | DS11: 293 | DT11: 293 | DU11: 293 | DV11: 293 | DW11: 293 | DX11: 293 | DY11: 293 | DZ11: 293 | EA11: 293 | EB11: 293 | EC11: 293 | ED11: 293 | EE11: 293 | EF11: 293 | EG11: 293 | EH11: 293 | EI11: 293 | EJ11: 293 | EK11: 293 | EL11: 293 | EM11: 293 | EN11: 293 | EO11: 293 | EP11: 293 | EQ11: 293 | ER11: 293 | ES11: 293 | ET11: 293 | EU11: 293 | EV11: 293 | EW11: 293 | EX11: 293 | EY11: 293 | EZ11: 293 | FA11: 293 | FB11: 293 | FC11: 293 | FD11: 293 | FE11: 293 | FF11: 293
B12: Statement Ending Date | C12: ='Old OSAR'!K22 -> 46022 | D12: =Q4 -> 46173 | H12: ='2025 Budget'!U15 -> 46022 | O12: In-Place Rent | P12: 6960534.1 | Q12: 6960534.1 | R12: 6960534.1 | S12: 6960534.1 | T12: 6960534.1 | U12: 6960534.1 | V12: 6960534.1 | W12: 6960534.1 | X12: 6960534.1 | Y12: 6960534.1 | Z12: 6960534.1 | AA12: 6960534.1 | AC12: Occupancy % | AE12: 0.94642857 | AF12: 0.9512987 | AG12: 0.93506494 | AH12: 0.9025974 | AI12: 0.88636364 | AJ12: 0.88636364 | AK12: 0.88636364 | AL12: 0.88636364 | AM12: 0.88636364 | AN12: 0.88636364 | AO12: 0.88636364 | AP12: 0.88636364 | AQ12: 0.88636364 | AR12: 0.88636364 | AS12: 0.88636364 | AT12: 0.88636364 | AU12: 0.88636364 | AV12: 0.88636364 | AW12: 0.88636364 | AX12: 0.88636364 | AY12: 0.88636364 | AZ12: 0.88636364 | BA12: 0.88636364 | BB12: 0.88636364 | BC12: 0.88636364 | BD12: 0.88636364 | BE12: 0.88636364 | BF12: 0.88636364 | BG12: 0.88636364 | BH12: 0.88636364 | BI12: 0.88636364 | BJ12: 0.88636364 | BK12: 0.88961039 | BL12: 0.90909091 | BM12: 0.93831169 | BN12: 0.9512987 | BO12: 0.9512987 | BP12: 0.9512987 | BQ12: 0.9512987 | BR12: 0.9512987 | BS12: 0.9512987 | BT12: 0.9512987 | BU12: 0.9512987 | BV12: 0.9512987 | BW12: 0.9512987 | BX12: 0.9512987 | BY12: 0.9512987 | BZ12: 0.9512987 | CA12: 0.9512987 | CB12: 0.9512987 | CC12: 0.9512987 | CD12: 0.9512987 | CE12: 0.9512987 | CF12: 0.9512987 | CG12: 0.9512987 | CH12: 0.9512987 | CI12: 0.9512987 | CJ12: 0.9512987 | CK12: 0.9512987 | CL12: 0.9512987 | CM12: 0.9512987 | CN12: 0.9512987 | CO12: 0.9512987 | CP12: 0.9512987 | CQ12: 0.9512987 | CR12: 0.9512987 | CS12: 0.9512987 | CT12: 0.9512987 | CU12: 0.9512987 | CV12: 0.9512987 | CW12: 0.9512987 | CX12: 0.9512987 | CY12: 0.9512987 | CZ12: 0.9512987 | DA12: 0.9512987 | DB12: 0.9512987 | DC12: 0.9512987 | DD12: 0.9512987 | DE12: 0.9512987 | DF12: 0.9512987 | DG12: 0.9512987 | DH12: 0.9512987 | DI12: 0.9512987 | DJ12: 0.9512987 | DK12: 0.9512987 | DL12: 0.9512987 | DM12: 0.9512987 | DN12: 0.9512987 | DO12: 0.9512987 | DP12: 0.9512987 | DQ12: 0.9512987 | DR12: 0.9512987 | DS12: 0.9512987 | DT12: 0.9512987 | DU12: 0.9512987 | DV12: 0.9512987 | DW12: 0.9512987 | DX12: 0.9512987 | DY12: 0.9512987 | DZ12: 0.9512987 | EA12: 0.9512987 | EB12: 0.9512987 | EC12: 0.9512987 | ED12: 0.9512987 | EE12: 0.9512987 | EF12: 0.9512987 | EG12: 0.9512987 | EH12: 0.9512987 | EI12: 0.9512987 | EJ12: 0.9512987 | EK12: 0.9512987 | EL12: 0.9512987 | EM12: 0.9512987 | EN12: 0.9512987 | EO12: 0.9512987 | EP12: 0.9512987 | EQ12: 0.9512987 | ER12: 0.9512987 | ES12: 0.9512987 | ET12: 0.9512987 | EU12: 0.9512987 | EV12: 0.9512987 | EW12: 0.9512987 | EX12: 0.9512987 | EY12: 0.9512987 | EZ12: 0.9512987 | FA12: 0.9512987 | FB12: 0.9512987 | FC12: 0.9512987 | FD12: 0.9512987 | FE12: 0.9512987 | FF12: 0.9512987
B13: Gross Potential Rent (3) | C13: ='Old OSAR'!K23 -> -327351.3 | D13: =SUMIFS($AH:$AH,$M:$M,$B13)*12 -> 7023252.6 | H13: ='2025 Budget'!U16 -> 0 | O13: Mark-to-Market (Cumulative) | Q13: 87125.942 | R13: 87125.942 | S13: 87125.942 | T13: 87125.942 | U13: 87125.942 | V13: 87125.942 | W13: 87125.942 | X13: 87125.942 | Y13: 87125.942 | Z13: 87125.942 | AA13: 87125.942
B14: Less: Vacancy Loss | D14: =SUMIFS($AH:$AH,$M:$M,$B14)*12 -> -684083.05 | H14: ='2025 Budget'!U17 -> 0 | O14: Reno Premiums (Cumulative) | Q14: 195710.22 | R14: 497328.42 | S14: 775921.84 | T14: 775921.84 | U14: 775921.84 | V14: 775921.84 | W14: 775921.84 | X14: 775921.84 | Y14: 775921.84 | Z14: 775921.84 | AA14: 775921.84
B15: OR | O15: Market Rent Growth (Cumulative) | Q15: -48765.261 | R15: 107144.43 | S15: 336517 | T15: 659839.11 | U15: 867049.15 | V15: 1102951.2 | W15: 1370747.2 | X15: 1646577.1 | Y15: 1930681.9 | Z15: 2223309.8 | AA15: 2524716.5
B16: Base Rent (3) | O16: Gross Potential Rent | P16: 6960534.1 | Q16: 7194605 | R16: 7652132.9 | S16: 8160098.8 | T16: 8483421 | U16: 8690631 | V16: 8926533.1 | W16: 9194329.1 | X16: 9470158.9 | Y16: 9754263.7 | Z16: 10046892 | AA16: 10348298 | AE16: =(AE23+AE24)/AE11 -> 1881.3889 | AF16: =(AF23+AF24)/AF11 -> 1894.1188 | AG16: =(AG23+AG24)/AG11 -> 1930.6913 | AH16: =(AH23+AH24)/AH11 -> 1935.0335 | AI16: =(AI23+AI24)/AI11 -> 1909.9129 | AJ16: =(AJ23+AJ24)/AJ11 -> 1919.6001 | AK16: =(AK23+AK24)/AK11 -> 1929.2921 | AL16: =(AL23+AL24)/AL11 -> 1938.9891 | ... AP16: =(AP23+AP24)/AP11 -> 1977.8261
B17: Delinquent Rent | C17: ='Old OSAR'!K27 -> 0 | D17: =SUMIFS($AH:$AH,$M:$M,$B17)*12 -> -16911.176 | E17: =C17-D17 -> 16911.176 | F17: =(C17-D17)/D17 -> -1 | H17: ='2025 Budget'!U20 -> -113103.08 | I17: =H17-C17 -> -113103.08 | J17: -1 | AC17: Monthly Proforma
B18: Parking Income | C18: ='Old OSAR'!K28 -> 0 | D18: =SUMIFS($AH:$AH,$M:$M,$B18)*12 -> 22176 | E18: =C18-D18 -> -22176 | F18: 1 | H18: ='2025 Budget'!U21 -> 0 | I18: =H18-C18 -> 0 | J18: =H18/C18-1 -> #DIV/0! | O18: Memorial Hills | P18: In-Place | Q18: 1 | R18: 2 | S18: 3 | T18: 4 | U18: 5 | V18: 6 | W18: 7 | X18: 8 | Y18: 9 | Z18: 10 | AA18: 11 | AC18: Year | AD18: 0 | AE18: 1 | AF18: =AE18+1 -> 2 | AG18: =AF18+1 -> 3 | AH18: =AG18+1 -> 4 | AI18: =AH18+1 -> 5 | AJ18: =AI18+1 -> 6 | AK18: =AJ18+1 -> 7 | AL18: =AK18+1 -> 8 | AM18: =AL18+1 -> 9 | ... FF18: =FE18+1 -> 132
B19: Other Income | C19: ='Old OSAR'!K29 -> 0 | D19: =SUMIFS($AH:$AH,$M:$M,$B19)*12 -> 364146.37 | E19: =C19-D19 -> -364146.37 | F19: =(C19-D19)/D19 -> -1 | H19: ='2025 Budget'!U22 -> 268442.16 | I19: =H19-C19 -> 268442.16 | J19: =H19/C19-1 -> #DIV/0! | O19: Operating Proforma | P19: 45809 | Q19: 46173 | R19: 46538 | S19: 46904 | T19: 47269 | U19: 47634 | V19: 47999 | W19: 48365 | X19: 48730 | Y19: 49095 | Z19: 49460 | AA19: 49826 | AC19: Month | AD19: 45809 | AE19: 45838 | AF19: =EOMONTH(AE19,1) -> 45869 | AG19: =EOMONTH(AF19,1) -> 45900 | AH19: =EOMONTH(AG19,1) -> 45930 | AI19: =EOMONTH(AH19,1) -> 45961 | AJ19: =EOMONTH(AI19,1) -> 45991 | AK19: =EOMONTH(AJ19,1) -> 46022 | AL19: =EOMONTH(AK19,1) -> 46053 | AM19: =EOMONTH(AL19,1) -> 46081 | ... FF19: =EOMONTH(FE19,1) -> 49826
O20: Revenues | AC20: Revenues
B21: *Effective Gross Income | C21: ='Old OSAR'!K32 -> #REF! | D21: =SUM(D13:D19) -> 6708580.8 | E21: =C21-D21 -> #REF! | F21: =(C21-D21)/D21 -> #REF! | H21: ='2025 Budget'!U24 -> 155339.08 | I21: =H21-C21 -> #REF! | J21: =H21/C21-1 -> #REF! | M21: Gross Potential Rent (3) | O21: Gross Potential Rent | P21: 7047660 | Q21: 7194605 | R21: 7652132.9 | S21: 8160098.8 | T21: 8483421 | U21: 8690631 | V21: 8926533.1 | W21: 9194329.1 | X21: 9470158.9 | Y21: 9754263.7 | Z21: 10046892 | AA21: 10348298 | AC21: Gross Potential Rent | AD21: 7047660 | AE21: 588242.49 | AF21: 589181.47 | AG21: 590121.95 | AH21: 591063.93 | AI21: 594046.07 | AJ21: 597029.71 | AK21: 600014.86 | AL21: 603001.52 | AM21: 605989.69 | AN21: 608979.38 | AO21: 611970.59 | AP21: 614963.31 | AQ21: 618446.28 | AR21: 621932.39 | AS21: 625421.63 | AT21: 628914.02 | AU21: 632409.57 | AV21: 635908.28 | AW21: 639410.17 | AX21: 642915.22 | AY21: 646423.47 | AZ21: 649934.9 | BA21: 653449.54 | BB21: 656967.38 | BC21: 660539.36 | BD21: 664114.41 | BE21: 667692.56 | BF21: 671273.79 | BG21: 674858.13 | BH21: 678445.57 | BI21: 682036.13 | BJ21: 685629.8 | BK21: 689226.6 | BL21: 692826.54 | BM21: 695999.68 | BN21: 697456.26 | BO21: 698906 | BP21: 700358.75 | BQ21: 701814.52 | BR21: 703273.32 | BS21: 704735.14 | BT21: 706200.01 | BU21: 707667.92 | BV21: 709138.88 | BW21: 710612.9 | BX21: 712089.99 | BY21: 713570.14 | BZ21: 715053.37 | CA21: 716453.41 | CB21: 717856.18 | CC21: 719261.71 | CD21: 720669.98 | CE21: 722081.01 | CF21: 723494.81 | CG21: 724911.37 | CH21: 726330.7 | CI21: 727752.82 | CJ21: 729177.72 | CK21: 730605.41 | CL21: 732035.89 | CM21: 733841.29 | CN21: 735651.14 | CO21: 737465.45 | CP21: 739284.24 | CQ21: 741107.52 | CR21: 742935.29 | CS21: 744767.57 | CT21: 746604.36 | CU21: 748445.69 | CV21: 750291.56 | CW21: 752141.98 | CX21: 753996.97 | CY21: 755856.53 | CZ21: 757720.67 | DA21: 759589.42 | DB21: 761462.77 | DC21: 763340.74 | DD21: 765223.35 | DE21: 767110.59 | DF21: 769002.5 | DG21: 770899.06 | DH21: 772800.31 | DI21: 774706.24 | DJ21: 776616.88 | DK21: 778532.22 | DL21: 780452.29 | DM21: 782377.1 | DN21: 784306.65 | DO21: 786240.96 | DP21: 788180.05 | DQ21: 790123.91 | DR21: 792072.57 | DS21: 794026.03 | DT21: 795984.32 | DU21: 797947.43 | DV21: 799915.38 | DW21: 801888.19 | DX21: 803865.86 | DY21: 805848.41 | DZ21: 807835.85 | EA21: 809828.19 | EB21: 811825.45 | EC21: 813827.63 | ED21: 815834.75 | EE21: 817846.82 | EF21: 819863.85 | EG21: 821885.85 | EH21: 823912.84 | EI21: 825944.84 | EJ21: 827981.84 | EK21: 830023.87 | EL21: 832070.93 | EM21: 834123.04 | EN21: 836180.21 | EO21: 838242.46 | EP21: 840309.79 | EQ21: 842382.22 | ER21: 844459.76 | ES21: 846542.43 | ET21: 848630.23 | EU21: 850723.18 | EV21: 852821.29 | EW21: 854924.58 | EX21: 857033.06 | EY21: 859146.73 | EZ21: 861265.62 | FA21: 863389.73 | FB21: 865519.08 | FC21: 867653.69 | FD21: 869793.55 | FE21: 871938.7 | FF21: 874089.14
M22: Gross Potential Rent (3) | O22: Loss to Lease | P22: -87125.942 | Q22: -69514.562 | R22: -104953.79 | S22: -107271.3 | T22: -107020.11 | U22: -103201.24 | V22: -133898 | W22: -137914.94 | X22: -142052.38 | Y22: -146313.96 | Z22: -150703.37 | AA22: -155224.48 | AC22: Loss to Lease | AD22: -87125.942 | AE22: -5792.8802 | AF22: -5792.8802 | AG22: -5792.8802 | AH22: -5792.8802 | AI22: -5792.8802 | AJ22: -5792.8802 | AK22: -5792.8802 | AL22: -5792.8802 | AM22: -5792.8802 | AN22: -5792.8802 | AO22: -5792.8802 | AP22: -5792.8802 | AQ22: -8746.1494 | AR22: -8746.1494 | AS22: -8746.1494 | AT22: -8746.1494 | AU22: -8746.1494 | AV22: -8746.1494 | AW22: -8746.1494 | AX22: -8746.1494 | AY22: -8746.1494 | AZ22: -8746.1494 | BA22: -8746.1494 | BB22: -8746.1494 | BC22: -8939.275 | BD22: -8939.275 | BE22: -8939.275 | BF22: -8939.275 | BG22: -8939.275 | BH22: -8939.275 | BI22: -8939.275 | BJ22: -8939.275 | BK22: -8939.275 | BL22: -8939.275 | BM22: -8939.275 | BN22: -8939.275 | BO22: -8918.3423 | BP22: -8918.3423 | BQ22: -8918.3423 | BR22: -8918.3423 | BS22: -8918.3423 | BT22: -8918.3423 | BU22: -8918.3423 | BV22: -8918.3423 | BW22: -8918.3423 | BX22: -8918.3423 | BY22: -8918.3423 | BZ22: -8918.3423 | CA22: -8600.1036 | CB22: -8600.1036 | CC22: -8600.1036 | CD22: -8600.1036 | CE22: -8600.1036 | CF22: -8600.1036 | CG22: -8600.1036 | CH22: -8600.1036 | CI22: -8600.1036 | CJ22: -8600.1036 | CK22: -8600.1036 | CL22: -8600.1036 | CM22: -11158.166 | CN22: -11158.166 | CO22: -11158.166 | CP22: -11158.166 | CQ22: -11158.166 | CR22: -11158.166 | CS22: -11158.166 | CT22: -11158.166 | CU22: -11158.166 | CV22: -11158.166 | CW22: -11158.166 | CX22: -11158.166 | CY22: -11492.911 | CZ22: -11492.911 | DA22: -11492.911 | DB22: -11492.911 | DC22: -11492.911 | DD22: -11492.911 | DE22: -11492.911 | DF22: -11492.911 | DG22: -11492.911 | DH22: -11492.911 | DI22: -11492.911 | DJ22: -11492.911 | DK22: -11837.699 | DL22: -11837.699 | DM22: -11837.699 | DN22: -11837.699 | DO22: -11837.699 | DP22: -11837.699 | DQ22: -11837.699 | DR22: -11837.699 | DS22: -11837.699 | DT22: -11837.699 | DU22: -11837.699 | DV22: -11837.699 | DW22: -12192.83 | DX22: -12192.83 | DY22: -12192.83 | DZ22: -12192.83 | EA22: -12192.83 | EB22: -12192.83 | EC22: -12192.83 | ED22: -12192.83 | EE22: -12192.83 | EF22: -12192.83 | EG22: -12192.83 | EH22: -12192.83 | EI22: -12558.615 | EJ22: -12558.615 | EK22: -12558.615 | EL22: -12558.615 | EM22: -12558.615 | EN22: -12558.615 | EO22: -12558.615 | EP22: -12558.615 | EQ22: -12558.615 | ER22: -12558.615 | ES22: -12558.615 | ET22: -12558.615 | EU22: -12935.373 | EV22: -12935.373 | EW22: -12935.373 | EX22: -12935.373 | EY22: -12935.373 | EZ22: -12935.373 | FA22: -12935.373 | FB22: -12935.373 | FC22: -12935.373 | FD22: -12935.373 | FE22: -12935.373 | FF22: -12935.373
O23: Net Effective Rent (NER) | P23: 6960534.1 | Q23: 7125090.4 | R23: 7547179.1 | S23: 8052827.5 | T23: 8376400.8 | U23: 8587429.8 | V23: 8792635.1 | W23: 9056414.1 | X23: 9328106.5 | Y23: 9607949.7 | Z23: 9896188.2 | AA23: 10193074 | AC23: Net Effective Rent (NER) | AD23: 6960534.1 | AE23: 582449.61 | AF23: 583388.59 | AG23: 584329.07 | AH23: 585271.05 | AI23: 588253.19 | AJ23: 591236.83 | AK23: 594221.98 | AL23: 597208.64 | AM23: 600196.81 | AN23: 603186.5 | AO23: 606177.71 | AP23: 609170.43 | AQ23: 609700.13 | AR23: 613186.24 | AS23: 616675.48 | AT23: 620167.87 | AU23: 623663.42 | AV23: 627162.13 | AW23: 630664.02 | AX23: 634169.08 | AY23: 637677.32 | AZ23: 641188.75 | BA23: 644703.39 | BB23: 648221.23 | BC23: 651600.08 | BD23: 655175.14 | BE23: 658753.28 | BF23: 662334.52 | BG23: 665918.86 | BH23: 669506.3 | BI23: 673096.85 | BJ23: 676690.53 | BK23: 680287.33 | BL23: 683887.26 | BM23: 687060.41 | BN23: 688516.99 | BO23: 689987.66 | BP23: 691440.41 | BQ23: 692896.18 | BR23: 694354.97 | BS23: 695816.8 | BT23: 697281.67 | BU23: 698749.58 | BV23: 700220.54 | BW23: 701694.56 | BX23: 703171.65 | BY23: 704651.8 | BZ23: 706135.03 | CA23: 707853.3 | CB23: 709256.08 | CC23: 710661.6 | CD23: 712069.88 | CE23: 713480.91 | CF23: 714894.7 | CG23: 716311.26 | CH23: 717730.6 | CI23: 719152.71 | CJ23: 720577.61 | CK23: 722005.3 | CL23: 723435.79 | CM23: 722683.12 | CN23: 724492.97 | CO23: 726307.29 | CP23: 728126.08 | CQ23: 729949.35 | CR23: 731777.12 | CS23: 733609.4 | CT23: 735446.2 | CU23: 737287.53 | CV23: 739133.39 | CW23: 740983.82 | CX23: 742838.8 | CY23: 744363.62 | CZ23: 746227.76 | DA23: 748096.51 | DB23: 749969.86 | DC23: 751847.83 | DD23: 753730.44 | DE23: 755617.68 | DF23: 757509.58 | DG23: 759406.15 | DH23: 761307.4 | DI23: 763213.33 | DJ23: 765123.97 | DK23: 766694.52 | DL23: 768614.6 | DM23: 770539.4 | DN23: 772468.95 | DO23: 774403.27 | DP23: 776342.35 | DQ23: 778286.21 | DR23: 780234.87 | DS23: 782188.34 | DT23: 784146.62 | DU23: 786109.73 | DV23: 788077.68 | DW23: 789695.36 | DX23: 791673.03 | DY23: 793655.58 | DZ23: 795643.02 | EA23: 797635.36 | EB23: 799632.62 | EC23: 801634.8 | ED23: 803641.92 | EE23: 805653.99 | EF23: 807671.02 | EG23: 809693.02 | EH23: 811720.01 | EI23: 813386.22 | EJ23: 815423.22 | EK23: 817465.25 | EL23: 819512.31 | EM23: 821564.42 | EN23: 823621.6 | EO23: 825683.84 | EP23: 827751.18 | EQ23: 829823.61 | ER23: 831901.15 | ES23: 833983.81 | ET23: 836071.62 | EU23: 837787.81 | EV23: 839885.92 | EW23: 841989.21 | EX23: 844097.68 | EY23: 846211.36 | EZ23: 848330.25 | FA23: 850454.36 | FB23: 852583.71 | FC23: 854718.31 | FD23: 856858.18 | FE23: 859003.33 | FF23: 861153.76
B24: OPERATING EXPENSES: | M24: Less: Vacancy Loss | O24: General Vacancy | P24: -406784.46 | Q24: -698843.45 | R24: -857633.98 | S24: -816942.08 | T24: -407941.6 | U24: -418218.98 | V24: -428212.75 | W24: -441059.13 | X24: -454290.9 | Y24: -467919.63 | Z24: -481957.22 | AA24: -496415.94 | AC24: General Vacancy | AD24: -406784.46 | AE24: -31202.657 | AF24: -28411.782 | AG24: -37943.446 | AH24: -57006.921 | AI24: -66846.953 | AJ24: -67186.003 | AK24: -67525.225 | AL24: -67864.618 | AM24: -68204.183 | AN24: -68543.92 | AO24: -68883.83 | AP24: -69223.913 | AQ24: -69284.106 | AR24: -69680.254 | AS24: -70076.759 | AT24: -70473.622 | AU24: -70870.843 | AV24: -71268.424 | AW24: -71666.365 | AX24: -72064.668 | AY24: -72463.332 | AZ24: -72862.358 | BA24: -73261.749 | BB24: -73661.503 | BC24: -74045.464 | BD24: -74451.72 | BE24: -74858.328 | BF24: -75265.286 | BG24: -75672.597 | BH24: -76080.261 | BI24: -76488.279 | BJ24: -76896.651 | BK24: -75096.653 | BL24: -62171.569 | BM24: -42383.597 | BN24: -33531.672 | BO24: -33603.295 | BP24: -33674.046 | BQ24: -33744.944 | BR24: -33815.989 | BS24: -33887.182 | BT24: -33958.523 | BU24: -34030.012 | BV24: -34101.65 | BW24: -34173.436 | BX24: -34245.372 | BY24: -34317.458 | BZ24: -34389.693 | CA24: -34473.375 | CB24: -34541.692 | CC24: -34610.143 | CD24: -34678.728 | CE24: -34747.447 | CF24: -34816.3 | CG24: -34885.289 | CH24: -34954.412 | CI24: -35023.671 | CJ24: -35093.066 | CK24: -35162.596 | CL24: -35232.262 | CM24: -35195.607 | CN24: -35283.749 | CO24: -35372.108 | CP24: -35460.686 | CQ24: -35549.481 | CR24: -35638.496 | CS24: -35727.731 | CT24: -35817.185 | CU24: -35906.86 | CV24: -35996.756 | CW24: -36086.874 | CX24: -36177.214 | CY24: -36251.475 | CZ24: -36342.261 | DA24: -36433.271 | DB24: -36524.506 | DC24: -36615.966 | DD24: -36707.651 | DE24: -36799.562 | DF24: -36891.701 | DG24: -36984.066 | DH24: -37076.659 | DI24: -37169.48 | DJ24: -37262.531 | DK24: -37339.019 | DL24: -37432.529 | DM24: -37526.27 | DN24: -37620.241 | DO24: -37714.445 | DP24: -37808.881 | DQ24: -37903.549 | DR24: -37998.452 | DS24: -38093.588 | DT24: -38188.959 | DU24: -38284.565 | DV24: -38380.407 | DW24: -38459.19 | DX24: -38555.505 | DY24: -38652.058 | DZ24: -38748.849 | EA24: -38845.878 | EB24: -38943.147 | EC24: -39040.656 | ED24: -39138.405 | EE24: -39236.395 | EF24: -39334.627 | EG24: -39433.102 | EH24: -39531.819 | EI24: -39612.965 | EJ24: -39712.17 | EK24: -39811.619 | EL24: -39911.314 | EM24: -40011.254 | EN24: -40111.441 | EO24: -40211.875 | EP24: -40312.557 | EQ24: -40413.487 | ER24: -40514.666 | ES24: -40616.095 | ET24: -40717.773 | EU24: -40801.354 | EV24: -40903.535 | EW24: -41005.968 | EX24: -41108.653 | EY24: -41211.592 | EZ24: -41314.785 | FA24: -41418.232 | FB24: -41521.934 | FC24: -41625.892 | FD24: -41730.106 | FE24: -41834.578 | FF24: -41939.307
B25: Real Estate Taxes | C25: ='Old OSAR'!K36 -> 1425631.4 | D25: =SUMIFS($AH:$AH,$M:$M,$B25)*12 -> 1483748.2 | E25: =C25-D25 -> -58116.762 | F25: =(C25-D25)/D25 -> -0.039168885 | H25: ='2025 Budget'!U28 -> 302702.88 | I25: =H25-C25 -> -1122928.5 | J25: =H25/C25-1 -> -0.78767101 | M25: Delinquent Rent | O25: Credit Loss | P25: -25478.68 | Q25: -16911.176 | R25: -17604.066 | S25: -19041.804 | T25: -20969.63 | U25: -21497.923 | V25: -22011.638 | W25: -22671.987 | X25: -23352.146 | Y25: -24052.711 | Z25: -24774.292 | AA25: -25517.521 | AC25: Credit Loss | AD25: -25478.68 | AE25: -1409.2647 | AF25: -1409.2647 | AG25: -1409.2647 | AH25: -1409.2647 | AI25: -1409.2647 | AJ25: -1409.2647 | AK25: -1409.2647 | AL25: -1409.2647 | AM25: -1409.2647 | AN25: -1409.2647 | AO25: -1409.2647 | AP25: -1409.2647 | AQ25: -1467.0055 | AR25: -1467.0055 | AS25: -1467.0055 | AT25: -1467.0055 | AU25: -1467.0055 | AV25: -1467.0055 | AW25: -1467.0055 | AX25: -1467.0055 | AY25: -1467.0055 | AZ25: -1467.0055 | BA25: -1467.0055 | BB25: -1467.0055 | BC25: -1586.817 | BD25: -1586.817 | BE25: -1586.817 | BF25: -1586.817 | BG25: -1586.817 | BH25: -1586.817 | BI25: -1586.817 | BJ25: -1586.817 | BK25: -1586.817 | BL25: -1586.817 | BM25: -1586.817 | BN25: -1586.817 | BO25: -1747.4691 | BP25: -1747.4691 | BQ25: -1747.4691 | BR25: -1747.4691 | BS25: -1747.4691 | BT25: -1747.4691 | BU25: -1747.4691 | BV25: -1747.4691 | BW25: -1747.4691 | BX25: -1747.4691 | BY25: -1747.4691 | BZ25: -1747.4691 | CA25: -1791.4936 | CB25: -1791.4936 | CC25: -1791.4936 | CD25: -1791.4936 | CE25: -1791.4936 | CF25: -1791.4936 | CG25: -1791.4936 | CH25: -1791.4936 | CI25: -1791.4936 | CJ25: -1791.4936 | CK25: -1791.4936 | CL25: -1791.4936 | CM25: -1834.3031 | CN25: -1834.3031 | CO25: -1834.3031 | CP25: -1834.3031 | CQ25: -1834.3031 | CR25: -1834.3031 | CS25: -1834.3031 | CT25: -1834.3031 | CU25: -1834.3031 | CV25: -1834.3031 | CW25: -1834.3031 | CX25: -1834.3031 | CY25: -1889.3322 | CZ25: -1889.3322 | DA25: -1889.3322 | DB25: -1889.3322 | DC25: -1889.3322 | DD25: -1889.3322 | DE25: -1889.3322 | DF25: -1889.3322 | DG25: -1889.3322 | DH25: -1889.3322 | DI25: -1889.3322 | DJ25: -1889.3322 | DK25: -1946.0122 | DL25: -1946.0122 | DM25: -1946.0122 | DN25: -1946.0122 | DO25: -1946.0122 | DP25: -1946.0122 | DQ25: -1946.0122 | DR25: -1946.0122 | DS25: -1946.0122 | DT25: -1946.0122 | DU25: -1946.0122 | DV25: -1946.0122 | DW25: -2004.3926 | DX25: -2004.3926 | DY25: -2004.3926 | DZ25: -2004.3926 | EA25: -2004.3926 | EB25: -2004.3926 | EC25: -2004.3926 | ED25: -2004.3926 | EE25: -2004.3926 | EF25: -2004.3926 | EG25: -2004.3926 | EH25: -2004.3926 | EI25: -2064.5243 | EJ25: -2064.5243 | EK25: -2064.5243 | EL25: -2064.5243 | EM25: -2064.5243 | EN25: -2064.5243 | EO25: -2064.5243 | EP25: -2064.5243 | EQ25: -2064.5243 | ER25: -2064.5243 | ES25: -2064.5243 | ET25: -2064.5243 | EU25: -2126.4601 | EV25: -2126.4601 | EW25: -2126.4601 | EX25: -2126.4601 | EY25: -2126.4601 | EZ25: -2126.4601 | FA25: -2126.4601 | FB25: -2126.4601 | FC25: -2126.4601 | FD25: -2126.4601 | FE25: -2126.4601 | FF25: -2126.4601
B26: Property Insurance | C26: ='Old OSAR'!K37 -> 81669.58 | D26: =SUMIFS($AH:$AH,$M:$M,$B26)*12 -> 215600 | E26: =C26-D26 -> -133930.42 | F26: =(C26-D26)/D26 -> -0.62119861 | H26: ='2025 Budget'!U29 -> 218571.52 | I26: =H26-C26 -> 136901.94 | J26: =H26/C26-1 -> 1.6762905 | M26: Other Income | O26: Model/Employee Units | P26: -74991.2 | Q26: -87850.266 | R26: -91449.693 | S26: -74188.846 | T26: -81699.856 | U26: -83758.142 | V26: -85759.627 | W26: -88332.416 | X26: -90982.389 | Y26: -93711.86 | Z26: -96523.216 | AA26: -99418.913 | AC26: Model/Employee Units | AD26: -74991.2 | AE26: -7320.8555 | AF26: -7320.8555 | AG26: -7320.8555 | AH26: -7320.8555 | AI26: -7320.8555 | AJ26: -7320.8555 | AK26: -7320.8555 | AL26: -7320.8555 | AM26: -7320.8555 | AN26: -7320.8555 | AO26: -7320.8555 | AP26: -7320.8555 | AQ26: -7620.8078 | AR26: -7620.8078 | AS26: -7620.8078 | AT26: -7620.8078 | AU26: -7620.8078 | AV26: -7620.8078 | AW26: -7620.8078 | AX26: -7620.8078 | AY26: -7620.8078 | AZ26: -7620.8078 | BA26: -7620.8078 | BB26: -7620.8078 | BC26: -6182.4039 | BD26: -6182.4039 | BE26: -6182.4039 | BF26: -6182.4039 | BG26: -6182.4039 | BH26: -6182.4039 | BI26: -6182.4039 | BJ26: -6182.4039 | BK26: -6182.4039 | BL26: -6182.4039 | BM26: -6182.4039 | BN26: -6182.4039 | BO26: -6808.3213 | BP26: -6808.3213 | BQ26: -6808.3213 | BR26: -6808.3213 | BS26: -6808.3213 | BT26: -6808.3213 | BU26: -6808.3213 | BV26: -6808.3213 | BW26: -6808.3213 | BX26: -6808.3213 | BY26: -6808.3213 | BZ26: -6808.3213 | CA26: -6979.8452 | CB26: -6979.8452 | CC26: -6979.8452 | CD26: -6979.8452 | CE26: -6979.8452 | CF26: -6979.8452 | CG26: -6979.8452 | CH26: -6979.8452 | CI26: -6979.8452 | CJ26: -6979.8452 | CK26: -6979.8452 | CL26: -6979.8452 | CM26: -7146.6356 | CN26: -7146.6356 | CO26: -7146.6356 | CP26: -7146.6356 | CQ26: -7146.6356 | CR26: -7146.6356 | CS26: -7146.6356 | CT26: -7146.6356 | CU26: -7146.6356 | CV26: -7146.6356 | CW26: -7146.6356 | CX26: -7146.6356 | CY26: -7361.0347 | CZ26: -7361.0347 | DA26: -7361.0347 | DB26: -7361.0347 | DC26: -7361.0347 | DD26: -7361.0347 | DE26: -7361.0347 | DF26: -7361.0347 | DG26: -7361.0347 | DH26: -7361.0347 | DI26: -7361.0347 | DJ26: -7361.0347 | DK26: -7581.8657 | DL26: -7581.8657 | DM26: -7581.8657 | DN26: -7581.8657 | DO26: -7581.8657 | DP26: -7581.8657 | DQ26: -7581.8657 | DR26: -7581.8657 | DS26: -7581.8657 | DT26: -7581.8657 | DU26: -7581.8657 | DV26: -7581.8657 | DW26: -7809.3217 | DX26: -7809.3217 | DY26: -7809.3217 | DZ26: -7809.3217 | EA26: -7809.3217 | EB26: -7809.3217 | EC26: -7809.3217 | ED26: -7809.3217 | EE26: -7809.3217 | EF26: -7809.3217 | EG26: -7809.3217 | EH26: -7809.3217 | EI26: -8043.6013 | EJ26: -8043.6013 | EK26: -8043.6013 | EL26: -8043.6013 | EM26: -8043.6013 | EN26: -8043.6013 | EO26: -8043.6013 | EP26: -8043.6013 | EQ26: -8043.6013 | ER26: -8043.6013 | ES26: -8043.6013 | ET26: -8043.6013 | EU26: -8284.9094 | EV26: -8284.9094 | EW26: -8284.9094 | EX26: -8284.9094 | EY26: -8284.9094 | EZ26: -8284.9094 | FA26: -8284.9094 | FB26: -8284.9094 | FC26: -8284.9094 | FD26: -8284.9094 | FE26: -8284.9094 | FF26: -8284.9094
B27: Utilities | C27: ='Old OSAR'!K38 -> 0 | D27: =SUMIFS($AH:$AH,$M:$M,$B27)*12 -> 369600 | E27: =C27-D27 -> -369600 | F27: =(C27-D27)/D27 -> -1 | H27: ='2025 Budget'!U30 -> 387718.27 | I27: =H27-C27 -> 387718.27 | J27: =H27/C27-1 -> #DIV/0! | M27: Other Income | O27: Concessions | P27: -22926 | Q27: -202934.11 | R27: -176040.66 | S27: -76167.215 | T27: -41939.259 | U27: -42995.846 | V27: -44023.275 | W27: -45343.974 | X27: -46704.293 | Y27: -48105.422 | Z27: -49548.584 | AA27: -51035.042 | AC27: Concessions | AD27: -22926 | AE27: -16911.176 | AF27: -16911.176 | AG27: -16911.176 | AH27: -16911.176 | AI27: -16911.176 | AJ27: -16911.176 | AK27: -16911.176 | AL27: -16911.176 | AM27: -16911.176 | AN27: -16911.176 | AO27: -16911.176 | AP27: -16911.176 | AQ27: -14670.055 | AR27: -14670.055 | AS27: -14670.055 | AT27: -14670.055 | AU27: -14670.055 | AV27: -14670.055 | AW27: -14670.055 | AX27: -14670.055 | AY27: -14670.055 | AZ27: -14670.055 | BA27: -14670.055 | BB27: -14670.055 | BC27: -6347.268 | BD27: -6347.268 | BE27: -6347.268 | BF27: -6347.268 | BG27: -6347.268 | BH27: -6347.268 | BI27: -6347.268 | BJ27: -6347.268 | BK27: -6347.268 | BL27: -6347.268 | BM27: -6347.268 | BN27: -6347.268 | BO27: -3494.9383 | BP27: -3494.9383 | BQ27: -3494.9383 | BR27: -3494.9383 | BS27: -3494.9383 | BT27: -3494.9383 | BU27: -3494.9383 | BV27: -3494.9383 | BW27: -3494.9383 | BX27: -3494.9383 | BY27: -3494.9383 | BZ27: -3494.9383 | CA27: -3582.9872 | CB27: -3582.9872 | CC27: -3582.9872 | CD27: -3582.9872 | CE27: -3582.9872 | CF27: -3582.9872 | CG27: -3582.9872 | CH27: -3582.9872 | CI27: -3582.9872 | CJ27: -3582.9872 | CK27: -3582.9872 | CL27: -3582.9872 | CM27: -3668.6063 | CN27: -3668.6063 | CO27: -3668.6063 | CP27: -3668.6063 | CQ27: -3668.6063 | CR27: -3668.6063 | CS27: -3668.6063 | CT27: -3668.6063 | CU27: -3668.6063 | CV27: -3668.6063 | CW27: -3668.6063 | CX27: -3668.6063 | CY27: -3778.6645 | CZ27: -3778.6645 | DA27: -3778.6645 | DB27: -3778.6645 | DC27: -3778.6645 | DD27: -3778.6645 | DE27: -3778.6645 | DF27: -3778.6645 | DG27: -3778.6645 | DH27: -3778.6645 | DI27: -3778.6645 | DJ27: -3778.6645 | DK27: -3892.0244 | DL27: -3892.0244 | DM27: -3892.0244 | DN27: -3892.0244 | DO27: -3892.0244 | DP27: -3892.0244 | DQ27: -3892.0244 | DR27: -3892.0244 | DS27: -3892.0244 | DT27: -3892.0244 | DU27: -3892.0244 | DV27: -3892.0244 | DW27: -4008.7851 | DX27: -4008.7851 | DY27: -4008.7851 | DZ27: -4008.7851 | EA27: -4008.7851 | EB27: -4008.7851 | EC27: -4008.7851 | ED27: -4008.7851 | EE27: -4008.7851 | EF27: -4008.7851 | EG27: -4008.7851 | EH27: -4008.7851 | EI27: -4129.0487 | EJ27: -4129.0487 | EK27: -4129.0487 | EL27: -4129.0487 | EM27: -4129.0487 | EN27: -4129.0487 | EO27: -4129.0487 | EP27: -4129.0487 | EQ27: -4129.0487 | ER27: -4129.0487 | ES27: -4129.0487 | ET27: -4129.0487 | EU27: -4252.9201 | EV27: -4252.9201 | EW27: -4252.9201 | EX27: -4252.9201 | EY27: -4252.9201 | EZ27: -4252.9201 | FA27: -4252.9201 | FB27: -4252.9201 | FC27: -4252.9201 | FD27: -4252.9201 | FE27: -4252.9201 | FF27: -4252.9201
B28: Repairs and Maintenance | C28: ='Old OSAR'!K39 -> 0 | D28: =SUMIFS($AH:$AH,$M:$M,$B28)*12 -> 377300 | E28: =C28-D28 -> -377300 | F28: =(C28-D28)/D28 -> -1 | H28: ='2025 Budget'!U31 -> 241403.27 | I28: =H28-C28 -> 241403.27 | J28: =H28/C28-1 -> #DIV/0! | O28: Net Effective Lease Income | P28: 6430353.7 | Q28: 6118551.4 | R28: 6404450.7 | S28: 7066487.6 | T28: 7823850.5 | U28: 8020958.9 | V28: 8212627.8 | W28: 8459006.6 | X28: 8712776.8 | Y28: 8974160.1 | Z28: 9243384.9 | AA28: 9520686.5 | AC28: Net Effective Lease Income | AD28: 6430353.7 | AE28: 525605.65 | AF28: 529335.51 | AG28: 520744.33 | AH28: 502622.84 | AI28: 495764.94 | AJ28: 498409.53 | AK28: 501055.46 | AL28: 503702.72 | AM28: 506351.33 | AN28: 509001.28 | AO28: 511652.58 | AP28: 514305.22 | AQ28: 516658.16 | AR28: 519748.11 | AS28: 522840.85 | AT28: 525936.38 | AU28: 529034.71 | AV28: 532135.84 | AW28: 535239.78 | AX28: 538346.54 | AY28: 541456.12 | AZ28: 544568.53 | BA28: 547683.77 | BB28: 550801.86 | BC28: 563438.13 | BD28: 566606.93 | BE28: 569778.47 | BF28: 572952.74 | BG28: 576129.77 | BH28: 579309.55 | BI28: 582492.09 | BJ28: 585677.39 | BK28: 591074.19 | BL28: 607599.2 | BM28: 630560.32 | BN28: 640868.83 | BO28: 644333.63 | BP28: 645715.63 | BQ28: 647100.51 | BR28: 648488.26 | BS28: 649878.89 | BT28: 651272.42 | BU28: 652668.84 | BV28: 654068.16 | BW28: 655470.4 | BX28: 656875.54 | BY28: 658283.61 | BZ28: 659694.61 | CA28: 661025.6 | CB28: 662360.06 | CC28: 663697.13 | CD28: 665036.82 | CE28: 666379.13 | CF28: 667724.08 | CG28: 669071.65 | CH28: 670421.86 | CI28: 671774.72 | CJ28: 673130.22 | CK28: 674488.38 | CL28: 675849.2 | CM28: 674837.97 | CN28: 676559.68 | CO28: 678285.63 | CP28: 680015.85 | CQ28: 681750.32 | CR28: 683489.08 | CS28: 685232.12 | CT28: 686979.47 | CU28: 688731.12 | CV28: 690487.09 | CW28: 692247.4 | CX28: 694012.04 | CY28: 695083.11 | CZ28: 696856.47 | DA28: 698634.2 | DB28: 700416.32 | DC28: 702202.83 | DD28: 703993.75 | DE28: 705789.09 | DF28: 707588.85 | DG28: 709393.05 | DH28: 711201.71 | DI28: 713014.82 | DJ28: 714832.4 | DK28: 715935.6 | DL28: 717762.16 | DM28: 719593.23 | DN28: 721428.81 | DO28: 723268.92 | DP28: 725113.57 | DQ28: 726962.76 | DR28: 728816.52 | DS28: 730674.85 | DT28: 732537.76 | DU28: 734405.26 | DV28: 736277.38 | DW28: 737413.67 | DX28: 739295.03 | DY28: 741181.03 | DZ28: 743071.67 | EA28: 744966.99 | EB28: 746866.97 | EC28: 748771.64 | ED28: 750681.01 | EE28: 752595.09 | EF28: 754513.89 | EG28: 756437.42 | EH28: 758365.7 | EI28: 759536.08 | EJ28: 761473.88 | EK28: 763416.46 | EL28: 765363.82 | EM28: 767316 | EN28: 769272.98 | EO28: 771234.79 | EP28: 773201.44 | EQ28: 775172.94 | ER28: 777149.31 | ES28: 779130.54 | ET28: 781116.67 | EU28: 782322.16 | EV28: 784318.1 | EW28: 786318.95 | EX28: 788324.74 | EY28: 790335.48 | EZ28: 792351.17 | FA28: 794371.84 | FB28: 796397.49 | FC28: 798428.13 | FD28: 800463.79 | FE28: 802504.46 | FF28: 804550.17
B29: Management Fees | C29: ='Old OSAR'!K40 -> #REF! | D29: =SUMIFS($AH:$AH,$M:$M,$B29)*12 -> 167714.52 | E29: =C29-D29 -> #REF! | F29: =(C29-D29)/D29 -> #REF! | H29: ='2025 Budget'!U32 -> 168764.36 | I29: =H29-C29 -> #REF! | J29: =H29/C29-1 -> #REF! | O29: Per Unit/Month | P29: 1739.8143 | Q29: 1655.4522 | R29: 1732.8059 | S29: 1911.9285 | T29: 2116.8427 | U29: 2170.1729 | V29: 2222.0313 | W29: 2288.6923 | X29: 2357.353 | Y29: 2428.0736 | Z29: 2500.9158 | AA29: 2575.9433 | AD29: 1739.8143
B30: Payroll & Benefits | C30: ='Old OSAR'!K40 -> #REF! | D30: =SUMIFS($AH:$AH,$M:$M,$B30)*12 -> 646800 | E30: =C30-D30 -> #REF! | F30: =(C30-D30)/D30 -> #REF! | H30: ='2025 Budget'!U33 -> 537465.12 | I30: =H30-C30 -> #REF! | J30: =H30/C30-1 -> #REF!
B31: Advertising & Marketing | C31: ='Old OSAR'!K41 -> 0 | D31: =SUMIFS($AH:$AH,$M:$M,$B31)*12 -> 261800 | E31: =C31-D31 -> -261800 | F31: =(C31-D31)/D31 -> -1 | H31: ='2025 Budget'!U34 -> 79996.4 | I31: =H31-C31 -> 79996.4 | J31: =H31/C31-1 -> #DIV/0! | M31: Other Income | O31: Utility Reimbs | P31: 343715.6 | Q31: 369600 | R31: 380688 | S31: 392108.64 | T31: 403871.9 | U31: 415988.06 | V31: 428467.7 | W31: 441321.73 | X31: 454561.38 | Y31: 468198.22 | Z31: 482244.17 | AA31: 496711.49 | AC31: Utility Reimbs | AD31: 343715.6 | AE31: 30800 | AF31: 30800 | AG31: 30800 | AH31: 30800 | AI31: 30800 | AJ31: 30800 | AK31: 30800 | AL31: 30800 | AM31: 30800 | AN31: 30800 | AO31: 30800 | AP31: 30800 | AQ31: 31724 | AR31: 31724 | AS31: 31724 | AT31: 31724 | AU31: 31724 | AV31: 31724 | AW31: 31724 | AX31: 31724 | AY31: 31724 | AZ31: 31724 | BA31: 31724 | BB31: 31724 | BC31: 32675.72 | BD31: 32675.72 | BE31: 32675.72 | BF31: 32675.72 | BG31: 32675.72 | BH31: 32675.72 | BI31: 32675.72 | BJ31: 32675.72 | BK31: 32675.72 | BL31: 32675.72 | BM31: 32675.72 | BN31: 32675.72 | BO31: 33655.992 | BP31: 33655.992 | BQ31: 33655.992 | BR31: 33655.992 | BS31: 33655.992 | BT31: 33655.992 | BU31: 33655.992 | BV31: 33655.992 | BW31: 33655.992 | BX31: 33655.992 | BY31: 33655.992 | BZ31: 33655.992 | CA31: 34665.671 | CB31: 34665.671 | CC31: 34665.671 | CD31: 34665.671 | CE31: 34665.671 | CF31: 34665.671 | CG31: 34665.671 | CH31: 34665.671 | CI31: 34665.671 | CJ31: 34665.671 | CK31: 34665.671 | CL31: 34665.671 | CM31: 35705.641 | CN31: 35705.641 | CO31: 35705.641 | CP31: 35705.641 | CQ31: 35705.641 | CR31: 35705.641 | CS31: 35705.641 | CT31: 35705.641 | CU31: 35705.641 | CV31: 35705.641 | CW31: 35705.641 | CX31: 35705.641 | CY31: 36776.811 | CZ31: 36776.811 | DA31: 36776.811 | DB31: 36776.811 | DC31: 36776.811 | DD31: 36776.811 | DE31: 36776.811 | DF31: 36776.811 | DG31: 36776.811 | DH31: 36776.811 | DI31: 36776.811 | DJ31: 36776.811 | DK31: 37880.115 | DL31: 37880.115 | DM31: 37880.115 | DN31: 37880.115 | DO31: 37880.115 | DP31: 37880.115 | DQ31: 37880.115 | DR31: 37880.115 | DS31: 37880.115 | DT31: 37880.115 | DU31: 37880.115 | DV31: 37880.115 | DW31: 39016.519 | DX31: 39016.519 | DY31: 39016.519 | DZ31: 39016.519 | EA31: 39016.519 | EB31: 39016.519 | EC31: 39016.519 | ED31: 39016.519 | EE31: 39016.519 | EF31: 39016.519 | EG31: 39016.519 | EH31: 39016.519 | EI31: 40187.014 | EJ31: 40187.014 | EK31: 40187.014 | EL31: 40187.014 | EM31: 40187.014 | EN31: 40187.014 | EO31: 40187.014 | EP31: 40187.014 | EQ31: 40187.014 | ER31: 40187.014 | ES31: 40187.014 | ET31: 40187.014 | EU31: 41392.624 | EV31: 41392.624 | EW31: 41392.624 | EX31: 41392.624 | EY31: 41392.624 | EZ31: 41392.624 | FA31: 41392.624 | FB31: 41392.624 | FC31: 41392.624 | FD31: 41392.624 | FE31: 41392.624 | FF31: 41392.624
B32: Professional Fees | C32: ='Old OSAR'!K42 -> 0 | D32: =SUMIFS($AH:$AH,$M:$M,$B32)*12 -> 0 | E32: =C32-D32 -> 0 | F32: =(C32-D32)/D32 -> #DIV/0! | H32: ='2025 Budget'!U35 -> 6475.2 | I32: =H32-C32 -> 6475.2 | J32: =H32/C32-1 -> #DIV/0! | M32: Other Income | O32: Bulk Cable/WiFi (Net) | P32: 0 | Q32: 47024.474 | R32: 126089.97 | S32: 139458.07 | T32: 143641.81 | U32: 147951.07 | V32: 152389.6 | W32: 156961.29 | X32: 161670.13 | Y32: 166520.23 | Z32: 171515.84 | AA32: 176661.31 | AC32: Bulk Cable/WiFi (Net) | AD32: 0 | AE32: 3918.7062 | AF32: 3918.7062 | AG32: 3918.7062 | AH32: 3918.7062 | AI32: 3918.7062 | AJ32: 3918.7062 | AK32: 3918.7062 | AL32: 3918.7062 | AM32: 3918.7062 | AN32: 3918.7062 | AO32: 3918.7062 | AP32: 3918.7062 | AQ32: 10507.498 | AR32: 10507.498 | AS32: 10507.498 | AT32: 10507.498 | AU32: 10507.498 | AV32: 10507.498 | AW32: 10507.498 | AX32: 10507.498 | AY32: 10507.498 | AZ32: 10507.498 | BA32: 10507.498 | BB32: 10507.498 | BC32: 11621.506 | BD32: 11621.506 | BE32: 11621.506 | BF32: 11621.506 | BG32: 11621.506 | BH32: 11621.506 | BI32: 11621.506 | BJ32: 11621.506 | BK32: 11621.506 | BL32: 11621.506 | BM32: 11621.506 | BN32: 11621.506 | BO32: 11970.151 | BP32: 11970.151 | BQ32: 11970.151 | BR32: 11970.151 | BS32: 11970.151 | BT32: 11970.151 | BU32: 11970.151 | BV32: 11970.151 | BW32: 11970.151 | BX32: 11970.151 | BY32: 11970.151 | BZ32: 11970.151 | CA32: 12329.256 | CB32: 12329.256 | CC32: 12329.256 | CD32: 12329.256 | CE32: 12329.256 | CF32: 12329.256 | CG32: 12329.256 | CH32: 12329.256 | CI32: 12329.256 | CJ32: 12329.256 | CK32: 12329.256 | CL32: 12329.256 | CM32: 12699.133 | CN32: 12699.133 | CO32: 12699.133 | CP32: 12699.133 | CQ32: 12699.133 | CR32: 12699.133 | CS32: 12699.133 | CT32: 12699.133 | CU32: 12699.133 | CV32: 12699.133 | CW32: 12699.133 | CX32: 12699.133 | CY32: 13080.107 | CZ32: 13080.107 | DA32: 13080.107 | DB32: 13080.107 | DC32: 13080.107 | DD32: 13080.107 | DE32: 13080.107 | DF32: 13080.107 | DG32: 13080.107 | DH32: 13080.107 | DI32: 13080.107 | DJ32: 13080.107 | DK32: 13472.511 | DL32: 13472.511 | DM32: 13472.511 | DN32: 13472.511 | DO32: 13472.511 | DP32: 13472.511 | DQ32: 13472.511 | DR32: 13472.511 | DS32: 13472.511 | DT32: 13472.511 | DU32: 13472.511 | DV32: 13472.511 | DW32: 13876.686 | DX32: 13876.686 | DY32: 13876.686 | DZ32: 13876.686 | EA32: 13876.686 | EB32: 13876.686 | EC32: 13876.686 | ED32: 13876.686 | EE32: 13876.686 | EF32: 13876.686 | EG32: 13876.686 | EH32: 13876.686 | EI32: 14292.986 | EJ32: 14292.986 | EK32: 14292.986 | EL32: 14292.986 | EM32: 14292.986 | EN32: 14292.986 | EO32: 14292.986 | EP32: 14292.986 | EQ32: 14292.986 | ER32: 14292.986 | ES32: 14292.986 | ET32: 14292.986 | EU32: 14721.776 | EV32: 14721.776 | EW32: 14721.776 | EX32: 14721.776 | EY32: 14721.776 | EZ32: 14721.776 | FA32: 14721.776 | FB32: 14721.776 | FC32: 14721.776 | FD32: 14721.776 | FE32: 14721.776 | FF32: 14721.776
B33: General and Administrative | C33: ='Old OSAR'!K43 -> 0 | D33: =SUMIFS($AH:$AH,$M:$M,$B33)*12 -> 123200 | E33: =C33-D33 -> -123200 | F33: =(C33-D33)/D33 -> -1 | H33: ='2025 Budget'!U36 -> 134336.84 | I33: =H33-C33 -> 134336.84 | J33: =H33/C33-1 -> #DIV/0! | M33: Other Income | O33: Amenity Fee | P33: 71785.88 | Q33: 73920 | R33: 76137.6 | S33: 78421.728 | T33: 80774.38 | U33: 83197.611 | V33: 85693.54 | W33: 88264.346 | X33: 90912.276 | Y33: 93639.644 | Z33: 96448.834 | AA33: 99342.299 | AC33: Amenity Fee | AD33: 71785.88 | AE33: 6160 | AF33: 6160 | AG33: 6160 | AH33: 6160 | AI33: 6160 | AJ33: 6160 | AK33: 6160 | AL33: 6160 | AM33: 6160 | AN33: 6160 | AO33: 6160 | AP33: 6160 | AQ33: 6344.8 | AR33: 6344.8 | AS33: 6344.8 | AT33: 6344.8 | AU33: 6344.8 | AV33: 6344.8 | AW33: 6344.8 | AX33: 6344.8 | AY33: 6344.8 | AZ33: 6344.8 | BA33: 6344.8 | BB33: 6344.8 | BC33: 6535.144 | BD33: 6535.144 | BE33: 6535.144 | BF33: 6535.144 | BG33: 6535.144 | BH33: 6535.144 | BI33: 6535.144 | BJ33: 6535.144 | BK33: 6535.144 | BL33: 6535.144 | BM33: 6535.144 | BN33: 6535.144 | BO33: 6731.1983 | BP33: 6731.1983 | BQ33: 6731.1983 | BR33: 6731.1983 | BS33: 6731.1983 | BT33: 6731.1983 | BU33: 6731.1983 | BV33: 6731.1983 | BW33: 6731.1983 | BX33: 6731.1983 | BY33: 6731.1983 | BZ33: 6731.1983 | CA33: 6933.1343 | CB33: 6933.1343 | CC33: 6933.1343 | CD33: 6933.1343 | CE33: 6933.1343 | CF33: 6933.1343 | CG33: 6933.1343 | CH33: 6933.1343 | CI33: 6933.1343 | CJ33: 6933.1343 | CK33: 6933.1343 | CL33: 6933.1343 | CM33: 7141.1283 | CN33: 7141.1283 | CO33: 7141.1283 | CP33: 7141.1283 | CQ33: 7141.1283 | CR33: 7141.1283 | CS33: 7141.1283 | CT33: 7141.1283 | CU33: 7141.1283 | CV33: 7141.1283 | CW33: 7141.1283 | CX33: 7141.1283 | CY33: 7355.3621 | CZ33: 7355.3621 | DA33: 7355.3621 | DB33: 7355.3621 | DC33: 7355.3621 | DD33: 7355.3621 | DE33: 7355.3621 | DF33: 7355.3621 | DG33: 7355.3621 | DH33: 7355.3621 | DI33: 7355.3621 | DJ33: 7355.3621 | DK33: 7576.023 | DL33: 7576.023 | DM33: 7576.023 | DN33: 7576.023 | DO33: 7576.023 | DP33: 7576.023 | DQ33: 7576.023 | DR33: 7576.023 | DS33: 7576.023 | DT33: 7576.023 | DU33: 7576.023 | DV33: 7576.023 | DW33: 7803.3037 | DX33: 7803.3037 | DY33: 7803.3037 | DZ33: 7803.3037 | EA33: 7803.3037 | EB33: 7803.3037 | EC33: 7803.3037 | ED33: 7803.3037 | EE33: 7803.3037 | EF33: 7803.3037 | EG33: 7803.3037 | EH33: 7803.3037 | EI33: 8037.4028 | EJ33: 8037.4028 | EK33: 8037.4028 | EL33: 8037.4028 | EM33: 8037.4028 | EN33: 8037.4028 | EO33: 8037.4028 | EP33: 8037.4028 | EQ33: 8037.4028 | ER33: 8037.4028 | ES33: 8037.4028 | ET33: 8037.4028 | EU33: 8278.5249 | EV33: 8278.5249 | EW33: 8278.5249 | EX33: 8278.5249 | EY33: 8278.5249 | EZ33: 8278.5249 | FA33: 8278.5249 | FB33: 8278.5249 | FC33: 8278.5249 | FD33: 8278.5249 | FE33: 8278.5249 | FF33: 8278.5249
B34: Other Expenses | C34: ='Old OSAR'!K44 -> 0 | D34: =SUMIFS($AH:$AH,$M:$M,$B34)*12 -> 0 | E34: =C34-D34 -> 0 | F34: 0 | H34: ='2025 Budget'!U37 -> 28944.2 | I34: =H34-C34 -> 28944.2 | J34: 1 | M34: Parking Income | O34: Parking/Storage | P34: 17787.24 | Q34: 22176 | R34: 22841.28 | S34: 23526.518 | T34: 24232.314 | U34: 24959.283 | V34: 25708.062 | W34: 26479.304 | X34: 27273.683 | Y34: 28091.893 | Z34: 28934.65 | AA34: 29802.69 | AC34: Parking/Storage | AD34: 17787.24 | AE34: 1848 | AF34: 1848 | AG34: 1848 | AH34: 1848 | AI34: 1848 | AJ34: 1848 | AK34: 1848 | AL34: 1848 | AM34: 1848 | AN34: 1848 | AO34: 1848 | AP34: 1848 | AQ34: 1903.44 | AR34: 1903.44 | AS34: 1903.44 | AT34: 1903.44 | AU34: 1903.44 | AV34: 1903.44 | AW34: 1903.44 | AX34: 1903.44 | AY34: 1903.44 | AZ34: 1903.44 | BA34: 1903.44 | BB34: 1903.44 | BC34: 1960.5432 | BD34: 1960.5432 | BE34: 1960.5432 | BF34: 1960.5432 | BG34: 1960.5432 | BH34: 1960.5432 | BI34: 1960.5432 | BJ34: 1960.5432 | BK34: 1960.5432 | BL34: 1960.5432 | BM34: 1960.5432 | BN34: 1960.5432 | BO34: 2019.3595 | BP34: 2019.3595 | BQ34: 2019.3595 | BR34: 2019.3595 | BS34: 2019.3595 | BT34: 2019.3595 | BU34: 2019.3595 | BV34: 2019.3595 | BW34: 2019.3595 | BX34: 2019.3595 | BY34: 2019.3595 | BZ34: 2019.3595 | CA34: 2079.9403 | CB34: 2079.9403 | CC34: 2079.9403 | CD34: 2079.9403 | CE34: 2079.9403 | CF34: 2079.9403 | CG34: 2079.9403 | CH34: 2079.9403 | CI34: 2079.9403 | CJ34: 2079.9403 | CK34: 2079.9403 | CL34: 2079.9403 | CM34: 2142.3385 | CN34: 2142.3385 | CO34: 2142.3385 | CP34: 2142.3385 | CQ34: 2142.3385 | CR34: 2142.3385 | CS34: 2142.3385 | CT34: 2142.3385 | CU34: 2142.3385 | CV34: 2142.3385 | CW34: 2142.3385 | CX34: 2142.3385 | CY34: 2206.6086 | CZ34: 2206.6086 | DA34: 2206.6086 | DB34: 2206.6086 | DC34: 2206.6086 | DD34: 2206.6086 | DE34: 2206.6086 | DF34: 2206.6086 | DG34: 2206.6086 | DH34: 2206.6086 | DI34: 2206.6086 | DJ34: 2206.6086 | DK34: 2272.8069 | DL34: 2272.8069 | DM34: 2272.8069 | DN34: 2272.8069 | DO34: 2272.8069 | DP34: 2272.8069 | DQ34: 2272.8069 | DR34: 2272.8069 | DS34: 2272.8069 | DT34: 2272.8069 | DU34: 2272.8069 | DV34: 2272.8069 | DW34: 2340.9911 | DX34: 2340.9911 | DY34: 2340.9911 | DZ34: 2340.9911 | EA34: 2340.9911 | EB34: 2340.9911 | EC34: 2340.9911 | ED34: 2340.9911 | EE34: 2340.9911 | EF34: 2340.9911 | EG34: 2340.9911 | EH34: 2340.9911 | EI34: 2411.2208 | EJ34: 2411.2208 | EK34: 2411.2208 | EL34: 2411.2208 | EM34: 2411.2208 | EN34: 2411.2208 | EO34: 2411.2208 | EP34: 2411.2208 | EQ34: 2411.2208 | ER34: 2411.2208 | ES34: 2411.2208 | ET34: 2411.2208 | EU34: 2483.5575 | EV34: 2483.5575 | EW34: 2483.5575 | EX34: 2483.5575 | EY34: 2483.5575 | EZ34: 2483.5575 | FA34: 2483.5575 | FB34: 2483.5575 | FC34: 2483.5575 | FD34: 2483.5575 | FE34: 2483.5575 | FF34: 2483.5575
B35: Ground Rent | C35: ='Old OSAR'!K45 -> 0 | D35: =SUMIFS($AH:$AH,$M:$M,$B35)*12 -> 0 | E35: =C35-D35 -> 0 | F35: 0 | H35: ='2025 Budget'!U38 -> 0 | I35: =H35-C35 -> 0 | J35: 1 | M35: Other Income | O35: Damages/Term Fee/MTM | P35: 56811.7 | Q35: 62832 | R35: 64716.96 | S35: 66658.469 | T35: 68658.223 | U35: 70717.97 | V35: 72839.509 | W35: 75024.694 | X35: 77275.435 | Y35: 79593.698 | Z35: 81981.509 | AA35: 84440.954 | AC35: Damages/Term Fee/MTM | AD35: 56811.7 | AE35: 5236 | AF35: 5236 | AG35: 5236 | AH35: 5236 | AI35: 5236 | AJ35: 5236 | AK35: 5236 | AL35: 5236 | AM35: 5236 | AN35: 5236 | AO35: 5236 | AP35: 5236 | AQ35: 5393.08 | AR35: 5393.08 | AS35: 5393.08 | AT35: 5393.08 | AU35: 5393.08 | AV35: 5393.08 | AW35: 5393.08 | AX35: 5393.08 | AY35: 5393.08 | AZ35: 5393.08 | BA35: 5393.08 | BB35: 5393.08 | BC35: 5554.8724 | BD35: 5554.8724 | BE35: 5554.8724 | BF35: 5554.8724 | BG35: 5554.8724 | BH35: 5554.8724 | BI35: 5554.8724 | BJ35: 5554.8724 | BK35: 5554.8724 | BL35: 5554.8724 | BM35: 5554.8724 | BN35: 5554.8724 | BO35: 5721.5186 | BP35: 5721.5186 | BQ35: 5721.5186 | BR35: 5721.5186 | BS35: 5721.5186 | BT35: 5721.5186 | BU35: 5721.5186 | BV35: 5721.5186 | BW35: 5721.5186 | BX35: 5721.5186 | BY35: 5721.5186 | BZ35: 5721.5186 | CA35: 5893.1641 | CB35: 5893.1641 | CC35: 5893.1641 | CD35: 5893.1641 | CE35: 5893.1641 | CF35: 5893.1641 | CG35: 5893.1641 | CH35: 5893.1641 | CI35: 5893.1641 | CJ35: 5893.1641 | CK35: 5893.1641 | CL35: 5893.1641 | CM35: 6069.9591 | CN35: 6069.9591 | CO35: 6069.9591 | CP35: 6069.9591 | CQ35: 6069.9591 | CR35: 6069.9591 | CS35: 6069.9591 | CT35: 6069.9591 | CU35: 6069.9591 | CV35: 6069.9591 | CW35: 6069.9591 | CX35: 6069.9591 | CY35: 6252.0578 | CZ35: 6252.0578 | DA35: 6252.0578 | DB35: 6252.0578 | DC35: 6252.0578 | DD35: 6252.0578 | DE35: 6252.0578 | DF35: 6252.0578 | DG35: 6252.0578 | DH35: 6252.0578 | DI35: 6252.0578 | DJ35: 6252.0578 | DK35: 6439.6196 | DL35: 6439.6196 | DM35: 6439.6196 | DN35: 6439.6196 | DO35: 6439.6196 | DP35: 6439.6196 | DQ35: 6439.6196 | DR35: 6439.6196 | DS35: 6439.6196 | DT35: 6439.6196 | DU35: 6439.6196 | DV35: 6439.6196 | DW35: 6632.8081 | DX35: 6632.8081 | DY35: 6632.8081 | DZ35: 6632.8081 | EA35: 6632.8081 | EB35: 6632.8081 | EC35: 6632.8081 | ED35: 6632.8081 | EE35: 6632.8081 | EF35: 6632.8081 | EG35: 6632.8081 | EH35: 6632.8081 | EI35: 6831.7924 | EJ35: 6831.7924 | EK35: 6831.7924 | EL35: 6831.7924 | EM35: 6831.7924 | EN35: 6831.7924 | EO35: 6831.7924 | EP35: 6831.7924 | EQ35: 6831.7924 | ER35: 6831.7924 | ES35: 6831.7924 | ET35: 6831.7924 | EU35: 7036.7462 | EV35: 7036.7462 | EW35: 7036.7462 | EX35: 7036.7462 | EY35: 7036.7462 | EZ35: 7036.7462 | FA35: 7036.7462 | FB35: 7036.7462 | FC35: 7036.7462 | FD35: 7036.7462 | FE35: 7036.7462 | FF35: 7036.7462
B36: *Total Operating Expenses | C36: ='Old OSAR'!K46 -> 0 | D36: =SUM(D25:D35) -> 3645762.7 | E36: =C36-D36 -> -3645762.7 | F36: =(C36-D36)/D36 -> -1 | H36: ='2025 Budget'!U39 -> 2106378.1 | I36: =H36-C36 -> 2106378.1 | J36: =H36/C36-1 -> #DIV/0! | M36: Other Income | O36: Pet Fees | P36: 19999 | Q36: 33264 | R36: 34261.92 | S36: 35289.778 | T36: 36348.471 | U36: 37438.925 | V36: 38562.093 | W36: 39718.956 | X36: 40910.524 | Y36: 42137.84 | Z36: 43401.975 | AA36: 44704.034 | AC36: Pet Fees | AD36: 19999 | AE36: 2772 | AF36: 2772 | AG36: 2772 | AH36: 2772 | AI36: 2772 | AJ36: 2772 | AK36: 2772 | AL36: 2772 | AM36: 2772 | AN36: 2772 | AO36: 2772 | AP36: 2772 | AQ36: 2855.16 | AR36: 2855.16 | AS36: 2855.16 | AT36: 2855.16 | AU36: 2855.16 | AV36: 2855.16 | AW36: 2855.16 | AX36: 2855.16 | AY36: 2855.16 | AZ36: 2855.16 | BA36: 2855.16 | BB36: 2855.16 | BC36: 2940.8148 | BD36: 2940.8148 | BE36: 2940.8148 | BF36: 2940.8148 | BG36: 2940.8148 | BH36: 2940.8148 | BI36: 2940.8148 | BJ36: 2940.8148 | BK36: 2940.8148 | BL36: 2940.8148 | BM36: 2940.8148 | BN36: 2940.8148 | BO36: 3029.0392 | BP36: 3029.0392 | BQ36: 3029.0392 | BR36: 3029.0392 | BS36: 3029.0392 | BT36: 3029.0392 | BU36: 3029.0392 | BV36: 3029.0392 | BW36: 3029.0392 | BX36: 3029.0392 | BY36: 3029.0392 | BZ36: 3029.0392 | CA36: 3119.9104 | CB36: 3119.9104 | CC36: 3119.9104 | CD36: 3119.9104 | CE36: 3119.9104 | CF36: 3119.9104 | CG36: 3119.9104 | CH36: 3119.9104 | CI36: 3119.9104 | CJ36: 3119.9104 | CK36: 3119.9104 | CL36: 3119.9104 | CM36: 3213.5077 | CN36: 3213.5077 | CO36: 3213.5077 | CP36: 3213.5077 | CQ36: 3213.5077 | CR36: 3213.5077 | CS36: 3213.5077 | CT36: 3213.5077 | CU36: 3213.5077 | CV36: 3213.5077 | CW36: 3213.5077 | CX36: 3213.5077 | CY36: 3309.913 | CZ36: 3309.913 | DA36: 3309.913 | DB36: 3309.913 | DC36: 3309.913 | DD36: 3309.913 | DE36: 3309.913 | DF36: 3309.913 | DG36: 3309.913 | DH36: 3309.913 | DI36: 3309.913 | DJ36: 3309.913 | DK36: 3409.2104 | DL36: 3409.2104 | DM36: 3409.2104 | DN36: 3409.2104 | DO36: 3409.2104 | DP36: 3409.2104 | DQ36: 3409.2104 | DR36: 3409.2104 | DS36: 3409.2104 | DT36: 3409.2104 | DU36: 3409.2104 | DV36: 3409.2104 | DW36: 3511.4867 | DX36: 3511.4867 | DY36: 3511.4867 | DZ36: 3511.4867 | EA36: 3511.4867 | EB36: 3511.4867 | EC36: 3511.4867 | ED36: 3511.4867 | EE36: 3511.4867 | EF36: 3511.4867 | EG36: 3511.4867 | EH36: 3511.4867 | EI36: 3616.8313 | EJ36: 3616.8313 | EK36: 3616.8313 | EL36: 3616.8313 | EM36: 3616.8313 | EN36: 3616.8313 | EO36: 3616.8313 | EP36: 3616.8313 | EQ36: 3616.8313 | ER36: 3616.8313 | ES36: 3616.8313 | ET36: 3616.8313 | EU36: 3725.3362 | EV36: 3725.3362 | EW36: 3725.3362 | EX36: 3725.3362 | EY36: 3725.3362 | EZ36: 3725.3362 | FA36: 3725.3362 | FB36: 3725.3362 | FC36: 3725.3362 | FD36: 3725.3362 | FE36: 3725.3362 | FF36: 3725.3362
M37: Other Income | O37: Other Fees | P37: 94629.72 | Q37: 92400 | R37: 95172 | S37: 98027.16 | T37: 100967.97 | U37: 103997.01 | V37: 107116.92 | W37: 110330.43 | X37: 113640.35 | Y37: 117049.56 | Z37: 120561.04 | AA37: 124177.87 | AC37: Other Fees | AD37: 94629.72 | AE37: 7700 | AF37: 7700 | AG37: 7700 | AH37: 7700 | AI37: 7700 | AJ37: 7700 | AK37: 7700 | AL37: 7700 | AM37: 7700 | AN37: 7700 | AO37: 7700 | AP37: 7700 | AQ37: 7931 | AR37: 7931 | AS37: 7931 | AT37: 7931 | AU37: 7931 | AV37: 7931 | AW37: 7931 | AX37: 7931 | AY37: 7931 | AZ37: 7931 | BA37: 7931 | BB37: 7931 | BC37: 8168.93 | BD37: 8168.93 | BE37: 8168.93 | BF37: 8168.93 | BG37: 8168.93 | BH37: 8168.93 | BI37: 8168.93 | BJ37: 8168.93 | BK37: 8168.93 | BL37: 8168.93 | BM37: 8168.93 | BN37: 8168.93 | BO37: 8413.9979 | BP37: 8413.9979 | BQ37: 8413.9979 | BR37: 8413.9979 | BS37: 8413.9979 | BT37: 8413.9979 | BU37: 8413.9979 | BV37: 8413.9979 | BW37: 8413.9979 | BX37: 8413.9979 | BY37: 8413.9979 | BZ37: 8413.9979 | CA37: 8666.4178 | CB37: 8666.4178 | CC37: 8666.4178 | CD37: 8666.4178 | CE37: 8666.4178 | CF37: 8666.4178 | CG37: 8666.4178 | CH37: 8666.4178 | CI37: 8666.4178 | CJ37: 8666.4178 | CK37: 8666.4178 | CL37: 8666.4178 | CM37: 8926.4104 | CN37: 8926.4104 | CO37: 8926.4104 | CP37: 8926.4104 | CQ37: 8926.4104 | CR37: 8926.4104 | CS37: 8926.4104 | CT37: 8926.4104 | CU37: 8926.4104 | CV37: 8926.4104 | CW37: 8926.4104 | CX37: 8926.4104 | CY37: 9194.2027 | CZ37: 9194.2027 | DA37: 9194.2027 | DB37: 9194.2027 | DC37: 9194.2027 | DD37: 9194.2027 | DE37: 9194.2027 | DF37: 9194.2027 | DG37: 9194.2027 | DH37: 9194.2027 | DI37: 9194.2027 | DJ37: 9194.2027 | DK37: 9470.0288 | DL37: 9470.0288 | DM37: 9470.0288 | DN37: 9470.0288 | DO37: 9470.0288 | DP37: 9470.0288 | DQ37: 9470.0288 | DR37: 9470.0288 | DS37: 9470.0288 | DT37: 9470.0288 | DU37: 9470.0288 | DV37: 9470.0288 | DW37: 9754.1296 | DX37: 9754.1296 | DY37: 9754.1296 | DZ37: 9754.1296 | EA37: 9754.1296 | EB37: 9754.1296 | EC37: 9754.1296 | ED37: 9754.1296 | EE37: 9754.1296 | EF37: 9754.1296 | EG37: 9754.1296 | EH37: 9754.1296 | EI37: 10046.754 | EJ37: 10046.754 | EK37: 10046.754 | EL37: 10046.754 | EM37: 10046.754 | EN37: 10046.754 | EO37: 10046.754 | EP37: 10046.754 | EQ37: 10046.754 | ER37: 10046.754 | ES37: 10046.754 | ET37: 10046.754 | EU37: 10348.156 | EV37: 10348.156 | EW37: 10348.156 | EX37: 10348.156 | EY37: 10348.156 | EZ37: 10348.156 | FA37: 10348.156 | FB37: 10348.156 | FC37: 10348.156 | FD37: 10348.156 | FE37: 10348.156 | FF37: 10348.156
