Workbook
Name \a: #N/A
Name \d: #N/A
Name _Order1: 255
Name _Order2: 0
Name ActEconInputs: #REF!
Name ActEconInputs: #REF!
Name Amortized: [1]!PMT
Name AmortToggle: #REF!
Name AmortToggle: #REF!
Name AptCleanContractPerTurn: #REF!
Name AptCleanContractPerTurn: #REF!
Name AptCleanInHousePerTurn: #REF!
Name AptCleanInHousePerTurn: #REF!
Name asdfasdf: #REF!
Name AvgEconRent: #REF!
Name AvgInPlaceRent: #REF!
Name AvgSF: #REF!
Name AvgStreetRent: #REF!
Name BackendMgtFee: #REF!
Name BaseRehabInputs: #REF!
Name Benchmark: #REF!
Name BKL_35: #REF!
Name Budget: #REF!
Name BUDTITLE: [2]DETAIL!#REF!
Name BURLINMM: #REF!
Name BURLINMM: #REF!
Name CapExContingPct: #REF!
Name CapExContingPct: #REF!
Name Capped: ' OSAR'!#REF!
Name CENDAV: [3]CAUSCAN!#REF!
Name CENDAV: [3]CAUSCAN!#REF!
Name CENDAV: [3]CAUSCAN!#REF!
Name City: [4]Input!$B$4
Name CITYSQMM: #REF!
Name CITYSQMM: #REF!
Name CITYSQMM: #REF!
Name ClientName: #REF!
Name ClientName: #REF!
Name ClosingAssump: #REF!
Name ClosingAssump: #REF!
Name ClosingComm: #REF!
Name ClosingCommRate: #REF!
Name CMNOTES: #REF!
Name COE: #REF!
Name colleen: [2]RENT!#REF!
Name CoveredbyInsurance: #REF!
Name CoveredbyInsurance: #REF!
Name CoveredbyInsurance: #REF!
Name cpirent: [2]RENT!#REF!
Name cpirent: [2]RENT!#REF!
Name cpirent: [2]RENT!#REF!
Name cpirent2: [2]RENT!#REF!
Name cpirent2: [2]RENT!#REF!
Name CreditCkFeePerTurn: #REF!
Name CreditCkFeePerTurn: #REF!
Name CreditCkFeePerTurn: #REF!
Name CreditCkFeePerTurnYr2: #REF!
Name CreditCkFeePerTurnYr2: #REF!
Name CreditCkFeePerTurnYr3: #REF!
Name CreditCkFeePerTurnYr3: #REF!

Sheet MF OSAR
B1: CREFC Investor Reporting Package
C2: MULTIFAMILY OPERATING STATEMENT ANALYSIS REPORT (includes Mobile Home Parks, Single Family Rentals, and Co-ops)
C3: ="as of" &TEXT(F6," MM/DD/YY") -> as of 03/31/26
C4: PROPERTY OVERVIEW | H4: Allocated Loan Amount/Percentage
C5: Property ID | E5: 1001-001 | F5: Paid Thru Date | G5: Debt Outside Trust (1) | H5: $ | I5: %
C6: Note A-Scheduled Loan Balance | E6: 280000000 | F6: 46112 | H6: 0 | I6: 1
C7: Note B-Scheduled Loan Balance
C8: Note C-Scheduled Loan Balance
C9: Property Name | E9: Quincy & Hollingsworth
C10: Property Type | E10: Mixed-Use (Multi-family) | M10: Commcercial Vacancy
C11: Property Address, City, State | E11: 70 W. 37th St. | M11: =1-(SUM('Rent Roll (COMM)'!F9:F16)/'Rent Roll (COMM)'!F18) -> 0.10014965
C12: Current Net Rentable SF/Units/Beds/Rooms | E12: 455 | G12: Use second box to specify sqft.,units…
C13: Year Built/Year Renovated | E13: 1986 | F13: 2021 | M13: Vacancy Factor
C14: Cap Ex Reserve (annually)/per Unit.etc. (2) | E14: 250 | F14: per unit | G14: specify annual/per unit… | M14: Commercial | N14: 0.1
C15: Statement Ending Date | E15: Underwriting | G15: 46022 | H15: =+$F$6 -> 46112 | I15: =+$F$6 -> 46112 | M15: Residential | N15: 0.03
C16: Occupancy Rate (physical) | E16: 0.93 | G16: 0.90549451 | H16: ='Rent Roll (MF)'!K536 -> 0.96043956 | I16: =+H16 -> 0.96043956
C17: Occupancy Date | E17: 45930 | G17: 46022 | H17: =+H15 -> 46112 | I17: =+I15 -> 46112
E18: (1) "X" if debt is outside of the trust, otherwise leave blank
E19: (2) Total $ amount of Capital Reserves required annually by loan documents
C20: INCOME:
C21: Number of Mos. Covered | J21: (prcdng yr to base) | K21: (prcdng yr to 2nd prcdng)
C22: Period Ended | E22: At Contribution | F22: 3rd Preceding | G22: DY Test | H22: TTM | I22: DY Test | J22: =TEXT(H15," mm/dd/yyyy")& "-U/W" -> 03/31/2026-U/W | K22: =TEXT(G15," mm/dd/yyyy - ") & TEXT(H15,"mm/dd/yyyy") -> 12/31/2025 - 03/31/2026 | M22: QoQ Variance | N22: QoQ Variance
C23: Statement Ending Date | E23: Information | G23: 46022 | H23: =+H15 -> 46112 | I23: =+I15 -> 46112 | J23: Variance | K23: Variance | L23: Notes | M23: $ | N23: %
C24: Gross Potential Rent (3) | E24: 28640482 | G24: 24755526 | H24: =+_xlfn.XLOOKUP(C24,'T12'!U:U,'T12'!V:V,"") -> 25677021 | I24: ='Rent Roll (MF)'!C531 -> 27270606 | J24: =IF(E24=0, " ",(H24-E24)/E24) -> -0.10347103 | K24: =IF(G24=0, " ",(H24-G24)/G24) -> 0.037223823 | L24: ="Annualized RR as of" &TEXT($I$15," mm/dd/yyy") & " less delinquent tenants & KV's" -> Annualized RR as of 03/31/2026 less delinquent tenants & KV's | M24: =+IFERROR(I24-G24,"") -> 2515080 | N24: =+IFERROR(M24/G24,"") -> 0.10159671
C25: Less: Vacancy Loss | E25: -1674366.6 | H25: =+_xlfn.XLOOKUP(C25,'T12'!U:U,'T12'!V:V,"") -> 0 | I25: =IF((1-N16)>'MF OSAR'!N15,"",-('MF OSAR'!N15-'MF OSAR'!M11)*O23) | J25: =IF(E25=0, " ",(H25-E25)/E25) -> -1 | K25: =IF(G25=0, " ",(H25-G25)/G25) -> #VALUE! | L25: Greater of actual & 3% vacancy factor | M25: =+IFERROR(I25-G25,"") | N25: =+IFERROR(M25/G25,"")
C26: OR | H26: =+_xlfn.XLOOKUP(C26,'T12'!U:U,'T12'!V:V,"") | M26: =+IFERROR(I26-G26,"") -> 0 | N26: =+IFERROR(M26/G26,"")
C27: Base Rent (3) | E27: 2816135.1 | G27: 2747575.1 | H27: =+_xlfn.XLOOKUP(C27,'T12'!U:U,'T12'!V:V,"") -> 2671554.2 | I27: ='Rent Roll (COMM)'!K18 -> 2774713.4 | J27: =IF(E27=0, " ",(H27-E27)/E27) -> -0.051340183 | K27: =IF(G27=0, " ",(H27-G27)/G27) -> -0.02766835 | L27: ="Annualized Commercial RR adjusted for greater of actual "&TEXT(1-'Rent Roll (COMM)'!O22,"0.00%")&" or 10.00% vacancy factor" -> Annualized Commercial RR adjusted for greater of actual 10.01% or 10.00% vacancy factor | M27: =+IFERROR(I27-G27,"") -> 27138.36 | N27: =+IFERROR(M27/G27,"") -> 0.0098772042
C28: Laundry/Vending Income | H28: =+_xlfn.XLOOKUP(C28,'T12'!U:U,'T12'!V:V,"") -> 0 | J28: =IF(E28=0, " ",(H28-E28)/E28) | K28: =IF(G28=0, " ",(H28-G28)/G28) | L28: =IF(G28=0, " ",(J28-G28)/G28) | M28: =+IFERROR(I28-G28,"") -> 0 | N28: =+IFERROR(M28/G28,"")
C29: Parking Income | G29: 600000 | H29: =+_xlfn.XLOOKUP(C29,'T12'!U:U,'T12'!V:V,"") -> 853260.5 | I29: ='Rent Roll (COMM)'!K24 -> 600000 | J29: =IF(E29=0, " ",(H29-E29)/E29) | K29: =IF(G29=0, " ",(H29-G29)/G29) -> 0.42210083 | L29: Annualized RR less delinquent tenants & KV's | M29: =+IFERROR(I29-G29,"") -> 0 | N29: =+IFERROR(M29/G29,"") -> 0
C30: Other Income | E30: -630195.19 | G30: -322324.28 | H30: =+_xlfn.XLOOKUP(C30,'T12'!U:U,'T12'!V:V,"") -> -748852.72 | I30: ='T12'!V35 -> -230307.58 | J30: =IF(E30=0, " ",(H30-E30)/E30) -> 0.18828695 | K30: =IF(G30=0, " ",(H30-G30)/G30) -> 1.3232898 | L30: ="T6 Other Income Less T6 Concessions " &TEXT($I$15,"mm/dd/yyyy") -> T6 Other Income Less T6 Concessions 03/31/2026 | M30: =+IFERROR(I30-G30,"") -> 92016.7 | N30: =+IFERROR(M30/G30,"") -> -0.28547865
C32: *Effective Gross Income | E32: =SUM(E23:E30) -> 29152055 | G32: 27780777 | H32: =+SUM(H24:H30) -> 28452983 | I32: =+SUM(I24:I30) -> 30415012 | J32: =IF(E32=0, " ",(H32-E32)/E32) -> -0.023980181 | K32: =IF(G32=0, " ",(H32-G32)/G32) -> 0.024196822 | M32: =+IFERROR(I32-G32,"") -> 2634235.1 | N32: =+IFERROR(M32/G32,"") -> 0.094822225
E33: (3) Use either Gross Potential (with Vacancy Loss) or Base Rents; use negative $amt for Vacancy Loss
C35: OPERATING EXPENSES: | J35: =IF(E35=0, " ",(H35-E35)/E35) | L35: =IF(G35=0, " ",(J35-G35)/G35)
C36: Real Estate Taxes | E36: 7092817.1 | G36: 6749271.6 | H36: =+_xlfn.XLOOKUP(C36,'T12'!U:U,'T12'!V:V,"") -> 6802665.6 | I36: =+MAX(H36,'RE Tax'!K1) -> 6802665.6 | J36: =IF(E36=0, " ",(H36-E36)/E36) -> -0.040907792 | K36: =IF(G36=0, " ",(H36-G36)/G36) -> 0.0079110833 | L36: ="Greater of actual tax bill from " & TEXT('RE Tax'!$J$3,"mm/d/yyyy") & "-" & TEXT('RE Tax'!$J$4,"mm/d/yyyy") & " (" & TEXT('RE Tax'!$K$1/1000000,"$0.0""MM""") & ") and TTM ended " & TEXT($I$15,"mm/d/yyyy") -> Greater of actual tax bill from 07/1/2025-06/30/2026 ($3.4MM) and TTM ended 03/31/2026 | M36: =+IFERROR(I36-G36,"") -> 53394.05 | N36: =+IFERROR(M36/G36,"") -> 0.0079110833
C37: Property Insurance | E37: 662281.56 | G37: 649173.44 | H37: =+_xlfn.XLOOKUP(C37,'T12'!U:U,'T12'!V:V,"") -> 651481 | I37: =+MAX(H37,Insurance!I1) -> 651481 | J37: =IF(E37=0, " ",(H37-E37)/E37) -> -0.016308114 | K37: =IF(G37=0, " ",(H37-G37)/G37) -> 0.0035546125 | L37: ="Greater of actual insurance premium from " & TEXT(Insurance!$I$4,"mm/d/yyyy") & "-" & TEXT(Insurance!$I$5,"mm/d/yyyy") & " (" & TEXT(Insurance!$I$1/1000,"$00.0""K""") & ") and TTM ended " & TEXT($I$15,"mm/d/yyyy") -> Greater of actual insurance premium from 09/30/2025-09/30/2026 ($605.1K) and TTM ended 03/31/2026 | M37: =+IFERROR(I37-G37,"") -> 2307.56 | N37: =+IFERROR(M37/G37,"") -> 0.0035546125
C38: Utilities | E38: 1133802.4 | G38: 1016154.2 | H38: =+_xlfn.XLOOKUP(C38,'T12'!U:U,'T12'!V:V,"") -> 1344132.8 | I38: =+H38 -> 1344132.8 | J38: =IF(E38=0, " ",(H38-E38)/E38) -> 0.18550889 | K38: =IF(G38=0, " ",(H38-G38)/G38) -> 0.32276452 | L38: =$H$22& " ended as of" &TEXT($I$15," mm/dd/yyyy") -> TTM ended as of 03/31/2026 | M38: =+IFERROR(I38-G38,"") -> 327978.54 | N38: =+IFERROR(M38/G38,"") -> 0.32276452
C39: Repairs and Maintenance | E39: 658885.75 | G39: 695520.41 | H39: =+_xlfn.XLOOKUP(C39,'T12'!U:U,'T12'!V:V,"") -> 781368.51 | I39: =+H39 -> 781368.51 | J39: =IF(E39=0, " ",(H39-E39)/E39) -> 0.18589378 | K39: =IF(G39=0, " ",(H39-G39)/G39) -> 0.12343002 | L39: =$H$22& " ended as of" &TEXT($I$15," mm/dd/yyyy") -> TTM ended as of 03/31/2026 | M39: =+IFERROR(I39-G39,"") -> 85848.1 | N39: =+IFERROR(M39/G39,"") -> 0.12343002
C40: Management Fees | E40: 728801.37 | G40: 694519.42 | H40: =+_xlfn.XLOOKUP(C40,'T12'!U:U,'T12'!V:V,"") -> 385416.19 | I40: =+MAX(H40,0.025*I32) -> 760375.3 | J40: =IF(E40=0, " ",(H40-E40)/E40) -> -0.47116429 | K40: =IF(G40=0, " ",(H40-G40)/G40) -> -0.4450606 | L40: Greater of actual or 2.50% of EGI | M40: =+IFERROR(I40-G40,"") -> 65855.877 | N40: =+IFERROR(M40/G40,"") -> 0.094822225
C41: Payroll & Benefits | E41: 628788.67 | G41: 294391.6 | H41: =+_xlfn.XLOOKUP(C41,'T12'!U:U,'T12'!V:V,"") -> 321346.34 | I41: =+H41 -> 321346.34 | J41: =IF(E41=0, " ",(H41-E41)/E41) -> -0.48894382 | K41: =IF(G41=0, " ",(H41-G41)/G41) -> 0.091560833 | L41: =$H$22& " ended as of" &TEXT($I$15," mm/dd/yyyy") -> TTM ended as of 03/31/2026 | M41: =+IFERROR(I41-G41,"") -> 26954.74 | N41: =+IFERROR(M41/G41,"") -> 0.091560833
C42: Advertising & Marketing | E42: 105422.37 | G42: 115325.44 | H42: =+_xlfn.XLOOKUP(C42,'T12'!U:U,'T12'!V:V,"") -> 112073.59 | I42: =+H42 -> 112073.59 | J42: =IF(E42=0, " ",(H42-E42)/E42) -> 0.063091182 | K42: =IF(G42=0, " ",(H42-G42)/G42) -> -0.028197161 | L42: =$H$22& " ended as of" &TEXT($I$15," mm/dd/yyyy") -> TTM ended as of 03/31/2026 | M42: =+IFERROR(I42-G42,"") -> -3251.85 | N42: =+IFERROR(M42/G42,"") -> -0.028197161
C43: Professional Fees | G43: 195156.35 | H43: =+_xlfn.XLOOKUP(C43,'T12'!U:U,'T12'!V:V,"") -> 171187.81 | I43: =+H43 -> 171187.81 | J43: =IF(E43=0, " ",(H43-E43)/E43) | K43: =IF(G43=0, " ",(H43-G43)/G43) -> -0.12281712 | L43: =$H$22& " ended as of" &TEXT($I$15," mm/dd/yyyy") -> TTM ended as of 03/31/2026 | M43: =+IFERROR(I43-G43,"") -> -23968.54 | N43: =+IFERROR(M43/G43,"") -> -0.12281712
C44: General and Administrative | E44: 988835.46 | G44: 2599132.7 | H44: =+_xlfn.XLOOKUP(C44,'T12'!U:U,'T12'!V:V,"") -> 2604757 | I44: =+H44 -> 2604757 | J44: =IF(E44=0, " ",(H44-E44)/E44) -> 1.6341662 | K44: =IF(G44=0, " ",(H44-G44)/G44) -> 0.0021639141 | L44: =$H$22& " ended as of" &TEXT($I$15," mm/dd/yyyy") -> TTM ended as of 03/31/2026 | M44: =+IFERROR(I44-G44,"") -> 5624.3 | N44: =+IFERROR(M44/G44,"") -> 0.0021639141
C45: Other Expenses | E45: 1057734 | G45: 0 | H45: =+_xlfn.XLOOKUP(C45,'T12'!U:U,'T12'!V:V,"") -> 0 | I45: =+H45 -> 0 | J45: =IF(E45=0, " ",(H45-E45)/E45) -> -1 | K45: =IF(G45=0, " ",(H45-G45)/G45) | L45: =$H$22& " ended as of" &TEXT($I$15," mm/dd/yyyy") -> TTM ended as of 03/31/2026 | M45: =+IFERROR(I45-G45,"") -> 0 | N45: =+IFERROR(M45/G45,"")
C46: Ground Rent | G46: 0 | H46: =+_xlfn.XLOOKUP(C46,'T12'!U:U,'T12'!V:V,"") -> 0 | I46: =+H46 -> 0 | J46: =IF(E46=0, " ",(H46-E46)/E46) | K46: =IF(G46=0, " ",(H46-G46)/G46) | L46: =$H$22& " ended as of" &TEXT($I$15," mm/dd/yyyy") -> TTM ended as of 03/31/2026 | M46: =+IFERROR(I46-G46,"") -> 0 | N46: =+IFERROR(M46/G46,"")
C47: *Total Operating Expenses | E47: 13057369 | G47: 13008645 | H47: =+SUM(H36:H46) -> 13174429 | I47: =+SUM(I36:I46) -> 13549388 | J47: =IF(E47=0, " ",(H47-E47)/E47) -> 0.0089650627 | K47: =IF(G47=0, " ",(H47-G47)/G47) -> 0.012744115 | M47: =+IFERROR(I47-G47,"") -> 540742.78 | N47: =+IFERROR(M47/G47,"") -> 0.041567955
C49: Operating Expense Ratio | E49: 0.4479056 | G49: 0.46826067 | H49: =+H47/H32 -> 0.46302452 | I49: =+I47/I32 -> 0.44548357 | J49: =IF(E49=0, " ",(H49-E49)/E49) -> 0.033754687 | K49: =IF(G49=0, " ",(H49-G49)/G49) -> -0.011182134
C51: *Net Operating Income | E51: 16094686 | G51: 14772132 | H51: =H32-H47 -> 15278554 | I51: =I32-I47 -> 16865624 | J51: =IF(E51=0, " ",(H51-E51)/E51) -> -0.050708145 | K51: =IF(G51=0, " ",(H51-G51)/G51) -> 0.034282312 | M51: =+IFERROR(I51-G51,"") -> 2093492.3 | N51: =+IFERROR(M51/G51,"") -> 0.14171904
C53: Capital Expenditures | E53: 113750 | G53: 113750 | H53: =+_xlfn.XLOOKUP(C53,'T12'!U:U,'T12'!V:V,"") | I53: =+L53*E12 -> 113750 | J53: =IF(E53=0, " ",(H53-E53)/E53) -> #VALUE! | K53: =IF(G53=0, " ",(H53-G53)/G53) -> #VALUE! | L53: =+E14 -> 250
C54: Extraordinary Capital Expenditures
C55: Total Capital Items | E55: 113750 | G55: 113750 | H55: =+SUM(H53:H54) -> 0 | I55: =+SUM(I53:I54) -> 113750 | J55: =IF(E55=0, " ",(H55-E55)/E55) -> -1 | K55: =IF(G55=0, " ",(H55-G55)/G55) -> -1
C57: *Net Cash Flow | E57: 15980936 | G57: 14658382 | H57: =+H51-H55 -> 15278554 | I57: =+I51-I55 -> 16751874 | J57: =IF(E57=0, " ",(H57-E57)/E57) -> -0.043951222 | K57: =IF(G57=0, " ",(H57-G57)/G57) -> 0.042308411 | L57: =IF(H57=0, " ",(I57-H57)/H57) -> 0.096430553
C59: Debt Service - A Note | G59: 16430098 | H59: =+I59 -> 16408778 | I59: =+'Debt Service'!L14 -> 16408778
C60: Debt Service - B Note
C61: Debt Service - C Note
C63: *Net Cash Flow after Debt Service | J63: =IF(E63=0, " ",(H63-E63)/E63) | K63: =IF(G63=0, " ",(H63-G63)/G63) | L63: =IF(H63=0, " ",(I63-H63)/H63)
C65: *DSCR: (NOI/Debt Service) - A Note | G65: 0.89908969 | H65: =+H51/H59 -> 0.93112081 | I65: =+I51/I59 -> 1.0278416 | K65: =IF(G65=0, " ",(H65-G65)/G65) -> 0.035626164 | L65: =IF(H65=0, " ",(I65-H65)/H65) -> 0.10387563
C66: *DSCR: (NOI/Debt Service) - A & B Note
C67: *DSCR: (NOI/Debt Service) - A, B & C Note
C69: *DSCR: (NCF/Debt Service) - A Note | G69: 0.89216642 | H69: =+H57/H59 -> 0.93112081 | I69: =+I57/I59 -> 1.0209093 | K69: =IF(G69=0, " ",(H69-G69)/G69) -> 0.04366269 | L69: =IF(H69=0, " ",(I69-H69)/H69) -> 0.096430553
C70: *DSCR: (NCF/Debt Service) - A & B Note
C71: *DSCR: (NCF/Debt Service) - A, B & C Note
C73: Debt Yield (NCF/UPB) | G73: 0.052351363 | H73: =+H57/E6 -> 0.054566266 | I73: =+I57/E6 -> 0.059828121
C75: Source of Financial Data:
E76: (ie. operating statements, financial statements, tax return, other)
C77: Notes and Assumptions: Years above will roll, always showing a 3yr sequential history. Comments from the most recent NOI Adjustment Worksheet should be carried forward to Operating Statement
C78: Analysis Report. Year-over-year variances (either higher or lower) must be explained and noted for the following: >20% DSCR change, >20% EGI/Total Operating Expenses or Total Capital
C79: Items. Quarterly variance comments may be necessary if the loan is on the Watch List.
C80: Income: Comments
C83: Expense: Comments
C86: Capital Items: Comments
C89: DSCR: Comments
C92: * Used in the CREFC Comparative Financial Status Report/CREFC Property File/CREFC Loan Periodic Update File. Note that information for multiple property loans must be consolidated (if available)
C93: for reporting to the CREFC Loan Periodic Update file.

Sheet Debt Service
K2: PREVIOUS | L2: CURRENT
K4: 46022 | L4: 46112
A5: UPB | K5: 280000000 | L5: =+'MF OSAR'!E6 -> 280000000 | M5: ="UPB as of" &TEXT('MF OSAR'!$F$6," mm/dd/yyy") -> UPB as of 03/31/2026
A7: SOFR | K7: 0.0368751 | L7: 0.0368 | M7: ="SOFR as of" &TEXT('MF OSAR'!$F$6," mm/dd/yyy") -> SOFR as of 03/31/2026
A8: Spread | K8: 0.021 | L8: 0.021
A9: Uncapped Interest Rate | K9: 0.0578751 | L9: =SUM(L7:L8) -> 0.0578 | M9: SOFR + Spread
A10: Rate Cap Strike Price | K10: 0.05 | L10: 0.05
A11: Effective Interest Rate | K11: 0.0578751 | L11: =MIN(L10,L7)+L8 -> 0.0578 | M11: MIN. of Rate Cap and SOFR + Spread
A13: Uncapped Debt Service | K13: 16430098 | L13: =L5*L9*(365/360) -> 16408778 | M13: Based on Act/360
A14: Capped Debt Service | K14: 16430098 | L14: =L5*L11*(365/360) -> 16408778 | M14: Based on Act/360
A16: DSCR (w/o Rate Cap) | K16: 0.89216642 | L16: =$L$19/L13 -> 1.0209093
A17: DSCR (with Rate Cap) | K17: 0.89216642 | L17: =$L$19/L14 -> 1.0209093
A19: NCF | K19: 14658382 | L19: =+'MF OSAR'!I57 -> 16751874
A20: Debt Yield (NCF/UPB) | K20: 0.052351363 | L20: =+L19/L5 -> 0.059828121

Sheet  OSAR
C1: CREFC Investor Reporting Package
B2: Print Switch | C2: 1 | D2: MULTIFAMILY OPERATING STATEMENT ANALYSIS REPORT (includes Mobile Home Parks, Single Family Rentals, and Co-ops)
D3: ="as of " &TEXT($G$6,"mm/dd/yyyy") -> as of 12/31/2025
D4: PROPERTY OVERVIEW | I4: Allocated Loan Amount/Percentage
D5: Property ID | F5: ="250231" -> 250231 | G5: Paid Thru Date | H5: Debt Outside Trust (1) | I5: $ | K5: %
D6: Note A-Scheduled Loan Balance | F6: 280000000 | G6: 46022 | I6: 0 | K6: =F6/SUM($F$6:$F$8) -> 1
D7: Note B-Scheduled Loan Balance
D8: Note C-Scheduled Loan Balance
D9: Property Name | F9: Quincy & Hollingsworth
D10: Property Type | F10: Mixed-Use (Multi-family)
D11: Property Address, City, State | F11: 70 W. 37th St.
D12: Current Net Rentable SF/Units/Beds/Rooms | F12: 455 | G12: Units | H12: Use second box to specify sqft.,units…
D13: Year Built/Year Renovated | F13: 1986 | G13: 2021
D14: Cap Ex Reserve (annually)/per Unit.etc. (2) | F14: 250 | G14: (Annual/ Per Unit) | H14: specify annual/per unit…
D15: Statement Ending Date | F15: Underwriting | N15: =G6 -> 46022
D16: Occupancy Rate (physical) | F16: 0.93 | N16: ='Rent Roll (MF)'!K536 -> 0.96043956
D17: Occupancy Date | F17: 45930 | N17: =G6 -> 46022
F18: (1) "X" if debt is outside of the trust, otherwise leave blank
F19: (2) Total $ amount of Capital Reserves required annually by loan documents
D20: INCOME:
D21: Number of Mos. Covered
D22: Period Ended | F22: At Contribution | N22: T12 | O22: DY Test | P22: Notes | R22: QoQ Variance | S22: QoQ Variance
D23: Statement Ending Date | F23: Information | N23: =N15 -> 46022 | O23: =N15 -> 46022 | R23: % | S23: $
D24: Gross Potential Rent (3) | F24: =UW!F9 -> 28640482 | N24: =SUMIF('T12'!$Q:$Q,$D24,'T12'!$O:$O) -> 25677021 | O24: ='Rent Roll (MF)'!C531 -> 27270606 | P24: ="Annualized RR as of" &TEXT(G6," mm/dd/yyy") & " less delinquent tenants & KV's" -> Annualized RR as of 12/31/2025 less delinquent tenants & KV's | R24: =IFERROR(S24/M24,"") | S24: =IFERROR(O24-M24,"") -> 27270606
D25: Less: Vacancy Loss | F25: =UW!F13 -> -1674366.6 | N25: =SUMIF('T12'!$Q:$Q,$D25,'T12'!$O:$O) -> 0 | O25: =IF((1-N16)>'MF OSAR'!N15,"",-('MF OSAR'!N15-'MF OSAR'!M11)*O23) | P25: Greater of actual & 3% vacancy factor | R25: =IFERROR(S25/M25,"") | S25: =IFERROR(O25-M25,"")
D26: OR | N26: =SUMIF('T12'!$Q:$Q,$D26,'T12'!$O:$O) -> 0 | R26: =IFERROR(S26/M26,"") | S26: =IFERROR(O26-M26,"") -> 0
D27: Commercial Income | F27: =UW!F10 -> 2816135.1 | N27: =SUMIF('T12'!$Q:$Q,$D27,'T12'!$O:$O) -> 0 | O27: ='Rent Roll (COMM)'!K18 -> 2774713.4 | P27: ="Annualized RR as of" &TEXT(G6," mm/dd/yyy") & " less delinquent tenants & KV's" -> Annualized RR as of 12/31/2025 less delinquent tenants & KV's | R27: =IFERROR(S27/M27,"") | S27: =IFERROR(O27-M27,"") -> 2774713.4
D28: Less: Vacancy Loss © | N28: =SUMIF('T12'!$Q:$Q,$D28,'T12'!$O:$O) -> 0 | O28: =IF('MF OSAR'!M11>'MF OSAR'!N14,"",-('MF OSAR'!N14-'MF OSAR'!M11)*O27) | P28: Greater of actual & 10% vacancy factor | S28: =IFERROR(O28-M28,"")
D29: Laundry/Vending Income | N29: =SUMIF('T12'!$Q:$Q,$D29,'T12'!$O:$O) -> 0 | O29: =N29 -> 0 | P29: =IF(G29=0, " ",(H29-G29)/G29) | R29: =IFERROR(S29/M29,"") | S29: =IFERROR(O29-M29,"") -> 0
D30: Parking Income | N30: =SUMIF('T12'!$Q:$Q,$D30,'T12'!$O:$O) -> 853260.5 | O30: ='Rent Roll (COMM)'!K24 -> 600000 | P30: Annualized RR less delinquent tenants & KV's | R30: =IFERROR(S30/M30,"") | S30: =IFERROR(O30-M30,"") -> 600000
D31: Other Income | F31: =UW!F11+SUM(UW!F14:F17) -> -630195.19 | N31: =SUMIF('T12'!$Q:$Q,$D31,'T12'!$O:$O) -> -748852.72 | O31: ='T12'!V35 -> -230307.58 | P31: ="T6 Other Income Less T6 Concessions " &TEXT($G$6,"mm/dd/yyyy") -> T6 Other Income Less T6 Concessions 12/31/2025 | R31: =IFERROR(S31/M31,"") | S31: =IFERROR(O31-M31,"") -> -230307.58
R32: =IFERROR(S32/M32,"") | S32: =IFERROR(O32-M32,"") -> 0
D33: *Effective Gross Income | F33: =SUM(F24:F31) -> 29152055 | G33: =SUM(G24:G31) -> 0 | H33: =SUM(H24:H31) -> 0 | I33: =SUM(I24:I31) -> 0 | J33: =SUM(J24:J31) -> 0 | K33: =SUM(K24:K31) -> 0 | L33: =SUM(L24:L31) -> 0 | M33: =SUM(M24:M31) -> 0 | ... O33: =SUM(O24:O31) -> 30415012 | R33: =IFERROR(S33/M33,"") | S33: =IFERROR(O33-M33,"") -> 30415012
F34: (3) Use either Gross Potential (with Vacancy Loss) or Base Rents; use negative $amt for Vacancy Loss
D36: OPERATING EXPENSES:
D37: Real Estate Taxes | F37: =UW!F36 -> 7092817.1 | N37: =SUMIF('T12'!$Q:$Q,$D37,'T12'!$O:$O) -> 6802665.6 | O37: =MAX(N37,'RE Tax'!K1) -> 6802665.6 | P37: ="Greater of Actual"& " or T12 ended " &TEXT($G$6,"mm/dd/yyyy") -> Greater of Actual or T12 ended 12/31/2025 | R37: =IFERROR(S37/M37,"") | S37: =IFERROR(O37-M37,"") -> 6802665.6
D38: Property Insurance | F38: =UW!F32 -> 662281.56 | N38: =SUMIF('T12'!$Q:$Q,$D38,'T12'!$O:$O) -> 651481 | O38: =MAX(N38,Insurance!I1) -> 651481 | P38: ="Greater of Actual"& " or T12 ended " &TEXT($G$6,"mm/dd/yyyy") -> Greater of Actual or T12 ended 12/31/2025 | R38: =IFERROR(S38/M38,"") | S38: =IFERROR(O38-M38,"") -> 651481
D39: Utilities | F39: =UW!F31 -> 1133802.4 | N39: =SUMIF('T12'!$Q:$Q,$D39,'T12'!$O:$O) -> 1344132.8 | O39: =N39 -> 1344132.8 | P39: ="T12"& " ended " &TEXT($G$6,"mm/dd/yyyy") -> T12 ended 12/31/2025 | R39: =IFERROR(S39/M39,"") | S39: =IFERROR(O39-M39,"") -> 1344132.8
D40: Repairs and Maintenance | F40: =UW!F28 -> 658885.75 | N40: =SUMIF('T12'!$Q:$Q,$D40,'T12'!$O:$O) -> 781368.51 | O40: =N40 -> 781368.51 | P40: ="T12"& " ended " &TEXT($G$6,"mm/dd/yyyy") -> T12 ended 12/31/2025 | R40: =IFERROR(S40/M40,"") | S40: =IFERROR(O40-M40,"") -> 781368.51
D41: Management Fees | F41: =UW!F37 -> 728801.37 | N41: =SUMIF('T12'!$Q:$Q,$D41,'T12'!$O:$O) -> 385416.19 | O41: =+MAX(N41,0.025*O33) -> 760375.3 | P41: 0.025 | R41: =IFERROR(S41/M41,"") | S41: =IFERROR(O41-M41,"") -> 760375.3
D42: Payroll & Benefits | F42: =UW!F21 -> 628788.67 | N42: =SUMIF('T12'!$Q:$Q,$D42,'T12'!$O:$O) -> 321346.34 | O42: =N42 -> 321346.34 | P42: ="T12"& " ended " &TEXT($G$6,"mm/dd/yyyy") -> T12 ended 12/31/2025 | R42: =IFERROR(S42/M42,"") | S42: =IFERROR(O42-M42,"") -> 321346.34
D43: Advertising & Marketing | F43: =UW!F23 -> 105422.37 | N43: =SUMIF('T12'!$Q:$Q,$D43,'T12'!$O:$O) -> 112073.59 | O43: =N43 -> 112073.59 | P43: ="T12"& " ended " &TEXT($G$6,"mm/dd/yyyy") -> T12 ended 12/31/2025 | R43: =IFERROR(S43/M43,"") | S43: =IFERROR(O43-M43,"") -> 112073.59
D44: Professional Fees | N44: =SUMIF('T12'!$Q:$Q,$D44,'T12'!$O:$O) -> 171187.81 | O44: =N44 -> 171187.81 | P44: ="T12"& " ended " &TEXT($G$6,"mm/dd/yyyy") -> T12 ended 12/31/2025 | R44: =IFERROR(S44/M44,"") | S44: =IFERROR(O44-M44,"") -> 171187.81
D45: General and Administrative | F45: =UW!F24+UW!F30 -> 988835.46 | N45: =SUMIF('T12'!$Q:$Q,$D45,'T12'!$O:$O) -> 2604757 | O45: =N45 -> 2604757 | P45: ="T12"& " ended " &TEXT($G$6,"mm/dd/yyyy") -> T12 ended 12/31/2025 | R45: =IFERROR(S45/M45,"") | S45: =IFERROR(O45-M45,"") -> 2604757
D46: Other Expenses | F46: =UW!F29 -> 1057734 | N46: =SUMIF('T12'!$Q:$Q,$D46,'T12'!$O:$O) -> 0 | O46: =N46 -> 0 | P46: ="T12"& " ended " &TEXT($G$6,"mm/dd/yyyy") -> T12 ended 12/31/2025 | R46: =IFERROR(S46/M46,"") | S46: =IFERROR(O46-M46,"") -> 0
D47: Ground Rent | N47: =SUMIF('T12'!$Q:$Q,$D47,'T12'!$O:$O) -> 0 | O47: =N47 -> 0 | P47: ="T12"& " ended " &TEXT($G$6,"mm/dd/yyyy") -> T12 ended 12/31/2025 | R47: =IFERROR(S47/M47,"") | S47: =IFERROR(O47-M47,"") -> 0
D48: *Total Operating Expenses | F48: =SUM(F37:F47) -> 13057369 | G48: =SUM(G37:G47) -> 0 | H48: =SUM(H37:H47) -> 0 | I48: =SUM(I37:I47) -> 0 | J48: =SUM(J37:J47) -> 0 | K48: =SUM(K37:K47) -> 0 | L48: =SUM(L37:L47) -> 0 | M48: =SUM(M37:M47) -> 0 | ... O48: =SUM(O37:O47) -> 13549388 | R48: =IFERROR(S48/M48,"") | S48: =IFERROR(O48-M48,"") -> 13549388
R49: =IFERROR(S49/M49,"")
D50: Operating Expense Ratio | F50: =F48/F33 -> 0.4479056 | R50: =IFERROR(S50/M50,"") | S50: =IFERROR(O50-M50,"") -> 0
R51: =IFERROR(S51/M51,"")
D52: *Net Operating Income | F52: =F33-F48 -> 16094686 | G52: =G33-G48 -> 0 | H52: =H33-H48 -> 0 | I52: =I33-I48 -> 0 | J52: =J33-J48 -> 0 | K52: =K33-K48 -> 0 | L52: =L33-L48 -> 0 | M52: =M33-M48 -> 0 | ... O52: =O33-O48 -> 16865624 | R52: =IFERROR(S52/M52,"") | S52: =IFERROR(O52-M52,"") -> 16865624
D54: Capital Expenditures | F54: =UW!F35 -> 113750 | O54: =F14*F12 -> 113750 | P54: $250 per unit
D55: Extraordinary Capital Expenditures
D56: Total Capital Items | F56: =F54 -> 113750 | G56: =G54 -> 0 | H56: =H54 -> 0 | I56: =I54 -> 0 | J56: =J54 -> 0 | K56: =K54 -> 0 | L56: =L54 -> 0 | M56: =M54 -> 0 | ... O56: =O54 -> 113750
D58: *Net Cash Flow | F58: =F52-F56 -> 15980936 | G58: =G52-G56 -> 0 | H58: =H52-H56 -> 0 | I58: =I52-I56 -> 0 | J58: =J52-J56 -> 0 | K58: =K52-K56 -> 0 | L58: =L52-L56 -> 0 | M58: =M52-M56 -> 0 | ... O58: =O52-O56 -> 16751874
D60: Debt Service - A Note | O60: =MIN('Debt Service'!L13:L14) -> 16408778
D61: Debt Service - B Note
D62: Debt Service - C Note
D64: *Net Cash Flow after Debt Service | F64: =F58-F60 -> 15980936 | G64: =G58-G60 -> 0 | H64: =H58-H60 -> 0 | I64: =I58-I60 -> 0 | J64: =J58-J60 -> 0 | K64: =K58-K60 -> 0 | L64: =L58-L60 -> 0 | M64: =M58-M60 -> 0 | ... O64: =O58-O60 -> 343096.14
D66: *DSCR: (NCF/Debt Service) | O66: ='Debt Service'!L17 -> 1.0209093
D67: *DSCR: (NOI/Debt Service) - A & B Note
D68: *DSCR: (NOI/Debt Service) - A, B & C Note
D70: *Debt Yield: (NOI/Debt Balance) | F70: =F58/F6 -> 0.057074772 | G70: =G58/G6 -> 0 | H70: =H58/H6 -> #DIV/0! | I70: =I58/I6 -> #DIV/0! | J70: =J58/J6 -> #DIV/0! | K70: =K58/K6 -> 0 | L70: =L58/L6 -> #DIV/0! | M70: =M58/M6 -> #DIV/0! | N70: =N58/$F$6 -> 0.045025001 | O70: =O58/$F$6 -> 0.059828121 | P70: 0.065
D72: Notes and Assumptions:

Sheet QoQ ∆
C2: 4Q25 | G2: 1Q26 | K2: QoQ ∆ | O2: Cash Management
B3: Property | C3: Occupancy | D3: NOI | E3: DY | F3: DSCR | G3: Occupancy | H3: NOI | I3: DY | J3: DSCR | K3: Occupancy | L3: NOI | M3: DY | N3: DSCR | O3: In CM? | P3: Threshold
B4: Quincy & Hollingsworth | C4: 0.90549451 | D4: 14772132 | E4: 0.052351363 | F4: 0.89216642 | G4: =+'MF OSAR'!I16 -> 0.96043956 | H4: =+'MF OSAR'!I51 -> 16865624 | I4: =+'MF OSAR'!I73 -> 0.059828121 | J4: =+'MF OSAR'!I69 -> 1.0209093 | K4: =G4-C4 -> 0.054945055 | L4: =H4-D4 -> 2093492.3 | M4: =I4-E4 -> 0.0074767582 | N4: =J4-F4 -> 0.12874288 | O4: No | P4: 0.065
B6: Notes:
B7: NOI adjusted per the loan agreement.
B8: DSCR inclusive of benefit from in-the-money rate cap.
B9: DY increased 70bps, driven by a 6% increase in occupancy

Sheet RR - Market & Affordable 4Q24
A1: Rent Roll with Lease Charges
A2: For Selected Properties
A3: As Of = 12/31/2024
A4: Month Year = 12/2024
A5: Unit | B5: Unit Type | C5: Unit | D5: Resident | E5: Name | F5: Market | G5: Charge | H5: Amount | I5: Resident | J5: Other | K5: Move In | L5: Lease | M5: Move Out | N5: Balance
C6: Sq Ft | F6: Rent | G6: Code | I6: Deposit | J6: Deposit | L6: Expiration
A7: Current/Notice/Vacant Residents
A8: 303 | B8: NY10CO3 | C8: 879 | D8: t0004256 | E8: Leila McDowell | F8: 3700 | G8: rent | H8: 3725 | I8: 3725 | J8: 0 | K8: 44188 | L8: 46013 | N8: 2400
G9: amenity | H9: 75
G10: gymspa | H10: -75
G11: Total | H11: 3725
A13: 304 | B13: NY10C47 | C13: 833 | D13: t0004257 | E13: Dwight Rhoden | F13: 3825 | G13: rent | H13: 3875 | I13: 3875 | J13: 0 | K13: 45145 | L13: 45874 | N13: 0
G14: amenity | H14: 75
G15: gas | H15: 20
G16: water | H16: 15
G17: Total | H17: 3985
A19: 309 | B19: NY10CO2 | C19: 862 | D19: t0004258 | E19: Lauren Sordo | F19: 3995 | G19: rent | H19: 3995 | I19: 3995 | J19: 0 | K19: 45579 | L19: 46125 | N19: 0
G20: amenity | H20: 100
G21: gas | H21: 20
G22: water | H22: 15
G23: Total | H23: 4130
A25: 310 | B25: NY10CO4 | C25: 879 | D25: t0004259 | E25: Rainee Walker | F25: 3907.75 | G25: rent | H25: 3953.75 | I25: 3953.75 | J25: 0 | K25: 44232 | L25: 45781 | N25: 596.42
G26: Total | H26: 3953.75
A28: 311 | B28: NY10C46 | C28: 828 | D28: t0004260 | E28: Alexander Demopoulos | F28: 3795 | G28: rent | H28: 3650 | I28: 3650 | J28: 0 | K28: 45342 | L28: 45747 | N28: -3650
G29: gas | H29: 20
G30: water | H30: 15
G31: Total | H31: 3685
A33: 403 | B33: NY10CO1 | C33: 837 | D33: t0004261 | E33: BRITTANY BROWN | F33: 4000 | G33: rent | H33: 4000 | I33: 4000 | J33: 0 | K33: 45372 | L33: 45767 | N33: -1600
G34: amenity | H34: 75
G35: gas | H35: 15
G36: water | H36: 10
G37: Total | H37: 4100
A39: 404 | B39: NY10C47 | C39: 818 | D39: t0004262 | E39: Tricia Newell | F39: 3600 | G39: rent | H39: 3750 | I39: 3750 | J39: 0 | K39: 45261 | L39: 46053 | N39: 0
G40: amenity | H40: 75
G41: Total | H41: 3825
A43: 405 | B43: NY10B17 | C43: 604 | D43: VACANT | E43: VACANT | F43: 3299 | H43: 0 | I43: 0 | J43: 0 | N43: 0
G44: Total | H44: 0
A46: 410 | B46: NY10C46 | C46: 817 | D46: t0004263 | E46: Laurence Smith | F46: 3656.5 | G46: rent | H46: 3850 | I46: 3850 | J46: 0 | K46: 45061 | L46: 45822 | N46: 0
G47: amenity | H47: 100
G48: Total | H48: 3950
A50: 501 | B50: NY10C42 | C50: 757 | D50: t0004264 | E50: Chesley Swann | F50: 3650 | G50: rent | H50: 3695 | I50: 3695 | J50: 0 | K50: 44823 | L50: 45948 | N50: 0
G51: conspec | H51: -284
G52: amenity | H52: 75
G53: gas | H53: 25
G54: water | H54: 20
G55: Total | H55: 3531
A57: 503 | B57: NY10C43 | C57: 773 | D57: t0004265 | E57: Javier Di Fiori | F57: 3650 | G57: rent | H57: 3550 | I57: 3550 | J57: 0 | K57: 45383 | L57: 45777 | N57: 0
G58: amenity | H58: 75
G59: gas | H59: 20
G60: water | H60: 15
G61: Total | H61: 3660
A63: 505 | B63: NY10C42 | C63: 794 | D63: t0004266 | E63: Ari Rosa | F63: 3750 | G63: rent | H63: 3324 | I63: 1000 | J63: 0 | K63: 45549 | L63: 45943 | N63: 0
G64: conspec | H64: -255.69
G65: amenity | H65: 75
G66: gas | H66: 25
G67: water | H67: 20
G68: Total | H68: 3188.31
A70: 506 | B70: NY10B1 | C70: 458 | D70: t0004267 | E70: Yutaroh Nakayama | F70: 3150 | G70: rent | H70: 3252.37 | I70: 3252.37 | J70: 0 | K70: 45089 | L70: 45849 | N70: 0
G71: amenity | H71: 75
G72: gas | H72: 10
G73: water | H73: 15
G74: Total | H74: 3352.37
A76: 507 | B76: NY10C44 | C76: 782 | D76: t0004268 | E76: Scott Kutlick | F76: 3950 | G76: rent | H76: 3950 | I76: 3950 | J76: 0 | K76: 44440 | L76: 46356 | N76: 3950
G77: amenity | H77: 100
G78: gas | H78: 25
G79: water | H79: 20
G80: Total | H80: 4095
A82: 508 | B82: NY10C18 | C82: 674 | D82: t0004269 | E82: Adriano Espaillat | F82: 3895 | G82: rent | H82: 3625 | I82: 3350 | J82: 0 | K82: 45348 | L82: 45740 | N82: 5882.24
G83: conspec | H83: -275
G84: amenity | H84: 75
G85: gas | H85: 20
G86: water | H86: 15
G87: Total | H87: 3460
A89: 509 | B89: NY10B16 | C89: 582 | D89: t0004270 | E89: Mitch Kalungi | F89: 3550 | G89: rent | H89: 3350 | I89: 0 | J89: 0 | K89: 45343 | L89: 45791 | N89: 0
G90: amenity | H90: 75
G91: gas | H91: 15
G92: water | H92: 10
G93: Total | H93: 3450
A95: 511 | B95: NY10C43 | C95: 757 | D95: t0004271 | E95: William Baker | F95: 3750 | G95: rent | H95: 3750 | I95: 3750 | J95: 0 | K95: 44935 | L95: 45696 | N95: 0
G96: amenity | H96: 75
G97: Total | H97: 3825
A99: 514 | B99: NY10C42 | C99: 773 | D99: t0004272 | E99: Albert Mitta | F99: 3650 | G99: rent | H99: 3650 | I99: 0 | J99: 0 | K99: 44972 | L99: 45760 | N99: 0
G100: gym | H100: 100
G101: gymcred | H101: -100
G102: Total | H102: 3650
A104: 516 | B104: NY10C45 | C104: 795 | D104: t0004273 | E104: Umar Cash | F104: 3299 | G104: rent | H104: 3299 | I104: 3299 | J104: 0 | K104: 45562 | L104: 46107 | N104: 0
G105: amenity | H105: 100
G106: gas | H106: 25
G107: water | H107: 20
G108: Total | H108: 3444
A110: 518 | B110: NY10C42 | C110: 780 | D110: VACANT | E110: VACANT | F110: 3695 | H110: 0 | I110: 0 | J110: 0 | N110: 0
G111: Total | H111: 0
A113: 519 | B113: NY10B1 | C113: 458 | D113: VACANT | E113: VACANT | F113: 3250 | H113: 0 | I113: 0 | J113: 0 | N113: 0
G114: Total | H114: 0
A116: 521 | B116: NY10C21 | C116: 677 | D116: t0004274 | E116: Rene Sandoval | F116: 3700 | G116: rent | H116: 3700 | I116: 3700 | J116: 0 | K116: 45460 | L116: 46069 | N116: 0
G117: conspec | H117: -411
G118: amenity | H118: 75
G119: gas | H119: 25
G120: water | H120: 20
G121: Total | H121: 3409
...

Sheet T12
A1: VBG 990 AOA LLC (Consolidated) (990conso)
A2: Statement (12 months)
A3: Period = Apr 2025-Mar 2026
A4: Book = Accrual | V4: 46112 | W4: 46022
C5: Apr 2025 | D5: May 2025 | E5: Jun 2025 | F5: Jul 2025 | G5: Aug 2025 | H5: Sep 2025 | I5: Oct 2025 | J5: Nov 2025 | K5: Dec 2025 | L5: Jan 2026 | M5: Feb 2026 | N5: Mar 2026 | O5: Total | Q5: Cost Category | S5: T6 | V5: Current T12 | W5: Previous T12
A6: 4000-0000 | B6: Revenues | U6: Gross Potential Rent (3) | V6: =+SUMIF(Q:Q,U6,O:O) -> 25677021 | W6: 24624190 | Y6: =+IF(ISNUMBER(W6),V6-W6,"") -> 1052831 | Z6: =+IF(ISNUMBER(Y6),Y6/W6,"") -> 0.042755963
A7: 4100-0000 | B7: RENTAL INCOME | U7: Less: Vacancy Loss | V7: =+SUMIF(Q:Q,U7,O:O) -> 0 | W7: 0 | Y7: =+IF(ISNUMBER(W7),V7-W7,"") -> 0 | Z7: =+IF(ISNUMBER(Y7),Y7/W7,"") -> #DIV/0!
A8: 4100-0010 | B8: Rent Income | C8: 25102.22 | D8: 25102.22 | E8: 25102.22 | F8: 0 | G8: 0 | H8: 0 | I8: 0 | J8: 0 | K8: 0 | L8: 0 | M8: 0 | N8: 0 | O8: 75306.66 | Q8: =IFERROR(INDEX(Coding!$D:$D,MATCH('T12'!$B8,Coding!$B:$B,0)),"") -> Gross Potential Rent (3) | S8: =IF(ISNUMBER(O8),SUM(I8:N8)*2,"") -> 0 | U8: Base Rent (3) | V8: =+SUMIF(Q:Q,U8,O:O) -> 2671554.2 | W8: 2720517.9 | Y8: =+IF(ISNUMBER(W8),V8-W8,"") -> -48963.7 | Z8: =+IF(ISNUMBER(Y8),Y8/W8,"") -> -0.017997933
A9: 4100-0011 | B9: Apartment Rent | C9: 1943935.2 | D9: 2079051.9 | E9: 2119875.6 | F9: 2150640 | G9: 2145712.1 | H9: 2163454.8 | I9: 2160223.7 | J9: 2144525.2 | K9: 2147740.2 | L9: 2128015.3 | M9: 2204388 | N9: 2214152.5 | O9: 25601715 | Q9: =IFERROR(INDEX(Coding!$D:$D,MATCH('T12'!$B9,Coding!$B:$B,0)),"") -> Gross Potential Rent (3) | S9: =IF(ISNUMBER(O9),SUM(I9:N9)*2,"") -> 25998090 | U9: Laundry/Vending Income | V9: =+SUMIF(Q:Q,U9,O:O) -> 0 | W9: 0 | Y9: =+IF(ISNUMBER(W9),V9-W9,"") -> 0 | Z9: =+IF(ISNUMBER(Y9),Y9/W9,"") -> #DIV/0!
A10: 4100-0014 | B10: Parking Income | C10: 50000 | D10: 50000 | E10: 50000 | F10: 50000 | G10: 50000 | H10: 50000 | I10: 50000 | J10: 50000 | K10: 50000 | L10: 50000 | M10: 50000 | N10: 50000 | O10: 600000 | Q10: =IFERROR(INDEX(Coding!$D:$D,MATCH('T12'!$B10,Coding!$B:$B,0)),"") -> Parking Income | S10: =IF(ISNUMBER(O10),SUM(I10:N10)*2,"") -> 600000 | U10: Parking Income | V10: =+SUMIF(Q:Q,U10,O:O) -> 853260.5 | W10: 863523 | Y10: =+IF(ISNUMBER(W10),V10-W10,"") -> -10262.5 | Z10: =+IF(ISNUMBER(Y10),Y10/W10,"") -> -0.011884455
A11: 4100-0016 | B11: Retail Rent | C11: 199667.01 | D11: 200701.39 | E11: 202566.99 | F11: 227669.21 | G11: 227763.45 | H11: 228776.26 | I11: 229785.44 | J11: 230473.05 | K11: 230473.05 | L11: 231226.12 | M11: 231226.12 | N11: 231226.12 | O11: 2671554.2 | Q11: =IFERROR(INDEX(Coding!$D:$D,MATCH('T12'!$B11,Coding!$B:$B,0)),"") -> Base Rent (3) | S11: =IF(ISNUMBER(O11),SUM(I11:N11)*2,"") -> 2768819.8 | U11: Other Income | V11: =+SUMIF(Q:Q,U11,O:O) -> -748852.72 | W11: -1105705.6 | Y11: =+IF(ISNUMBER(W11),V11-W11,"") -> 356852.93 | Z11: =+IF(ISNUMBER(Y11),Y11/W11,"") -> -0.32273773
A12: 4100-0050 | B12: Concessions | C12: -186855 | D12: -216204.5 | E12: -232135 | F12: -197780 | G12: -145260 | H12: -152872.5 | I12: -147080 | J12: -104641.33 | K12: -67435 | L12: -73037.5 | M12: -186702.5 | N12: -185560 | O12: -1895563.3 | Q12: =IFERROR(INDEX(Coding!$D:$D,MATCH('T12'!$B12,Coding!$B:$B,0)),"") -> Other Income | S12: =IF(ISNUMBER(O12),SUM(I12:N12)*2,"") -> -1528912.7 | U12: *Effective Gross Income | V12: =+SUM(V6:V11) -> 28452983 | W12: 27102526 | Y12: =+IF(ISNUMBER(W12),V12-W12,"") -> 1350457.7 | Z12: =+IF(ISNUMBER(Y12),Y12/W12,"") -> 0.049827744
A13: 4100-0052 | B13: Employer Provided Housing | C13: -9000 | D13: -9000 | E13: -9000 | F13: -9000 | G13: -9000 | H13: -9000 | I13: -9000 | J13: -9000 | K13: -9000 | L13: -9000 | M13: -9000 | N13: -9000 | O13: -108000 | Q13: =IFERROR(INDEX(Coding!$D:$D,MATCH('T12'!$B13,Coding!$B:$B,0)),"") -> Other Income | S13: =IF(ISNUMBER(O13),SUM(I13:N13)*2,"") -> -108000 | Y13: =+IF(ISNUMBER(W13),V13-W13,"") | Z13: =+IF(ISNUMBER(Y13),Y13/W13,"")
A14: 4100-0057 | B14: Cleaning Fees | C14: 0 | D14: 0 | E14: 0 | F14: 0 | G14: 200 | H14: 150 | I14: 250 | J14: 0 | K14: 0 | L14: 300 | M14: 400 | N14: 0 | O14: 1300 | Q14: =IFERROR(INDEX(Coding!$D:$D,MATCH('T12'!$B14,Coding!$B:$B,0)),"") -> Other Income | S14: =IF(ISNUMBER(O14),SUM(I14:N14)*2,"") -> 1900 | Y14: =+IF(ISNUMBER(W14),V14-W14,"") | Z14: =+IF(ISNUMBER(Y14),Y14/W14,"")
A15: 4100-0060 | B15: Percentage Rent | C15: 0 | D15: 0 | E15: 561 | F15: 0 | G15: 610.5 | H15: 0 | I15: 0 | J15: 594 | K15: 0 | L15: 0 | M15: 0 | N15: 0 | O15: 1765.5 | Q15: =IFERROR(INDEX(Coding!$D:$D,MATCH('T12'!$B15,Coding!$B:$B,0)),"") -> Other Income | S15: =IF(ISNUMBER(O15),SUM(I15:N15)*2,"") -> 1188 | U15: OPERATING EXPENSES: | Y15: =+IF(ISNUMBER(W15),V15-W15,"") | Z15: =+IF(ISNUMBER(Y15),Y15/W15,"")
A16: 4100-0061 | B16: Percentage Rent - Parking | C16: 0 | D16: 0 | E16: 64324 | F16: 0 | G16: 0 | H16: 70541 | I16: 0 | J16: 0 | K16: 87458 | L16: -87458 | M16: 87458 | N16: 30937.5 | O16: 253260.5 | Q16: =IFERROR(INDEX(Coding!$D:$D,MATCH('T12'!$B16,Coding!$B:$B,0)),"") -> Parking Income | S16: =IF(ISNUMBER(O16),SUM(I16:N16)*2,"") -> 236791 | U16: Real Estate Taxes | V16: =+SUMIF(Q:Q,U16,O:O) -> 6802665.6 | W16: 6749271.6 | Y16: =+IF(ISNUMBER(W16),V16-W16,"") -> 53394.05 | Z16: =+IF(ISNUMBER(Y16),Y16/W16,"") -> 0.0079110833
A17: 4100-0063 | B17: Pet Rent/Fees | C17: 50 | D17: 50 | E17: 50 | F17: 50 | G17: 50 | H17: 50 | I17: 50 | J17: 50 | K17: 50 | L17: 50 | M17: 50 | N17: 50 | O17: 600 | Q17: =IFERROR(INDEX(Coding!$D:$D,MATCH('T12'!$B17,Coding!$B:$B,0)),"") -> Other Income | S17: =IF(ISNUMBER(O17),SUM(I17:N17)*2,"") -> 600 | U17: Property Insurance | V17: =+SUMIF(Q:Q,U17,O:O) -> 651481 | W17: 649173.44 | Y17: =+IF(ISNUMBER(W17),V17-W17,"") -> 2307.56 | Z17: =+IF(ISNUMBER(Y17),Y17/W17,"") -> 0.0035546125
A18: 4100-0064 | B18: Resident Referral | C18: 0 | D18: 0 | E18: 0 | F18: 0 | G18: 0 | H18: 0 | I18: -1500 | J18: 0 | K18: 0 | L18: 0 | M18: -2500 | N18: -500 | O18: -4500 | Q18: =IFERROR(INDEX(Coding!$D:$D,MATCH('T12'!$B18,Coding!$B:$B,0)),"") -> Other Income | S18: =IF(ISNUMBER(O18),SUM(I18:N18)*2,"") -> -9000 | U18: Utilities | V18: =+SUMIF(Q:Q,U18,O:O) -> 1344132.8 | W18: 1016154.2 | Y18: =+IF(ISNUMBER(W18),V18-W18,"") -> 327978.54 | Z18: =+IF(ISNUMBER(Y18),Y18/W18,"") -> 0.32276452
A19: 4100-0450 | B19: Bad Debt Expense - Non operating | C19: 0 | D19: 0 | E19: -134000.03 | F19: 340 | G19: 0 | H19: 159 | I19: 0 | J19: 0 | K19: -60274.18 | L19: 0 | M19: 0 | N19: 26170.49 | O19: -167604.72 | Q19: =IFERROR(INDEX(Coding!$D:$D,MATCH('T12'!$B19,Coding!$B:$B,0)),"") -> Other Income | S19: =IF(ISNUMBER(O19),SUM(I19:N19)*2,"") -> -68207.38 | U19: Repairs and Maintenance | V19: =+SUMIF(Q:Q,U19,O:O) -> 781368.51 | W19: 695520.41 | Y19: =+IF(ISNUMBER(W19),V19-W19,"") -> 85848.1 | Z19: =+IF(ISNUMBER(Y19),Y19/W19,"") -> 0.12343002
A20: 4199-9999 | B20: Total Rent Income | C20: 2022899.5 | D20: 2129701 | E20: 2087344.8 | F20: 2221919.2 | G20: 2270076.1 | H20: 2351258.6 | I20: 2282729.1 | J20: 2312000.9 | K20: 2379012.1 | L20: 2240095.9 | M20: 2375319.7 | N20: 2357476.6 | O20: 27029833 | Q20: =IFERROR(INDEX(Coding!$C:$C,MATCH('T12'!$B20,Coding!$B:$B,0)),"") -> 0 | S20: =IF(ISNUMBER(O20),SUM(I20:N20)*2,"") -> 27893269 | U20: Management Fees | V20: =+SUMIF(Q:Q,U20,O:O) -> 385416.19 | W20: 369733.47 | Y20: =+IF(ISNUMBER(W20),V20-W20,"") -> 15682.72 | Z20: =+IF(ISNUMBER(Y20),Y20/W20,"") -> 0.042416284
A21: 4200-0000 | B21: Reimbursements & Escalations | Q21: =IFERROR(INDEX(Coding!$C:$C,MATCH('T12'!$B21,Coding!$B:$B,0)),"") -> 0 | S21: =IF(ISNUMBER(O21),SUM(I21:N21)*2,"") | U21: Payroll & Benefits | V21: =+SUMIF(Q:Q,U21,O:O) -> 321346.34 | W21: 294391.6 | Y21: =+IF(ISNUMBER(W21),V21-W21,"") -> 26954.74 | Z21: =+IF(ISNUMBER(Y21),Y21/W21,"") -> 0.091560833
A22: 4200-0010 | B22: Operating Expense Escalations | C22: -54202 | D22: 0 | E22: 44689.35 | F22: -44689.35 | G22: 0 | H22: 48021.82 | I22: -48021.82 | J22: 0 | K22: 18586.29 | L22: -18586.29 | M22: 0 | N22: 29432.76 | O22: -24769.24 | Q22: =IFERROR(INDEX(Coding!$D:$D,MATCH('T12'!$B22,Coding!$B:$B,0)),"") -> Other Income | S22: =IF(ISNUMBER(O22),SUM(I22:N22)*2,"") -> -37178.12 | U22: Advertising & Marketing | V22: =+SUMIF(Q:Q,U22,O:O) -> 112073.59 | W22: 115325.44 | Y22: =+IF(ISNUMBER(W22),V22-W22,"") -> -3251.85 | Z22: =+IF(ISNUMBER(Y22),Y22/W22,"") -> -0.028197161
A23: 4200-0025 | B23: Water & Sewer Income | C23: 2020 | D23: 2170.86 | E23: 4397.06 | F23: 0 | G23: 8564.24 | H23: 5039.32 | I23: 0 | J23: 4475.28 | K23: 4656.66 | L23: 4978.64 | M23: 5201.51 | N23: 4741.31 | O23: 46244.88 | Q23: =IFERROR(INDEX(Coding!$D:$D,MATCH('T12'!$B23,Coding!$B:$B,0)),"") -> Other Income | S23: =IF(ISNUMBER(O23),SUM(I23:N23)*2,"") -> 48106.8 | U23: Professional Fees | V23: =+SUMIF(Q:Q,U23,O:O) -> 171187.81 | W23: 195156.35 | Y23: =+IF(ISNUMBER(W23),V23-W23,"") -> -23968.54 | Z23: =+IF(ISNUMBER(Y23),Y23/W23,"") -> -0.12281712
A24: 4200-0027 | B24: Sprinkler Supervisory Service | C24: 325 | D24: 325 | E24: 325 | F24: 325 | G24: 325 | H24: 325 | I24: 325 | J24: 325 | K24: 325 | L24: 325 | M24: 325 | N24: 325 | O24: 3900 | Q24: =IFERROR(INDEX(Coding!$D:$D,MATCH('T12'!$B24,Coding!$B:$B,0)),"") -> Other Income | S24: =IF(ISNUMBER(O24),SUM(I24:N24)*2,"") -> 3900 | U24: General and Administrative | V24: =+SUMIF(Q:Q,U24,O:O) -> 2604757 | W24: 2599132.7 | Y24: =+IF(ISNUMBER(W24),V24-W24,"") -> 5624.3 | Z24: =+IF(ISNUMBER(Y24),Y24/W24,"") -> 0.0021639141
A25: 4200-0031 | B25: Electric - Sub metering | C25: 20376.44 | D25: 31723.82 | E25: 66669.22 | F25: 102016.17 | G25: 89368.35 | H25: 33248.96 | I25: 112964.63 | J25: 19188.96 | K25: 52168.8 | L25: 42118.14 | M25: 49008.81 | N25: 37892.87 | O25: 656745.17 | Q25: =IFERROR(INDEX(Coding!$D:$D,MATCH('T12'!$B25,Coding!$B:$B,0)),"") -> Other Income | S25: =IF(ISNUMBER(O25),SUM(I25:N25)*2,"") -> 626684.42 | U25: Other Expenses | V25: =+SUMIF(Q:Q,U25,O:O) -> 0 | W25: 0 | Y25: =+IF(ISNUMBER(W25),V25-W25,"") -> 0 | Z25: =+IF(ISNUMBER(Y25),Y25/W25,"") -> #DIV/0!
A26: 4200-0040 | B26: Hvac Income Escalation | C26: 2793.75 | D26: 2793.75 | E26: 2793.75 | F26: 2793.75 | G26: 2793.75 | H26: 2793.75 | I26: 2793.75 | J26: 2793.75 | K26: 2793.75 | L26: 10293.75 | M26: 2793.75 | N26: 2793.75 | O26: 41025 | Q26: =IFERROR(INDEX(Coding!$D:$D,MATCH('T12'!$B26,Coding!$B:$B,0)),"") -> Other Income | S26: =IF(ISNUMBER(O26),SUM(I26:N26)*2,"") -> 48525 | U26: Ground Rent | V26: =+SUMIF(Q:Q,U26,O:O) -> 0 | W26: 0 | Y26: =+IF(ISNUMBER(W26),V26-W26,"") -> 0 | Z26: =+IF(ISNUMBER(Y26),Y26/W26,"") -> #DIV/0!
A27: 4200-0050 | B27: Real Estate Tax Escalations | C27: 3412.8 | D27: 3412.8 | E27: 3412.8 | F27: 5056.02 | G27: 5056.02 | H27: 5056.02 | I27: 5056.02 | J27: 5056.02 | K27: 5056.02 | L27: 4675.79 | M27: 4675.79 | N27: 4675.79 | O27: 54601.89 | Q27: =IFERROR(INDEX(Coding!$D:$D,MATCH('T12'!$B27,Coding!$B:$B,0)),"") -> Other Income | S27: =IF(ISNUMBER(O27),SUM(I27:N27)*2,"") -> 58390.86 | U27: *Total Operating Expenses | V27: =+SUM(V16:V26) -> 13174429 | W27: 12683859 | Y27: =+IF(ISNUMBER(W27),V27-W27,"") -> 490569.62 | Z27: =+IF(ISNUMBER(Y27),Y27/W27,"") -> 0.038676684
A28: 4200-0060 | B28: Back charges - Net | C28: 0 | D28: 0 | E28: 0 | F28: 0 | G28: 0 | H28: 0 | I28: 5784.02 | J28: 80 | K28: 0 | L28: 0 | M28: 910 | N28: 0 | O28: 6774.02 | Q28: =IFERROR(INDEX(Coding!$D:$D,MATCH('T12'!$B28,Coding!$B:$B,0)),"") -> Other Income | S28: =IF(ISNUMBER(O28),SUM(I28:N28)*2,"") -> 13548.04 | Y28: =+IF(ISNUMBER(W28),V28-W28,"") | Z28: =+IF(ISNUMBER(Y28),Y28/W28,"")
A29: 4200-0090 | B29: Income - Sundry Billings | C29: 0 | D29: -120 | E29: -120 | F29: 0 | G29: 0 | H29: 0 | I29: 0 | J29: 0 | K29: 0 | L29: 0 | M29: 0 | N29: 0 | O29: -240 | Q29: =IFERROR(INDEX(Coding!$D:$D,MATCH('T12'!$B29,Coding!$B:$B,0)),"") -> Other Income | S29: =IF(ISNUMBER(O29),SUM(I29:N29)*2,"") -> 0 | U29: *Net Operating Income | V29: =+V12-V27 -> 15278554 | W29: 14418666 | Y29: =+IF(ISNUMBER(W29),V29-W29,"") -> 859888.09 | Z29: =+IF(ISNUMBER(Y29),Y29/W29,"") -> 0.059637145
A30: 4299-9999 | B30: Total Reimbursements & Escal. | C30: -25274.01 | D30: 40306.23 | E30: 122167.18 | F30: 65501.59 | G30: 106107.36 | H30: 94484.87 | I30: 78901.6 | J30: 31919.01 | K30: 83586.52 | L30: 43805.03 | M30: 62914.86 | N30: 79861.48 | O30: 784281.72 | Q30: =IFERROR(INDEX(Coding!$C:$C,MATCH('T12'!$B30,Coding!$B:$B,0)),"") -> 0 | S30: =IF(ISNUMBER(O30),SUM(I30:N30)*2,"") -> 761977
A31: 4300-0000 | B31: Other | Q31: =IFERROR(INDEX(Coding!$C:$C,MATCH('T12'!$B31,Coding!$B:$B,0)),"") -> 0 | S31: =IF(ISNUMBER(O31),SUM(I31:N31)*2,"")
A32: 4300-0150 | B32: Application Fee Income | C32: 800 | D32: 400 | E32: 1240 | F32: 1200 | G32: 1040 | H32: 760 | I32: 920 | J32: 420 | K32: 340 | L32: 1680 | M32: 920 | N32: 380 | O32: 10100 | Q32: =IFERROR(INDEX(Coding!$D:$D,MATCH('T12'!$B32,Coding!$B:$B,0)),"") -> Other Income | S32: =IF(ISNUMBER(O32),SUM(I32:N32)*2,"") -> 9320 | V32: T6 Figures
A33: 4300-0300 | B33: Miscellaneous Income | C33: 42889.57 | D33: 45286.29 | E33: 40372.54 | F33: 38722.55 | G33: 49829.81 | H33: 43994.3 | I33: 43532.79 | J33: 56230.76 | K33: 51369.8 | L33: 51517.83 | M33: 71793.8 | N33: 54020.68 | O33: 589560.72 | Q33: =IFERROR(INDEX(Coding!$D:$D,MATCH('T12'!$B33,Coding!$B:$B,0)),"") -> Other Income | S33: =IF(ISNUMBER(O33),SUM(I33:N33)*2,"") -> 656931.32 | U33: Other Income | V33: =SUMIF(Q:Q,U33,S:S)-S12 -> 1298605.1
A34: 4300-0350 | B34: Late Charges | C34: 350 | D34: 440 | E34: 450 | F34: 550 | G34: 1725.28 | H34: 2994.04 | I34: -177.91 | J34: 450 | K34: 350 | L34: 700 | M34: 4430.7 | N34: 8190.28 | O34: 20452.39 | Q34: =IFERROR(INDEX(Coding!$D:$D,MATCH('T12'!$B34,Coding!$B:$B,0)),"") -> Other Income | S34: =IF(ISNUMBER(O34),SUM(I34:N34)*2,"") -> 27886.14 | U34: Concessions | V34: =S12 -> -1528912.7
A35: 4300-0400 | B35: Bounced/Stopped Check Income | C35: 50 | D35: 400 | E35: 475 | F35: 200 | G35: 200 | H35: 275 | I35: 425 | J35: 400 | K35: 325 | L35: 230 | M35: 975 | N35: 1100 | O35: 5055 | Q35: =IFERROR(INDEX(Coding!$D:$D,MATCH('T12'!$B35,Coding!$B:$B,0)),"") -> Other Income | S35: =IF(ISNUMBER(O35),SUM(I35:N35)*2,"") -> 6910 | U35: T6 Other Income less Concessions | V35: =V33+V34 -> -230307.58
A36: 4300-0450 | B36: Lease Termination Income | C36: 0 | D36: 0 | E36: 0 | F36: 5150 | G36: 0 | H36: 0 | I36: 0 | J36: 0 | K36: 6550 | L36: 0 | M36: 2000 | N36: 0 | O36: 13700 | Q36: =IFERROR(INDEX(Coding!$D:$D,MATCH('T12'!$B36,Coding!$B:$B,0)),"") -> Other Income | S36: =IF(ISNUMBER(O36),SUM(I36:N36)*2,"") -> 17100
A37: 4399-9999 | B37: Total Other Income | C37: 44089.57 | D37: 46526.29 | E37: 42537.54 | F37: 45822.55 | G37: 52795.09 | H37: 48023.34 | I37: 44699.88 | J37: 57500.76 | K37: 58934.8 | L37: 54127.83 | M37: 80119.5 | N37: 63690.96 | O37: 638868.11 | Q37: =IFERROR(INDEX(Coding!$C:$C,MATCH('T12'!$B37,Coding!$B:$B,0)),"") -> 0 | S37: =IF(ISNUMBER(O37),SUM(I37:N37)*2,"") -> 718147.46
A38: 4599-9999 | B38: TOTAL OPERATING INCOME | C38: 2041715 | D38: 2216533.5 | E38: 2252049.5 | F38: 2333243.4 | G38: 2428978.5 | H38: 2493766.8 | I38: 2406330.6 | J38: 2401420.7 | K38: 2521533.4 | L38: 2338028.8 | M38: 2518354 | N38: 2501029 | O38: 28452983 | Q38: =IFERROR(INDEX(Coding!$C:$C,MATCH('T12'!$B38,Coding!$B:$B,0)),"") -> 0 | S38: =IF(ISNUMBER(O38),SUM(I38:N38)*2,"") -> 29373393
A39: 4999-9999 | B39: Total Revenues | C39: 2041715 | D39: 2216533.5 | E39: 2252049.5 | F39: 2333243.4 | G39: 2428978.5 | H39: 2493766.8 | I39: 2406330.6 | J39: 2401420.7 | K39: 2521533.4 | L39: 2338028.8 | M39: 2518354 | N39: 2501029 | O39: 28452983 | Q39: =IFERROR(INDEX(Coding!$C:$C,MATCH('T12'!$B39,Coding!$B:$B,0)),"") -> 0 | S39: =IF(ISNUMBER(O39),SUM(I39:N39)*2,"") -> 29373393
A40: 5000-0000 | B40: OPERATING EXPENSES | Q40: =IFERROR(INDEX(Coding!$C:$C,MATCH('T12'!$B40,Coding!$B:$B,0)),"") -> 0 | S40: =IF(ISNUMBER(O40),SUM(I40:N40)*2,"")
A41: 5000-1000 | B41: Reimbursable Expenses | Q41: =IFERROR(INDEX(Coding!$C:$C,MATCH('T12'!$B41,Coding!$B:$B,0)),"") -> 0 | S41: =IF(ISNUMBER(O41),SUM(I41:N41)*2,"")
A42: 5100-0000 | B42: Real Estate Taxes | Q42: =IFERROR(INDEX(Coding!$C:$C,MATCH('T12'!$B42,Coding!$B:$B,0)),"") -> 0 | S42: =IF(ISNUMBER(O42),SUM(I42:N42)*2,"")
A43: 5100-0050 | B43: Real Estate Taxes | C43: 0 | D43: 0 | E43: 1649225.2 | F43: 0 | G43: 0 | H43: 1720010.6 | I43: 0 | J43: 0 | K43: 1720010.6 | L43: 0 | M43: 0 | N43: 1703619.3 | O43: 6792865.6 | Q43: =IFERROR(INDEX(Coding!$C:$C,MATCH('T12'!$B43,Coding!$B:$B,0)),"") -> 0 | S43: =IF(ISNUMBER(O43),SUM(I43:N43)*2,"") -> 6847259.7
A44: 5100-0350 | B44: Real Estate Tax Consultant | C44: 0 | D44: 0 | E44: 0 | F44: 0 | G44: 0 | H44: 350 | I44: 0 | J44: 0 | K44: 9450 | L44: 0 | M44: 0 | N44: 0 | O44: 9800 | Q44: =IFERROR(INDEX(Coding!$C:$C,MATCH('T12'!$B44,Coding!$B:$B,0)),"") -> 0 | S44: =IF(ISNUMBER(O44),SUM(I44:N44)*2,"") -> 18900
A45: 5100-9999 | B45: Total Real Estate Taxes | C45: 0 | D45: 0 | E45: 1649225.2 | F45: 0 | G45: 0 | H45: 1720360.6 | I45: 0 | J45: 0 | K45: 1729460.6 | L45: 0 | M45: 0 | N45: 1703619.3 | O45: 6802665.6 | Q45: =IFERROR(INDEX(Coding!$D:$D,MATCH('T12'!$B45,Coding!$B:$B,0)),"") -> Real Estate Taxes | S45: =IF(ISNUMBER(O45),SUM(I45:N45)*2,"") -> 6866159.7
A46: 5200-0000 | B46: Insurance | Q46: =IFERROR(INDEX(Coding!$C:$C,MATCH('T12'!$B46,Coding!$B:$B,0)),"") -> 0 | S46: =IF(ISNUMBER(O46),SUM(I46:N46)*2,"")
A47: 5200-0050 | B47: Insurance | C47: 1062.64 | D47: 43473.65 | E47: 1058.96 | F47: 1074.54 | G47: 1056.91 | H47: 1056.41 | I47: 1030.88 | J47: 1030.26 | K47: 1029.84 | L47: 1029.44 | M47: 1011.64 | N47: 1011.49 | O47: 54926.66 | Q47: =IFERROR(INDEX(Coding!$C:$C,MATCH('T12'!$B47,Coding!$B:$B,0)),"") -> 0 | S47: =IF(ISNUMBER(O47),SUM(I47:N47)*2,"") -> 12287.1
A48: 5200-0100 | B48: Insurance - Prop & Liability | C48: 0 | D48: 0 | E48: 147011.92 | F48: 0 | G48: 0 | H48: 147011.92 | I48: 0 | J48: 0 | K48: 151265.25 | L48: 0 | M48: 0 | N48: 151265.25 | O48: 596554.34 | Q48: =IFERROR(INDEX(Coding!$C:$C,MATCH('T12'!$B48,Coding!$B:$B,0)),"") -> 0 | S48: =IF(ISNUMBER(O48),SUM(I48:N48)*2,"") -> 605061
A49: 5200-9999 | B49: Total Insurance | C49: 1062.64 | D49: 43473.65 | E49: 148070.88 | F49: 1074.54 | G49: 1056.91 | H49: 148068.33 | I49: 1030.88 | J49: 1030.26 | K49: 152295.09 | L49: 1029.44 | M49: 1011.64 | N49: 152276.74 | O49: 651481 | Q49: =IFERROR(INDEX(Coding!$D:$D,MATCH('T12'!$B49,Coding!$B:$B,0)),"") -> Property Insurance | S49: =IF(ISNUMBER(O49),SUM(I49:N49)*2,"") -> 617348.1 | W49: =V12-O38 -> 0
A50: 5400-0000 | B50: Utilities | Q50: =IFERROR(INDEX(Coding!$C:$C,MATCH('T12'!$B50,Coding!$B:$B,0)),"") -> 0 | S50: =IF(ISNUMBER(O50),SUM(I50:N50)*2,"")
A51: 5400-0100 | B51: Water & Sewer | C51: -33430.94 | D51: 43260.35 | E51: 30434.37 | F51: -30434.37 | G51: 42224.89 | H51: 35976.36 | I51: -31668.67 | J51: 43960.2 | K51: 32715.62 | L51: -32615.62 | M51: 45098.12 | N51: 33137.41 | O51: 178657.72 | Q51: =IFERROR(INDEX(Coding!$C:$C,MATCH('T12'!$B51,Coding!$B:$B,0)),"") -> 0 | S51: =IF(ISNUMBER(O51),SUM(I51:N51)*2,"") -> 181254.12
A52: 5400-0550 | B52: Gas | C52: 47095.57 | D52: 50430.52 | E52: 66604.67 | F52: 22842.79 | G52: 35806.89 | H52: 49858.63 | I52: 18841.24 | J52: 20701.58 | K52: 65453.03 | L52: 36028.14 | M52: 67636.71 | N52: 131732.67 | O52: 613032.44 | Q52: =IFERROR(INDEX(Coding!$C:$C,MATCH('T12'!$B52,Coding!$B:$B,0)),"") -> 0 | S52: =IF(ISNUMBER(O52),SUM(I52:N52)*2,"") -> 680786.74
A53: 5400-0800 | B53: Electricity - Cam | C53: 28615.52 | D53: 29495.24 | E53: 48757.83 | F53: 25923.16 | G53: 73217.32 | H53: 92741.49 | I53: 23552.27 | J53: 42580.2 | K53: 45883.53 | L53: 9758.76 | M53: 32459.59 | N53: 95446.16 | O53: 548431.07 | Q53: =IFERROR(INDEX(Coding!$C:$C,MATCH('T12'!$B53,Coding!$B:$B,0)),"") -> 0 | S53: =IF(ISNUMBER(O53),SUM(I53:N53)*2,"") -> 499361.02
A54: 5400-0900 | B54: Electric - Interior | C54: 8569.73 | D54: 0 | E54: -8359.66 | F54: 0 | G54: -210.07 | H54: 0 | I54: 0 | J54: 0 | K54: 0 | L54: 0 | M54: 0 | N54: 0 | O54: 0 | Q54: =IFERROR(INDEX(Coding!$C:$C,MATCH('T12'!$B54,Coding!$B:$B,0)),"") -> 0 | S54: =IF(ISNUMBER(O54),SUM(I54:N54)*2,"") -> 0
A55: 5400-1100 | B55: Utility Consultant | C55: -1265.88 | D55: 0 | E55: 3167.18 | F55: -680.5 | G55: 680.5 | H55: 486.25 | I55: 0 | J55: 0 | K55: 1596 | L55: -528 | M55: 0 | N55: 556 | O55: 4011.55 | Q55: =IFERROR(INDEX(Coding!$C:$C,MATCH('T12'!$B55,Coding!$B:$B,0)),"") -> 0 | S55: =IF(ISNUMBER(O55),SUM(I55:N55)*2,"") -> 3248
A56: 5400-9999 | B56: Total Utilities | C56: 49584 | D56: 123186.11 | E56: 140604.39 | F56: 17651.08 | G56: 151719.53 | H56: 179062.73 | I56: 10724.84 | J56: 107241.98 | K56: 145648.18 | L56: 12643.28 | M56: 145194.42 | N56: 260872.24 | O56: 1344132.8 | Q56: =IFERROR(INDEX(Coding!$D:$D,MATCH('T12'!$B56,Coding!$B:$B,0)),"") -> Utilities | S56: =IF(ISNUMBER(O56),SUM(I56:N56)*2,"") -> 1364649.9
A57: 5499-9999 | B57: Total Reimbursable Expenses | C57: 50646.64 | D57: 166659.76 | E57: 1937900.5 | F57: 18725.62 | G57: 152776.44 | H57: 2047491.6 | I57: 11755.72 | J57: 108272.24 | K57: 2027403.8 | L57: 13672.72 | M57: 146206.06 | N57: 2116768.3 | O57: 8798279.4 | Q57: =IFERROR(INDEX(Coding!$C:$C,MATCH('T12'!$B57,Coding!$B:$B,0)),"") -> 0 | S57: =IF(ISNUMBER(O57),SUM(I57:N57)*2,"") -> 8848157.7
A58: 5500-0000 | B58: Non Reimbursable Expenses | Q58: =IFERROR(INDEX(Coding!$C:$C,MATCH('T12'!$B58,Coding!$B:$B,0)),"") -> 0 | S58: =IF(ISNUMBER(O58),SUM(I58:N58)*2,"")
A59: 5520-0000 | B59: Professional Fees | Q59: =IFERROR(INDEX(Coding!$C:$C,MATCH('T12'!$B59,Coding!$B:$B,0)),"") -> 0 | S59: =IF(ISNUMBER(O59),SUM(I59:N59)*2,"")
A60: 5520-0100 | B60: Professional Fees | C60: 17947.98 | D60: 5263.83 | E60: 8623.12 | F60: -2946.54 | G60: 15041.95 | H60: 6907.8 | I60: 840.98 | J60: 7088.44 | K60: 14034.94 | L60: 728.54 | M60: 371.18 | N60: 12046.06 | O60: 85948.28 | Q60: =IFERROR(INDEX(Coding!$C:$C,MATCH('T12'!$B60,Coding!$B:$B,0)),"") -> 0 | S60: =IF(ISNUMBER(O60),SUM(I60:N60)*2,"") -> 70220.28
A61: 5520-0200 | B61: Computer Consultants | C61: -2099.6 | D61: 3255 | E61: 2099.6 | F61: 4378.88 | G61: 0 | H61: 0 | I61: 0 | J61: 21132.29 | K61: 3906.43 | L61: -1513.04 | M61: 2419.22 | N61: 3985.23 | O61: 37564.01 | Q61: =IFERROR(INDEX(Coding!$C:$C,MATCH('T12'!$B61,Coding!$B:$B,0)),"") -> 0 | S61: =IF(ISNUMBER(O61),SUM(I61:N61)*2,"") -> 59860.26
A62: 5520-9999 | B62: Total Professional Fees | C62: 15848.38 | D62: 8518.83 | E62: 10722.72 | F62: 1432.34 | G62: 15041.95 | H62: 6907.8 | I62: 840.98 | J62: 28220.73 | K62: 17941.37 | L62: -784.5 | M62: 2790.4 | N62: 16031.29 | O62: 123512.29 | Q62: =IFERROR(INDEX(Coding!$C:$C,MATCH('T12'!$B62,Coding!$B:$B,0)),"") -> Professional Fees | S62: =IF(ISNUMBER(O62),SUM(I62:N62)*2,"") -> 130080.54
A63: 5530-0000 | B63: Operating Professional Fees | Q63: =IFERROR(INDEX(Coding!$D:$D,MATCH('T12'!$B63,Coding!$B:$B,0)),"") -> 0 | S63: =IF(ISNUMBER(O63),SUM(I63:N63)*2,"")
A64: 5530-0100 | B64: Legal Fees (Non Lease) | C64: 5614.02 | D64: 1487.2 | E64: -1263 | F64: 4256.59 | G64: 0 | H64: 7798.53 | I64: 3798.99 | J64: 5336.62 | K64: 1958.1 | L64: 343.2 | M64: 343.2 | N64: 4361.56 | O64: 34035.01 | Q64: =IFERROR(INDEX(Coding!$C:$C,MATCH('T12'!$B64,Coding!$B:$B,0)),"") -> 0 | S64: =IF(ISNUMBER(O64),SUM(I64:N64)*2,"") -> 32283.34
A65: 5530-0350 | B65: Legal - Service Contracts | C65: -4393.15 | D65: 2025 | E65: 9812.66 | F65: -3700.99 | G65: 3700.99 | H65: 1035 | I65: 0 | J65: 1595 | K65: 0 | L65: 0 | M65: 6261.42 | N65: -2695.42 | O65: 13640.51 | Q65: =IFERROR(INDEX(Coding!$C:$C,MATCH('T12'!$B65,Coding!$B:$B,0)),"") -> 0 | S65: =IF(ISNUMBER(O65),SUM(I65:N65)*2,"") -> 10322
A66: 5530-9999 | B66: Total Operating Professional Fees | C66: 1220.87 | D66: 3512.2 | E66: 8549.66 | F66: 555.6 | G66: 3700.99 | H66: 8833.53 | I66: 3798.99 | J66: 6931.62 | K66: 1958.1 | L66: 343.2 | M66: 6604.62 | N66: 1666.14 | O66: 47675.52 | Q66: =IFERROR(INDEX(Coding!$C:$C,MATCH('T12'!$B66,Coding!$B:$B,0)),"") -> Professional Fees | S66: =IF(ISNUMBER(O66),SUM(I66:N66)*2,"") -> 42605.34
A67: 5540-0000 | B67: Architects & Engineers | Q67: =IFERROR(INDEX(Coding!$D:$D,MATCH('T12'!$B67,Coding!$B:$B,0)),"") -> 0 | S67: =IF(ISNUMBER(O67),SUM(I67:N67)*2,"")
A68: 5540-0100 | B68: Engineering Fees | C68: 0 | D68: 0 | E68: 0 | F68: 2150 | G68: 0 | H68: -2150 | I68: 0 | J68: 0 | K68: 0 | L68: 0 | M68: 0 | N68: 0 | O68: 0 | Q68: =IFERROR(INDEX(Coding!$C:$C,MATCH('T12'!$B68,Coding!$B:$B,0)),"") -> 0 | S68: =IF(ISNUMBER(O68),SUM(I68:N68)*2,"") -> 0
A69: 5540-9999 | B69: Total Architects & Engineers | C69: 0 | D69: 0 | E69: 0 | F69: 2150 | G69: 0 | H69: -2150 | I69: 0 | J69: 0 | K69: 0 | L69: 0 | M69: 0 | N69: 0 | O69: 0 | Q69: =IFERROR(INDEX(Coding!$C:$C,MATCH('T12'!$B69,Coding!$B:$B,0)),"") -> 0 | S69: =IF(ISNUMBER(O69),SUM(I69:N69)*2,"") -> 0
A70: 5550-0000 | B70: PROPERTY MANAGEMENT FEES | Q70: =IFERROR(INDEX(Coding!$C:$C,MATCH('T12'!$B70,Coding!$B:$B,0)),"") -> 0 | S70: =IF(ISNUMBER(O70),SUM(I70:N70)*2,"")
A71: 5550-0050 | B71: Property Mgmt. Fees | C71: 25640.6 | D71: 29778.53 | E71: 33922.16 | F71: 25556.06 | G71: 31506.83 | H71: 29698.23 | I71: 41052.71 | J71: 29651.77 | K71: 38027.74 | L71: 33134.33 | M71: 34131.07 | N71: 33316.16 | O71: 385416.19 | Q71: =IFERROR(INDEX(Coding!$C:$C,MATCH('T12'!$B71,Coding!$B:$B,0)),"") -> 0 | S71: =IF(ISNUMBER(O71),SUM(I71:N71)*2,"") -> 418627.56
A72: 5550-9999 | B72: TOTAL PROPERTY MANAGEMENT FEES | C72: 25640.6 | D72: 29778.53 | E72: 33922.16 | F72: 25556.06 | G72: 31506.83 | H72: 29698.23 | I72: 41052.71 | J72: 29651.77 | K72: 38027.74 | L72: 33134.33 | M72: 34131.07 | N72: 33316.16 | O72: 385416.19 | Q72: =IFERROR(INDEX(Coding!$C:$C,MATCH('T12'!$B72,Coding!$B:$B,0)),"") -> Management Fees | S72: =IF(ISNUMBER(O72),SUM(I72:N72)*2,"") -> 418627.56
A73: 5600-0000 | B73: Service Contracts | Q73: =IFERROR(INDEX(Coding!$C:$C,MATCH('T12'!$B73,Coding!$B:$B,0)),"") -> 0 | S73: =IF(ISNUMBER(O73),SUM(I73:N73)*2,"")
A74: 5610-0000 | B74: Cleaning/ Maintenance | Q74: =IFERROR(INDEX(Coding!$D:$D,MATCH('T12'!$B74,Coding!$B:$B,0)),"") -> 0 | S74: =IF(ISNUMBER(O74),SUM(I74:N74)*2,"")
A75: 5610-0010 | B75: Janitorial - Porter | C75: -219745.31 | D75: 84441.4 | E75: 426099.61 | F75: -100107.07 | G75: 3077.79 | H75: 391445.42 | I75: -341150.78 | J75: 98757.69 | K75: 542516.87 | L75: -272365.63 | M75: 90858.8 | N75: 395211.91 | O75: 1099040.7 | Q75: =IFERROR(INDEX(Coding!$C:$C,MATCH('T12'!$B75,Coding!$B:$B,0)),"") -> 0 | S75: =IF(ISNUMBER(O75),SUM(I75:N75)*2,"") -> 1027657.7
A76: 5610-0030 | B76: Cleaning Services - Contract | C76: 0 | D76: 0 | E76: 0 | F76: 0 | G76: 2100.23 | H76: -2100.23 | I76: 0 | J76: 50126.13 | K76: -50126.13 | L76: 618 | M76: 2617.36 | N76: 0 | O76: 3235.36 | Q76: =IFERROR(INDEX(Coding!$C:$C,MATCH('T12'!$B76,Coding!$B:$B,0)),"") -> 0 | S76: =IF(ISNUMBER(O76),SUM(I76:N76)*2,"") -> 6470.72
A77: 5610-0041 | B77: Janitorial Supplies | C77: -16781.5 | D77: 625.82 | E77: 31059.42 | F77: -5830.32 | G77: 12087.5 | H77: 9418.94 | I77: 0 | J77: 5610.27 | K77: 12626.62 | L77: -665.01 | M77: 0 | N77: 12635.44 | O77: 60787.18 | Q77: =IFERROR(INDEX(Coding!$C:$C,MATCH('T12'!$B77,Coding!$B:$B,0)),"") -> 0 | S77: =IF(ISNUMBER(O77),SUM(I77:N77)*2,"") -> 60414.64
A78: 5610-0080 | B78: Exterminating Contract | C78: 7844.44 | D78: 2391.32 | E78: 16102.62 | F78: -6913.56 | G78: 7545.04 | H78: 6706.71 | I78: 0 | J78: 7272.85 | K78: 6990.34 | L78: -791.34 | M78: 3320.69 | N78: 15021.32 | O78: 65490.43 | Q78: =IFERROR(INDEX(Coding!$C:$C,MATCH('T12'!$B78,Coding!$B:$B,0)),"") -> 0 | S78: =IF(ISNUMBER(O78),SUM(I78:N78)*2,"") -> 63627.72
A79: 5610-0090 | B79: Uniforms | C79: -375 | D79: 0 | E79: 1925 | F79: -750 | G79: 1500 | H79: 375 | I79: 375 | J79: 0 | K79: 750 | L79: 0 | M79: 375 | N79: 4302.75 | O79: 8477.75 | Q79: =IFERROR(INDEX(Coding!$C:$C,MATCH('T12'!$B79,Coding!$B:$B,0)),"") -> 0 | S79: =IF(ISNUMBER(O79),SUM(I79:N79)*2,"") -> 11605.5
A80: 5611-0010 | B80: Refuse Removal | C80: -2083.43 | D80: 0 | E80: 3700.77 | F80: -785.08 | G80: 785.08 | H80: 2053.28 | I80: 0 | J80: 518.94 | K80: 1746.61 | L80: 0 | M80: 0 | N80: 1522.56 | O80: 7458.73 | Q80: =IFERROR(INDEX(Coding!$C:$C,MATCH('T12'!$B80,Coding!$B:$B,0)),"") -> 0 | S80: =IF(ISNUMBER(O80),SUM(I80:N80)*2,"") -> 7576.22
A81: 5611-0040 | B81: Snow Removal | C81: 0 | D81: 0 | E81: 0 | F81: 0 | G81: 0 | H81: 0 | I81: 0 | J81: 0 | K81: 0 | L81: 0 | M81: 0 | N81: 2758.01 | O81: 2758.01 | Q81: =IFERROR(INDEX(Coding!$C:$C,MATCH('T12'!$B81,Coding!$B:$B,0)),"") -> 0 | S81: =IF(ISNUMBER(O81),SUM(I81:N81)*2,"") -> 5516.02
A82: 5611-0041 | B82: Supplies & Small Equipment | C82: 0 | D82: 0 | E82: 0 | F82: 0 | G82: 0 | H82: 0 | I82: 0 | J82: 0 | K82: 0 | L82: 0 | M82: 0 | N82: 628.21 | O82: 628.21 | Q82: =IFERROR(INDEX(Coding!$C:$C,MATCH('T12'!$B82,Coding!$B:$B,0)),"") -> 0 | S82: =IF(ISNUMBER(O82),SUM(I82:N82)*2,"") -> 1256.42
A83: 5611-0074 | B83: Landscaping Repairs/Replacements | C83: -3538.44 | D83: 3538.44 | E83: 4572.75 | F83: -3538.44 | G83: 3538.44 | H83: 3538.44 | I83: 0 | J83: 0 | K83: 3538.44 | L83: 0 | M83: 0 | N83: 3644.59 | O83: 15294.22 | Q83: =IFERROR(INDEX(Coding!$C:$C,MATCH('T12'!$B83,Coding!$B:$B,0)),"") -> 0 | S83: =IF(ISNUMBER(O83),SUM(I83:N83)*2,"") -> 14366.06
A84: 5611-0075 | B84: Interior Landscaping | C84: -435.48 | D84: 762.09 | E84: 1088.7 | F84: -217.74 | G84: 653.22 | H84: 979.83 | I84: 0 | J84: 544.35 | K84: 14701.89 | L84: 0 | M84: 108.87 | N84: 1306.44 | O84: 19492.17 | Q84: =IFERROR(INDEX(Coding!$C:$C,MATCH('T12'!$B84,Coding!$B:$B,0)),"") -> 0 | S84: =IF(ISNUMBER(O84),SUM(I84:N84)*2,"") -> 33323.1
A85: 5611-0085 | B85: Metal Refinishing | C85: -893.33 | D85: 2617.36 | E85: 10469.42 | F85: -5234.7 | G85: 10469.4 | H85: 2617.35 | I85: 0 | J85: 2617.35 | K85: 5234.7 | L85: 0 | M85: 0 | N85: 18286.67 | O85: 46184.22 | Q85: =IFERROR(INDEX(Coding!$C:$C,MATCH('T12'!$B85,Coding!$B:$B,0)),"") -> 0 | S85: =IF(ISNUMBER(O85),SUM(I85:N85)*2,"") -> 52277.44
A86: 5619-9999 | B86: Total Cleaning / Maintenance | C86: -236008.05 | D86: 94376.43 | E86: 495018.29 | F86: -123376.91 | G86: 41756.7 | H86: 415034.74 | I86: -340775.78 | J86: 165447.58 | K86: 537979.34 | L86: -273203.98 | M86: 97280.72 | N86: 455317.9 | O86: 1328847 | Q86: =IFERROR(INDEX(Coding!$C:$C,MATCH('T12'!$B86,Coding!$B:$B,0)),"") -> 0 | S86: =IF(ISNUMBER(O86),SUM(I86:N86)*2,"") -> 1284091.6
A87: 5620-0000 | B87: Security / Fire | Q87: =IFERROR(INDEX(Coding!$C:$C,MATCH('T12'!$B87,Coding!$B:$B,0)),"") -> 0 | S87: =IF(ISNUMBER(O87),SUM(I87:N87)*2,"")
A88: 5620-0010 | B88: Hardware, Glass, Locks | C88: -2482.69 | D88: 1952.66 | E88: 11578.43 | F88: -3388.73 | G88: 0 | H88: 3388.73 | I88: -3388.73 | J88: 0 | K88: 3388.73 | L88: -3388.73 | M88: 166.97 | N88: 16150.73 | O88: 23977.37 | Q88: =IFERROR(INDEX(Coding!$C:$C,MATCH('T12'!$B88,Coding!$B:$B,0)),"") -> 0 | S88: =IF(ISNUMBER(O88),SUM(I88:N88)*2,"") -> 25857.94
A89: 5620-0030 | B89: Security Contract | C89: -177302.35 | D89: 73801.66 | E89: 347167.43 | F89: -93650.61 | G89: 65109.48 | H89: 246925.42 | I89: -202705.19 | J89: 50126.13 | K89: 368982.85 | L89: -100905.51 | M89: 0 | N89: 324965.03 | O89: 902514.34 | Q89: =IFERROR(INDEX(Coding!$C:$C,MATCH('T12'!$B89,Coding!$B:$B,0)),"") -> 0 | S89: =IF(ISNUMBER(O89),SUM(I89:N89)*2,"") -> 880926.62
A90: 5620-0032 | B90: Security - Other | C90: 0 | D90: 0 | E90: -842.82 | F90: 0 | G90: 0 | H90: 425.23 | I90: -425.23 | J90: 0 | K90: 2482.35 | L90: 0 | M90: 0 | N90: 425.23 | O90: 2064.76 | Q90: =IFERROR(INDEX(Coding!$C:$C,MATCH('T12'!$B90,Coding!$B:$B,0)),"") -> 0 | S90: =IF(ISNUMBER(O90),SUM(I90:N90)*2,"") -> 4964.7
A91: 5629-9999 | B91: Total Security | C91: -179785.04 | D91: 75754.32 | E91: 357903.04 | F91: -97039.34 | G91: 65109.48 | H91: 250739.38 | I91: -206519.15 | J91: 50126.13 | K91: 374853.93 | L91: -104294.24 | M91: 166.97 | N91: 341540.99 | O91: 928556.47 | Q91: =IFERROR(INDEX(Coding!$C:$C,MATCH('T12'!$B91,Coding!$B:$B,0)),"") -> 0 | S91: =IF(ISNUMBER(O91),SUM(I91:N91)*2,"") -> 911749.26
A92: 5630-0000 | B92: Fire Protection | Q92: =IFERROR(INDEX(Coding!$C:$C,MATCH('T12'!$B92,Coding!$B:$B,0)),"") -> 0 | S92: =IF(ISNUMBER(O92),SUM(I92:N92)*2,"")
A93: 5630-0050 | B93: Fire Protection | C93: -11905.28 | D93: 0 | E93: 26303.63 | F93: -16008.27 | G93: 16860.45 | H93: 6859.77 | I93: 1210.38 | J93: 3876 | K93: 6456.41 | L93: 228 | M93: 666 | N93: 16132.96 | O93: 50680.05 | Q93: =IFERROR(INDEX(Coding!$C:$C,MATCH('T12'!$B93,Coding!$B:$B,0)),"") -> 0 | S93: =IF(ISNUMBER(O93),SUM(I93:N93)*2,"") -> 57139.5
A94: 5639-9999 | B94: Total Fire Protection | C94: -11905.28 | D94: 0 | E94: 26303.63 | F94: -16008.27 | G94: 16860.45 | H94: 6859.77 | I94: 1210.38 | J94: 3876 | K94: 6456.41 | L94: 228 | M94: 666 | N94: 16132.96 | O94: 50680.05 | Q94: =IFERROR(INDEX(Coding!$C:$C,MATCH('T12'!$B94,Coding!$B:$B,0)),"") -> 0 | S94: =IF(ISNUMBER(O94),SUM(I94:N94)*2,"") -> 57139.5
A95: 5699-9999 | B95: Total Service Contracts | C95: -427698.37 | D95: 170130.75 | E95: 879224.96 | F95: -236424.52 | G95: 123726.63 | H95: 672633.89 | I95: -546084.55 | J95: 219449.71 | K95: 919289.68 | L95: -377270.22 | M95: 98113.69 | N95: 812991.85 | O95: 2308083.5 | Q95: =IFERROR(INDEX(Coding!$C:$C,MATCH('T12'!$B95,Coding!$B:$B,0)),"") -> General and Administrative | S95: =IF(ISNUMBER(O95),SUM(I95:N95)*2,"") -> 2252980.3
A96: 5999-9999 | B96: Total Non Reimbursable Expenses | C96: -384988.52 | D96: 211940.31 | E96: 932419.5 | F96: -206730.52 | G96: 173976.4 | H96: 715923.45 | I96: -500391.87 | J96: 284253.83 | K96: 977216.89 | L96: -344577.19 | M96: 141639.78 | N96: 864005.44 | O96: 2864687.5 | Q96: =IFERROR(INDEX(Coding!$D:$D,MATCH('T12'!$B96,Coding!$B:$B,0)),"") -> 0 | S96: =IF(ISNUMBER(O96),SUM(I96:N96)*2,"") -> 2844293.8
A97: 6100-0000 | B97: Leasing & Promotion | Q97: =IFERROR(INDEX(Coding!$C:$C,MATCH('T12'!$B97,Coding!$B:$B,0)),"") -> 0 | S97: =IF(ISNUMBER(O97),SUM(I97:N97)*2,"")
A98: 6110-0000 | B98: Advertising / Marketing | Q98: =IFERROR(INDEX(Coding!$C:$C,MATCH('T12'!$B98,Coding!$B:$B,0)),"") -> 0 | S98: =IF(ISNUMBER(O98),SUM(I98:N98)*2,"")
A99: 6110-0100 | B99: Advertising | C99: -18000 | D99: 21650 | E99: 9510.2 | F99: -4755.1 | G99: 13455.1 | H99: 8760.2 | I99: 850 | J99: 8760.2 | K99: 23084.7 | L99: 1355.1 | M99: 0 | N99: 29065.3 | O99: 93735.7 | Q99: =IFERROR(INDEX(Coding!$C:$C,MATCH('T12'!$B99,Coding!$B:$B,0)),"") -> 0 | S99: =IF(ISNUMBER(O99),SUM(I99:N99)*2,"") -> 126230.6
A100: 6110-0150 | B100: Community Relations | C100: 0 | D100: 0 | E100: 5860.1 | F100: 435.5 | G100: 435.5 | H100: 837.12 | I100: 0 | J100: 0 | K100: 6590.17 | L100: 0 | M100: 822.04 | N100: 3357.46 | O100: 18337.89 | Q100: =IFERROR(INDEX(Coding!$C:$C,MATCH('T12'!$B100,Coding!$B:$B,0)),"") -> 0 | S100: =IF(ISNUMBER(O100),SUM(I100:N100)*2,"") -> 21539.34
...

Sheet Occupancy Rollup
B3: Residential | D3: Total Units | E3: Occupied Units | F3: Occupancy % | I3: Rollup | J3: % of Property | K3: Occupancy
B4: Quincy | I4: Residential | J4: =J10/J12 -> 0.8677586 | K4: =F6 -> 0
B5: Hollingsworth | I5: Commercial | J5: =J11/J12 -> 0.1322414 | K5: =F12 -> 0
B6: Total | D6: =SUM(D4:D5) -> 0 | E6: =SUM(E4:E5) -> 0 | I6: Wtd. AVG | J6: =SUM(J4:J5) -> 1 | K6: =SUMPRODUCT(J4:J5,K4:K5) -> 0
B9: Commercial | D9: Total SF | E9: Occupied SF | F9: Occupancy % | I9: Property Type | J9: Total SF
B10: Retail | I10: MF | J10: 276979
B11: Parking | I11: Commercial | J11: 42210
B12: Total | D12: =SUM(D10:D11) -> 0 | E12: =SUM(E10:E11) -> 0 | I12: Total | J12: =SUM(J10:J11) -> 319189

Sheet Rent Roll (MF)
B2: Rent Roll
B3: For Selected Properties
B4: As Of = 03/31/2026
B5: Month Year = 03/2026
B6: Unit | C6: Unit Type | D6: Unit | E6: Resident | F6: Name | G6: Market | H6: Actual | I6: Resident | J6: Other | K6: Move In | L6: Lease | M6: Move Out | N6: Balance
D7: Sq Ft | G7: Rent | H7: Rent | I7: Deposit | J7: Deposit | L7: Expiration
B8: Current/Notice/Vacant Residents | P8: 4Q25 Rent
B9: 501 | C9: hw0101 | D9: 461 | E9: t0002659 | F9: Yash Sinha | G9: 4000 | H9: 4050 | I9: 2025 | J9: 0 | K9: 46080 | L9: 46444 | N9: -3626.78 | P9: =+_xlfn.XLOOKUP(F9,'[15]Rent Roll (MF)'!$F:$F,'[15]Rent Roll (MF)'!$H:$H,"x") -> x
B10: 502 | C10: hw1102 | D10: 677 | E10: t0002376 | F10: Shannon Suhendra | G10: 5000 | H10: 5150 | I10: 5150 | J10: 0 | K10: 45888 | L10: 46252 | N10: 50 | P10: =+_xlfn.XLOOKUP(F10,'[15]Rent Roll (MF)'!$F:$F,'[15]Rent Roll (MF)'!$H:$H,"x") -> 5150
B11: 503 | C11: hw1103 | D11: 729 | E11: t0002341 | F11: Giebien Na | G11: 5200 | H11: 5250 | I11: 5250 | J11: 0 | K11: 45897 | L11: 46261 | N11: 0 | P11: =+_xlfn.XLOOKUP(F11,'[15]Rent Roll (MF)'!$F:$F,'[15]Rent Roll (MF)'!$H:$H,"x") -> 5250
B12: 504 | C12: hw0104 | D12: 538 | E12: t0001981 | F12: William Sauser | G12: 3700 | H12: 4275 | I12: 4175 | J12: 0 | K12: 45747 | L12: 46476 | N12: 0 | P12: =+_xlfn.XLOOKUP(F12,'[15]Rent Roll (MF)'!$F:$F,'[15]Rent Roll (MF)'!$H:$H,"x") -> 4175
B13: 505 | C13: hw2105 | D13: 735 | E13: t0002578 | F13: Danyal Khomusi | G13: 6000 | H13: 6000 | I13: 3000 | J13: 0 | K13: 46037 | L13: 46401 | N13: 0 | P13: =+_xlfn.XLOOKUP(F13,'[15]Rent Roll (MF)'!$F:$F,'[15]Rent Roll (MF)'!$H:$H,"x") -> x
B14: 506 | C14: hw1106 | D14: 583 | E14: t0001679 | F14: Miriam George | G14: 5000 | H14: 5100 | I14: 5000 | J14: 0 | K14: 45562 | L14: 46295 | N14: 0 | P14: =+_xlfn.XLOOKUP(F14,'[15]Rent Roll (MF)'!$F:$F,'[15]Rent Roll (MF)'!$H:$H,"x") -> 5100
B15: 507 | C15: hw0107 | D15: 420 | E15: t0002319 | F15: Ishika Kaushal | G15: 3950 | H15: 4100 | I15: 4100 | J15: 0 | K15: 45867 | L15: 46234 | N15: -4225 | P15: =+_xlfn.XLOOKUP(F15,'[15]Rent Roll (MF)'!$F:$F,'[15]Rent Roll (MF)'!$H:$H,"x") -> 4100
B16: 508 | C16: hw1108 | D16: 694 | E16: t0002654 | F16: Ted Chung | G16: 5250 | H16: 5300 | I16: 2650 | J16: 0 | K16: 46087 | L16: 46512 | N16: -750 | P16: =+_xlfn.XLOOKUP(F16,'[15]Rent Roll (MF)'!$F:$F,'[15]Rent Roll (MF)'!$H:$H,"x") -> x
B17: 509 | C17: hw1109 | D17: 698 | E17: VACANT | F17: VACANT | G17: 5400 | H17: 0 | I17: 0 | J17: 0 | N17: 0 | P17: =+_xlfn.XLOOKUP(F17,'[15]Rent Roll (MF)'!$F:$F,'[15]Rent Roll (MF)'!$H:$H,"x") -> 0
B18: 510 | C18: hw1110 | D18: 698 | E18: t0000625 | F18: Marc Stanke | G18: 4000 | H18: 5000 | I18: 4000 | J18: 0 | K18: 45261 | L18: 46326 | N18: 0 | P18: =+_xlfn.XLOOKUP(F18,'[15]Rent Roll (MF)'!$F:$F,'[15]Rent Roll (MF)'!$H:$H,"x") -> 5000
B19: 511 | C19: hw1111 | D19: 698 | E19: t0002411 | F19: Cooper Sherman | G19: 5170 | H19: 5170 | I19: 2585 | J19: 0 | K19: 45915 | L19: 46248 | N19: 0 | P19: =+_xlfn.XLOOKUP(F19,'[15]Rent Roll (MF)'!$F:$F,'[15]Rent Roll (MF)'!$H:$H,"x") -> 5170
B20: 512 | C20: hw0112 | D20: 456 | E20: t0002470 | F20: Kyle Taneja | G20: 3800 | H20: 3650 | I20: 1825 | J20: 0 | K20: 45960 | L20: 46324 | N20: -3775 | P20: =+_xlfn.XLOOKUP(F20,'[15]Rent Roll (MF)'!$F:$F,'[15]Rent Roll (MF)'!$H:$H,"x") -> 3650
B21: 514 | C21: hw1114 | D21: 736 | E21: t0000431 | F21: Chirag Patel | G21: 4000 | H21: 5000 | I21: 0 | J21: 0 | K21: 46055 | L21: 46539 | N21: -2625 | P21: =+_xlfn.XLOOKUP(F21,'[15]Rent Roll (MF)'!$F:$F,'[15]Rent Roll (MF)'!$H:$H,"x") -> 4500
B22: 515 | C22: hw1115 | D22: 523 | E22: t0001636 | F22: Felipe Valderrama | G22: 4750 | H22: 4820 | I22: 4750 | J22: 0 | K22: 45562 | L22: 46295 | N22: 280 | P22: =+_xlfn.XLOOKUP(F22,'[15]Rent Roll (MF)'!$F:$F,'[15]Rent Roll (MF)'!$H:$H,"x") -> 4820
B23: 516 | C23: hw1116 | D23: 662 | E23: t0001609 | F23: Soumya Mishra | G23: 5250 | H23: 5350 | I23: 5250 | J23: 0 | K23: 45541 | L23: 46295 | N23: 0 | P23: =+_xlfn.XLOOKUP(F23,'[15]Rent Roll (MF)'!$F:$F,'[15]Rent Roll (MF)'!$H:$H,"x") -> 5350
B24: 517 | C24: hw2217 | D24: 902 | E24: t0002726 | F24: Byung Park | G24: 8480 | H24: 8480 | I24: 3568.71 | J24: 0 | K24: 46097 | L24: 46461 | N24: -3838.71 | P24: =+_xlfn.XLOOKUP(F24,'[15]Rent Roll (MF)'!$F:$F,'[15]Rent Roll (MF)'!$H:$H,"x") -> x
B25: 518 | C25: hw1118 | D25: 520 | E25: t0000374 | F25: YowJen Chen | G25: 4715 | H25: 4500 | I25: 4409 | J25: 0 | K25: 45139 | L25: 46326 | N25: 0 | P25: =+_xlfn.XLOOKUP(F25,'[15]Rent Roll (MF)'!$F:$F,'[15]Rent Roll (MF)'!$H:$H,"x") -> 4500
B26: 519 | C26: hw0119 | D26: 481 | E26: t0002363 | F26: David Panangian | G26: 4250 | H26: 4000 | I26: 4000 | J26: 0 | K26: 45896 | L26: 46260 | N26: -4125 | P26: =+_xlfn.XLOOKUP(F26,'[15]Rent Roll (MF)'!$F:$F,'[15]Rent Roll (MF)'!$H:$H,"x") -> 4000
B27: 520 | C27: hw0120 | D27: 550 | E27: VACANT | F27: VACANT | G27: 3600 | H27: 0 | I27: 0 | J27: 0 | N27: 0 | P27: =+_xlfn.XLOOKUP(F27,'[15]Rent Roll (MF)'!$F:$F,'[15]Rent Roll (MF)'!$H:$H,"x") -> 0
B28: 601 | C28: hw0101 | D28: 461 | E28: t0002245 | F28: Jordan Lee | G28: 3890 | H28: 4450 | I28: 2225 | J28: 0 | K28: 45849 | L28: 46234 | N28: 0 | P28: =+_xlfn.XLOOKUP(F28,'[15]Rent Roll (MF)'!$F:$F,'[15]Rent Roll (MF)'!$H:$H,"x") -> 4450
B29: 602 | C29: hw1102 | D29: 677 | E29: t0001859 | F29: Alexander Serafine | G29: 5100 | H29: 5150 | I29: 5100 | J29: 0 | K29: 45660 | L29: 46418 | N29: 0 | P29: =+_xlfn.XLOOKUP(F29,'[15]Rent Roll (MF)'!$F:$F,'[15]Rent Roll (MF)'!$H:$H,"x") -> 5100
B30: 603 | C30: hw1103 | D30: 729 | E30: t0000015 | F30: Rina Desai | G30: 5535 | H30: 5400 | I30: 5210 | J30: 0 | K30: 44344 | L30: 46173 | M30: 46144 | N30: -5400 | P30: =+_xlfn.XLOOKUP(F30,'[15]Rent Roll (MF)'!$F:$F,'[15]Rent Roll (MF)'!$H:$H,"x") -> 5400
B31: 604 | C31: hw0104 | D31: 538 | E31: t0001864 | F31: Xueying Li | G31: 4100 | H31: 4150 | I31: 4100 | J31: 0 | K31: 45666 | L31: 46418 | N31: 0 | P31: =+_xlfn.XLOOKUP(F31,'[15]Rent Roll (MF)'!$F:$F,'[15]Rent Roll (MF)'!$H:$H,"x") -> 4100
B32: 605 | C32: hw2105 | D32: 735 | E32: t0002511 | F32: Heung Lam Chang | G32: 6900 | H32: 6000 | I32: 3000 | J32: 0 | K32: 45975 | L32: 46339 | M32: 46148 | N32: -6125 | P32: =+_xlfn.XLOOKUP(F32,'[15]Rent Roll (MF)'!$F:$F,'[15]Rent Roll (MF)'!$H:$H,"x") -> 6000
B33: 606 | C33: hw1106 | D33: 583 | E33: VACANT | F33: VACANT | G33: 5370 | H33: 0 | I33: 0 | J33: 0 | N33: 0 | P33: =+_xlfn.XLOOKUP(F33,'[15]Rent Roll (MF)'!$F:$F,'[15]Rent Roll (MF)'!$H:$H,"x") -> 0
B34: 607 | C34: hw0107 | D34: 420 | E34: t0002340 | F34: Mona Patel | G34: 3740 | H34: 4000 | I34: 4000 | J34: 0 | K34: 45876 | L34: 46240 | N34: -4125 | P34: =+_xlfn.XLOOKUP(F34,'[15]Rent Roll (MF)'!$F:$F,'[15]Rent Roll (MF)'!$H:$H,"x") -> 4000
B35: 608 | C35: hw1108 | D35: 694 | E35: t0000004 | F35: Erik Peterson | G35: 5295 | H35: 5150 | I35: 4870 | J35: 0 | K35: 44065 | L35: 46630 | N35: 0 | P35: =+_xlfn.XLOOKUP(F35,'[15]Rent Roll (MF)'!$F:$F,'[15]Rent Roll (MF)'!$H:$H,"x") -> 5150
B36: 609 | C36: hw1109 | D36: 698 | E36: t0001929 | F36: David Booth | G36: 5300 | H36: 5250 | I36: 5250 | J36: 0 | K36: 45712 | L36: 46446 | N36: 0 | P36: =+_xlfn.XLOOKUP(F36,'[15]Rent Roll (MF)'!$F:$F,'[15]Rent Roll (MF)'!$H:$H,"x") -> 5250
B37: 610 | C37: hw1110 | D37: 698 | E37: t0002684 | F37: Lawrence Goldberg | G37: 5300 | H37: 5420 | I37: 2710 | J37: 0 | K37: 46072 | L37: 46436 | N37: -3314.65 | P37: =+_xlfn.XLOOKUP(F37,'[15]Rent Roll (MF)'!$F:$F,'[15]Rent Roll (MF)'!$H:$H,"x") -> x
B38: 611 | C38: hw1111 | D38: 698 | E38: t0002306 | F38: Rhaíza Garanovschi Peres Ceolim | G38: 5000 | H38: 5400 | I38: 5400 | J38: 0 | K38: 45870 | L38: 46234 | N38: -5525 | P38: =+_xlfn.XLOOKUP(F38,'[15]Rent Roll (MF)'!$F:$F,'[15]Rent Roll (MF)'!$H:$H,"x") -> 5400
B39: 612 | C39: hw0112 | D39: 456 | E39: t0001960 | F39: Hanah Jun | G39: 4100 | H39: 4000 | I39: 4000 | J39: 0 | K39: 45747 | L39: 46111 | M39: 46122 | N39: 0 | P39: =+_xlfn.XLOOKUP(F39,'[15]Rent Roll (MF)'!$F:$F,'[15]Rent Roll (MF)'!$H:$H,"x") -> 4000
B40: 614 | C40: hw1114 | D40: 736 | E40: t0002307 | F40: Brenna Chitkara | G40: 5400 | H40: 5550 | I40: 5550 | J40: 0 | K40: 45880 | L40: 46245 | N40: 0 | P40: =+_xlfn.XLOOKUP(F40,'[15]Rent Roll (MF)'!$F:$F,'[15]Rent Roll (MF)'!$H:$H,"x") -> 5550
B41: 615 | C41: hw1115 | D41: 523 | E41: t0002715 | F41: Eesh Dadheech | G41: 4750 | H41: 4900 | I41: 2450 | J41: 0 | K41: 46079 | L41: 46502 | N41: -6686.61 | P41: =+_xlfn.XLOOKUP(F41,'[15]Rent Roll (MF)'!$F:$F,'[15]Rent Roll (MF)'!$H:$H,"x") -> x
B42: 616 | C42: hw1116 | D42: 662 | E42: t0002303 | F42: Michael Belle | G42: 5235 | H42: 5400 | I42: 5400 | J42: 0 | K42: 45884 | L42: 46248 | N42: -5525 | P42: =+_xlfn.XLOOKUP(F42,'[15]Rent Roll (MF)'!$F:$F,'[15]Rent Roll (MF)'!$H:$H,"x") -> 5400
B43: 617 | C43: hw2217 | D43: 902 | E43: DOWN | F43: DOWN | G43: 8125 | H43: 0 | I43: 0 | J43: 0 | N43: 0 | P43: =+_xlfn.XLOOKUP(F43,'[15]Rent Roll (MF)'!$F:$F,'[15]Rent Roll (MF)'!$H:$H,"x") -> 0
B44: 618 | C44: hw1118 | D44: 520 | E44: t0002367 | F44: Kathleen Humato | G44: 4740 | H44: 4800 | I44: 4800 | J44: 0 | K44: 45904 | L44: 46268 | N44: 0 | P44: =+_xlfn.XLOOKUP(F44,'[15]Rent Roll (MF)'!$F:$F,'[15]Rent Roll (MF)'!$H:$H,"x") -> 4800
B45: 619 | C45: hw0119 | D45: 481 | E45: t0002463 | F45: David Wang | G45: 4700 | H45: 3950 | I45: 1975 | J45: 0 | K45: 45940 | L45: 46274 | N45: 0 | P45: =+_xlfn.XLOOKUP(F45,'[15]Rent Roll (MF)'!$F:$F,'[15]Rent Roll (MF)'!$H:$H,"x") -> 3950
B46: 620 | C46: hw0120 | D46: 550 | E46: t0002524 | F46: Saara Sondej | G46: 4250 | H46: 4000 | I46: 2000 | J46: 0 | K46: 45992 | L46: 46356 | N46: 0 | P46: =+_xlfn.XLOOKUP(F46,'[15]Rent Roll (MF)'!$F:$F,'[15]Rent Roll (MF)'!$H:$H,"x") -> 4000
B47: 701 | C47: hw0101 | D47: 461 | E47: t0001883 | F47: Sofia Boucher | G47: 4000 | H47: 4050 | I47: 4000 | J47: 0 | K47: 45681 | L47: 46418 | N47: 0 | P47: =+_xlfn.XLOOKUP(F47,'[15]Rent Roll (MF)'!$F:$F,'[15]Rent Roll (MF)'!$H:$H,"x") -> 4000
B48: 702 | C48: hw1102 | D48: 677 | E48: t0000633 | F48: Jesse Luo | G48: 5265 | H48: 4120 | I48: 4050 | J48: 0 | K48: 45237 | L48: 46356 | N48: 0 | P48: =+_xlfn.XLOOKUP(F48,'[15]Rent Roll (MF)'!$F:$F,'[15]Rent Roll (MF)'!$H:$H,"x") -> 4120
B49: 703 | C49: hw1103 | D49: 729 | E49: t0001439 | F49: Kreesha Khanna | G49: 5250 | H49: 5500 | I49: 5250 | J49: 0 | K49: 45505 | L49: 46234 | N49: 0 | P49: =+_xlfn.XLOOKUP(F49,'[15]Rent Roll (MF)'!$F:$F,'[15]Rent Roll (MF)'!$H:$H,"x") -> 5500
B50: 704 | C50: hw0104 | D50: 538 | E50: t0002325 | F50: Dhanishk Gummadi | G50: 4360 | H50: 4200 | I50: 4200 | J50: 0 | K50: 45873 | L50: 46237 | N50: 0 | P50: =+_xlfn.XLOOKUP(F50,'[15]Rent Roll (MF)'!$F:$F,'[15]Rent Roll (MF)'!$H:$H,"x") -> 4200
B51: 705 | C51: hw2105 | D51: 735 | E51: t0000338 | F51: Jessica Shin | G51: 6670 | H51: =+P51 -> 6850 | I51: 0 | J51: 0 | K51: 45102 | L51: 46203 | M51: 46113 | N51: 0 | P51: =+_xlfn.XLOOKUP(F51,'[15]Rent Roll (MF)'!$F:$F,'[15]Rent Roll (MF)'!$H:$H,"x") -> 6850
B52: 706 | C52: hw1106 | D52: 583 | E52: t0002267 | F52: Zijian Han | G52: 5100 | H52: 5450 | I52: 2725 | J52: 0 | K52: 45846 | L52: 46234 | N52: -1008.88 | P52: =+_xlfn.XLOOKUP(F52,'[15]Rent Roll (MF)'!$F:$F,'[15]Rent Roll (MF)'!$H:$H,"x") -> 5450
B53: 707 | C53: hw0107 | D53: 420 | E53: t0001341 | F53: Sebastiane Caballes | G53: 3950 | H53: 4200 | I53: 3950 | J53: 0 | K53: 45463 | L53: 46203 | N53: 0 | P53: =+_xlfn.XLOOKUP(F53,'[15]Rent Roll (MF)'!$F:$F,'[15]Rent Roll (MF)'!$H:$H,"x") -> 4200
B54: 708 | C54: hw1108 | D54: 694 | E54: t0000849 | F54: Amara Sarao | G54: 4800 | H54: 5100 | I54: 4800 | J54: 0 | K54: 45337 | L54: 46630 | N54: 0 | P54: =+_xlfn.XLOOKUP(F54,'[15]Rent Roll (MF)'!$F:$F,'[15]Rent Roll (MF)'!$H:$H,"x") -> 5100
B55: 709 | C55: hw1109 | D55: 698 | E55: t0002486 | F55: Kenny Kang | G55: 5320 | H55: 5450 | I55: 2725 | J55: 0 | K55: 45978 | L55: 46342 | N55: -5575 | P55: =+_xlfn.XLOOKUP(F55,'[15]Rent Roll (MF)'!$F:$F,'[15]Rent Roll (MF)'!$H:$H,"x") -> 5450
B56: 710 | C56: hw1110 | D56: 698 | E56: t0001657 | F56: Matthew Zelinger | G56: 5250 | H56: 5500 | I56: 5250 | J56: 0 | K56: 45559 | L56: 46295 | N56: 0 | P56: =+_xlfn.XLOOKUP(F56,'[15]Rent Roll (MF)'!$F:$F,'[15]Rent Roll (MF)'!$H:$H,"x") -> 5500
B57: 711 | C57: hw1111 | D57: 698 | E57: t0002614 | F57: Ben Baler | G57: 5320 | H57: 5330 | I57: 2665 | J57: 0 | K57: 46066 | L57: 46611 | N57: -2087.86 | P57: =+_xlfn.XLOOKUP(F57,'[15]Rent Roll (MF)'!$F:$F,'[15]Rent Roll (MF)'!$H:$H,"x") -> x
B58: 712 | C58: hw0112 | D58: 456 | E58: t0002398 | F58: Akash Salam | G58: 3850 | H58: 4175 | I58: 2087 | J58: 0 | K58: 45910 | L58: 46274 | N58: 0 | P58: =+_xlfn.XLOOKUP(F58,'[15]Rent Roll (MF)'!$F:$F,'[15]Rent Roll (MF)'!$H:$H,"x") -> 4175
B59: 714 | C59: hw1114 | D59: 736 | E59: t0002462 | F59: Kaartik Jain | G59: 5450 | H59: 5475 | I59: 2737.5 | J59: 0 | K59: 45945 | L59: 46279 | N59: 0 | P59: =+_xlfn.XLOOKUP(F59,'[15]Rent Roll (MF)'!$F:$F,'[15]Rent Roll (MF)'!$H:$H,"x") -> 5475
B60: 715 | C60: hw1115 | D60: 523 | E60: t0001771 | F60: Oluwafemi Otitoju | G60: 4800 | H60: 4857 | I60: 4800 | J60: 0 | K60: 45609 | L60: 46446 | N60: 0 | P60: =+_xlfn.XLOOKUP(F60,'[15]Rent Roll (MF)'!$F:$F,'[15]Rent Roll (MF)'!$H:$H,"x") -> 4857
B61: 716 | C61: hw1116 | D61: 662 | E61: t0001979 | F61: Defne Ungun | G61: 5260 | H61: 5400 | I61: 5400 | J61: 0 | K61: 45722 | L61: 46477 | N61: -5625 | P61: =+_xlfn.XLOOKUP(F61,'[15]Rent Roll (MF)'!$F:$F,'[15]Rent Roll (MF)'!$H:$H,"x") -> 5400
B62: 717 | C62: hw2217 | D62: 902 | E62: t0001610 | F62: Ryan Rivera | G62: 7500 | H62: 7900 | I62: 7500 | J62: 0 | K62: 45561 | L62: 46295 | N62: 0 | P62: =+_xlfn.XLOOKUP(F62,'[15]Rent Roll (MF)'!$F:$F,'[15]Rent Roll (MF)'!$H:$H,"x") -> 7900
B63: 718 | C63: hw1118 | D63: 520 | E63: t0002042 | F63: Miranda Piroonhapat | G63: 4550 | H63: 4700 | I63: 4700 | J63: 0 | K63: 45778 | L63: 46203 | N63: 0 | P63: =+_xlfn.XLOOKUP(F63,'[15]Rent Roll (MF)'!$F:$F,'[15]Rent Roll (MF)'!$H:$H,"x") -> 4700
B64: 719 | C64: hw0119 | D64: 481 | E64: t0001639 | F64: Kubanychbek Maripbek | G64: 3900 | H64: 3950 | I64: 3900 | J64: 0 | K64: 45562 | L64: 46295 | N64: 0 | P64: =+_xlfn.XLOOKUP(F64,'[15]Rent Roll (MF)'!$F:$F,'[15]Rent Roll (MF)'!$H:$H,"x") -> 3950
B65: 720 | C65: hw0120 | D65: 550 | E65: VACANT | F65: VACANT | G65: 4650 | H65: 0 | I65: 0 | J65: 0 | N65: 0 | P65: =+_xlfn.XLOOKUP(F65,'[15]Rent Roll (MF)'!$F:$F,'[15]Rent Roll (MF)'!$H:$H,"x") -> 0
B66: 801 | C66: hw0101 | D66: 461 | E66: t0002537 | F66: Oleksiy Fedorov | G66: 4000 | H66: 4100 | I66: 2050 | J66: 0 | K66: 46003 | L66: 46367 | M66: 46176 | N66: -4225 | P66: =+_xlfn.XLOOKUP(F66,'[15]Rent Roll (MF)'!$F:$F,'[15]Rent Roll (MF)'!$H:$H,"x") -> 4100
B67: 802 | C67: hw1102 | D67: 677 | E67: t0001957 | F67: Aditya Raju | G67: 4600 | H67: 5300 | I67: 5300 | J67: 0 | K67: 45714 | L67: 46446 | N67: -5425 | P67: =+_xlfn.XLOOKUP(F67,'[15]Rent Roll (MF)'!$F:$F,'[15]Rent Roll (MF)'!$H:$H,"x") -> 5300
B68: 803 | C68: hw1103 | D68: 729 | E68: t0002373 | F68: Jahaan Turkhud | G68: 5000 | H68: 5100 | I68: 5100 | J68: 0 | K68: 45894 | L68: 46258 | N68: -5225 | P68: =+_xlfn.XLOOKUP(F68,'[15]Rent Roll (MF)'!$F:$F,'[15]Rent Roll (MF)'!$H:$H,"x") -> 5100
B69: 804 | C69: hw0104 | D69: 538 | E69: t0002011 | F69: Lilly Xu | G69: 3800 | H69: 4175 | I69: 4175 | J69: 0 | K69: 45747 | L69: 46477 | N69: -4400 | P69: =+_xlfn.XLOOKUP(F69,'[15]Rent Roll (MF)'!$F:$F,'[15]Rent Roll (MF)'!$H:$H,"x") -> 4175
B70: 805 | C70: hw2105 | D70: 735 | E70: t0002480 | F70: Charles Blondeau Andrews | G70: 7000 | H70: 6588 | I70: 3294 | J70: 0 | K70: 45953 | L70: 46317 | N70: -6713 | P70: =+_xlfn.XLOOKUP(F70,'[15]Rent Roll (MF)'!$F:$F,'[15]Rent Roll (MF)'!$H:$H,"x") -> 6588
B71: 806 | C71: hw1106 | D71: 583 | E71: t0001558 | F71: Emily Steirman | G71: 5000 | H71: 5100 | I71: 5000 | J71: 0 | K71: 45524 | L71: 46265 | N71: -5275 | P71: =+_xlfn.XLOOKUP(F71,'[15]Rent Roll (MF)'!$F:$F,'[15]Rent Roll (MF)'!$H:$H,"x") -> 5100
B72: 807 | C72: hw0107 | D72: 420 | E72: t0000999 | F72: Daniel Choo | G72: 4200 | H72: 4300 | I72: 4200 | J72: 0 | K72: 45397 | L72: 46142 | M72: 46142 | N72: -4425 | P72: =+_xlfn.XLOOKUP(F72,'[15]Rent Roll (MF)'!$F:$F,'[15]Rent Roll (MF)'!$H:$H,"x") -> 4300
B73: 808 | C73: hw1108 | D73: 694 | E73: t0002285 | F73: Eric Xu | G73: 5500 | H73: 5600 | I73: 5600 | J73: 0 | K73: 45870 | L73: 46234 | N73: 0 | P73: =+_xlfn.XLOOKUP(F73,'[15]Rent Roll (MF)'!$F:$F,'[15]Rent Roll (MF)'!$H:$H,"x") -> 5600
B74: 809 | C74: hw1109 | D74: 698 | E74: t0001550 | F74: Yunah Ko | G74: 5300 | H74: 5500 | I74: 5300 | J74: 0 | K74: 45533 | L74: 46265 | N74: 0 | P74: =+_xlfn.XLOOKUP(F74,'[15]Rent Roll (MF)'!$F:$F,'[15]Rent Roll (MF)'!$H:$H,"x") -> 5500
B75: 810 | C75: hw1110 | D75: 698 | E75: t0002304 | F75: Alexander Sahni | G75: 5345 | H75: 5600 | I75: 2800 | J75: 0 | K75: 45861 | L75: 46234 | N75: 5725 | P75: =+_xlfn.XLOOKUP(F75,'[15]Rent Roll (MF)'!$F:$F,'[15]Rent Roll (MF)'!$H:$H,"x") -> 5600
B76: 811 | C76: hw1111 | D76: 698 | E76: t0002343 | F76: Jamile Simao | G76: 5345 | H76: 5475 | I76: 5475 | J76: 0 | K76: 45887 | L76: 46251 | N76: -5600 | P76: =+_xlfn.XLOOKUP(F76,'[15]Rent Roll (MF)'!$F:$F,'[15]Rent Roll (MF)'!$H:$H,"x") -> 5475
B77: 812 | C77: hw0112 | D77: 456 | E77: t0002465 | F77: Sarah Cohen | G77: 3900 | H77: 3850 | I77: 1925 | J77: 0 | K77: 45954 | L77: 46318 | N77: 0 | P77: =+_xlfn.XLOOKUP(F77,'[15]Rent Roll (MF)'!$F:$F,'[15]Rent Roll (MF)'!$H:$H,"x") -> 3850
B78: 814 | C78: hw1114 | D78: 736 | E78: t0000711 | F78: Stephanie Schmidt | G78: 4500 | H78: 4550 | I78: 4500 | J78: 0 | K78: 45275 | L78: 46752 | N78: 0 | P78: =+_xlfn.XLOOKUP(F78,'[15]Rent Roll (MF)'!$F:$F,'[15]Rent Roll (MF)'!$H:$H,"x") -> 4500
B79: 815 | C79: hw1115 | D79: 523 | E79: t0002246 | F79: Jingxian Pan | G79: 4835 | H79: 5150 | I79: 5150 | J79: 0 | K79: 45838 | L79: 46202 | N79: 0 | P79: =+_xlfn.XLOOKUP(F79,'[15]Rent Roll (MF)'!$F:$F,'[15]Rent Roll (MF)'!$H:$H,"x") -> 5150
B80: 816 | C80: hw1116 | D80: 662 | E80: t0002345 | F80: Vivien Hevizi | G80: 5100 | H80: 5220 | I80: 5220 | J80: 0 | K80: 45882 | L80: 46246 | N80: -5345 | P80: =+_xlfn.XLOOKUP(F80,'[15]Rent Roll (MF)'!$F:$F,'[15]Rent Roll (MF)'!$H:$H,"x") -> 5220
B81: 817 | C81: hw2217 | D81: 902 | E81: t0002500 | F81: Tejo Tunuguntla | G81: 8000 | H81: 7000 | I81: 3500 | J81: 0 | K81: 45964 | L81: 46295 | N81: 0 | P81: =+_xlfn.XLOOKUP(F81,'[15]Rent Roll (MF)'!$F:$F,'[15]Rent Roll (MF)'!$H:$H,"x") -> 7000
B82: 818 | C82: hw1118 | D82: 520 | E82: VACANT | F82: VACANT | G82: 4800 | H82: 0 | I82: 0 | J82: 0 | N82: 0 | P82: =+_xlfn.XLOOKUP(F82,'[15]Rent Roll (MF)'!$F:$F,'[15]Rent Roll (MF)'!$H:$H,"x") -> 0
B83: 819 | C83: hw0119 | D83: 481 | E83: t0002692 | F83: Sriniketa Gunampalli | G83: 4100 | H83: 4000 | I83: 2000 | J83: 0 | K83: 46080 | L83: 46444 | N83: -3580.36 | P83: =+_xlfn.XLOOKUP(F83,'[15]Rent Roll (MF)'!$F:$F,'[15]Rent Roll (MF)'!$H:$H,"x") -> x
B84: 820 | C84: hw0120 | D84: 550 | E84: t0001366 | F84: Samantha Kost | G84: 3950 | H84: 4100 | I84: 3950 | J84: 0 | K84: 45488 | L84: 46234 | N84: -4225 | P84: =+_xlfn.XLOOKUP(F84,'[15]Rent Roll (MF)'!$F:$F,'[15]Rent Roll (MF)'!$H:$H,"x") -> 4100
B85: 901 | C85: hw0101 | D85: 461 | E85: t0002765 | F85: Rishabh Jain | G85: 4275 | H85: 4200 | I85: 2100 | J85: 0 | K85: 46111 | L85: 46475 | N85: -8120.97 | P85: =+_xlfn.XLOOKUP(F85,'[15]Rent Roll (MF)'!$F:$F,'[15]Rent Roll (MF)'!$H:$H,"x") -> 7750
B86: 902 | C86: hw1102 | D86: 677 | E86: t0000284 | F86: Jehanzeb Kayani | G86: 5315 | H86: =+P86 -> 5300 | I86: 5125 | J86: 0 | K86: 45047 | L86: 46203 | M86: 46203 | N86: 0 | P86: =+_xlfn.XLOOKUP(F86,'[15]Rent Roll (MF)'!$F:$F,'[15]Rent Roll (MF)'!$H:$H,"x") -> 5300
B87: 903 | C87: hw1103 | D87: 729 | E87: t0000401 | F87: Sara Rosas Ruiz | G87: 4800 | H87: 5150 | I87: 0 | J87: 0 | K87: 45169 | L87: 46265 | N87: 0 | P87: =+_xlfn.XLOOKUP(F87,'[15]Rent Roll (MF)'!$F:$F,'[15]Rent Roll (MF)'!$H:$H,"x") -> 5150
B88: 904 | C88: hw0104 | D88: 538 | E88: t0002036 | F88: Andrew Zhang | G88: 3550 | H88: 4175 | I88: 4175 | J88: 0 | K88: 45754 | L88: 46507 | N88: 0 | P88: =+_xlfn.XLOOKUP(F88,'[15]Rent Roll (MF)'!$F:$F,'[15]Rent Roll (MF)'!$H:$H,"x") -> 4175
B89: 905 | C89: hw2105 | D89: 735 | E89: t0002545 | F89: Mehul Sreenivas | G89: 6500 | H89: 6050 | I89: 3025 | J89: 0 | K89: 46027 | L89: 46391 | N89: -3316.07 | P89: =+_xlfn.XLOOKUP(F89,'[15]Rent Roll (MF)'!$F:$F,'[15]Rent Roll (MF)'!$H:$H,"x") -> x
B90: 906 | C90: hw1106 | D90: 583 | E90: t0002660 | F90: Jake Landers | G90: 5100 | H90: 4995 | I90: 2498.5 | J90: 0 | K90: 46076 | L90: 46440 | M90: 46171 | N90: 0 | P90: =+_xlfn.XLOOKUP(F90,'[15]Rent Roll (MF)'!$F:$F,'[15]Rent Roll (MF)'!$H:$H,"x") -> x
B91: 907 | C91: hw0107 | D91: 420 | E91: t0002360 | F91: Richard Liang | G91: 4250 | H91: 4000 | I91: 4000 | J91: 0 | K91: 45902 | L91: 46234 | N91: -4125 | P91: =+_xlfn.XLOOKUP(F91,'[15]Rent Roll (MF)'!$F:$F,'[15]Rent Roll (MF)'!$H:$H,"x") -> 4000
B92: 908 | C92: hw1108 | D92: 694 | E92: t0000424 | F92: Melanie Iovino | G92: 5370 | H92: 5500 | I92: 5374 | J92: 0 | K92: 45226 | L92: 46326 | N92: -5625 | P92: =+_xlfn.XLOOKUP(F92,'[15]Rent Roll (MF)'!$F:$F,'[15]Rent Roll (MF)'!$H:$H,"x") -> 5500
B93: 909 | C93: hw1109 | D93: 698 | E93: t0000831 | F93: Nur Bulbuloglu | G93: 5500 | H93: 5800 | I93: 5500 | J93: 0 | K93: 45337 | L93: 46446 | N93: -5925 | P93: =+_xlfn.XLOOKUP(F93,'[15]Rent Roll (MF)'!$F:$F,'[15]Rent Roll (MF)'!$H:$H,"x") -> 5750
B94: 910 | C94: hw1110 | D94: 698 | E94: t0001951 | F94: David Wang | G94: 4150 | H94: 5300 | I94: 5300 | J94: 0 | K94: 45712 | L94: 46446 | N94: 5475 | P94: =+_xlfn.XLOOKUP(F94,'[15]Rent Roll (MF)'!$F:$F,'[15]Rent Roll (MF)'!$H:$H,"x") -> 3950
B95: 911 | C95: hw1111 | D95: 698 | E95: t0002709 | F95: Zong Ming Shen | G95: 5400 | H95: 5400 | I95: 2700 | J95: 0 | K95: 46112 | L95: 46476 | N95: -8100 | P95: =+_xlfn.XLOOKUP(F95,'[15]Rent Roll (MF)'!$F:$F,'[15]Rent Roll (MF)'!$H:$H,"x") -> x
B96: 912 | C96: hw0112 | D96: 456 | E96: t0002385 | F96: Christopher Fifty | G96: 3950 | H96: 3850 | I96: 3850 | J96: 0 | K96: 45915 | L96: 46279 | M96: 46162 | N96: -3975 | P96: =+_xlfn.XLOOKUP(F96,'[15]Rent Roll (MF)'!$F:$F,'[15]Rent Roll (MF)'!$H:$H,"x") -> 3850
B97: 914 | C97: hw1114 | D97: 736 | E97: t0002485 | F97: Nicholas Atwood | G97: 5700 | H97: 5500 | I97: 2750 | J97: 0 | K97: 45952 | L97: 46316 | N97: 0 | P97: =+_xlfn.XLOOKUP(F97,'[15]Rent Roll (MF)'!$F:$F,'[15]Rent Roll (MF)'!$H:$H,"x") -> 5500
B98: 915 | C98: hw1115 | D98: 523 | E98: t0002047 | F98: sulagshan raveendrakumar | G98: 4860 | H98: 4900 | I98: 4900 | J98: 0 | K98: 45775 | L98: 46507 | N98: 0 | P98: =+_xlfn.XLOOKUP(F98,'[15]Rent Roll (MF)'!$F:$F,'[15]Rent Roll (MF)'!$H:$H,"x") -> 4900
B99: 916 | C99: hw1116 | D99: 662 | E99: t0002287 | F99: Stanley Wong | G99: 5310 | H99: 5500 | I99: 5500 | J99: 0 | K99: 45877 | L99: 46234 | N99: 0 | P99: =+_xlfn.XLOOKUP(F99,'[15]Rent Roll (MF)'!$F:$F,'[15]Rent Roll (MF)'!$H:$H,"x") -> 5500
B100: 917 | C100: hw2217 | D100: 902 | E100: t0002192 | F100: Lauren Thomas | G100: 8800 | H100: 8500 | I100: 8500 | J100: 0 | K100: 45839 | L100: 46203 | N100: -8625 | P100: =+_xlfn.XLOOKUP(F100,'[15]Rent Roll (MF)'!$F:$F,'[15]Rent Roll (MF)'!$H:$H,"x") -> 8500
B101: 918 | C101: hw1118 | D101: 520 | E101: t0002619 | F101: Yohan Mamane | G101: 5000 | H101: 4300 | I101: 2150 | J101: 0 | K101: 46029 | L101: 46393 | N101: -4425 | P101: =+_xlfn.XLOOKUP(F101,'[15]Rent Roll (MF)'!$F:$F,'[15]Rent Roll (MF)'!$H:$H,"x") -> 0
...

Sheet Rent Roll (COMM)
B2: Rent Roll
B3: Property: 990conso From Date: 03/31/2026 By Property
B4: Property | C4: Unit(s) | D4: Lease | E4: Lease Type | F4: Area | G4: Lease From | H4: Lease To | I4: Term | J4: Monthly | K4: Annual
J5: Rent | K5: Rent | M5: 46112
M6: WALT
B7: 990comvb - VBG 990 AOA LLC,New York
B8: Current Leases
B9: 990comvb | C9: 980A | D9: 980 FOOD CORP. | E9: Retail | F9: 823 | G9: 44964 | H9: 48944 | I9: 131 | J9: 25855.29 | K9: =+J9*12 -> 310263.48 | M9: =(H9-$M$5)/365 -> 7.7589041
B10: 990comvb | C10: 980B | D10: Sanmiwago 980 Inc. | E10: Retail | F10: 799 | G10: 45166 | H10: 50801 | I10: 186 | J10: 25076.58 | K10: =+J10*12 -> 300918.96 | M10: =(H10-$M$5)/365 -> 12.846575
B11: 990comvb | C11: 980C | D11: Daebak Shinhwa Inc | E11: Retail | F11: 931 | G11: 44679 | H11: 48610 | I11: 130 | J11: 35513.63 | K11: =+J11*12 -> 426163.56 | M11: =(H11-$M$5)/365 -> 6.8438356
B12: 990comvb | C12: 986 | D12: OAKBERRY MIDTOWN EAST LLC | E12: Retail | F12: 466 | G12: 45078 | H12: 48852 | I12: 124 | J12: 14852.6 | K12: =+J12*12 -> 178231.2 | M12: =(H12-$M$5)/365 -> 7.5068493
B13: 990comvb | C13: 988 | D13: Teso Mini | E13: Retail | F13: 1606 | G13: 45204 | H13: 48975 | I13: 124 | J13: 32357.45 | K13: =+J13*12 -> 388289.4 | M13: =(H13-$M$5)/365 -> 7.8438356
B14: 990comvb | C14: 992 | D14: I Milky Management INC | E14: Retail | F14: 558 | G14: 43770 | H14: 47879 | I14: 135 | J14: 19433.2 | K14: =+J14*12 -> 233198.4 | M14: =(H14-$M$5)/365 -> 4.8410959
B15: 990comvb | C15: 994 | D15: Krispy Kreme Doughnut Corporation # 205 | E15: Retail | F15: 557 | G15: 43585 | H15: 49368 | I15: 191 | J15: 19398.37 | K15: =+J15*12 -> 232780.44 | M15: =(H15-$M$5)/365 -> 8.9205479
B16: 990comvb | C16: 996 | D16: Panks Private Corporation | E16: Retail | F16: 2077 | G16: 43617 | H16: 47452 | I16: 126 | J16: 58739 | K16: =+J16*12 -> 704868 | M16: =(H16-$M$5)/365 -> 3.6712329
B17: 990comvb | C17: 1I-MEZZ | D17: VACANT | F17: 870 | I17: 0 | J17: 0 | K17: =+J17*12 -> 0
B18: Total Current | F18: =+SUM(F9:F17) -> 8687 | J18: =+SUM(J9:J17) -> 231226.12 | K18: =+SUM(K9:K17) -> 2774713.4 | M18: =SUMPRODUCT(M9:M16,F9:F16)/SUM(F9:F16) -> 6.960755
B21: 990prkvb - VBG 990 AOA LLC,New York
B22: Current Leases | N22: Comm Occupancy | O22: =SUM(F9:F16)/F18 -> 0.89985035
B23: 990prkvb | C23: 1H | D23: 990 6th Avenue Garage LLC | E23: Parking | F23: 33523 | G23: 44129 | H23: 46477 | I23: 78 | J23: 50000 | K23: 600000
B24: Total Current | F24: 33523 | J24: 50000 | K24: 600000

Sheet Insurance
H1: 25/26 Premium | I1: 605061
H4: From | I4: 45930
H5: To | I5: =+I4+365 -> 46295

Sheet RE Tax
J1: ="Taxes paid through" & TEXT(' OSAR'!$G$6," mm/dd/yyy") -> Taxes paid through 12/31/2025 | K1: 3441526.6
AD2: Taxes due: | AE2: 0
J3: 45839 | K3: From
J4: =+J3+364 -> 46203 | K4: To

Sheet UW
B1: IP & MTM CASH FLOW
B2: Quincy & Hollingsworth
B3: Investment Year | C3: T-12 | D3: T-12 | E3: T-12 | F3: In-Place | G3: Comments | H3: MTM | I3: Comments | K3: 1 | L3: 1 | M3: 1 | N3: 2 | O3: 3 | P3: 4 | Q3: 5 | R3: 6 | S3: 7 | T3: 8 | U3: 9 | V3: 10 | W3: 11 | X3: 12 | Y3: 13 | Z3: 14 | AA3: 15 | AB3: 16 | AC3: 17 | AD3: 18 | AE3: 19 | AF3: 20 | AG3: 21 | AJ3: T-12 | AK3: T-12 Manual | AL3: T-6 Annualized | AM3: T-3 Annualized
B4: Year Ending | K4: $/SF | L4: $/Unit | M4: 46295 | N4: 46660 | O4: 47026 | P4: 47391 | Q4: 47756 | R4: 48121 | S4: 48487 | T4: 48852 | U4: 49217 | V4: 49582 | W4: 49948 | X4: 50313 | Y4: 50678 | Z4: 51043 | AA4: 51409 | AB4: 51774 | AC4: 52139 | AD4: 52504 | AE4: 52870 | AF4: 53235 | AG4: N/A
M5: 107.09866 | N5: 112.11664 | O5: 115.48014 | P5: 118.94454 | Q5: 122.51288 | R5: 126.18826 | S5: 129.97391
B6: INCOME | C6: $/SF | D6: $/Unit | E6: $ Gross | F6: $ Gross | H6: $ Gross | K6: $/SF | L6: $/Unit | AP6: UW Year 1 | AQ6: Current | AS6: VAR % | AT6: VAR $
B7: Potential Rental Revenue | C7: 79.142305 | D7: 48179.226 | E7: 21921548 | F7: 28640482 | G7: 103.39935 | H7: 30534159 | I7: 110.236 | K7: 107.13964 | L7: 65223.083 | M7: 29676503 | N7: 31066959 | O7: 31998968 | P7: 32958937 | Q7: 33947705 | R7: 34966136 | S7: 36015120 | T7: 37095574 | U7: 38208441 | V7: 39354695 | W7: 40535335 | X7: 41751395 | Y7: 0 | Z7: 0 | AA7: 0 | AB7: 0 | AC7: 0 | AD7: 0 | AE7: 0 | AF7: 0 | AG7: 0 | AJ7: 21921548 | AK7: 0 | AL7: 23103085 | AM7: 24571451
B8: Loss To Lease | C8: 0 | D8: 0 | E8: 0 | F8: 0 | G8: - | H8: 0 | I8: - | K8: -2.2911194 | L8: -1394.758 | M8: -634614.88 | N8: -553282.57 | O8: -429447.79 | P8: -442331.22 | Q8: -455601.16 | R8: -469269.19 | S8: -483347.27 | T8: -497847.69 | U8: -512783.12 | V8: -528166.61 | W8: -544011.61 | X8: -560331.96 | Y8: 0 | Z8: 0 | AA8: 0 | AB8: 0 | AC8: 0 | AD8: 0 | AE8: 0 | AF8: 0 | AG8: 0 | AJ8: 0 | AK8: 0 | AL8: 0 | AM8: 0 | AO8: INCOME:
A9: Gross Potential Rent (3) | B9: Scheduled Base Rental Revenue | C9: 79.142305 | D9: 48179.226 | E9: 21921548 | F9: 28640482 | H9: 30534159 | K9: 104.84852 | L9: 63828.325 | M9: 29041888 | N9: 30513677 | O9: 31569520 | P9: 32516606 | Q9: 33492104 | R9: 34496867 | S9: 35531773 | T9: 36597726 | U9: 37695658 | V9: 38826528 | W9: 39991324 | X9: 41191064 | Y9: 0 | Z9: 0 | AA9: 0 | AB9: 0 | AC9: 0 | AD9: 0 | AE9: 0 | AF9: 0 | AG9: 0 | AJ9: 21921548 | AK9: 0 | AL9: 23103085 | AM9: 24571451 | AO9: Number of Mos. Covered
A10: Commercial Income | B10: Commerical Income | D10: 6597.3025 | E10: 3001772.6 | F10: 2816135.1 | G10: Year 1 | H10: 2816135.1 | I10: Year 1 | K10: 10.166956 | L10: 6189.3079 | M10: 2816135.1 | N10: 3061480.5 | O10: 3196818.9 | P10: 3349627.2 | Q10: 3551449.5 | R10: 3525657.3 | S10: 3635641.8 | T10: 3744711.1 | U10: 3857052.4 | V10: 3972764 | W10: 4091946.9 | X10: 4214705.3 | AO10: Period Ended
A11: Other Income | B11: Other Income | C11: 5.6840306 | D11: 3460.2504 | E11: 1574413.9 | F11: 2125510.6 | G11: Year 1 | H11: 2125510.6 | I11: Year 1 | K11: 7.6736281 | L11: 4671.4518 | M11: 2125510.6 | N11: 2189275.9 | O11: 2254954.2 | P11: 2322602.8 | Q11: 2392280.9 | R11: 2464049.3 | S11: 2537970.8 | T11: 2614109.9 | U11: 2692533.2 | V11: 2773309.2 | W11: 6948455.4 | X11: 7156909 | Y11: 0 | Z11: 0 | AA11: 0 | AB11: 0 | AC11: 0 | AD11: 0 | AE11: 0 | AF11: 0 | AG11: 0 | AJ11: 4576186.6 | AK11: 0 | AL11: 4615272.4 | AM11: 4352092.8 | AO11: Statement Ending Date
B12: Potential Gross Income | C12: 95.66349 | D12: 58236.779 | E12: 26497735 | F12: 33582127 | H12: 35475805 | K12: 122.68911 | L12: 74689.085 | M12: 33983534 | N12: 35764433 | O12: 37021293 | P12: 38188836 | Q12: 39435834 | R12: 40486574 | S12: 41705386 | T12: 42956547 | U12: 44245244 | V12: 45572601 | W12: 51031726 | X12: 52562678 | Y12: 0 | Z12: 0 | AA12: 0 | AB12: 0 | AC12: 0 | AD12: 0 | AE12: 0 | AF12: 0 | AG12: 0 | AJ12: 26497735 | AK12: 0 | AL12: 27718357 | AM12: 28923544 | AO12: Gross Potential Rent (3) | AP12: =SUMIF(A:A,$AO12,$M:$M) -> 29041888 | AQ12: =SUMIF(' OSAR'!D:D,UW!$AO12,' OSAR'!O:O) -> 27270606 | AS12: =IFERROR(IF(ISNUMBER(AT12),AT12/AP12,""),"") -> -0.060990588 | AT12: =IF(ISNUMBER(AQ12),AQ12-AP12,"") -> -1771281.8
A13: Less: Vacancy Loss | B13: Minus: Vacancy | C13: 0 | D13: 0 | E13: 0 | F13: -1674366.6 | G13: 0.058461538 | H13: -916024.77 | I13: 0.03 | K13: -3.1454557 | L13: -1914.8497 | M13: -871256.63 | N13: -915410.3 | O13: -947085.61 | P13: -975498.18 | Q13: -1004763.1 | R13: -1034906 | S13: -1065953.2 | T13: -1097931.8 | U13: -1130869.7 | V13: -1164795.8 | W13: -1199739.7 | X13: -1235731.9 | Y13: 0 | Z13: 0 | AA13: 0 | AB13: 0 | AC13: 0 | AD13: 0 | AE13: 0 | AF13: 0 | AG13: 0 | AJ13: 0 | AK13: 0 | AL13: 0 | AM13: 0 | AO13: Less: Vacancy Loss | AP13: =SUMIF(A:A,$AO13,$M:$M) -> -871256.63 | AQ13: =SUMIF(' OSAR'!D:D,UW!$AO13,' OSAR'!O:O) -> 0 | AS13: =IF(ISNUMBER(AT13),AT13/AP13,"") -> -1 | AT13: =IF(ISNUMBER(AQ13),AQ13-AP13,"") -> 871256.63
A14: Other Income | B14: Minus: Credit Loss | C14: -0.54869204 | D14: -334.02563 | E14: -151981.66 | F14: -151981.66 | G14: 0.005306533 | H14: -76335.398 | I14: 0.0025 | K14: -0.26212131 | L14: -159.57081 | M14: -72604.72 | N14: -76284.192 | O14: -78923.801 | P14: -81291.515 | Q14: -83730.26 | R14: -86242.168 | S14: -88829.433 | T14: -91494.316 | U14: -94239.146 | V14: -97066.32 | W14: -99978.309 | X14: -102977.66 | Y14: 0 | Z14: 0 | AA14: 0 | AB14: 0 | AC14: 0 | AD14: 0 | AE14: 0 | AF14: 0 | AG14: 0 | AJ14: -151981.66 | AK14: 0 | AL14: -192131.98 | AM14: -536000.12 | AO14: OR | AP14: =SUMIF(A:A,$AO14,$M:$M) -> 0 | AS14: =IF(ISNUMBER(AT14),AT14/AP14,"") | AT14: =IF(ISNUMBER(AQ14),AQ14-AP14,"")
A15: Other Income | B15: Minus: Model Unit | C15: -0.38990718 | D15: -237.36264 | E15: -108000 | F15: -62946.113 | G15: 1 | H15: -67108.042 | I15: 1 | K15: -0.23043632 | L15: -140.28203 | M15: -63828.325 | N15: -67063.026 | O15: -69383.561 | P15: -71465.068 | Q15: -73609.02 | R15: -75817.291 | S15: -78091.809 | T15: -80434.564 | U15: -82847.6 | V15: -85333.028 | W15: -87893.019 | X15: -90529.81 | Y15: 0 | Z15: 0 | AA15: 0 | AB15: 0 | AC15: 0 | AD15: 0 | AE15: 0 | AF15: 0 | AG15: 0 | AJ15: -108000 | AK15: 0 | AL15: -108000 | AM15: -108000 | AO15: Commercial Income | AP15: =SUMIF(A:A,$AO15,$M:$M) -> 2816135.1 | AQ15: =SUMIF(' OSAR'!D:D,UW!$AO15,' OSAR'!O:O) -> 2774713.4 | AS15: =IFERROR(IF(ISNUMBER(AT15),AT15/AP15,""),"") -> -0.014708691 | AT15: =IF(ISNUMBER(AQ15),AQ15-AP15,"") -> -41421.66
A16: Other Income | B16: Minus: Concessions Initial Lease Up | C16: -9.4885566 | D16: -5776.3205 | E16: -2628225.8 | F16: 0 | G16: - | H16: 0 | I16: - | K16: 0 | L16: 0 | M16: 0 | N16: 0 | O16: 0 | P16: 0 | Q16: 0 | R16: 0 | S16: 0 | T16: 0 | U16: 0 | V16: 0 | W16: 0 | X16: 0 | Y16: 0 | Z16: 0 | AA16: 0 | AB16: 0 | AC16: 0 | AD16: 0 | AE16: 0 | AF16: 0 | AG16: 0 | AJ16: -2628225.8 | AK16: 0 | AL16: -2703024.5 | AM16: -2540778 | AO16: Less: Vacancy Loss © | AP16: =SUMIF(A:A,$AO16,$M:$M) -> 0 | AQ16: =SUMIF(' OSAR'!D:D,UW!$AO16,' OSAR'!O:O) -> 0 | AS16: =IFERROR(IF(ISNUMBER(AT16),AT16/AP16,""),"") | AT16: =IF(ISNUMBER(AQ16),AQ16-AP16,"") -> 0
A17: Other Income | B17: Minus: Concessions Ongoing | C17: 0 | D17: 0 | E17: 0 | F17: -2540778 | G17: 1.0645539 | H17: 0 | I17: 0 | K17: -13.017589 | L17: -7924.6789 | M17: -3605728.9 | N17: -1941626.9 | O17: 0 | P17: 0 | Q17: 0 | R17: 0 | S17: 0 | T17: 0 | U17: 0 | V17: 0 | W17: 0 | X17: 0 | Y17: 0 | Z17: 0 | AA17: 0 | AB17: 0 | AC17: 0 | AD17: 0 | AE17: 0 | AF17: 0 | AG17: 0 | AJ17: 0 | AK17: 0 | AL17: 0 | AM17: 0 | AO17: Laundry/Vending Income | AP17: =SUMIF(A:A,$AO17,$M:$M) -> 0 | AQ17: =SUMIF(' OSAR'!D:D,UW!$AO17,' OSAR'!O:O) -> 0 | AS17: =IFERROR(IF(ISNUMBER(AT17),AT17/AP17,""),"") | AT17: =IF(ISNUMBER(AQ17),AQ17-AP17,"") -> 0
B18: Effective Gross Income | C18: 85.236335 | D18: 51889.07 | E18: 23609527 | F18: 29152055 | H18: 34416336 | K18: 106.03351 | L18: 64549.703 | M18: 29370115 | N18: 32764049 | O18: 35925900 | P18: 37060581 | Q18: 38273732 | R18: 39289608 | S18: 40472511 | T18: 41686687 | U18: 42937287 | V18: 44225406 | W18: 49644115 | X18: 51133438 | Y18: 0 | Z18: 0 | AA18: 0 | AB18: 0 | AC18: 0 | AD18: 0 | AE18: 0 | AF18: 0 | AG18: 0 | AJ18: 23609527 | AK18: 0 | AL18: 24715201 | AM18: 25738766 | AO18: Parking Income | AP18: =SUMIF(A:A,$AO18,$M:$M) -> 0 | AQ18: =SUMIF(' OSAR'!D:D,UW!$AO18,' OSAR'!O:O) -> 600000 | AS18: =IFERROR(IF(ISNUMBER(AT18),AT18/AP18,""),"") | AT18: =IF(ISNUMBER(AQ18),AQ18-AP18,"") -> 600000
M19: 0.007480093 | N19: 0.11555739 | O19: 0.096503693 | P19: 0.031583919 | Q19: 0.032734266 | R19: 0.026542389 | AO19: Other Income | AP19: =SUMIF(A:A,$AO19,$M:$M) -> -1616651.4 | AQ19: =SUMIF(' OSAR'!D:D,UW!$AO19,' OSAR'!O:O) -> -230307.58 | AS19: =IFERROR(IF(ISNUMBER(AT19),AT19/AP19,""),"") -> -0.85754035 | AT19: =IF(ISNUMBER(AQ19),AQ19-AP19,"") -> 1386343.8
B20: OPERATING EXPENSES | C20: $/SF | D20: $/Unit | E20: $ Gross | F20: $ Gross | H20: $ Gross | K20: $/SF | L20: $/Unit | AS20: =IF(ISNUMBER(AT20),AT20/AP20,"") | AT20: =IF(ISNUMBER(AQ20),AQ20-AP20,"")
A21: Payroll & Benefits | B21: Payroll | C21: 1.8652456 | D21: 1135.5 | E21: 516652.5 | F21: 628788.67 | G21: Year 1 | H21: 628788.67 | I21: Year 1 | K21: 2.2700854 | L21: 1381.9531 | M21: 628788.67 | N21: 647652.33 | O21: 667081.9 | P21: 687094.36 | Q21: 707707.19 | R21: 728938.41 | S21: 750806.56 | T21: 773330.76 | U21: 796530.68 | V21: 820426.6 | W21: 845039.4 | X21: 870390.58 | Y21: 0 | Z21: 0 | AA21: 0 | AB21: 0 | AC21: 0 | AD21: 0 | AE21: 0 | AF21: 0 | AG21: 0 | AJ21: 516652.5 | AK21: 0 | AL21: 300552.52 | AM21: 298921.16 | AO21: *Effective Gross Income | AP21: =SUM(AP12:AP19) -> 29370115 | AQ21: =SUM(AQ12:AQ19) -> 30415012 | AS21: =IFERROR(IF(ISNUMBER(AT21),AT21/AP21,""),"") -> 0.035576876 | AT21: =IF(ISNUMBER(AQ21),AQ21-AP21,"") -> 1044896.9
B22: Employee Units | C22: 0 | D22: 0 | E22: 0 | F22: 0 | G22: Year 1 | H22: 0 | I22: Year 1 | K22: 0 | L22: 0 | M22: 0 | N22: 0 | O22: 0 | P22: 0 | Q22: 0 | R22: 0 | S22: 0 | T22: 0 | U22: 0 | V22: 0 | W22: 0 | X22: 0 | Y22: 0 | Z22: 0 | AA22: 0 | AB22: 0 | AC22: 0 | AD22: 0 | AE22: 0 | AF22: 0 | AG22: 0 | AJ22: 0 | AK22: 0 | AL22: 0 | AM22: 0 | AS22: =IF(ISNUMBER(AT22),AT22/AP22,"") | AT22: =IF(ISNUMBER(AQ22),AQ22-AP22,"")
A23: Advertising & Marketing | B23: Marketing | C23: 0.8439851 | D23: 513.79031 | E23: 233774.59 | F23: 105422.37 | G23: Year 1 | H23: 105422.37 | I23: Year 1 | K23: 0.38060128 | L23: 231.69751 | M23: 105422.37 | N23: 108585.04 | O23: 111842.59 | P23: 115197.87 | Q23: 118653.8 | R23: 122213.42 | S23: 125879.82 | T23: 129656.22 | U23: 133545.9 | V23: 137552.28 | W23: 141678.85 | X23: 145929.21 | Y23: 0 | Z23: 0 | AA23: 0 | AB23: 0 | AC23: 0 | AD23: 0 | AE23: 0 | AF23: 0 | AG23: 0 | AJ23: 233774.59 | AK23: 0 | AL23: 122914.18 | AM23: 94312.56 | AS23: =IF(ISNUMBER(AT23),AT23/AP23,"") | AT23: =IF(ISNUMBER(AQ23),AQ23-AP23,"")
A24: General and Administrative | B24: General & Admin. | C24: 1.2472661 | D24: 759.29446 | E24: 345478.98 | F24: 230687.46 | G24: Year 1 | H24: 230687.46 | I24: Year 1 | K24: 0.83283977 | L24: 507.0054 | M24: 230687.46 | N24: 237608.08 | O24: 244736.32 | P24: 252078.41 | Q24: 259640.76 | R24: 267429.99 | S24: 275452.89 | T24: 283716.47 | U24: 292227.97 | V24: 300994.81 | W24: 310024.65 | X24: 319325.39 | Y24: 0 | Z24: 0 | AA24: 0 | AB24: 0 | AC24: 0 | AD24: 0 | AE24: 0 | AF24: 0 | AG24: 0 | AJ24: 345478.98 | AK24: 0 | AL24: 418691.58 | AM24: 406850.28 | AO24: OPERATING EXPENSES: | AS24: =IFERROR(IF(ISNUMBER(AT24),AT24/AP24,""),"") | AT24: =IF(ISNUMBER(AQ24),AQ24-AP24,"")
B25: Miscellaneous | C25: 0 | D25: 0 | E25: 0 | F25: 0 | G25: Year 1 | H25: 0 | I25: Year 1 | K25: 0 | L25: 0 | M25: 0 | N25: 0 | O25: 0 | P25: 0 | Q25: 0 | R25: 0 | S25: 0 | T25: 0 | U25: 0 | V25: 0 | W25: 0 | X25: 0 | Y25: 0 | Z25: 0 | AA25: 0 | AB25: 0 | AC25: 0 | AD25: 0 | AE25: 0 | AF25: 0 | AG25: 0 | AJ25: 0 | AK25: 0 | AL25: 0 | AM25: 0 | AO25: Real Estate Taxes | AS25: =IFERROR(IF(ISNUMBER(AT25),AT25/AP25,""),"") | AT25: =IF(ISNUMBER(AQ25),AQ25-AP25,"")
B26: Landscaping/Grounds | C26: 0 | D26: 0 | E26: 0 | F26: 0 | G26: Year 1 | H26: 0 | I26: Year 1 | K26: 0 | L26: 0 | M26: 0 | N26: 0 | O26: 0 | P26: 0 | Q26: 0 | R26: 0 | S26: 0 | T26: 0 | U26: 0 | V26: 0 | W26: 0 | X26: 0 | Y26: 0 | Z26: 0 | AA26: 0 | AB26: 0 | AC26: 0 | AD26: 0 | AE26: 0 | AF26: 0 | AG26: 0 | AJ26: 0 | AK26: 0 | AL26: 0 | AM26: 0 | AO26: Property Insurance | AS26: =IFERROR(IF(ISNUMBER(AT26),AT26/AP26,""),"") | AT26: =IF(ISNUMBER(AQ26),AQ26-AP26,"")
B27: Make-ready | C27: 0 | D27: 0 | E27: 0 | F27: 0 | G27: Year 1 | H27: 0 | I27: Year 1 | K27: 0 | L27: 0 | M27: 0 | N27: 0 | O27: 0 | P27: 0 | Q27: 0 | R27: 0 | S27: 0 | T27: 0 | U27: 0 | V27: 0 | W27: 0 | X27: 0 | Y27: 0 | Z27: 0 | AA27: 0 | AB27: 0 | AC27: 0 | AD27: 0 | AE27: 0 | AF27: 0 | AG27: 0 | AJ27: 0 | AK27: 0 | AL27: 0 | AM27: 0 | AO27: Utilities | AS27: =IFERROR(IF(ISNUMBER(AT27),AT27/AP27,""),"") | AT27: =IF(ISNUMBER(AQ27),AQ27-AP27,"")
A28: Repairs and Maintenance | B28: Repairs & Maint. | C28: 2.7912309 | D28: 1699.2093 | E28: 773140.25 | F28: 658885.75 | G28: Year 1 | H28: 658885.75 | I28: Year 1 | K28: 2.3787434 | L28: 1448.1005 | M28: 658885.75 | N28: 678652.32 | O28: 699011.89 | P28: 719982.25 | Q28: 741581.71 | R28: 763829.16 | S28: 786744.04 | T28: 810346.36 | U28: 834656.75 | V28: 859696.45 | W28: 885487.35 | X28: 912051.97 | Y28: 0 | Z28: 0 | AA28: 0 | AB28: 0 | AC28: 0 | AD28: 0 | AE28: 0 | AF28: 0 | AG28: 0 | AJ28: 773140.25 | AK28: 0 | AL28: 571985.88 | AM28: 633759.64 | AO28: Real Estate Taxes | AP28: =SUMIF(A:A,$AO28,$M:$M) -> 7092817.1 | AQ28: =SUMIF(' OSAR'!D:D,UW!$AO28,' OSAR'!O:O) -> 6802665.6 | AS28: =IFERROR(IF(ISNUMBER(AT28),AT28/AP28,""),"") -> -0.040907792 | AT28: =IF(ISNUMBER(AQ28),AQ28-AP28,"") -> -290151.49
A29: General and Administrative | B29: Janitorial | C29: 4.7233394 | D29: 2875.4133 | E29: 1308313.1 | F29: 1057734 | G29: Year 1 | H29: 1057734 | I29: Year 1 | K29: 3.8186861 | L29: 2324.6902 | M29: 1057734 | N29: 1089466.1 | O29: 1122150 | P29: 1155814.5 | Q29: 1190489 | R29: 1226203.7 | S29: 1262989.8 | T29: 1300879.5 | U29: 1339905.8 | V29: 1380103 | W29: 1421506.1 | X29: 1464151.3 | Y29: 0 | Z29: 0 | AA29: 0 | AB29: 0 | AC29: 0 | AD29: 0 | AE29: 0 | AF29: 0 | AG29: 0 | AJ29: 1308313.1 | AK29: 0 | AL29: 1325578.8 | AM29: 1413546.7 | AO29: Property Insurance | AP29: =SUMIF(A:A,$AO29,$M:$M) -> 662281.56 | AQ29: =SUMIF(' OSAR'!D:D,UW!$AO29,' OSAR'!O:O) -> 651481 | AS29: =IFERROR(IF(ISNUMBER(AT29),AT29/AP29,""),"") -> -0.016308114 | AT29: =IF(ISNUMBER(AQ29),AQ29-AP29,"") -> -10800.563
A30: General and Administrative | B30: Security/Life Safety | C30: 2.8077034 | D30: 1709.2373 | E30: 777702.96 | F30: 758148 | G30: Year 1 | H30: 758148 | I30: Year 1 | K30: 2.7371051 | L30: 1666.2593 | M30: 758148 | N30: 780892.44 | O30: 804319.22 | P30: 828448.79 | Q30: 853302.26 | R30: 878901.32 | S30: 905268.36 | T30: 932426.41 | U30: 960399.21 | V30: 989211.18 | W30: 1018887.5 | X30: 1049454.1 | Y30: 0 | Z30: 0 | AA30: 0 | AB30: 0 | AC30: 0 | AD30: 0 | AE30: 0 | AF30: 0 | AG30: 0 | AJ30: 777702.96 | AK30: 0 | AL30: 944260.76 | AM30: 1073082.7 | AO30: Utilities | AP30: =SUMIF(A:A,$AO30,$M:$M) -> 1133802.4 | AQ30: =SUMIF(' OSAR'!D:D,UW!$AO30,' OSAR'!O:O) -> 1344132.8 | AS30: =IFERROR(IF(ISNUMBER(AT30),AT30/AP30,""),"") -> 0.18550889 | AT30: =IF(ISNUMBER(AQ30),AQ30-AP30,"") -> 210330.42
A31: Utilities | B31: Utilities | C31: 3.3075394 | D31: 2013.5209 | E31: 916152.02 | F31: 1133802.4 | G31: Year 1 | H31: 1133802.4 | I31: Year 1 | K31: 4.0933119 | L31: 2491.8733 | M31: 1133802.4 | N31: 1167816.4 | O31: 1202850.9 | P31: 1238936.5 | Q31: 1276104.6 | R31: 1314387.7 | S31: 1353819.3 | T31: 1394433.9 | U31: 1436266.9 | V31: 1479354.9 | W31: 1523735.6 | X31: 1569447.6 | Y31: 0 | Z31: 0 | AA31: 0 | AB31: 0 | AC31: 0 | AD31: 0 | AE31: 0 | AF31: 0 | AG31: 0 | AJ31: 916152.02 | AK31: 0 | AL31: 808211.8 | AM31: 1253498 | AO31: Repairs and Maintenance | AP31: =SUMIF(A:A,$AO31,$M:$M) -> 658885.75 | AQ31: =SUMIF(' OSAR'!D:D,UW!$AO31,' OSAR'!O:O) -> 781368.51 | AS31: =IFERROR(IF(ISNUMBER(AT31),AT31/AP31,""),"") -> 0.18589378 | AT31: =IF(ISNUMBER(AQ31),AQ31-AP31,"") -> 122482.76
A32: Property Insurance | B32: Insurance | C32: 2.3819379 | D32: 1450.0453 | E32: 659770.59 | F32: 662281.56 | G32: Year 1 | H32: 662281.56 | I32: Year 1 | K32: 2.3910031 | L32: 1455.5639 | M32: 662281.56 | N32: 682150.01 | O32: 702614.51 | P32: 723692.95 | Q32: 745403.73 | R32: 767765.85 | S32: 790798.82 | T32: 814522.79 | U32: 838958.47 | V32: 864127.22 | W32: 890051.04 | X32: 916752.57 | Y32: 0 | Z32: 0 | AA32: 0 | AB32: 0 | AC32: 0 | AD32: 0 | AE32: 0 | AF32: 0 | AG32: 0 | AJ32: 659770.59 | AK32: 0 | AL32: 689234.86 | AM32: 770428.68 | AO32: Management Fees | AP32: =SUMIF(A:A,$AO32,$M:$M) -> 734252.87 | AQ32: =SUMIF(' OSAR'!D:D,UW!$AO32,' OSAR'!O:O) -> 760375.3 | AS32: =IFERROR(IF(ISNUMBER(AT32),AT32/AP32,""),"") -> 0.035576876 | AT32: =IF(ISNUMBER(AQ32),AQ32-AP32,"") -> 26122.423
B33: Misc #1 | C33: 0 | D33: 0 | E33: 0 | F33: 0 | G33: Year 1 | H33: 0 | I33: Year 1 | K33: 0 | L33: 0 | M33: 0 | N33: 0 | O33: 0 | P33: 0 | Q33: 0 | R33: 0 | S33: 0 | T33: 0 | U33: 0 | V33: 0 | W33: 0 | X33: 0 | Y33: 0 | Z33: 0 | AA33: 0 | AB33: 0 | AC33: 0 | AD33: 0 | AE33: 0 | AF33: 0 | AG33: 0 | AJ33: 0 | AK33: 0 | AL33: 0 | AM33: 0 | AO33: Payroll & Benefits | AP33: =SUMIF(A:A,$AO33,$M:$M) -> 628788.67 | AQ33: =SUMIF(' OSAR'!D:D,UW!$AO33,' OSAR'!O:O) -> 321346.34 | AS33: =IFERROR(IF(ISNUMBER(AT33),AT33/AP33,""),"") -> -0.48894382 | AT33: =IF(ISNUMBER(AQ33),AQ33-AP33,"") -> -307442.33
B34: Misc #2 | C34: 0 | D34: 0 | E34: 0 | F34: 0 | G34: Year 1 | H34: 0 | I34: Year 1 | K34: 0 | L34: 0 | M34: 0 | N34: 0 | O34: 0 | P34: 0 | Q34: 0 | R34: 0 | S34: 0 | T34: 0 | U34: 0 | V34: 0 | W34: 0 | X34: 0 | Y34: 0 | Z34: 0 | AA34: 0 | AB34: 0 | AC34: 0 | AD34: 0 | AE34: 0 | AF34: 0 | AG34: 0 | AJ34: 0 | AK34: 0 | AL34: 0 | AM34: 0 | AO34: Advertising & Marketing | AP34: =SUMIF(A:A,$AO34,$M:$M) -> 105422.37 | AQ34: =SUMIF(' OSAR'!D:D,UW!$AO34,' OSAR'!O:O) -> 112073.59 | AS34: =IFERROR(IF(ISNUMBER(AT34),AT34/AP34,""),"") -> 0.063091182 | AT34: =IF(ISNUMBER(AQ34),AQ34-AP34,"") -> 6651.2218
B35: Replacement Reserve | F35: 113750 | G35: 250 | H35: 113750 | I35: 250 | AO35: Professional Fees | AP35: =SUMIF(A:A,$AO35,$M:$M) -> 0 | AQ35: =SUMIF(' OSAR'!D:D,UW!$AO35,' OSAR'!O:O) -> 171187.81 | AS35: =IFERROR(IF(ISNUMBER(AT35),AT35/AP35,""),"") | AT35: =IF(ISNUMBER(AQ35),AQ35-AP35,"") -> 171187.81
A36: Real Estate Taxes | B36: RE Taxes | C36: 23.82507 | D36: 14503.917 | E36: 6599282.4 | F36: 7092817.1 | G36: Year 1 | H36: 7092817.1 | I36: Year 1 | K36: 25.606855 | L36: 15588.609 | M36: 7092817.1 | N36: 7863968.6 | O36: 9066051.6 | P36: 9603826.9 | Q36: 9950260 | R36: 10212008 | S36: 10519539 | T36: 10835125 | U36: 11160179 | V36: 11494984 | W36: 11839834 | X36: 12195029 | Y36: 0 | Z36: 0 | AA36: 0 | AB36: 0 | AC36: 0 | AD36: 0 | AE36: 0 | AF36: 0 | AG36: 0 | AJ36: 6599282.4 | AK36: 0 | AL36: 6598901 | AM36: 6596901 | AO36: General and Administrative | AP36: =SUMIF(A:A,$AO36,$M:$M) -> 2046569.5 | AQ36: =SUMIF(' OSAR'!D:D,UW!$AO36,' OSAR'!O:O) -> 2604757 | AS36: =IFERROR(IF(ISNUMBER(AT36),AT36/AP36,""),"") -> 0.27274299 | AT36: =IF(ISNUMBER(AQ36),AQ36-AP36,"") -> 558187.49
A37: Management Fees | B37: Management Fee | C37: 1.2326346 | D37: 750.3873 | E37: 341426.22 | F37: 728801.37 | G37: 0.025 | H37: 860408.41 | I37: 0.025 | K37: 2.6508377 | L37: 1613.7426 | M37: 734252.87 | N37: 819101.22 | O37: 898147.51 | P37: 926514.53 | Q37: 956843.3 | R37: 982240.21 | S37: 1011812.8 | T37: 1042167.2 | U37: 1073432.2 | V37: 1105635.1 | W37: 1138804.2 | X37: 1172968.3 | Y37: 0 | Z37: 0 | AA37: 0 | AB37: 0 | AC37: 0 | AD37: 0 | AE37: 0 | AF37: 0 | AG37: 0 | AJ37: 341426.22 | AK37: 0 | AL37: 348480.26 | AM37: 357365.16 | AO37: Other Expenses | AP37: =SUMIF(A:A,$AO37,$M:$M) -> 0 | AQ37: =SUMIF(' OSAR'!D:D,UW!$AO37,' OSAR'!O:O) -> 0 | AS37: =IFERROR(IF(ISNUMBER(AT37),AT37/AP37,""),"") | AT37: =IF(ISNUMBER(AQ37),AQ37-AP37,"") -> 0
B38: Total Operating Expenses | C38: 45.025952 | D38: 27410.315 | E38: 12471694 | F38: 13171119 | H38: 13302726 | K38: 47.160068 | L38: 28709.495 | M38: 13062820 | N38: 14075893 | O38: 15518807 | P38: 16251587 | Q38: 16799986 | R38: 17263918 | S38: 17783111 | T38: 18316605 | U38: 18866103 | V38: 19432086 | W38: 20015048 | X38: 20615500 | Y38: 0 | Z38: 0 | AA38: 0 | AB38: 0 | AC38: 0 | AD38: 0 | AE38: 0 | AF38: 0 | AG38: 0 | AJ38: 12471694 | AK38: 0 | AL38: 12128812 | AM38: 12898666 | AO38: Ground Rent | AP38: =SUMIF(A:A,$AO38,$M:$M) -> 0 | AQ38: =SUMIF(' OSAR'!D:D,UW!$AO38,' OSAR'!O:O) -> 0 | AS38: =IFERROR(IF(ISNUMBER(AT38),AT38/AP38,""),"") | AT38: =IF(ISNUMBER(AQ38),AQ38-AP38,"") -> 0
B39: Operating Expenses % EGR | E39: 0.52824834 | F39: 0.45180756 | H39: 0.38652358 | M39: 0.44476572 | N39: 0.42961395 | O39: 0.43196709 | P39: 0.43851409 | Q39: 0.43894299 | R39: 0.43940162 | S39: 0.43938739 | T39: 0.43938739 | U39: 0.43938739 | V39: 0.43938739 | W39: 0.40317062 | X39: 0.40317062 | Y39: 0 | Z39: 0 | AA39: 0 | AB39: 0 | AC39: 0 | AD39: 0 | AE39: 0 | AF39: 0 | AG39: 0 | AS39: =IF(ISNUMBER(AT39),AT39/AP39,"") | AT39: =IF(ISNUMBER(AQ39),AQ39-AP39,"")
B40: Real Estate Taxes %/EGR | E40: 0.27951777 | F40: 0.24330419 | H40: 0.20608867 | M40: 0.24149777 | N40: 0.24001822 | O40: 0.25235419 | P40: 0.2591386 | Q40: 0.25997622 | R40: 0.25991626 | S40: 0.25991812 | T40: 0.25991812 | U40: 0.25991812 | V40: 0.25991812 | W40: 0.2384942 | X40: 0.2384942 | Y40: 0 | Z40: 0 | AA40: 0 | AB40: 0 | AC40: 0 | AD40: 0 | AE40: 0 | AF40: 0 | AG40: 0 | AS40: =IF(ISNUMBER(AT40),AT40/AP40,"") | AT40: =IF(ISNUMBER(AQ40),AQ40-AP40,"")
AO41: *Total Operating Expenses | AP41: =SUM(AP28:AP38) -> 13062820 | AQ41: =SUM(AQ28:AQ38) -> 13549388 | AS41: =IF(ISNUMBER(AT41),AT41/AP41,"") -> 0.037248291 | AT41: =IF(ISNUMBER(AQ41),AQ41-AP41,"") -> 486567.73
B42: Net Operating Income | C42: 40.210382 | D42: 24478.755 | E42: 11137834 | F42: 15980936 | H42: 21113611 | K42: 58.873438 | L42: 35840.208 | M42: 16307295 | N42: 18688156 | O42: 20407094 | P42: 20808994 | Q42: 21473746 | R42: 22025691 | S42: 22689400 | T42: 23370082 | U42: 24071185 | V42: 24793320 | W42: 29629067 | X42: 30517939 | Y42: 0 | Z42: 0 | AA42: 0 | AB42: 0 | AC42: 0 | AD42: 0 | AE42: 0 | AF42: 0 | AG42: 0 | AJ42: 11137834 | AK42: 0 | AL42: 12586389 | AM42: 12840100 | AS42: =IF(ISNUMBER(AT42),AT42/AP42,"") | AT42: =IF(ISNUMBER(AQ42),AQ42-AP42,"")
AO43: Operating Expense Ratio | AP43: =AP41/AP21 -> 0.44476572 | AQ43: =AQ41/AQ21 -> 0.44548357 | AS43: =IF(ISNUMBER(AT43),AT43/AP43,"") -> 0.0016139945 | AT43: =IF(ISNUMBER(AQ43),AQ43-AP43,"") -> 0.00071784943
B44: Below the line OpEx | C44: 0 | D44: 0 | E44: 0 | K44: 0 | L44: 0 | M44: 0 | N44: 0 | O44: 0 | P44: 0 | Q44: 0 | R44: 0 | S44: 0 | T44: 0 | U44: 0 | V44: 0 | W44: 0 | X44: 0 | Y44: 0 | Z44: 0 | AA44: 0 | AB44: 0 | AC44: 0 | AD44: 0 | AE44: 0 | AF44: 0 | AG44: 0 | AJ44: 0 | AK44: 0 | AL44: 0 | AM44: 0 | AS44: =IF(ISNUMBER(AT44),AT44/AP44,"") | AT44: =IF(ISNUMBER(AQ44),AQ44-AP44,"")
B45: Adjusted Net Operating Income | C45: 40.210382 | D45: 24478.755 | E45: 11137834 | K45: 58.873438 | L45: 35840.208 | M45: 16307295 | N45: 18688156 | O45: 20407094 | P45: 20808994 | Q45: 21473746 | R45: 22025691 | S45: 22689400 | T45: 23370082 | U45: 24071185 | V45: 24793320 | W45: 29629067 | X45: 30517939 | Y45: 0 | Z45: 0 | AA45: 0 | AB45: 0 | AC45: 0 | AD45: 0 | AE45: 0 | AF45: 0 | AG45: 0 | AJ45: 11137834 | AK45: 0 | AL45: 12586389 | AM45: 12840100 | AO45: *Net Operating Income | AP45: =AP21-AP41 -> 16307295 | AQ45: =AQ21-AQ41 -> 16865624 | AS45: =IF(ISNUMBER(AT45),AT45/AP45,"") -> 0.034238003 | AT45: =IF(ISNUMBER(AQ45),AQ45-AP45,"") -> 558329.2
B47: CAPITAL | K47: $/SF | L47: $/Unit
B48: Flooring | K48: 0 | L48: 0 | M48: 0 | N48: 0 | O48: 0 | P48: 0 | Q48: 0 | R48: 0 | S48: 0 | T48: 0 | U48: 0 | V48: 0 | W48: 0 | X48: 0 | Y48: 0 | Z48: 0 | AA48: 0 | AB48: 0 | AC48: 0 | AD48: 0 | AE48: 0 | AF48: 0 | AG48: 0
B49: Appliances/HVAC/Water Heater | K49: 0 | L49: 0 | M49: 0 | N49: 0 | O49: 0 | P49: 0 | Q49: 0 | R49: 0 | S49: 0 | T49: 0 | U49: 0 | V49: 0 | W49: 0 | X49: 0 | Y49: 0 | Z49: 0 | AA49: 0 | AB49: 0 | AC49: 0 | AD49: 0 | AE49: 0 | AF49: 0 | AG49: 0
B50: Building Capital | K50: 0 | L50: 0 | M50: 0 | N50: 0 | O50: 0 | P50: 0 | Q50: 0 | R50: 0 | S50: 0 | T50: 0 | U50: 0 | V50: 0 | W50: 0 | X50: 0 | Y50: 0 | Z50: 0 | AA50: 0 | AB50: 0 | AC50: 0 | AD50: 0 | AE50: 0 | AF50: 0 | AG50: 0
B51: Capital Reserves | K51: #VALUE! | L51: #VALUE! | M51: #VALUE! | N51: #VALUE! | O51: #VALUE! | P51: #VALUE! | Q51: #VALUE! | R51: #VALUE! | S51: #VALUE! | T51: #VALUE! | U51: #VALUE! | V51: #VALUE! | W51: 113750 | X51: 113750 | Y51: 0 | Z51: 0 | AA51: 0 | AB51: 0 | AC51: 0 | AD51: 0 | AE51: 0 | AF51: 0 | AG51: 0
B52: Unit Buyout Costs | K52: 0 | L52: 0 | M52: 0 | N52: 0 | O52: 0 | P52: 0 | Q52: 0 | R52: 0 | S52: 0 | T52: 0 | U52: 0 | V52: 0 | W52: 0 | X52: 0 | Y52: 0 | Z52: 0 | AA52: 0 | AB52: 0 | AC52: 0 | AD52: 0 | AE52: 0 | AF52: 0 | AG52: 0
B53: Unit Renovation Capital | K53: 0 | L53: 0 | M53: 0 | N53: 0 | O53: 0 | P53: 0 | Q53: 0 | R53: 0 | S53: 0 | T53: 0 | U53: 0 | V53: 0 | W53: 0 | X53: 0 | Y53: 0 | Z53: 0 | AA53: 0 | AB53: 0 | AC53: 0 | AD53: 0 | AE53: 0 | AF53: 0 | AG53: 0
B54: Total Capital Expenses | K54: #VALUE! | L54: #VALUE! | M54: #VALUE! | N54: #VALUE! | O54: #VALUE! | P54: #VALUE! | Q54: #VALUE! | R54: #VALUE! | S54: #VALUE! | T54: #VALUE! | U54: #VALUE! | V54: #VALUE! | W54: 113750 | X54: 113750 | Y54: 0 | Z54: 0 | AA54: 0 | AB54: 0 | AC54: 0 | AD54: 0 | AE54: 0 | AF54: 0 | AG54: 0
B56: Net Cash Flow | K56: #VALUE! | L56: #VALUE! | M56: #VALUE! | N56: #VALUE! | O56: #VALUE! | P56: #VALUE! | Q56: #VALUE! | R56: #VALUE! | S56: #VALUE! | T56: #VALUE! | U56: #VALUE! | V56: #VALUE! | W56: 29515317 | X56: 30404189 | Y56: 0 | Z56: 0 | AA56: 0 | AB56: 0 | AC56: 0 | AD56: 0 | AE56: 0 | AF56: 0 | AG56: 0
B59: RENT DETAIL
B60: Mkt Rent: | E60: 4014.9355 | F60: 5319.0271 | M60: 5319.0271 | N60: 5588.5855 | O60: 5781.9634 | P60: 5955.4223 | Q60: 6134.085 | R60: 6318.1075 | S60: 6507.6508 | T60: 6702.8803 | U60: 6903.9667 | V60: 7111.0857
B61: PSF: | E61: 0 | M61: 0 | N61: 0 | O61: 0 | P61: 0 | Q61: 0 | R61: 0 | S61: 0 | T61: 0 | U61: 0 | V61: 0
B62: Effective Rent: | E62: 9177.1541 | M62: 6224.0904 | N62: 6550.2625 | O62: 6780.4567 | P62: 6994.2923 | Q62: 7222.6803 | R62: 7415.1234 | S62: 7638.3491 | T62: 7867.4995 | U62: 8103.5245 | V62: 8346.6302
B63: PSF: | E63: 7.9719575 | M63: 10.224092 | N63: 10.759884 | O63: 11.138016 | P63: 11.489276 | Q63: 11.864441 | R63: 12.18056 | S63: 12.547245 | T63: 12.923662 | U63: 13.311372 | V63: 13.710713
L70: MULTIFAMILY UNIT MIX
L71: UNIT TYPE | M71: TOTAL UNITS | N71: VAC UNITS | O71: % UNITS | P71: AVG SF | Q71: BEDS | R71: IN-PLACE ($/MONTH) | S71: IN-PLACE ($/SF) | T71: IN-PLACE ($/BED) | U71: RENO COST ($/UNIT) | V71: RENO COST ($/SF) | W71: PREMIUM ($/UNIT) | X71: POST-RENO ($/MONTH) | Y71: POST-RENO ($/SF) | Z71: POST-RENO ($/BED)
L72: NON-RENOVATED MARKET RATE
F73: Holl | G73: =SUMPRODUCT(M74:M76,R74:R76)/SUM(M74:M76) -> 5247.4258 | L73: Hollingsworth | O73: 0 | S73: 0 | T73: 0 | V73: 0 | X73: 0 | Y73: 0 | Z73: 0
F74: Quincy | G74: =SUMPRODUCT(M79:M81,R79:R81)/SUM(M79:M81) -> 5235.8 | L74: Studio | M74: 120 | N74: 0 | O74: 0.26373626 | P74: 484.33333 | Q74: 1 | R74: 4105.821 | S74: 8.477263 | T74: 4264.7345 | V74: 0 | X74: 4105.821 | Y74: 8.477263 | Z74: 4105.821
L75: 1 BR | M75: 220 | N75: 0 | O75: 0.48351648 | P75: 656.18182 | Q75: 1 | R75: 5562.6258 | S75: 8.477263 | T75: 5364.7678 | V75: 0 | X75: 5562.6258 | Y75: 8.477263 | Z75: 5562.6258
L76: 2 BR | M76: 40 | N76: 0 | O76: 0.087912088 | P76: 818.5 | Q76: 2 | R76: 6938.6397 | S76: 8.477263 | T76: 7374.3421 | V76: 0 | X76: 6938.6397 | Y76: 8.477263 | Z76: 3469.3199
O77: 0 | S77: 0 | T77: 0 | V77: 0 | X77: 0 | Y77: 0 | Z77: 0
L78: Quincy | O78: 0 | S78: 0 | T78: 0 | V78: 0 | X78: 0 | Y78: 0 | Z78: 0
L79: Studio | M79: 51 | N79: 0 | O79: 0.11208791 | P79: 442 | Q79: 1 | R79: 4155.3968 | S79: 9.4013503 | T79: 4155.3968 | V79: 0 | X79: 4155.3968 | Y79: 9.4013503 | Z79: 4155.3968
L80: 1 BR | M80: 12 | N80: 0 | O80: 0.026373626 | P80: 606 | Q80: 1 | R80: 5697.2183 | S80: 9.4013503 | T80: 5697.2183 | V80: 0 | X80: 5697.2183 | Y80: 9.4013503 | Z80: 5697.2183
L81: 2 BR | M81: 12 | N81: 0 | O81: 0.026373626 | P81: 996.25 | Q81: 2 | R81: 9366.0952 | S81: 9.4013503 | T81: 4683.0476 | V81: 0 | X81: 9366.0952 | Y81: 9.4013503 | Z81: 4683.0476
O82: 0 | S82: 0 | T82: 0 | V82: 0 | X82: 0 | Y82: 0 | Z82: 0
O83: 0 | S83: 0 | T83: 0 | V83: 0 | X83: 0 | Y83: 0 | Z83: 0
O84: 0 | S84: 0 | T84: 0 | V84: 0 | X84: 0 | Y84: 0 | Z84: 0
O85: 0 | S85: 0 | T85: 0 | V85: 0 | X85: 0 | Y85: 0 | Z85: 0
O86: 0 | S86: 0 | T86: 0 | V86: 0 | X86: 0 | Y86: 0 | Z86: 0
O87: 0 | S87: 0 | T87: 0 | V87: 0 | X87: 0 | Y87: 0 | Z87: 0
L88: SUBTOTAL | M88: 455 | N88: 0 | O88: 1 | P88: 608.76703 | Q88: 1.1142857 | R88: 5245.5094 | S88: 8.6166122 | T88: 4707.5085 | U88: 0 | V88: 0 | W88: 0 | X88: 5245.5094 | Y88: 8.6166122 | Z88: 4707.5085

Sheet Coding
B2: Revenues | C2: Cost Code | D2: Cost Code | J2: Number of Mos. Covered | M2: Gross Potential Rent (3)
B3: RENTAL INCOME | J3: Period Ended | M3: Less: Vacancy Loss
B4: Rent Income | C4: Gross Potential Rent (3) | D4: Gross Potential Rent (3) | J4: Statement Ending Date | M4: Commercial Income
B5: Apartment Rent | C5: Gross Potential Rent (3) | D5: Gross Potential Rent (3) | J5: Gross Potential Rent (3) | M5: Less: Vacancy Loss ©
B6: Pos Income | C6: Other Income | D6: Other Income | J6: Less: Vacancy Loss | M6: Laundry/Vending Income
B7: Special Area Rent | C7: Other Income | D7: Other Income | J7: OR | M7: Parking Income
B8: Parking Income | C8: Parking Income | D8: Parking Income | J8: Base Rent (3) | M8: Other Income
B9: Straight Line Rental Income | C9: Other Income | D9: Other Income | J9: Laundry/Vending Income | M9: Real Estate Taxes
B10: Retail Rent | C10: Commercial Income | D10: Base Rent (3) | J10: Parking Income | M10: Property Insurance
B11: Warehouse Rent | C11: Other Income | D11: Other Income | J11: Other Income | M11: Utilities
B12: Basement, Storage & Other | C12: Other Income | D12: Other Income | M12: Repairs and Maintenance
B13: Air Rights Rent | C13: Other Income | D13: Other Income | J13: *Effective Gross Income | M13: Management Fees
B14: Free Rent | C14: Other Income | D14: Other Income | M14: Payroll & Benefits
B15: Nnn - Office | C15: Other Income | D15: Other Income | M15: Advertising & Marketing
B16: Nnn - Retail | C16: Other Income | D16: Other Income | J16: OPERATING EXPENSES: | M16: Professional Fees
B17: Ground Rent Income | C17: Other Income | D17: Other Income | J17: Real Estate Taxes | M17: General and Administrative
B18: Free Rent-Contra | C18: Other Income | D18: Other Income | J18: Property Insurance | M18: Other Expenses
B19: Deferred Rent (Covid-19) | C19: Other Income | D19: Other Income | J19: Utilities | M19: Ground Rent
B20: Deferred Rent - Retail (Covid-19) | C20: Other Income | D20: Other Income | J20: Repairs and Maintenance
B21: Deferred Rent - Apartment (Covid-19) | C21: Other Income | D21: Other Income | J21: Management Fees
B22: Collection Loss | C22: Other Income | D22: Other Income | J22: Payroll & Benefits
B23: Bad Debt Recovery: Collections | C23: Other Income | D23: Other Income | J23: Advertising & Marketing
B24: Vacancy Loss | C24: Less: Vacancy Loss | D24: Less: Vacancy Loss | J24: Professional Fees
B25: Vacancy (Covid-19) | C25: Less: Vacancy Loss | D25: Less: Vacancy Loss | J25: General and Administrative
B26: Concessions | C26: Other Income | D26: Other Income | J26: Other Expenses
B27: Concessions (Covid-19) | C27: Other Income | D27: Other Income | J27: Ground Rent
B28: Employer Provided Housing | C28: Other Income | D28: Other Income
B29: Fines | C29: Other Income | D29: Other Income
B30: Furniture Rental | C30: Other Income | D30: Other Income
B31: Premium Due Ins Company | C31: Other Income | D31: Other Income
B32: Key Deposit | C32: Other Income | D32: Other Income
B33: Cleaning Fees | C33: Other Income | D33: Other Income
B34: Locks/Keys/Cards | C34: Other Income | D34: Other Income
B35: Month-To Month Premium | C35: Other Income | D35: Other Income
B36: Percentage Rent | C36: Other Income | D36: Other Income
B37: Percentage Rent - Parking | C37: Parking Income | D37: Parking Income
B38: Insufficient Notice Fee | C38: Other Income | D38: Other Income
B39: Pet Rent/Fees | C39: Other Income | D39: Other Income
... B44: Bad Debt Expense - Admin Exp | C44: Other Income | D44: Other Income
B45: Total Rent Income
B46: Reimbursements & Escalations
B47: Cam - Sponsor | C47: Other Income | D47: Other Income
B48: C.A.M. Income | C48: Other Income | D48: Other Income
B49: C.A.M. Inc. - Sponsor Shortfall | C49: Other Income | D49: Other Income
B50: C.A.M. Inc. - Reserve Funding | C50: Other Income | D50: Other Income
B51: Cam Income - Transfers | C51: Other Income | D51: Other Income
B52: C.A.M. Inc.- Prior Year | C52: Other Income | D52: Other Income
B53: Operating Expense Escalations | C53: Other Income | D53: Other Income
B54: Utility Escalations | C54: Other Income | D54: Other Income
B55: Cpi Escalations | C55: Other Income | D55: Other Income
B56: Water & Sewer Income | C56: Other Income | D56: Other Income
B57: Sprinkler Supervisory Service | C57: Other Income | D57: Other Income
B58: Base Electric Income | C58: Other Income | D58: Other Income
... B74: Income - Sundry Billings | C74: Other Income | D74: Other Income
B75: Total Reimbursements & Escal.
B76: Other
B77: Laundry Income | C77: Other Income | D77: Other Income
B78: Application Fee Income | C78: Other Income | D78: Other Income
B79: Legal Fee Income | C79: Other Income | D79: Other Income
B80: Income Sundry Billings - Contr | C80: Other Income | D80: Other Income
B81: Miscellaneous Income | C81: Other Income | D81: Other Income
B82: Interest Income - Deferred Rent | C82: Other Income | D82: Other Income
B83: Late Charges | C83: Other Income | D83: Other Income
B84: Waived Fees - Late Charges (Covid-19) | C84: Other Income | D84: Other Income
B85: Bounced/Stopped Check Income | C85: Other Income | D85: Other Income
B86: Lease Termination Income | C86: Other Income | D86: Other Income
B87: Income - Golf Course | C87: Other Income | D87: Other Income
B88: Condenser Water Income | C88: Other Income | D88: Other Income
B89: Admin Fee Income | C89: Other Income | D89: Other Income
B90: Total Other Income
B91: TOTAL OPERATING INCOME
B92: Income From Funds
B93: Fund Mgmt. Fee Income
B94: Loan Application Fee Income
B95: Loan Application Expense
B96: Gp Promote - Capital
B97: Profit Part. Fee Income
B98: Interest Income
B99: Origination Fee Income
B100: Exit Fee Income
B101: Interest Income - Mortgages
... B155: Gross Receipt Tax Expense
B156: Total Real Estate Taxes | C156: Real Estate Taxes | D156: Real Estate Taxes
B157: Insurance
B158: Insurance
B159: Insurance - Prop & Liability
B160: Insurance Refunds/Credits
B161: Insurance - Other
B162: Insurance - Auto
B163: Total Insurance | C163: Property Insurance | D163: Property Insurance
B164: Rent & Related - Master Leases
B165: Base Rent - Master Leases
B166: Re Taxes - Master Leases
B167: Other Charges - Master Leases
B168: Utilities
B169: Energy Management
B170: Water & Sewer
B171: Water & Sewer Refunds/Credits
B172: Water - Testing
B173: Water - Clubhouse
...
